{
    "province": "LAS PALMAS",
    "date": "2009-06-01T00:00:00",
    "url": "https://www.20minutos.es/noticia/471744/0/prision/trama/arrecife/",
    "title": {
        "raw_text": "El juez dicta el séptimo ingreso en prisión por la trama de corrupción de Lanzarote",
        "lemmatized_text": "el juez dictar el 7 ingreso en prisión por el trama de corrupción de lanzarote",
        "lemmatized_text_reduced": "juez dictar 7 ingreso prisión trama corrupción lanzarote",
        "persons": [],
        "locations": [
            "Lanzarote"
        ],
        "organizations": [],
        "others": [],
        "dates": [],
        "numbers": []
    },
    "lead": {
        "raw_text": "Envía a la cárcel al empresario Fernando Becerra. Ha decretado la libertad sin fianza del empresario Jesús Martín. CONSULTA AQUÍ MÁS NOTICIAS DE LAS PALMAS .",
        "lemmatized_text": "enviar a el cárcel a el empresario fernando_becerra haber decretar el libertad sin fianza de el empresario jesús_martín consulta_aquí_más_noticias_de_las_palmas",
        "lemmatized_text_reduced": "enviar cárcel empresario fernando_becerra haber decretar libertad fianza empresario jesús_martín consulta_aquí_más_noticias_de_las_palmas",
        "persons": [
            "Fernando_Becerra",
            "Jesús_Martín"
        ],
        "locations": [],
        "organizations": [
            "CONSULTA_AQUÍ_MÁS_NOTICIAS_DE_LAS_PALMAS"
        ],
        "others": [],
        "dates": [],
        "numbers": []
    },
    "body": {
        "raw_text": "El juez del juzgado de instrucción número 5 de Arrecife, César Romero Pamparacuatro, ha decretado en la tarde del lunes el ingreso en prisión del empresario Fernando Becerra, el séptimo encarcelamiento de implicados en la trama de corrupción de Lanzarote . Fernando Becerra Robaya, imputado por cohecho , es hermano de Ubaldo Becerra (PIL), el teniente de alcalde del Ayuntamiento de Arrecife de Lanzarote, que fue cesado por el primer edil después de su detención y que ahora también está en la cárcel. Según ha informado el Tribunal Superior de Justicia de Canarias, el juez ha decretado este lunes también la puesta en libertad sin fianza del empresario Jesús Martín Brito, quien también ha sido imputado por cohecho. En la madrugada del lunes ingresó en prisión otro constructor detenido por la trama de corrupción de Lanzarote, Lluis Lleó Khunel , quien fue arrestado el pasado jueves en Reus (Tarragona). Cobro de comisiones ilegales Con Fernando Becerra y Lluis Lleó son siete los imputados en la operación Unión que ingresan en prisión acusados de participar en esta red que cobraba comisiones ilegales a empresarios a cambio de la contratación de obras y servicios o la gestión de permisos y licencias. Los otros imputados que han sido enviados a prisión por este caso son Dimas Martín, líder del PIL que ya cumplía condena por otros delitos; Ubaldo Becerra, ex teniente de alcalde de Arrecife y encargado del Plan General, por cohecho; José Miguel Rodríguez, ex concejal de Hacienda y Urbanismo, por cohecho; Segundo Rodríguez, ex vicepresidente del Cabildo de Lanzarote, por cohecho; y Matías Curbelo, asesor del Patronato de Turismo de la isla, por cohecho.",
        "lemmatized_text": "el juez de el juzgado de instrucción número 5 de arrecife césar_romero_pamparacuatro haber decretar en el tarde de el [L:??/??/??:??.??:??] el ingreso en prisión de el empresario fernando_becerra el 7 encarcelamiento de implicar en el trama de corrupción de lanzarote fernando_becerra_robaya imputar por cohecho ser hermano de ubaldo_becerra pil el teniente de alcalde de el ayuntamiento_de_arrecife_de_lanzarote que ser cesar por el 1 edil después_de su detención y que ahora también estar en el cárcel según haber informar el tribunal_superior_de_justicia_de_canarias el juez haber decretar este [L:??/??/??:??.??:??] también el puesta en libertad sin fianza de el empresario jesús_martín_brito quien también haber ser imputar por cohecho en el madrugada de el [L:??/??/??:??.??:??] ingresar en prisión otro constructor detener por el trama de corrupción de lanzarote lluis_lleó_khunel quien ser arrestar el [J:??/??/??:??.??:??] en reus tarragona cobro de comisión ilegal con_fernando_becerra y lluis_lleó ser 7 el imputar en el operación unión que ingresar en prisión acusar de participar en este red que cobrar comisión ilegal a empresario a_cambio_de el contratación de obra y servicio o el gestión de permiso y licencia el otro imputar que haber ser enviar a prisión por este caso ser dimas_martín líder de el pil que ya cumplir condena por otro delito ubaldo_becerra ex teniente de alcalde de arrecife y encargar de el plan_general por cohecho josé_miguel_rodríguez ex concejal de hacienda y urbanismo por cohecho segundo_rodríguez ex vicepresidente de el cabildo_de_lanzarote por cohecho y matías_curbelo asesor de el patronato_de_turismo de el isla por cohecho",
        "lemmatized_text_reduced": "juez juzgado instrucción número arrecife césar_romero_pamparacuatro haber decretar tarde ingreso prisión empresario fernando_becerra 7 encarcelamiento implicar trama corrupción lanzarote fernando_becerra_robaya imputar cohecho ser hermano ubaldo_becerra pil teniente alcalde ayuntamiento_de_arrecife_de_lanzarote ser cesar 1 edil detención estar cárcel haber informar tribunal_superior_de_justicia_de_canarias juez haber decretar puesta libertad fianza empresario jesús_martín_brito haber ser imputar cohecho madrugada ingresar prisión constructor detener trama corrupción lanzarote lluis_lleó_khunel ser arrestar reus tarragona cobro comisión ilegal con_fernando_becerra lluis_lleó ser imputar operación unión ingresar prisión acusar participar red cobrar comisión ilegal empresario contratación obra servicio gestión permiso licencia imputar haber ser enviar prisión caso ser dimas_martín líder pil cumplir condena delito ubaldo_becerra ex teniente alcalde arrecife encargar plan_general cohecho josé_miguel_rodríguez ex concejal hacienda urbanismo cohecho segundo_rodríguez ex vicepresidente cabildo_de_lanzarote cohecho matías_curbelo asesor patronato_de_turismo isla cohecho",
        "persons": [
            "César_Romero_Pamparacuatro",
            "Fernando_Becerra",
            "Fernando_Becerra_Robaya",
            "Ubaldo_Becerra",
            "Jesús_Martín_Brito",
            "Lluis_Lleó_Khunel",
            "Lluis_Lleó",
            "Dimas_Martín",
            "Ubaldo_Becerra",
            "José_Miguel_Rodríguez",
            "Segundo_Rodríguez",
            "Matías_Curbelo"
        ],
        "locations": [
            "Lanzarote",
            "Lanzarote",
            "Reus",
            "Tarragona",
            "Arrecife"
        ],
        "organizations": [
            "Arrecife",
            "PIL",
            "Ayuntamiento_de_Arrecife_de_Lanzarote",
            "Tribunal_Superior_de_Justicia_de_Canarias",
            "Con_Fernando_Becerra",
            "Unión",
            "PIL",
            "Cabildo_de_Lanzarote",
            "Patronato_de_Turismo"
        ],
        "others": [
            "Plan_General",
            "Hacienda",
            "Urbanismo"
        ],
        "dates": [
            "[L:??/??/??:??.??:??]",
            "[L:??/??/??:??.??:??]",
            "[L:??/??/??:??.??:??]",
            "[J:??/??/??:??.??:??]"
        ],
        "numbers": [
            "5",
            "7"
        ]
    }
}
