{
    "province": "LAS PALMAS",
    "date": "2011-01-18T00:00:00",
    "url": "https://www.20minutos.es/noticia/932064/0/",
    "title": {
        "raw_text": "Los trámites para la adjudicación del Pabellón de Deportes en Gran Canaria para Mundobasket 2014 \"siguen a buen ritmo\"",
        "lemmatized_text": "el trámite para el adjudicación de el pabellón_de_deportes en gran_canaria_para_mundobasket 2014 seguir a bueno ritmo",
        "lemmatized_text_reduced": "trámite adjudicación pabellón_de_deportes gran_canaria_para_mundobasket seguir bueno ritmo",
        "persons": [],
        "locations": [
            "Gran_Canaria_para_Mundobasket"
        ],
        "organizations": [
            "Pabellón_de_Deportes"
        ],
        "others": [],
        "dates": [],
        "numbers": [
            "2014"
        ]
    },
    "lead": {
        "raw_text": "La mesa de contratación del Instituto Insular de Deportes de Gran Canaria, encargada del expediente de adjudicación del Palacio Multiusos para la celebración del Mundobasket 2014 en la isla, ha procedido este martes a la apertura del sobre con los criterios objetivos, por lo que desde el Cabildo insular explicaron que los trámites \"siguen a buen ritmo\".",
        "lemmatized_text": "el mesa de contratación de el instituto_insular_de_deportes_de_gran_canaria encargar de el expediente de adjudicación de el palacio_multiusos para el celebración de el mundobasket 2014 en el isla haber proceder este [M:??/??/??:??.??:??] a el apertura de el sobre con el criterio objetivo por el que desde el cabildo insular explicar que el trámite seguir a bueno ritmo",
        "lemmatized_text_reduced": "mesa contratación instituto_insular_de_deportes_de_gran_canaria encargar expediente adjudicación palacio_multiusos celebración mundobasket isla haber proceder apertura criterio objetivo cabildo insular explicar trámite seguir bueno ritmo",
        "persons": [],
        "locations": [
            "Palacio_Multiusos"
        ],
        "organizations": [
            "Instituto_Insular_de_Deportes_de_Gran_Canaria",
            "Cabildo"
        ],
        "others": [
            "Mundobasket"
        ],
        "dates": [
            "[M:??/??/??:??.??:??]"
        ],
        "numbers": [
            "2014"
        ]
    },
    "body": {
        "raw_text": "La mesa de contratación del Instituto Insular de Deportes de Gran Canaria, encargada del expediente de adjudicación del Palacio Multiusos para la celebración del Mundobasket 2014 en la isla, ha procedido este martes a la apertura del sobre con los criterios objetivos, por lo que desde el Cabildo insular explicaron que los trámites \"siguen a buen ritmo\". En un comunicado, la Corporación insular explicó que previamente se ha dado a conocer el informe técnico emitido por la Comisión de Expertos designada al efecto con una puntuación máxima del 55 por ciento de la calificación total relacionadas con el proyecto técnico y las mejoras a la obra. Los criterios objetivos que se han dado a conocer y que han ofertado cada una de las nueve UTES presentadas a la licitación tienen una puntuación del 45 por ciento de la suma total y hacen referencia al importe de la ejecución de obra, plazo de ejecución y cláusula de penalización por demora. Asimismo, dicha documentación ha sido remitida a los servicios técnicos del Instituto Insular de Deportes de Gran Canaria y posterior propuesta de adjudicación que se espera en el plazo estimativo de una semana. Paralelamente al trámite administrativo para la adjudicación de la obra, el Pleno del Cabildo tiene previsto aprobar, esta misma semana —viernes—, los convenios suscritos con el Estado y la Comunidad Autónoma de Canarias.",
        "lemmatized_text": "el mesa de contratación de el instituto_insular_de_deportes_de_gran_canaria encargar de el expediente de adjudicación de el palacio_multiusos para el celebración de el mundobasket 2014 en el isla haber proceder este [M:??/??/??:??.??:??] a el apertura de el sobre con el criterio objetivo por el que desde el cabildo insular explicar que el trámite seguir a bueno ritmo en uno comunicado el corporación insular explicar que previamente se haber dar_a_conocer el informe técnico emitir por el comisión_de_expertos designar a el efecto con uno puntuación máximo de el 55 por 100 de el calificación total relacionar con el proyecto técnico y el mejora a el obra el criterio objetivo que se haber dar_a_conocer y que haber ofertar cada uno de el 9 utes presentar a el licitación tener uno puntuación de el 45 por 100 de el suma total y hacer_referencia a el importe de el ejecución de obra plazo de ejecución y cláusula de penalización por demora asimismo decir documentación haber ser remitir a el servicio técnico de el instituto_insular_de_deportes_de_gran_canaria y posterior propuesta de adjudicación que se esperar en el plazo estimativo de uno semana paralelamente a el trámite administrativo para el adjudicación de el obra el pleno_del_cabildo tener prever aprobar este mismo semana [V:??/??/??:??.??:??] el convenio suscribir con el estado y el comunidad_autónoma_de_canarias",
        "lemmatized_text_reduced": "mesa contratación instituto_insular_de_deportes_de_gran_canaria encargar expediente adjudicación palacio_multiusos celebración mundobasket isla haber proceder apertura criterio objetivo cabildo insular explicar trámite seguir bueno ritmo comunicado corporación insular explicar previamente haber dar_a_conocer informe técnico emitir comisión_de_expertos designar efecto puntuación máximo calificación total relacionar proyecto técnico mejora obra criterio objetivo haber dar_a_conocer haber ofertar utes presentar licitación tener puntuación suma total hacer_referencia importe ejecución obra plazo ejecución cláusula penalización demora decir documentación haber ser remitir servicio técnico instituto_insular_de_deportes_de_gran_canaria posterior propuesta adjudicación esperar plazo estimativo semana paralelamente trámite administrativo adjudicación obra pleno_del_cabildo tener prever aprobar mismo semana convenio suscribir estado comunidad_autónoma_de_canarias",
        "persons": [],
        "locations": [
            "Palacio_Multiusos"
        ],
        "organizations": [
            "Instituto_Insular_de_Deportes_de_Gran_Canaria",
            "Cabildo",
            "Corporación",
            "Comisión_de_Expertos",
            "UTES",
            "Instituto_Insular_de_Deportes_de_Gran_Canaria",
            "Pleno_del_Cabildo",
            "Estado",
            "Comunidad_Autónoma_de_Canarias"
        ],
        "others": [
            "Mundobasket"
        ],
        "dates": [
            "[M:??/??/??:??.??:??]",
            "[V:??/??/??:??.??:??]"
        ],
        "numbers": [
            "2014",
            "55",
            "100",
            "9",
            "45",
            "100"
        ]
    }
}
