{
    "province": "LAS PALMAS",
    "date": "2010-01-19T00:00:00",
    "url": "https://www.20minutos.es/noticia/610294/0/",
    "title": {
        "raw_text": "Fiscal pide al Supremo que confirme condena al ex presidente de Audiencia de Las Palmas por favorecer a un 'narco'",
        "lemmatized_text": "fiscal pedir a el supremo que confirmar condena a el ex presidente de audiencia_de_las_palmas por favorecer a uno narco",
        "lemmatized_text_reduced": "fiscal pedir supremo confirmar condena ex presidente audiencia_de_las_palmas favorecer narco",
        "persons": [],
        "locations": [],
        "organizations": [
            "Supremo",
            "Audiencia_de_Las_Palmas"
        ],
        "others": [],
        "dates": [],
        "numbers": []
    },
    "lead": {
        "raw_text": "El fiscal ha pedido hoy al Tribunal Supremo que confirme la condena impuesta en abril del pasado año al ex presidente de la Audiencia Provincial de Las Palmas, José Antonio Martín Martín por favorecer a un narcotraficante. Al magistrado le fue impuesta la suspensión para empleo o cargo público que implica el desempeño de funciones jurisdiccionales durante un año y seis meses por un delito de actividades prohibidas a los funcionarios públicos.",
        "lemmatized_text": "el fiscal haber pedir hoy a el tribunal_supremo que confirmar el condena imponer en [??:??/4/??:??.??:??] de el pasar año a el ex presidente de el audiencia_provincial_de_las_palmas josé_antonio_martín_martín por favorecer a uno narcotraficante a el magistrado le ser imponer el suspensión para empleo o cargo público que implicar el desempeño de función jurisdiccional durante uno año y 6 mes por uno delito de actividad prohibir a el funcionario público",
        "lemmatized_text_reduced": "fiscal haber pedir tribunal_supremo confirmar condena imponer pasar año ex presidente audiencia_provincial_de_las_palmas josé_antonio_martín_martín favorecer narcotraficante magistrado ser imponer suspensión empleo cargo público implicar desempeño función jurisdiccional año mes delito actividad prohibir funcionario público",
        "persons": [
            "José_Antonio_Martín_Martín"
        ],
        "locations": [],
        "organizations": [
            "Tribunal_Supremo",
            "Audiencia_Provincial_de_Las_Palmas"
        ],
        "others": [],
        "dates": [
            "[??:??/4/??:??.??:??]"
        ],
        "numbers": [
            "6"
        ]
    },
    "body": {
        "raw_text": "Durante la vista pública celebrada en el alto tribunal para deliberar sobre los recursos planteados por la defensa de Martín y del otro condenado en la causa —Wilebaldo Luis Yanes, como autor por cooperación de un delito de actividades prohibidas a los funcionarios—, el representante del Ministerio Público defendió que el juez de instrucción que investigó el caso actuó \"con arreglo al derecho\" y no hubo \"ninguna persecución\" contra Martín. Según el relato de hechos probados, Martín y Luis Yanes estaban unidos por una \"intensa relación de amistad\". Al mismo tiempo, Luis Yanes mantenía relaciones comerciales con Julio Bornia Bordón, a quien conoce desde el año 2001, y quien tenía un hermano —Rafael Bornia Bordón— en prisión provisional imputado por un presunto delito de tráfico de drogas y cuya situación estaba pendiente de revisión ante la Audiencia Provincial de Las Palmas. Al conocer la amistad de Luis Yanes con el entonces presidente de la Audiencia Provincial de Las Palmas, Bornia le explicó la situación en la que se encontraba su hermano e intentó \"una serie de maniobras tendentes a buscar un contacto directo con José Antonio Martín y poder, de esta forma, expresarle su deseo de que su hermano Rafael fuese puesto en libertad, y obtener del magistrado la información y el asesoramiento preciso en orden a la estrategia procesal que debería seguir para obtener su libertad\". De esta manera, la Sala sostuvo en su sentencia que el 5 de mayo de 2005 Luis Yanes contactó telefónicamente con Martín confirmándole una cena previamente pactada con Julio Bornia para esa misma noche en un restaurante de Las Palmas de Gran Canaria. La reunión tuvo lugar ese día en el domicilio de Martín, donde Bornia facilitó al magistrado determinada documentación para que la estudiara y le insistió en lo \"injusto\" que le parecía la situación de prisión de su hermano Rafael. En junio de 2005 se sucedieron las conversaciones entre las tres personas. Ese mes, Luis informó a Julio Bornia de que había entregado a Martín \"nueva documentación\", al tiempo que le trasmitió la \"necesaria tranquilidad toda vez que el magistrado estaba haciendo todo lo que podía\". \"dile que no se enrolle\" Cuando se acercó el momento de la vista del recurso de apelación para tratar el tema de la puesta en libertad de Rafael Bornia, previsto para el día 28 de julio de 2005 en la Sección Primera de la Audiencia Provincial, el 27 de julio el magistrado llamó a Luis Yanes y le confirmó que la Sección encargada del recurso es la que él presidía y le dio \"una serie de recomendaciones\" para que se las trasmitiese a Julio Bornia Bordón y éste a su letrado en relación con la estrategia que debería seguir en la vista del recurso que se celebraría al siguiente día. En concreto, según la Sala, le dijo: \"Dile que no se enrolle, que explique las cosas claritas y sencillas, confianza y seguridad. Que explique la procedencia del dinero, que lo explique clarito y sencillo. Que lo explique de palabra, pero de una forma sencilla sin rollos y que diga que está dispuesto a prestar una fianza, la cantidad que se le diga\". \"Bueno, pero dile eso, que no se enrolle y que lo explique sencillo. Porque si no predispone a la gente en contra, que se deje de rollos, vale\". Al finalizar la conversación telefónica, continuaba la sentencia, Wilebaldo contactó con Julio Bornia a quien informó de lo asesorado por Martín. Al día siguiente, en los momentos previos a la celebración de la vista, el magistrado comentó al fiscal encargado del recurso, Javier García Cabañas, la posibilidad de que la Fiscalía, modificando su criterio, pidiese la libertad de Rafael Bornia. Sin embargo, el fiscal lo rechazó, al igual que se mostró contrario a solicitar la libertad del acusado con la prestación de una alta fianza. Su abogado pide la absolución El abogado del magistrado pidió hoy la absolución de su defendido, argumentado que la acusación se basa sólo en unas escuchas telefónicas que no estaban suficientemente motivadas y en las que no se ha podido probar que la voz que se escucha corresponda a la de Martín. Además, el abogado sostuvo que las recomendaciones supondrían un mero \"asesoramiento accidental\", que en ningún caso constituyen un \"asesoramiento jurídico\". En este punto, recordó que el fiscal pidió el archivo en un caso semejante, el de una conversación que una abogada mantuvo con la presidenta del Tribunal Constitucional, María Emilia Casas. Por su parte, el fiscal defendió que las \"sospechas\" para ordenar la intervención de las comunicaciones de Martín estaban lo suficientemente motivadas e hizo hincapié en que la conversación en la que orientó al hermano del 'narco' se produjo el mismo día antes de que se produjera la vista en la Audiencia Provincial, en la que después el magistrado defendió la puesta en libertad del imputado.",
        "lemmatized_text": "durante el vista público celebrar en el alto tribunal para deliberar sobre el recurso plantear por el defensa de martín y de el otro condenar en el causa wilebaldo_luis_yanes como autor por cooperación de uno delito de actividad prohibir a el funcionario el representante de el ministerio_público defender que el juez de instrucción que investigar el caso actuar con arreglo a el derecho y no haber ninguno persecución contra martín según el relato de hecho probar martín y luis_yanes estar unir por uno intenso relación de amistad a el mismo tiempo luis_yanes mantener relación comercial con [??:??/7/??:??.??:??] bornia_bordón a quien conocer desde el [??:??/??/2001:??.??:??] y quien tener uno hermano rafael_bornia_bordón en prisión provisional imputar por uno presunto delito de tráfico de droga y cuyo situación estar pendiente de revisión ante el audiencia_provincial_de_las_palmas a el conocer el amistad de luis_yanes con el entonces presidente de el audiencia_provincial_de_las_palmas bornia le explicar el situación en el que se encontrar su hermano y intentar uno serie de maniobra tendente a buscar uno contacto directo con josé_antonio_martín y poder de este forma expresar le su deseo de que su hermano rafael ser poner en libertad y obtener de el magistrado el información y el asesoramiento preciso en_orden_a el estrategia procesal que deber seguir para obtener su libertad de este manera el sala sostener en su sentencia que el [??:5/5/2005:??.??:??] luis_yanes contactar telefónicamente con martín confirmar le uno cena previamente pactar con [??:??/7/??:??.??:??] bornia para ese mismo noche en uno restaurante de las_palmas_de_gran_canaria el reunión tener_lugar ese día en el domicilio de martín donde bornia facilitar a el magistrado determinar documentación para que lo estudiar y le insistir en el injusto que le parecer el situación de prisión de su hermano rafael en [??:??/6/2005:??.??:??] se suceder el conversación entre el 3 persona ese mes luis informar a [??:??/7/??:??.??:??] bornia de que haber entregar a martín nuevo documentación al_tiempo_que le trasmitir el necesario tranquilidad todo vez que el magistrado estar hacendar todo el que poder decir le que no se enrollar cuando se acercar el momento de el vista de el recurso de apelación para tratar el tema de el puesta en libertad de rafael_bornia prever para el [??:28/7/2005:??.??:??] en el sección_primera_de_la_audiencia_provincial el [??:27/7/??:??.??:??] el magistrado llamar a luis_yanes y le confirmar que el sección encargar de el recurso ser el que él presidir y le dar uno serie de recomendación para que se lo trasmitir a [??:??/7/??:??.??:??] bornia_bordón y este a su letrado en relación con el estrategia que deber seguir en el vista de el recurso que se celebrar a el siguiente día en concreto según el sala le decir decir le que no se enrollar que explicar el cosa claro y sencillo confianza y seguridad que explicar el procedencia de el dinero que lo explicar claro y sencillo que lo explicar de palabra pero de uno forma sencillo sin rollo y que decir que estar disponer a prestar uno fianza el cantidad que se le decir bueno pero decir le ese que no se enrollar y que lo explicar sencillo porque si no predisponer a el gente en contra que se dejar de rollo valer a el finalizar el conversación telefónico continuar el sentencia wilebaldo contactar con [??:??/7/??:??.??:??] bornia a quien informar de el asesorar por martín a el día siguiente en el momento previo a el celebración de el vista el magistrado comentar a el fiscal encargar de el recurso javier_garcía_cabañas el posibilidad de que el fiscalía modificar su criterio pedir el libertad de rafael_bornia sin embargo el fiscal lo rechazar al_igual_que se mostrar contrario a solicitar el libertad de el acusado con el prestación de uno alto fianza su abogado pedir el absolución el abogado de el magistrado pedir hoy el absolución de su defendido argumentar que el acusación se basar sólo en uno escucha telefónico que no estar suficientemente motivar y en el que no se haber poder probar que el voz que se escuchar corresponder a el de martín además el abogado sostener que el recomendación suponer uno mero asesoramiento accidental que en ninguno caso constituir uno asesoramiento jurídico en este punto recordar que el fiscal pedir el archivo en uno caso semejante el de uno conversación que uno abogado mantener con el presidente de el tribunal_constitucional maría_emilia_casas por su parte el fiscal defender que el sospecha para ordenar el intervención de el comunicación de martín estar el suficientemente motivar y hacer hincapié en que el conversación en el que orientar a el hermano de el narco se producir el mismo día antes_de que se producir el vista en el audiencia_provincial en el que después el magistrado defender el puesta en libertad de el imputar",
        "lemmatized_text_reduced": "vista público celebrar alto tribunal deliberar recurso plantear defensa martín condenar causa wilebaldo_luis_yanes autor cooperación delito actividad prohibir funcionario representante ministerio_público defender juez instrucción investigar caso actuar arreglo derecho haber persecución martín relato hecho probar martín luis_yanes estar unir intenso relación amistad mismo tiempo luis_yanes mantener relación comercial bornia_bordón conocer tener hermano rafael_bornia_bordón prisión provisional imputar presunto delito tráfico droga situación estar pendiente revisión audiencia_provincial_de_las_palmas conocer amistad luis_yanes presidente audiencia_provincial_de_las_palmas bornia explicar situación encontrar hermano intentar serie maniobra tendente buscar contacto directo josé_antonio_martín poder forma expresar deseo hermano rafael ser poner libertad obtener magistrado información asesoramiento preciso estrategia procesal deber seguir obtener libertad manera sala sostener sentencia luis_yanes contactar telefónicamente martín confirmar cena previamente pactar bornia mismo noche restaurante las_palmas_de_gran_canaria reunión tener_lugar día domicilio martín bornia facilitar magistrado determinar documentación estudiar insistir injusto parecer situación prisión hermano rafael suceder conversación persona mes luis informar bornia haber entregar martín nuevo documentación trasmitir necesario tranquilidad vez magistrado estar hacendar poder decir enrollar acercar momento vista recurso apelación tratar tema puesta libertad rafael_bornia prever sección_primera_de_la_audiencia_provincial magistrado llamar luis_yanes confirmar sección encargar recurso ser presidir dar serie recomendación trasmitir bornia_bordón letrado relación estrategia deber seguir vista recurso celebrar siguiente día concreto sala decir decir enrollar explicar cosa claro sencillo confianza seguridad explicar procedencia dinero explicar sencillo explicar palabra forma sencillo rollo decir estar disponer prestar fianza cantidad decir decir enrollar explicar sencillo predisponer gente contra dejar rollo valer finalizar conversación telefónico continuar sentencia wilebaldo contactar bornia informar asesorar martín día siguiente momento previo celebración vista magistrado comentar fiscal encargar recurso javier_garcía_cabañas posibilidad fiscalía modificar criterio pedir libertad rafael_bornia embargo fiscal rechazar mostrar contrario solicitar libertad acusado prestación alto fianza abogado pedir absolución el abogado magistrado pedir absolución defendido argumentar acusación basar escucha telefónico estar suficientemente motivar haber poder probar voz escuchar corresponder martín abogado sostener recomendación suponer mero asesoramiento accidental caso constituir asesoramiento jurídico punto recordar fiscal pedir archivo caso semejante conversación abogado mantener presidente tribunal_constitucional maría_emilia_casas parte fiscal defender sospecha ordenar intervención comunicación martín estar suficientemente motivar hacer hincapié conversación orientar hermano narco producir mismo día producir vista audiencia_provincial magistrado defender puesta libertad imputar",
        "persons": [
            "Wilebaldo_Luis_Yanes",
            "Martín",
            "Martín",
            "Luis_Yanes",
            "Luis_Yanes",
            "Bornia_Bordón",
            "Rafael_Bornia_Bordón",
            "Luis_Yanes",
            "Bornia",
            "José_Antonio_Martín",
            "Rafael",
            "Luis_Yanes",
            "Martín",
            "Bornia",
            "Rafael",
            "Luis",
            "Martín",
            "Luis_Yanes",
            "Bornia_Bordón",
            "Wilebaldo",
            "Bornia",
            "Javier_García_Cabañas",
            "Rafael_Bornia",
            "María_Emilia_Casas",
            "Martín"
        ],
        "locations": [
            "Martín",
            "Las_Palmas_de_Gran_Canaria",
            "Martín",
            "Rafael_Bornia",
            "Martín",
            "Audiencia_Provincial"
        ],
        "organizations": [
            "Ministerio_Público",
            "Audiencia_Provincial_de_Las_Palmas",
            "Audiencia_Provincial_de_Las_Palmas",
            "Sala",
            "Bornia",
            "Bornia",
            "Sección_Primera_de_la_Audiencia_Provincial",
            "Sala",
            "Martín",
            "Fiscalía",
            "Tribunal_Constitucional"
        ],
        "others": [
            "Sección",
            "El"
        ],
        "dates": [
            "[??:??/7/??:??.??:??]",
            "[??:??/??/2001:??.??:??]",
            "[??:5/5/2005:??.??:??]",
            "[??:??/7/??:??.??:??]",
            "[??:??/6/2005:??.??:??]",
            "[??:??/7/??:??.??:??]",
            "[??:28/7/2005:??.??:??]",
            "[??:27/7/??:??.??:??]",
            "[??:??/7/??:??.??:??]",
            "[??:??/7/??:??.??:??]"
        ],
        "numbers": [
            "3"
        ]
    }
}
