{
    "province": "LAS PALMAS",
    "date": "2010-02-24T00:00:00",
    "url": "https://www.20minutos.es/noticia/637292/0/",
    "title": {
        "raw_text": "El Arsenal Militar de Las Palmas conmemora el viernes la creación de la Infantería de Marina española",
        "lemmatized_text": "el arsenal_militar_de_las_palmas conmemorar el [V:??/??/??:??.??:??] el creación de el infantería_de_marina español",
        "lemmatized_text_reduced": "arsenal_militar_de_las_palmas conmemorar creación infantería_de_marina español",
        "persons": [],
        "locations": [],
        "organizations": [
            "Arsenal_Militar_de_Las_Palmas",
            "Infantería_de_Marina"
        ],
        "others": [],
        "dates": [
            "[V:??/??/??:??.??:??]"
        ],
        "numbers": []
    },
    "lead": {
        "raw_text": "El Arsenal Militar de Las Palmas conmemorará el próximo viernes, a las 11.30 horas, el 473 aniversario de la creación de la Infantería de Marina española con la celebración de un acto militar presidido por el coronel Luis Quijano de Benito.",
        "lemmatized_text": "el arsenal_militar_de_las_palmas conmemorar el [V:??/??/??:??.??:??] a el TM_h:11.3 el 473 aniversario de el creación de el infantería_de_marina español con el celebración de uno acto militar presidir por el coronel luis_quijano_de_benito",
        "lemmatized_text_reduced": "arsenal_militar_de_las_palmas conmemorar aniversario creación infantería_de_marina español celebración acto militar presidir coronel luis_quijano_de_benito",
        "persons": [
            "Luis_Quijano_de_Benito"
        ],
        "locations": [],
        "organizations": [
            "Arsenal_Militar_de_Las_Palmas",
            "Infantería_de_Marina"
        ],
        "others": [],
        "dates": [
            "[V:??/??/??:??.??:??]"
        ],
        "numbers": [
            "TM_h:11.3",
            "473"
        ]
    },
    "body": {
        "raw_text": "A la Infantería de Marina española se le reconoce la antigüedad de 1537, que corresponde a la del Tercio Nuevo del Mar de Nápoles, del que procede, y se fija la fecha del 27 de febrero como el día de su creación, por corresponder ese día al de la constitución de los Tercios de la Armada del Mar Océano, de Galeras de Sicilia y de Nápoles, según informó la Armada Española en un comunicado La presencia permanente de la Infantería de Marina en el archipiélago se remonta al año 1940, con la creación del Tercio de Canarias basado en el Arsenal. Con el paso de los años y después de cambiar de denominación y ubicación, se asienta en el año 2002, de nuevo, en el Arsenal Militar de Las Palmas, denominándose Unidad de Seguridad de Canarias (USCAN). Su misión principal es estar preparada para el cumplimiento de las misiones permanentes específicas de la Armada relacionadas con la protección y la seguridad física de bases, instalaciones navales, personas y del transporte de municiones y materiales sensibles. El Cuerpo de Infantería de Marina proporciona a la Armada la capacidad necesaria para cumplir las misiones propias de las fuerzas de desembarco y proporcionar protección a la flota y a las instalaciones en tierra. La USCAN está mandada por el Teniente coronel de Infantería de Marina D. Alfredo González Molina. Nacido en Madrid en el año 1960, ingresó en la Escuela Naval Militar en 1980. A lo largo de su carrera ha estado destinado en el Tercio de Armada, en la Subdirección de Personal de la Armada, en la Escuela Naval Militar como profesor. Ha participado en la misión de Bosnia-Herzegovina, en la misión de paz de Naciones Unidas en Guatemala (Minugua) y en la 'Operación Alfa-Charlie' de ayuda humanitaria a Centroamérica.",
        "lemmatized_text": "a el infantería_de_marina español se le reconocer el antigüedad de 1537 que corresponder a el de el tercio_nuevo_del_mar_de_nápoles de el que proceder y se fijar el fecha de el [??:27/2/??:??.??:??] como el día de su creación por corresponder ese día a el de el constitución de el tercios_de_la_armada_del_mar_océano de galeras_de_sicilia y de nápoles según informar el armada_española en uno comunicado la presencia permanente de el infantería_de_marina en el archipiélago se remontar a el [??:??/??/1940:??.??:??] con el creación de el tercio_de_canarias basar en el arsenal con el paso de el año y después_de cambiar de denominación y ubicación se asentar en el [??:??/??/2002:??.??:??] de nuevo en el arsenal_militar_de_las_palmas denominar se unidad_de_seguridad_de_canarias uscan su misión principal ser estar preparar para el cumplimiento de el misión permanente específico de el armada relacionar con el protección y el seguridad físico de base instalación naval persona y de el transporte de munición y material sensible el cuerpo_de_infantería_de_marina proporcionar a el armada el capacidad necesario para cumplir el misión propio de el fuerza de desembarco y proporcionar protección a el flota y a el instalación en tierra el uscan estar mandar por el teniente coronel de infantería_de_marina_d._alfredo_gonzález_molina nacer en madrid en el [??:??/??/1960:??.??:??] ingresar en el escuela_naval_militar en 1980 a el largo de su carrera haber estar destinar en el tercio_de_armada en el subdirección_de_personal_de_la_armada en el escuela_naval_militar como profesor haber participar en el misión de bosnia-herzegovina en el misión de paz de naciones_unidas en guatemala minugua y en el operación_alfa-charlie de ayuda humanitario a centroamérica",
        "lemmatized_text_reduced": "infantería_de_marina español reconocer antigüedad corresponder tercio_nuevo_del_mar_de_nápoles proceder fijar fecha día creación corresponder día constitución tercios_de_la_armada_del_mar_océano galeras_de_sicilia nápoles informar armada_española comunicado la presencia permanente infantería_de_marina archipiélago remontar creación tercio_de_canarias basar arsenal paso año cambiar denominación ubicación asentar nuevo arsenal_militar_de_las_palmas denominar unidad_de_seguridad_de_canarias uscan misión principal ser estar preparar cumplimiento misión permanente específico armada relacionar protección seguridad físico base instalación naval persona transporte munición material sensible cuerpo_de_infantería_de_marina proporcionar armada capacidad necesario cumplir misión propio fuerza desembarco proporcionar protección flota instalación tierra uscan estar mandar teniente coronel infantería_de_marina_d._alfredo_gonzález_molina nacer madrid ingresar escuela_naval_militar largo carrera haber estar destinar tercio_de_armada subdirección_de_personal_de_la_armada escuela_naval_militar profesor haber participar misión bosnia-herzegovina misión paz naciones_unidas guatemala minugua operación_alfa-charlie ayuda humanitario centroamérica",
        "persons": [
            "La",
            "Infantería_de_Marina_D._Alfredo_González_Molina"
        ],
        "locations": [
            "Tercio_Nuevo_del_Mar_de_Nápoles",
            "Tercios_de_la_Armada_del_Mar_Océano",
            "Galeras_de_Sicilia",
            "Nápoles",
            "Madrid",
            "Subdirección_de_Personal_de_la_Armada",
            "Bosnia-Herzegovina",
            "Guatemala",
            "Minugua",
            "Centroamérica"
        ],
        "organizations": [
            "Infantería_de_Marina",
            "Armada_Española",
            "Infantería_de_Marina",
            "Arsenal",
            "Arsenal_Militar_de_Las_Palmas",
            "Unidad_de_Seguridad_de_Canarias",
            "USCAN",
            "Armada",
            "Cuerpo_de_Infantería_de_Marina",
            "Armada",
            "USCAN",
            "Teniente",
            "Escuela_Naval_Militar",
            "Tercio_de_Armada",
            "Escuela_Naval_Militar",
            "Naciones_Unidas"
        ],
        "others": [
            "Tercio_de_Canarias",
            "Operación_Alfa-Charlie"
        ],
        "dates": [
            "[??:27/2/??:??.??:??]",
            "[??:??/??/1940:??.??:??]",
            "[??:??/??/2002:??.??:??]",
            "[??:??/??/1960:??.??:??]"
        ],
        "numbers": [
            "1537",
            "1980"
        ]
    }
}
