{
    "province": "LAS PALMAS",
    "date": "2010-01-14T00:00:00",
    "url": "https://www.20minutos.es/noticia/606629/0/",
    "title": {
        "raw_text": "Empresarios traducen el descenso de los precios en las islas en que el archipiélago continúa en situación \"crítica\"",
        "lemmatized_text": "empresarios traducir el descenso de el precio en el isla en que el archipiélago continuar en situación crítica",
        "lemmatized_text_reduced": "empresarios traducir descenso precio isla archipiélago continuar situación crítica",
        "persons": [
            "Empresarios"
        ],
        "locations": [],
        "organizations": [],
        "others": [],
        "dates": [],
        "numbers": []
    },
    "lead": {
        "raw_text": "La Confederación Canaria de Empresarios (CCE) señaló que los datos aparecidos hoy en el Índice de Precios al Consumo (IPC), donde se observa que los precios han descendido en el archipiélago un 0,4 por ciento durante 2009, suponen que las islas continúan en situación \"crítica\".",
        "lemmatized_text": "el confederación_canaria_de_empresarios cce señalar que el dato aparecer hoy en el índice_de_precios a el consumo ipc donde se observar que el precio haber descender en el archipiélago uno 0,4 por 100 durante 2009 suponer que el isla continuar en situación crítica",
        "lemmatized_text_reduced": "confederación_canaria_de_empresarios cce señalar dato aparecer índice_de_precios consumo ipc observar precio haber descender archipiélago suponer isla continuar situación crítica",
        "persons": [],
        "locations": [
            "Índice_de_Precios"
        ],
        "organizations": [
            "Confederación_Canaria_de_Empresarios",
            "CCE",
            "Consumo"
        ],
        "others": [
            "IPC"
        ],
        "dates": [],
        "numbers": [
            "0,4",
            "100",
            "2009"
        ]
    },
    "body": {
        "raw_text": "Asimismo, indicó que la inflación subyacente en Canarias \"ha acentuado su ritmo de descenso\", ya que ha cerrado el año con una variación negativa del 0,7 por ciento interanual, \"lo que pone de manifiesto que Canarias continúa sumida en una situación crítica y que el estancamiento del consumo privado sigue marcando la coyuntura de la economía regional\". La CCE apuntó, en nota de prensa, que 2009 se cerró con variaciones \"nulas o descensos en la gran mayoría\" de los grupos que componen la cesta de consumo en Canarias, grupos \"tradicionalmente inflacionistas\" en Navidad, tales como Vestido y calzado, Bebidas alcohólicas y tabaco o Alimentos y bebidas no alcohólicas, que experimentaron descensos mensuales del 0,6 por ciento, 0,5 por ciento y 0,1 por ciento, respectivamente. Estas caídas se unieron a las producidas en el grupo de Bienes y servicios relacionados con el transporte (-0,3%), entre los que se incluyen los carburantes y la adquisición de vehículos. Sin embargo, la excepción fue el apartado de Ocio y cultura, así como Hoteles, cafés y restaurantes, ya que registraron repuntes moderados respecto a noviembre del 0,9 por ciento y del 0,2 por ciento mensual, respectivamente. Respecto a la evolución anual de la inflación, el IPC de Canarias cerró 2009 con una variación anual negativa del 0,4 por ciento, convirtiendo a las islas en la \"única\" comunidad autónoma donde han descendido los precios. Esto contrasta con lo observado en el conjunto nacional, ya que el IPC en España se situó en el 0,8 por ciento, y las demás comunidades autónomas registran variaciones positivas, \"en todos los casos\", superiores al 0,5 por ciento. La CCE aseguró que la caída en los precios en Canarias durante 2009 ha afectado \"especialmente\" a los grupos de Alimentos y bebidas no alcohólicas donde se recoge un descenso del 2,7 por ciento en comparación con el ejercicio anterior, además de Medicina, así como Vestido y calzado que cerraron el año con unos precios inferiores a los de 2008, en un 2,0 por ciento y en un 1,2 por ciento, respectivamente. Estos descensos son \"más acentuados\" que en el resto del territorio nacional, una \"tónica que se mantiene\" en otros grupos que componen el IPC, tales como Menaje, Ocio y cultura o Comunicaciones, donde se han registrado también variaciones negativas del 1,0 por ciento, en los dos primeros casos, y del 0,4 por ciento en el último. Así, en Canarias, \"únicamente\" se han encarecido los precios en Bebidas alcohólicas y tabaco (3,4%), Enseñanza (2,7%) y Transportes\" (1,1%), este último a causa de la \"influencia ejercida por la trayectoria alcista de los carburantes fósiles durante buena parte del ejercicio, una tendencia que probablemente se intensifique durante los próximos meses\".",
        "lemmatized_text": "asimismo indicar que el inflación subyacente en canarias haber acentuar su ritmo de descenso ya_que haber cerrar el año con uno variación negativo de el 0,7 por 100 interanual el que poner_de_manifiesto que canarias continuar sumir en uno situación crítico y que el estancamiento de el consumo privar seguir marcar el coyuntura de el economía regional el cce apuntar en nota de prensa que 2009 se cerrar con variación nulo o descenso en el gran mayoría de el grupo que componer el cesta de consumo en canarias grupo tradicionalmente inflacionista en navidad tal como vestido y calzado bebidas alcohólico y tabaco o alimentos y bebida no alcohólico que experimentar descenso mensual de el 0,6 por 100 0,5 por 100 y 0,1 por 100 respectivamente este caída se unir a el producir en el grupo de bienes y servicio relacionar con el transporte -0,3/100 entre el que se incluir el carburante y el adquisición de vehículo sin embargo el excepción ser el apartado de ocio y cultura así_como hoteles café y restaurante ya_que registrar repunte moderar respecto_a [??:??/11/-99999:??.??:??] por 100 y de el 0,2 por 100 mensual respectivamente respecto_a el evolución anual de el inflación el ipc_de_canarias cerrar 2009 con uno variación anual negativa de el 0,4 por 100 convertir a el isla en el único comunidad autónomo donde haber descender el precio este contrastar con el observar en el conjunto nacional ya_que el ipc en españa se situar en el 0,8 por 100 y el demás comunidad autónomo registrar variación positivo en todo el caso superior a el 0,5 por 100 el cce asegurar que el caída en el precio en canarias durante 2009 haber afectar especialmente a el grupo de alimentos y bebida no alcohólico donde se recoger uno descenso de el 2,7 por 100 en comparación con el ejercicio anterior además_de medicina así_como vestido y calzado que cerrar el año con uno precio inferior a el de 2008 en uno 2,0 por 100 y en uno 1,2 por 100 respectivamente este descenso ser más acentuar que en el resto de el territorio nacional uno tónica que se mantener en otro grupo que componer el ipc tal como menaje ocio y cultura o comunicaciones donde se haber registrar también variación negativo de el 1,0 por 100 en el 2 1 caso y de el 0,4 por 100 en el último así en canarias únicamente se haber encarecer el precio en bebidas alcohólico y tabaco 3,4/100 enseñanza 2,7/100 y transportes 1,1/100 este último a_causa_de el influencia ejercer por el trayectoria alcista de el carburante fósil durante bueno parte de el ejercicio uno tendencia que probablemente se intensificar durante el próximo mes",
        "lemmatized_text_reduced": "indicar inflación subyacente canarias haber acentuar ritmo descenso haber cerrar año variación negativo interanual poner_de_manifiesto canarias continuar sumir situación crítico estancamiento consumo privar seguir marcar coyuntura economía regional cce apuntar nota prensa cerrar variación nulo descenso gran mayoría grupo componer cesta consumo canarias grupo tradicionalmente inflacionista navidad vestido calzado bebidas alcohólico tabaco alimentos bebida alcohólico experimentar descenso mensual respectivamente caída unir producir grupo bienes servicio relacionar transporte incluir carburante adquisición vehículo embargo excepción ser apartado ocio cultura hoteles café restaurante registrar repunte moderar mensual respectivamente evolución anual inflación ipc_de_canarias cerrar variación anual negativa convertir isla único comunidad autónomo haber descender precio contrastar observar conjunto nacional ipc españa situar comunidad autónomo registrar variación positivo caso superior cce asegurar caída precio canarias haber afectar especialmente grupo alimentos bebida alcohólico recoger descenso comparación ejercicio anterior medicina vestido calzado cerrar año precio inferior respectivamente descenso ser acentuar resto territorio nacional tónica mantener grupo componer ipc menaje ocio cultura comunicaciones haber registrar variación negativo 1 caso último canarias únicamente haber encarecer precio bebidas alcohólico tabaco enseñanza transportes último influencia ejercer trayectoria alcista carburante fósil bueno parte ejercicio tendencia probablemente intensificar próximo mes",
        "persons": [
            "Vestido",
            "Bebidas",
            "Ocio",
            "Hoteles",
            "Vestido",
            "Menaje",
            "Ocio",
            "Enseñanza"
        ],
        "locations": [
            "Canarias",
            "Canarias",
            "Canarias",
            "Bienes",
            "España",
            "Canarias",
            "Alimentos",
            "Canarias",
            "Bebidas"
        ],
        "organizations": [
            "CCE",
            "Alimentos",
            "CCE",
            "Medicina",
            "Transportes"
        ],
        "others": [
            "Navidad",
            "IPC_de_Canarias",
            "IPC",
            "IPC",
            "Comunicaciones"
        ],
        "dates": [
            "[??:??/11/-99999:??.??:??]"
        ],
        "numbers": [
            "0,7",
            "100",
            "2009",
            "0,6",
            "100",
            "0,5",
            "100",
            "0,1",
            "100",
            "-0,3/100",
            "100",
            "0,2",
            "100",
            "2009",
            "0,4",
            "100",
            "0,8",
            "100",
            "0,5",
            "100",
            "2009",
            "2,7",
            "100",
            "2008",
            "2,0",
            "100",
            "1,2",
            "100",
            "1,0",
            "100",
            "2",
            "0,4",
            "100",
            "3,4/100",
            "2,7/100",
            "1,1/100"
        ]
    }
}
