{
    "province": "LAS PALMAS",
    "date": "2011-02-26T00:00:00",
    "url": "https://www.20minutos.es/noticia/972191/0/",
    "title": {
        "raw_text": "Kate Ryan, Whigfield y Robert Ramírez actuarán en la Gala Drag Queen del Carnaval de Las Palmas de Gran Canaria",
        "lemmatized_text": "kate_ryan whigfield y robert_ramírez actuar en el gala_drag_queen_del_carnaval_de_las_palmas_de_gran_canaria",
        "lemmatized_text_reduced": "kate_ryan whigfield robert_ramírez actuar gala_drag_queen_del_carnaval_de_las_palmas_de_gran_canaria",
        "persons": [
            "Kate_Ryan",
            "Whigfield",
            "Robert_Ramírez"
        ],
        "locations": [
            "Gala_Drag_Queen_del_Carnaval_de_Las_Palmas_de_Gran_Canaria"
        ],
        "organizations": [],
        "others": [],
        "dates": [],
        "numbers": []
    },
    "lead": {
        "raw_text": "La gala Drag Queen de Las Palmas de Gran Canaria --viernes 4 de marzo a las 21.00 horas) sonará a música dance de la mano de tres artistas: la belga Kate Ryan --Ella Elle L'A--, la danesa Whigfield --Saturday Night-- y Robert Ramírez --Sick of Love--. Todos ellos serán los invitados especiales al gran espectáculo de las plataformas y la trasgresión, informó el Ayuntamiento capitalino en un comunicado.",
        "lemmatized_text": "el gala drag_queen_de_las_palmas_de_gran_canaria [V:4/3/??:9.00:pm] sonar a música danzar de_la_mano_de 3 artista el belga kate_ryan él elle_l'a el danés whigfield saturday_night y robert_ramírez sick of love todo ellos ser el invitado especial a el gran espectáculo de el plataforma y el trasgresión informar el ayuntamiento capitalino en uno comunicado",
        "lemmatized_text_reduced": "gala drag_queen_de_las_palmas_de_gran_canaria sonar música danzar artista belga kate_ryan elle_l'a danés whigfield saturday_night robert_ramírez sick of love ser invitado especial gran espectáculo plataforma trasgresión informar ayuntamiento capitalino comunicado",
        "persons": [
            "Kate_Ryan",
            "Elle_L'A",
            "Whigfield",
            "Saturday_Night",
            "Robert_Ramírez",
            "Sick",
            "Love"
        ],
        "locations": [],
        "organizations": [
            "Drag_Queen_de_Las_Palmas_de_Gran_Canaria",
            "Ayuntamiento"
        ],
        "others": [],
        "dates": [
            "[V:4/3/??:9.00:pm]"
        ],
        "numbers": [
            "3"
        ]
    },
    "body": {
        "raw_text": "La gala Drag Queen de Las Palmas de Gran Canaria —viernes 4 de marzo a las 21.00 horas) sonará a música dance de la mano de tres artistas: la belga Kate Ryan —Ella Elle L'A—, la danesa Whigfield —Saturday Night— y Robert Ramírez —Sick of Love—. Todos ellos serán los invitados especiales al gran espectáculo de las plataformas y la trasgresión, informó el Ayuntamiento capitalino en un comunicado. La belga Kate Ryan es una de las cantantes más destacadas de la música dance europea, conocida sobre todo en nuestro país porque su Ella Elle L'A fue sin duda una de las canciones del verano español del 2008. Del mismo álbum, Free —en el que colaboró la española Soraya—, destacó además otro single, una nueva versión de la conocida Voyage voyage. Ryan, representante de su país en el Festival de Eurovisión 2006, publicó el pasado año French Conection, en el que sobresalía el pegadizo single Babacar. Su gira en España fue un éxito en el que destacaron conciertos como los de Santander o Bilbao con 20.000 y 30.000 personas respectivamente. Además, el primer disco de Kate Ryan, Scream for more, se editó en muchos países por diferentes sellos dance y consiguió la nominación como Mejor Canción Del Año en los premios Belgas TMF (que forman parte del grupo MTV). En 2002 publicó el álbum Different, que sorprendió al público español con los singles Desenchantée y Mon coeur résiste encore; ambos, cantados en francés, llegaron a ser número uno de superventas en singles. Por su parte, Sannie Carlson, conocida artísticamente como Whigfield, es la danesa que marcó un hito en la música pop-dance vendiendo millones de copias en todo el mundo; en 1994 se ganó un lugar en el Libro Guinness de los Récords con la canción Saturday Night, como el primer artista en ir directamente al número uno en las listas de singles del Reino Unido con su single de debut. Después de muchos años en el escenario, Sannie Carlson ha decidido concentrarse en el otro lado de la industria de la música, escribiendo y componiendo para otros artistas como el ganador del Grammy Benny Benassi, Ann Lee y In-Grid. Su último lanzamiento es el álbum llamado All in One, además del cover de Right in the night (la famosa pista de Jam & Spoon) y una nueva canción llamada Rainbow. También actuará Robert Ramírez, uno de los artistas del momento en España. Su canción Sick of love ha revolucionado las pistas de baile españolas y, tras su éxito el tema se ha lanzado en Alemania, Francia, Italia, Holanda, Portugal, Venezuela, Turquía, México, Argentina, Reino Unido y Estados Unidos, entre otros. Posteriormente, nada más presentarse su segundo single, I' a Number, Fiat la solicitó como canción para el spot de televisión en el lanzamiento de su modelo Bravo. Por último, el grupo canario M-Lou, interpretará su versión del clásico de los años 80, Deeper of Love, con la voz de once cantantes dirigidos por María Lola Jaria.",
        "lemmatized_text": "el gala drag_queen_de_las_palmas_de_gran_canaria [V:4/3/??:9.00:pm] sonar a música danzar de_la_mano_de 3 artista el belga kate_ryan ella_elle_l'a el danés whigfield saturday_night y robert_ramírez sick of love todo ellos ser el invitado especial a el gran espectáculo de el plataforma y el trasgresión informar el ayuntamiento capitalino en uno comunicado el belga kate_ryan ser uno de el cantante más destacar de el música danzar europeo conocer sobre todo en nuestro país porque su ella_elle_l'a ser sin duda uno de el canción de el verano español de el 2008 de el mismo álbum free en el que colaborar el español soraya destacar además otro single uno nuevo versión de el conocer voyage voyage ryan representante de su país en el festival_de_eurovisión 2006 publicar el pasar año french_conection en el que sobresalir el pegadizo single babacar su gira en españa ser uno éxito en el que destacar concierto como el de santander o bilbao con 20 y 30 persona respectivamente además el 1 disco de kate_ryan scream for morar se editar en mucho país por diferente sello danzar y conseguir el nominación como mejor_canción_del_año en el premio belgas_tmf que formar_parte de el grupo mtv en 2002 publicar el álbum different que sorprender a el público español con el single desenchantée y mon coeur résiste encore ambos cantar en francés llegar a ser número uno de superventa en single por su parte sannie_carlson conocer artísticamente como whigfield ser el danés que marcar uno hito en el música pop-dance vender millón de copia en todo el mundo en 1994 se ganar uno lugar en el libro_guinness_de_los_récords con el canción saturday_night como el 1 artista en ir directamente a el número uno en el lista de single de el reino_unido con su single de debut después_de mucho año en el escenario sannie_carlson haber decidir concentrar se en_el_otro_lado_de el industria de el música escribir y componer para otro artista como el ganador de el grammy_benny_benassi ann_lee y in-grid su último lanzamiento ser el álbum llamar all in one además de el cover de right in the night el famoso pista de jam_&_spoon y uno nuevo canción llamar rainbow también actuar robert_ramírez uno de el artista de el momento en españa su canción sick of love haber revolucionar el pista de baile español y tras su éxito el tema se haber lanzar en alemania francia italia holanda portugal venezuela turquía méxico argentina reino_unido y estados_unidos entre otro posteriormente nada más presentar se su 2 single i a number fiat lo solicitar como canción para el spot de televisión en el lanzamiento de su modelo bravo por último el grupo canario m-lou interpretar su versión de el clásico de el año 80 deeper of love con el voz de 11 cantante dirigir por maría_lola_jaria",
        "lemmatized_text_reduced": "gala drag_queen_de_las_palmas_de_gran_canaria sonar música danzar artista belga kate_ryan ella_elle_l'a danés whigfield saturday_night robert_ramírez sick of love ser invitado especial gran espectáculo plataforma trasgresión informar ayuntamiento capitalino comunicado belga kate_ryan ser cantante destacar música danzar europeo conocer país ella_elle_l'a ser duda canción verano español mismo álbum free colaborar español soraya destacar single nuevo versión conocer voyage voyage ryan representante país festival_de_eurovisión publicar pasar año french_conection sobresalir pegadizo single babacar gira españa ser éxito destacar concierto santander bilbao persona respectivamente 1 disco kate_ryan scream for morar editar país sello danzar conseguir nominación mejor_canción_del_año premio belgas_tmf formar_parte grupo mtv publicar álbum different sorprender público español single desenchantée mon coeur résiste encore cantar francés llegar ser número superventa single parte sannie_carlson conocer artísticamente whigfield ser danés marcar hito música pop-dance vender millón copia mundo ganar lugar libro_guinness_de_los_récords canción saturday_night 1 artista ir directamente número lista single reino_unido single debut año escenario sannie_carlson haber decidir concentrar industria música escribir componer artista ganador grammy_benny_benassi ann_lee in-grid último lanzamiento ser álbum llamar all in one cover right in night famoso pista jam_&_spoon nuevo canción llamar rainbow actuar robert_ramírez artista momento españa canción sick of love haber revolucionar pista baile español éxito tema haber lanzar alemania francia italia holanda portugal venezuela turquía méxico argentina reino_unido estados_unidos posteriormente presentar 2 single i number fiat solicitar canción spot televisión lanzamiento modelo bravo último grupo canario m-lou interpretar versión clásico año deeper of love voz cantante dirigir maría_lola_jaria",
        "persons": [
            "Kate_Ryan",
            "Saturday_Night",
            "Robert_Ramírez",
            "Sick",
            "Love",
            "Kate_Ryan",
            "Free",
            "Soraya",
            "Voyage",
            "Ryan",
            "French_Conection",
            "Scream",
            "Mejor_Canción_Del_Año",
            "Different",
            "Mon",
            "Sannie_Carlson",
            "Whigfield",
            "Saturday_Night",
            "Sannie_Carlson",
            "Ann_Lee",
            "All",
            "Right",
            "Robert_Ramírez",
            "Sick",
            "Bravo",
            "Love",
            "María_Lola_Jaria"
        ],
        "locations": [
            "España",
            "Santander",
            "Bilbao",
            "Libro_Guinness_de_los_Récords",
            "Reino_Unido",
            "España",
            "Alemania",
            "Italia",
            "Holanda",
            "Portugal",
            "Venezuela",
            "México",
            "Estados_Unidos",
            "Number"
        ],
        "organizations": [
            "Drag_Queen_de_Las_Palmas_de_Gran_Canaria",
            "Whigfield",
            "Ayuntamiento",
            "Ella_Elle_L'A",
            "Babacar",
            "MTV",
            "In-Grid",
            "One",
            "Rainbow",
            "Francia",
            "Turquía",
            "Argentina",
            "Reino_Unido",
            "Fiat",
            "M-Lou",
            "Deeper"
        ],
        "others": [
            "Ella_Elle_L'A",
            "Festival_de_Eurovisión",
            "Kate_Ryan",
            "Belgas_TMF",
            "Desenchantée",
            "Grammy_Benny_Benassi",
            "Jam_&_Spoon",
            "I"
        ],
        "dates": [
            "[V:4/3/??:9.00:pm]"
        ],
        "numbers": [
            "3",
            "2008",
            "2006",
            "20",
            "30",
            "2002",
            "1994",
            "80",
            "11"
        ]
    }
}
