{
    "province": "LAS PALMAS",
    "date": "2007-10-08T00:00:00",
    "url": "https://www.20minutos.es/noticia/287547/0/drogas/canarias/trafico/",
    "title": {
        "raw_text": "Las Islas Canarias: parada casi obligada para el tráfico de drogas hacia la UE",
        "lemmatized_text": "el islas_canarias parada casi obligar para el tráfico de droga hacia el ue",
        "lemmatized_text_reduced": "islas_canarias parada obligar tráfico droga ue",
        "persons": [],
        "locations": [
            "Islas_Canarias"
        ],
        "organizations": [
            "UE"
        ],
        "others": [],
        "dates": [],
        "numbers": []
    },
    "lead": {
        "raw_text": "Un informe de la Europol revela que las tres rutas pasan por las Islas. Las miles de toneladas de cocaína provienen de Sudamérica. Barcas rápidas, cargueros y barcos contenedores: el transporte ideal. CONSULTA AQUÍ TODAS LAS NOTICIAS DE LAS PALMAS.",
        "lemmatized_text": "uno informe de el europol revelar que el 3 ruta pasar por el islas el mil de tonelada de cocaína provenir de sudamérica barcas rápido carguero y barco contenedor el transporte ideal consulta_aquí_todas_las_noticias_de_las_palmas",
        "lemmatized_text_reduced": "informe europol revelar ruta pasar islas mil tonelada cocaína provenir sudamérica barcas rápido carguero barco contenedor transporte ideal consulta_aquí_todas_las_noticias_de_las_palmas",
        "persons": [
            "Barcas"
        ],
        "locations": [
            "Sudamérica"
        ],
        "organizations": [
            "Europol",
            "Islas",
            "CONSULTA_AQUÍ_TODAS_LAS_NOTICIAS_DE_LAS_PALMAS"
        ],
        "others": [],
        "dates": [],
        "numbers": [
            "3"
        ]
    },
    "body": {
        "raw_text": "Para los traficantes sudamericanos de cocaína la costa oeste de África y la ruta que incluye a las Islas Canarias tiene cada vez más importancia. Así se desprende del último informe de Europol, en el que también alertan de que las tres principales rutas de esta droga hacia Europa tocan algún punto de la geografía española . Según el organismo de coordinación policial europeo, las embarcaciones procedentes de América que contrabandean con ‘coca' y que navegan por el Atlántico para llevar la carga a la Unión Europea paran o transitan por España por alguna de las tres principales rutas identificas por Europol. Rutas de los narcotraficantes Las rutas de los narcotraficantes puestas al descubierto por la Europol son tres . La norte , que comienza en el Caribe, pasa por las Azores y se va a España y Portugal. La del centro tiene su punto de partida en Sudamérica rumbo Cabo Verde, Madeira y las Islas Canarias para luego ir al continente vía Portugal y España. Por último la ruta africana . Ésta, según la misma fuente, sale desde Sudamérica y va hasta el norte de África para de ahí ser transportada hasta España y Portugal. Para Europol los países de partida de estos cargamentos de miles de toneladas de cocaína son \"Colombia, Venezuela, Brasil, Ecuador, Chile, Argentina y Surinam\". El informe revela que \" las barcas rápidas, los cargueros y los barcos contenedores siguen siendo los medios de transporte más utilizados para mover la droga por la región, pero los traficantes también usan aviones para dejar caer la carga en aguas internacionales\". El organismo cree que las bandas colombianas son las que dominan el mercado de importación de cocaína y que \"sus principales socios son los españoles y portugueses, por lo que la costa oeste del continente africano está ganando importancia en el tráfico y almacenamiento de la cocaína que viene de América, que más tarde se traslada a la costa norte de Portugal o de Galicia\". CONSULTA AQUÍ MÁS NOTICIAS DE LAS PALMAS",
        "lemmatized_text": "para el traficante sudamericano de cocaína el costa oeste de áfrica y el ruta que incluir a el islas_canarias tener cada vez más importancia así se desprender de el último informe de europol en el que también alertar de que el 3 principal ruta de este droga hacia europa tocar alguno punto de el geografía español según el organismo de coordinación policial europeo el embarcación procedente de américa que contrabandear con coca y que navegar por el atlántico para llevar el carga a el unión_europea parar o transitar por españa por alguno de el 3 principal ruta identificar por europol rutas de el narcotraficante las ruta de el narcotraficante poner a el descubierto por el europol ser 3 el norte que comenzar en el caribe pasar por el azores y se ir a españa y portugal el de el centro tener su punto de partida en sudamérica rumbo cabo_verde madeira y el islas_canarias para luego ir a el continente vía portugal y españa por último el ruta africano este según el mismo fuente salir desde sudamérica y ir hasta el norte de áfrica para de ahí ser transportar hasta españa y portugal para europol el país de partida de este cargamento de mil de tonelada de cocaína ser colombia venezuela brasil ecuador chile argentina y surinam el informe revelar que el barca rápido el carguero y el barco contenedor seguir ser el medio de transporte más utilizar para mover el droga por el región pero el traficante también usar avión para dejar caer el carga en agua internacional el organismo creer que el banda colombiano ser el que dominar el mercado de importación de cocaína y que su principal socio ser el español y portugués por el que el costa oeste de el continente africano estar ganar importancia en el tráfico y almacenamiento de el cocaína que venir de américa que más tarde se trasladar a el costa norte de portugal o de galicia consulta_aquí_más_noticias_de_las_palmas",
        "lemmatized_text_reduced": "traficante sudamericano cocaína costa oeste áfrica ruta incluir islas_canarias tener vez importancia desprender último informe europol alertar principal ruta droga europa tocar punto geografía español organismo coordinación policial europeo embarcación procedente américa contrabandear coca navegar atlántico llevar carga unión_europea parar transitar españa principal ruta identificar europol rutas narcotraficante las ruta narcotraficante poner descubierto europol ser norte comenzar caribe pasar azores ir españa portugal centro tener punto partida sudamérica rumbo cabo_verde madeira islas_canarias ir continente portugal españa último ruta africano mismo fuente salir sudamérica ir norte áfrica ser transportar españa portugal europol país partida cargamento mil tonelada cocaína ser colombia venezuela brasil ecuador chile argentina surinam informe revelar barca rápido carguero barco contenedor seguir ser medio transporte utilizar mover droga región traficante usar avión dejar caer carga agua internacional organismo creer banda colombiano ser dominar mercado importación cocaína principal socio ser español portugués costa oeste continente africano estar ganar importancia tráfico almacenamiento cocaína venir américa trasladar costa norte portugal galicia consulta_aquí_más_noticias_de_las_palmas",
        "persons": [
            "España",
            "Rutas"
        ],
        "locations": [
            "África",
            "Islas_Canarias",
            "América",
            "España",
            "Portugal",
            "Sudamérica",
            "Cabo_Verde",
            "Madeira",
            "Islas_Canarias",
            "Portugal",
            "España",
            "Sudamérica",
            "África",
            "Portugal",
            "Venezuela",
            "América",
            "Portugal",
            "Galicia"
        ],
        "organizations": [
            "Europol",
            "Europa",
            "Atlántico",
            "Unión_Europea",
            "Europol",
            "Europol",
            "Caribe",
            "Azores",
            "España",
            "Europol",
            "Colombia",
            "Brasil",
            "Ecuador",
            "Chile",
            "Argentina",
            "Surinam",
            "CONSULTA_AQUÍ_MÁS_NOTICIAS_DE_LAS_PALMAS"
        ],
        "others": [
            "Las"
        ],
        "dates": [],
        "numbers": [
            "3",
            "3",
            "3"
        ]
    }
}
