{
    "province": "LAS PALMAS",
    "date": "2010-01-15T00:00:00",
    "url": "https://www.20minutos.es/noticia/607166/0/",
    "title": {
        "raw_text": "Gran Canaria espera recibir \"como mínimo\" 600.000 turistas peninsulares a lo largo del 2010",
        "lemmatized_text": "gran_canaria esperar recibir como_mínimo 600 turista peninsular a el largo de el 2010",
        "lemmatized_text_reduced": "gran_canaria esperar recibir turista peninsular largo",
        "persons": [],
        "locations": [],
        "organizations": [
            "Gran_Canaria"
        ],
        "others": [],
        "dates": [],
        "numbers": [
            "600",
            "2010"
        ]
    },
    "lead": {
        "raw_text": "El Cabildo de Gran Canaria se ha mostrado hoy \"moderadamente optimista\" con la cifra de turistas peninsulares que prevé recibir en 2010 esperando que \"como mínimo\" unos 600.000 visitantes procedentes de la Península escojan la isla como destino, ya que las principales compañías aéreas han anunciado un incremento de capacidad para este año.",
        "lemmatized_text": "el cabildo_de_gran_canaria se haber mostrar hoy moderadamente optimista con el cifra de turista peninsular que prever recibir en 2010 esperar que como_mínimo uno 600 visitante procedente de el península escoger el isla como destino ya_que el principal compañía aéreo haber anunciar uno incremento de capacidad para este año",
        "lemmatized_text_reduced": "cabildo_de_gran_canaria haber mostrar moderadamente optimista cifra turista peninsular prever recibir esperar visitante procedente península escoger isla destino principal compañía aéreo haber anunciar incremento capacidad año",
        "persons": [],
        "locations": [
            "Península"
        ],
        "organizations": [
            "Cabildo_de_Gran_Canaria"
        ],
        "others": [],
        "dates": [],
        "numbers": [
            "2010",
            "600"
        ]
    },
    "body": {
        "raw_text": "Así lo manifestó hoy el consejero de Turismo, Comercio Exterior e Innovación Tecnológica, Roberto Moreno, en una rueda de prensa en la que recordó que si se cumplen las previsiones, Gran Canaria recibirá alrededor de 100.000 turistas peninsulares más que los contabilizados en 2009. \"Si hay que ser moderadamente optimistas y sabiendo que el turismo peninsular tiene tres picos en el año; diciembre, agosto-septiembre y el mes en el que cae semana santa, creo que podríamos esperar alrededor de 600.000 turistas peninsulares como mínimo a lo largo del año 2010 en Gran Canaria\", afirmó el también presidente del Patronato de Turismo de la isla. En este sentido, recordó que durante el invierno se han aumentado \"notablemente\" las plazas de avión de Península a Gran Canaria y ahora el trayecto cuenta con \"37 vuelos más cada semana comparados con el invierno anterior.\" El consejero insular de Turismo señaló que este mercado turístico \"ha seguido la tónica a la baja del resto de mercados turísticos con un decrecimiento entre enero y noviembre del 13 por ciento, eso sitúa a la isla en torno al medio millón de turistas hasta el mes de noviembre\". \"Aun así se ha convertido en el segundo mercado en importancia por nacionalidades para la isla debido a la fuerte bajada del mercado inglés e irlandés durante el pasado año\", agregó. Moreno destacó que Gran Canaria tiene \"uno de los mayores índices de fidelidad del turismo peninsular en toda Canarias, ya que el descenso del turismo peninsular de enero a noviembre en el conjunto del archipiélago ha sido de un 21 por ciento mientras que Gran Canaria se ha quedado en un 13 por ciento de descenso\". \"Es un mercado importante, el gasto diario en destino del turista peninsular es alto comparado con otras nacionalidades, y en Gran Canaria comparado con el conjunto de Canarias es también de los más altos, según el Istac el gasto diario medio del turista peninsular en Canarias está en el orden de los 48 euros y en Gran Canaria está en el orden de los 58 euros\", dijo el consejero de Turismo. Asimismo, desveló que \"las zonas de la Península donde mejor y más se vende Gran Canaria como destino son las de toda la franja mediterránea; Cataluña, Comunidad Valenciana, Murcia y también Andalucía\". Incremento de turistas extranjeros que viajan vía península El presidente del Patronato de Turismo de Gran Canaria, subrayó que la contabilidad de turistas \"tiene tres componentes; los turistas extranjeros que vienen en vuelos directos, los turistas peninsulares y los turistas extranjeros que vienen vía Península\". \"Este último grupo, según datos de Frontur, en los meses de octubre, septiembre y noviembre en Gran Canaria ha crecido notablemente, en parte debido a eses incremento de rutas Península-Gran Canaria, que no sólo usan los clientes peninsulares\", aclaró Moreno. Finalmente, desveló que en este aspecto \"el número total, a falta de los datos de diciembre, roza los 3 millones de turistas en Gran Canaria en 2009, en 2008 3,4 millones como suma de esos tres componentes\".",
        "lemmatized_text": "así lo manifestar hoy el consejero de turismo comercio_exterior y innovación_tecnológica roberto_moreno en uno rueda de prensa en el que recordar que si se cumplir el previsión gran_canaria recibir alrededor_de 100 turista peninsular más que el contabilizar en 2009 si haber que ser moderadamente optimista y saber que el turismo peninsular tener 3 pico en el año [??:??/12/??:??.??:??] agosto-septiembre y el mes en el que caer semana santo creer que poder esperar alrededor_de 600 turista peninsular como_mínimo a el largo de el [??:??/??/2010:??.??:??] en gran_canaria afirmar el también presidente de el patronato_de_turismo de el isla en este sentido recordar que durante el invierno se haber aumentar notablemente el plaza de avión de península a gran_canaria y ahora el trayecto contar con 37 vuelo más cada semana comparar con el invierno anterior el consejero insular de turismo señalar que este mercado turístico haber seguir el tónica a el baja de el resto de mercado turístico con uno decrecimiento entre [??:??/1/??:??.??:??] y [??:??/11/13:??.??:??] por 100 ese situar a el isla en torno a el 500000 de turista hasta el [??:??/11/??:??.??:??] aun así se haber convertir en el 2 mercado en importancia por nacionalidad para el isla debido_a el fuerte bajada de el mercado inglés y irlandés durante el pasar año agregar moreno destacar que gran_canaria tener uno de el mayor índice de fidelidad de el turismo peninsular en todo canarias ya_que el descenso de el turismo peninsular de [??:??/1/??:??.??:??] a [??:??/11/??:??.??:??] en el conjunto de el archipiélago haber ser de uno 21 por 100 mientras_que gran_canaria se haber quedar en uno 13 por 100 de descenso ser uno mercado importante el gasto diario en destino de el turista peninsular ser alto comparar con otro nacionalidad y en gran_canaria comparar con el conjunto de canarias ser también de el más alto según el istac el gasto diario medio de el turista peninsular en canarias estar en el orden de el $_ECU:48 y en gran_canaria estar en el orden de el $_ECU:58 decir el consejero de turismo asimismo desvelar que el zona de el península donde mejor y más se vender gran_canaria como destino ser el de todo el franja mediterráneo cataluña comunidad_valenciana murcia y también andalucía incremento de turista extranjero que viajar vía península el presidente de el patronato_de_turismo_de_gran_canaria subrayar que el contabilidad de turista tener 3 componente el turista extranjero que venir en vuelo directo el turista peninsular y el turista extranjero que venir vía península este último grupo según dato de frontur en el mes de [??:??/10/??:??.??:??] [??:??/9/??:??.??:??] y [??:??/11/??:??.??:??] en gran_canaria haber crecer notablemente en parte debido_a eses incremento de ruta península-gran_canaria que no_sólo usar el cliente peninsular aclarar moreno finalmente desvelar que en este aspecto el número total a falta de el dato de [??:??/12/??:??.??:??] rozar el 3000000 de turista en gran_canaria en 2009 en 2008 3,4 millón como sumar de ese 3 componente",
        "lemmatized_text_reduced": "manifestar consejero turismo comercio_exterior innovación_tecnológica roberto_moreno rueda prensa recordar cumplir previsión gran_canaria recibir turista peninsular contabilizar haber ser moderadamente optimista saber turismo peninsular tener pico año agosto-septiembre mes caer semana santo creer poder esperar turista peninsular largo gran_canaria afirmar presidente patronato_de_turismo isla sentido recordar invierno haber aumentar notablemente plaza avión península gran_canaria trayecto contar vuelo semana comparar invierno anterior consejero insular turismo señalar mercado turístico haber seguir tónica baja resto mercado turístico decrecimiento situar isla torno turista haber convertir 2 mercado importancia nacionalidad isla fuerte bajada mercado inglés irlandés pasar año agregar moreno destacar gran_canaria tener mayor índice fidelidad turismo peninsular canarias descenso turismo peninsular conjunto archipiélago haber ser gran_canaria haber quedar descenso ser mercado importante gasto diario destino turista peninsular ser alto comparar nacionalidad gran_canaria comparar conjunto canarias ser alto istac gasto diario medio turista peninsular canarias estar orden gran_canaria estar orden decir consejero turismo desvelar zona península vender gran_canaria destino ser franja mediterráneo cataluña comunidad_valenciana murcia andalucía incremento turista extranjero viajar vía península el presidente patronato_de_turismo_de_gran_canaria subrayar contabilidad turista tener componente turista extranjero venir vuelo directo turista peninsular turista extranjero venir península último grupo dato frontur mes gran_canaria haber crecer notablemente parte eses incremento ruta península-gran_canaria usar cliente peninsular aclarar moreno finalmente desvelar aspecto número total falta dato rozar turista gran_canaria millón sumar componente",
        "persons": [
            "Comercio_Exterior",
            "Innovación_Tecnológica",
            "Roberto_Moreno",
            "Gran_Canaria",
            "El",
            "Moreno"
        ],
        "locations": [
            "Gran_Canaria",
            "Península",
            "Gran_Canaria",
            "Canarias",
            "Gran_Canaria",
            "Canarias",
            "Canarias",
            "Gran_Canaria",
            "Península",
            "Cataluña",
            "Comunidad_Valenciana",
            "Murcia",
            "Andalucía",
            "Península",
            "Frontur",
            "Gran_Canaria",
            "Gran_Canaria"
        ],
        "organizations": [
            "Patronato_de_Turismo",
            "Gran_Canaria",
            "Gran_Canaria",
            "Istac",
            "Gran_Canaria",
            "Patronato_de_Turismo_de_Gran_Canaria"
        ],
        "others": [
            "Turismo",
            "Turismo",
            "Turismo",
            "Península-Gran_Canaria"
        ],
        "dates": [
            "[??:??/12/??:??.??:??]",
            "[??:??/??/2010:??.??:??]",
            "[??:??/1/??:??.??:??]",
            "[??:??/11/13:??.??:??]",
            "[??:??/11/??:??.??:??]",
            "[??:??/1/??:??.??:??]",
            "[??:??/11/??:??.??:??]",
            "[??:??/10/??:??.??:??]",
            "[??:??/9/??:??.??:??]",
            "[??:??/11/??:??.??:??]",
            "[??:??/12/??:??.??:??]"
        ],
        "numbers": [
            "100",
            "2009",
            "3",
            "600",
            "37",
            "100",
            "500000",
            "21",
            "100",
            "13",
            "100",
            "$_ECU:48",
            "$_ECU:58",
            "3",
            "3000000",
            "2009",
            "2008",
            "3,4",
            "3"
        ]
    }
}
