{
    "province": "LAS PALMAS",
    "date": "2010-05-21T00:00:00",
    "url": "https://www.20minutos.es/noticia/713765/0/",
    "title": {
        "raw_text": "La llegada de turistas internacionales cae en Canarias un 15,3% en abril a causa de la nube volcánica",
        "lemmatized_text": "el llegada de turista internacional caer en canarias uno 15,3/100 en [??:??/4/??:??.??:??] a_causa_de el nube volcánico",
        "lemmatized_text_reduced": "llegada turista internacional caer canarias nube volcánico",
        "persons": [],
        "locations": [
            "Canarias"
        ],
        "organizations": [],
        "others": [],
        "dates": [
            "[??:??/4/??:??.??:??]"
        ],
        "numbers": [
            "15,3/100"
        ]
    },
    "lead": {
        "raw_text": "En España la entrada de visitantes internacionales se redujo un 13,3% el pasado mes de abril",
        "lemmatized_text": "en españa el entrada de visitante internacional se reducir uno 13,3/100 el [??:??/4/??:??.??:??]",
        "lemmatized_text_reduced": "españa entrada visitante internacional reducir",
        "persons": [],
        "locations": [
            "España"
        ],
        "organizations": [],
        "others": [],
        "dates": [
            "[??:??/4/??:??.??:??]"
        ],
        "numbers": [
            "13,3/100"
        ]
    },
    "body": {
        "raw_text": "La llegada de turistas internacionales cayó en Canarias un 15,3 por ciento en abril, y con respecto al mismo mes del pasado año, en esta ocasión la reducción se ha debido a los efectos que la nube volcánica de Islandia ha provocado en el espacio aéreo, así como por la dependencia de las islas al transporte aéreo. En el conjunto nacional, fueron un total de 3,9 millones los turistas internacionales que llegaron a España en abril y lo que supuso un descenso del 13,3 por ciento con respecto al mismo mes del ejercicio anterior, un retroceso también atribuido principalmente a los efectos del cierre del espacio aéreo por la nube volcánica islandesa, según las cifras proporcionadas hoy por la encuesta de Movimientos Turísticos en fronteras (Frontur), elaborada por el Ministerio de Industria, Turismo y Comercio. \"Este resultado ha estado fuertemente condicionado por la nube volcánica que ha invadido el espacio aéreo internacional y la consiguiente cancelación de vuelos, que en caso de España tuvo una duración de siete días\", señala la encuesta. Con respecto al acumulado de los cuatro primeros meses del año, llegaron a España un total de 12,7 millones de turistas, lo que representa un retroceso del 4,3 por ciento. Según especifica, las llegadas desde Reino Unido y Alemania han sido las más afectadas por las cenizas generadas por el volcán islandés, debido al cierre del espacio aéreo de estos países. Reino Unido resultó ser el mercado emisor con más afectación con un total de 800.000 llegadas en abril, lo que supone una caída interanual del 27,7 por ciento, mientras que Alemania registró una caída del 21,4 por ciento, hasta 631.855 visitantes. Francia, que se situó como segundo mercado en llegadas, registró un retroceso más moderado del 2 por ciento, hasta 733.362 turistas, mientras que Italia experimentó un descenso del 4,4 por ciento hasta 292.092 visitantes. No obstante, se registró \"un aumento reseñable\" de la llegada de turistas procedentes de Estados Unidos, que no se vio afectado por los problemas derivados de la ceniza. Concretamente, las llegadas aumentaron un 4,8 por ciento, hasta 98.013 visitantes. Con respecto a los destinos, Cataluña, con 1,1 millones de llegadas, sigue siendo el destino más visitado por los turistas internacionales y registró un retroceso moderado del 7,2 por ciento gracias a el menor peso de las llegadas a la región por vía aérea. Mayores descensos en canarias y baleares Por el contrario, Islas Canarias e Islas Baleares registraron los descensos más acusados, del 15,3 por ciento y del 11,9 por ciento, respectivamente, por su mayor dependencia del transporte aéreo. Andalucía y la Comunidad Valenciana presentaron descensos del 12,3 por ciento y del 19,2 por ciento debido al menor flujo de turistas procedentes de Reino Unido. En cuanto a las vías de acceso, los aeropuertos registraron la caída más pronunciada en el volumen de turistas internacionales recibidos como consecuencia del cierre del espacio aéreo en abril, con un total de 2,8 millones de llegadas, lo que supone un descenso del 17,1 por ciento. Por carretera, las llegadas descendieron un 1,6 por ciento hasta 955.370 turistas debido al efecto Semana Santa ya que en 2009 cayó toda la semana en el mes de abril mientras que en el presente ejercicio sólo a partir del jueves Santo, que cayó el 1 de abril. Con respecto al tipo de alojamiento, tanto los hoteles como el alojamiento no hotelero presentaron descensos del 10,2 por ciento y del 16,6 por ciento, respectivamente. En cuanto a la forma de organizar el viaje, retrocedieron más las llegada de turistas que no recurrieron al paquete turístico, con un 13,9 por ciento frente a los que sí contrataron, con una caída del 9,7 por ciento.",
        "lemmatized_text": "el llegada de turista internacional caer en canarias uno 15,3 por 100 en [??:??/4/??:??.??:??] y con respecto a el mismo mes de el pasar año en este ocasión el reducción se haber debido_a el efecto que el nube volcánico de islandia haber provocar en el espacio aéreo así_como por el dependencia de el isla a el transporte aéreo en el conjunto nacional ser uno total de 3,9 millón el turista internacional que llegar a españa en [??:??/4/??:??.??:??] y el que suponer uno descenso de el 13,3 por 100 con respecto a el mismo mes de el ejercicio anterior uno retroceso también atribuir principalmente a el efecto de el cierre de el espacio aéreo por el nube volcánico islandés según el cifra proporcionar hoy por el encuesta de movimientos_turísticos en frontera frontur elaborar por el ministerio_de_industria turismo y comercio este resultado haber estar fuertemente condicionar por el nube volcánico que haber invadir el espacio aéreo internacional y el consiguiente cancelación de vuelo que en_caso_de españa tener uno duración de TM_d:7 señalar el encuesta con respecto a el acumular de el 4 1 mes de el año llegar a españa uno total de 12,7 millón de turista el que representar uno retroceso de el 4,3 por 100 según especificar el llegada desde reino_unido y alemania haber ser el más afectar por el ceniza generar por el volcán islandés deber a el cierre de el espacio aéreo de este país reino_unido resultar ser el mercado emisor con más afectación con uno total de 800 llegada en [??:??/4/??:??.??:??] el que suponer uno caída interanual de el 27,7 por 100 mientras_que alemania registrar uno caída de el 21,4 por 100 hasta 631.855 visitante francia que se situar como 2 mercado en llegada registrar uno retroceso más moderar de el 2 por 100 hasta 733.362 turista mientras_que italia experimentar uno descenso de el 4,4 por 100 hasta 292.092 visitante no_obstante se registrar uno aumento reseñable de el llegada de turista procedente de estados_unidos que no se ver afectar por el problema derivar de el ceniza concretamente el llegada aumentar uno 4,8 por 100 hasta 98.013 visitante con_respecto_a el destino cataluña con 1,1 millón de llegada seguir ser el destino más visitar por el turista internacional y registrar uno retroceso moderar de el 7,2 por 100 gracias_a el menor peso de el llegada a el región por vía aéreo mayor descenso en canario y balear por_el_contrario islas_canarias y islas_baleares registrar el descenso más acusar de el 15,3 por 100 y de el 11,9 por 100 respectivamente por su mayor dependencia de el transporte aéreo andalucía y el comunidad_valenciana presentar descenso de el 12,3 por 100 y de el 19,2 por 100 deber a el menor flujo de turista procedente de reino_unido en_cuanto_a el vía de acceso el aeropuerto registrar el caída más pronunciar en el volumen de turista internacional recibir como consecuencia de el cierre de el espacio aéreo en [??:??/4/??:??.??:??] con uno total de 2,8 millón de llegada el que suponer uno descenso de el 17,1 por 100 por carretera el llegada descender uno 1,6 por 100 hasta 955.37 turista deber a el efecto semana_santa ya_que en 2009 caer todo el semana en el [??:??/4/??:??.??:??] mientras_que en el presente ejercicio sólo a partir de el [J:??/??/??:??.??:??] santo que caer el [??:1/4/??:??.??:??] con respecto a el tipo de alojamiento tanto el hotel como el alojamiento no hotelero presentar descenso de el 10,2 por 100 y de el 16,6 por 100 respectivamente en_cuanto_a el forma de organizar el viaje retroceder más el llegada de turista que no recurrir a el paquete turístico con uno 13,9 por 100 frente_a el que sí contratar con uno caída de el 9,7 por 100",
        "lemmatized_text_reduced": "llegada turista internacional caer canarias respecto mismo mes pasar año ocasión reducción haber efecto nube volcánico islandia haber provocar espacio aéreo dependencia isla transporte aéreo conjunto nacional ser total millón turista internacional llegar españa suponer descenso respecto mismo mes ejercicio anterior retroceso atribuir principalmente efecto cierre espacio aéreo nube volcánico islandés cifra proporcionar encuesta movimientos_turísticos frontera frontur elaborar ministerio_de_industria turismo comercio resultado haber estar fuertemente condicionar nube volcánico haber invadir espacio aéreo internacional consiguiente cancelación vuelo españa tener duración señalar encuesta respecto acumular 1 mes año llegar españa total millón turista representar retroceso especificar llegada reino_unido alemania haber ser afectar ceniza generar volcán islandés deber cierre espacio aéreo país reino_unido resultar ser mercado emisor afectación total llegada suponer caída interanual alemania registrar caída visitante francia situar 2 mercado llegada registrar retroceso moderar turista italia experimentar descenso visitante registrar aumento reseñable llegada turista procedente estados_unidos ver afectar problema derivar ceniza concretamente llegada aumentar visitante destino cataluña millón llegada seguir ser destino visitar turista internacional registrar retroceso moderar menor peso llegada región vía aéreo mayor descenso canario balear por_el_contrario islas_canarias islas_baleares registrar descenso acusar respectivamente mayor dependencia transporte aéreo andalucía comunidad_valenciana presentar descenso deber menor flujo turista procedente reino_unido vía acceso aeropuerto registrar caída pronunciar volumen turista internacional recibir consecuencia cierre espacio aéreo total millón llegada suponer descenso carretera llegada descender turista deber efecto semana_santa caer semana presente ejercicio partir santo caer respecto tipo alojamiento hotel alojamiento hotelero presentar descenso respectivamente forma organizar viaje retroceder llegada turista recurrir paquete turístico contratar caída",
        "persons": [
            "España",
            "Por_el_contrario",
            "Islas_Canarias",
            "Islas_Baleares",
            "Semana_Santa"
        ],
        "locations": [
            "Canarias",
            "Islandia",
            "España",
            "Movimientos_Turísticos",
            "Frontur",
            "España",
            "Reino_Unido",
            "Alemania",
            "Reino_Unido",
            "Estados_Unidos",
            "Cataluña",
            "Andalucía",
            "Reino_Unido"
        ],
        "organizations": [
            "Ministerio_de_Industria",
            "Turismo",
            "Comercio",
            "Alemania",
            "Francia",
            "Italia",
            "Comunidad_Valenciana"
        ],
        "others": [
            "Santo"
        ],
        "dates": [
            "[??:??/4/??:??.??:??]",
            "[??:??/4/??:??.??:??]",
            "[??:??/4/??:??.??:??]",
            "[??:??/4/??:??.??:??]",
            "[??:??/4/??:??.??:??]",
            "[J:??/??/??:??.??:??]",
            "[??:1/4/??:??.??:??]"
        ],
        "numbers": [
            "15,3",
            "100",
            "3,9",
            "13,3",
            "100",
            "TM_d:7",
            "4",
            "12,7",
            "4,3",
            "100",
            "800",
            "27,7",
            "100",
            "21,4",
            "100",
            "631.855",
            "2",
            "100",
            "733.362",
            "4,4",
            "100",
            "292.092",
            "4,8",
            "100",
            "98.013",
            "1,1",
            "7,2",
            "100",
            "15,3",
            "100",
            "11,9",
            "100",
            "12,3",
            "100",
            "19,2",
            "100",
            "2,8",
            "17,1",
            "100",
            "1,6",
            "100",
            "955.37",
            "2009",
            "10,2",
            "100",
            "16,6",
            "100",
            "13,9",
            "100",
            "9,7",
            "100"
        ]
    }
}
