{
    "province": "LAS PALMAS",
    "date": "2010-02-17T00:00:00",
    "url": "https://www.20minutos.es/noticia/631750/0/",
    "title": {
        "raw_text": "Casa África acoge un encuentro informal entre europeos y africanos para avanzar en una estrategia conjunta",
        "lemmatized_text": "casa_áfrica acoger uno encuentro informal entre europeo y africano para avanzar en uno estrategia conjunto",
        "lemmatized_text_reduced": "casa_áfrica acoger encuentro informal europeo africano avanzar estrategia conjunto",
        "persons": [],
        "locations": [
            "Casa_África"
        ],
        "organizations": [],
        "others": [],
        "dates": [],
        "numbers": []
    },
    "lead": {
        "raw_text": "Casa África, en el marco de la presidencia española en la Unión Europea (UE), ha acogido una reunión informal entre expertos africanos y europeos que ha permitido avanzar en la preparación del Plan de Acción para la estrategia conjunta que pretenden desarrollar en los próximos años la UE con los países africanos.",
        "lemmatized_text": "casa_áfrica en el marco de el presidencia español en el unión_europea ue haber acoger uno reunión informal entre experto africano y europeo que haber permitir avanzar en el preparación de el plan_de_acción para el estrategia conjunto que pretender desarrollar en el próximo año el ue con el país africano",
        "lemmatized_text_reduced": "casa_áfrica marco presidencia español unión_europea ue haber acoger reunión informal experto africano europeo haber permitir avanzar preparación plan_de_acción estrategia conjunto pretender desarrollar próximo año ue país africano",
        "persons": [],
        "locations": [
            "Casa_África"
        ],
        "organizations": [
            "Unión_Europea",
            "UE",
            "UE"
        ],
        "others": [
            "Plan_de_Acción"
        ],
        "dates": [],
        "numbers": []
    },
    "body": {
        "raw_text": "Además, a finales de 2010, está previsto que Tripoli (Libia) acoja la III Cumbre UE-África que reunirá a los jefes de Estado y de Gobierno de ambos continentes para evaluar y renovar la estrategia conjunta lanzada hace tres años en Lisboa y adoptar el nuevo Plan de Acción para el periodo 2011-2013, según informó Casa África en nota de prensa. Por ello, con el objetivo de diseñar el contenido de lo que los países tratarán en esta Cumbre, los especialistas en las relaciones Europa-África de diversos gobiernos de ambos continentes e instituciones comunitarias han debatido a puerta cerrada en Las Palmas de Gran Canaria, donde se encuentra la sede de Casa África. Así, en dicho encuentro participaron 26 representantes que han evaluado el plan vigente, además de debatir sobre las posibilidades del nuevo acuerdo que deberá aprobarse en Libia. Respecto al I Plan de Acción 2008-2010, ya han pasado tres años, y con él África y la UE han constituido un \"partenariado, más allá de la habitual relación donante-receptor\". De ahí que con la citada reunión se pretenda \"reforzar y hacer más efectivos\" los ocho partenariados existentes en la actualidad, tales como paz y seguridad; buena gobernanza y derechos humanos; comercio, integración regional e infraestructura; objetivos de desarrollo del Milenio; energía; cambio climático; migraciones, movilidad y desarrollo; y ciencia, información y nuevas tecnologías. En cuanto a las personas que asistieron a dicha reunión informal fueron representantes de la Comisión Europea, así como procedentes de España, Bélgica, Austria, Alemania, Reino Unido y Suecia; mientras que por la parte africana asistieron representantes de la Unión Africana (UA y de la Comunidad Económica de Estados del África Occidental (CEDEAO)), de Egipto, Etiopía, Kenia, Mozambique, Nigeria, Senegal y Sudáfrica.",
        "lemmatized_text": "además a final de 2010 estar prever que tripoli libio acoger el iii_cumbre_ue-áfrica que reunir a el jefe de estado y de gobierno de ambos continente para evaluar y renovar el estrategia conjunto lanzar hacer 3 año en lisboa y adoptar el nuevo plan_de_acción para el periodo 2011-2013 según informar casa_áfrica en nota de prensa por ello con el objetivo de diseñar el contenido de el que el país tratar en este cumbre el especialista en el relación europa-áfrica de diverso gobierno de ambos continente y institución comunitario haber debatir a_puerta_cerrada en las_palmas_de_gran_canaria donde se encontrar el sede de casa_áfrica así en decir encuentro participar 26 representante que haber evaluar el plan vigente además_de debatir sobre el posibilidad de el nuevo acuerdo que deber aprobar se en libia respecto a el i_plan_de_acción 2008-2010 ya haber pasar 3 año y con él áfrica y el ue haber constituir uno partenariado más_allá_de el habitual relación donante-receptor de ahí que con el citar reunión se pretender reforzar y hacer más efectivo el 8 partenariados existente en el actualidad tal como paz y seguridad bueno gobernanza y derecho humano comercio integración regional y infraestructura objetivo de desarrollo de el milenio energía cambio climático migración movilidad y desarrollo y ciencia información y nuevo tecnología en_cuanto_a el persona que asistir a decir reunión informal ser representante de el comisión_europea así_como procedente de españa bélgica austria alemania reino_unido y suecia mientras_que por el parte africano asistir representante de el unión_africana ua y de el comunidad_económica_de_estados_del_áfrica_occidental cedeao de egipto etiopía kenia mozambique nigeria senegal y sudáfrica",
        "lemmatized_text_reduced": "final estar prever tripoli libio acoger iii_cumbre_ue-áfrica reunir jefe estado gobierno continente evaluar renovar estrategia conjunto lanzar hacer año lisboa adoptar nuevo plan_de_acción periodo informar casa_áfrica nota prensa objetivo diseñar contenido país tratar cumbre especialista relación europa-áfrica gobierno continente institución comunitario haber debatir las_palmas_de_gran_canaria encontrar sede casa_áfrica decir encuentro participar representante haber evaluar plan vigente debatir posibilidad nuevo acuerdo deber aprobar libia respecto i_plan_de_acción haber pasar año áfrica ue haber constituir partenariado habitual relación donante-receptor citar reunión pretender reforzar hacer efectivo partenariados existente actualidad paz seguridad bueno gobernanza derecho humano comercio integración regional infraestructura objetivo desarrollo milenio energía cambio climático migración movilidad desarrollo ciencia información nuevo tecnología persona asistir decir reunión informal ser representante comisión_europea procedente españa bélgica austria alemania reino_unido suecia parte africano asistir representante unión_africana ua comunidad_económica_de_estados_del_áfrica_occidental cedeao egipto etiopía kenia mozambique nigeria senegal sudáfrica",
        "persons": [
            "Tripoli"
        ],
        "locations": [
            "Lisboa",
            "Casa_África",
            "Las_Palmas_de_Gran_Canaria",
            "Casa_África",
            "Libia",
            "España",
            "Bélgica",
            "Reino_Unido",
            "Suecia",
            "Egipto",
            "Etiopía",
            "Kenia",
            "Mozambique",
            "Nigeria",
            "Senegal",
            "Sudáfrica"
        ],
        "organizations": [
            "Estado",
            "Gobierno",
            "África",
            "UE",
            "Milenio",
            "Comisión_Europea",
            "Austria",
            "Alemania",
            "Unión_Africana",
            "UA",
            "Comunidad_Económica_de_Estados_del_África_Occidental",
            "CEDEAO"
        ],
        "others": [
            "III_Cumbre_UE-África",
            "Plan_de_Acción",
            "Cumbre",
            "Europa-África",
            "I_Plan_de_Acción"
        ],
        "dates": [],
        "numbers": [
            "2010",
            "3",
            "2011-2013",
            "26",
            "2008-2010",
            "3",
            "8"
        ]
    }
}
