{
    "province": "LAS PALMAS",
    "date": "2011-01-04T00:00:00",
    "url": "https://www.20minutos.es/noticia/919715/0/",
    "title": {
        "raw_text": "El paro subió en Canarias en 2010 en 5.837 personas, situándose en 254.620 desempleados",
        "lemmatized_text": "el paro subir en canarias en 2010 en 5.837 persona situar se en 254.62 desempleado",
        "lemmatized_text_reduced": "paro subir canarias persona situar desempleado",
        "persons": [],
        "locations": [
            "Canarias"
        ],
        "organizations": [],
        "others": [],
        "dates": [],
        "numbers": [
            "2010",
            "5.837",
            "254.62"
        ]
    },
    "lead": {
        "raw_text": "El número de parados registrados en las oficinas de los servicios públicos de empleo en la Comunidad Autónoma de Canarias subió en 5.837 personas durante el pasado año 2010 (+2,35%) y la cifra total de parados quedó establecida en 254.620 personas.",
        "lemmatized_text": "el número de parado registrar en el oficina de el servicio público de empleo en el comunidad_autónoma_de_canarias subir en 5.837 persona durante el [??:??/??/2010:??.??:??] +2,35/100 y el cifra total de parado quedar establecer en 254.62 persona",
        "lemmatized_text_reduced": "número parado registrar oficina servicio público empleo comunidad_autónoma_de_canarias subir persona cifra total parado quedar establecer persona",
        "persons": [],
        "locations": [],
        "organizations": [
            "Comunidad_Autónoma_de_Canarias"
        ],
        "others": [],
        "dates": [
            "[??:??/??/2010:??.??:??]"
        ],
        "numbers": [
            "5.837",
            "+2,35/100",
            "254.62"
        ]
    },
    "body": {
        "raw_text": "El número de parados registrados en las oficinas de los servicios públicos de empleo en la Comunidad Autónoma de Canarias subió en 5.837 personas durante el pasado año 2010 (+2,35%) y la cifra total de parados quedó establecida en 254.620 personas. Este ascenso se produjo tras registrarse en el último mes del año un descenso del paro en 2.073 personas respecto al mes anterior (-0,81%), según datos ofrecidos este martes por el Ministerio de Trabajo e Inmigración. Por provincias, de los 2.073 parados menos en las islas durante diciembre, 784 fueron contratados en Las Palmas y 1.289 en Santa Cruz de Tenerife, mientras que la provincia oriental cerró el año con 2.425 parados más que diciembre de 2010 (137.880 personas) y la tinerfeña lo hizo con 3.412 más (116.740). Del total de desempleados de Canarias, 127.713 son hombres y 126.907mujeres. Además, 21.014 son menores de 25 años, de los que 11.429 son hombres y 9.585. Entre los desempleados mayores de 25 años, un total de 233.606, 116.284 son hombres y 117.322 mujeres. El sector que ha registrado un mayor descenso mensual en el archipiélago fue el sector servicios, con una bajada de 3.454 personas; mientras que industria bajó en 3 individuos y construcción (+517), agricultura (+150) y las personas sin empleo anterior (+717) aumentaron durante el mes de diciembre. Respecto a los contratos, Canarias registró un total de 5.584 contratos menos durante el pasado mes (-3.757 en Las Palmas y -1.827 en Santa Cruz de Tenerife), cerrando el año con 46.841 contratos, 3.143 más que el año anterior. Conjunto nacional A nivel nacional, el número de parados registrados en las oficinas de los servicios públicos de empleo (antiguo Inem) se ha situado al finalizar diciembre de 2010 en 4,1 millones de personas, tras subir en 176.470 desempleados en el conjunto de 2010, con un aumento porcentual del 4,5% respecto a 2009, informó hoy el Ministerio de Trabajo e Inmigración. En concreto, el volumen total de parados ha alcanzado a cierre del pasado año la cifra de 4.100.073 desempleados, su nivel anual más alto en toda la serie histórica comparable, que arranca en 1996. La subida del desempleo en 2010 ha sido muy inferior a las experimentadas en 2008 y 2009, años en los que las listas de las oficinas públicas de empleo sumaron 999.416 y 794.640 parados más, respectivamente. La de 2010 ha sido, de este modo, la tercera mayor subida anual del desempleo de toda la serie comparable, pero la menor desde que comenzó la crisis. La secretaria de Estado de Empleo, Mari Luz Rodríguez, ha destacado en un comunicado que, aunque el paro ha aumentado en 2010, su crecimiento ha sido el más bajo de los últimos tres años. No obstante, Rodríguez ha reconocido que no se puede hacer una \"lectura complaciente\" de los datos, pues sigue habiendo más de 4 millones de personas en paro por las que seguir trabajando. A esa cifra de más de 4,1 millones de desempleados con la que se ha cerrado el año se ha llegado después de que el paro bajara en diciembre en 10.221 personas, el 0,25% respecto al mes anterior. Esta caída pone fin a cuatro meses consecutivos de crecimiento del desempleo y supone, además, el mejor dato en un mes de diciembre de la última década. Sube más el paro entre las mujeres El paro ha subido en 2010 en ambos sexos, aunque más entre las mujeres, con 135.818 nuevas paradas (+7,1%), frente a un incremento del desempleo masculino de 40.652 hombres (+2%), situándose el total de mujeres en paro en 2.046.885 y el de varones, en 2.053.188. En términos intermensuales (diciembre sobre noviembre), el paro femenino ha bajado en 35.844 mujeres (-1,7%), mientras que el de varones se ha incrementado en 25.623 (+1,2%). Los servicios y el colectivo sin empleo anterior , Los peor parados Por sectores, el paro ha bajado en 2010 en la industria, con 17.164 desempleados menos (-3,3%), y en la construcción, que ha registrado 28.657 parados menos (-3,6%), pero ha subido en el resto, principalmente en los servicios, que han sumado 130.874 parados más (+5,8%). No obstante, los mayores repuntes porcentuales se los han anotado el colectivo sin empleo anterior, que ha registrado 70.721 parados más en el año (+24,7%), y la agricultura, con 20.696 nuevos desempleados (+19,5%).",
        "lemmatized_text": "el número de parado registrar en el oficina de el servicio público de empleo en el comunidad_autónoma_de_canarias subir en 5.837 persona durante el [??:??/??/2010:??.??:??] +2,35/100 y el cifra total de parado quedar establecer en 254.62 persona este ascenso se producir tras registrar se en el último mes de el año uno descenso de el paro en 2.073 persona respecto a el mes anterior -0,81/100 según dato ofrecer este [M:??/??/??:??.??:??] por el ministerio_de_trabajo y inmigración por provincia de el 2.073 parado menos en el isla durante [??:??/12/??:??.??:??] 784 ser contratar en las_palmas y 1.289 en santa_cruz_de_tenerife mientras_que el provincia oriental cerrar el año con 2.425 parado más que [??:??/12/2010:??.??:??] 137.88 persona y el tinerfeño lo hacer con 3.412 más 116.74 de el total de desempleado de canarias 127.713 ser hombre y 126.907mujeres además 21.014 ser menor de 25 año de el que 11.429 ser hombre y 9.585 entre el desempleado mayor de 25 año uno total de 233.606 116.284 ser hombre y 117.322 mujer el sector que haber registrar uno mayor descenso mensual en el archipiélago ser el sector servicio con uno bajada de 3.454 persona mientras_que industria bajar en 3 individuo y construcción +517 agricultura +150 y el persona sin empleo anterior +717 aumentar durante el [??:??/12/??:??.??:??] respecto_a el contrato canarias registrar uno total de 5.584 contrato menos durante el pasar mes -3.757 en las_palmas y -1.827 en santa_cruz_de_tenerife cerrar el año con 46.841 contrato 3.143 más que el año anterior conjunto nacional a nivel nacional el número de parado registrar en el oficina de el servicio público de empleo antiguo inem se haber situar a el finalizar [??:??/12/2010:??.??:??] en 4,1 millón de persona tras subir en 176.47 desempleado en el conjunto de 2010 con uno aumento porcentual de el 4,5/100 respecto_a 2009 informar hoy el ministerio_de_trabajo y inmigración en concreto el volumen total de parado haber alcanzar a cierre de el pasar año el cifra de 4.100.073 desempleado su nivel anual más alto en todo el serie histórico comparable que arrancar en 1996 el subida de el desempleo en 2010 haber ser muy inferior a el experimentar en 2008 y 2009 año en el que el lista de el oficina público de empleo sumar 999.416 y 794.64 parado más respectivamente el de 2010 haber ser de este modo el 3 mayor subida anual de el desempleo de todo el serie comparable pero el menor desde que comenzar el crisis el secretario de estado_de_empleo mari_luz_rodríguez haber destacar en uno comunicado que aunque el paro haber aumentar en 2010 su crecimiento haber ser el más bajo de el último 3 año no_obstante rodríguez haber reconocer que no se poder hacer uno lectura complaciente de el dato pues seguir haber más de 4000000 de persona en paro por el que seguir trabajar a ese cifra de más de 4,1 millón de desempleado con el que se haber cerrar el año se haber llegar después_de que el paro bajar en [??:??/12/??:??.??:??] en 10.221 persona el 0,25/100 respecto a el mes anterior este caída poner fin a 4 mes consecutivo de crecimiento de el desempleo y suponer además el mejor dato en uno [??:??/12/??:??.??:??] de el último década subir más el paro entre el mujer el paro haber subir en 2010 en ambos sexo aunque más entre el mujer con 135.818 nuevo parada +7,1/100 frente_a uno incremento de el desempleo masculino de 40.652 hombre +2/100 situar se el total de mujer en paro en 2.046.885 y el de varón en 2.053.188 en término intermensual [??:??/12/??:??.??:??] sobre [??:??/11/??:??.??:??] el paro femenino haber bajar en 35.844 mujer -1,7/100 mientras_que el de varón se haber incrementar en 25.623 +1,2/100 el servicio y el colectivo sin empleo anterior los peor parado por sector el paro haber bajar en 2010 en el industria con 17.164 desempleado menos -3,3/100 y en el construcción que haber registrar 28.657 parado menos -3,6/100 pero haber subir en el resto principalmente en el servicio que haber sumar 130.874 parado más +5,8/100 no_obstante el mayor repunte porcentual se lo haber anotar el colectivo sin empleo anterior que haber registrar 70.721 parado más en el año +24,7/100 y el agricultura con 20.696 nuevo desempleado +19,5/100",
        "lemmatized_text_reduced": "número parado registrar oficina servicio público empleo comunidad_autónoma_de_canarias subir persona cifra total parado quedar establecer persona ascenso producir registrar último mes año descenso paro persona respecto mes anterior dato ofrecer ministerio_de_trabajo inmigración provincia parado isla ser contratar las_palmas santa_cruz_de_tenerife provincia oriental cerrar año parado persona tinerfeño hacer total desempleado canarias ser hombre ser menor año ser hombre desempleado mayor año total ser hombre mujer sector haber registrar mayor descenso mensual archipiélago ser sector servicio bajada persona industria bajar individuo construcción agricultura persona empleo anterior aumentar contrato canarias registrar total contrato pasar mes las_palmas santa_cruz_de_tenerife cerrar año contrato año anterior conjunto nacional a nivel nacional número parado registrar oficina servicio público empleo antiguo inem haber situar finalizar millón persona subir desempleado conjunto aumento porcentual informar ministerio_de_trabajo inmigración concreto volumen total parado haber alcanzar cierre pasar año cifra desempleado nivel anual alto serie histórico comparable arrancar subida desempleo haber ser inferior experimentar año lista oficina público empleo sumar parado respectivamente haber ser modo 3 mayor subida anual desempleo serie comparable menor comenzar crisis secretario estado_de_empleo mari_luz_rodríguez haber destacar comunicado paro haber aumentar crecimiento haber ser bajo último año rodríguez haber reconocer poder hacer lectura complaciente dato seguir haber persona paro seguir trabajar cifra millón desempleado haber cerrar año haber llegar paro bajar persona respecto mes anterior caída poner fin mes consecutivo crecimiento desempleo suponer mejor dato último década subir paro mujer el paro haber subir sexo mujer nuevo parada incremento desempleo masculino hombre situar total mujer paro varón término intermensual paro femenino haber bajar mujer varón haber incrementar servicio colectivo empleo anterior los peor parado por sector paro haber bajar industria desempleado construcción haber registrar parado haber subir resto principalmente servicio haber sumar parado mayor repunte porcentual haber anotar colectivo empleo anterior haber registrar parado año agricultura nuevo desempleado",
        "persons": [
            "Mari_Luz_Rodríguez",
            "Rodríguez",
            "Los"
        ],
        "locations": [
            "Santa_Cruz_de_Tenerife",
            "Canarias",
            "Canarias",
            "Santa_Cruz_de_Tenerife"
        ],
        "organizations": [
            "Comunidad_Autónoma_de_Canarias",
            "Ministerio_de_Trabajo",
            "Inmigración",
            "Las_Palmas",
            "Las_Palmas",
            "Inem",
            "Ministerio_de_Trabajo",
            "Inmigración",
            "Estado_de_Empleo",
            "El",
            "Por"
        ],
        "others": [
            "A"
        ],
        "dates": [
            "[??:??/??/2010:??.??:??]",
            "[M:??/??/??:??.??:??]",
            "[??:??/12/??:??.??:??]",
            "[??:??/12/2010:??.??:??]",
            "[??:??/12/??:??.??:??]",
            "[??:??/12/2010:??.??:??]",
            "[??:??/12/??:??.??:??]",
            "[??:??/12/??:??.??:??]",
            "[??:??/12/??:??.??:??]",
            "[??:??/11/??:??.??:??]"
        ],
        "numbers": [
            "5.837",
            "+2,35/100",
            "254.62",
            "2.073",
            "-0,81/100",
            "2.073",
            "784",
            "1.289",
            "2.425",
            "137.88",
            "3.412",
            "116.74",
            "127.713",
            "126.907mujeres",
            "21.014",
            "25",
            "11.429",
            "9.585",
            "25",
            "233.606",
            "116.284",
            "117.322",
            "3.454",
            "3",
            "+517",
            "+150",
            "+717",
            "5.584",
            "-3.757",
            "-1.827",
            "46.841",
            "3.143",
            "4,1",
            "176.47",
            "2010",
            "4,5/100",
            "2009",
            "4.100.073",
            "1996",
            "2010",
            "2008",
            "2009",
            "999.416",
            "794.64",
            "2010",
            "2010",
            "3",
            "4000000",
            "4,1",
            "10.221",
            "0,25/100",
            "4",
            "2010",
            "135.818",
            "+7,1/100",
            "40.652",
            "+2/100",
            "2.046.885",
            "2.053.188",
            "35.844",
            "-1,7/100",
            "25.623",
            "+1,2/100",
            "2010",
            "17.164",
            "-3,3/100",
            "28.657",
            "-3,6/100",
            "130.874",
            "+5,8/100",
            "70.721",
            "+24,7/100",
            "20.696",
            "+19,5/100"
        ]
    }
}
