{
    "province": "LAS PALMAS",
    "date": "2011-01-04T00:00:00",
    "url": "https://www.20minutos.es/noticia/920150/0/",
    "title": {
        "raw_text": "Rivero afirma que los datos del paro en Canarias \"afianzan el trabajo que se está haciendo\"",
        "lemmatized_text": "rivero afirmar que el dato de el paro en canarias afianzar el trabajo que se estar hacendar",
        "lemmatized_text_reduced": "rivero afirmar dato paro canarias afianzar trabajo estar hacendar",
        "persons": [
            "Rivero"
        ],
        "locations": [
            "Canarias"
        ],
        "organizations": [],
        "others": [],
        "dates": [],
        "numbers": []
    },
    "lead": {
        "raw_text": "El presidente del Gobierno de Canarias, Paulino Rivero, ha afirmado este martes que los datos del paro en la Comunidad Autónoma \"afianzan el trabajo que se está haciendo\" desde las instituciones de las islas, según manifestó durante unas declaraciones a los medios de comunicación.",
        "lemmatized_text": "el presidente de el gobierno_de_canarias paulino_rivero haber afirmar este [M:??/??/??:??.??:??] que el dato de el paro en el comunidad_autónoma afianzar el trabajo que se estar hacendar desde el institución de el isla según manifestar durante uno declaración a el medio de comunicación",
        "lemmatized_text_reduced": "presidente gobierno_de_canarias paulino_rivero haber afirmar dato paro comunidad_autónoma afianzar trabajo estar hacendar institución isla manifestar declaración medio comunicación",
        "persons": [
            "Paulino_Rivero"
        ],
        "locations": [],
        "organizations": [
            "Gobierno_de_Canarias",
            "Comunidad_Autónoma"
        ],
        "others": [],
        "dates": [
            "[M:??/??/??:??.??:??]"
        ],
        "numbers": []
    },
    "body": {
        "raw_text": "El presidente del Gobierno de Canarias, Paulino Rivero, ha afirmado este martes que los datos del paro en la Comunidad Autónoma \"afianzan el trabajo que se está haciendo\" desde las instituciones de las islas, según manifestó durante unas declaraciones a los medios de comunicación. \"Los datos conocidos esta mañana del paro confirman lo que ya avancé, que la tendencia a la reducción del paro de iba a mantener en diciembre en Canarias, lo que confirma la tendencia del último semestre\", dijo. Además, explicó que estos datos confirman también que el dato interanual sitúa a las islas entre las comunidades autónomas con mejor comportamiento en la tasa de desempleo. \"Estas cifras —agregó— afianzan el trabajo que se está haciendo\". Por su parte, el número de parados registrados en las oficinas de los servicios públicos de empleo en la Comunidad Autónoma de Canarias subió en 5.837 personas durante el pasado año 2010 (+2,35%) y la cifra total de parados quedó establecida en 254.620 personas. Este ascenso se produjo tras registrarse en el último mes del año un descenso del paro en 2.073 personas respecto al mes anterior (-0,81%). Por provincias, de los 2.073 parados menos en las islas durante diciembre, 784 fueron contratados en Las Palmas y 1.289 en Santa Cruz de Tenerife, mientras que la provincia oriental cerró el año con 2.425 parados más que diciembre de 2010 (137.880 personas) y la tinerfeña lo hizo con 3.412 más (116.740).",
        "lemmatized_text": "el presidente de el gobierno_de_canarias paulino_rivero haber afirmar este [M:??/??/??:??.??:??] que el dato de el paro en el comunidad_autónoma afianzar el trabajo que se estar hacendar desde el institución de el isla según manifestar durante uno declaración a el medio de comunicación el dato conocer este mañana de el paro confirmar el que ya avanzar que el tendencia a el reducción de el paro de ir a mantener en [??:??/12/??:??.??:??] en canarias el que confirmar el tendencia de el último semestre decir además explicar que este dato confirmar también que el dato interanual situar a el isla entre el comunidad autónomo con mejor comportamiento en el tasa de desempleo este cifra agregar afianzar el trabajo que se estar hacendar por su parte el número de parado registrar en el oficina de el servicio público de empleo en el comunidad_autónoma_de_canarias subir en 5.837 persona durante el [??:??/??/2010:??.??:??] +2,35/100 y el cifra total de parado quedar establecer en 254.62 persona este ascenso se producir tras registrar se en el último mes de el año uno descenso de el paro en 2.073 persona respecto a el mes anterior -0,81/100 por provincia de el 2.073 parado menos en el isla durante [??:??/12/??:??.??:??] 784 ser contratar en las_palmas y 1.289 en santa_cruz_de_tenerife mientras_que el provincia oriental cerrar el año con 2.425 parado más que [??:??/12/2010:??.??:??] 137.88 persona y el tinerfeño lo hacer con 3.412 más 116.74",
        "lemmatized_text_reduced": "presidente gobierno_de_canarias paulino_rivero haber afirmar dato paro comunidad_autónoma afianzar trabajo estar hacendar institución isla manifestar declaración medio comunicación dato conocer mañana paro confirmar avanzar tendencia reducción paro ir mantener canarias confirmar tendencia último semestre decir explicar dato confirmar dato interanual situar isla comunidad autónomo mejor comportamiento tasa desempleo cifra agregar afianzar trabajo estar hacendar parte número parado registrar oficina servicio público empleo comunidad_autónoma_de_canarias subir persona cifra total parado quedar establecer persona ascenso producir registrar último mes año descenso paro persona respecto mes anterior provincia parado isla ser contratar las_palmas santa_cruz_de_tenerife provincia oriental cerrar año parado persona tinerfeño hacer",
        "persons": [
            "Paulino_Rivero"
        ],
        "locations": [
            "Canarias",
            "Santa_Cruz_de_Tenerife"
        ],
        "organizations": [
            "Gobierno_de_Canarias",
            "Comunidad_Autónoma",
            "Comunidad_Autónoma_de_Canarias",
            "Las_Palmas"
        ],
        "others": [],
        "dates": [
            "[M:??/??/??:??.??:??]",
            "[??:??/12/??:??.??:??]",
            "[??:??/??/2010:??.??:??]",
            "[??:??/12/??:??.??:??]",
            "[??:??/12/2010:??.??:??]"
        ],
        "numbers": [
            "5.837",
            "+2,35/100",
            "254.62",
            "2.073",
            "-0,81/100",
            "2.073",
            "784",
            "1.289",
            "2.425",
            "137.88",
            "3.412",
            "116.74"
        ]
    }
}
