{
    "province": "LAS PALMAS",
    "date": "2010-06-04T00:00:00",
    "url": "https://www.20minutos.es/noticia/727879/0/",
    "title": {
        "raw_text": "Lanzarote conciencia a más de 40.000 escolares, residentes y turistas sobre 'Vivir en una Reserva de la Biosfera'",
        "lemmatized_text": "lanzarote conciencia a más de 40 escolar residente y turista sobre vivir en uno reserva_de_la_biosfera",
        "lemmatized_text_reduced": "lanzarote conciencia escolar residente turista vivir reserva_de_la_biosfera",
        "persons": [],
        "locations": [
            "Lanzarote",
            "Reserva_de_la_Biosfera"
        ],
        "organizations": [],
        "others": [],
        "dates": [],
        "numbers": [
            "40"
        ]
    },
    "lead": {
        "raw_text": "El Cabildo de Lanzarote ha organizado la campaña 'Vivir en una Reserva de la Biosfera' a fin de concienciar de ello a más de 40.000 escolares, residentes y turistas en una iniciativa que se prolongará hasta octubre.",
        "lemmatized_text": "el cabildo_de_lanzarote haber organizar el campaña vivir en uno reserva_de_la_biosfera a_fin_de concienciar de ello a más de 40 escolar residente y turista en uno iniciativa que se prolongar hasta [??:??/10/??:??.??:??]",
        "lemmatized_text_reduced": "cabildo_de_lanzarote haber organizar campaña vivir reserva_de_la_biosfera concienciar escolar residente turista iniciativa prolongar",
        "persons": [],
        "locations": [
            "Reserva_de_la_Biosfera"
        ],
        "organizations": [
            "Cabildo_de_Lanzarote"
        ],
        "others": [],
        "dates": [
            "[??:??/10/??:??.??:??]"
        ],
        "numbers": [
            "40"
        ]
    },
    "body": {
        "raw_text": "\"Lanzarote Reserva (de vida, de ideas, de culturas, de espacios, de belleza, de retos, de posibilidades,) de la Biosfera\". Así reza uno de los lemas incluidos en la campaña de sensibilización y concienciación puesta en marcha por el Cabildo de Lanzarote, con la organización y dirección de la Oficina de la Reserva de la Biosfera. El presidente del Cabildo, Pedro San Ginés, acompañado por la gerente de la Reserva de la Biosfera, Ana Carrasco, presentó hoy la campaña insular de concienciación 'Vivir en una Reserva de La Biosfera', dirigida a estudiantes, visitantes y vecinos. La actividad tiene tres objetivos: mejorar el conocimiento de la población en general sobre lo que significa y supone vivir en una Reserva de la Biosfera; informar sobre los desafíos y retos a los que se enfrenta Lanzarote como Reserva; e intentar promover en los ciudadanos actitudes de responsabilidad y compromiso con la declaración de la Unesco, según informa la corporación insular en un comunicado. La campaña tiene una incidencia especial en la comunidad educativa dado que se \"ha trabajado en abril, mayo y junio con 12.000 alumnos y profesores, destinatarios principales de las actuaciones previstas, aunque las actividades no se dirigen solo a ellos y se espera que pueda llegar a unas 30.000 personas de toda la isla\", explicó Pedro San Ginés. Igualmente, confirmó que la presentación de la campaña se lleva a cabo coincidiendo con la celebración del Día Mundial de Mediambiente (5 de junio), a pesar de que algunas de las actividades comenzaron a desarrollarse en abril. Exposición itinerante y página web Para lograr la sensibilización y la concienciación de escolares, turistas y residentes, la Oficina de la Reserva de la Biosfera ha planificado una serie de actividades como una muestra itinerante con 17 paneles traducidos a cuatro idiomas, y varias actividades paralelas asociadas a la exposición, como charlas y conferencias, dinamización del juego 'El Secreto de la Reserva', reparto de dípticos informativos en el entorno próximo a la exposición, talleres, pasacalles y un largo etcétera. La muestra expositiva quiere dar a conocer la Reserva de la Biosfera de Lanzarote resaltando su imagen, objetivos y actividades principales. Asimismo, se pretende sensibilizar a la población sobre los problemas ambientales más importantes y ofrecer claves de solución es el objetivo principal de esta exposición, que podrá ser apreciada a partir de hoy tras la inauguración de la Semana de Medioambiente en Arrecife, y estará expuesta en el Charco de San Ginés hasta el 12 de junio. Las siguientes paradas de la exposición serán: del 14 al 19 de junio en la Casa de la Cultura de Yaiza; del 21 al 26 de junio en Tías; del 4 al 14 de agosto en Playa Blanca; del 11 al 19 de septiembre en Tinajo; del 20 al 25 de septiembre en San Bartolomé; del 27 de septiembre al 2 de octubre en Haría; del 7 al 9 de octubre en La Graciosa; y del 17 al 24 de octubre en Teguise. Por otro lado, se ha anunciado la próxima presentación de una página web específica para esta campaña, que está en proceso de construcción, y cientos de dípticos, folletos informativos y otros que serán repartidos por toda la geografía insular.",
        "lemmatized_text": "lanzarote_reserva de vida de idea de cultura de espacio de belleza de reto de posibilidad de el biosfera así rezar uno de el lema incluir en el campaña de sensibilización y concienciación poner en marcha por el cabildo_de_lanzarote con el organización y dirección de el oficina_de_la_reserva_de_la_biosfera el presidente de el cabildo pedro_san_ginés acompañar por el gerente de el reserva_de_la_biosfera ana_carrasco presentar hoy el campaña insular de concienciación vivir en uno reserva_de_la_biosfera dirigir a estudiante visitante y vecino el actividad tener 3 objetivo mejorar el conocimiento de el población en general sobre el que significar y suponer vivir en uno reserva_de_la_biosfera informar sobre el desafío y reto a el que se enfrentar lanzarote como reserva y intentar promover en el ciudadano actitud de responsabilidad y compromiso con el declaración de el unesco según informar el corporación insular en uno comunicado el campaña tener uno incidencia especial en el comunidad educativo dado_que se haber trabajar en [??:??/4/??:??.??:??] [??:??/5/??:??.??:??] y [??:??/6/??:??.??:??] con 12 alumno y profesor destinatario principal de el actuación prever aunque el actividad no se dirigir solo a ellos y se esperar que poder llegar a uno 30 persona de todo el isla explicar pedro_san_ginés igualmente confirmar que el presentación de el campaña se llevar_a_cabo coincidir con el celebración de el día_mundial_de_mediambiente [??:5/6/??:??.??:??] a_pesar_de que alguno de el actividad comenzar a desarrollar se en [??:??/4/??:??.??:??] exposición itinerante y página web para lograr el sensibilización y el concienciación de escolar turista y residente el oficina_de_la_reserva_de_la_biosfera haber planificar uno serie de actividad como uno muestra itinerante con 17 panel traducir a 4 idioma y varios actividad paralelo asociar a el exposición como charla y conferencia dinamización de el juego el secreto_de_la_reserva reparto de díptico informativo en el entorno próximo a el exposición taller pasacalle y uno largo etcétera el muestra expositivo querer dar_a_conocer el reserva_de_la_biosfera_de_lanzarote resaltar su imagen objetivo y actividad principal asimismo se pretender sensibilizar a el población sobre el problema ambiental más importante y ofrecer clave de solución ser el objetivo principal de este exposición que poder ser apreciar a_partir_de hoy tras el inauguración de el semana_de_medioambiente en arrecife y estar exponer en el charco_de_san_ginés hasta el [??:12/6/??:??.??:??] el siguiente parada de el exposición ser de el 14 a el [??:19/6/??:??.??:??] en el casa_de_la_cultura_de_yaiza de el 21 a el [??:26/6/??:??.??:??] en tías de el 4 a el [??:14/8/??:??.??:??] en playa_blanca de el 11 a el [??:19/9/??:??.??:??] en tinajo de el 20 a el [??:25/9/??:??.??:??] en san_bartolomé de el [??:27/9/??:??.??:??] a el [??:2/10/??:??.??:??] en haría de el 7 a el [??:9/10/??:??.??:??] en la_graciosa y de el 17 a el [??:24/10/??:??.??:??] en teguise por_otro_lado se haber anunciar el próximo presentación de uno página web específico para este campaña que estar en proceso de construcción y ciento de díptico folleto informativo y otro que ser repartir por todo el geografía insular",
        "lemmatized_text_reduced": "lanzarote_reserva vida idea cultura espacio belleza reto posibilidad biosfera rezar lema incluir campaña sensibilización concienciación poner marcha cabildo_de_lanzarote organización dirección oficina_de_la_reserva_de_la_biosfera presidente cabildo pedro_san_ginés acompañar gerente reserva_de_la_biosfera ana_carrasco presentar campaña insular concienciación vivir reserva_de_la_biosfera dirigir estudiante visitante vecino actividad tener objetivo mejorar conocimiento población general significar suponer vivir reserva_de_la_biosfera informar desafío reto enfrentar lanzarote reserva intentar promover ciudadano actitud responsabilidad compromiso declaración unesco informar corporación insular comunicado campaña tener incidencia especial comunidad educativo haber trabajar alumno profesor destinatario principal actuación prever actividad dirigir esperar poder llegar persona isla explicar pedro_san_ginés igualmente confirmar presentación campaña llevar_a_cabo coincidir celebración día_mundial_de_mediambiente actividad comenzar desarrollar exposición itinerante página web para lograr sensibilización concienciación escolar turista residente oficina_de_la_reserva_de_la_biosfera haber planificar serie actividad muestra itinerante panel traducir idioma actividad paralelo asociar exposición charla conferencia dinamización juego secreto_de_la_reserva reparto díptico informativo entorno próximo exposición taller pasacalle largo etcétera muestra expositivo querer dar_a_conocer reserva_de_la_biosfera_de_lanzarote resaltar imagen objetivo actividad principal pretender sensibilizar población problema ambiental importante ofrecer clave solución ser objetivo principal exposición poder ser apreciar inauguración semana_de_medioambiente arrecife estar exponer charco_de_san_ginés siguiente parada exposición ser casa_de_la_cultura_de_yaiza tías playa_blanca tinajo san_bartolomé haría la_graciosa teguise haber anunciar próximo presentación página web específico campaña estar proceso construcción ciento díptico folleto informativo ser repartir geografía insular",
        "persons": [
            "Pedro_San_Ginés",
            "Ana_Carrasco",
            "Pedro_San_Ginés"
        ],
        "locations": [
            "Lanzarote_Reserva",
            "Biosfera",
            "Reserva_de_la_Biosfera",
            "Reserva_de_La_Biosfera",
            "Reserva_de_la_Biosfera",
            "Lanzarote",
            "Secreto_de_la_Reserva",
            "Reserva_de_la_Biosfera_de_Lanzarote",
            "Arrecife",
            "Charco_de_San_Ginés",
            "Casa_de_la_Cultura_de_Yaiza",
            "Tías",
            "Playa_Blanca",
            "Tinajo",
            "San_Bartolomé",
            "Haría",
            "La_Graciosa",
            "Teguise"
        ],
        "organizations": [
            "Cabildo_de_Lanzarote",
            "Oficina_de_la_Reserva_de_la_Biosfera",
            "Cabildo",
            "Reserva",
            "Unesco",
            "Día_Mundial_de_Mediambiente",
            "Para",
            "Oficina_de_la_Reserva_de_la_Biosfera"
        ],
        "others": [
            "Semana_de_Medioambiente"
        ],
        "dates": [
            "[??:??/4/??:??.??:??]",
            "[??:??/5/??:??.??:??]",
            "[??:??/6/??:??.??:??]",
            "[??:5/6/??:??.??:??]",
            "[??:??/4/??:??.??:??]",
            "[??:12/6/??:??.??:??]",
            "[??:19/6/??:??.??:??]",
            "[??:26/6/??:??.??:??]",
            "[??:14/8/??:??.??:??]",
            "[??:19/9/??:??.??:??]",
            "[??:25/9/??:??.??:??]",
            "[??:27/9/??:??.??:??]",
            "[??:2/10/??:??.??:??]",
            "[??:9/10/??:??.??:??]",
            "[??:24/10/??:??.??:??]"
        ],
        "numbers": [
            "3",
            "12",
            "30",
            "17",
            "4",
            "14",
            "21",
            "4",
            "11",
            "20",
            "7",
            "17"
        ]
    }
}
