{
    "province": "LAS PALMAS",
    "date": "2010-01-20T00:00:00",
    "url": "https://www.20minutos.es/noticia/610775/0/",
    "title": {
        "raw_text": "La siniestralidad laboral desciende en Canarias un 19% con 28.434 accidentes en 2009, 9.809 menos que en 2008",
        "lemmatized_text": "el siniestralidad laboral descender en canarias uno 19/100 con 28.434 accidente en 2009 9.809 menos que en 2008",
        "lemmatized_text_reduced": "siniestralidad laboral descender canarias accidente",
        "persons": [],
        "locations": [
            "Canarias"
        ],
        "organizations": [],
        "others": [],
        "dates": [],
        "numbers": [
            "19/100",
            "28.434",
            "2009",
            "9.809",
            "2008"
        ]
    },
    "lead": {
        "raw_text": "La siniestralidad laboral ha descendido en la Comunidad Autónoma de Canarias entorno al 19 por ciento durante 2009, ya que se produjeron un total de 28.434 accidentes, 9.809 menos que el mismo dato de 2008, según adelantaron hoy el director general de Trabajo del Gobierno de Canarias, Tomás Pino; y el consejero de Empleo, Industria y Comercio, Jorge Rodríguez, durante la presentación de la II Encuesta Canaria de Condiciones de Trabajo.",
        "lemmatized_text": "el siniestralidad laboral haber descender en el comunidad_autónoma_de_canarias entorno a el 19 por 100 durante 2009 ya_que se producir uno total de 28.434 accidente 9.809 menos que el mismo dato de 2008 según adelantar hoy el director general de trabajo_del_gobierno_de_canarias tomás_pino y el consejero de empleo industria y comercio jorge_rodríguez durante el presentación de el ii_encuesta_canaria_de_condiciones_de_trabajo",
        "lemmatized_text_reduced": "siniestralidad laboral haber descender comunidad_autónoma_de_canarias entorno producir total accidente mismo dato adelantar director general trabajo_del_gobierno_de_canarias tomás_pino consejero empleo industria comercio jorge_rodríguez presentación ii_encuesta_canaria_de_condiciones_de_trabajo",
        "persons": [
            "Tomás_Pino",
            "Jorge_Rodríguez"
        ],
        "locations": [
            "Comunidad_Autónoma_de_Canarias"
        ],
        "organizations": [
            "Trabajo_del_Gobierno_de_Canarias",
            "Empleo",
            "Industria",
            "Comercio"
        ],
        "others": [
            "II_Encuesta_Canaria_de_Condiciones_de_Trabajo"
        ],
        "dates": [],
        "numbers": [
            "19",
            "100",
            "2009",
            "28.434",
            "9.809",
            "2008"
        ]
    },
    "body": {
        "raw_text": "De esta manera, en las islas se produjeron casi 28.500 accidentes en 2009, que incluyen aquellos leves, graves y mortales. \"Estamos hablando de 9.809 accidentes menos que los constatados en 2008. Una rebaja muy significativa\", concretó el director general. Del total de accidentes, 155 fueron graves, 21 mortales y el resto leves, que suponen una disminución del 19 por ciento en la siniestralidad absoluta porcentual, mientras que en cuanto a mortales, el descenso fue del 47 por ciento. De los 21 accidentes mortales, 12 de ellos fueron patologías no traumáticas —derrames cerebrales, infartos y patologías similares— \"que son muy difíciles de prevenir\". \"Es verdad —continuó Pino— que ha sido un año positivo a nivel del Estado pero (a falta de que lleguen las cifras definitivas) somos de las regiones que otro año más seguimos reduciendo en mayor porcentaje las cifras de siniestralidad laboral\". Aumentan las empresas que evalúan riesgos En este sentido, la II Encuesta Canaria de Condiciones de Trabajo, que se realizó a trabajadores y empresarios, revela que el 99,2 por ciento de las empresas del archipiélago afirma haber llevado a cabo una evaluación de riesgos laborales en sus negocios, dato superior al último conocido, de 2003, que era del 75,6 por ciento. Por el contrario, el 47,5 por ciento de los trabajadores canarios encuestados manifestaron que en su empresa se han adoptado medidas preventivas de riesgos laborales, cifra que en la provincia de Las Palmas asciende al 44 por ciento y en Santa Cruz de Tenerife al 51,8 por ciento. El consejero de Empleo, Industria y Comercio, ante estos datos, manifestó que no tienen que ser necesariamente contradictorios, sino complementarios. \"El que se haya llegado al 99,2 por ciento de las empresas que reconocen que se ha realizado esa actividad es muy positivo porque ha crecido muchísimo en cinco años. Esto está en consonancia con los resultados que estamos obteniendo año tras año de reducción de accidentes entorno a un 10 o un 15 por ciento cada año de la siniestralidad, y eso es consecuencia del esfuerzo que han hecho todos, no sólo el Gobierno canario, sino empresarios y sindicatos\", dijo Rodríguez. \"Ahora —añadió— que el 47,5 por ciento de los trabajadores perciban que su seguridad ha mejorado es perfectamente compatible con la otra cifra y, además, es muy buen resultado. La mitad de los trabajadores piensa que en los últimos cincos años ha mejorado su prevención de riesgos laborales\".EL 28,5% Piensa que su trabajo afecta a su salud Por otra parte, en el caso de los trabajadores canarios, las 1.233 entrevistas realizadas revelaron que el 28,5 por ciento de ellos opina que el trabajo que desempeñan afecta a su salud, porcentaje que asciende hasta el 51,2 por ciento en el caso del sector agrario. Así, en el sector de la Construcción, fue el 42,1 por ciento de los empleados los que consideraron que su trabajo tenía consecuencias para su salud. Además, en referencia al conjunto de trabajadores nacionales, independientemente del sector, la cifra de empleados que ven perjuicios para su salud por su labor fue del 26,8 por ciento, frente al 40,4 por ciento de los trabajadores de otras nacionalidad. Asimismo, la cifra entres los jóvenes —de 16 a 24 años— se situó en el 30,6 por ciento. Por sectores, el 100 por cien de los camioneros, repartidores, taxistas y otros conductores se ven expuestos a riesgos laborales, dato que se sitúa en el 95,1 por ciento para los trabajadores de la construcción y minería; en el 94,3 por ciento para los de defensa y seguridad y el área de mecánicos, reparadores y soldadores; y en el 93 por ciento de los técnicos en ciencias e informáticos. Sobre la manipulación o inhalación de sustancias nocivas o tóxicas en el puesto de trabajo, el 29,4 por ciento de los trabajadores canarios afirmaron verse expuestos, número que asciende al 54,9 por ciento en la construcción; al 54 por ciento en el sector agrario; al 42,5 por ciento en la industria; y al 24,4 por ciento en el sector servicios. Finalmente, en cuanto a la organización preventiva de riesgos y siniestralidad laboral, el 92 por ciento de las empresas de las islas tiene un servicio de prevención ajeno. Además, el 36 por ciento cuenta con un trabajador designado por el empresario para estos asuntos, el 12,4 por ciento con un sistema de prevención mancomunado y el 14,2 por ciento con un servicio de prevención propio.",
        "lemmatized_text": "de este manera en el isla se producir casi 28.5 accidente en 2009 que incluir aquel leve grave y mortal estar hablar de 9.809 accidente menos que el constatar en 2008 uno rebaja muy significativo concretar el director general de el total de accidente 155 ser grave 21 mortal y el resto leve que suponer uno disminución de el 19 por 100 en el siniestralidad absoluto porcentual mientras_que en_cuanto_a mortal el descenso ser de el 47 por 100 de el 21 accidente mortal 12 de ellos ser patología no traumático derrame cerebral infarto y patología similar que ser muy difícil de prevenir ser verdad continuar pino que haber ser uno año positivo a nivel de el estado pero a falta de que llegar el cifra definitivo ser de el región que otro año más seguir reducir en mayor porcentaje el cifra de siniestralidad laboral aumentar el empresa que evaluar riesgo en este sentido el ii_encuesta_canaria_de_condiciones_de_trabajo que se realizar a trabajador y empresario revelar que el 99,2 por 100 de el empresa de el archipiélago afirmar haber llevar_a_cabo uno evaluación de riesgo laboral en su negocio dato superior a el último conocer de 2003 que ser de el 75,6 por 100 por_el_contrario el 47,5 por 100 de el trabajador canario encuestar manifestar que en su empresa se haber adoptar medida preventivo de riesgo laboral cifra que en el provincia de las_palmas ascender a el 44 por 100 y en santa_cruz_de_tenerife a el 51,8 por 100 el consejero de empleo industria y comercio ante este dato manifestar que no tener que ser necesariamente contradictorio sino complementario el que se haber llegar a el 99,2 por 100 de el empresa que reconocer que se haber realizar ese actividad ser muy positivo porque haber crecer mucho en 5 año este estar en consonancia con el resultado que estar obtener año tras año de reducción de accidente entorno a uno 10 o uno 15 por 100 cada año de el siniestralidad y ese ser consecuencia de el esfuerzo que haber hacer todo no_sólo el gobierno canario sino empresario y sindicato decir rodríguez ahora añadir que el 47,5 por 100 de el trabajador percibir que su seguridad haber mejorar ser perfectamente compatible con el otro cifra y además ser muy bueno resultado el mitad de el trabajador pensar que en el último cincos año haber mejorar su prevención de riesgo laboral el 28,5/100 piensa que su trabajo afectar a su salud por otro parte en el caso de el trabajador canario el 1.233 entrevista realizar revelar que el 28,5 por 100 de ellos opinar que el trabajo que desempeñar afectar a su salud porcentaje que ascender hasta el 51,2 por 100 en el caso de el sector agrario así en el sector de el construcción ser el 42,1 por 100 de el empleado el que considerar que su trabajo tener consecuencia para su salud además en referencia a el conjunto de trabajador nacional independientemente de el sector el cifra de empleado que ver perjuicio para su salud por su labor ser de el 26,8 por 100 frente a el 40,4 por 100 de el trabajador de otro nacionalidad asimismo el cifra entrar el joven de 16 a 24 año se situar en el 30,6 por 100 por sector el 100/100 de el camionero repartidor taxista y otro conductor se ver exponer a riesgo laboral dato que se situar en el 95,1 por 100 para el trabajador de el construcción y minería en el 94,3 por 100 para el de defensa y seguridad y el área de mecánico reparador y soldador y en el 93 por 100 de el técnico en ciencia y informático sobre el manipulación o inhalación de sustancia nocivo o tóxico en_el_puesto_de trabajo el 29,4 por 100 de el trabajador canario afirmar ver se exponer número que ascender a el 54,9 por 100 en el construcción a el 54 por 100 en el sector agrario a el 42,5 por 100 en el industria y a el 24,4 por 100 en el sector servicio finalmente en_cuanto_a el organización preventivo de riesgo y siniestralidad laboral el 92 por 100 de el empresa de el isla tener uno servicio de prevención ajeno además el 36 por 100 cuenta con uno trabajador designar por el empresario para este asunto el 12,4 por 100 con uno sistema de prevención mancomunar y el 14,2 por 100 con uno servicio de prevención propio",
        "lemmatized_text_reduced": "manera isla producir accidente incluir leve grave mortal estar hablar accidente constatar rebaja significativo concretar director general total accidente ser grave mortal resto leve suponer disminución siniestralidad absoluto porcentual mortal descenso ser accidente mortal ser patología traumático derrame cerebral infarto patología similar ser difícil prevenir ser verdad continuar pino haber ser año positivo nivel estado falta llegar cifra definitivo ser región año seguir reducir mayor porcentaje cifra siniestralidad laboral aumentar empresa evaluar riesgo en sentido ii_encuesta_canaria_de_condiciones_de_trabajo realizar trabajador empresario revelar empresa archipiélago afirmar haber llevar_a_cabo evaluación riesgo laboral negocio dato superior último conocer ser trabajador canario encuestar manifestar empresa haber adoptar medida preventivo riesgo laboral cifra provincia las_palmas ascender santa_cruz_de_tenerife consejero empleo industria comercio dato manifestar tener ser necesariamente contradictorio complementario haber llegar empresa reconocer haber realizar actividad ser positivo haber crecer año estar consonancia resultado estar obtener año año reducción accidente entorno año siniestralidad ser consecuencia esfuerzo haber hacer gobierno canario empresario sindicato decir rodríguez añadir trabajador percibir seguridad haber mejorar ser perfectamente compatible cifra ser bueno resultado mitad trabajador pensar último cincos año haber mejorar prevención riesgo laboral piensa trabajo afectar salud por parte caso trabajador canario entrevista realizar revelar opinar trabajo desempeñar afectar salud porcentaje ascender caso sector agrario sector construcción ser empleado considerar trabajo tener consecuencia salud referencia conjunto trabajador nacional independientemente sector cifra empleado ver perjuicio salud labor ser trabajador nacionalidad cifra entrar joven año situar sector camionero repartidor taxista conductor ver exponer riesgo laboral dato situar trabajador construcción minería defensa seguridad área mecánico reparador soldador técnico ciencia informático manipulación inhalación sustancia nocivo tóxico trabajo trabajador canario afirmar ver exponer número ascender construcción sector agrario industria sector servicio finalmente organización preventivo riesgo siniestralidad laboral empresa isla tener servicio prevención ajeno cuenta trabajador designar empresario asunto sistema prevención mancomunar servicio prevención propio",
        "persons": [
            "Pino",
            "Rodríguez",
            "Piensa"
        ],
        "locations": [
            "Las_Palmas",
            "Santa_Cruz_de_Tenerife"
        ],
        "organizations": [
            "Estado",
            "En",
            "Empleo",
            "Industria",
            "Comercio",
            "Gobierno",
            "Por"
        ],
        "others": [
            "II_Encuesta_Canaria_de_Condiciones_de_Trabajo",
            "Construcción"
        ],
        "dates": [],
        "numbers": [
            "28.5",
            "2009",
            "9.809",
            "2008",
            "155",
            "21",
            "19",
            "100",
            "47",
            "100",
            "21",
            "12",
            "99,2",
            "100",
            "2003",
            "75,6",
            "100",
            "47,5",
            "100",
            "44",
            "100",
            "51,8",
            "100",
            "99,2",
            "100",
            "5",
            "10",
            "15",
            "100",
            "47,5",
            "100",
            "28,5/100",
            "1.233",
            "28,5",
            "100",
            "51,2",
            "100",
            "42,1",
            "100",
            "26,8",
            "100",
            "40,4",
            "100",
            "16",
            "24",
            "30,6",
            "100",
            "100/100",
            "95,1",
            "100",
            "94,3",
            "100",
            "93",
            "100",
            "29,4",
            "100",
            "54,9",
            "100",
            "54",
            "100",
            "42,5",
            "100",
            "24,4",
            "100",
            "92",
            "100",
            "36",
            "100",
            "12,4",
            "100",
            "14,2",
            "100"
        ]
    }
}
