{
    "province": "LAS PALMAS",
    "date": "2011-02-07T00:00:00",
    "url": "https://www.20minutos.es/noticia/952343/0/militar/fuerteventura/tanqueta/",
    "title": {
        "raw_text": "Fallece un militar al volcar una tanqueta en Fuerteventura",
        "lemmatized_text": "fallecer uno militar a el volcar uno tanqueta en fuerteventura",
        "lemmatized_text_reduced": "fallecer militar volcar tanqueta fuerteventura",
        "persons": [],
        "locations": [
            "Fuerteventura"
        ],
        "organizations": [],
        "others": [],
        "dates": [],
        "numbers": []
    },
    "lead": {
        "raw_text": "Era un militar venezolano de 28 años del Regimiento de Infantería Ligera Tenerife 49. Murió en un accidente durante un ejercicio táctico al volcar una tanqueta. En el siniestro han resultado heridos también tres soldados.",
        "lemmatized_text": "ser uno militar venezolano de 28 año de el regimiento_de_infantería_ligera_tenerife 49 morir en uno accidente durante uno ejercicio táctico a el volcar uno tanqueta en el siniestro haber resultar herir también 3 soldado",
        "lemmatized_text_reduced": "ser militar venezolano año regimiento_de_infantería_ligera_tenerife morir accidente ejercicio táctico volcar tanqueta siniestro haber resultar herir soldado",
        "persons": [],
        "locations": [],
        "organizations": [],
        "others": [
            "Regimiento_de_Infantería_Ligera_Tenerife"
        ],
        "dates": [],
        "numbers": [
            "28",
            "49",
            "3"
        ]
    },
    "body": {
        "raw_text": "Un militar de 28 años y natural de Caracas (Venezuela) ha fallecido este lunes en Pájara ( Fuerteventura ), en un accidente que se produjo durante un ejercicio táctico al volcar una tanqueta y en el que otros tres soldados han resultado heridos. El fallecido era miembro del Regimiento de Infantería Ligera Tenerife 49 . Así lo ha informado este lunes el Mando de Canarias en un comunicado en el que ha precisado que el fallecido es el soldado José Tomás Fariña García , quien ha fallecido a las 16.40 horas locales cuando el vehículo en el que realizaba un ejercicio táctico ha sufrido un accidente en el campo de tiro de Pájara en circunstancias que no han sido precisadas. En el siniestro han resultado heridos los soldados Alexander Alonso Castro, Raquel García Habas y Miguel Bauluz Pérez, que han sido evacuados al Hospital Insular de Fuerteventura, en Puerto de Rosario, donde han quedado ingresados. Todos ellos, al igual que el fallecido, pertenecen al II Batallón del Regimiento de Infantería Ligera Tenerife 49. El II Batallón realiza un ejercicio táctico de preparación del contingente que el próximo abril se desplazará a Afganistán. Los accidentados viajaban a bordo de un vehículo blindado LMV que ha volcado por causas que todavía se desconocen. El comunicado añade que José Tomás Fariña ingresó en el Ejército en febrero de 2007, estaba casado y tenía tres hijos , mientras que su familia ha sido informada y está siendo atendida por personal de la unidad. En un primer momento, la Delegación del Gobierno en Canarias informó de que los heridos en este accidente eran dos, aunque el Mando de Canarias ha elevado a tres el número de afectados.",
        "lemmatized_text": "uno militar de 28 año y natural de caracas venezuela haber fallecer este [L:??/??/??:??.??:??] en pájara fuerteventura en uno accidente que se producir durante uno ejercicio táctico a el volcar uno tanqueta y en el que otro 3 soldado haber resultar herido el fallecer ser miembro de el regimiento_de_infantería_ligera_tenerife 49 así lo haber informar este [L:??/??/??:??.??:??] el mando_de_canarias en uno comunicado en el que haber precisar que el fallecer ser el soldado josé_tomás_fariña_garcía quien haber fallecer a el TM_h:16.4 local cuando el vehículo en el que realizar uno ejercicio táctico haber sufrir uno accidente en el campo de tiro de pájara en circunstancia que no haber ser precisar en el siniestro haber resultar herido el soldado alexander_alonso_castro raquel_garcía_habas y miguel_bauluz_pérez que haber ser evacuar a el hospital_insular_de_fuerteventura en puerto_de_rosario donde haber quedar ingresar todo ellos al_igual_que el fallecer pertenecer a el ii_batallón_del_regimiento_de_infantería_ligera_tenerife 49 el ii_batallón realizar uno ejercicio táctico de preparación de el contingente que el [??:??/4/??:??.??:??] se desplazar a afganistán el accidentado viajar a_bordo de uno vehículo blindar lmv que haber volcar por causa que todavía se desconocer el comunicado añadir que josé_tomás_fariña ingresar en el ejército en [??:??/2/2007:??.??:??] estar casar y tener 3 hijo mientras_que su familia haber ser informar y estar ser atender por personal de el unidad en uno 1 momento el delegación_del_gobierno en canarias informar de que el herido en este accidente ser 2 aunque el mando_de_canarias haber elevar a 3 el número de afectado",
        "lemmatized_text_reduced": "militar año natural caracas venezuela haber fallecer pájara fuerteventura accidente producir ejercicio táctico volcar tanqueta soldado haber resultar herido fallecer ser miembro regimiento_de_infantería_ligera_tenerife haber informar mando_de_canarias comunicado haber precisar fallecer ser soldado josé_tomás_fariña_garcía haber fallecer local vehículo realizar ejercicio táctico haber sufrir accidente campo tiro pájara circunstancia haber ser precisar siniestro haber resultar herido soldado alexander_alonso_castro raquel_garcía_habas miguel_bauluz_pérez haber ser evacuar hospital_insular_de_fuerteventura puerto_de_rosario haber quedar ingresar fallecer pertenecer ii_batallón_del_regimiento_de_infantería_ligera_tenerife ii_batallón realizar ejercicio táctico preparación contingente desplazar afganistán accidentado viajar vehículo blindar lmv haber volcar causa desconocer comunicado añadir josé_tomás_fariña ingresar ejército estar casar tener hijo familia haber ser informar estar ser atender personal unidad 1 momento delegación_del_gobierno canarias informar herido accidente ser mando_de_canarias haber elevar número afectado",
        "persons": [
            "José_Tomás_Fariña_García",
            "Alexander_Alonso_Castro",
            "Raquel_García_Habas",
            "Miguel_Bauluz_Pérez",
            "José_Tomás_Fariña"
        ],
        "locations": [
            "Caracas",
            "Venezuela",
            "Pájara",
            "Fuerteventura",
            "Pájara",
            "Puerto_de_Rosario",
            "Afganistán",
            "Canarias"
        ],
        "organizations": [
            "Mando_de_Canarias",
            "II_Batallón",
            "LMV",
            "Ejército",
            "Delegación_del_Gobierno",
            "Mando_de_Canarias"
        ],
        "others": [
            "Regimiento_de_Infantería_Ligera_Tenerife",
            "Hospital_Insular_de_Fuerteventura",
            "II_Batallón_del_Regimiento_de_Infantería_Ligera_Tenerife"
        ],
        "dates": [
            "[L:??/??/??:??.??:??]",
            "[L:??/??/??:??.??:??]",
            "[??:??/4/??:??.??:??]",
            "[??:??/2/2007:??.??:??]"
        ],
        "numbers": [
            "28",
            "3",
            "49",
            "TM_h:16.4",
            "49",
            "3",
            "2",
            "3"
        ]
    }
}
