{
    "province": "LAS PALMAS",
    "date": "2009-06-02T00:00:00",
    "url": "https://www.20minutos.es/noticia/471961/0/citan/imputados/arrecife/",
    "title": {
        "raw_text": "Citan a declarar a varios imputados por la trama de corrupción de Lanzarote",
        "lemmatized_text": "citar a declarar a varios imputar por el trama de corrupción de lanzarote",
        "lemmatized_text_reduced": "citar declarar imputar trama corrupción lanzarote",
        "persons": [],
        "locations": [
            "Lanzarote"
        ],
        "organizations": [],
        "others": [],
        "dates": [],
        "numbers": []
    },
    "lead": {
        "raw_text": "Entre ellos a Fabián Martín, vicepresidente del Cabildo de Lanzarote. Rubén Placeres, consejero de Educación y Cultura, dice que dimitirá. CONSULTA AQUÍ MÁS NOTICIAS DE LAS PALMAS .",
        "lemmatized_text": "entre ellos a fabián_martín vicepresidente de el cabildo_de_lanzarote rubén_placeres consejero de educación y cultura decir que dimitir consulta_aquí_más_noticias_de_las_palmas",
        "lemmatized_text_reduced": "fabián_martín vicepresidente cabildo_de_lanzarote rubén_placeres consejero educación cultura decir dimitir consulta_aquí_más_noticias_de_las_palmas",
        "persons": [
            "Fabián_Martín",
            "Rubén_Placeres"
        ],
        "locations": [],
        "organizations": [
            "Cabildo_de_Lanzarote",
            "CONSULTA_AQUÍ_MÁS_NOTICIAS_DE_LAS_PALMAS"
        ],
        "others": [
            "Educación",
            "Cultura"
        ],
        "dates": [],
        "numbers": []
    },
    "body": {
        "raw_text": "La Unidad Central Operativa (UCO) de la Guardia Civil ha citado en la tarde del martes a declarar al vicepresidente del Cabildo de Lanzarote , Fabián Martín Martín (PIL), como imputado en la trama de corrupción destapada en la isla , informaron fuentes de la investigación. La UCO ha citado también a declarar como imputado al consejero socialista de Educación y Cultura del Cabildo de Lanzarote, Rubén Placeres, quien ha anunciado que dimitirá tras ser citado en la investigación. Según fuentes de la dirección socialista en Lanzarote, el consejero ha comunicado al partido, además, su deseo de causar baja en la formación política. Asimismo, la UCO llamó también este martes a declarar como imputados a la alcaldesa de Yaiza, Gladys Acuña (PIL), y al de Tinajo, Jesús Machín (CC). Otro miembro de la familia Martín Fabián Martín es hijo del líder del Partido de Independientes de Lanzarote (PIL) Dimas Martín, presunto cerebro de esta trama, que está en la cárcel cumpliendo 8 años de cárcel por otros delitos y que ha sido imputado en este caso por cohecho y tráfico de influencias. También su hermana Elena Martín, jefa de contratación del Ayuntamiento de Arrecife, fue detenida el pasado día 25 en el Consistorio, aunque fue puesta en libertad con cargos . En esta operación ya hay siete personas en prisión y otras 13 imputadas por el juez por delitos de corrupción.",
        "lemmatized_text": "el unidad_central_operativa uco de el guardia_civil haber citar en el tarde de el [M:??/??/??:??.??:??] a declarar a el vicepresidente de el cabildo_de_lanzarote fabián_martín_martín pil como imputar en el trama de corrupción destapar en el isla informar fuente de el investigación el uco haber citar también a declarar como imputar a el consejero socialista de educación y cultura_del_cabildo_de_lanzarote rubén_placeres quien haber anunciar que dimitir tras ser citar en el investigación según fuente de el dirección socialista en lanzarote el consejero haber comunicar a el partido además su deseo de causar baja en el formación político asimismo el uco llamar también este [M:??/??/??:??.??:??] a declarar como imputar a el alcaldesa de yaiza gladys_acuña pil y a el de tinajo jesús_machín cc otro miembro de el familia martín_fabián_martín ser hijo de el líder de el partido_de_independientes_de_lanzarote pil dimas_martín presunto cerebro de este trama que estar en el cárcel cumplir 8 año de cárcel por otro delito y que haber ser imputar en este caso por cohecho y tráfico de influencia también su hermano elena_martín jefe de contratación de el ayuntamiento_de_arrecife ser detener el [??:25/??/??:??.??:??] en el consistorio aunque ser poner en libertad con cargo en este operación ya haber 7 persona en prisión y otro 13 imputar por el juez por delito de corrupción",
        "lemmatized_text_reduced": "unidad_central_operativa uco guardia_civil haber citar tarde declarar vicepresidente cabildo_de_lanzarote fabián_martín_martín pil imputar trama corrupción destapar isla informar fuente investigación uco haber citar declarar imputar consejero socialista educación cultura_del_cabildo_de_lanzarote rubén_placeres haber anunciar dimitir ser citar investigación fuente dirección socialista lanzarote consejero haber comunicar partido deseo causar baja formación político uco llamar declarar imputar alcaldesa yaiza gladys_acuña pil tinajo jesús_machín cc miembro familia martín_fabián_martín ser hijo líder partido_de_independientes_de_lanzarote pil dimas_martín presunto cerebro trama estar cárcel cumplir año cárcel delito haber ser imputar caso cohecho tráfico influencia hermano elena_martín jefe contratación ayuntamiento_de_arrecife ser detener consistorio ser poner libertad cargo operación haber persona prisión imputar juez delito corrupción",
        "persons": [
            "Fabián_Martín_Martín",
            "Rubén_Placeres",
            "Gladys_Acuña",
            "Jesús_Machín",
            "Martín_Fabián_Martín",
            "Dimas_Martín",
            "Elena_Martín"
        ],
        "locations": [
            "Lanzarote",
            "Yaiza",
            "Tinajo"
        ],
        "organizations": [
            "Unidad_Central_Operativa",
            "UCO",
            "Guardia_Civil",
            "Cabildo_de_Lanzarote",
            "PIL",
            "UCO",
            "Cultura_del_Cabildo_de_Lanzarote",
            "UCO",
            "PIL",
            "CC",
            "Partido_de_Independientes_de_Lanzarote",
            "PIL",
            "Ayuntamiento_de_Arrecife",
            "Consistorio"
        ],
        "others": [
            "Educación"
        ],
        "dates": [
            "[M:??/??/??:??.??:??]",
            "[M:??/??/??:??.??:??]",
            "[??:25/??/??:??.??:??]"
        ],
        "numbers": [
            "8",
            "7",
            "13"
        ]
    }
}
