{
    "province": "LAS PALMAS",
    "date": "2010-03-01T00:00:00",
    "url": "https://www.20minutos.es/noticia/640483/0/",
    "title": {
        "raw_text": "El turismo de apartamentos en Canarias cae un 3,13% en enero a pesar del empuje de Gran Canaria",
        "lemmatized_text": "el turismo de apartamento en canarias caer uno 3,13/100 en [??:??/1/??:??.??:??] a pesar de el empuje de gran_canaria",
        "lemmatized_text_reduced": "turismo apartamento canarias caer pesar empuje gran_canaria",
        "persons": [],
        "locations": [
            "Canarias"
        ],
        "organizations": [],
        "others": [
            "Gran_Canaria"
        ],
        "dates": [
            "[??:??/1/??:??.??:??]"
        ],
        "numbers": [
            "3,13/100"
        ]
    },
    "lead": {
        "raw_text": "El número de pernoctaciones en apartamentos de las islas Canarias ha descendido un 3,13 por ciento en enero, hasta alcanzar los 3,16 millones de noches, a pesar del empuje de Gran Canaria, que las incrementó 79.066 pernoctaciones y un 6,03 por ciento más, según la Encuesta de alojamiento turístico en apartamentos publicada hoy por el Instituto canario de estadística (Istac).",
        "lemmatized_text": "el número de pernoctación en apartamento de el isla canarias haber descender uno 3,13 por 100 en [??:??/1/??:??.??:??] hasta alcanzar el 3,16 millón de noche a pesar de el empuje de gran_canaria que lo incrementar 79.066 pernoctación y uno 6,03 por 100 más según el encuesta de alojamiento turístico en apartamento publicar hoy por el instituto canario de estadística istac",
        "lemmatized_text_reduced": "número pernoctación apartamento isla canarias haber descender alcanzar millón noche pesar empuje gran_canaria incrementar pernoctación encuesta alojamiento turístico apartamento publicar instituto canario estadística istac",
        "persons": [],
        "locations": [
            "Canarias",
            "Istac"
        ],
        "organizations": [
            "Instituto"
        ],
        "others": [
            "Gran_Canaria",
            "Encuesta"
        ],
        "dates": [
            "[??:??/1/??:??.??:??]"
        ],
        "numbers": [
            "3,13",
            "100",
            "3,16",
            "79.066",
            "6,03",
            "100"
        ]
    },
    "body": {
        "raw_text": "El número de noches total ha caído en 102.317, lastrado principalmente por el descenso en 116.809 pernoctaciones en la isla de Tenerife. El Hierro registró el mayor descenso, con un 52,49 por ciento menos, seguido de La Gomera (-12,17%), Fuerteventura (-12,05%), Tenerife (-12,04%) y Lanzarote (-5,43%), mientras que en lado positivo sólo se situaron La Palma (+20,06%) y Gran Canaria (+6,03%). El número de viajeros, en cambio, creció un 1,69 por ciento en enero en el conjunto de las islas, hasta alcanzar los 326.320 viajeros, gracias principalmente a Gran Canaria, que incrementó la entrada de turistas en 15.361 y un 12,87 por ciento más. En concreto, el turismo de apartamentos en el archipiélago aumentó el primer mes de 2010 en 5.429 personas, después de aumentar en Gran Canaria, La Palma y La Gomera y decrecer en el resto de islas. En Gran Canaria, el total de enero se elevó a las 134.675 personas, un 12,87 por ciento más que los 119.314 del mismo mes del ejercicio anterior, mientras que Tenerife, el segundo mercado de las islas en este tipo de alojamiento turístico, registró 95.005 viajeros, un 6,18 por ciento menos que los 101.261 registrados en enero de 2009. Lanzarote redujo la entrada de viajeros en un 4,36 por ciento, hasta situarse en 62.464 personas este mes de enero, frente a los 65.310 de enero del año anterior.",
        "lemmatized_text": "el número de noche total haber caer en 102.317 lastrar principalmente por el descenso en 116.809 pernoctación en el isla de tenerife el hierro registrar el mayor descenso con uno 52,49 por 100 menos seguir de la_gomera -12,17/100 fuerteventura -12,05/100 tenerife -12,04/100 y lanzarote -5,43/100 mientras_que en lado positivo sólo se situar la_palma +20,06/100 y gran_canaria +6,03/100 el número de viajero en cambio crecer uno 1,69 por 100 en [??:??/1/??:??.??:??] en el conjunto de el isla hasta alcanzar el 326.32 viajero gracia principalmente a gran_canaria que incrementar el entrada de turista en 15.361 y uno 12,87 por 100 más en concreto el turismo de apartamento en el archipiélago aumentar el 1 mes de 2010 en 5.429 persona después_de aumentar en gran_canaria la_palma y la_gomera y decrecer en el resto de isla en gran_canaria el total de [??:??/1/??:??.??:??] se elevar a el 134.675 persona uno 12,87 por 100 más que el 119.314 de el mismo mes de el ejercicio anterior mientras_que tenerife el 2 mercado de el isla en este tipo de alojamiento turístico registrar 95.005 viajero uno 6,18 por 100 menos que el 101.261 registrar en [??:??/1/2009:??.??:??] lanzarote reducir el entrada de viajero en uno 4,36 por 100 hasta situar se en 62.464 persona este [??:??/1/??:??.??:??] frente_a el 65.31 de [??:??/1/??:??.??:??] de el año anterior",
        "lemmatized_text_reduced": "número noche total haber caer lastrar principalmente descenso pernoctación isla tenerife hierro registrar mayor descenso seguir la_gomera fuerteventura tenerife lanzarote lado positivo situar la_palma gran_canaria número viajero cambio crecer conjunto isla alcanzar viajero gracia principalmente gran_canaria incrementar entrada turista concreto turismo apartamento archipiélago aumentar 1 mes persona aumentar gran_canaria la_palma la_gomera decrecer resto isla gran_canaria total elevar persona mismo mes ejercicio anterior tenerife 2 mercado isla tipo alojamiento turístico registrar viajero registrar lanzarote reducir entrada viajero situar persona año anterior",
        "persons": [
            "Hierro",
            "Gran_Canaria"
        ],
        "locations": [
            "Tenerife",
            "La_Gomera",
            "Lanzarote",
            "La_Palma",
            "Gran_Canaria",
            "La_Palma",
            "Gran_Canaria",
            "Lanzarote"
        ],
        "organizations": [
            "Fuerteventura",
            "Tenerife",
            "Gran_Canaria",
            "La_Gomera",
            "Tenerife"
        ],
        "others": [],
        "dates": [
            "[??:??/1/??:??.??:??]",
            "[??:??/1/??:??.??:??]",
            "[??:??/1/2009:??.??:??]",
            "[??:??/1/??:??.??:??]",
            "[??:??/1/??:??.??:??]"
        ],
        "numbers": [
            "102.317",
            "116.809",
            "52,49",
            "100",
            "-12,17/100",
            "-12,05/100",
            "-12,04/100",
            "-5,43/100",
            "+20,06/100",
            "+6,03/100",
            "1,69",
            "100",
            "326.32",
            "15.361",
            "12,87",
            "100",
            "2010",
            "5.429",
            "134.675",
            "12,87",
            "100",
            "119.314",
            "95.005",
            "6,18",
            "100",
            "101.261",
            "4,36",
            "100",
            "62.464",
            "65.31"
        ]
    }
}
