{
    "province": "LAS PALMAS",
    "date": "2010-03-26T00:00:00",
    "url": "https://www.20minutos.es/noticia/662313/0/",
    "title": {
        "raw_text": "S.Las fiestas comienzan con sol y más de 18ºC en toda España, de lunes a miércoles lloverá y el jueves mejorará",
        "lemmatized_text": "s._las fiesta comenzar con sol y más de 18ºC en todo españa de [L:??/??/??:??.??:??] a [X:??/??/??:??.??:??] llover y el [J:??/??/??:??.??:??] mejorar",
        "lemmatized_text_reduced": "s._las fiesta comenzar sol españa llover mejorar",
        "persons": [
            "S._Las"
        ],
        "locations": [
            "España"
        ],
        "organizations": [],
        "others": [],
        "dates": [
            "[L:??/??/??:??.??:??]",
            "[X:??/??/??:??.??:??]",
            "[J:??/??/??:??.??:??]"
        ],
        "numbers": [
            "18ºC"
        ]
    },
    "lead": {
        "raw_text": "En Canarias soplarán alisios moderados que favorecerán la formación de nubes en el norte",
        "lemmatized_text": "en canarias soplar alisio moderado que favorecer el formación de nube en el norte",
        "lemmatized_text_reduced": "canarias soplar alisio moderado favorecer formación nube norte",
        "persons": [],
        "locations": [
            "Canarias"
        ],
        "organizations": [],
        "others": [],
        "dates": [],
        "numbers": []
    },
    "body": {
        "raw_text": "La inminente Semana Santa no será \"terriblemente mala\" en cuanto al tiempo se refiere ya que durante este sábado y domingo se espera que el sol brille y que las temperaturas suban en \"toda\" España, aunque entre el lunes y el miércoles pasará un frente que dejará lluvias en la mitad noroccidental, es decir al lado izquierdo de los Pirineos hasta Gibraltar, según informó hoy la Agencia Estatal de Meteorología (AEMET), que añadió que desde el jueves al domingo la situación volverá a ser estable. Así, el portavoz de la AEMET, Ángel Rivera, explicó a Europa Press que se prevé una Semana Santa \"propia de primavera\", es decir que el tiempo no se mantendrá estable durante toda la semana. Además, señaló que lunes, martes y miércoles serán los días más inestables de forma general y en particular en la mitad noroccidental donde se esperan precipitaciones débiles e incluso moderadas en Galicia. Si bien, a partir del miércoles por la tarde la estabilidad y los termómetros se irán recuperando \"sin llegar a alcanzar las buenas temperaturas de este fin de semana\". Durante la segunda parte de la semana se espera un tiempo \"en general relativamente estable, con algún chubasco no generalizado\", por lo que de jueves a domingo habrá \"riesgo pequeño\" de algunas precipitaciones débiles y dispersas. Concretamente, mañana sábado y el domingo de Ramos los termómetros subirán en toda España salvo en Levante, donde se mantendrán sin cambios, hasta 22 y 23 grados centígrados en el sur; a 18 o 20 grados centígrados en el centro; de 16 a 17 grados centígrados en el norte y uno o dos grados más en las costas del norte de la Península, y se mantendrán en unos 20 grados centígrados en Levante. Rivera agregó que el lunes llegará por el noroeste un sistema frontal atlántico que cruzará la Península de oeste a este dejando precipitaciones moderadas en el noroeste y áreas de montaña y que disminuirán cuanto más al sur y al este de la Península. Existe poca probabilidad de que lleguen al Mediterráneo y Baleares. \"No serán importantes, salvo en Galicia\", puntualizó. En esos días, las temperaturas caerán de forma moderada, de unos 4 o 5 grados centígrados en la vertiente atlántica peninsular, y de unos 2 grados centígrados en el resto. No obstante, Rivera precisó que no se esperan heladas en esta semana. La segunda mitad se arregla Ya el miércoles, indicó que las lluvias tiendan a remitir menos en el litoral y en los Pirineos, donde podrán mantenerse con una intensidad localmente moderada. El viento será de componente oeste moderado con intervalos de fuerte, sobre todo el martes. En Canarias, soplarán alisios moderados que favorecerán la formación de nubes en el norte del archipiélago dejando cielos poco nubosos en el sur. El portavoz de la AEMET adelantó que a partir del miércoles por la tarde, el jueves, viernes y sábado santo se tenderá a una \"estabilización generalizada del tiempo\" y tan solo en el extremo norte peninsular hay una \"pequeña probabilidad\" de precipitaciones débiles, aunque éstas se podrían extender de forma \"ocasional\" a puntos dispersos de la mitad noroccidental.",
        "lemmatized_text": "el inminente semana_santa no ser terriblemente malo en cuanto a el tiempo se referir ya_que durante este [S:??/??/??:??.??:??] y [G:??/??/??:??.??:??] se esperar que el sol brillar y que el temperatura subir en todo españa aunque entre el [L:??/??/??:??.??:??] y el [X:??/??/??:??.??:??] pasar uno frente que dejar lluvia en el mitad noroccidental ser decir a el lado izquierdo de el pirineos hasta gibraltar según informar hoy el agencia_estatal_de_meteorología aemet que añadir que desde el [J:??/??/??:??.??:??] a el [G:??/??/??:??.??:??] el situación volver a ser estable así el portavoz de el aemet ángel_rivera explicar a europa_press que se prever uno semana_santa propio de primavera ser decir que el tiempo no se mantener estable durante todo el semana además señalar que [L:??/??/??:??.??:??] [M:??/??/??:??.??:??] y [X:??/??/??:??.??:??] ser el día más inestable de forma general y en particular en el mitad noroccidental donde se esperar precipitación débil y incluso moderar en galicia si bien a partir de el [X:??/??/??:??.??:pm] el estabilidad y el termómetro se ir recuperar sin llegar a alcanzar el bueno temperatura de este fin de semana durante el 2 parte de el semana se esperar uno tiempo en general relativamente estable con alguno chubasco no generalizar por el que de [J:??/??/??:??.??:??] a [G:??/??/??:??.??:??] haber riesgo pequeño de alguno precipitación débil y disperso concretamente mañana [S:??/??/??:??.??:??] y el [G:??/??/??:??.??:??] de ramos el termómetro subir en todo españa salvo en levante donde se mantener sin cambio hasta 22 y TP_C:23 en el sur a 18 o TP_C:20 en el centro de 16 a TP_C:17 en el norte y uno o 2 grado más en el costa de el norte de el península y se mantener en uno TP_C:20 en levante rivera agregar que el [L:??/??/??:??.??:??] llegar por el noroeste uno sistema frontal atlántico que cruzar el península de oeste a este dejar precipitación moderar en el noroeste y área de montaña y que disminuir cuanto más a el sur y a el este de el península existir poco probabilidad de que llegar a el mediterráneo y baleares no ser importante salvo en galicia puntualizar en ese día el temperatura caer de forma moderar de uno 4 o TP_C:5 en el vertiente atlántico peninsular y de uno TP_C:2 en el resto no_obstante rivera precisar que no se esperar helar en este semana el 2 mitad se arreglar ya el [X:??/??/??:??.??:??] indicar que el lluvia tender a remitir menos en el litoral y en el pirineos donde poder mantener se con uno intensidad localmente moderar el viento ser de componente oeste moderar con intervalo de fuerte sobre todo el [M:??/??/??:??.??:??] en canarias soplar alisio moderado que favorecer el formación de nube en el norte de el archipiélago dejar cielo poco nuboso en el sur el portavoz de el aemet adelantar que a partir de el [X:??/??/??:??.??:pm] el [J:??/??/??:??.??:??] [V:??/??/??:??.??:??] y [S:??/??/??:??.??:??] santo se tender a uno estabilización generalizar de el tiempo y tan solo en el extremo norte peninsular haber uno pequeño probabilidad de precipitación débil aunque este se poder extender de forma ocasional a punto disperso de el mitad noroccidental",
        "lemmatized_text_reduced": "inminente semana_santa ser terriblemente malo tiempo referir esperar sol brillar temperatura subir españa pasar frente dejar lluvia mitad noroccidental ser decir lado izquierdo pirineos gibraltar informar agencia_estatal_de_meteorología aemet añadir situación volver ser estable portavoz aemet ángel_rivera explicar europa_press prever semana_santa propio primavera ser decir tiempo mantener estable semana señalar ser día inestable forma general particular mitad noroccidental esperar precipitación débil moderar galicia partir estabilidad termómetro ir recuperar llegar alcanzar bueno temperatura fin semana 2 parte semana esperar tiempo general relativamente estable chubasco generalizar haber riesgo pequeño precipitación débil disperso concretamente ramos termómetro subir españa levante mantener cambio sur centro norte grado costa norte península mantener levante rivera agregar llegar noroeste sistema frontal atlántico cruzar península oeste dejar precipitación moderar noroeste área montaña disminuir sur península existir probabilidad llegar mediterráneo baleares ser importante galicia puntualizar día temperatura caer forma moderar vertiente atlántico peninsular resto rivera precisar esperar helar semana 2 mitad arreglar ya indicar lluvia tender remitir litoral pirineos poder mantener intensidad localmente moderar viento ser componente oeste moderar intervalo fuerte canarias soplar alisio moderado favorecer formación nube norte archipiélago dejar cielo nuboso sur portavoz aemet adelantar partir santo tender estabilización generalizar tiempo solo extremo norte peninsular haber pequeño probabilidad precipitación débil poder extender forma ocasional punto disperso mitad noroccidental",
        "persons": [
            "Semana_Santa",
            "España",
            "Ángel_Rivera",
            "Europa_Press",
            "Rivera",
            "Rivera",
            "Ya"
        ],
        "locations": [
            "Pirineos",
            "Gibraltar",
            "Galicia",
            "Ramos",
            "España",
            "Levante",
            "Península",
            "Levante",
            "Península",
            "Península",
            "Mediterráneo",
            "Baleares",
            "Galicia",
            "Pirineos",
            "Canarias"
        ],
        "organizations": [
            "Agencia_Estatal_de_Meteorología",
            "AEMET",
            "AEMET",
            "AEMET"
        ],
        "others": [
            "Semana_Santa"
        ],
        "dates": [
            "[S:??/??/??:??.??:??]",
            "[G:??/??/??:??.??:??]",
            "[L:??/??/??:??.??:??]",
            "[X:??/??/??:??.??:??]",
            "[J:??/??/??:??.??:??]",
            "[G:??/??/??:??.??:??]",
            "[L:??/??/??:??.??:??]",
            "[M:??/??/??:??.??:??]",
            "[X:??/??/??:??.??:??]",
            "[X:??/??/??:??.??:pm]",
            "[J:??/??/??:??.??:??]",
            "[G:??/??/??:??.??:??]",
            "[S:??/??/??:??.??:??]",
            "[G:??/??/??:??.??:??]",
            "[L:??/??/??:??.??:??]",
            "[X:??/??/??:??.??:??]",
            "[M:??/??/??:??.??:??]",
            "[X:??/??/??:??.??:pm]",
            "[J:??/??/??:??.??:??]",
            "[V:??/??/??:??.??:??]",
            "[S:??/??/??:??.??:??]"
        ],
        "numbers": [
            "22",
            "TP_C:23",
            "18",
            "TP_C:20",
            "16",
            "TP_C:17",
            "2",
            "TP_C:20",
            "4",
            "TP_C:5",
            "TP_C:2"
        ]
    }
}
