{
    "province": "LAS PALMAS",
    "date": "2010-04-14T00:00:00",
    "url": "https://www.20minutos.es/noticia/677289/0/",
    "title": {
        "raw_text": "La candidatura de Las Palmas de Gran Canaria a Capital Cultural Europea ocupa el octavo puesto con 132.509 votos",
        "lemmatized_text": "el candidatura de las_palmas_de_gran_canaria a capital_cultural_europea ocupar el 8 puesto con 132.509 voto",
        "lemmatized_text_reduced": "candidatura las_palmas_de_gran_canaria capital_cultural_europea ocupar 8 puesto voto",
        "persons": [],
        "locations": [
            "Las_Palmas_de_Gran_Canaria",
            "Capital_Cultural_Europea"
        ],
        "organizations": [],
        "others": [],
        "dates": [],
        "numbers": [
            "132.509"
        ]
    },
    "lead": {
        "raw_text": "La candidatura de Las Palmas de Gran Canaria a la Capitalidad Europea de la Cultura ocupa el octavo puesto entre las ciudades españolas que más votos acumulan en la página web www.candidatecities.com, perteneciente a la Asociación de Ciudades Candidatas a la Capitalidad Europea de la Cultura. Así, la ciudad canaria ha obtenido hasta la fecha el 4,66 por ciento de los votos de los internautas, sumando 132.509, según los datos consultados por Europa Press.",
        "lemmatized_text": "el candidatura de las_palmas_de_gran_canaria a el capitalidad_europea_de_la_cultura ocupar el 8 puesto entre el ciudad español que más voto acumular en el página web www.candidatecities.com perteneciente a el asociación_de_ciudades_candidatas a el capitalidad_europea_de_la_cultura así el ciudad canario haber obtener hasta el fecha el 4,66 por 100 de el voto de el internauta sumar 132.509 según el dato consultar por europa_press",
        "lemmatized_text_reduced": "candidatura las_palmas_de_gran_canaria capitalidad_europea_de_la_cultura ocupar 8 puesto ciudad español voto acumular página web www.candidatecities.com perteneciente asociación_de_ciudades_candidatas capitalidad_europea_de_la_cultura ciudad canario haber obtener fecha voto internauta sumar dato consultar europa_press",
        "persons": [],
        "locations": [
            "Las_Palmas_de_Gran_Canaria"
        ],
        "organizations": [
            "Capitalidad_Europea_de_la_Cultura",
            "Asociación_de_Ciudades_Candidatas",
            "Europa_Press"
        ],
        "others": [
            "Capitalidad_Europea_de_la_Cultura"
        ],
        "dates": [],
        "numbers": [
            "4,66",
            "100",
            "132.509"
        ]
    },
    "body": {
        "raw_text": "Encabezando la lista se encuentra la ciudad de Oviedo, con un 15,61 por ciento de los votos (443.811), siguiéndole muy de cerca la candidatura de Santander, que cuenta con 427.668 votos, lo que supone un 15,04 por ciento de los votos totales emitidos hasta el momento, un total de 2.843.635. Otras candidaturas destacadas son Cáceres, con 336.538 votos (11,83%); Córdoba, con 271.929 (9,56%); Málaga, con 257.748 (9,06%); Zaragoza, con 226.040 (7,95%); y Burgos, que ha obtenido 171.719 votos, el equivalente al 6,04 por ciento del total. Por detrás de Las Palmas de Gran Canaria, que ocupa la octava posición, quedarían Tarragona, con 119.464 votos (4,2%); Cuenca, con 113.949 (4,01%); San Sebastián, con 83.816 (2,95%); Segovia, con 76.444 (2,69%); Alcalá de Henares, con 71.711 (2,52%); Murcia, con 67.960 (2,39%); y, cerrando la lista, la ciudad de Pamplona, con un total de 42.329 votos, lo que significa un 1,49 por ciento del total emitidos. La Asociación de Ciudades Candidatas a la Capitalidad Europea de la Cultura, tiene como finalidad dinamizar la cooperación cultural entre las ciudades y agentes culturales públicos y privados que han participado o presentado su candidatura a la Capitalidad Europea de la Cultura. Esta Asociación es una iniciativa de la sociedad civil y se constituyó en el año 2008, con la colaboración del Ministerio de Cultura de España. Son miembros de la misma, además de Oviedo, las ciudades de Bialystok (Polonia), Burgos (España), Cáceres (España), Cuenca (España), Las Palmas de Gran Canaria (España), Matera (Italia), Mons (Bélgica), Murcia (España), Pamplona (España), Pilsen (República Checa), Ravenna (Italia), Santander (España), Segovia (España), Torun (Polonia) y Wroclaw (Polonia). No obstante, a la de Oviedo le sigue muy de cerca la candidatura de Santander, que cuenta con 427.654 votos, lo que supone un 15,04 por ciento de los votos totales emitidos, un total de 283.475. Otras candidaturas destacadas en esta encuesta son la de Cáceres (11,84% de los votos), Córdoba (9,56 de los votos), Málaga (9,06) y Zaragoza (7,95%).",
        "lemmatized_text": "encabezar el lista se encontrar el ciudad de oviedo con uno 15,61 por 100 de el voto 443.811 seguir le muy de cerca el candidatura de santander que contar con 427.668 voto el que suponer uno 15,04 por 100 de el voto total emitir hasta el momento uno total de 2.843.635 otro candidatura destacar ser cáceres con 336.538 voto 11,83/100 córdoba con 271.929 9,56/100 málaga con 257.748 9,06/100 zaragoza con 226.04 7,95/100 y burgos que haber obtener 171.719 voto el equivalente a el 6,04 por 100 de el total por detrás_de las_palmas_de_gran_canaria que ocupar el 8 posición quedar tarragona con 119.464 voto 4,2/100 cuenca con 113.949 4,01/100 san_sebastián con 83.816 2,95/100 segovia con 76.444 2,69/100 alcalá_de_henares con 71.711 2,52/100 murcia con 67.96 2,39/100 y cerrar el lista el ciudad de pamplona con uno total de 42.329 voto el que significar uno 1,49 por 100 de el total emitir el asociación_de_ciudades_candidatas a el capitalidad_europea_de_la_cultura tener como finalidad dinamizar el cooperación cultural entre el ciudad y agente cultural público y privar que haber participar o presentar su candidatura a el capitalidad_europea_de_la_cultura este asociación ser uno iniciativa de el sociedad civil y se constituir en el [??:??/??/2008:??.??:??] con el colaboración de el ministerio_de_cultura_de_españa ser miembro de el mismo además_de oviedo el ciudad de bialystok polonia burgos españa cáceres españa cuenca españa las_palmas_de_gran_canaria españa matera italia mons bélgica murcia españa pamplona españa pilsen república_checa ravenna italia santander españa segovia españa torun polonia y wroclaw polonia no_obstante a el de oviedo le seguir muy de cerca el candidatura de santander que contar con 427.654 voto el que suponer uno 15,04 por 100 de el voto total emitir uno total de 283.475 otro candidatura destacar en este encuesta ser el de cáceres 11,84/100 de el voto córdoba 9,56 de el voto málaga 9,06 y zaragoza 7,95/100",
        "lemmatized_text_reduced": "encabezar lista encontrar ciudad oviedo voto seguir candidatura santander contar voto suponer voto total emitir momento total candidatura destacar ser cáceres voto córdoba málaga zaragoza burgos haber obtener voto equivalente total las_palmas_de_gran_canaria ocupar 8 posición quedar tarragona voto cuenca san_sebastián segovia alcalá_de_henares murcia cerrar lista ciudad pamplona total voto significar total emitir asociación_de_ciudades_candidatas capitalidad_europea_de_la_cultura tener finalidad dinamizar cooperación cultural ciudad agente cultural público privar haber participar presentar candidatura capitalidad_europea_de_la_cultura asociación ser iniciativa sociedad civil constituir colaboración ministerio_de_cultura_de_españa ser miembro mismo oviedo ciudad bialystok polonia burgos españa cáceres españa cuenca españa las_palmas_de_gran_canaria españa matera italia mons bélgica murcia españa pamplona españa pilsen república_checa ravenna italia santander españa segovia españa torun polonia wroclaw polonia oviedo seguir candidatura santander contar voto suponer voto total emitir total candidatura destacar encuesta ser cáceres voto córdoba voto málaga zaragoza",
        "persons": [
            "Burgos",
            "San_Sebastián",
            "Oviedo",
            "Burgos",
            "Cáceres",
            "Matera",
            "Torun",
            "Wroclaw",
            "Oviedo"
        ],
        "locations": [
            "Oviedo",
            "Santander",
            "Cáceres",
            "Córdoba",
            "Málaga",
            "Zaragoza",
            "Tarragona",
            "Cuenca",
            "Segovia",
            "Murcia",
            "Pamplona",
            "Bialystok",
            "Polonia",
            "Cuenca",
            "Las_Palmas_de_Gran_Canaria",
            "Italia",
            "Mons",
            "Murcia",
            "España",
            "Pamplona",
            "Ravenna",
            "Italia",
            "Santander",
            "España",
            "Segovia",
            "Santander",
            "Cáceres",
            "Córdoba",
            "Málaga",
            "Zaragoza"
        ],
        "organizations": [
            "Las_Palmas_de_Gran_Canaria",
            "Asociación_de_Ciudades_Candidatas",
            "Asociación",
            "Ministerio_de_Cultura_de_España",
            "España",
            "España",
            "España",
            "España",
            "Bélgica",
            "España",
            "Pilsen",
            "República_Checa",
            "España",
            "Polonia",
            "Polonia"
        ],
        "others": [
            "Alcalá_de_Henares",
            "Capitalidad_Europea_de_la_Cultura",
            "Capitalidad_Europea_de_la_Cultura"
        ],
        "dates": [
            "[??:??/??/2008:??.??:??]"
        ],
        "numbers": [
            "15,61",
            "100",
            "443.811",
            "427.668",
            "15,04",
            "100",
            "2.843.635",
            "336.538",
            "11,83/100",
            "271.929",
            "9,56/100",
            "257.748",
            "9,06/100",
            "226.04",
            "7,95/100",
            "171.719",
            "6,04",
            "100",
            "119.464",
            "4,2/100",
            "113.949",
            "4,01/100",
            "83.816",
            "2,95/100",
            "76.444",
            "2,69/100",
            "71.711",
            "2,52/100",
            "67.96",
            "2,39/100",
            "42.329",
            "1,49",
            "100",
            "427.654",
            "15,04",
            "100",
            "283.475",
            "11,84/100",
            "9,56",
            "9,06",
            "7,95/100"
        ]
    }
}
