{
    "province": "LAS PALMAS",
    "date": "2010-05-03T00:00:00",
    "url": "https://www.20minutos.es/noticia/695527/0/",
    "title": {
        "raw_text": "Las ventas de coches caen un 13,61% en Las Palmas en abril",
        "lemmatized_text": "el venta de coche caer uno 13,61/100 en las_palmas en [??:??/4/??:??.??:??]",
        "lemmatized_text_reduced": "venta coche caer las_palmas",
        "persons": [],
        "locations": [],
        "organizations": [
            "Las_Palmas"
        ],
        "others": [],
        "dates": [
            "[??:??/4/??:??.??:??]"
        ],
        "numbers": [
            "13,61/100"
        ]
    },
    "lead": {
        "raw_text": "La adquisición de vehículos crece un 3,2% en Canarias",
        "lemmatized_text": "el adquisición de vehículo crecer uno 3,2/100 en canarias",
        "lemmatized_text_reduced": "adquisición vehículo crecer canarias",
        "persons": [],
        "locations": [
            "Canarias"
        ],
        "organizations": [],
        "others": [],
        "dates": [],
        "numbers": [
            "3,2/100"
        ]
    },
    "body": {
        "raw_text": "La adquisición de vehículos en la provincia de Las Palmas ha vuelto a dar cifras negativas, ya que el pasado mes de abril se matricularon un total de 1.168 unidades en la provincia, frente a las 1.352 del mismo periodo del año pasado, lo que supone una caída del 13,61 por ciento. Así lo reflejan datos de la consultora MSI para la Federación de Asociaciones de Concesionarios de la Automoción (Faconauto), que precisan que en el archipiélago aumentaron un 3,2 por ciento las ventas, al pasar de 2.247 unidades en abril de 2009 a 2.319 el pasado mes del presente año. Suben un 28,6% En santa cruz de tenerife Por su parte, la compra de coches en Santa Cruz de Tenerife sigue arrojando buenos resultados, favorecidos por las ayudas oficiales contempladas en el Plan 2000E. De este modo, en abril se matricularon un total de 1.151 unidades en la provincia, frente a las 895 del mismo periodo del año pasado, lo que supone un incremento del 28,6 por ciento. Faconauto asegura que el agotamiento de los fondos del Plan 2000E está influyendo negativamente sobre las ventas de coches, y auguró que en los meses de mayo y junio la tendencia del mercado será \"claramente a la baja\".EMPEORAMIENTO La patronal considera que en abril las matriculaciones se han desacelerado como consecuencia del agotamiento del Plan 2000E, a pesar de que el mercado creció casi un 40%. Además, en virtud de los pedidos que manejan los concesionarios, pronostica un empeoramiento para los meses de mayo y junio. La patronal de los concesionarios calcula que, sin las ayudas oficiales, en abril se habrían dejado de vender 12.000 automóviles. Asimismo, indica que en el último mes se acogieron al Plan 2000E unas 38.000 operaciones. El presidente de Faconauto, Antonio Romero-Haupold, señaló que los datos de abril, \"aun siendo positivos, marcan lo que va a ocurrir en mayo y en junio, cuando el Plan 2000E esté definitivamente acabado\". \"Esperamos que el mercado empiece a resentirse y mucha menos alegría en el cierre de operaciones\", abundó. La organización subrayó el cambio de tendencia de la demanda que ha generado el Plan 2000E, ya que más del 70% de los coches comercializados en abril tenían emisiones inferiores a 150 gramos de CO2 por kilómetro recorrido, es decir, los que pueden acogerse al programa de ayudas. Este dato implica que la mayor parte de los coches que se están vendiendo en España están fabricados en factorías españolas, lo que permite el mantenimiento de los puestos de trabajo en toda la cadena de valor del sector: fabricantes de componentes, marcas y distribuidores.",
        "lemmatized_text": "el adquisición de vehículo en el provincia de las_palmas haber volver a dar cifra negativo ya_que el [??:??/4/??:??.??:??] se matricular uno total de 1.168 unidad en el provincia frente_a el 1.352 de el mismo periodo de el año pasar el que suponer uno caída de el 13,61 por 100 así lo reflejar dato de el consultor msi_para_la_federación_de_asociaciones_de_concesionarios_de_la_automoción faconauto que precisar que en el archipiélago aumentar uno 3,2 por 100 el venta a el pasar de 2.247 unidad en [??:??/4/2009:??.??:??] a 2.319 el pasar mes de el presente año subir uno 28,6/100 en santo cruz de tenerife por su parte el compra de coche en santa_cruz_de_tenerife seguir arrojar bueno resultado favorecer por el ayuda oficial contemplar en el plan 2000E de este modo en [??:??/4/??:??.??:??] se matricular uno total de 1.151 unidad en el provincia frente_a el 895 de el mismo periodo de el año pasar el que suponer uno incremento de el 28,6 por 100 faconauto asegurar que el agotamiento de el fondo de el plan 2000E estar influir negativamente sobre el venta de coche y augurar que en el mes de [??:??/5/??:??.??:??] y [??:??/6/??:??.??:??] el tendencia de el mercado ser claramente a el baja empeoramiento_la patronal considerar que en [??:??/4/??:??.??:??] el matriculación se haber desacelerar como consecuencia de el agotamiento de el plan 2000E a_pesar_de que el mercado crecer casi uno 40/100 además en_virtud_de el pedido que manejar el concesionario pronosticar uno empeoramiento para el mes de [??:??/5/??:??.??:??] y [??:??/6/??:??.??:??] el patronal de el concesionario calcular que sin el ayuda oficial en [??:??/4/??:??.??:??] se haber dejar de vender 12 automóvil asimismo indicar que en el último mes se acoger a el plan 2000E uno 38 operación el presidente de faconauto antonio_romero-haupold señalar que el dato de [??:??/4/??:??.??:??] aun ser positivo marcar el que ir a ocurrir en [??:??/5/??:??.??:??] y en [??:??/6/??:??.??:??] cuando el plan 2000E estar definitivamente acabar esperar que el mercado empezar a resentir se y mucho menos alegría en el cierre de operación abundar el organización subrayar el cambio de tendencia de el demanda que haber generar el plan 2000E ya_que más de el 70/100 de el coche comercializar en [??:??/4/??:??.??:??] tener emisión inferior a WG_g:150 de CO2 por kilómetro recorrido ser decir el que poder acoger se a el programa de ayuda este dato implicar que el mayor parte de el coche que se estar vender en españa estar fabricar en factoría español el que permitir el mantenimiento de el puesto de trabajo en todo el cadena de valor de el sector fabricante de componente marca y distribuidor",
        "lemmatized_text_reduced": "adquisición vehículo provincia las_palmas haber volver dar cifra negativo matricular total unidad provincia mismo periodo año pasar suponer caída reflejar dato consultor msi_para_la_federación_de_asociaciones_de_concesionarios_de_la_automoción faconauto precisar archipiélago aumentar venta pasar unidad pasar mes presente año subir en santo cruz tenerife por parte compra coche santa_cruz_de_tenerife seguir arrojar bueno resultado favorecer ayuda oficial contemplar plan modo matricular total unidad provincia mismo periodo año pasar suponer incremento faconauto asegurar agotamiento fondo plan estar influir negativamente venta coche augurar mes tendencia mercado ser claramente baja empeoramiento_la patronal considerar matriculación haber desacelerar consecuencia agotamiento plan mercado crecer pedido manejar concesionario pronosticar empeoramiento mes patronal concesionario calcular ayuda oficial haber dejar vender automóvil indicar último mes acoger plan operación presidente faconauto antonio_romero-haupold señalar dato ser positivo marcar ir ocurrir plan estar definitivamente acabar esperar mercado empezar resentir alegría cierre operación abundar organización subrayar cambio tendencia demanda haber generar plan coche comercializar tener emisión inferior kilómetro recorrido ser decir poder acoger programa ayuda dato implicar mayor parte coche estar vender españa estar fabricar factoría español permitir mantenimiento puesto trabajo cadena valor sector fabricante componente marca distribuidor",
        "persons": [
            "En",
            "Faconauto",
            "EMPEORAMIENTO_La",
            "Antonio_Romero-Haupold"
        ],
        "locations": [
            "Santa_Cruz_de_Tenerife",
            "España"
        ],
        "organizations": [
            "Las_Palmas",
            "MSI_para_la_Federación_de_Asociaciones_de_Concesionarios_de_la_Automoción",
            "Faconauto",
            "Por",
            "Faconauto"
        ],
        "others": [
            "Plan",
            "Plan",
            "Plan",
            "Plan",
            "Plan",
            "Plan"
        ],
        "dates": [
            "[??:??/4/??:??.??:??]",
            "[??:??/4/2009:??.??:??]",
            "[??:??/4/??:??.??:??]",
            "[??:??/5/??:??.??:??]",
            "[??:??/6/??:??.??:??]",
            "[??:??/4/??:??.??:??]",
            "[??:??/5/??:??.??:??]",
            "[??:??/6/??:??.??:??]",
            "[??:??/4/??:??.??:??]",
            "[??:??/4/??:??.??:??]",
            "[??:??/5/??:??.??:??]",
            "[??:??/6/??:??.??:??]",
            "[??:??/4/??:??.??:??]"
        ],
        "numbers": [
            "1.168",
            "1.352",
            "13,61",
            "100",
            "3,2",
            "100",
            "2.247",
            "2.319",
            "28,6/100",
            "2000E",
            "1.151",
            "895",
            "28,6",
            "100",
            "2000E",
            "2000E",
            "40/100",
            "12",
            "2000E",
            "38",
            "2000E",
            "2000E",
            "70/100",
            "WG_g:150",
            "CO2"
        ]
    }
}
