{
    "province": "LAS PALMAS",
    "date": "2010-05-03T00:00:00",
    "url": "https://www.20minutos.es/noticia/695427/0/",
    "title": {
        "raw_text": "Canarias sufre la mayor caída de 2010 en afiliados a la Seguridad Social de hostelería y agencias de viajes",
        "lemmatized_text": "canario sufrir el mayor caída de 2010 en afiliado a el seguridad_social de hostelería y agencia de viaje",
        "lemmatized_text_reduced": "canario sufrir mayor caída afiliado seguridad_social hostelería agencia viaje",
        "persons": [],
        "locations": [],
        "organizations": [],
        "others": [
            "Seguridad_Social"
        ],
        "dates": [],
        "numbers": [
            "2010"
        ]
    },
    "lead": {
        "raw_text": "La Comunidad Autónoma de Canarias registró hasta marzo un descenso del 3 por ciento en el número de afiliados a la Seguridad Social, lo que supone el mayor descenso de todas las comunidades autónomas, según datos difundidos por el Instituto de Estudios Turísticos (IET).",
        "lemmatized_text": "el comunidad_autónoma_de_canarias registrar hasta [??:??/3/??:??.??:??] uno descenso de el 3 por 100 en el número de afiliado a el seguridad_social el que suponer el mayor descenso de todo el comunidad autónomo según dato difundir por el instituto_de_estudios_turísticos iet",
        "lemmatized_text_reduced": "comunidad_autónoma_de_canarias registrar descenso número afiliado seguridad_social suponer mayor descenso comunidad autónomo dato difundir instituto_de_estudios_turísticos iet",
        "persons": [],
        "locations": [],
        "organizations": [
            "Comunidad_Autónoma_de_Canarias",
            "Instituto_de_Estudios_Turísticos",
            "IET"
        ],
        "others": [
            "Seguridad_Social"
        ],
        "dates": [
            "[??:??/3/??:??.??:??]"
        ],
        "numbers": [
            "3",
            "100"
        ]
    },
    "body": {
        "raw_text": "De esta forma, el número total de afiliados en el archipiélago dentro del sector turístico queda reducido a los 105.553 trabajadores. En el acumulado del año las siguientes por la cola fueron Baleares (-2,1%), la Comunidad Valenciana (-1,7%) y la Comunidad de Madrid (-0,4%). Canarias también se apuntó la mayor caída en marzo con casi un 1 por ciento de afiliados menos, seguida de la Comunidad de Madrid, con un recorte del 0,2%, hasta los 190.947 afiliados. Andalucía contabilizó 201.275 trabajadores afiliados a estas actividades, un 4,3% más hasta marzo; la mayor subida, seguida de Cataluña, que cuenta con el mayor número de afiliados con 216.067, un 2% más, y de Baleares, que registró 57.613 trabajadores, un 1,1% más. En el conjunto nacional, el número de trabajadores dados de alta en la Seguridad Social aumentó un 0,9% en marzo, hasta 1,89 millones de afiliados, con respecto al mismo mes del año anterior. De ellos, 1,44 millones de empleados fueron asalariados, un 1,3% más con respecto al mismo mes del año pasado, y un total de 454.673 fueron autónomos (-0,4%). Por actividad, la afiliación en hostelería y agencias de viajes se incrementó un 1,5% en marzo, hasta 1,29 millones trabajadores. En el periodo acumulado, la afiliación a la Seguridad Social en actividades vinculadas al sector turístico acumula una caída del 0,1%, hasta los 1,86 millones de trabajadores. De ellos, 1,41 millones correspondieron a trabajadores asalariados, cifra que permaneció invariable, y un total de 452.807 (-0,7%) a autónomos. Por actividad, el número de trabajadores en hostelería se situó el pasado mes en 1,29 millones de afiliados. De ellos, el 77% corresponde a actividades de restauración (servicios de comidas y bebidas), y el 22,9%, 243.749 trabajadores, a empresas de alojamientos turísticos. En ambos subsectores la afiliación aumentó un 2,3% en alojamientos y un 1,8% en restauración, con respecto al mismo mes de 2008. En cuanto a las agencias de viajes, el número de afiliados alcanzó los 54.098 en marzo, lo que supone una caída del 6,5% con respecto al mismo del año anterior. De enero a marzo, la afiliación en este sector se recortó un 8%, hasta los 53.665 trabajadores.",
        "lemmatized_text": "de este forma el número total de afiliado en el archipiélago dentro de el sector turístico quedar reducir a el 105.553 trabajador en el acumular de el año el siguiente por el cola ser baleares -2,1/100 el comunidad_valenciana -1,7/100 y el comunidad_de_madrid -0,4/100 canario también se apuntar el mayor caída en [??:??/3/??:??.??:??] con casi uno 1 por 100 de afiliado menos seguir de el comunidad_de_madrid con uno recorte de el 0,2/100 hasta el 190.947 afiliado andalucía contabilizar 201.275 trabajador afiliar a este actividad uno 4,3/100 más hasta [??:??/3/??:??.??:??] el mayor subida seguir de cataluña que contar con el mayor número de afiliado con 216.067 uno 2/100 más y de baleares que registrar 57.613 trabajador uno 1,1/100 más en el conjunto nacional el número de trabajador dar_de_alta en el seguridad_social aumentar uno 0,9/100 en [??:??/3/??:??.??:??] hasta 1,89 millón de afiliado con respecto a el mismo mes de el año anterior de ellos 1,44 millón de empleado ser asalariar uno 1,3/100 más con respecto a el mismo mes de el año pasar y uno total de 454.673 ser autónomo -0,4/100 por actividad el afiliación en hostelería y agencia de viaje se incrementar uno 1,5/100 en [??:??/3/??:??.??:??] hasta 1,29 millón trabajador en el periodo acumular el afiliación a el seguridad_social en actividad vincular a el sector turístico acumular uno caída de el 0,1/100 hasta el 1,86 millón de trabajador de ellos 1,41 millón corresponder a trabajador asalariar cifra que permanecer invariable y uno total de 452.807 -0,7/100 a autónomo por actividad el número de trabajador en hostelería se situar el pasar mes en 1,29 millón de afiliado de ellos el 77/100 corresponder a actividad de restauración servicio de comida y bebida y el 22,9/100 243.749 trabajador a empresa de alojamiento turístico en ambos subsector el afiliación aumentar uno 2,3/100 en alojamiento y uno 1,8/100 en restauración con respecto a el mismo mes de 2008 en_cuanto_a el agencia de viaje el número de afiliado alcanzar el 54.098 en [??:??/3/??:??.??:??] el que suponer uno caída de el 6,5/100 con respecto a el mismo de el año anterior de [??:??/1/??:??.??:??] a [??:??/3/??:??.??:??] el afiliación en este sector se recortar uno 8/100 hasta el 53.665 trabajador",
        "lemmatized_text_reduced": "forma número total afiliado archipiélago sector turístico quedar reducir trabajador acumular año siguiente cola ser baleares comunidad_valenciana comunidad_de_madrid canario apuntar mayor caída afiliado seguir comunidad_de_madrid recorte afiliado andalucía contabilizar trabajador afiliar actividad mayor subida seguir cataluña contar mayor número afiliado baleares registrar trabajador conjunto nacional número trabajador seguridad_social aumentar millón afiliado respecto mismo mes año anterior millón empleado ser asalariar respecto mismo mes año pasar total ser autónomo actividad afiliación hostelería agencia viaje incrementar millón trabajador periodo acumular afiliación seguridad_social actividad vincular sector turístico acumular caída millón trabajador millón corresponder trabajador asalariar cifra permanecer invariable total autónomo actividad número trabajador hostelería situar pasar mes millón afiliado corresponder actividad restauración servicio comida bebida trabajador empresa alojamiento turístico subsector afiliación aumentar alojamiento restauración respecto mismo mes agencia viaje número afiliado alcanzar suponer caída respecto año anterior afiliación sector recortar trabajador",
        "persons": [],
        "locations": [
            "Baleares",
            "Andalucía",
            "Cataluña",
            "Baleares"
        ],
        "organizations": [
            "Comunidad_Valenciana",
            "Comunidad_de_Madrid",
            "Comunidad_de_Madrid"
        ],
        "others": [
            "Seguridad_Social",
            "Seguridad_Social"
        ],
        "dates": [
            "[??:??/3/??:??.??:??]",
            "[??:??/3/??:??.??:??]",
            "[??:??/3/??:??.??:??]",
            "[??:??/3/??:??.??:??]",
            "[??:??/3/??:??.??:??]",
            "[??:??/1/??:??.??:??]",
            "[??:??/3/??:??.??:??]"
        ],
        "numbers": [
            "105.553",
            "-2,1/100",
            "-1,7/100",
            "-0,4/100",
            "1",
            "100",
            "0,2/100",
            "190.947",
            "201.275",
            "4,3/100",
            "216.067",
            "2/100",
            "57.613",
            "1,1/100",
            "0,9/100",
            "1,89",
            "1,44",
            "1,3/100",
            "454.673",
            "-0,4/100",
            "1,5/100",
            "1,29",
            "0,1/100",
            "1,86",
            "1,41",
            "452.807",
            "-0,7/100",
            "1,29",
            "77/100",
            "22,9/100",
            "243.749",
            "2,3/100",
            "1,8/100",
            "2008",
            "54.098",
            "6,5/100",
            "8/100",
            "53.665"
        ]
    }
}
