{
    "province": "LAS PALMAS",
    "date": "2009-12-26T00:00:00",
    "url": "https://www.20minutos.es/noticia/595772/0/",
    "title": {
        "raw_text": "Alerta amarilla en La Palma y El Hierro por fuerte oleaje",
        "lemmatized_text": "alerta amarillo en la_palma y el_hierro por fuerte oleaje",
        "lemmatized_text_reduced": "amarillo la_palma el_hierro fuerte oleaje",
        "persons": [],
        "locations": [
            "La_Palma",
            "El_Hierro"
        ],
        "organizations": [],
        "others": [],
        "dates": [],
        "numbers": []
    },
    "lead": {
        "raw_text": "En Canarias las precipitaciones serán débiles o localmente moderadas",
        "lemmatized_text": "en canarias el precipitación ser débil o localmente moderar",
        "lemmatized_text_reduced": "canarias precipitación ser débil localmente moderar",
        "persons": [],
        "locations": [
            "Canarias"
        ],
        "organizations": [],
        "others": [],
        "dates": [],
        "numbers": []
    },
    "body": {
        "raw_text": "La Agencia Estatal de Meteorología (Aemet) mantiene la alerta amarilla en el norte y oeste de La Palma y el suroeste del Hierro por fuerte oleaje, situación que persistirá hasta las 14.00 horas de hoy. De este modo, durante la jornada de hoy se prevén fenómenos costeros adversos con mar de fondo de hasta 4 metros afectando al norte y oeste de La Palma y norte y oeste del Hierro durante la primera mitad del día. En el oeste de ambas islas las aguas costeras serán de fuerza 4, amainando desde primeras horas de la mañana a variable fuerza 2 a 3, y marejada, disminuyendo durante la mañana a rizada a marejadilla. Además de mar de fondo del oeste de hasta 4 metros, girando y disminuyendo a noroeste de 3 metros por la tarde. Por su parte, el resto de las islas se librarán de la alerta por mal tiempo, aunque la Aemet prevé precipitaciones débiles o localmente moderadas. En la vertiente oeste de las islas se prevén cielos nubosos en general, mientras que en el resto de zonas se registrarán intervalos nubosos, predominando la nubosidad alta, y aumentando la nubosidad durante las primeras horas de la tarde salvo en cumbres. Asimismo, en Lanzarote y Fuerteventura los cielos presentarán intervalos nubosos predominando la nubosidad alta, tendiendo a abrirse claros durante la tarde. Un total de 29 Provincias en alerta Un total de 29 provincias permanecen hoy en alerta por fuertes lluvias y viento, que serán más persistentes en puntos del cuadrante suroeste peninsular, según datos actualizados de la Aemet. Así, seis provincias (Huesca, Zaragoza, La Rioja, Navarra, Burgos y Soria) permanecen en alerta naranja por nieve, mientras que en Cádiz, Granada, Málaga y Ceuta está activado el mismo nivel de alerta por fuertes lluvias. También hay alerta amarilla por nieve en Teruel, Cuenca, Guadalajara, Barcelona, Girona, LLeida y Cáceres, mientras que el Andalucía los avisos son por lluvias, vientos y fenómenos costeros. En este sentido, la Aemet destaca las precipitaciones fuertes y/o persistentes que se registrarán en puntos del cuadrante suroeste, así como nevadas en puntos de la zona centro y fuerte viento en puntos de Castilla-Mancha, Baleares, Canarias y el litoral cantábrico oriental. Respecto a la predicción, en el cantábrico oriental y en el Pirineo se producirán precipitaciones débiles al principio de la jornada, tendiendo a intervalos nubosos. En el sur y suroeste peninsular, habrá un aumento de la nubosidad con precipitaciones débiles a moderadas que podrían ser localmente fuertes y/opersistentes y acompañadas de tormenta. Estas lluvias se presentarán en forma débil a moderada en el resto de la mitad sur y zona centro a lo largo del día, pero sin alcanzar el tercio norte. En el caso de Baleares, los cielos estarán poco nubosos, aumentando a intervalos nubosos con probabilidad de alguna lluvia débil al final de la jornada en Ibiza. En Canarias, las precipitaciones serán débiles o localmente moderadas. La cota de nieve en la Península oscilará entre los 900 y 1.200 metros en la mitad norte de la Península y los 1.800 a 2.000 metros en Andalucía. La AEMET también prevé brumas y nieblas matinales en el noroeste peninsular. Las temperaturas no registrarán cambios en Canarias, mientras que en el resto sufrirán un descenso ligero o moderado, aunque será localmente notable en el caso de las diurnas del norte peninsular. Los vientos serán moderados a fuertes en Baleares, y moderados con rachas fuertes o muy fuertes en zonas altas de Canarias. En la Península, de componente oeste girando a componente este, flojo a moderado con intervalos de fuerte en el Cantábrico y en el litoral de Andalucía occidental.",
        "lemmatized_text": "el agencia_estatal_de_meteorología aemet mantener el alerta amarillo en el norte y oeste de la_palma y el suroeste de el hierro por fuerte oleaje situación que persistir hasta el TM_h:14 de hoy de este modo durante el jornada de hoy se prever fenómeno costero adverso con mar de fondo de hasta LN_m:4 afectar a el norte y oeste de la_palma y norte y oeste de el hierro durante el 1 mitad de el día en el oeste de ambos isla el agua costero ser de fuerza 4 amainar desde 1 hora de el mañana a variable fuerza 2 a 3 y marejada disminuir durante el mañana a rizar a marejadilla además_de mar de fondo de el oeste de hasta LN_m:4 girar y disminuir a noroeste de LN_m:3 por el tarde por su parte el resto de el isla se librar de el alerta por mal tiempo aunque el aemet prever precipitación débil o localmente moderar en el vertiente oeste de el isla se prever cielo nuboso en general mientras_que en el resto de zona se registrar intervalo nuboso predominar el nubosidad alto y aumentar el nubosidad durante el 1 hora de el tarde salvo en cumbre asimismo en lanzarote y fuerteventura el cielo presentar intervalo nuboso predominar el nubosidad alto tender a abrir se claro durante el tarde uno total de 29 provincias en alertar uno total de 29 provincia permanecer hoy en alerta por fuerte lluvia y viento que ser más persistente en punto de el cuadrante suroeste peninsular según dato actualizar de el aemet así 6 provincia huesca zaragoza la_rioja navarra burgos y soria permanecer en alerta naranja por nieve mientras_que en cádiz granada málaga y ceuta estar activar el mismo nivel de alerta por fuerte lluvia también haber alerta amarillo por nieve en teruel cuenca guadalajara barcelona girona lleida y cáceres mientras_que el andalucía el aviso ser por lluvia viento y fenómeno costero en este sentido el aemet destacar el precipitación fuerte y o persistente que se registrar en punto de el cuadrante suroeste así_como nevada en punto de el zona centro y fuerte viento en punto de castilla-mancha baleares canarias y el litoral cantábrico oriental respecto_a el predicción en el cantábrico oriental y en el pirineo se producir precipitación débil a el principio de el jornada tender a intervalo nuboso en el sur y suroeste peninsular haber uno aumento de el nubosidad con precipitación débil a moderado que poder ser localmente fuerte y opersistentes y acompañar de tormenta este lluvia se presentar en forma débil a moderado en el resto de el mitad sur y zona centro a el largo de el día pero sin alcanzar el tercio norte en el caso de baleares el cielo estar poco nuboso aumentar a intervalo nuboso con probabilidad de alguno lluvia débil a el final de el jornada en ibiza en canarias el precipitación ser débil o localmente moderar el cota de nieve en el península oscilar entre el 900 y LN_m:1.2 en el mitad norte de el península y el 1.8 a LN_m:2 en andalucía el aemet también prever bruma y niebla matinal en el noroeste peninsular el temperatura no registrar cambio en canarias mientras_que en el resto sufrir uno descenso ligero o moderar aunque ser localmente notable en el caso de el diurno de el norte peninsular el viento ser moderar a fuerte en baleares y moderar con racha fuerte o muy fuerte en zona alto de canarias en el península de componente oeste girar a componente este flojo a moderar con intervalo de fuerte en el cantábrico y en el litoral de andalucía occidental",
        "lemmatized_text_reduced": "agencia_estatal_de_meteorología aemet mantener alerta amarillo norte oeste la_palma suroeste hierro fuerte oleaje situación persistir modo jornada prever fenómeno costero adverso mar fondo afectar norte oeste la_palma norte oeste hierro 1 mitad día oeste isla agua costero ser fuerza amainar 1 hora mañana variable fuerza marejada disminuir mañana rizar marejadilla mar fondo oeste girar disminuir noroeste tarde parte resto isla librar alerta mal tiempo aemet prever precipitación débil localmente moderar vertiente oeste isla prever cielo nuboso general resto zona registrar intervalo nuboso predominar nubosidad alto aumentar nubosidad 1 hora tarde cumbre lanzarote fuerteventura cielo presentar intervalo nuboso predominar nubosidad alto tender abrir claro tarde total provincias alertar total provincia permanecer alerta fuerte lluvia viento ser persistente punto cuadrante suroeste peninsular dato actualizar aemet provincia huesca zaragoza la_rioja navarra burgos soria permanecer alerta naranja nieve cádiz granada málaga ceuta estar activar mismo nivel alerta fuerte lluvia haber alerta amarillo nieve teruel cuenca guadalajara barcelona girona lleida cáceres andalucía aviso ser lluvia viento fenómeno costero sentido aemet destacar precipitación fuerte persistente registrar punto cuadrante suroeste nevada punto zona centro fuerte viento punto castilla-mancha baleares canarias litoral cantábrico oriental predicción cantábrico oriental pirineo producir precipitación débil principio jornada tender intervalo nuboso sur suroeste peninsular haber aumento nubosidad precipitación débil moderado poder ser localmente fuerte opersistentes acompañar tormenta lluvia presentar forma débil moderado resto mitad sur zona centro largo día alcanzar tercio norte caso baleares cielo estar nuboso aumentar intervalo nuboso probabilidad lluvia débil final jornada ibiza canarias precipitación ser débil localmente moderar cota nieve península oscilar mitad norte península andalucía aemet prever bruma niebla matinal noroeste peninsular temperatura registrar cambio canarias resto sufrir descenso ligero moderar ser localmente notable caso diurno norte peninsular viento ser moderar fuerte baleares moderar racha fuerte fuerte zona alto canarias península componente oeste girar componente flojo moderar intervalo fuerte cantábrico litoral andalucía occidental",
        "persons": [
            "Hierro",
            "Hierro"
        ],
        "locations": [
            "La_Palma",
            "La_Palma",
            "Lanzarote",
            "Huesca",
            "La_Rioja",
            "Navarra",
            "Burgos",
            "Soria",
            "Cádiz",
            "Granada",
            "Málaga",
            "Ceuta",
            "Teruel",
            "Cuenca",
            "Guadalajara",
            "Barcelona",
            "Girona",
            "Cáceres",
            "Castilla-Mancha",
            "Baleares",
            "Canarias",
            "Pirineo",
            "Baleares",
            "Ibiza",
            "Canarias",
            "Península",
            "Península",
            "Andalucía",
            "Canarias",
            "Baleares",
            "Canarias",
            "Península",
            "Cantábrico",
            "Andalucía"
        ],
        "organizations": [
            "Agencia_Estatal_de_Meteorología",
            "Aemet",
            "Aemet",
            "Fuerteventura",
            "Aemet",
            "Zaragoza",
            "LLeida",
            "Andalucía",
            "AEMET"
        ],
        "others": [
            "Provincias",
            "Aemet"
        ],
        "dates": [],
        "numbers": [
            "TM_h:14",
            "LN_m:4",
            "4",
            "2",
            "3",
            "LN_m:4",
            "LN_m:3",
            "29",
            "29",
            "6",
            "900",
            "LN_m:1.2",
            "1.8",
            "LN_m:2"
        ]
    }
}
