{
    "province": "LAS PALMAS",
    "date": "2009-12-09T00:00:00",
    "url": "https://www.20minutos.es/noticia/584513/0/aminatu/haidar/aaiun/",
    "title": {
        "raw_text": "Haidar: \"Volveré a El Aaiún viva o muerta\"",
        "lemmatized_text": "haidar volver a el_aaiún vivo o morir",
        "lemmatized_text_reduced": "haidar volver el_aaiún vivo morir",
        "persons": [
            "Haidar"
        ],
        "locations": [
            "El_Aaiún"
        ],
        "organizations": [],
        "others": [],
        "dates": [],
        "numbers": []
    },
    "lead": {
        "raw_text": "Ha pospuesto hasta este jueves su declaración ante la prensa porque \"no se siente con fuerzas\". 200 personalidades han pedido la mediación del Rey Juan Carlos. ENCUESTA: ¿Debe continuar la huelga de hambre?",
        "lemmatized_text": "haber posponer hasta este [J:??/??/??:??.??:??] su declaración ante el prensa porque no se sentir con fuerza 200 personalidad haber pedir el mediación de el rey_juan_carlos encuesta deber continuar el huelga de hambre",
        "lemmatized_text_reduced": "haber posponer declaración prensa sentir fuerza personalidad haber pedir mediación rey_juan_carlos encuesta deber continuar huelga hambre",
        "persons": [
            "Rey_Juan_Carlos"
        ],
        "locations": [],
        "organizations": [],
        "others": [],
        "dates": [
            "[J:??/??/??:??.??:??]"
        ],
        "numbers": [
            "200"
        ]
    },
    "body": {
        "raw_text": "La activista saharaui Aminatu Haidar, que cumple su vigésimo cuarto día de huelga de hambre en protesta por su expulsión de Marruecos, el pasado 14 de noviembre, ha asegurado este miércoles que volverá a El Aaiún \"viva o muerta\" . La activista saharaui ha cumplido 24 días en huelga de hambre en el aeropuerto de Lanzarote Así contestó Haidar cuando era trasladada a un baño próximo al habitáculo en el que se encuentra en el aeropuerto de Lanzarote, al ser preguntada si confiaba en volver pronto a El Aaiún. Éstas han sido las únicas palabras que ha pronunciado Haidar, quien ha decidido posponer hasta este jueves, \"porque no se siente con fuerzas\", la declaración que preveía realizar el miércoles en el Aeropuerto de Lanzarote. Allí sigue una huelga de hambre desde hace 24 días para conseguir su regreso a El Aaiún, de donde fue expulsada el 14 de noviembre. En relación con el caso Haidar, el ministro de Justicia marroquí, Abdelwahed Radi, ha dicho en Madrid que tanto su país como España son \"víctimas\" de \"personas contrarias y hostiles a la unidad territorial de Marruecos\" y que habría preferido que Haidar hubiera fuera expulsada \"a otro país\" .",
        "lemmatized_text": "el activista saharaui aminatu_haidar que cumplir su 20 4 día de huelga de hambre en protesta por su expulsión de marruecos el [??:14/11/??:??.??:??] haber asegurar este [X:??/??/??:??.??:??] que volver a el_aaiún vivo o morir el activista saharaui haber cumplir TM_d:24 en huelga de hambre en el aeropuerto de lanzarote_así contestar haidar cuando ser trasladar a uno baño próximo a el habitáculo en el que se encontrar en el aeropuerto de lanzarote a el ser preguntar si confiar en volver pronto a el_aaiún este haber ser el único palabra que haber pronunciar haidar quien haber decidir posponer hasta este [J:??/??/??:??.??:??] porque no se sentir con fuerza el declaración que prever realizar el [X:??/??/??:??.??:??] en el aeropuerto_de_lanzarote allí seguir uno huelga de hambre desde hacer TM_d:24 para conseguir su regreso a el_aaiún de donde ser expulsar el [??:14/11/??:??.??:??] en relación con el caso haidar el ministro de justicia marroquí abdelwahed_radi haber decir en madrid que tanto su país como españa ser víctima de persona contrario y hostil a el unidad territorial de marruecos y que haber preferir que haidar haber ser expulsar a otro país",
        "lemmatized_text_reduced": "activista saharaui aminatu_haidar cumplir 20 4 día huelga hambre protesta expulsión marruecos haber asegurar volver el_aaiún vivo morir activista saharaui haber cumplir huelga hambre aeropuerto lanzarote_así contestar haidar ser trasladar baño próximo habitáculo encontrar aeropuerto lanzarote ser preguntar confiar volver el_aaiún haber ser único palabra haber pronunciar haidar haber decidir posponer sentir fuerza declaración prever realizar aeropuerto_de_lanzarote seguir huelga hambre hacer conseguir regreso el_aaiún ser expulsar relación caso haidar ministro justicia marroquí abdelwahed_radi haber decir madrid país españa ser víctima persona contrario hostil unidad territorial marruecos haber preferir haidar haber ser expulsar país",
        "persons": [
            "Aminatu_Haidar",
            "El_Aaiún",
            "Haidar",
            "Haidar",
            "Haidar",
            "Abdelwahed_Radi",
            "España",
            "Haidar"
        ],
        "locations": [
            "Marruecos",
            "Lanzarote_Así",
            "Lanzarote",
            "El_Aaiún",
            "Aeropuerto_de_Lanzarote",
            "El_Aaiún",
            "Madrid",
            "Marruecos"
        ],
        "organizations": [],
        "others": [
            "Justicia"
        ],
        "dates": [
            "[??:14/11/??:??.??:??]",
            "[X:??/??/??:??.??:??]",
            "[J:??/??/??:??.??:??]",
            "[X:??/??/??:??.??:??]",
            "[??:14/11/??:??.??:??]"
        ],
        "numbers": [
            "TM_d:24",
            "TM_d:24"
        ]
    }
}
