{
    "province": "LAS PALMAS",
    "date": "2008-07-05T00:00:00",
    "url": "https://www.20minutos.es/noticia/396204/0/empresario/liberado/venezuela/",
    "title": {
        "raw_text": "Liberado el empresario canario secuestrado el jueves en Venezuela",
        "lemmatized_text": "liberar el empresario canario secuestrar el [J:??/??/??:??.??:??] en venezuela",
        "lemmatized_text_reduced": "liberar empresario canario secuestrar venezuela",
        "persons": [],
        "locations": [
            "Venezuela"
        ],
        "organizations": [],
        "others": [],
        "dates": [
            "[J:??/??/??:??.??:??]"
        ],
        "numbers": []
    },
    "lead": {
        "raw_text": "Se trata del empresario canario Juan Carlos Benítez Armas. Vive en Las Palmas y tiene negocios ferreteros en Venezuela. Fue sorprendido por delincuentes el jueves en su casa de Anaco.",
        "lemmatized_text": "se tratar de el empresario canario juan_carlos_benítez_armas vivir en las_palmas y tener negocio ferretero en venezuela ser sorprender por delincuente el [J:??/??/??:??.??:??] en su casa de anaco",
        "lemmatized_text_reduced": "tratar empresario canario juan_carlos_benítez_armas vivir las_palmas tener negocio ferretero venezuela ser sorprender delincuente casa anaco",
        "persons": [
            "Juan_Carlos_Benítez_Armas"
        ],
        "locations": [
            "Venezuela",
            "Anaco"
        ],
        "organizations": [
            "Las_Palmas"
        ],
        "others": [],
        "dates": [
            "[J:??/??/??:??.??:??]"
        ],
        "numbers": []
    },
    "body": {
        "raw_text": "El empresario canario Juan Carlos Benítez Armas, que fue secuestrado esta semana en Venezuela, ha sido liberado hoy en Caracas y se encuentra en buen estado de salud, según fuentes del Gobierno de Canarias. Benítez Armas fue liberado sobre las cinco de la madrugada (hora de Venezuela) y tras ser sometido a un reconocimiento médico, en el que se determinó su buen estado físico, el empresario descansa ya que durante el secuestro no ha podido dormir. Así lo el director general de Relaciones con América del Gobierno de Canarias, Miguel Ángel Machín, quien dijo haber conocido la noticia de la liberación del empresario canario en conversación telefónica con un primo del secuestrado. La familia de Juan Carlos Benítez Armas viaja desde Madrid a Caracas para encontrarse con el empresario. El Gobierno de Canarias expresó su felicitación por \"el buen desenlace\" del secuestro y se ha puesto a disposición de Juan Carlos Benítez Armas en todo lo que necesite, según destacó el director general de Relaciones con América del Gobierno canario. Juan Carlos Benítez Armas, natural de la isla de El Hierro, fue sorprendido por delincuentes en la madrugada del jueves en su residencia en la ciudad de Anaco, en el estado de Anzóategui, 390 kilómetros al este de Caracas. Poseedor de diversos comercios relacionados con el sector ferretero en Venezuela, pese a que vive en Las Palmas de Gran Canaria, había viajado al país sudamericano el pasado 24 de junio por motivos de negocios y tenía previsto regresar a Canarias el 21 de julio. La familia del empresario canario secuestrado en Venezuela Juan Carlos Benítez Armas no quiso ayer pronunciarse públicamente sobre su situación, de la que tuvo noticia recientemente, aseguraron fuentes de su entorno en Las Palmas de Gran Canaria.",
        "lemmatized_text": "el empresario canario juan_carlos_benítez_armas que ser secuestrar este semana en venezuela haber ser liberar hoy en caracas y se encontrar en bueno estado de salud según fuente de el gobierno_de_canarias benítez_armas ser liberar sobre el [??:??/??/??:5.00:am] hora de venezuela y tras ser someter a uno reconocimiento médico en el que se determinar su bueno estado físico el empresario descansar ya_que durante el secuestro no haber poder dormir así lo el director general de relaciones con américa_del_gobierno_de_canarias miguel_ángel_machín quien decir haber conocer el noticia de el liberación de el empresario canario en conversación telefónico con uno primo de el secuestrar el familia de juan_carlos_benítez_armas viajar desde madrid a caracas para encontrar se con el empresario el gobierno_de_canarias expresar su felicitación por el bueno desenlace de el secuestro y se haber poner a disposición de juan_carlos_benítez_armas en todo el que necesitar según destacar el director general de relaciones con américa_del_gobierno canario juan_carlos_benítez_armas natural de el isla de el_hierro ser sorprender por delincuente en el madrugada de el [J:??/??/??:??.??:??] en su residencia en el ciudad de anaco en el estado de anzóategui LN_km:390 a el este de caracas poseedor de diverso comercio relacionar con el sector ferretero en venezuela pese_a que vivir en las_palmas_de_gran_canaria haber viajar a el país sudamericano el [??:24/6/??:??.??:??] por motivo de negocio y tener prever regresar a canarias el [??:21/7/??:??.??:??] el familia de el empresario canario secuestrar en venezuela_juan_carlos_benítez_armas no querer ayer pronunciar se públicamente sobre su situación de el que tener noticia recientemente asegurar fuente de su entorno en las_palmas_de_gran_canaria",
        "lemmatized_text_reduced": "empresario canario juan_carlos_benítez_armas ser secuestrar semana venezuela haber ser liberar caracas encontrar bueno estado salud fuente gobierno_de_canarias benítez_armas ser liberar hora venezuela ser someter reconocimiento médico determinar bueno estado físico empresario descansar secuestro haber poder dormir director general relaciones américa_del_gobierno_de_canarias miguel_ángel_machín decir haber conocer noticia liberación empresario canario conversación telefónico primo secuestrar familia juan_carlos_benítez_armas viajar madrid caracas encontrar empresario gobierno_de_canarias expresar felicitación bueno desenlace secuestro haber poner disposición juan_carlos_benítez_armas necesitar destacar director general relaciones américa_del_gobierno canario juan_carlos_benítez_armas natural isla el_hierro ser sorprender delincuente madrugada residencia ciudad anaco estado anzóategui caracas poseedor comercio relacionar sector ferretero venezuela vivir las_palmas_de_gran_canaria haber viajar país sudamericano motivo negocio tener prever regresar canarias familia empresario canario secuestrar venezuela_juan_carlos_benítez_armas querer pronunciar públicamente situación tener noticia recientemente asegurar fuente entorno las_palmas_de_gran_canaria",
        "persons": [
            "Juan_Carlos_Benítez_Armas",
            "Benítez_Armas",
            "Miguel_Ángel_Machín",
            "Juan_Carlos_Benítez_Armas",
            "Juan_Carlos_Benítez_Armas",
            "Juan_Carlos_Benítez_Armas"
        ],
        "locations": [
            "Venezuela",
            "Caracas",
            "Venezuela",
            "Madrid",
            "Caracas",
            "El_Hierro",
            "Anaco",
            "Anzóategui",
            "Caracas",
            "Venezuela",
            "Las_Palmas_de_Gran_Canaria",
            "Canarias",
            "Venezuela_Juan_Carlos_Benítez_Armas",
            "Las_Palmas_de_Gran_Canaria"
        ],
        "organizations": [
            "Gobierno_de_Canarias",
            "Relaciones",
            "América_del_Gobierno_de_Canarias",
            "Gobierno_de_Canarias",
            "Relaciones",
            "América_del_Gobierno"
        ],
        "others": [],
        "dates": [
            "[??:??/??/??:5.00:am]",
            "[J:??/??/??:??.??:??]",
            "[??:24/6/??:??.??:??]",
            "[??:21/7/??:??.??:??]"
        ],
        "numbers": [
            "LN_km:390"
        ]
    }
}
