{
    "province": "LAS PALMAS",
    "date": "2010-02-22T00:00:00",
    "url": "https://www.20minutos.es/noticia/635290/0/",
    "title": {
        "raw_text": "El 1-1-2 Canarias recibe cerca de 56.000 llamadas durante los días de la borrasca",
        "lemmatized_text": "el 1-1-2 canarias recibir cerca de 56 llamada durante el día de el borrasca",
        "lemmatized_text_reduced": "canarias recibir llamada día borrasca",
        "persons": [],
        "locations": [
            "Canarias"
        ],
        "organizations": [],
        "others": [],
        "dates": [],
        "numbers": [
            "1-1-2",
            "56"
        ]
    },
    "lead": {
        "raw_text": "Sólo el día 1 de febrero, el Cecoes incrementó su actividad más de un 200%",
        "lemmatized_text": "sólo el [??:1/2/??:??.??:??] el cecoes incrementar su actividad más de uno 200/100",
        "lemmatized_text_reduced": "cecoes incrementar actividad",
        "persons": [],
        "locations": [],
        "organizations": [
            "Cecoes"
        ],
        "others": [],
        "dates": [
            "[??:1/2/??:??.??:??]"
        ],
        "numbers": [
            "200/100"
        ]
    },
    "body": {
        "raw_text": "El Centro Coordinador de Emergencias y Seguridad (Cecoes) 1-1-2, dependiente de la Consejería de Presidencia, Justicia y Seguridad del Gobierno de Canarias, recibió un total de 55.867 llamadas durante los días en que se registraron los principales fenómenos meteorológicos adversos (FMA) del presente mes de febrero en las islas. Esto supuso un incremento medio de la actividad de las Salas Operativas de más del 160 por ciento, siendo el día 1 de febrero el que llegó a registrar una mayor actividad con un crecimiento de más del 200 por ciento, según informó el Ejecutivo regional en un comunicado. Para dar respuesta a esta creciente demanda el Cecoes 1-1-2 reforzó con personal sus Salas Operativas, lo que permitió resolver 7.225 incidentes en todo el archipiélago canario en sólo tres días y atender a 6.518 personas. Del total de estos incidentes, 2.492 correspondieron al día 1, 2.091 al día 17 y 2.642 al 18, siendo los relacionados con la seguridad ciudadana y los clasificados por extinción, salvamento y rescate los que experimentaron un mayor incremento. En este sentido, el día l los servicios relacionados con la seguridad ciudadana alcanzaron los 632, el día 17 sumaron 630 y al día siguiente 707. Por su parte, los servicios clasificados por extinción, salvamento y rescate fueron 954 el primer día del mes de febrero, 690 el día 17 y 1.166 el día siguiente. Respecto al número de personas atendidas en los incidentes producidos el día 1 de febrero el 1-1-2 dio respuesta a 2.023, mientras que los días 17 y 18 se atendieron a 4.495 ciudadanos, de las cuales 1.965 correspondieron a la jornada del 17 y 2.530 a la del 18, fecha en la que el Cecoes registró el mayor número de afectados por este tipo de fenómenos durante el presente mes. Actividad por días En cuanto a la actividad del día 1 de febrero, día en el que la provincia de Santa Cruz de Tenerife y la isla de Gran Canaria se encontraban en situación de alerta por lluvias y tormentas, el 1-1-2 Canarias recibió 22.074 llamadas, 16.039 de ellas en la provincia de Santa Cruz de Tenerife y 6.035 en la de Las Palmas. Sin embargo, el mismo día de la semana anterior, un día de actividad normal sin FMA, el Cecoes recibió 6.824 llamadas en todo el archipiélago lo que supone un incremento en el número de atenciones telefónicas del 223 por ciento. Todas esas llamadas se plasmaron en la atención de 2.492 incidentes, frente a los 1.288 del lunes de la semana anterior. Del total de servicios, 1.573 fueron resueltos en la provincia de Santa Cruz de Tenerife y 919 en la de Las Palmas. Además, la mayor parte de los incidentes atendidos estuvieron relacionados con la seguridad ciudadana, los cuales sumaron 632, y con el sector de extinción, salvamento y rescate que aglutinó 954. El miércoles 17 de febrero, día de comienzo del FMA por lluvia, viento y mal estado de la mar en toda la Comunidad Autónoma, el CECOES 1-1-2 recibió 18.697 llamadas, más del doble de las recibidas el miércoles de la anterior semana lo que supuso un incremento en la actividad del 147 por ciento. De la suma total de llamadas, 11.480 correspondieron a la provincia de Santa Cruz de Tenerife y 7.217 fueron recibidas en la sala operativa de Las Palmas de Gran Canaria. Ese día el 1-1-2 del Gobierno de Canarias resolvió 2.091 incidentes, 987 en la provincia de Santa Cruz de Tenerife y 1.104 en la de Las Palmas, mientras que el miércoles de la semana anterior se atendieron un total de 1.301 servicios. La mayoría de incidentes , De seguridad ciudadana En cuanto a la tipología de los incidentes atendidos, los mayores incrementos se produjeron en los relacionados con la seguridad ciudadana, que pasaron de los 432 de un día normal a los 630 incidentes del día 17, y los referidos a extinción, salvamento y rescate que ascendieron desde los 116 servicios registrados el mismo día de la semana anterior a los 690 el día de comienzo del FMA. Un día después, el 18 de febrero, el Centro Coordinador recibió 15.096 llamadas, frente a las 6.797 atendidas un jueves de actividad normal lo que se traduce en que la atención telefónica creció un 122 por ciento. Además, del cómputo total de llamadas recibidas ese día 8.170 correspondieron a la provincia de Santa Cruz de Tenerife y 6.926 a la de Las Palmas. En relación a los incidentes registrados, el día 18 fueron atendidos 2.642, mientras que el mismo día de la semana anterior se contabilizaron 1.332. Por provincias, la de Santa Cruz de Tenerife sumó 1.278 y la de Las Palmas 1.364. Sin embargo, el jueves de la anterior semana se registraron 593 y 739 respectivamente. Por último, los 707 incidentes clasificados por seguridad ciudadana y los 1.166 relacionados con extinción, salvamento y rescate aglutinaron la mayor parte los servicios atendidos ese día, cifras que superaron ampliamente las registradas en un jueves de actividad normal.",
        "lemmatized_text": "el centro_coordinador_de_emergencias y seguridad cecoes 1-1-2 dependiente de el consejería_de_presidencia justicia y seguridad_del_gobierno_de_canarias recibir uno total de 55.867 llamada durante el día en que se registrar el principal fenómeno meteorológico adverso fma de el [??:??/2/??:??.??:??] en el isla este suponer uno incremento medio de el actividad de el salas_operativas de más de el 160 por 100 ser el [??:1/2/??:??.??:??] el que llegar a registrar uno mayor actividad con uno crecimiento de más de el 200 por 100 según informar el ejecutivo regional en uno comunicado para dar respuesta a este creciente demanda el cecoes 1-1-2 reforzar con personal su salas_operativas el que permitir resolver 7.225 incidente en todo el archipiélago canario en sólo TM_d:3 y atender a 6.518 persona de el total de este incidente 2.492 corresponder a el [??:1/??/??:??.??:??] 2.091 a el [??:17/??/??:??.??:??] y 2.642 a el 18 ser el relacionar con el seguridad ciudadano y el clasificar por extinción salvamento y rescate el que experimentar uno mayor incremento en este sentido el día l el servicio relacionar con el seguridad ciudadano alcanzar el 632 el [??:17/??/??:??.??:??] sumar 630 y a el día siguiente 707 por su parte el servicio clasificar por extinción salvamento y rescate ser 954 el 1 día de el [??:??/2/??:??.??:??] 690 el [??:17/??/??:??.??:??] y 1.166 el día siguiente respecto a el número de persona atender en el incidente producir el [??:1/2/??:??.??:??] el 1-1-2 dar respuesta a 2.023 mientras_que el día 17 y 18 se atender a 4.495 ciudadano de el cual 1.965 corresponder a el jornada de el 17 y 2.53 a el de el 18 fecha en el que el cecoes registrar el mayor número de afectado por este tipo de fenómeno durante el presente mes actividad por día en_cuanto_a el actividad de el [??:1/2/??:??.??:??] día en el que el provincia de santa_cruz_de_tenerife y el isla de gran_canaria se encontrar en situación de alerta por lluvia y tormenta el 1-1-2 canarias recibir 22.074 llamada 16.039 de ellos en el provincia de santa_cruz_de_tenerife y 6.035 en el de las_palmas sin embargo el mismo día de el semana anterior uno día de actividad normal sin fma el cecoes recibir 6.824 llamada en todo el archipiélago el que suponer uno incremento en el número de atención telefónico de el 223 por 100 todo ese llamada se plasmar en el atención de 2.492 incidente frente_a el [L:??/??/??:1.00:??] de el semana anterior de el total de servicio 1.573 ser resolver en el provincia de santa_cruz_de_tenerife y 919 en el de las_palmas además el mayor parte de el incidente atender estar relacionar con el seguridad ciudadano el cual sumar 632 y con el sector de extinción salvamento y rescate que aglutinar 954 el [X:17/2/??:??.??:??] día de comienzo de el fma por lluvia viento y mal estar de el mar en todo el comunidad_autónoma el cecoes 1-1-2 recibir 18.697 llamada más de el doble de el recibir el [X:??/??/??:??.??:??] de el anterior semana el que suponer uno incremento en el actividad de el 147 por 100 de el suma total de llamada 11.48 corresponder a el provincia de santa_cruz_de_tenerife y 7.217 ser recibir en el sala operativo de las_palmas_de_gran_canaria ese día el 1-1-2 de el gobierno_de_canarias resolver 2.091 incidente 987 en el provincia de santa_cruz_de_tenerife y 1.104 en el de las_palmas mientras_que el [X:??/??/??:??.??:??] de el semana anterior se atender uno total de 1.301 servicio el mayoría de incidente de seguridad ciudadano en_cuanto_a el tipología de el incidente atender el mayor incremento se producir en el relacionar con el seguridad ciudadano que pasar de el 432 de uno día normal a el 630 incidente de el [??:17/??/??:??.??:??] y el referir a extinción salvamento y rescate que ascender desde el 116 servicio registrar el mismo día de el semana anterior a el 690 el día de comienzo de el fma uno día después el [??:18/2/??:??.??:??] el centro_coordinador recibir 15.096 llamada frente_a el 6.797 atender uno [J:??/??/??:??.??:??] de actividad normal el que se traducir en que el atención telefónico crecer uno 122 por 100 además de el cómputo total de llamada recibir ese [??:8/??/??:??.??:??] corresponder a el provincia de santa_cruz_de_tenerife y 6.926 a el de las_palmas en relación a el incidente registrar el [??:18/??/??:??.??:??] ser atender 2.642 mientras_que el mismo día de el semana anterior se contabilizar 1.332 por provincia el de santa_cruz_de_tenerife sumar 1.278 y el de las_palmas 1.364 sin embargo el [J:??/??/??:??.??:??] de el anterior semana se registrar 593 y 739 respectivamente por último el 707 incidente clasificar por seguridad ciudadano y el 1.166 relacionar con extinción salvamento y rescate aglutinar el mayor parte el servicio atender ese día cifra que superar ampliamente el registrar en uno [J:??/??/??:??.??:??] de actividad normal",
        "lemmatized_text_reduced": "centro_coordinador_de_emergencias seguridad cecoes dependiente consejería_de_presidencia justicia seguridad_del_gobierno_de_canarias recibir total llamada día registrar principal fenómeno meteorológico adverso fma isla suponer incremento medio actividad salas_operativas ser llegar registrar mayor actividad crecimiento informar ejecutivo regional comunicado dar respuesta creciente demanda cecoes reforzar personal salas_operativas permitir resolver incidente archipiélago canario atender persona total incidente corresponder ser relacionar seguridad ciudadano clasificar extinción salvamento rescate experimentar mayor incremento sentido día l servicio relacionar seguridad ciudadano alcanzar sumar día siguiente parte servicio clasificar extinción salvamento rescate ser 1 día día siguiente respecto número persona atender incidente producir dar respuesta día atender ciudadano corresponder jornada fecha cecoes registrar mayor número afectado tipo fenómeno presente mes actividad día en_cuanto_a actividad día provincia santa_cruz_de_tenerife isla gran_canaria encontrar situación alerta lluvia tormenta canarias recibir llamada provincia santa_cruz_de_tenerife las_palmas embargo mismo día semana anterior día actividad normal fma cecoes recibir llamada archipiélago suponer incremento número atención telefónico llamada plasmar atención incidente semana anterior total servicio ser resolver provincia santa_cruz_de_tenerife las_palmas mayor parte incidente atender estar relacionar seguridad ciudadano sumar sector extinción salvamento rescate aglutinar día comienzo fma lluvia viento estar mar comunidad_autónoma cecoes recibir llamada doble recibir anterior semana suponer incremento actividad suma total llamada corresponder provincia santa_cruz_de_tenerife ser recibir sala operativo las_palmas_de_gran_canaria día gobierno_de_canarias resolver incidente provincia santa_cruz_de_tenerife las_palmas semana anterior atender total servicio mayoría incidente de seguridad ciudadano en_cuanto_a tipología incidente atender mayor incremento producir relacionar seguridad ciudadano pasar día normal incidente referir extinción salvamento rescate ascender servicio registrar mismo día semana anterior día comienzo fma día centro_coordinador recibir llamada atender actividad normal traducir atención telefónico crecer cómputo total llamada recibir corresponder provincia santa_cruz_de_tenerife las_palmas relación incidente registrar ser atender mismo día semana anterior contabilizar provincia santa_cruz_de_tenerife sumar las_palmas embargo anterior semana registrar respectivamente último incidente clasificar seguridad ciudadano relacionar extinción salvamento rescate aglutinar mayor parte servicio atender día cifra superar ampliamente registrar actividad normal",
        "persons": [
            "Salas_Operativas",
            "De",
            "En_cuanto_a"
        ],
        "locations": [
            "Santa_Cruz_de_Tenerife",
            "Gran_Canaria",
            "Canarias",
            "Santa_Cruz_de_Tenerife",
            "Las_Palmas",
            "Santa_Cruz_de_Tenerife",
            "Las_Palmas",
            "Santa_Cruz_de_Tenerife",
            "Las_Palmas_de_Gran_Canaria",
            "Santa_Cruz_de_Tenerife",
            "Las_Palmas",
            "Santa_Cruz_de_Tenerife",
            "Las_Palmas",
            "Santa_Cruz_de_Tenerife"
        ],
        "organizations": [
            "Centro_Coordinador_de_Emergencias",
            "Cecoes",
            "Consejería_de_Presidencia",
            "Justicia",
            "Seguridad_del_Gobierno_de_Canarias",
            "Ejecutivo",
            "Cecoes",
            "Cecoes",
            "En_cuanto_a",
            "FMA",
            "Cecoes",
            "FMA",
            "Comunidad_Autónoma",
            "CECOES",
            "Gobierno_de_Canarias",
            "FMA",
            "Centro_Coordinador",
            "Las_Palmas"
        ],
        "others": [
            "Seguridad",
            "FMA",
            "Salas_Operativas"
        ],
        "dates": [
            "[??:??/2/??:??.??:??]",
            "[??:1/2/??:??.??:??]",
            "[??:1/??/??:??.??:??]",
            "[??:17/??/??:??.??:??]",
            "[??:17/??/??:??.??:??]",
            "[??:??/2/??:??.??:??]",
            "[??:17/??/??:??.??:??]",
            "[??:1/2/??:??.??:??]",
            "[??:1/2/??:??.??:??]",
            "[L:??/??/??:1.00:??]",
            "[X:17/2/??:??.??:??]",
            "[X:??/??/??:??.??:??]",
            "[X:??/??/??:??.??:??]",
            "[??:17/??/??:??.??:??]",
            "[??:18/2/??:??.??:??]",
            "[J:??/??/??:??.??:??]",
            "[??:8/??/??:??.??:??]",
            "[??:18/??/??:??.??:??]",
            "[J:??/??/??:??.??:??]",
            "[J:??/??/??:??.??:??]"
        ],
        "numbers": [
            "1-1-2",
            "55.867",
            "160",
            "100",
            "200",
            "100",
            "1-1-2",
            "7.225",
            "TM_d:3",
            "6.518",
            "2.492",
            "2.091",
            "2.642",
            "18",
            "632",
            "630",
            "707",
            "954",
            "690",
            "1.166",
            "1-1-2",
            "2.023",
            "17",
            "18",
            "4.495",
            "1.965",
            "17",
            "2.53",
            "18",
            "1-1-2",
            "22.074",
            "16.039",
            "6.035",
            "6.824",
            "223",
            "100",
            "2.492",
            "1.573",
            "919",
            "632",
            "954",
            "1-1-2",
            "18.697",
            "147",
            "100",
            "11.48",
            "7.217",
            "1-1-2",
            "2.091",
            "987",
            "1.104",
            "1.301",
            "432",
            "630",
            "116",
            "690",
            "15.096",
            "6.797",
            "122",
            "100",
            "6.926",
            "2.642",
            "1.332",
            "1.278",
            "1.364",
            "593",
            "739",
            "707",
            "1.166"
        ]
    }
}
