{
    "province": "LAS PALMAS",
    "date": "2010-02-22T00:00:00",
    "url": "https://www.20minutos.es/noticia/635187/0/",
    "title": {
        "raw_text": "Martín atribuye el aumento de la llegada de turistas a Canarias a las campañas de promoción en Europa",
        "lemmatized_text": "martín atribuir el aumento de el llegada de turista a canarias a el campaña de promoción en europa",
        "lemmatized_text_reduced": "martín atribuir aumento llegada turista canarias campaña promoción europa",
        "persons": [
            "Martín"
        ],
        "locations": [
            "Canarias",
            "Europa"
        ],
        "organizations": [],
        "others": [],
        "dates": [],
        "numbers": []
    },
    "lead": {
        "raw_text": "La consejera de Turismo del Gobierno de Canarias, Rita Martín, valoró hoy \"positivamente\" el hecho de que, por primera vez desde hace meses, el archipiélago lidere la llegada de turistas extranjeros a España con cifras, que según ella, \"se mantienen prácticamente estables, gracias, a la intensificación de las campañas de promoción en Europa y a la respuesta de países como Alemania, que en este mes de enero de 2010 han tenido un comportamiento muy positivo\".",
        "lemmatized_text": "el consejero de turismo_del_gobierno_de_canarias rita_martín valorar hoy positivamente el hecho de que por 1 vez desde hacer mes el archipiélago liderar el llegada de turista extranjero a españa con cifra que según él se mantener prácticamente estable gracia a el intensificación de el campaña de promoción en europa y a el respuesta de país como alemania que en este [??:??/1/2010:??.??:??] haber tener uno comportamiento muy positivo",
        "lemmatized_text_reduced": "consejero turismo_del_gobierno_de_canarias rita_martín valorar positivamente hecho 1 vez hacer mes archipiélago liderar llegada turista extranjero españa cifra mantener prácticamente estable gracia intensificación campaña promoción europa respuesta país alemania haber tener comportamiento positivo",
        "persons": [
            "Rita_Martín",
            "España"
        ],
        "locations": [
            "Europa",
            "Alemania"
        ],
        "organizations": [
            "Turismo_del_Gobierno_de_Canarias"
        ],
        "others": [],
        "dates": [
            "[??:??/1/2010:??.??:??]"
        ],
        "numbers": []
    },
    "body": {
        "raw_text": "En este sentido, la consejera regional de Turismo destaca en un comunicado la importancia de empezar el año con cifras positivas fruto, entre otras cosas, de las campañas de promoción que lleva a cabo su departamento \"Ya estamos viendo los resultados de nuestra campaña 'Compartimos nuestra fortuna' que está en marcha en el norte de Europa. Considero que estamos consiguiendo nuestro objetivo que no es otro sino el de seguir siendo líderes en esta temporada de invierno\", añadió Martín. El Ejecutivo regional explica que Canarias ha comenzado el presente año 2010 con un incremento en la entrada de turistas extranjeros de un 1,73 por ciento, lo que permite que el descenso en la entrada de turistas extranjeros y nacionales sea de tan sólo un -0,05 por ciento. Así, según datos de Frontur Canarias, elaborados por el Instituto Canario de Estadística (Istac) y el Instituto de Estudios Turísticos (Iet), facilitados por el Gobierno autonómico, las islas recibieron en enero de 2010 la visita de 893.338 turistas, de los que 795.789 son extranjeros, procedentes de aeropuertos, con un incremento respecto al mismo período del año anterior de un 1,73 por ciento. En lo que respecta a los residentes en el resto de España, el archipiélago recibió la visita de 97.549 turistas, con un descenso del 11,80 por ciento. Oferta diferenciada Martín se mostró optimista ante estos datos aunque precisó que \"hay que seguir trabajando muy duro para conseguir que las islas continúen siendo un destino turístico líder\". \"Sin lugar a dudas, nuestra oferta diferenciada basada en los cuatro productos turísticos: náutico, familiar, de salud y de volcanes está llegando a los potenciales turistas que están descubriendo las múltiples posibilidades que ofrecen las Islas teniendo además la seguridad y la cercanía como valores añadidos\", agregó. El departamento de Turismo informó de que Gran Canaria ha recibido 254.479 turistas extranjeros, 678 residentes en España; Lanzarote, 122.800 turistas extranjeros, 51.533 residentes en España; Fuerteventura, 107.124 turistas extranjeros, 744 residentes en España; Tenerife, 286.989 turistas extranjeros, 118 residentes en España; y La Palma ha sido visitada por 14.739 turistas extranjeros, 911 residentes en el territorio español.",
        "lemmatized_text": "en este sentido el consejero regional de turismo destacar en uno comunicado el importancia de empezar el año con cifra positivo fruto entre otro cosa de el campaña de promoción que llevar_a_cabo su departamento ya estar ver el resultado de nuestro campaña compartir nuestro fortuna que estar en marcha en el norte de europa considerar que estar conseguir nuestro objetivo que no ser otro sino el de seguir ser líder en este temporada de invierno añadir martín el ejecutivo regional explicar que canarias haber comenzar el [??:??/??/2010:??.??:??] con uno incremento en el entrada de turista extranjero de uno 1,73 por 100 el que permitir que el descenso en el entrada de turista extranjero y nacional ser de tan sólo uno -0,05 por 100 así según dato de frontur_canarias elaborar por el instituto_canario_de_estadística istac y el instituto_de_estudios_turísticos iet facilitar por el gobierno autonómico el isla recibir en [??:??/1/2010:??.??:??] el visita de 893.338 turista de el que 795.789 ser extranjero procedente de aeropuerto con uno incremento respecto a el mismo período de el año anterior de uno 1,73 por 100 en el que respectar a el residente en el resto de españa el archipiélago recibir el visita de 97.549 turista con uno descenso de el 11,80 por 100 oferta diferenciar martín se mostrar optimista ante este dato aunque precisar que haber que seguir trabajar muy duro para conseguir que el isla continuar ser uno destino turístico líder sin_lugar_a_dudas nuestro oferta diferenciar basar en el 4 producto turístico náutico familiar de salud y de volcán estar llegar a el potencial turista que estar descubrir el múltiple posibilidad que ofrecer el islas tener además el seguridad y el cercanía como valor añadir agregar el departamento de turismo informar de que gran_canaria haber recibir 254.479 turista extranjero 678 residente en españa lanzarote 122.8 turista extranjero 51.533 residente en españa fuerteventura 107.124 turista extranjero 744 residente en españa tenerife 286.989 turista extranjero 118 residente en españa y la_palma haber ser visitar por 14.739 turista extranjero 911 residente en el territorio español",
        "lemmatized_text_reduced": "sentido consejero regional turismo destacar comunicado importancia empezar año cifra positivo fruto cosa campaña promoción llevar_a_cabo departamento estar ver resultado campaña compartir fortuna estar marcha norte europa considerar estar conseguir objetivo ser seguir ser líder temporada invierno añadir martín ejecutivo regional explicar canarias haber comenzar incremento entrada turista extranjero permitir descenso entrada turista extranjero nacional ser dato frontur_canarias elaborar instituto_canario_de_estadística istac instituto_de_estudios_turísticos iet facilitar gobierno autonómico isla recibir visita turista ser extranjero procedente aeropuerto incremento respecto mismo período año anterior respectar residente resto españa archipiélago recibir visita turista descenso oferta diferenciar martín mostrar optimista dato precisar haber seguir trabajar duro conseguir isla continuar ser destino turístico líder oferta diferenciar basar producto turístico náutico familiar salud volcán estar llegar potencial turista estar descubrir múltiple posibilidad ofrecer islas tener seguridad cercanía valor añadir agregar departamento turismo informar gran_canaria haber recibir turista extranjero residente españa lanzarote turista extranjero residente españa fuerteventura turista extranjero residente españa tenerife turista extranjero residente españa la_palma haber ser visitar turista extranjero residente territorio español",
        "persons": [
            "Martín",
            "Frontur_Canarias",
            "Martín"
        ],
        "locations": [
            "Europa",
            "Canarias",
            "España",
            "España",
            "Lanzarote",
            "España",
            "España",
            "Tenerife",
            "España",
            "La_Palma"
        ],
        "organizations": [
            "Ejecutivo",
            "Instituto_Canario_de_Estadística",
            "Istac",
            "Instituto_de_Estudios_Turísticos",
            "Iet",
            "Gobierno",
            "Islas",
            "Turismo",
            "Gran_Canaria",
            "Fuerteventura"
        ],
        "others": [
            "Turismo"
        ],
        "dates": [
            "[??:??/??/2010:??.??:??]",
            "[??:??/1/2010:??.??:??]"
        ],
        "numbers": [
            "1,73",
            "100",
            "-0,05",
            "100",
            "893.338",
            "795.789",
            "1,73",
            "100",
            "97.549",
            "11,80",
            "100",
            "4",
            "254.479",
            "678",
            "122.8",
            "51.533",
            "107.124",
            "744",
            "286.989",
            "118",
            "14.739",
            "911"
        ]
    }
}
