{
    "province": "LAS PALMAS",
    "date": "2010-05-04T00:00:00",
    "url": "https://www.20minutos.es/noticia/696202/0/",
    "title": {
        "raw_text": "El precio del plátano canario sube un 3,09% en abril pero se desploma un 16% interanual",
        "lemmatized_text": "el precio de el plátano canario subir uno 3,09/100 en [??:??/4/??:??.??:??] pero se desplomar uno 16/100 interanual",
        "lemmatized_text_reduced": "precio plátano canario subir desplomar interanual",
        "persons": [],
        "locations": [],
        "organizations": [],
        "others": [],
        "dates": [
            "[??:??/4/??:??.??:??]"
        ],
        "numbers": [
            "3,09/100",
            "16/100"
        ]
    },
    "lead": {
        "raw_text": "Preparar una ensalada es hasta un 11% más caro en abril por la subida de tomates, cebollas y lechuga",
        "lemmatized_text": "preparar uno ensalada ser hasta uno 11/100 más caro en [??:??/4/??:??.??:??] por el subida de tomate cebolla y lechuga",
        "lemmatized_text_reduced": "preparar ensalada ser caro subida tomate cebolla lechuga",
        "persons": [],
        "locations": [],
        "organizations": [],
        "others": [],
        "dates": [
            "[??:??/4/??:??.??:??]"
        ],
        "numbers": [
            "11/100"
        ]
    },
    "body": {
        "raw_text": "El precio del plátano de Canarias ha subido un 3,09 por ciento en abril, aunque en términos interanuales se ha desplomado un 16,08 por ciento, según datos difundidos hoy por el Ministerio de Industria, Turismo y Comercio. De esta forma, los plátanos de Canarias lideraron el 'ranking' de productos alimenticios que más bajaron de precio en interanual, seguido de la merluza (-10,44%), la leche esterilizada (-8,79%) y el aceite de girasol refinado (-8,15%). En concreto, el precio del plátano canario se situó de media el pasado mes en los 1,67 euros el kilo, aunque ha llegado en abril a marcar un mínimo de 1,24 euros el kilo. Mientras, otros productos como tomates, cebollas y lechugas se han encarecido, lo que en abril hizo que preparar una ensalada fuera hasta un 11% más caro que en el mes anterior. En concreto, los tomates para ensalada se encarecieron un 11,27% en el cuarto mes del año respecto a marzo, las lechugas, un 9,47%, y las cebollas, un 4,67%. Otros alimentos frescos que también subieron en abril en tasa mensual fueron los pimientos verdes (+14,81%) y los plátanos de Canarias (+3,09%). Por el contrario, el precio de las judías verdes bajó un 7,18% respecto a marzo, seguido de la bacaladilla (-3,38%) y los limones (-3,13%). El departamento que dirige Miguel Sebastián destacó, por otro lado, la estabilidad registrada en los precios de los alimentos envasados. En términos mensuales, se abarató el aceite de oliva (-1,75%), la mantequilla (-1,66%), la harina de trigo (-1,37%) el pan de molde de trigo (-1,24%) y la leche esterilizada (-1,19%), frente al encarecimiento de los refrescos de cola (+0,85%) y las gambas congeladas (+0,30%). En tasa interanual, los plátanos de Canarias, la merluza, la leche esterilizada y el aceite de girasol refinado fueron los alimentos que más se abarataron en abril, con descensos de precios que oscilaron entre el 8% y el 16%. Otros alimentos frescos que también experimentaron descensos significativos fueron las peras de agua, con una reducción del 8,02%, y la carne de pollo fresca y los gallos, que se abarataron un 7,79% y un 7,31%, respectivamente. Por contra, en abril se encarecieron las lechugas, con una subida interanual del precio del 18,18%, así como los limomes (+10,71%), los pimientos verdes (+6,90%), el salmón (+6,08%) y las naranjas (+5,97%). En cuanto a los productos envasados, además de la leche esterilizada y el aceite de girasol refinado, experimentaron bajadas de precios significativas en abril el azúcar (-6,67%), la mantequilla (-6,32%) y el yogurt (-6,19%). Por contra, se encareció el tomate natural (+5,56%) y, en menor medida, los refrescos de cola (+1,72%).",
        "lemmatized_text": "el precio de el plátano de canarias haber subir uno 3,09 por 100 en [??:??/4/??:??.??:??] aunque en término interanual se haber desplomar uno 16,08 por 100 según dato difundir hoy por el ministerio_de_industria turismo y comercio de este forma el plátano de canarias liderar el ranking de producto alimenticio que más bajar de precio en interanual seguir de el merluza -10,44/100 el leche esterilizar -8,79/100 y el aceite de girasol refinar -8,15/100 en concreto el precio de el plátano canario se situar de medio el pasar mes en el $_ECU:1,67 el kilo aunque haber llegar en [??:??/4/??:??.??:??] a marcar uno mínimo de $_ECU:1,24 el kilo mientras otro producto como tomate cebolla y lechuga se haber encarecer el que en [??:??/4/??:??.??:??] hacer que preparar uno ensalada fuera hasta uno 11/100 más caro que en el mes anterior en concreto el tomate para ensalada se encarecer uno 11,27/100 en el 4 mes de el año respecto_a [??:??/3/??:??.??:??] el lechuga uno 9,47/100 y el cebolla uno 4,67/100 otro alimento fresco que también subir en [??:??/4/??:??.??:??] en tasa mensual ser el pimiento verde +14,81/100 y el plátano de canarias +3,09/100 por_el_contrario el precio de el judía verde bajar uno 7,18/100 respecto_a [??:??/3/??:??.??:??] seguir de el bacaladilla -3,38/100 y el limón -3,13/100 el departamento que dirigir miguel_sebastián destacar por_otro_lado el estabilidad registrar en el precio de el alimento envasar en término mensual se abaratar el aceite de oliva -1,75/100 el mantequilla -1,66/100 el harina de trigo -1,37/100 el pan de molde de trigo -1,24/100 y el leche esterilizar -1,19/100 frente a el encarecimiento de el refresco de cola +0,85/100 y el gamba congelar +0,30/100 en tasa interanual el plátano de canarias el merluza el leche esterilizar y el aceite de girasol refinar ser el alimento que más se abaratar en [??:??/4/??:??.??:??] con descenso de precio que oscilar entre el 8/100 y el 16/100 otro alimento fresco que también experimentar descenso significativo ser el pera de agua con uno reducción de el 8,02/100 y el carne de pollo fresco y el gallo que se abaratar uno 7,79/100 y uno 7,31/100 respectivamente por contra en [??:??/4/??:??.??:??] se encarecer el lechuga con uno subida interanual de el precio de el 18,18/100 así_como el limomes +10,71/100 el pimiento verde +6,90/100 el salmón +6,08/100 y el naranja +5,97/100 en_cuanto_a el producto envasar además_de el leche esterilizar y el aceite de girasol refinar experimentar bajar de precio significativo en [??:??/4/??:??.??:??] el azúcar -6,67/100 el mantequilla -6,32/100 y el yogur -6,19/100 por contra se encarecer el tomate natural +5,56/100 y en menor medida el refresco de cola +1,72/100",
        "lemmatized_text_reduced": "precio plátano canarias haber subir término interanual haber desplomar dato difundir ministerio_de_industria turismo comercio forma plátano canarias liderar ranking producto alimenticio bajar precio interanual seguir merluza leche esterilizar aceite girasol refinar concreto precio plátano canario situar medio pasar mes kilo haber llegar marcar mínimo kilo producto tomate cebolla lechuga haber encarecer hacer preparar ensalada caro mes anterior concreto tomate ensalada encarecer 4 mes año lechuga cebolla alimento fresco subir tasa mensual ser pimiento verde plátano canarias precio judía verde bajar seguir bacaladilla limón departamento dirigir miguel_sebastián destacar estabilidad registrar precio alimento envasar término mensual abaratar aceite oliva mantequilla harina trigo pan molde trigo leche esterilizar encarecimiento refresco cola gamba congelar tasa interanual plátano canarias merluza leche esterilizar aceite girasol refinar ser alimento abaratar descenso precio oscilar alimento fresco experimentar descenso significativo ser pera agua reducción carne pollo fresco gallo abaratar respectivamente encarecer lechuga subida interanual precio limomes pimiento verde salmón naranja producto envasar leche esterilizar aceite girasol refinar experimentar bajar precio significativo azúcar mantequilla yogur encarecer tomate natural menor medida refresco cola",
        "persons": [
            "Miguel_Sebastián"
        ],
        "locations": [
            "Canarias",
            "Canarias",
            "Canarias",
            "Canarias"
        ],
        "organizations": [
            "Ministerio_de_Industria",
            "Turismo",
            "Comercio"
        ],
        "others": [],
        "dates": [
            "[??:??/4/??:??.??:??]",
            "[??:??/4/??:??.??:??]",
            "[??:??/4/??:??.??:??]",
            "[??:??/3/??:??.??:??]",
            "[??:??/4/??:??.??:??]",
            "[??:??/3/??:??.??:??]",
            "[??:??/4/??:??.??:??]",
            "[??:??/4/??:??.??:??]",
            "[??:??/4/??:??.??:??]"
        ],
        "numbers": [
            "3,09",
            "100",
            "16,08",
            "100",
            "-10,44/100",
            "-8,79/100",
            "-8,15/100",
            "$_ECU:1,67",
            "$_ECU:1,24",
            "11/100",
            "11,27/100",
            "9,47/100",
            "4,67/100",
            "+14,81/100",
            "+3,09/100",
            "7,18/100",
            "-3,38/100",
            "-3,13/100",
            "-1,75/100",
            "-1,66/100",
            "-1,37/100",
            "-1,24/100",
            "-1,19/100",
            "+0,85/100",
            "+0,30/100",
            "8/100",
            "16/100",
            "8,02/100",
            "7,79/100",
            "7,31/100",
            "18,18/100",
            "+10,71/100",
            "+6,90/100",
            "+6,08/100",
            "+5,97/100",
            "-6,67/100",
            "-6,32/100",
            "-6,19/100",
            "+5,56/100",
            "+1,72/100"
        ]
    }
}
