{
    "province": "LAS PALMAS",
    "date": "2010-05-04T00:00:00",
    "url": "https://www.20minutos.es/noticia/695978/0/",
    "title": {
        "raw_text": "El número de afiliados a la Seguridad Social en Canarias cae un 3,56% en abril, situándose en los 683.990 cotizantes",
        "lemmatized_text": "el número de afiliado a el seguridad_social en canarias caer uno 3,56/100 en [??:??/4/??:??.??:??] situar se en el 683.99 cotizante",
        "lemmatized_text_reduced": "número afiliado seguridad_social canarias caer situar cotizante",
        "persons": [],
        "locations": [
            "Canarias"
        ],
        "organizations": [],
        "others": [
            "Seguridad_Social"
        ],
        "dates": [
            "[??:??/4/??:??.??:??]"
        ],
        "numbers": [
            "3,56/100",
            "683.99"
        ]
    },
    "lead": {
        "raw_text": "El número de afiliados a la Seguridad Social en Canarias cayó un 3,56 por ciento en abril con respecto al mismo mes del pasado año, por lo que se situó en los 683.990 cotizantes en el archipiélago, según los datos difundidos hoy por el Ministerio de Trabajo e Inmigración.",
        "lemmatized_text": "el número de afiliado a el seguridad_social en canarias caer uno 3,56 por 100 en [??:??/4/??:??.??:??] con respecto a el mismo mes de el pasar año por el que se situar en el 683.99 cotizante en el archipiélago según el dato difundir hoy por el ministerio_de_trabajo y inmigración",
        "lemmatized_text_reduced": "número afiliado seguridad_social canarias caer respecto mismo mes pasar año situar cotizante archipiélago dato difundir ministerio_de_trabajo inmigración",
        "persons": [],
        "locations": [
            "Canarias"
        ],
        "organizations": [
            "Ministerio_de_Trabajo",
            "Inmigración"
        ],
        "others": [
            "Seguridad_Social"
        ],
        "dates": [
            "[??:??/4/??:??.??:??]"
        ],
        "numbers": [
            "3,56",
            "100",
            "683.99"
        ]
    },
    "body": {
        "raw_text": "Este caída interanual del 3,56 por ciento en el archipiélago, ha supuesto 25.269 afiliados menos. Asimismo, con respecto a marzo de este mismo año, Canarias perdió en abril 2.294 cotizantes (-0,33%). Por provincias, el mayor descenso interanual de afiliados al Sistema se produjo en Santa Cruz de Tenerife, con una caída del 4,03 por ciento, lo que ha supuesto la pérdida de 13.626 cotizantes, fijando el número de afiliados en la actualidad en 324.166. En este sentido, en la provincia de Las Palmas el descenso fue de un 3,13 por ciento, lo que ha implicado 11.643 afiliados menos aunque se mantiene en los 359.824 cotizantes en abril de 2010. Por otro lado, en el conjunto de Canarias fue el Régimen General el que englobó a un mayor número de afiliados al Sistema, en concreto, 550.102; seguido de los Autónomos que se situaron en 105.441; el Régimen Agrario con 15.424; los Empleados del Hogar con 7.555 cotizantes; y finalmente los Trabajo de Mar con 5.469. El número de afiliados crece en el conjunto nacional En lo que respecta al conjunto nacional, la Seguridad Social ganó 53.852 afiliados (+0,31%) en el mes de abril, con lo que el total de ocupados se situó al finalizar el mes pasado en 17.648.660 cotizantes. Este aumento es el tercero que encadena la afiliación a la Seguridad Social tras los 26.000 nuevos cotizantes que ganó en febrero, y los más de 22.000 de marzo. En el último año, el sistema ha perdido 385.523 afiliados, un 2,14 por ciento menos. Trabajo destacó que esta tasa contrasta con la caída interanual del 6,83 por ciento que se experimentó hace un año, \"lo que revela una importante moderación en la pérdida de afiliados\" con respecto a abril de 2009. El secretario de Estado de la Seguridad Social, Octavio Granado, subrayó en un comunicado que el dato de abril demuestra que el sistema está dejando \"ya muy atrás\" las cifras \"más duras del ajuste\". Por segundo mes consecutivo, el Régimen Especial de Trabajadores Autónomos (RETA) incrementó su número de afiliados en abril, esta vez en 2.764 personas (+0,09%). También subió la afiliación en el Régimen General, que ganó 64.022 cotizantes en el mes (+0,48%); en el Régimen del Hogar, que experimentó un repunte de 1.872 afiliados (+0,64%), y el Régimen del Mar, con 648 nuevos ocupados (+1%). Por su parte, el Régimen Especial Agrario perdió 15.390 cotizantes (-1,8%) y el del Carbón 65 ocupados (-0,9%). Con el repunte de afiliados de abril, el Régimen General sitúa su número de cotizantes en 13.319.739 ocupados, 306.228 menos que un año atrás (-2,25%), mientras que el Régimen de Autónomos suma un total de 3.137.430 ocupados, acumulando una pérdida de 107.096 afiliados en el último año (-3,3%). Dentro del Régimen General, la evolución de la afiliación en abril fue, en general, positiva, con pocos descensos. La mayor caída fue de nuevo para la de la industria manufacturera, que perdió 7.575 cotizantes (-0,41%), seguida de la administración pública (-3.855 afiliados). Entre los ascensos, el mayor se lo anotó la hostelería, que ganó 43.175 afiliados en el mes (+4,7%), seguido de las actividades sanitarias y los servicios sociales, con 8.644 cotizantes más (+0,64%). Sube en ambos sexos y entre los extranjeros En abril, la afiliación masculina subió en 15.060 personas (+0,15%), mientras que la ocupación femenina se incrementó más del doble, con 38.793 nuevas cotizantes mujeres (+0,49%). En total, al finalizar el mes pasado estaban afiliadas a la Seguridad Social una media de 7.914.407 mujeres, mientras que los hombres sumaban 9.734.254 afiliados, con caídas interanuales del 0,46 por ciento y del 3,46 por ciento, respectivamente. Por su parte, la afiliación media de trabajadores extranjeros encadenó en abril su tercer aumento mensual consecutivo al ganar 22.139 ocupados (+1,2%), hasta un total de 1.850.369 ocupados. De ellos, 1.212.531 cotizaban al Régimen General, 252.611 al Agrario, 197.412 al de Autónomos, 181.881 al del Hogar, 5.205 al del Mar y 730 al del Carbón. La afiliación descendió en abril en seis comunidades autónomas, especialmente en Comunidad Valenciana (-5.796 ocupados) y Aragón (-2.999 cotizantes), y subió en el resto de regiones, principalmente en Andalucía y Baleares, donde se ganaron 21.547 y 20.177 ocupados, respectivamente.",
        "lemmatized_text": "este caída interanual de el 3,56 por 100 en el archipiélago haber suponer 25.269 afiliado menos asimismo con_respecto_a [??:??/3/??:??.??:??] de este mismo año canarias perder en [??:??/4/??:??.??:??] 2.294 cotizante -0,33/100 por provincia el mayor descenso interanual de afiliado a el sistema se producir en santa_cruz_de_tenerife con uno caída de el 4,03 por 100 el que haber suponer el pérdida de 13.626 cotizante fijar el número de afiliado en el actualidad en 324.166 en este sentido en el provincia de las_palmas el descenso ser de uno 3,13 por 100 el que haber implicar 11.643 afiliado menos aunque se mantener en el 359.824 cotizante en [??:??/4/2010:??.??:??] por_otro_lado en el conjunto de canarias ser el régimen_general el que englobar a uno mayor número de afiliado a el sistema en concreto 550.102 seguir de el autónomos que se situar en 105.441 el régimen_agrario con 15.424 el empleados_del_hogar con 7.555 cotizante y finalmente el trabajo_de_mar con 5.469 el número de afiliado crecer en el conjunto nacional en el que respectar a el conjunto nacional el seguridad_social ganar 53.852 afiliado +0,31/100 en el [??:??/4/??:??.??:??] con el que el total de ocupar se situar a el finalizar el mes pasar en 17.648.660 cotizante este aumento ser el 3 que encadenar el afiliación a el seguridad_social tras el 26 nuevo cotizante que ganar en [??:??/2/??:??.??:??] y el más de [??:22/3/??:??.??:??] en el último año el sistema haber perder 385.523 afiliado uno 2,14 por 100 menos trabajo destacar que este tasa contrastar con el caída interanual de el 6,83 por 100 que se experimentar hacer uno año el que revelar uno importante moderación en el pérdida de afiliado con_respecto_a [??:??/4/2009:??.??:??] el secretario de estado_de_la_seguridad_social octavio_granado subrayar en uno comunicado que el dato de [??:??/4/??:??.??:??] demostrar que el sistema estar dejar ya muy atrás el cifra más duro de el ajuste por 2 mes consecutivo el régimen_especial_de_trabajadores_autónomos reta incrementar su número de afiliado en [??:??/4/??:??.??:??] este vez en 2.764 persona +0,09/100 también subir el afiliación en el régimen_general que ganar 64.022 cotizante en el mes +0,48/100 en el régimen_del_hogar que experimentar uno repunte de 1.872 afiliado +0,64/100 y el régimen_del_mar con 648 nuevo ocupar +1/100 por su parte el régimen_especial_agrario perder 15.39 cotizante -1,8/100 y el de el carbón 65 ocupar -0,9/100 con el repunte de afiliado de [??:??/4/??:??.??:??] el régimen_general situar su número de cotizante en 13.319.739 ocupar 306.228 menos que uno año atrás -2,25/100 mientras_que el régimen_de_autónomos sumar uno total de 3.137.430 ocupar acumular uno pérdida de 107.096 afiliado en el último año -3,3/100 dentro de el régimen_general el evolución de el afiliación en [??:??/4/??:??.??:??] ser en general positivo con poco descenso el mayor caída ser de nuevo para el de el industria manufacturero que perder 7.575 cotizante -0,41/100 seguir de el administración público -3.855 afiliado entre el ascenso el mayor se lo anotar el hostelería que ganar 43.175 afiliado en el mes +4,7/100 seguir de el actividad sanitario y el servicio social con 8.644 cotizante más +0,64/100 subir en ambos sexo y entre el extranjero en [??:??/4/??:??.??:??] el afiliación masculino subir en 15.06 persona +0,15/100 mientras_que el ocupación femenino se incrementar más de el doble con 38.793 nuevo cotizante mujer +0,49/100 en total a el finalizar el mes pasar estar afiliar a el seguridad_social uno media de 7.914.407 mujer mientras_que el hombre sumar 9.734.254 afiliado con caída interanual de el 0,46 por 100 y de el 3,46 por 100 respectivamente por su parte el afiliación medio de trabajador extranjero encadenar en [??:??/4/??:??.??:??] su 3 aumento mensual consecutivo a el ganar 22.139 ocupar +1,2/100 hasta uno total de 1.850.369 ocupar de ellos 1.212.531 cotizar a el régimen_general 252.611 a el agrario 197.412 a el de autónomos 181.881 a el de el hogar 5.205 a el de el mar y 730 a el de el carbón el afiliación descender en [??:??/4/??:??.??:??] en 6 comunidad autónomo especialmente en comunidad_valenciana -5.796 ocupar y aragón -2.999 cotizante y subir en el resto de región principalmente en andalucía y baleares donde se ganar 21.547 y 20.177 ocupar respectivamente",
        "lemmatized_text_reduced": "caída interanual archipiélago haber suponer afiliado mismo año canarias perder cotizante provincia mayor descenso interanual afiliado sistema producir santa_cruz_de_tenerife caída haber suponer pérdida cotizante fijar número afiliado actualidad sentido provincia las_palmas descenso ser haber implicar afiliado mantener cotizante conjunto canarias ser régimen_general englobar mayor número afiliado sistema concreto seguir autónomos situar régimen_agrario empleados_del_hogar cotizante finalmente trabajo_de_mar número afiliado crecer conjunto nacional en respectar conjunto nacional seguridad_social ganar afiliado total ocupar situar finalizar mes pasar cotizante aumento ser 3 encadenar afiliación seguridad_social nuevo cotizante ganar último año sistema haber perder afiliado trabajo destacar tasa contrastar caída interanual experimentar hacer año revelar importante moderación pérdida afiliado secretario estado_de_la_seguridad_social octavio_granado subrayar comunicado dato demostrar sistema estar dejar cifra duro ajuste 2 mes consecutivo régimen_especial_de_trabajadores_autónomos reta incrementar número afiliado vez persona subir afiliación régimen_general ganar cotizante mes régimen_del_hogar experimentar repunte afiliado régimen_del_mar nuevo ocupar parte régimen_especial_agrario perder cotizante carbón ocupar repunte afiliado régimen_general situar número cotizante ocupar año régimen_de_autónomos sumar total ocupar acumular pérdida afiliado último año régimen_general evolución afiliación ser general positivo descenso mayor caída ser nuevo industria manufacturero perder cotizante seguir administración público afiliado ascenso mayor anotar hostelería ganar afiliado mes seguir actividad sanitario servicio social cotizante subir sexo extranjero en afiliación masculino subir persona ocupación femenino incrementar doble nuevo cotizante mujer total finalizar mes pasar estar afiliar seguridad_social media mujer hombre sumar afiliado caída interanual respectivamente parte afiliación medio trabajador extranjero encadenar 3 aumento mensual consecutivo ganar ocupar total ocupar cotizar régimen_general agrario autónomos hogar mar carbón afiliación descender comunidad autónomo especialmente comunidad_valenciana ocupar aragón cotizante subir resto región principalmente andalucía baleares ganar ocupar respectivamente",
        "persons": [
            "Octavio_Granado",
            "En"
        ],
        "locations": [
            "Canarias",
            "Santa_Cruz_de_Tenerife",
            "Las_Palmas",
            "Canarias",
            "Autónomos",
            "Mar",
            "Carbón",
            "Comunidad_Valenciana",
            "Aragón",
            "Andalucía",
            "Baleares"
        ],
        "organizations": [
            "Sistema",
            "Régimen_General",
            "Sistema",
            "Autónomos",
            "Régimen_Agrario",
            "Empleados_del_Hogar",
            "Trabajo_de_Mar",
            "En",
            "Trabajo",
            "Estado_de_la_Seguridad_Social",
            "Régimen_Especial_de_Trabajadores_Autónomos",
            "RETA",
            "Régimen_General",
            "Régimen_del_Hogar",
            "Régimen_del_Mar",
            "Régimen_Especial_Agrario",
            "Régimen_General",
            "Régimen_de_Autónomos",
            "Régimen_General",
            "Régimen_General",
            "Agrario",
            "Hogar"
        ],
        "others": [
            "Seguridad_Social",
            "Seguridad_Social",
            "Carbón",
            "Seguridad_Social"
        ],
        "dates": [
            "[??:??/3/??:??.??:??]",
            "[??:??/4/??:??.??:??]",
            "[??:??/4/2010:??.??:??]",
            "[??:??/4/??:??.??:??]",
            "[??:??/2/??:??.??:??]",
            "[??:22/3/??:??.??:??]",
            "[??:??/4/2009:??.??:??]",
            "[??:??/4/??:??.??:??]",
            "[??:??/4/??:??.??:??]",
            "[??:??/4/??:??.??:??]",
            "[??:??/4/??:??.??:??]",
            "[??:??/4/??:??.??:??]",
            "[??:??/4/??:??.??:??]",
            "[??:??/4/??:??.??:??]"
        ],
        "numbers": [
            "3,56",
            "100",
            "25.269",
            "2.294",
            "-0,33/100",
            "4,03",
            "100",
            "13.626",
            "324.166",
            "3,13",
            "100",
            "11.643",
            "359.824",
            "550.102",
            "105.441",
            "15.424",
            "7.555",
            "5.469",
            "53.852",
            "+0,31/100",
            "17.648.660",
            "26",
            "385.523",
            "2,14",
            "100",
            "6,83",
            "100",
            "2.764",
            "+0,09/100",
            "64.022",
            "+0,48/100",
            "1.872",
            "+0,64/100",
            "648",
            "+1/100",
            "15.39",
            "-1,8/100",
            "65",
            "-0,9/100",
            "13.319.739",
            "306.228",
            "-2,25/100",
            "3.137.430",
            "107.096",
            "-3,3/100",
            "7.575",
            "-0,41/100",
            "-3.855",
            "43.175",
            "+4,7/100",
            "8.644",
            "+0,64/100",
            "15.06",
            "+0,15/100",
            "38.793",
            "+0,49/100",
            "7.914.407",
            "9.734.254",
            "0,46",
            "100",
            "3,46",
            "100",
            "22.139",
            "+1,2/100",
            "1.850.369",
            "1.212.531",
            "252.611",
            "197.412",
            "181.881",
            "5.205",
            "730",
            "6",
            "-5.796",
            "-2.999",
            "21.547",
            "20.177"
        ]
    }
}
