{
    "province": "LAS PALMAS",
    "date": "2010-05-04T00:00:00",
    "url": "https://www.20minutos.es/noticia/695975/0/",
    "title": {
        "raw_text": "Canarias lidera la subida del paro en abril con un aumento del 1,72% y 4.508 nuevos desempleados",
        "lemmatized_text": "canario liderar el subida de el paro en [??:??/4/??:??.??:??] con uno aumento de el 1,72/100 y 4.508 nuevo desempleado",
        "lemmatized_text_reduced": "canario liderar subida paro aumento nuevo desempleado",
        "persons": [],
        "locations": [],
        "organizations": [],
        "others": [],
        "dates": [
            "[??:??/4/??:??.??:??]"
        ],
        "numbers": [
            "1,72/100",
            "4.508"
        ]
    },
    "lead": {
        "raw_text": "El paro en Canarias se situó en abril en las 266.042 personas, lo que supone un aumento del 1,72 por ciento y la incorporación de 4.508 nuevos al desempleo, según informó hoy el Ministerio de Trabajo e Inmigración, que confirmó así los datos filtrados el pasado fin de semana.",
        "lemmatized_text": "el paro en canarias se situar en [??:??/4/??:??.??:??] en el 266.042 persona el que suponer uno aumento de el 1,72 por 100 y el incorporación de 4.508 nuevo a el desempleo según informar hoy el ministerio_de_trabajo y inmigración que confirmar así el dato filtrar el pasar fin de semana",
        "lemmatized_text_reduced": "paro canarias situar persona suponer aumento incorporación nuevo desempleo informar ministerio_de_trabajo inmigración confirmar dato filtrar pasar fin semana",
        "persons": [],
        "locations": [
            "Canarias"
        ],
        "organizations": [
            "Ministerio_de_Trabajo",
            "Inmigración"
        ],
        "others": [],
        "dates": [
            "[??:??/4/??:??.??:??]"
        ],
        "numbers": [
            "266.042",
            "1,72",
            "100",
            "4.508"
        ]
    },
    "body": {
        "raw_text": "De esta forma Canarias lidera el aumento del paro entre las comunidades autónomas y sólo tienen un índice superior de aumento del desempleo las ciudades autónomas de Ceuta (+4%) y Melilla (+2,04%). Además, el archipiélago canario contraviene así la tendencia marcada este mes por el conjunto de la economía, donde el desempleo se redujo en 24.188 personas, un 0,6% menos que en marzo, y su primer descenso en nueve meses. En términos interanuales, el paro en las islas Canarias aumentó un 7,93 por ciento y exactamente hay 19.542 parados más en abril de 2010 que en el mismo mes del pasado ejercicio. El paro extranjero en Canarias aumentó en 464 personas, un 1,73 por ciento más, hasta los 27.303 individuos, mientras que en dato interanual el aumento es mayor, del 2,89 por ciento y 767 personas más. Del total de extranjeros parados en Canarias 8.136 son de países comunitarios y 19.167 de fuera de la Unión Europea (UE). Por provincias el mayor aumento relativo del paro se lo anota la de Las Palmas, con un 1,96 por ciento más y 2.790 nuevos parados hasta un total de 144.959 personas en las listas del desempleo. Respecto a abril de 2009 el aumento es del 6,40 por ciento y 8.725 personas. En la provincia occidental, el desempleo alcanzó en abril las 121.083 personas tras registrar un aumento de 1.718 nuevos parados, un 1,44 por ciento más. En términos interanuales el aumento es del 9,81 por ciento y 10.817 personas. Sector servicios y construcción los peores El reparto por género es de 131.433 parados varones y 134.609 mujeres. La mayoría de los parados están en el sector servicios (174.048), seguido de la construcción (53.190), los que no tenían empleo anterior sumaban 22.235, 11.824 de la industria y 4.745 del sector agrario. En el conjunto de España, el volumen total de desempleados se situó en las 4.142.425 personas con una reducción de parados que contrasta con el incremento de 39.478 desempleados que se experimentó en igual mes de 2009. En los últimos doce meses, el paro ha aumentado en 497.545 desempleados, un 13,6% más, de los que 244.239 son varones y 253.306 mujeres, con incrementos relativos del 13,2% y del 14%, respectivamente. La secretaria general de Empleo, Maravillas Rojo, destacó en un comunicado el \"buen dato\" que ha registrado el paro en abril, lo que, a su juicio, indica que \"se está frenando la destrucción de empleo\" y que \"paulatinamente\" los datos del desempleo se van aproximando a las cifras mensuales anteriores a la crisis. Sube sólo en las mujeres y desciende en el 'LADRILLO'. El descenso del paro en abril correspondió exclusivamente a los varones, ya que entre las mujeres se incrementó el desempleo. En concreto, en abril se registraron con 1.332 nuevas paradas respecto a marzo (+0,06%), frente a una caída del desempleo masculino de 25.520 hombres (-1,2%). Así, al finalizar abril, el número de mujeres en paro sumaba 2.054.380, mientras que el de varones desempleados era de 2.088.045. Por sectores, la construcción volvió a arrojar un dato positivo al reducir su cifra de parados por segundo mes consecutivo, con 15.535 desempleados menos (-1,9%). También bajó el desempleo en el sector servicios, donde hubo 13.740 parados menos (-0,5%), y en la industria, con 6.046 desempleados menos (-1,1%). Por el contrario, el paro repuntó en abril en el colectivo sin empleo anterior, que sumó 7.133 parados más (+2,2%), y en la agricultura, con 4.020 nuevos desempleados (+3,3%). Por edades, el desempleo de los jóvenes menores de 25 años bajó en abril en 6.246 personas, el 1,3% menos, frente a un descenso del paro entre los mayores de 25 años de 17.942 personas (-0,5%). Baja el paro en trece comunidades . El recorte del paro se nota también entre la población extranjera, que en abril experimentó un descenso del 0,5% en su cifra de parados, con 3.401 desempleados menos. En total, los inmigrantes en paro sumaban al finalizar el mes pasado 612.919 desempleados, con un repunte de 112.902 parados (+22,6%) respecto a un año atrás. En abril, el paro bajó en trece comunidades autónomas, especialmente en Cataluña (-10.382 parados), Andalucía (-4.086 desempleados) y Baleares (-3.861 parados), y subió en las cuatro restantes, encabezadas por Canarias y Comunidad Valenciana, que registraron 4.508 y 3.233 parados más, respectivamente. Por provincias, el paro bajó en 34 de ellas, especialmente en Barcelona (-7.191 desempleados), Cádiz (-3.956 desempleados) y Baleares, y se incrementó en las 18 restantes, lideradas por Jaén (3.340 desempleados más) y Las Palmas (2.790 parados más).",
        "lemmatized_text": "de este forma canarias liderar el aumento de el paro entre el comunidad autónomo y sólo tener uno índice superior de aumento de el desempleo el ciudad autónomo de ceuta +4/100 y melilla +2,04/100 además el archipiélago canario contravenir así el tendencia marcar este mes por el conjunto de el economía donde el desempleo se reducir en 24.188 persona uno 0,6/100 menos que en [??:??/3/??:??.??:??] y su 1 descenso en 9 mes en término interanual el paro en el isla canarias aumentar uno 7,93 por 100 y exactamente haber 19.542 parado más en [??:??/4/2010:??.??:??] que en el mismo mes de el pasar ejercicio el paro extranjero en canarias aumentar en 464 persona uno 1,73 por 100 más hasta el 27.303 individuo mientras_que en dato interanual el aumento ser mayor de el 2,89 por 100 y 767 persona más de el total de extranjero parado en canarias 8.136 ser de país comunitario y 19.167 de fuera_de el unión_europea ue por provincia el mayor aumento relativo de el paro se lo anotar el de las_palmas con uno 1,96 por 100 más y 2.79 nuevo parado hasta uno total de 144.959 persona en el lista de el desempleo respecto_a [??:??/4/2009:??.??:??] el aumento ser de el 6,40 por 100 y 8.725 persona en el provincia occidental el desempleo alcanzar en [??:??/4/??:??.??:??] el 121.083 persona tras registrar uno aumento de 1.718 nuevo parado uno 1,44 por 100 más en término interanual el aumento ser de el 9,81 por 100 y 10.817 persona sector servicio y construcción el peor el reparto por género ser de 131.433 parado varón y 134.609 mujer el mayoría de el parado estar en el sector servicio 174.048 seguir de el construcción 53.19 el que no tener empleo anterior sumar 22.235 11.824 de el industria y 4.745 de el sector agrario en el conjunto de españa el volumen total de desempleado se situar en el 4.142.425 persona con uno reducción de parado que contrastar con el incremento de 39.478 desempleado que se experimentar en igual mes de 2009 en el último 12 mes el paro haber aumentar en 497.545 desempleado uno 13,6/100 más de el que 244.239 ser varón y 253.306 mujer con incremento relativo de el 13,2/100 y de el 14/100 respectivamente el secretario general de empleo maravillas_rojo destacar en uno comunicado el bueno dato que haber registrar el paro en [??:??/4/??:??.??:??] el que a su juicio indicar que se estar frenar el destrucción de empleo y que paulatinamente el dato de el desempleo se ir aproximar a el cifra mensual anterior a el crisis subir sólo en el mujer y descender en el ladrillo el descenso de el paro en [??:??/4/??:??.??:??] corresponder exclusivamente a el varón ya_que entre el mujer se incrementar el desempleo en concreto en [??:??/4/??:??.??:??] se registrar con 1.332 nuevo parada respecto_a [??:??/3/??:??.??:??] +0,06/100 frente_a uno caída de el desempleo masculino de 25.52 hombre -1,2/100 así a el finalizar [??:??/4/??:??.??:??] el número de mujer en paro sumar 2.054.380 mientras_que el de varón desempleado ser de 2.088.045 por sector el construcción volver a arrojar uno dato positivo a el reducir su cifra de parado por 2 mes consecutivo con 15.535 desempleado menos -1,9/100 también bajar el desempleo en el sector servicio donde haber 13.74 parado menos -0,5/100 y en el industria con 6.046 desempleado menos -1,1/100 por_el_contrario el paro repuntar en [??:??/4/??:??.??:??] en el colectivo sin empleo anterior que sumar 7.133 parado más +2,2/100 y en el agricultura con 4.02 nuevo desempleado +3,3/100 por edad el desempleo de el joven menor de 25 año bajar en [??:??/4/??:??.??:??] en 6.246 persona el 1,3/100 menos frente_a uno descenso de el paro entre el mayor de 25 año de 17.942 persona -0,5/100 bajar el paro en 13 comunidad el recorte de el paro se notar también entre el población extranjero que en [??:??/4/??:??.??:??] experimentar uno descenso de el 0,5/100 en su cifra de parado con 3.401 desempleado menos en total el inmigrante en paro sumar a el finalizar el mes pasar 612.919 desempleado con uno repunte de 112.902 parado +22,6/100 respecto_a uno año atrás en [??:??/4/??:??.??:??] el paro bajar en 13 comunidad autónomo especialmente en cataluña -10.382 parado andalucía -4.086 desempleado y baleares -3.861 parado y subir en el 4 restante encabezar por canarias y comunidad_valenciana que registrar 4.508 y 3.233 parado más respectivamente por provincia el paro bajar en 34 de ellos especialmente en barcelona -7.191 desempleado cádiz -3.956 desempleado y baleares y se incrementar en el 18 restante liderar por jaén 3.34 desempleado más y las_palmas 2.79 parado más",
        "lemmatized_text_reduced": "forma canarias liderar aumento paro comunidad autónomo tener índice superior aumento desempleo ciudad autónomo ceuta melilla archipiélago canario contravenir tendencia marcar mes conjunto economía desempleo reducir persona 1 descenso mes término interanual paro isla canarias aumentar exactamente haber parado mismo mes pasar ejercicio paro extranjero canarias aumentar persona individuo dato interanual aumento ser mayor persona total extranjero parado canarias ser país comunitario unión_europea ue provincia mayor aumento relativo paro anotar las_palmas nuevo parado total persona lista desempleo aumento ser persona provincia occidental desempleo alcanzar persona registrar aumento nuevo parado término interanual aumento ser persona sector servicio construcción peor el reparto género ser parado varón mujer mayoría parado estar sector servicio seguir construcción tener empleo anterior sumar industria sector agrario conjunto españa volumen total desempleado situar persona reducción parado contrastar incremento desempleado experimentar igual mes último mes paro haber aumentar desempleado ser varón mujer incremento relativo respectivamente secretario general empleo maravillas_rojo destacar comunicado bueno dato haber registrar paro juicio indicar estar frenar destrucción empleo paulatinamente dato desempleo ir aproximar cifra mensual anterior crisis subir mujer descender ladrillo descenso paro corresponder exclusivamente varón mujer incrementar desempleo concreto registrar nuevo parada caída desempleo masculino hombre finalizar número mujer paro sumar varón desempleado ser sector construcción volver arrojar dato positivo reducir cifra parado 2 mes consecutivo desempleado bajar desempleo sector servicio haber parado industria desempleado paro repuntar colectivo empleo anterior sumar parado agricultura nuevo desempleado edad desempleo joven menor año bajar persona descenso paro mayor año persona bajar paro comunidad recorte paro notar población extranjero experimentar descenso cifra parado desempleado total inmigrante paro sumar finalizar mes pasar desempleado repunte parado año paro bajar comunidad autónomo especialmente cataluña parado andalucía desempleado baleares parado subir restante encabezar canarias comunidad_valenciana registrar parado respectivamente provincia paro bajar especialmente barcelona desempleado cádiz desempleado baleares incrementar restante liderar jaén desempleado las_palmas parado",
        "persons": [
            "Sector",
            "Maravillas_Rojo"
        ],
        "locations": [
            "Canarias",
            "Ceuta",
            "Melilla",
            "Canarias",
            "Canarias",
            "Canarias",
            "España",
            "Cataluña",
            "Andalucía",
            "Baleares",
            "Canarias",
            "Comunidad_Valenciana",
            "Barcelona",
            "Cádiz",
            "Baleares",
            "Jaén"
        ],
        "organizations": [
            "Unión_Europea",
            "UE",
            "Las_Palmas",
            "Empleo",
            "Las_Palmas"
        ],
        "others": [
            "El"
        ],
        "dates": [
            "[??:??/3/??:??.??:??]",
            "[??:??/4/2010:??.??:??]",
            "[??:??/4/2009:??.??:??]",
            "[??:??/4/??:??.??:??]",
            "[??:??/4/??:??.??:??]",
            "[??:??/4/??:??.??:??]",
            "[??:??/4/??:??.??:??]",
            "[??:??/3/??:??.??:??]",
            "[??:??/4/??:??.??:??]",
            "[??:??/4/??:??.??:??]",
            "[??:??/4/??:??.??:??]",
            "[??:??/4/??:??.??:??]",
            "[??:??/4/??:??.??:??]"
        ],
        "numbers": [
            "+4/100",
            "+2,04/100",
            "24.188",
            "0,6/100",
            "9",
            "7,93",
            "100",
            "19.542",
            "464",
            "1,73",
            "100",
            "27.303",
            "2,89",
            "100",
            "767",
            "8.136",
            "19.167",
            "1,96",
            "100",
            "2.79",
            "144.959",
            "6,40",
            "100",
            "8.725",
            "121.083",
            "1.718",
            "1,44",
            "100",
            "9,81",
            "100",
            "10.817",
            "131.433",
            "134.609",
            "174.048",
            "53.19",
            "22.235",
            "11.824",
            "4.745",
            "4.142.425",
            "39.478",
            "2009",
            "12",
            "497.545",
            "13,6/100",
            "244.239",
            "253.306",
            "13,2/100",
            "14/100",
            "1.332",
            "+0,06/100",
            "25.52",
            "-1,2/100",
            "2.054.380",
            "2.088.045",
            "15.535",
            "-1,9/100",
            "13.74",
            "-0,5/100",
            "6.046",
            "-1,1/100",
            "7.133",
            "+2,2/100",
            "4.02",
            "+3,3/100",
            "25",
            "6.246",
            "1,3/100",
            "25",
            "17.942",
            "-0,5/100",
            "13",
            "0,5/100",
            "3.401",
            "612.919",
            "112.902",
            "+22,6/100",
            "13",
            "-10.382",
            "-4.086",
            "-3.861",
            "4",
            "4.508",
            "3.233",
            "34",
            "-7.191",
            "-3.956",
            "18",
            "3.34",
            "2.79"
        ]
    }
}
