{
    "province": "LAS PALMAS",
    "date": "2009-07-07T00:00:00",
    "url": "https://www.20minutos.es/noticia/477629/0/turismo/extranjero/gran-canaria/",
    "title": {
        "raw_text": "El turismo extranjero desciende en Gran Canaria un 19% en lo que va de verano",
        "lemmatized_text": "el turismo extranjero descender en gran_canaria uno 19/100 en el que ir de verano",
        "lemmatized_text_reduced": "turismo extranjero descender gran_canaria ir verano",
        "persons": [],
        "locations": [
            "Gran_Canaria"
        ],
        "organizations": [],
        "others": [],
        "dates": [],
        "numbers": [
            "19/100"
        ]
    },
    "lead": {
        "raw_text": "Se prevé que el turismo nacional caiga en torno a un 10%. Los datos responden a la media acumulada de mayo y junio. CONSULTA AQUÍ MÁS NOTICIAS DE LAS PALMAS .",
        "lemmatized_text": "se prever que el turismo nacional caer en_torno_a uno 10/100 el dato responder a el media acumular de [??:??/5/??:??.??:??] y [??:??/6/??:??.??:??] consulta_aquí_más_noticias_de_las_palmas",
        "lemmatized_text_reduced": "prever turismo nacional caer dato responder media acumular consulta_aquí_más_noticias_de_las_palmas",
        "persons": [],
        "locations": [],
        "organizations": [
            "CONSULTA_AQUÍ_MÁS_NOTICIAS_DE_LAS_PALMAS"
        ],
        "others": [],
        "dates": [
            "[??:??/5/??:??.??:??]",
            "[??:??/6/??:??.??:??]"
        ],
        "numbers": [
            "10/100"
        ]
    },
    "body": {
        "raw_text": "El consejero de Turismo del Cabildo de Gran Canaria, Roberto Moreno, anunció este martes que el turismo extranjero ha descendido en Gran Canaria un 19% , mientras que el nacional se prevé que caiga en torno a un 10% de forma acumulada, durante mayo y junio de este año. Moreno apuntó que estos datos responden a la media acumulada de mayo y junio, y destacó que el descenso del turismo nacional \"es mucho más moderado \" que el extranjero. De todos modos, indicó que \"es obvio\" que se está atravesando por el \"peor verano de la historia del turismo en Canarias y en Gran Canaria\". En lo que respecta a los mercados, señaló que la isla de Gran Canaria continúa con la tendencia de hace unos meses y centrada en el \"mantenimiento o pequeña subida\" de turistas de los países nórdicos , como Dinamarca, Finlandia o Suecia, que \"especialmente se están comportando muy bien\". Respecto a los mercados emergentes, destacó los viajeros procedentes de Europa del Este porque ha habido un \"crecimiento de turistas\" de Polonia o República Checa. Sin embargo, subrayó que \"es la caída casi en picado del mercado británico , no sólo hacia Gran Canaria, sino a toda Canarias, el que está tirando hacia abajo de las medias y de las estadísticas\".",
        "lemmatized_text": "el consejero de turismo_del_cabildo_de_gran_canaria roberto_moreno anunciar este [M:??/??/??:??.??:??] que el turismo extranjero haber descender en gran_canaria uno 19/100 mientras_que el nacional se prever que caer en_torno_a uno 10/100 de forma acumular durante [??:??/5/??:??.??:??] y [??:??/6/??:??.??:??] de este año moreno apuntar que este dato responder a el media acumular de [??:??/5/??:??.??:??] y [??:??/6/??:??.??:??] y destacar que el descenso de el turismo nacional ser mucho más moderar que el extranjero de_todos_modos indicar que ser obvio que se estar atravesar por el peor verano de el historia de el turismo en canarias y en gran_canaria en el que respectar a el mercado señalar que el isla de gran_canaria continuar con el tendencia de hacer uno mes y centrar en el mantenimiento o pequeño subida de turista de el país nórdico como dinamarca finlandia o suecia que especialmente se estar comportar muy bien respecto_a el mercado emergente destacar el viajero procedente de europa_del_este porque haber haber uno crecimiento de turista de polonia o república_checa sin embargo subrayar que ser el caída casi en picado de el mercado británico no_sólo hacia gran_canaria sino a todo canarias el que estar tirar hacia abajo de el media y de el estadística",
        "lemmatized_text_reduced": "consejero turismo_del_cabildo_de_gran_canaria roberto_moreno anunciar turismo extranjero haber descender gran_canaria nacional prever caer forma acumular año moreno apuntar dato responder media acumular destacar descenso turismo nacional ser moderar extranjero indicar ser obvio estar atravesar peor verano historia turismo canarias gran_canaria respectar mercado señalar isla gran_canaria continuar tendencia hacer mes centrar mantenimiento pequeño subida turista país nórdico dinamarca finlandia suecia especialmente estar comportar mercado emergente destacar viajero procedente europa_del_este haber haber crecimiento turista polonia república_checa embargo subrayar ser caída picado mercado británico gran_canaria canarias estar tirar media estadística",
        "persons": [
            "Roberto_Moreno"
        ],
        "locations": [
            "Gran_Canaria",
            "Canarias",
            "Gran_Canaria",
            "Gran_Canaria",
            "Dinamarca",
            "Finlandia",
            "Suecia",
            "Europa_del_Este",
            "República_Checa",
            "Gran_Canaria",
            "Canarias"
        ],
        "organizations": [
            "Polonia"
        ],
        "others": [
            "Turismo_del_Cabildo_de_Gran_Canaria"
        ],
        "dates": [
            "[M:??/??/??:??.??:??]",
            "[??:??/5/??:??.??:??]",
            "[??:??/6/??:??.??:??]",
            "[??:??/5/??:??.??:??]",
            "[??:??/6/??:??.??:??]"
        ],
        "numbers": [
            "19/100",
            "10/100"
        ]
    }
}
