{
    "province": "LAS PALMAS",
    "date": "2008-07-11T00:00:00",
    "url": "https://www.20minutos.es/noticia/398115/0/",
    "title": {
        "raw_text": "Canarias registra en junio la mayor subida de precios de España",
        "lemmatized_text": "canario registrar en [??:??/6/??:??.??:??] el mayor subida de precio de españa",
        "lemmatized_text_reduced": "canario registrar mayor subida precio españa",
        "persons": [],
        "locations": [
            "España"
        ],
        "organizations": [],
        "others": [],
        "dates": [
            "[??:??/6/??:??.??:??]"
        ],
        "numbers": []
    },
    "lead": {
        "raw_text": "Transporte, bebidas alcohólicas y tabaco, son lo que más ha subido. En Canarias sólo bajaron los precios del vestido y el calzado. CONSULTA AQUÍ MÁS NOTICIAS DE LAS PALMAS.",
        "lemmatized_text": "transporte bebida alcohólico y tabaco ser el que más haber subir en canarias sólo bajar el precio de el vestir y el calzado consulta_aquí_más_noticias_de_las_palmas",
        "lemmatized_text_reduced": "transporte bebida alcohólico tabaco ser haber subir canarias bajar precio vestir calzado consulta_aquí_más_noticias_de_las_palmas",
        "persons": [
            "Transporte"
        ],
        "locations": [
            "Canarias"
        ],
        "organizations": [
            "CONSULTA_AQUÍ_MÁS_NOTICIAS_DE_LAS_PALMAS"
        ],
        "others": [],
        "dates": [],
        "numbers": []
    },
    "body": {
        "raw_text": "El IPC subió en Canarias un 0,8 por ciento, la mayor subida de las autonomías españolas, y su tasa interanual se situó en el 5,4 por ciento, sólo superada por Castilla La Mancha con un 5,6, según datos difundidos hoy por el Instituto Nacional de Estadística. El Índice subió en el conjunto del estado un 0,6 por ciento y la tasa interanual nacional se situó cuatro décimas por debajo de la canaria, en el 5 por ciento, la más alta desde 1995. En lo que va de año , el IPC ha subido en Canarias un 3 por ciento , dos décimas por encima del conjunto de España, que se situó en el 2,8 por ciento. Así, el IPC se alcanzó en junio en 108,2, lo que implica que lo que se compraba con 100 euros en 2006, dos años después cuesta 8,2 euros más en Canarias y 8,3 más en toda España Todos los epígrafes subieron en el archipiélag o salvo los vestidos y el calzado , que bajaron un 0,7 por ciento. La mayor subida la registró, con diferencia, el transporte , que alcanzó un aumento del 3,2 por ciento seguido de las bebidas alcohólicas y el tabaco que subieron un 0,9 por ciento. Un 0,6 por ciento aumentaron los alimentos y bebidas no alcohólicas, un 0,4 los hoteles y cafés, un 0,3 el ocio y la cultura, el menaje un 0,2 por ciento y un 0,1 los medicamentos y la vivienda, mientras las comunicaciones se mantuvieron estables. La mayor subida en lo que va de año es para el transporte, con un aumento del 8,6 por ciento, y también en los últimos doce meses, pues alcanza el 12,3 por ciento. La alimentación ha subido en el último año un 9,1 por ciento y la vivienda un 4,2 por ciento . Por provincias, tanto Las Palmas como Santa Cruz de Tenerife registraron un aumento del IPC del 0,8 por ciento, aunque la segunda tiene un índice de 108,6 y la primera de 107,7, que es el precio de los productos en junio de 2008 frente a los cien euros que costaban en el año base, establecido en 2006. Las Palmas acumula en lo que va de año un incremento del IPC del 2,9 por ciento y en los últimos doce meses del 5,2 por ciento, mientras Santa Cruz de Tenerife suma hasta junio 3,1 y en el último año un 5,5 por ciento. El Ministerio de Economía y Hacienda destacó que el repunte en la tasa interanual del IPC del mes de junio se ha debido al \"notable incremento\" de los precios del barril de petróleo en los mercados internacionales, con una subida del 86% en el último año, así como a la subida de los precios de los alimentos frescos, que podrían haberse visto afectados por el paro del transporte y el amarre de la flota pesquera que se produjeron ese mes.",
        "lemmatized_text": "el ipc subir en canarias uno 0,8 por 100 el mayor subida de el autonomía español y su tasa interanual se situar en el 5,4 por 100 sólo superar por castilla_la_mancha con uno 5,6 según dato difundir hoy por el instituto_nacional_de_estadística el índice subir en el conjunto de el estado uno 0,6 por 100 y el tasa interanual nacional se situar 4 décima por debajo_de el canario en el 5 por 100 el más alto desde 1995 en el que ir de año el ipc haber subir en canarias uno 3 por 100 2 décima por encima de el conjunto de españa que se situar en el 2,8 por 100 así el ipc se alcanzar en [??:??/6/??:??.??:??] en 108,2 el que implicar que el que se comprar con $_ECU:100 en 2006 2 año después costar $_ECU:8,2 más en canarias y 8,3 más en todo españa_todos el epígrafe subir en el archipiélag o salvo el vestido y el calzado que bajar uno 0,7 por 100 el mayor subida lo registrar con diferencia el transporte que alcanzar uno aumento de el 3,2 por 100 seguir de el bebida alcohólico y el tabaco que subir uno 0,9 por 100 uno 0,6 por 100 aumentar el alimento y bebida no alcohólico uno 0,4 el hotel y café uno 0,3 el ocio y el cultura el menaje uno 0,2 por 100 y uno 0,1 el medicamento y el vivienda mientras el comunicación se mantener estable el mayor subida en el que ir de año ser para el transporte con uno aumento de el 8,6 por 100 y también en el último 12 mes pues alcanzar el 12,3 por 100 el alimentación haber subir en el último año uno 9,1 por 100 y el vivienda uno 4,2 por 100 por provincia tanto las_palmas como santa_cruz_de_tenerife registrar uno aumento de el ipc de el 0,8 por 100 aunque el 2 tener uno índice de 108,6 y el 1 de 107,7 que ser el precio de el producto en [??:??/6/2008:??.??:??] frente_a el $_ECU:100 que costar en el año base establecer en 2006 el palmas acumular en el que ir de año uno incremento de el ipc de el 2,9 por 100 y en el último 12 mes de el 5,2 por 100 mientras santa_cruz_de_tenerife sumar hasta [??:??/6/??:??.??:??] 3,1 y en el último año uno 5,5 por 100 el ministerio_de_economía y hacienda destacar que el repunte en el tasa interanual de el ipc de el [??:??/6/??:??.??:??] se haber deber a el notable incremento de el precio de el barril de petróleo en el mercado internacional con uno subida de el 86/100 en el último año así_como a el subida de el precio de el alimento fresco que poder haber se ver afectar por el paro de el transporte y el amarre de el flota pesquero que se producir ese mes",
        "lemmatized_text_reduced": "ipc subir canarias mayor subida autonomía español tasa interanual situar superar castilla_la_mancha dato difundir instituto_nacional_de_estadística índice subir conjunto estado tasa interanual nacional situar décima canario alto ir año ipc haber subir canarias décima conjunto españa situar ipc alcanzar implicar comprar año costar canarias españa_todos epígrafe subir archipiélag vestido calzado bajar mayor subida registrar diferencia transporte alcanzar aumento seguir bebida alcohólico tabaco subir aumentar alimento bebida alcohólico hotel café ocio cultura menaje medicamento vivienda comunicación mantener estable mayor subida ir año ser transporte aumento último mes alcanzar alimentación haber subir último año vivienda provincia las_palmas santa_cruz_de_tenerife registrar aumento ipc 2 tener índice 1 ser precio producto costar año base establecer palmas acumular ir año incremento ipc último mes santa_cruz_de_tenerife sumar último año ministerio_de_economía hacienda destacar repunte tasa interanual ipc haber deber notable incremento precio barril petróleo mercado internacional subida último año subida precio alimento fresco poder haber ver afectar paro transporte amarre flota pesquero producir mes",
        "persons": [
            "España"
        ],
        "locations": [
            "Canarias",
            "Canarias",
            "Canarias"
        ],
        "organizations": [
            "Castilla_La_Mancha",
            "Instituto_Nacional_de_Estadística",
            "Índice",
            "España_Todos",
            "Las_Palmas",
            "Santa_Cruz_de_Tenerife",
            "Palmas",
            "Santa_Cruz_de_Tenerife",
            "Ministerio_de_Economía",
            "Hacienda"
        ],
        "others": [
            "IPC",
            "IPC",
            "IPC",
            "IPC",
            "IPC",
            "IPC"
        ],
        "dates": [
            "[??:??/6/??:??.??:??]",
            "[??:??/6/2008:??.??:??]",
            "[??:??/6/??:??.??:??]",
            "[??:??/6/??:??.??:??]"
        ],
        "numbers": [
            "0,8",
            "100",
            "5,4",
            "100",
            "5,6",
            "0,6",
            "100",
            "4",
            "5",
            "100",
            "1995",
            "3",
            "100",
            "2",
            "2,8",
            "100",
            "108,2",
            "$_ECU:100",
            "2006",
            "2",
            "$_ECU:8,2",
            "8,3",
            "0,7",
            "100",
            "3,2",
            "100",
            "0,9",
            "100",
            "0,6",
            "100",
            "0,4",
            "0,3",
            "0,2",
            "100",
            "0,1",
            "8,6",
            "100",
            "12",
            "12,3",
            "100",
            "9,1",
            "100",
            "4,2",
            "100",
            "0,8",
            "100",
            "108,6",
            "107,7",
            "$_ECU:100",
            "2006",
            "2,9",
            "100",
            "12",
            "5,2",
            "100",
            "3,1",
            "5,5",
            "100",
            "86/100"
        ]
    }
}
