{
    "province": "LAS PALMAS",
    "date": "2010-03-10T00:00:00",
    "url": "https://www.20minutos.es/noticia/648266/0/",
    "title": {
        "raw_text": "El Gobierno recorta las pensiones de los nuevos jubilados desde 2010 con un cambio en la fórmula de cálculo",
        "lemmatized_text": "el gobierno recortar el pensión de el nuevo jubilado desde 2010 con uno cambio en el fórmula de cálculo",
        "lemmatized_text_reduced": "gobierno recortar pensión nuevo jubilado cambio fórmula cálculo",
        "persons": [],
        "locations": [],
        "organizations": [
            "Gobierno"
        ],
        "others": [],
        "dates": [],
        "numbers": [
            "2010"
        ]
    },
    "lead": {
        "raw_text": "El Gobierno central ha recortado el importe de la mayoría de pensiones de jubilación para aquellos trabajadores que se retiren a partir de enero de 2010, a través de un cambio en la fórmula de cálculo con el que no se tendrá en cuenta el último mes cotizado a la Seguridad Social antes del que corresponda a la fecha de la jubilación sino uno 15 años atrás, hasta ahora fuera del periodo de cálculo.",
        "lemmatized_text": "el gobierno central haber recortar el importe de el mayoría de pensión de jubilación para aquel trabajador que se retirar a_partir_de [??:??/1/2010:??.??:??] a_través_de uno cambio en el fórmula de cálculo con el que no se tener_en_cuenta el último mes cotizar a el seguridad_social antes de el que corresponder a el fecha de el jubilación sino uno 15 año atrás hasta ahora ser de el periodo de cálculo",
        "lemmatized_text_reduced": "gobierno central haber recortar importe mayoría pensión jubilación trabajador retirar cambio fórmula cálculo tener_en_cuenta último mes cotizar seguridad_social corresponder fecha jubilación año ser periodo cálculo",
        "persons": [],
        "locations": [],
        "organizations": [
            "Gobierno"
        ],
        "others": [
            "Seguridad_Social"
        ],
        "dates": [
            "[??:??/1/2010:??.??:??]"
        ],
        "numbers": [
            "15"
        ]
    },
    "body": {
        "raw_text": "El recorte es difícil de cuantificar de forma genérica ya que depende de las aportaciones que cada persona haya ido realizando al sistema de pensiones y de su situación laboral. Si por ejemplo está cobrando el paro al final de su vida laboral o tiene un sueldo inferior al de hace 15 años, lo que no es lo habitual, el cambio le beneficia, pero lo habitual es contar con un mayor sueldo según su edad avanza o, en el caso de los autónomos, cotizar con una base más alta los últimos años. Incluso sin tener en cuenta estas variables, retirarse un 2 de febrero de 2010 y que la Seguridad Social no tenga en cuenta el enero trabajado —como sí ocurría hasta diciembre de 2009— tiene un efecto estadístico claramente negativo para el pensionista si se proyecta la paga que cobraría un trabajador con al menos 35 años cotizados y que en los últimos 15 lo ha hecho con lo mínimo o, por el contrario, con los máximos permitidos. En concreto, en 7 de los 12 meses el saldo es negativo para el pensionista, según un cálculo realizado por Europa Press. Con el nuevo sistema y los datos objetivados (con las cifras de los extremos estadísticos y todas las cotizaciones mínimas o máximas) jubilarse en enero, marzo, abril, mayo, junio, julio y noviembre de 2010 supondría a este pensionista cobrar menos que si la Ley de Presupuestos aprobada a final de año no hubiera modificado el apartado 1.1 del Artículo 162 que marca la base reguladora de la pensión de jubilación de la Ley General de la Seguridad Social y que varía el redactado anterior de \"inmediatamente anteriores a aquel en que se produzca el hecho causante\" por el \"inmediatamente anteriores al mes previo al del hecho causante\". Además, en los 5 meses que saldría positivo para el nuevo pensionista, las subidas no suman en términos absolutos tanto como las bajadas, lo que refleja el claro ahorro en pensiones de jubilación para el Estado de esta medida ideada por el Gobierno de José Luis Rodríguez Zapatero y aprobada en el Congreso de los Diputados con el apoyo de Partido Nacionalista Vasco (PNV) y Coalición Canaria (CC). El promedio de ahorro para el Estado se sitúa en los 1,37 euros en el caso de cotizantes que lo hayan hecho por lo mínimo y de 4,5 euros en el de los que lo hicieran por el techo de la base de cotización, pero es potencialmente mayor teniendo en cuenta las variables ya comentadas de la habitual diferencia entre las aportaciones más actuales frente a las antiguas a pesar de que estas últimas se actualizan en base al IPC. En todo caso, el efecto de esta reforma es relativamente fácil de revertir para el ciudadano, simplemente retrasando voluntariamente un mes la jubilación. Y es que si antes al retirarse un 2 de febrero, se podía contar con incorporar enero al cálculo, para hacerlo ahora (si es que tasa su pensión y económicamente le interesa) deberá retirarse por ejemplo el 2 de marzo y, con ello, incorporará la cotización de enero al cálculo que la Seguridad Social haga para su pensión. Desapercibida entre el debate más amplio Ésta medida, que entró vía Ley de Acompañamiento en los Presupuestos, ha pasado desapercibida en medio del debate iniciado a principios de 2010 sobre la reforma del sistema de pensiones y la posible ampliación del mínimo de edad de jubilación a los 67 años, y sólo los primeros casos concretos de pensionistas están poniendo encima de la mesa las diferencias entre las pensiones que los nuevos jubilados pensaban cobrar (en base a las estimaciones realizadas por la propia Seguridad Social) y las que finalmente cobrarán. Al menos un caso concreto —donde la diferencia asciende a 167,16 euros anuales— cuya documentación obra en manos de Europa Press queda reflejado que oficialmente la Seguridad Social no fundamenta estas diferencias económicas en la nueva ley, sino que la da por hecho y fundamenta con otros legalismos. En todo caso, en las oficinas de la Dirección Provincial de Las Palmas del Instituto Nacional de la Seguridad Social (INSS) sí se está transmitiendo de forma verbal que el motivo fundamental de esta variación es la modificación del periodo de cálculo, según indicó a Europa Press este afectado.",
        "lemmatized_text": "el recorte ser difícil de cuantificar de forma genérico ya_que depender de el aportación que cada persona haber ir realizar a el sistema de pensión y de su situación laboral si por_ejemplo estar cobrar el paro a el final de su vida laboral o tener uno sueldo inferior a el de hacer 15 año el que no ser lo habitual el cambio le beneficiar pero el habitual ser contar con uno mayor sueldo según su edad avanzar o en el caso de el autónomo cotizar con uno base más alto el último año incluso sin tener_en_cuenta este variable retirar se uno [??:2/2/2010:??.??:??] y que el seguridad_social no tener_en_cuenta el [??:??/1/??:??.??:??] trabajar como sí ocurrir hasta [??:??/12/2009:??.??:??] tener uno efecto estadístico claramente negativo para el pensionista si se proyectar el paga que cobrar uno trabajador con a el menos 35 año cotizar y que en el último 15 lo haber hacer con el mínimo o por_el_contrario con el máximo permitir en concreto en 7 de el 12 mes el saldo ser negativo para el pensionista según uno cálculo realizar por europa_press con el nuevo sistema y el dato objetivar con el cifra de el extremo estadístico y todo el cotización mínimo o máximo jubilar se en [??:??/1/??:??.??:??] [??:??/3/??:??.??:??] [??:??/4/??:??.??:??] [??:??/5/??:??.??:??] [??:??/6/??:??.??:??] [??:??/7/??:??.??:??] y [??:??/11/2010:??.??:??] suponer a este pensionista cobrar menos que si el ley_de_presupuestos aprobar a final de año no haber modificar el apartado 1.1 de el artículo 162 que marcar el base regulador de el pensión de jubilación de el ley_general_de_la_seguridad_social y que variar el redactar anterior de inmediatamente anterior a aquel en que se producir el hecho causante por el inmediatamente anterior a el mes previo a el de el hecho causante además en el 5 mes que salir positivo para el nuevo pensionista el subida no sumar en término absoluto tanto como el bajada el que reflejar el claro ahorro en pensión de jubilación para el estado de este medida idear por el gobierno_de_josé_luis_rodríguez_zapatero y aprobar en el congreso_de_los_diputados con el apoyo de partido_nacionalista_vasco pnv y coalición_canaria cc el promedio de ahorro para el estado se situar en el $_ECU:1,37 en el caso de cotizante que lo haber hacer por el mínimo y de $_ECU:4,5 en el de el que lo hacer por el techo de el base de cotización pero ser potencialmente mayor tener_en_cuenta el variable ya comentar de el habitual diferencia entre el aportación más actual frente_a el antiguo a_pesar_de que este último se actualizar en base a el ipc en_todo_caso el efecto de este reforma ser relativamente fácil de revertir para el ciudadano simplemente retrasar voluntariamente uno mes el jubilación y ser que si antes a el retirar se uno [??:2/2/??:??.??:??] se poder contar con incorporar [??:??/1/??:??.??:??] a el cálculo para hacer lo ahora si ser que tasa su pensión y económicamente le interesar deber retirar se por_ejemplo el [??:2/3/??:??.??:??] y con ello incorporar el cotización de [??:??/1/??:??.??:??] a el cálculo que el seguridad_social hacer para su pensión desapercibida entre el debate más amplio ésta medida que entrar vía ley_de_acompañamiento en el presupuestos haber pasar desapercibido en medio de el debate iniciar a_principios_de 2010 sobre el reforma de el sistema de pensión y el posible ampliación de el mínimo de edad de jubilación a el 67 año y sólo el 1 caso concreto de pensionista estar poner encima_de el mesa el diferencia entre el pensión que el nuevo jubilado pensar cobrar en base a el estimación realizar por el propio seguridad_social y el que finalmente cobrar a el menos uno caso concreto donde el diferencia ascender a $_ECU:167,16 anual cuyo documentación obra en_manos_de europa_press quedar reflejar que oficialmente el seguridad_social no fundamentar este diferencia económico en el nuevo ley sino_que el dar por hecho y fundamentar con otro legalismo en_todo_caso en el oficina de el dirección_provincial_de_las_palmas_del_instituto_nacional_de_la_seguridad_social inss sí se estar transmitir de forma verbal que el motivo fundamental de este variación ser el modificación de el periodo de cálculo según indicar a europa_press este afectar",
        "lemmatized_text_reduced": "recorte ser difícil cuantificar forma genérico depender aportación persona haber ir realizar sistema pensión situación laboral estar cobrar paro final vida laboral tener sueldo inferior hacer año ser habitual cambio beneficiar habitual ser contar mayor sueldo edad avanzar caso autónomo cotizar base alto último año tener_en_cuenta variable retirar seguridad_social tener_en_cuenta trabajar ocurrir tener efecto estadístico claramente negativo pensionista proyectar paga cobrar trabajador año cotizar último haber hacer mínimo máximo permitir concreto mes saldo ser negativo pensionista cálculo realizar europa_press nuevo sistema dato objetivar cifra extremo estadístico cotización mínimo máximo jubilar suponer pensionista cobrar ley_de_presupuestos aprobar final año haber modificar apartado artículo marcar base regulador pensión jubilación ley_general_de_la_seguridad_social variar redactar anterior inmediatamente anterior producir hecho causante inmediatamente anterior mes previo hecho causante mes salir positivo nuevo pensionista subida sumar término absoluto bajada reflejar claro ahorro pensión jubilación estado medida idear gobierno_de_josé_luis_rodríguez_zapatero aprobar congreso_de_los_diputados apoyo partido_nacionalista_vasco pnv coalición_canaria cc promedio ahorro estado situar caso cotizante haber hacer mínimo hacer techo base cotización ser potencialmente mayor tener_en_cuenta variable comentar habitual diferencia aportación actual antiguo último actualizar base ipc efecto reforma ser relativamente fácil revertir ciudadano simplemente retrasar voluntariamente mes jubilación ser retirar poder contar incorporar cálculo hacer ser tasa pensión económicamente interesar deber retirar incorporar cotización cálculo seguridad_social hacer pensión desapercibida debate amplio ésta medida entrar ley_de_acompañamiento presupuestos haber pasar desapercibido medio debate iniciar reforma sistema pensión posible ampliación mínimo edad jubilación año 1 caso concreto pensionista estar poner mesa diferencia pensión nuevo jubilado pensar cobrar base estimación realizar propio seguridad_social finalmente cobrar caso concreto diferencia ascender anual documentación obra europa_press quedar reflejar oficialmente seguridad_social fundamentar diferencia económico nuevo ley dar hecho fundamentar legalismo oficina dirección_provincial_de_las_palmas_del_instituto_nacional_de_la_seguridad_social inss estar transmitir forma verbal motivo fundamental variación ser modificación periodo cálculo indicar europa_press afectar",
        "persons": [
            "Desapercibida",
            "Europa_Press",
            "Europa_Press"
        ],
        "locations": [],
        "organizations": [
            "Europa_Press",
            "Estado",
            "Gobierno_de_José_Luis_Rodríguez_Zapatero",
            "Congreso_de_los_Diputados",
            "Partido_Nacionalista_Vasco",
            "PNV",
            "Coalición_Canaria",
            "CC",
            "Estado",
            "Ésta",
            "Presupuestos",
            "Dirección_Provincial_de_Las_Palmas_del_Instituto_Nacional_de_la_Seguridad_Social",
            "INSS"
        ],
        "others": [
            "Seguridad_Social",
            "Ley_de_Presupuestos",
            "Artículo",
            "Ley_General_de_la_Seguridad_Social",
            "IPC",
            "Seguridad_Social",
            "Ley_de_Acompañamiento",
            "Seguridad_Social",
            "Seguridad_Social"
        ],
        "dates": [
            "[??:2/2/2010:??.??:??]",
            "[??:??/1/??:??.??:??]",
            "[??:??/12/2009:??.??:??]",
            "[??:??/1/??:??.??:??]",
            "[??:??/3/??:??.??:??]",
            "[??:??/4/??:??.??:??]",
            "[??:??/5/??:??.??:??]",
            "[??:??/6/??:??.??:??]",
            "[??:??/7/??:??.??:??]",
            "[??:??/11/2010:??.??:??]",
            "[??:2/2/??:??.??:??]",
            "[??:??/1/??:??.??:??]",
            "[??:2/3/??:??.??:??]",
            "[??:??/1/??:??.??:??]"
        ],
        "numbers": [
            "15",
            "35",
            "15",
            "7",
            "12",
            "1.1",
            "162",
            "5",
            "$_ECU:1,37",
            "$_ECU:4,5",
            "2010",
            "67",
            "$_ECU:167,16"
        ]
    }
}
