{
    "province": "LAS PALMAS",
    "date": "2009-12-03T00:00:00",
    "url": "https://www.20minutos.es/noticia/580798/0/haidar/responsabiliza/gobierno/",
    "title": {
        "raw_text": "Haidar responsabiliza al Gobierno español de lo que le pueda suceder",
        "lemmatized_text": "haidar responsabilizar a el gobierno español de el que le poder suceder",
        "lemmatized_text_reduced": "haidar responsabilizar gobierno español poder suceder",
        "persons": [
            "Haidar"
        ],
        "locations": [],
        "organizations": [
            "Gobierno"
        ],
        "others": [],
        "dates": [],
        "numbers": []
    },
    "lead": {
        "raw_text": "La activista saharaui dice que está \"decidida a ir hasta el final\". Está en huelga de hambre desde el 16 de noviembre. España da por cerrada la posibilidad de que Marruecos le conceda pasaporte y le pide que acepte la nacionalidad española.",
        "lemmatized_text": "el activista saharaui decir que estar decidir a ir hasta el final estar en huelga de hambre desde el [??:16/11/??:??.??:??] españa dar por cerrar el posibilidad de que marruecos le conceder pasaporte y le pedir que aceptar el nacionalidad español",
        "lemmatized_text_reduced": "activista saharaui decir estar decidir ir final estar huelga hambre españa dar cerrar posibilidad marruecos conceder pasaporte pedir aceptar nacionalidad español",
        "persons": [
            "España"
        ],
        "locations": [],
        "organizations": [
            "Marruecos"
        ],
        "others": [],
        "dates": [
            "[??:16/11/??:??.??:??]"
        ],
        "numbers": []
    },
    "body": {
        "raw_text": "La activista saharaui Aminatu Haidar , en huelga de hambre desde el pasado 16 de noviembre por su expulsión a Lanzarote desde El Aaiún por las autoridades marroquíes, está \"decidida a ir hasta el final\" en su protesta y será el Gobierno español el \"responsable\" de lo que le pueda suceder. Nada me ha dolido tanto como lo que está haciendo España, un país democrático y un Estado de Derecho Es el mensaje que, según la plataforma que la apoya, Haidar ha trasmitido en su reunión a Agustín Santos, el jefe de gabinete del ministro de Asuntos Exteriores y de Cooperación, Miguel Ángel Moratinos, quien se trasladó nuevamente este jueves a Lanzarote para ver a la activista y reiterarle la oferta del Gobierno de darle el estatus de refugiada o un pasaporte español. Haidar se encuentra en el aeropuerto lanzaroteño de Guamiceta desde el pasado día 13 de noviembre tras ser expulsada después de haber sido detenida el día anterior al llegar en un vuelo a la capital del Sáhara Occidental; el día 16 inició su huelga de hambre para poder regresar a El Aaiún. Según un comunicado distribuido por la plataforma, Haidar insiste en que no vino a España por su \"propia voluntad\" sino que lo hizo \"obligada\". \"He sido secuestrada, detenida, torturada, alejada de mis hijos por Marruecos\" pero, afirma, \"eso nunca me ha dolido tanto como lo que está haciendo España, un país democrático y un Estado de Derecho\". Sin posibilidad de pasaporte marroquí En su comparecencia ante los medios tras su encuentro, Santos no ha mencionado que Haidar le hablara en esos términos. Lo que sí ha confirmado es que España ha dado por \"cerrada\" la posibilidad de que Marruecos le conceda pasaporte y ha considerado que es el momento de buscar \"con rapidez\" soluciones al caso de acuerdo con el derecho español, debido a la situación física de la activista saharaui en huelga de hambre. España tiene la convicción de que Marruecos no le entregará documentación que permita viajar a El Aaiún Santos ha explicado que el Ministerio de Asuntos Exteriores ha presentado a la embajada de Marruecos un nota verbal en la que se solicita \"de manera formal y escrita\" que el Gobierno de Marruecos dote de documentación a Haidar para poder regresar, si bien no ha obtenido todavía respuesta alguna. No obstante, y con arreglo a las manifestaciones efectuadas por altos cargos del país vecino, España tiene la convicción de que el Gobierno de Marruecos no entregará documentación que permita viajar a la activista saharaui a El Aaiún \"a menos que reafirme su marroquinidad y solicite perdón a las autoridades de Marruecos\", según Santos. El Gobierno español mantiene su ofrecimiento a la activista saharaui de darle un pasaporte españo l o el estatuto de refugiada, según Santos. El representante de Exteriores afirmó que es cierto, como opina Haidar, que el estatuto de refugiada le impediría viajar a la capital del Sáhara Occidental, pero no si lo hace con pasaporte español.",
        "lemmatized_text": "el activista saharaui aminatu_haidar en huelga de hambre desde el [??:16/11/??:??.??:??] por su expulsión a lanzarote desde el_aaiún por el autoridad marroquí estar decidir a ir hasta el final en su protesta y ser el gobierno español el responsable de el que le poder suceder nada me haber doler tanto como el que estar hacendar españa uno país democrático y uno estado_de_derecho_es el mensaje que según el plataforma que lo apoyar haidar haber trasmitir en su reunión a agustín_santos el jefe de gabinete de el ministro de asuntos_exteriores y de cooperación miguel_ángel_moratinos quien se trasladar nuevamente este [J:??/??/??:??.??:??] a lanzarote para ver a el activista y reiterar le el oferta de el gobierno de dar le el estatus de refugiado o uno pasaporte español haidar se encontrar en el aeropuerto lanzaroteño de guamiceta desde el [??:13/11/??:??.??:??] tras ser expulsar después_de haber ser detener el día anterior a el llegar en uno vuelo a el capital de el sáhara_occidental el [??:16/??/??:??.??:??] iniciar su huelga de hambre para poder regresar a el_aaiún según uno comunicado distribuir por el plataforma haidar insistir en que no venir a españa por su propio voluntad sino_que lo hacer obligar haber ser secuestrar detener torturar alejar de mi hijo por marruecos pero afirmar ese nunca me haber doler tanto como el que estar hacendar españa uno país democrático y uno estado_de_derecho sin posibilidad de pasaporte marroquí en su comparecencia ante el medio tras su encuentro santos no haber mencionar que haidar le hablar en ese término el que sí haber confirmar ser que españa haber dar por cerrar el posibilidad de que marruecos le conceder pasaporte y haber considerar que ser el momento de buscar con rapidez solución a el caso de_acuerdo_con el derecho español debido_a el situación físico de el activista saharaui en huelga de hambre españa tener el convicción de que marruecos no le entregar documentación que permitir viajar a el_aaiún_santos haber explicar que el ministerio_de_asuntos_exteriores haber presentar a el embajada de marruecos uno nota verbal en el que se solicitar de manera formal y escribir que el gobierno_de_marruecos dotar de documentación a haidar para poder regresar si bien no haber obtener todavía respuesta alguno no_obstante y con arreglo a el manifestación efectuar por alto cargo de el país vecino españa tener el convicción de que el gobierno_de_marruecos no entregar documentación que permitir viajar a el activista saharaui a el_aaiún a_menos_que reafirmar su marroquinidad y solicitar perdón a el autoridad de marruecos según santos el gobierno español mantener su ofrecimiento a el activista saharaui de dar le uno pasaporte españo l o el estatuto de refugiado según santos el representante de exteriores afirmar que ser cierto como opinar haidar que el estatuto de refugiado le impedir viajar a el capital de el sáhara_occidental pero no si lo hacer con pasaporte español",
        "lemmatized_text_reduced": "activista saharaui aminatu_haidar huelga hambre expulsión lanzarote el_aaiún autoridad marroquí estar decidir ir final protesta ser gobierno español responsable poder suceder haber doler estar hacendar españa país democrático estado_de_derecho_es mensaje plataforma apoyar haidar haber trasmitir reunión agustín_santos jefe gabinete ministro asuntos_exteriores cooperación miguel_ángel_moratinos trasladar nuevamente lanzarote ver activista reiterar oferta gobierno dar estatus refugiado pasaporte español haidar encontrar aeropuerto lanzaroteño guamiceta ser expulsar haber ser detener día anterior llegar vuelo capital sáhara_occidental iniciar huelga hambre poder regresar el_aaiún comunicado distribuir plataforma haidar insistir venir españa propio voluntad hacer obligar haber ser secuestrar detener torturar alejar hijo marruecos afirmar haber doler estar hacendar españa país democrático estado_de_derecho posibilidad pasaporte marroquí en comparecencia medio encuentro santos haber mencionar haidar hablar término haber confirmar ser españa haber dar cerrar posibilidad marruecos conceder pasaporte haber considerar ser momento buscar rapidez solución caso derecho español situación físico activista saharaui huelga hambre españa tener convicción marruecos entregar documentación permitir viajar el_aaiún_santos haber explicar ministerio_de_asuntos_exteriores haber presentar embajada marruecos nota verbal solicitar manera formal escribir gobierno_de_marruecos dotar documentación haidar poder regresar haber obtener respuesta arreglo manifestación efectuar alto cargo país vecino españa tener convicción gobierno_de_marruecos entregar documentación permitir viajar activista saharaui el_aaiún reafirmar marroquinidad solicitar perdón autoridad marruecos santos gobierno español mantener ofrecimiento activista saharaui dar pasaporte españo l estatuto refugiado santos representante exteriores afirmar ser cierto opinar haidar estatuto refugiado impedir viajar capital sáhara_occidental hacer pasaporte español",
        "persons": [
            "Aminatu_Haidar",
            "Haidar",
            "Agustín_Santos",
            "Miguel_Ángel_Moratinos",
            "Haidar",
            "Haidar",
            "España",
            "Santos",
            "Haidar",
            "España",
            "España",
            "España",
            "Santos",
            "Santos",
            "Haidar"
        ],
        "locations": [
            "Lanzarote",
            "El_Aaiún",
            "España",
            "Lanzarote",
            "Guamiceta",
            "Sáhara_Occidental",
            "El_Aaiún",
            "España",
            "El_Aaiún_Santos",
            "Marruecos",
            "Haidar",
            "El_Aaiún",
            "Marruecos",
            "Sáhara_Occidental"
        ],
        "organizations": [
            "Gobierno",
            "Asuntos_Exteriores",
            "Gobierno",
            "Marruecos",
            "En",
            "Marruecos",
            "Marruecos",
            "Ministerio_de_Asuntos_Exteriores",
            "Gobierno_de_Marruecos",
            "Gobierno_de_Marruecos",
            "Gobierno",
            "Exteriores"
        ],
        "others": [
            "Estado_de_Derecho_Es",
            "Cooperación",
            "Estado_de_Derecho"
        ],
        "dates": [
            "[??:16/11/??:??.??:??]",
            "[J:??/??/??:??.??:??]",
            "[??:13/11/??:??.??:??]",
            "[??:16/??/??:??.??:??]"
        ],
        "numbers": []
    }
}
