{
    "province": "LAS PALMAS",
    "date": "2011-02-14T00:00:00",
    "url": "https://www.20minutos.es/noticia/959106/0/",
    "title": {
        "raw_text": "Fuerteventura recibe un 33% más de turistas extranjeros durante el mes de enero",
        "lemmatized_text": "fuerteventura recibir uno 33/100 más de turista extranjero durante el [??:??/1/??:??.??:??]",
        "lemmatized_text_reduced": "fuerteventura recibir turista extranjero",
        "persons": [],
        "locations": [],
        "organizations": [
            "Fuerteventura"
        ],
        "others": [],
        "dates": [
            "[??:??/1/??:??.??:??]"
        ],
        "numbers": [
            "33/100"
        ]
    },
    "lead": {
        "raw_text": "Fuerteventura lidera la recuperación de turistas del archipiélago, pues en el mes de enero la isla recibió 32.257 turistas internacionales más que en enero del año anterior, esto es, cosechó un aumento del 33,22 por ciento, frente a la media de Canarias que se sitúa en un +11,76%.",
        "lemmatized_text": "fuerteventura liderar el recuperación de turista de el archipiélago pues en el [??:??/1/??:??.??:??] el isla recibir 32.257 turista internacional más que en [??:??/1/??:??.??:??] de el año anterior este ser cosechar uno aumento de el 33,22 por 100 frente_a el media de canarias que se situar en uno +11,76/100",
        "lemmatized_text_reduced": "fuerteventura liderar recuperación turista archipiélago isla recibir turista internacional año anterior ser cosechar aumento media canarias situar",
        "persons": [],
        "locations": [
            "Canarias"
        ],
        "organizations": [
            "Fuerteventura"
        ],
        "others": [],
        "dates": [
            "[??:??/1/??:??.??:??]",
            "[??:??/1/??:??.??:??]"
        ],
        "numbers": [
            "32.257",
            "33,22",
            "100",
            "+11,76/100"
        ]
    },
    "body": {
        "raw_text": "Fuerteventura lidera la recuperación de turistas del archipiélago, pues en el mes de enero la isla recibió 32.257 turistas internacionales más que en enero del año anterior, esto es, cosechó un aumento del 33,22 por ciento, frente a la media de Canarias que se sitúa en un +11,76%. En un comunicado, la consejera de Turismo, Águeda Montelongo, aclaró que \"este incremento no es producto de la crisis de Egipto y Túnez, puesto que en enero todavía no se estaban produciendo los desvíos de aviones a Fuerteventura\". \"En los próximos meses contaremos con un incremento de turistas especialmente notable, pues al aumento ya previsto como el que reflejan los datos de enero, habrá que sumar las llegadas de turistas no previstos con anterioridad producto de la crisis en Túnez y Egipto\", dijo. Así, en términos totales, Fuerteventura recibió en enero 129.372 turistas procedentes de aeropuertos internacionales, un 33,22 por ciento más que en enero de 2009. De los 91.368 turistas extranjeros más que recibió el archipiélago el pasado mes, 32.257 llegaron a Fuerteventura. Siguiendo la tendencia de los últimos meses, el mercado que más turistas incrementa en Fuerteventura fue Reino Unido, que envió a Fuerteventura en enero 11.999 británicos más que el año pasado, lo que supone un incremento del 59,72 por ciento. Le sigue Alemania, pues Fuerteventura recibió en enero 9.434 alemanes más (+19,16%), alcanzando la cifra total de 58.669 turistas procedentes de Alemania. En tercer y cuarto lugar se encuentran Italia e Irlanda, quienes llevaron a Fuerteventura 2.554 y 2.553 turistas más que en el mismo mes del año pasado, esto es, un incremento de 145,44% y 192,97%, respectivamente. Finalmente, en términos porcentuales, destacan además los incrementos cosechados en países como Polonia (+81,64%) y Francia (+27,33%), que desde hace más de un año mantienen una tendencia positiva.",
        "lemmatized_text": "fuerteventura liderar el recuperación de turista de el archipiélago pues en el [??:??/1/??:??.??:??] el isla recibir 32.257 turista internacional más que en [??:??/1/??:??.??:??] de el año anterior este ser cosechar uno aumento de el 33,22 por 100 frente_a el media de canarias que se situar en uno +11,76/100 en uno comunicado el consejero de turismo águeda_montelongo aclarar que este incremento no ser producto de el crisis de egipto y túnez puesto que en [??:??/1/??:??.??:??] todavía no se estar producir el desvío de avión a fuerteventura en el próximo mes contar con uno incremento de turista especialmente notable pues a el aumento ya prever como el que reflejar el dato de [??:??/1/??:??.??:??] haber que sumar el llegada de turista no prever con anterioridad producto de el crisis en túnez y egipto decir así en término total fuerteventura recibir en [??:??/1/??:??.??:??] 129.372 turista procedente de aeropuerto internacional uno 33,22 por 100 más que en [??:??/1/2009:??.??:??] de el 91.368 turista extranjero más que recibir el archipiélago el pasar mes 32.257 llegar a fuerteventura seguir el tendencia de el último mes el mercado que más turista incrementar en fuerteventura ser reino_unido que enviar a fuerteventura en [??:??/1/??:??.??:??] 11.999 británico más que el año pasar el que suponer uno incremento de el 59,72 por 100 le seguir alemania pues fuerteventura recibir en [??:??/1/??:??.??:??] 9.434 alemán más +19,16/100 alcanzar el cifra total de 58.669 turista procedente de alemania en 3 y 4 lugar se encontrar italia y irlanda quien llevar a fuerteventura 2.554 y 2.553 turista más que en el mismo mes de el año pasar este ser uno incremento de 145,44/100 y 192,97/100 respectivamente finalmente en término porcentual destacar además el incremento cosechar en país como polonia +81,64/100 y francia +27,33/100 que desde hacer más de uno año mantener uno tendencia positivo",
        "lemmatized_text_reduced": "fuerteventura liderar recuperación turista archipiélago isla recibir turista internacional año anterior ser cosechar aumento media canarias situar comunicado consejero turismo águeda_montelongo aclarar incremento ser producto crisis egipto túnez puesto estar producir desvío avión fuerteventura próximo mes contar incremento turista especialmente notable aumento prever reflejar dato haber sumar llegada turista prever anterioridad producto crisis túnez egipto decir término total fuerteventura recibir turista procedente aeropuerto internacional turista extranjero recibir archipiélago pasar mes llegar fuerteventura seguir tendencia último mes mercado turista incrementar fuerteventura ser reino_unido enviar fuerteventura británico año pasar suponer incremento seguir alemania fuerteventura recibir alemán alcanzar cifra total turista procedente alemania 3 4 lugar encontrar italia irlanda llevar fuerteventura turista mismo mes año pasar ser incremento respectivamente finalmente término porcentual destacar incremento cosechar país polonia francia hacer año mantener tendencia positivo",
        "persons": [
            "Águeda_Montelongo"
        ],
        "locations": [
            "Canarias",
            "Túnez",
            "Túnez",
            "Egipto",
            "Fuerteventura",
            "Fuerteventura",
            "Reino_Unido",
            "Alemania",
            "Irlanda",
            "Polonia",
            "Francia"
        ],
        "organizations": [
            "Fuerteventura",
            "Egipto",
            "Fuerteventura",
            "Fuerteventura",
            "Fuerteventura",
            "Alemania",
            "Fuerteventura",
            "Italia",
            "Fuerteventura"
        ],
        "others": [
            "Turismo"
        ],
        "dates": [
            "[??:??/1/??:??.??:??]",
            "[??:??/1/??:??.??:??]",
            "[??:??/1/??:??.??:??]",
            "[??:??/1/??:??.??:??]",
            "[??:??/1/??:??.??:??]",
            "[??:??/1/2009:??.??:??]",
            "[??:??/1/??:??.??:??]",
            "[??:??/1/??:??.??:??]"
        ],
        "numbers": [
            "32.257",
            "33,22",
            "100",
            "+11,76/100",
            "129.372",
            "33,22",
            "100",
            "91.368",
            "32.257",
            "11.999",
            "59,72",
            "100",
            "9.434",
            "+19,16/100",
            "58.669",
            "2.554",
            "2.553",
            "145,44/100",
            "192,97/100",
            "+81,64/100",
            "+27,33/100"
        ]
    }
}
