{
    "province": "LAS PALMAS",
    "date": "2011-02-16T00:00:00",
    "url": "https://www.20minutos.es/noticia/961526/0/",
    "title": {
        "raw_text": "Canarias lidera en enero número de pasajeros transportados en 'low cost' con 486.420 personas, 24% más",
        "lemmatized_text": "canario liderar en [??:??/1/??:??.??:??] número de pasajero transportar en low cost con 486.42 persona 24/100 más",
        "lemmatized_text_reduced": "canario liderar número pasajero transportar low cost persona",
        "persons": [],
        "locations": [],
        "organizations": [],
        "others": [],
        "dates": [
            "[??:??/1/??:??.??:??]"
        ],
        "numbers": [
            "486.42",
            "24/100"
        ]
    },
    "lead": {
        "raw_text": "Se ha registrado una recuperación de actividad que \"se ha dejado notar\" en los aeropuertos españoles.",
        "lemmatized_text": "se haber registrar uno recuperación de actividad que se haber dejar notar en el aeropuerto español",
        "lemmatized_text_reduced": "haber registrar recuperación actividad haber dejar notar aeropuerto español",
        "persons": [],
        "locations": [],
        "organizations": [],
        "others": [],
        "dates": [],
        "numbers": []
    },
    "body": {
        "raw_text": "Las aerolíneas de bajo coste transportaron en Canarias 486.420 pasajeros en enero, lo que supone un aumento del 24 por ciento respecto al mismo mes del ejercicio anterior, convirtiendo a las islas como la región en la que más personas trasladaron las 'low cost', según datos difundidos por el Instituto de Estudios Turísticos (IET), dependiente del Ministerio de Industria, Turismo y Comercio. Por el contrario, en las compañías tradicionales volaron en las islas 386.760 pasajeros durante el pasado mes, representando un descenso del 1,5 por ciento en relación al mismo dato de 2010. En el conjunto de España, las 'low cost' transportaron 1,7 millones de pasajeros en enero, lo que supone un aumento del 14,4 por ciento con respecto al mismo mes del ejercicio anterior, frente a las compañías tradicionales, que trasladaron a 1,6 millones de viajeros, un 4,3 por ciento más. Por mercados, Reino Unido y Alemania lideran las entradas en compañías de bajo coste, con un 29,8 y 19,7 por ciento de los pasajeros que eligieron esta vía, respectivamente, con sendos aumentos del 2,8 por ciento, para el mercado británico (520.261 viajeros) y del 9,6 por ciento para el alemán (343.175 pasajeros). Italia, tercer emisor, incrementó un 26,3 por ciento las llegadas hasta 238.750 de viajeros, el equivalente al 13,7 por ciento del total de las entradas por esta vía. Le siguió Francia, con el 6,3 por ciento del total y 110.210 viajeros, un 22,3 por ciento más que hace un año. Junto a Canarias también encabezan el ranking de entradas en compañías de bajo coste en enero Cataluña con el 21,8 por ciento de entradas, 379.465 viajeros, un 15,7 por ciento más, y Comunidad de Madrid con 258.882, un 20,2 por ciento más. Les siguen Comunidad Valenciana, con 224.365 pasajeros, un 9,9 por ciento más, Andalucía con 213.332 viajeros, un 13,9 por ciento más, y Baleares con 128.88 pasajeros, y un descenso del 6,5 por ciento. En términos de evolución, todas estas regiones recibieron un mayor volumen de pasajeros de bajo coste que en enero de 2010, una recuperación de actividad que \"se ha dejado notar\" en los aeropuertos españoles. TRANSPORTAN 1,7 Millones de personas En el conjunto nacional, las aerolíneas de bajo coste transportaron 1,7 millones de pasajeros en enero, lo que supone un aumento del 14,4 por ciento con respecto al mismo mes del ejercicio anterior, frente a las compañías tradicionales, que trasladaron a 1,6 millones de viajeros, un 4,3 por ciento más. Por mercados, Reino Unido, Alemania emitieron e Italia emitieron en conjunto el 63,2 por ciento de los pasajeros que llegaron a España en compañías de bajo coste en el primer mes del año. Los tres registraron crecimientos con una evolución de los mercados de origen \"muy positiva\". Reino Unido y Alemania lideran las entradas en compañías de bajo coste, con un 29,8 y un 19,7 por ciento de los pasajeros que eligieron esta vía, respectivamente, con sendos aumentos del 2,8 por ciento, para el mercado británico (520.261 viajeros) y del 9,6 por ciento para el alemán (343.175 pasajeros). Italia, tercer emisor, incrementó un 26,3 por ciento las llegadas hasta 238.750 de viajeros, el equivalente al 13,7 por ciento del total de las entradas por esta vía. Le siguió Francia, con el 6,3 por ciento del total y 110.210 viajeros, un 22,3 por ciento más que hace un año. El resto de países presentaron aumentos generalizados, incluso de dos dígitos, en el número de pasajeros de bajo coste emitidos hacia España. Los aeropuertos españoles más utilizados por las aerolíneas de bajo coste en enero fueron el de Barcelona-El Prat, que alcanzó los 297.993 pasajeros, lo que supone un aumento del 41 por ciento; el de Madrid-Barajas, con 258.882 pasajeros y un aumento del 20,2 por ciento; el de Tenerife Sur, con 182.509 pasajeros, un 15,6 por ciento más. Les siguieron el de Málaga, que experimentó un aumento del 7,8 por ciento, hasta 163.561 pasajeros, Alicante, que recibió 156.630 viajeros, un 2,2 por ciento más, y Gran Canaria, con un aumento del 32,8 por ciento, hasta 139.887 viajeros. Sólo dos aeropuertos cerraron enero en negativo, Girona, con 74.537 pasajeros, un 30,5 por ciento menos, y Palma de Mallorca, con un descenso del 6 por ciento, hasta 125.295 pasajeros. En el lado opuesto, el mayor aumento lo registró Fuerteventura, con 74.537 viajeros, un 53,5 por ciento más. El grado de ocupación de las compañías de bajo coste alcanzó el 70 por ciento el mes pasado, una tasa de cinto puntos superior a la de las compañías tradicionales. Ryanair, easyJet y Air Berlin se mantuvieron como las principales compañías de bajo coste en España en 2010 con seis de cada diez pasajeros en conjunto. Las tres compañías aumentaron las cifras de pasajeros en enero con respecto al mismo mes del año pasado.",
        "lemmatized_text": "el aerolínea de bajo coste transportar en canarias 486.42 pasajero en [??:??/1/??:??.??:??] el que suponer uno aumento de el 24 por 100 respecto a el mismo mes de el ejercicio anterior convertir a el isla como el región en el que más persona trasladar el low cost según dato difundir por el instituto_de_estudios_turísticos iet dependiente de el ministerio_de_industria turismo y comercio por_el_contrario en el compañía tradicional volar en el isla 386.76 pasajero durante el pasar mes representar uno descenso de el 1,5 por 100 en relación a el mismo dato de 2010 en el conjunto de españa el low cost transportar 1,7 millón de pasajero en [??:??/1/??:??.??:??] el que suponer uno aumento de el 14,4 por 100 con respecto a el mismo mes de el ejercicio anterior frente_a el compañía tradicional que trasladar a 1,6 millón de viajero uno 4,3 por 100 más por mercado reino_unido y alemania liderar el entrada en compañía de bajo coste con uno 29,8 y 19,7 por 100 de el pasajero que elegir este vía respectivamente con sendos aumento de el 2,8 por 100 para el mercado británico 520.261 viajero y de el 9,6 por 100 para el alemán 343.175 pasajero italia 3 emisor incrementar uno 26,3 por 100 el llegada hasta 238.75 de viajero el equivalente a el 13,7 por 100 de el total de el entrada por este vía le seguir francia con el 6,3 por 100 de el total y 110.21 viajero uno 22,3 por 100 más que hacer uno año junto_a canarias también encabezar el ranking de entrada en compañía de bajo coste en [??:??/1/??:??.??:??] cataluña con el 21,8 por 100 de entrada 379.465 viajero uno 15,7 por 100 más y comunidad_de_madrid con 258.882 uno 20,2 por 100 más le seguir comunidad_valenciana con 224.365 pasajero uno 9,9 por 100 más andalucía con 213.332 viajero uno 13,9 por 100 más y baleares con 128.88 pasajero y uno descenso de el 6,5 por 100 en término de evolución todo este región recibir uno mayor volumen de pasajero de bajo coste que en [??:??/1/2010:??.??:??] uno recuperación de actividad que se haber dejar notar en el aeropuerto español transportar 1,7 millones de persona en el conjunto nacional el aerolínea de bajo coste transportar 1,7 millón de pasajero en [??:??/1/??:??.??:??] el que suponer uno aumento de el 14,4 por 100 con respecto a el mismo mes de el ejercicio anterior frente_a el compañía tradicional que trasladar a 1,6 millón de viajero uno 4,3 por 100 más por mercado reino_unido alemania emitir y italia emitir en conjunto el 63,2 por 100 de el pasajero que llegar a españa en compañía de bajo coste en el 1 mes de el año el 3 registrar crecimiento con uno evolución de el mercado de origen muy positivo reino_unido y alemania liderar el entrada en compañía de bajo coste con uno 29,8 y uno 19,7 por 100 de el pasajero que elegir este vía respectivamente con sendos aumento de el 2,8 por 100 para el mercado británico 520.261 viajero y de el 9,6 por 100 para el alemán 343.175 pasajero italia 3 emisor incrementar uno 26,3 por 100 el llegada hasta 238.75 de viajero el equivalente a el 13,7 por 100 de el total de el entrada por este vía le seguir francia con el 6,3 por 100 de el total y 110.21 viajero uno 22,3 por 100 más que hacer uno año el resto de país presentar aumento generalizar incluso de 2 dígito en el número de pasajero de bajo coste emitir hacia españa el aeropuerto español más utilizar por el aerolínea de bajo coste en [??:??/1/??:??.??:??] ser el de barcelona-el_prat que alcanzar el 297.993 pasajero el que suponer uno aumento de el 41 por 100 el de madrid-barajas con 258.882 pasajero y uno aumento de el 20,2 por 100 el de tenerife_sur con 182.509 pasajero uno 15,6 por 100 más le seguir el de málaga que experimentar uno aumento de el 7,8 por 100 hasta 163.561 pasajero alicante que recibir 156.63 viajero uno 2,2 por 100 más y gran_canaria con uno aumento de el 32,8 por 100 hasta 139.887 viajero sólo 2 aeropuerto cerrar [??:??/1/??:??.??:??] en negativo girona con 74.537 pasajero uno 30,5 por 100 menos y palma_de_mallorca con uno descenso de el 6 por 100 hasta 125.295 pasajero en el lado oponer el mayor aumento lo registrar fuerteventura con 74.537 viajero uno 53,5 por 100 más el grado de ocupación de el compañía de bajo coste alcanzar el 70 por 100 el mes pasar uno tasa de cinto punto superior a el de el compañía tradicional ryanair easyjet y air_berlin se mantener como el principal compañía de bajo coste en españa en 2010 con 6/10 pasajero en conjunto el 3 compañía aumentar el cifra de pasajero en [??:??/1/??:??.??:??] con respecto a el mismo mes de el año pasar",
        "lemmatized_text_reduced": "aerolínea coste transportar canarias pasajero suponer aumento respecto mismo mes ejercicio anterior convertir isla región persona trasladar low cost dato difundir instituto_de_estudios_turísticos iet dependiente ministerio_de_industria turismo comercio compañía tradicional volar isla pasajero pasar mes representar descenso relación mismo dato conjunto españa low cost transportar millón pasajero suponer aumento respecto mismo mes ejercicio anterior compañía tradicional trasladar millón viajero mercado reino_unido alemania liderar entrada compañía coste pasajero elegir vía respectivamente aumento mercado británico viajero alemán pasajero italia 3 emisor incrementar llegada viajero equivalente total entrada vía seguir francia total viajero hacer año canarias encabezar ranking entrada compañía coste cataluña entrada viajero comunidad_de_madrid seguir comunidad_valenciana pasajero andalucía viajero baleares pasajero descenso término evolución región recibir mayor volumen pasajero coste recuperación actividad haber dejar notar aeropuerto español transportar millones persona en conjunto nacional aerolínea coste transportar millón pasajero suponer aumento respecto mismo mes ejercicio anterior compañía tradicional trasladar millón viajero mercado reino_unido alemania emitir italia emitir conjunto pasajero llegar españa compañía coste 1 mes año registrar crecimiento evolución mercado origen positivo reino_unido alemania liderar entrada compañía coste pasajero elegir vía respectivamente aumento mercado británico viajero alemán pasajero italia 3 emisor incrementar llegada viajero equivalente total entrada vía seguir francia total viajero hacer año resto país presentar aumento generalizar dígito número pasajero coste emitir españa aeropuerto español utilizar aerolínea coste ser barcelona-el_prat alcanzar pasajero suponer aumento madrid-barajas pasajero aumento tenerife_sur pasajero seguir málaga experimentar aumento pasajero alicante recibir viajero gran_canaria aumento viajero aeropuerto cerrar negativo girona pasajero palma_de_mallorca descenso pasajero lado oponer mayor aumento registrar fuerteventura viajero grado ocupación compañía coste alcanzar mes pasar tasa cinto punto superior compañía tradicional ryanair easyjet air_berlin mantener principal compañía coste españa pasajero conjunto compañía aumentar cifra pasajero respecto mismo mes año pasar",
        "persons": [
            "En",
            "Tenerife_Sur",
            "Ryanair"
        ],
        "locations": [
            "Canarias",
            "España",
            "Italia",
            "Canarias",
            "Cataluña",
            "Comunidad_Valenciana",
            "Andalucía",
            "Baleares",
            "Reino_Unido",
            "España",
            "Italia",
            "España",
            "Málaga",
            "Alicante",
            "Gran_Canaria",
            "Girona",
            "Palma_de_Mallorca",
            "España"
        ],
        "organizations": [
            "Instituto_de_Estudios_Turísticos",
            "IET",
            "Ministerio_de_Industria",
            "Turismo",
            "Comercio",
            "Reino_Unido",
            "Alemania",
            "Francia",
            "Comunidad_de_Madrid",
            "Alemania",
            "Italia",
            "Reino_Unido",
            "Alemania",
            "Francia",
            "Barcelona-El_Prat",
            "Fuerteventura",
            "Air_Berlin"
        ],
        "others": [
            "Millones",
            "Madrid-Barajas"
        ],
        "dates": [
            "[??:??/1/??:??.??:??]",
            "[??:??/1/??:??.??:??]",
            "[??:??/1/??:??.??:??]",
            "[??:??/1/2010:??.??:??]",
            "[??:??/1/??:??.??:??]",
            "[??:??/1/??:??.??:??]",
            "[??:??/1/??:??.??:??]",
            "[??:??/1/??:??.??:??]"
        ],
        "numbers": [
            "486.42",
            "24",
            "100",
            "386.76",
            "1,5",
            "100",
            "2010",
            "1,7",
            "14,4",
            "100",
            "1,6",
            "4,3",
            "100",
            "29,8",
            "19,7",
            "100",
            "2,8",
            "100",
            "520.261",
            "9,6",
            "100",
            "343.175",
            "26,3",
            "100",
            "238.75",
            "13,7",
            "100",
            "6,3",
            "100",
            "110.21",
            "22,3",
            "100",
            "21,8",
            "100",
            "379.465",
            "15,7",
            "100",
            "258.882",
            "20,2",
            "100",
            "224.365",
            "9,9",
            "100",
            "213.332",
            "13,9",
            "100",
            "128.88",
            "6,5",
            "100",
            "1,7",
            "1,7",
            "14,4",
            "100",
            "1,6",
            "4,3",
            "100",
            "63,2",
            "100",
            "3",
            "29,8",
            "19,7",
            "100",
            "2,8",
            "100",
            "520.261",
            "9,6",
            "100",
            "343.175",
            "26,3",
            "100",
            "238.75",
            "13,7",
            "100",
            "6,3",
            "100",
            "110.21",
            "22,3",
            "100",
            "2",
            "297.993",
            "41",
            "100",
            "258.882",
            "20,2",
            "100",
            "182.509",
            "15,6",
            "100",
            "7,8",
            "100",
            "163.561",
            "156.63",
            "2,2",
            "100",
            "32,8",
            "100",
            "139.887",
            "2",
            "74.537",
            "30,5",
            "100",
            "6",
            "100",
            "125.295",
            "74.537",
            "53,5",
            "100",
            "70",
            "100",
            "2010",
            "6/10",
            "3"
        ]
    }
}
