{
    "province": "LAS PALMAS",
    "date": "2010-03-02T00:00:00",
    "url": "https://www.20minutos.es/noticia/641822/0/",
    "title": {
        "raw_text": "NC asegura que la cifra del Gobierno de Canarias de crear 80.000 empleos \"es un imposible, pura propaganda\"",
        "lemmatized_text": "nc asegurar que el cifra de el gobierno_de_canarias de crear 80 empleo ser uno imposible puro propaganda",
        "lemmatized_text_reduced": "nc asegurar cifra gobierno_de_canarias crear empleo ser imposible puro propaganda",
        "persons": [],
        "locations": [],
        "organizations": [
            "NC",
            "Gobierno_de_Canarias"
        ],
        "others": [],
        "dates": [],
        "numbers": [
            "80"
        ]
    },
    "lead": {
        "raw_text": "Nueva Canarias (NC) ha asegurado tras conocer las cifras del paro en el archipiélago de los dos primeros meses del año, con 9.156 parados más, que \"el anuncio del Gobierno autonómico de que se crearán 80.000 empleos entre el presente año y mayo de 2011 es un imposible, pura propaganda\".",
        "lemmatized_text": "nueva_canarias nc haber asegurar tras conocer el cifra de el paro en el archipiélago de el 2 1 mes de el año con 9.156 parado más que el anuncio de el gobierno autonómico de que se crear 80 empleo entre el presente año y [??:??/5/2011:??.??:??] ser uno imposible puro propaganda",
        "lemmatized_text_reduced": "nueva_canarias nc haber asegurar conocer cifra paro archipiélago 1 mes año parado anuncio gobierno autonómico crear empleo presente año ser imposible puro propaganda",
        "persons": [
            "Nueva_Canarias"
        ],
        "locations": [],
        "organizations": [
            "NC",
            "Gobierno"
        ],
        "others": [],
        "dates": [
            "[??:??/5/2011:??.??:??]"
        ],
        "numbers": [
            "2",
            "9.156",
            "80"
        ]
    },
    "body": {
        "raw_text": "En un comunicado, la formación explicó que de hecho, los datos de enero y febrero, logran un nuevo récord histórico en el número de parados registrados, que ya alcanzan las 257.939 personas, suponiendo además el fin de la estabilización del desempleo alrededor de los 248.000 parados durante los últimos 7 meses del año 2009. \"Un repunte que tira por tierra las afirmaciones del consejero de Empleo del Gobierno de Canarias, Jorge Rodríguez, cuando anunciaba que el desempleo en las Islas se había estabilizado\", apuntó NC. \"Un desacierto más —añadió— del Ejecutivo autonómico en materia de empleo al que ya nos estamos acostumbrando en el archipiélago y que demuestra una profunda irresponsabilidad ya que lo que pretenden es hacer propaganda electoral sin que en la práctica se estén tomando las medidas adecuadas para frenar el paro que es un drama en Canarias\". NC hizo especial hincapié en los numerosos anuncios de medidas \"que han quedado en nada o que ni siquiera estaban estructuradas como el aumento del impuesto sobre el tabaco rubio para generar 10.000 puestos de trabajo o la creación de 80.000 empleos, 20.000 de ellos a través del pago de los costes de la seguridad social a las empresas que amplíen su plantilla\". La organización nacionalista apuntó que, por el contrario, el Gobierno canario lo que ha hecho es reducir en los tres últimos presupuestos de Canarias la inversión productiva y ha incrementado el gasto corriente. \"Lo contrario de lo que deben ser unas cuentas anticrisis y que fomenten el empleo\", matizó NC. El partido que lidera Román Rodríguez instó así al Gobierno autonómico a que ponga en marcha un plan de obras en los municipios como el que se ha llevado a cabo por parte del Ejecutivo central, conocido como Plan Zapatero, ya que éste ha conseguido mantener al menos el empleo en la construcción, como demuestra el hecho de que entre mayo y octubre de 2009 el paro disminuyó de forma continua en este sector, y sin embargo, sube por cuarto mes consecutivo desde noviembre de 2009, alcanzando en febrero 52.243 parados, un 20,2 por ciento del total de desempleados de las islas.",
        "lemmatized_text": "en uno comunicado el formación explicar que de hecho el dato de [??:??/1/??:??.??:??] y [??:??/2/??:??.??:??] lograr uno nuevo récord histórico en el número de parado registrar que ya alcanzar el 257.939 persona suponer además el fin de el estabilización de el desempleo alrededor_de el 248 parado durante el último 7 mes de el [??:??/??/2009:??.??:??] uno repunte que tirar por tierra el afirmación de el consejero de empleo_del_gobierno_de_canarias jorge_rodríguez cuando anunciar que el desempleo en el islas se haber estabilizar apuntar nc uno desacierto más añadir de el ejecutivo autonómico en_materia_de empleo a el que ya nos estar acostumbrar en el archipiélago y que demostrar uno profundo irresponsabilidad ya_que el que pretender ser hacer propaganda electoral sin que en el práctica se estar tomar el medida adecuar para frenar el paro que ser uno drama en canarias nc hacer especial hincapié en el numeroso anuncio de medida que haber quedar en nada o que ni siquiera estar estructurar como el aumento de el impuesto sobre el tabaco rubio para generar 10 puesto de trabajo o el creación de 80 empleo 20 de ellos a través de el pago de el coste de el seguridad social a el empresa que ampliar su plantilla el organización nacionalista apuntar que por_el_contrario el gobierno canario el que haber hacer ser reducir en el 3 último presupuesto de canarias el inversión productivo y haber incrementar el gasto corriente el contrario de el que deber ser uno cuenta anticrisis y que fomentar el empleo matizar nc el partido que liderar román_rodríguez instar así a el gobierno autonómico a que poner en marcha uno plan de obra en el municipio como el que se haber llevar_a_cabo por parte de el ejecutivo central conocer como plan_zapatero ya_que este haber conseguir mantener a el menos el empleo en el construcción como demostrar el hecho de que entre [??:??/5/??:??.??:??] y [??:??/10/2009:??.??:??] el paro disminuir de forma continuo en este sector y sin embargo subir por 4 mes consecutivo desde [??:??/11/2009:??.??:??] alcanzar en [??:??/2/??:??.??:??] 52.243 parado uno 20,2 por 100 de el total de desempleado de el isla",
        "lemmatized_text_reduced": "comunicado formación explicar hecho dato lograr nuevo récord histórico número parado registrar alcanzar persona suponer fin estabilización desempleo parado último mes repunte tirar tierra afirmación consejero empleo_del_gobierno_de_canarias jorge_rodríguez anunciar desempleo islas haber estabilizar apuntar nc desacierto añadir ejecutivo autonómico empleo estar acostumbrar archipiélago demostrar profundo irresponsabilidad pretender ser hacer propaganda electoral práctica estar tomar medida adecuar frenar paro ser drama canarias nc hacer especial hincapié numeroso anuncio medida haber quedar estar estructurar aumento impuesto tabaco rubio generar puesto trabajo creación empleo través pago coste seguridad social empresa ampliar plantilla organización nacionalista apuntar gobierno canario haber hacer ser reducir último presupuesto canarias inversión productivo haber incrementar gasto corriente contrario deber ser cuenta anticrisis fomentar empleo matizar nc partido liderar román_rodríguez instar gobierno autonómico poner marcha plan obra municipio haber llevar_a_cabo parte ejecutivo central conocer plan_zapatero haber conseguir mantener empleo construcción demostrar hecho paro disminuir forma continuo sector embargo subir 4 mes consecutivo alcanzar parado total desempleado isla",
        "persons": [
            "Jorge_Rodríguez",
            "Román_Rodríguez",
            "Plan_Zapatero"
        ],
        "locations": [
            "Islas",
            "Canarias",
            "Canarias"
        ],
        "organizations": [
            "Empleo_del_Gobierno_de_Canarias",
            "NC",
            "Ejecutivo",
            "NC",
            "Gobierno",
            "NC",
            "Gobierno",
            "Ejecutivo"
        ],
        "others": [],
        "dates": [
            "[??:??/1/??:??.??:??]",
            "[??:??/2/??:??.??:??]",
            "[??:??/??/2009:??.??:??]",
            "[??:??/5/??:??.??:??]",
            "[??:??/10/2009:??.??:??]",
            "[??:??/11/2009:??.??:??]",
            "[??:??/2/??:??.??:??]"
        ],
        "numbers": [
            "257.939",
            "248",
            "7",
            "10",
            "80",
            "20",
            "3",
            "52.243",
            "20,2",
            "100"
        ]
    }
}
