{
    "province": "LAS PALMAS",
    "date": "2008-06-02T00:00:00",
    "url": "https://www.20minutos.es/noticia/384855/0/precio/vivienda/palmas/",
    "title": {
        "raw_text": "El precio de la vivienda usada en Canarias cayó un 1,8% en el último año",
        "lemmatized_text": "el precio de el vivienda usar en canarias caer uno 1,8/100 en el último año",
        "lemmatized_text_reduced": "precio vivienda usar canarias caer último año",
        "persons": [],
        "locations": [
            "Canarias"
        ],
        "organizations": [],
        "others": [],
        "dates": [],
        "numbers": [
            "1,8/100"
        ]
    },
    "lead": {
        "raw_text": "Según el portal Facilisimo.com El archipiélago canario es la cuarta Comunidad Autónoma con mayor descenso intermensual. CONSULTA AQUÍ MÁS NOTICIAS DE LAS PALMAS Y TENERIFE",
        "lemmatized_text": "según el portal facilisimo.com_el archipiélago canario ser el 4 comunidad_autónoma con mayor descenso intermensual consulta_aquí_más_noticias_de_las_palmas_y_tenerife",
        "lemmatized_text_reduced": "portal facilisimo.com_el archipiélago canario ser 4 comunidad_autónoma mayor descenso intermensual consulta_aquí_más_noticias_de_las_palmas_y_tenerife",
        "persons": [],
        "locations": [],
        "organizations": [
            "Comunidad_Autónoma",
            "CONSULTA_AQUÍ_MÁS_NOTICIAS_DE_LAS_PALMAS_Y_TENERIFE"
        ],
        "others": [
            "Facilisimo.com_El"
        ],
        "dates": [],
        "numbers": []
    },
    "body": {
        "raw_text": "El precio de la vivienda de segunda mano en Canarias cayó un 1,8% en los últimos doce meses, según , según el 'Preciómetro' correspondiente al mes de mayo de Facilisimo.com . La situación actual en realidad no es una sorpresa Estos datos sitúan al Archipiélago como la cuarta Comunidad Autónoma con mayor descenso intermensual , por detrás de Castilla-La Mancha (-2,6%), Asturias (-2,1%) y Castilla y León (-1,9%). Por su parte, sólo Andalucía y País Vasco presentaron ascensos, del 0,05% en ambos casos. Caídas del 5,6% A nivel nacional el precio de la vivienda de segunda mano cayó un 5,6% en los últimos doce meses, según el 'Preciómetro' de mayo de Facilisimo.com. Además, en lo que va de año, los precios han bajado un 3,6%, mientras que sólo en mayo cayeron un 1% respecto al mes anterior . Según el portal inmobiliario, \"la situación actual en realidad no es una sorpresa \". Así, a primeros de año, Facilisimo.com estimó un descenso anual de un 10% aproximadamente, índice al que se acercan las cifras, \"incluso más suavemente de lo esperado \", matiza. El 'Preciómetro' es una herramienta de Facilisimo.com que estudia las fluctuaciones del mercado de la vivienda a tiempo real a través de una muestra de más de 100.000 inmuebles de segunda mano de toda España. CONSULTA AQUÍ MÁS NOTICIAS DE LAS PALMAS Y TENERIFE",
        "lemmatized_text": "el precio de el vivienda de_segunda_mano en canarias caer uno 1,8/100 en el último 12 mes según según el preciómetro correspondiente a el [??:??/5/??:??.??:??] de facilisimo.com el situación actual en realidad no ser uno sorpresa estos dato situar a el archipiélago como el 4 comunidad_autónoma con mayor descenso intermensual por detrás_de castilla-la_mancha -2,6/100 asturias -2,1/100 y castilla y león -1,9/100 por su parte sólo andalucía y país_vasco presentar ascenso de el 0,05/100 en ambos caso caer de el 5,6/100 a nivel nacional el precio de el vivienda de_segunda_mano caer uno 5,6/100 en el último 12 mes según el preciómetro de [??:??/5/??:??.??:??] de facilisimo com además en el que ir de año el precio haber bajar uno 3,6/100 mientras_que sólo en [??:??/5/??:??.??:??] caer uno 1/100 respecto a el mes anterior según el portal inmobiliario el situación actual en realidad no ser uno sorpresa así a 1 de año facilisimo.com estimar uno descenso anual de uno 10/100 aproximadamente índice a el que se acercar el cifra incluso más suavemente de el esperar matizar el preciómetro ser uno herramienta de facilisimo.com que estudiar el fluctuación de el mercado de el vivienda a tiempo real a_través_de uno muestra de más de 100 inmueble de_segunda_mano de todo españa consulta_aquí_más_noticias_de_las_palmas_y_tenerife",
        "lemmatized_text_reduced": "precio vivienda canarias caer último mes preciómetro correspondiente facilisimo.com situación actual realidad ser sorpresa estos dato situar archipiélago 4 comunidad_autónoma mayor descenso intermensual castilla-la_mancha asturias castilla león parte andalucía país_vasco presentar ascenso caso caer a nivel nacional precio vivienda caer último mes preciómetro facilisimo com ir año precio haber bajar caer respecto mes anterior portal inmobiliario situación actual realidad ser sorpresa 1 año facilisimo.com estimar descenso anual aproximadamente índice acercar cifra suavemente esperar matizar preciómetro ser herramienta facilisimo.com estudiar fluctuación mercado vivienda tiempo real muestra inmueble españa consulta_aquí_más_noticias_de_las_palmas_y_tenerife",
        "persons": [
            "Estos",
            "León",
            "Preciómetro"
        ],
        "locations": [
            "Canarias",
            "Archipiélago",
            "Asturias",
            "Castilla",
            "Andalucía",
            "Facilisimo",
            "España"
        ],
        "organizations": [
            "Facilisimo.com",
            "Comunidad_Autónoma",
            "Castilla-La_Mancha",
            "País_Vasco",
            "Facilisimo.com",
            "Facilisimo.com",
            "CONSULTA_AQUÍ_MÁS_NOTICIAS_DE_LAS_PALMAS_Y_TENERIFE"
        ],
        "others": [
            "Preciómetro",
            "A",
            "Preciómetro"
        ],
        "dates": [
            "[??:??/5/??:??.??:??]",
            "[??:??/5/??:??.??:??]",
            "[??:??/5/??:??.??:??]"
        ],
        "numbers": [
            "1,8/100",
            "12",
            "-2,6/100",
            "-2,1/100",
            "-1,9/100",
            "0,05/100",
            "5,6/100",
            "5,6/100",
            "12",
            "3,6/100",
            "1/100",
            "10/100",
            "100"
        ]
    }
}
