{
    "province": "LAS PALMAS",
    "date": "2010-06-02T00:00:00",
    "url": "https://www.20minutos.es/noticia/725490/0/",
    "title": {
        "raw_text": "Cámara de Las Palmas recuerda que aún no se está creando empleo estable pese a ver los datos como una buena señal",
        "lemmatized_text": "cámara_de_las_palmas recordar que aun no se estar crear empleo estable pese_a ver el dato como uno bueno señal",
        "lemmatized_text_reduced": "cámara_de_las_palmas recordar estar crear empleo estable ver dato bueno señal",
        "persons": [
            "Cámara_de_Las_Palmas"
        ],
        "locations": [],
        "organizations": [],
        "others": [],
        "dates": [],
        "numbers": []
    },
    "lead": {
        "raw_text": "El presidente de la Cámara de Comercio de Las Palmas, Ángel Luis Tadeo Tejera, a la vista de los datos del paro en las islas durante el mes de mayo --con una baja de 126 personas en el número de parados-- ha recordado que aún no se está creando empleo estable, aunque ha considerado las cifras como una buena señal, según informó hoy en un comunicado.",
        "lemmatized_text": "el presidente de el cámara_de_comercio_de_las_palmas ángel_luis_tadeo_tejera a el vista de el dato de el paro en el isla durante el [??:??/5/??:??.??:??] con uno baja de 126 persona en el número de parado haber recordar que aun no se estar crear empleo estable aunque haber considerar el cifra como uno bueno señal según informar hoy en uno comunicado",
        "lemmatized_text_reduced": "presidente cámara_de_comercio_de_las_palmas ángel_luis_tadeo_tejera vista dato paro isla baja persona número parado haber recordar estar crear empleo estable haber considerar cifra bueno señal informar comunicado",
        "persons": [
            "Ángel_Luis_Tadeo_Tejera"
        ],
        "locations": [],
        "organizations": [
            "Cámara_de_Comercio_de_Las_Palmas"
        ],
        "others": [],
        "dates": [
            "[??:??/5/??:??.??:??]"
        ],
        "numbers": [
            "126"
        ]
    },
    "body": {
        "raw_text": "De esta manera, incidió en la necesidad de \"crear un clima positivo para iniciar definitivamente el camino de la recuperación\". \"Y cambiar la tendencia de lo que llevamos de año es una buena señal, sobre todo en mayo, un mes en que el paro crece tradicionalmente en el archipiélago\", dijo. Aun así, el máximo representante cameral hizo especial hincapié en el nuevo crecimiento del paro en Servicios, que acumula dos tercios del desempleo de Canarias. De hecho, es la Construcción el sector más determinante para el leve retroceso del mes de mayo, \"un sector en el que la temporalidad es alta, por lo que no se puede decir que se esté creando aún empleo estable\". Tadeo Tejera insistió en la necesidad de alcanzar un acuerdo para abordar la reforma laboral o, en cualquier caso, que no se siga dilatando \"y sea realmente el 11 de junio la fecha límite para ofrecer al empresariado los mecanismos necesarios para la creación de empleo\". Por su parte, el número de desempleados inscritos en las oficinas de los servicios públicos de empleo bajó en 126 personas en el mes de mayo en la Comunidad Autónoma de Canarias, lo que supone un descenso del 0,05 por ciento con respecto al mes de abril, con lo que la cifra total de parados se sitúa en la región en 265.916. En términos interanuales, el paro en el mes de mayo en el archipiélago registró un aumento de 16.255 personas, un 6,51 por ciento más que en el mismo mes del año anterior, según los datos aportados hoy por el Ministerio de Trabajo e Inmigración. En el conjunto nacional, el número de parados bajó en 76.223 personas en mayo, un 1,84% respecto a abril, con lo que el volumen total de desempleados se situó en 4.066.202 personas, lo que supone el segundo descenso consecutivo tras el de abril.",
        "lemmatized_text": "de este manera incidir en_la_necesidad_de crear uno clima positivo para iniciar definitivamente el camino de el recuperación y cambiar el tendencia de el que llevar de año ser uno bueno señal sobre todo en [??:??/5/??:??.??:??] uno mes en que el paro crecer tradicionalmente en el archipiélago decir aun así el máximo representante cameral hacer especial hincapié en el nuevo crecimiento de el paro en servicios que acumular 2/3 de el desempleo de canarias de hecho ser el construcción el sector más determinante para el leve retroceso de el [??:??/5/??:??.??:??] uno sector en el que el temporalidad ser alto por el que no se poder decir que se estar crear aun empleo estable tadeo_tejera insistir en_la_necesidad_de alcanzar uno acuerdo para abordar el reforma laboral o en cualquiera caso que no se seguir dilatar y ser realmente el [??:11/6/??:??.??:??] el fecha límite para ofrecer a el empresariado el mecanismo necesario para el creación de empleo por su parte el número de desempleado inscribir en el oficina de el servicio público de empleo bajar en 126 persona en el [??:??/5/??:??.??:??] en el comunidad_autónoma_de_canarias el que suponer uno descenso de el 0,05 por 100 con respecto a el [??:??/4/??:??.??:??] con el que el cifra total de parado se situar en el región en 265.916 en término interanual el paro en el [??:??/5/??:??.??:??] en el archipiélago registrar uno aumento de 16.255 persona uno 6,51 por 100 más que en el mismo mes de el año anterior según el dato aportar hoy por el ministerio_de_trabajo y inmigración en el conjunto nacional el número de parado bajar en 76.223 persona en [??:??/5/??:??.??:??] uno 1,84/100 respecto_a [??:??/4/??:??.??:??] con el que el volumen total de desempleado se situar en 4.066.202 persona el que suponer el 2 descenso consecutivo tras el de [??:??/4/??:??.??:??]",
        "lemmatized_text_reduced": "manera incidir crear clima positivo iniciar definitivamente camino recuperación cambiar tendencia llevar año ser bueno señal mes paro crecer tradicionalmente archipiélago decir máximo representante cameral hacer especial hincapié nuevo crecimiento paro servicios acumular desempleo canarias hecho ser construcción sector determinante leve retroceso sector temporalidad ser alto poder decir estar crear empleo estable tadeo_tejera insistir alcanzar acuerdo abordar reforma laboral caso seguir dilatar ser realmente fecha límite ofrecer empresariado mecanismo necesario creación empleo parte número desempleado inscribir oficina servicio público empleo bajar persona comunidad_autónoma_de_canarias suponer descenso respecto cifra total parado situar región término interanual paro archipiélago registrar aumento persona mismo mes año anterior dato aportar ministerio_de_trabajo inmigración conjunto nacional número parado bajar persona volumen total desempleado situar persona suponer 2 descenso consecutivo",
        "persons": [
            "Tadeo_Tejera"
        ],
        "locations": [
            "Servicios",
            "Canarias",
            "Comunidad_Autónoma_de_Canarias"
        ],
        "organizations": [
            "Ministerio_de_Trabajo",
            "Inmigración"
        ],
        "others": [
            "Construcción"
        ],
        "dates": [
            "[??:??/5/??:??.??:??]",
            "[??:??/5/??:??.??:??]",
            "[??:11/6/??:??.??:??]",
            "[??:??/5/??:??.??:??]",
            "[??:??/4/??:??.??:??]",
            "[??:??/5/??:??.??:??]",
            "[??:??/5/??:??.??:??]",
            "[??:??/4/??:??.??:??]",
            "[??:??/4/??:??.??:??]"
        ],
        "numbers": [
            "2/3",
            "126",
            "0,05",
            "100",
            "265.916",
            "16.255",
            "6,51",
            "100",
            "76.223",
            "1,84/100",
            "4.066.202"
        ]
    }
}
