{
    "province": "LAS PALMAS",
    "date": "2011-01-10T00:00:00",
    "url": "https://www.20minutos.es/noticia/923865/0/",
    "title": {
        "raw_text": "Canarias prevé cerrar con datos \"positivos\" la llegada de turistas en 2010",
        "lemmatized_text": "canario prever cerrar con dato positivo el llegada de turista en 2010",
        "lemmatized_text_reduced": "canario prever cerrar dato positivo llegada turista",
        "persons": [],
        "locations": [],
        "organizations": [],
        "others": [],
        "dates": [],
        "numbers": [
            "2010"
        ]
    },
    "lead": {
        "raw_text": "El viceconsejero de Turismo del Gobierno de Canarias, Ricardo Fernández, ha señalado que con \"casi toda seguridad\" prevé cerrar con datos \"positivos\" la llegada de visitantes en 2010 con respecto a 2009, principalmente motivado por la mejoría en las cifras del segundo trimestre, así como de los meses de octubre y noviembre.",
        "lemmatized_text": "el viceconsejero de turismo_del_gobierno_de_canarias ricardo_fernández haber señalar que con casi todo seguridad prever cerrar con dato positivo el llegada de visitante en 2010 con_respecto_a 2009 principalmente motivar por el mejoría en el cifra de el 2 trimestre así_como de el mes de [??:??/10/??:??.??:??] y [??:??/11/??:??.??:??]",
        "lemmatized_text_reduced": "viceconsejero turismo_del_gobierno_de_canarias ricardo_fernández haber señalar seguridad prever cerrar dato positivo llegada visitante principalmente motivar mejoría cifra 2 trimestre mes",
        "persons": [
            "Ricardo_Fernández"
        ],
        "locations": [],
        "organizations": [
            "Turismo_del_Gobierno_de_Canarias"
        ],
        "others": [],
        "dates": [
            "[??:??/10/??:??.??:??]",
            "[??:??/11/??:??.??:??]"
        ],
        "numbers": [
            "2010",
            "2009"
        ]
    },
    "body": {
        "raw_text": "El viceconsejero de Turismo del Gobierno de Canarias, Ricardo Fernández, ha señalado que con \"casi toda seguridad\" prevé cerrar con datos \"positivos\" la llegada de visitantes en 2010 con respecto a 2009, principalmente motivado por la mejoría en las cifras del segundo trimestre, así como de los meses de octubre y noviembre. \"En líneas generales el cierre, casi con toda seguridad, va a ser positivo frente al de 2009. Hasta el mes de junio no se produjo ese cambio de tendencia, pasar de número negativos a positivos, y en el último trimestre los datos son conocidos, octubre y noviembre los datos son conocidos, y en diciembre casi con toda seguridad va a ser datos positivos\", apuntilló Fernández en un comunicado. De todos modos, y en relación a los datos de diciembre, aunque no dio cifras, aseguró que según se ha manifestado el sector \"ha habido una mejor ocupación en líneas generales en las distintas islas\" aunque matizó que La Palma \"siempre tiene una carencia y es un problema de conectividad aérea\" en el que, afirmó, están trabajando con el Cabildo, de ahí que en dicha isla los datos \"no son todo lo bueno\" que querían. Por su parte, la gerente de Promotur, María Méndez, recordó que Canarias ha liderado en noviembre el sector turístico internacional en España con un crecimiento del 4,7 por ciento frente al 2,8 por ciento del conjunto nacional; mientras que en el acumulado Canarias subió un 5,2 por ciento frente al 1,3 por ciento nacional. Méndez se refirió asimismo al mercado peninsular, del que dijo que en noviembre Canarias fue el tercer mes consecutivo con datos \"positivos\" y en el acumulado aparecen la cifra negativa del -2,6 por ciento, lo que justificó indicando que al comienzo de 2010 hubo meses malos. Sin embargo, Fernández sí incidió en que se está percibiendo \"un cambio de tendencia frente a otros años\" lo que justificó en una mejora de la economía en diferentes países europeos. A modo de ejemplo, se refirió al gasto turístico donde, dijo, Canarias \"está a la cabeza\" en el conjunto nacional. Por otro lado, cuestionado por cómo van a conseguir ese millón más de turistas que el presidente canario, Paulino Rivero, se ha puesto como objetivo en 2011, indicó que para ello se está trabajando desde distintos frentes con las líneas aéreas a través de las rebajas de tasas, así como en las ferias. En cuanto a las previsiones para el verano de 2011, apuntó que en turismo internacional las expectativas están en un incremento del 5 por ciento, mientras que del mercado nacional no hay previsiones porque \"cada vez se reserva más tarde\". Entre los objetivos de este año se encuentra también el mercado ruso.",
        "lemmatized_text": "el viceconsejero de turismo_del_gobierno_de_canarias ricardo_fernández haber señalar que con casi todo seguridad prever cerrar con dato positivo el llegada de visitante en 2010 con_respecto_a 2009 principalmente motivar por el mejoría en el cifra de el 2 trimestre así_como de el mes de [??:??/10/??:??.??:??] y [??:??/11/??:??.??:??] en_líneas_generales el cierre casi con todo seguridad ir a ser positivo frente a el de 2009 hasta el [??:??/6/??:??.??:??] no se producir ese cambio de tendencia pasar de número negativo a positivo y en el último trimestre el dato ser conocer [??:??/10/??:??.??:??] y [??:??/11/??:??.??:??] el dato ser conocer y en [??:??/12/??:??.??:??] casi con todo seguridad ir a ser dato positivo apuntillar fernández en uno comunicado de_todos_modos y en relación a el dato de [??:??/12/??:??.??:??] aunque no dar cifra asegurar que según se haber manifestar el sector haber haber uno mejor ocupación en_líneas_generales en el distinto isla aunque matizar que la_palma siempre tener uno carencia y ser uno problema de conectividad aéreo en el que afirmar estar trabajar con el cabildo de ahí que en decir isla el dato no ser todo lo bueno que querer por su parte el gerente de promotur maría_méndez recordar que canarias haber liderar en [??:??/11/??:??.??:??] el sector turístico internacional en españa con uno crecimiento de el 4,7 por 100 frente a el 2,8 por 100 de el conjunto nacional mientras_que en el acumular canarias subir uno 5,2 por 100 frente a el 1,3 por 100 nacional méndez se referir asimismo a el mercado peninsular de el que decir que en [??:??/11/??:??.??:??] canarias ser el 3 mes consecutivo con dato positivo y en el acumular aparecer el cifra negativo de el -2,6 por 100 el que justificar indicar que a el comienzo de 2010 haber mes malo sin embargo fernández sí incidir en que se estar percibir uno cambio de tendencia frente_a otro año el que justificar en uno mejora de el economía en diferente país europeo a_modo_de ejemplo se referir a el gasto turístico donde decir canarias estar a el cabeza en el conjunto nacional por_otro_lado cuestionar por cómo ir a conseguir ese millón más de turista que el presidente canario paulino_rivero se haber poner como objetivo en 2011 indicar que para ello se estar trabajar desde distinto frente con el línea aéreo a_través_de el rebaja de tasa así_como en el feria en_cuanto_a el previsión para el verano de 2011 apuntar que en turismo internacional el expectativa estar en uno incremento de el 5 por 100 mientras_que de el mercado nacional no haber previsión porque cada vez se reservar más tarde entre el objetivo de este año se encontrar también el mercado ruso",
        "lemmatized_text_reduced": "viceconsejero turismo_del_gobierno_de_canarias ricardo_fernández haber señalar seguridad prever cerrar dato positivo llegada visitante principalmente motivar mejoría cifra 2 trimestre mes cierre seguridad ir ser positivo producir cambio tendencia pasar número negativo positivo último trimestre dato ser conocer dato ser conocer seguridad ir ser dato positivo apuntillar fernández comunicado relación dato dar cifra asegurar haber manifestar sector haber haber mejor ocupación distinto isla matizar la_palma tener carencia ser problema conectividad aéreo afirmar estar trabajar cabildo decir isla dato ser bueno querer parte gerente promotur maría_méndez recordar canarias haber liderar sector turístico internacional españa crecimiento frente conjunto nacional acumular canarias subir frente nacional méndez referir mercado peninsular decir canarias ser 3 mes consecutivo dato positivo acumular aparecer cifra negativo justificar indicar comienzo haber mes malo embargo fernández incidir estar percibir cambio tendencia año justificar mejora economía país europeo ejemplo referir gasto turístico decir canarias estar cabeza conjunto nacional cuestionar ir conseguir millón turista presidente canario paulino_rivero haber poner objetivo indicar estar trabajar frente línea aéreo rebaja tasa feria previsión verano apuntar turismo internacional expectativa estar incremento mercado nacional haber previsión vez reservar objetivo año encontrar mercado ruso",
        "persons": [
            "Ricardo_Fernández",
            "Fernández",
            "María_Méndez",
            "Méndez",
            "Fernández",
            "Paulino_Rivero"
        ],
        "locations": [
            "La_Palma",
            "Canarias",
            "España",
            "Canarias",
            "Canarias",
            "Canarias"
        ],
        "organizations": [
            "Turismo_del_Gobierno_de_Canarias",
            "Cabildo"
        ],
        "others": [
            "Promotur"
        ],
        "dates": [
            "[??:??/10/??:??.??:??]",
            "[??:??/11/??:??.??:??]",
            "[??:??/6/??:??.??:??]",
            "[??:??/10/??:??.??:??]",
            "[??:??/11/??:??.??:??]",
            "[??:??/12/??:??.??:??]",
            "[??:??/12/??:??.??:??]",
            "[??:??/11/??:??.??:??]",
            "[??:??/11/??:??.??:??]"
        ],
        "numbers": [
            "2010",
            "2009",
            "2009",
            "4,7",
            "100",
            "2,8",
            "100",
            "5,2",
            "100",
            "1,3",
            "100",
            "-2,6",
            "100",
            "2010",
            "2011",
            "2011",
            "5",
            "100"
        ]
    }
}
