{
    "province": "LAS PALMAS",
    "date": "2011-01-10T00:00:00",
    "url": "https://www.20minutos.es/noticia/924292/0/",
    "title": {
        "raw_text": "Soria informa al Comité Ejecutivo del PP de la denuncia que presentó contra la juez Rosell",
        "lemmatized_text": "soria informar a el comité_ejecutivo_del_pp de el denuncia que presentar contra el juez rosell",
        "lemmatized_text_reduced": "soria informar comité_ejecutivo_del_pp denuncia presentar juez rosell",
        "persons": [
            "Rosell"
        ],
        "locations": [
            "Soria"
        ],
        "organizations": [
            "Comité_Ejecutivo_del_PP"
        ],
        "others": [],
        "dates": [],
        "numbers": []
    },
    "lead": {
        "raw_text": "El presidente del PP canario, José Manuel Soria, ha informado este lunes a los miembros del Comité Ejecutivo Nacional del PP de la denuncia que el pasado 20 de diciembre interpuso contra la juez Victoria Rosell, indicaron a Europa Press fuentes 'populares' asistentes a la reunión.",
        "lemmatized_text": "el presidente de el pp canario josé_manuel_soria haber informar este [L:??/??/??:??.??:??] a el miembro de el comité_ejecutivo_nacional_del_pp de el denuncia que el [??:20/12/??:??.??:??] interponer contra el juez victoria_rosell indicar a europa_press fuente popular asistente a el reunión",
        "lemmatized_text_reduced": "presidente pp canario josé_manuel_soria haber informar miembro comité_ejecutivo_nacional_del_pp denuncia interponer juez victoria_rosell indicar europa_press fuente popular asistente reunión",
        "persons": [
            "José_Manuel_Soria",
            "Victoria_Rosell",
            "Europa_Press"
        ],
        "locations": [],
        "organizations": [
            "PP",
            "Comité_Ejecutivo_Nacional_del_PP"
        ],
        "others": [],
        "dates": [
            "[L:??/??/??:??.??:??]",
            "[??:20/12/??:??.??:??]"
        ],
        "numbers": []
    },
    "body": {
        "raw_text": "El presidente del PP canario, José Manuel Soria, ha informado este lunes a los miembros del Comité Ejecutivo Nacional del PP de la denuncia que el pasado 20 de diciembre interpuso contra la juez Victoria Rosell, indicaron a Europa Press fuentes 'populares' asistentes a la reunión. Soria, acompañado por María Dolores de Cospedal y Federico Trillo, presentó una denuncia ante el Consejo General del Poder Judicial (CGPJ) contra la juez Rosell por actuar en contra de la Ley Orgánica del Poder Judicial \"al asesorar a su pareja sentimental\", el periodista Carlos Sosa, en la redacción de la querella contra el dirigente popular por el caso del salmón, que se archivó en 2009. Además, el ex vicepresidente del Gobierno canario denunció que la magistrada suscribió un manifiesto público en contra de la resolución de archivo de la misma por el Tribunal Superior de Justicia de Canarias (TSJC). En su intervención ante el Comité Ejecutivo, Soria ha informado a los dirigentes del PP de esta iniciativa y ha recordado que ha pedido que el CGPJ analice el disco duro del ordenador por entender que se ha podido producir \"un asesoramiento permanente\" por parte de la juez. Además, el ex vicepresidente del Gobierno canario ha señalado que ahora están a la espera de ver qué decide el Consejo General del Poder Judicial, que dispone de seis meses para instruir esta denuncia. En la misma reunión, Soria ha hecho un análisis de la situación económica y ha elogiado que Mariano Rajoy haga hincapié en que el problema más importante de los españoles es el empleo. Según ha añadido, hay que poner el acento en que el PP es la alternativa que puede solucionar los problemas de la sociedad española, como ya hizo en 1996, según fuentes 'populares'.",
        "lemmatized_text": "el presidente de el pp canario josé_manuel_soria haber informar este [L:??/??/??:??.??:??] a el miembro de el comité_ejecutivo_nacional_del_pp de el denuncia que el [??:20/12/??:??.??:??] interponer contra el juez victoria_rosell indicar a europa_press fuente popular asistente a el reunión soria acompañar por maría_dolores_de_cospedal y federico_trillo presentar uno denuncia ante el consejo_general_del_poder_judicial cgpj contra el juez rosell por actuar en_contra_de el ley_orgánica_del_poder_judicial a el asesorar a su pareja sentimental el periodista carlos_sosa en el redacción de el querella contra el dirigente popular por el caso de el salmón que se archivar en 2009 además el ex vicepresidente de el gobierno canario denunciar que el magistrado suscribir uno manifiesto público en_contra_de el resolución de archivo de el mismo por el tribunal_superior_de_justicia_de_canarias tsjc en su intervención ante el comité_ejecutivo soria haber informar a el dirigente de el pp de este iniciativa y haber recordar que haber pedir que el cgpj analizar el disco duro de el ordenador por entender que se haber poder producir uno asesoramiento permanente por parte de el juez además el ex vicepresidente de el gobierno canario haber señalar que ahora estar a_la_espera_de ver qué decidir el consejo_general_del_poder_judicial que disponer de 6 mes para instruir este denuncia en el mismo reunión soria haber hacer uno análisis de el situación económico y haber elogiar que mariano_rajoy hacer hincapié en que el problema más importante de el español ser el empleo según haber añadir haber que poner el acento en que el pp ser el alternativa que poder solucionar el problema de el sociedad español como ya hacer en 1996 según fuente popular",
        "lemmatized_text_reduced": "presidente pp canario josé_manuel_soria haber informar miembro comité_ejecutivo_nacional_del_pp denuncia interponer juez victoria_rosell indicar europa_press fuente popular asistente reunión soria acompañar maría_dolores_de_cospedal federico_trillo presentar denuncia consejo_general_del_poder_judicial cgpj juez rosell actuar ley_orgánica_del_poder_judicial asesorar pareja sentimental periodista carlos_sosa redacción querella dirigente popular caso salmón archivar ex vicepresidente gobierno canario denunciar magistrado suscribir manifiesto público resolución archivo mismo tribunal_superior_de_justicia_de_canarias tsjc intervención comité_ejecutivo soria haber informar dirigente pp iniciativa haber recordar haber pedir cgpj analizar disco duro ordenador entender haber poder producir asesoramiento permanente parte juez ex vicepresidente gobierno canario haber señalar estar ver decidir consejo_general_del_poder_judicial disponer mes instruir denuncia mismo reunión soria haber hacer análisis situación económico haber elogiar mariano_rajoy hacer hincapié problema importante español ser empleo haber añadir haber poner acento pp ser alternativa poder solucionar problema sociedad español hacer fuente popular",
        "persons": [
            "José_Manuel_Soria",
            "Victoria_Rosell",
            "Europa_Press",
            "María_Dolores_de_Cospedal",
            "Federico_Trillo",
            "Rosell",
            "Carlos_Sosa",
            "Mariano_Rajoy"
        ],
        "locations": [
            "Soria",
            "Soria"
        ],
        "organizations": [
            "PP",
            "Comité_Ejecutivo_Nacional_del_PP",
            "Consejo_General_del_Poder_Judicial",
            "CGPJ",
            "Gobierno",
            "Tribunal_Superior_de_Justicia_de_Canarias",
            "TSJC",
            "Comité_Ejecutivo",
            "Soria",
            "PP",
            "CGPJ",
            "Gobierno",
            "Consejo_General_del_Poder_Judicial",
            "PP"
        ],
        "others": [
            "Ley_Orgánica_del_Poder_Judicial"
        ],
        "dates": [
            "[L:??/??/??:??.??:??]",
            "[??:20/12/??:??.??:??]"
        ],
        "numbers": [
            "2009",
            "6",
            "1996"
        ]
    }
}
