{
    "province": "LAS PALMAS",
    "date": "2011-01-03T00:00:00",
    "url": "https://www.20minutos.es/noticia/918915/0/",
    "title": {
        "raw_text": "El precio de la vivienda nueva disminuye un 3% en Canarias durante 2010",
        "lemmatized_text": "el precio de el vivienda nuevo disminuir uno 3/100 en canarias durante 2010",
        "lemmatized_text_reduced": "precio vivienda nuevo disminuir canarias",
        "persons": [],
        "locations": [
            "Canarias"
        ],
        "organizations": [],
        "others": [],
        "dates": [],
        "numbers": [
            "3/100",
            "2010"
        ]
    },
    "lead": {
        "raw_text": "El precio de la vivienda nueva cayó un 3 por ciento en Canarias, dos décimas menos que en el conjunto nacional (-3,2 por ciento), según Sociedad de Tasación. Así, la Comunidad es la sexta CCAA, junto con Murcia, que menor descenso experimentó en el precio.",
        "lemmatized_text": "el precio de el vivienda nuevo caer uno 3 por 100 en canarias 2 décima menos que en el conjunto nacional -3,2 por 100 según sociedad_de_tasación así el comunidad ser el 6 ccaa junto_con murcia que menor descenso experimentar en el precio",
        "lemmatized_text_reduced": "precio vivienda nuevo caer canarias décima conjunto nacional sociedad_de_tasación comunidad ser 6 ccaa murcia menor descenso experimentar precio",
        "persons": [],
        "locations": [
            "Canarias",
            "Murcia"
        ],
        "organizations": [
            "Sociedad_de_Tasación",
            "Comunidad",
            "CCAA"
        ],
        "others": [],
        "dates": [],
        "numbers": [
            "3",
            "100",
            "2",
            "-3,2",
            "100"
        ]
    },
    "body": {
        "raw_text": "El precio de la vivienda nueva cayó un 3 por ciento en Canarias, dos décimas menos que en el conjunto nacional (-3,2 por ciento), según Sociedad de Tasación. Así, la Comunidad es la sexta CCAA, junto con Murcia, que menor descenso experimentó en el precio. De esta manera, Santa Cruz de Tenerife, con un descenso del 3,9 por ciento, es la capital donde más cae el precio, mientras que en Las Palmas de Gran Canaria se contrae un 2,6 por ciento. Esta última ciudad cuenta con el metro cuadrado más caro (1.669 ?/m2) mientras que en Santa Cruz el coste se sitúa en los 1.582 ?/m2 construido. En cuanto a las poblaciones que no son capital de provincia, el Boletín de Vivienda Nueva indica que Arrecife (-9,4%) es la localidad que ha registrado una mayor caída en los precios de la vivienda libre, seguida de La Orotava (-4,9%) y El Puerto de la Cruz (-4,4%). Por otro lado, las poblaciones donde menos se ha reducido el precio son Telde (-3,4%) y San Cristóbal de la Laguna (-3,8%). (Ver datos página 36-40 Boletín). En el conjunto nacional, con respecto al primer semestre de 2010 el precio medio de la vivienda se contrajo un 2,4 por ciento. Por provincias, los precios disminuyeron en 46 capitales de provincia, aumentaron en tres (Lugo, Palencia y Pontevedra) y no sufrieron variación en una de ellas (Ourense). La caída ha sido más acusada en Aragón (-5,8 por ciento), Extremadura (-5,2 por ciento) y Baleares (-4,6 por ciento). Por el contrario, Galicia (-0,7 por ciento), Asturias (-1,4) y Navarra (-1,5 por ciento) son las regiones donde menos ha bajado el precio de la vivienda libre en sus capitales. En siete capitales los precios medios disminuyeron más del 5 por ciento respecto al 2009, en 17 capitales los precios cayeron entre el 3 por ciento y el 5 por ciento, en 23 la reducción fue de entre el 0 por ciento y el 3 por ciento. En las tres capitales restantes los precios aumentaron hasta un 3 por ciento. Sociedad de Tasación destaca que para 2011 la oferta de vivienda nueva seguirá siendo importante, básicamente por el considerable 'stock' de vivienda ya construida y de colocación \"muy lenta\", y añade que esta oferta será menos abundante en las zonas céntricas de las ciudades por la escasez de inmuebles nuevos ya construidos y de suelo edificable. EN 2011 Se mantendrá la caída de los precios Así, indica que es previsible que en la primera parte del año las ventas tiendan a ralentizarse y se mantenga la tendencia de caída de los precios hasta que se absorba el excedente de oferta existente. Este descenso, agrega, se podrá producir tanto en las primeras residencias como en las segundas viviendas y en las turísticas. Como conclusión, señala que en 2011 se mantendrá el ajuste en el nivel de la oferta iniciado al final de 2008 para adecuarse a un volumen de demanda inferior al de periodos anteriores. Asimismo, apunta que la desaparición del incentivo fiscal para la adquisición de vivienda supondrá posiblemente un mayor debilitamiento de la demanda actual, que incida negativamente en la evolución de los precios si se mantienen las condiciones de financiación actuales.",
        "lemmatized_text": "el precio de el vivienda nuevo caer uno 3 por 100 en canarias 2 décima menos que en el conjunto nacional -3,2 por 100 según sociedad_de_tasación así el comunidad ser el 6 ccaa junto_con murcia que menor descenso experimentar en el precio de este manera santa_cruz_de_tenerife con uno descenso de el 3,9 por 100 ser el capital donde más caer el precio mientras_que en las_palmas_de_gran_canaria se contraer uno 2,6 por 100 este último ciudad contar con el metro cuadrado más caro 1.669 /m2 mientras_que en santa_cruz el coste se situar en el 1.582 /m2 construir en_cuanto_a el población que no ser capital de provincia el boletín_de_vivienda_nueva indicar que arrecife -9,4/100 ser el localidad que haber registrar uno mayor caída en el precio de el vivienda libre seguir de la_orotava -4,9/100 y el_puerto_de_la_cruz -4,4/100 por_otro_lado el población donde menos se haber reducir el precio ser telde -3,4/100 y san_cristóbal_de_la_laguna -3,8/100 ver dato página 36-40 boletín en el conjunto nacional con respecto a el 1 semestre de 2010 el precio medio de el vivienda se contraer uno 2,4 por 100 por provincia el precio disminuir en 46 capital de provincia aumentar en 3 lugo palencia y pontevedra y no sufrir variación en uno de ellos ourense el caída haber ser más acusar en aragón -5,8 por 100 extremadura -5,2 por 100 y baleares -4,6 por 100 por_el_contrario galicia -0,7 por 100 asturias -1,4 y navarra -1,5 por 100 ser el región donde menos haber bajar el precio de el vivienda libre en su capital en 7 capital el precio medio disminuir más de el 5 por 100 respecto a el 2009 en 17 capital el precio caer entre el 3 por 100 y el 5 por 100 en 23 el reducción ser de entre el 0 por 100 y el 3 por 100 en el 3 capital restante el precio aumentar hasta uno 3 por 100 sociedad_de_tasación destacar que para 2011 el oferta de vivienda nuevo seguir ser importante básicamente por el considerable stock de vivienda ya construir y de colocación muy lento y añadir que este oferta ser menos abundante en el zona céntrico de el ciudad por el escasez de inmueble nuevo ya construir y de suelo edificable en 2011 se mantener el caída de el precio así indicar que ser previsible que en el 1 parte de el año el venta tender a ralentizar se y se mantener el tendencia de caída de el precio hasta que se absorber el excedente de oferta existente este descenso agregar se poder producir tanto en el 1 residencia como en el 2 vivienda y en el turístico como conclusión señalar que en 2011 se mantener el ajuste en el nivel de el oferta iniciar a el final de 2008 para adecuar se a uno volumen de demanda inferior a el de periodo anterior asimismo apuntar que el desaparición de el incentivo fiscal para el adquisición de vivienda suponer posiblemente uno mayor debilitamiento de el demanda actual que incidir negativamente en el evolución de el precio si se mantener el condición de financiación actual",
        "lemmatized_text_reduced": "precio vivienda nuevo caer canarias décima conjunto nacional sociedad_de_tasación comunidad ser 6 ccaa murcia menor descenso experimentar precio manera santa_cruz_de_tenerife descenso ser capital caer precio las_palmas_de_gran_canaria contraer último ciudad contar metro cuadrado caro santa_cruz coste situar construir población ser capital provincia boletín_de_vivienda_nueva indicar arrecife ser localidad haber registrar mayor caída precio vivienda libre seguir la_orotava el_puerto_de_la_cruz población haber reducir precio ser telde san_cristóbal_de_la_laguna ver dato página boletín conjunto nacional respecto 1 semestre precio medio vivienda contraer provincia precio disminuir capital provincia aumentar lugo palencia pontevedra sufrir variación ourense caída haber ser acusar aragón extremadura baleares galicia asturias navarra ser región haber bajar precio vivienda libre capital capital precio medio disminuir respecto capital precio caer reducción ser capital restante precio aumentar sociedad_de_tasación destacar oferta vivienda nuevo seguir ser importante básicamente considerable stock vivienda construir colocación lento añadir oferta ser abundante zona céntrico ciudad escasez inmueble nuevo construir suelo edificable se mantener caída precio así indicar ser previsible 1 parte año venta tender ralentizar mantener tendencia caída precio absorber excedente oferta existente descenso agregar poder producir 1 residencia 2 vivienda turístico conclusión señalar mantener ajuste nivel oferta iniciar final adecuar volumen demanda inferior periodo anterior apuntar desaparición incentivo fiscal adquisición vivienda suponer posiblemente mayor debilitamiento demanda actual incidir negativamente evolución precio mantener condición financiación actual",
        "persons": [
            "Santa_Cruz_de_Tenerife",
            "Arrecife",
            "Se",
            "Así"
        ],
        "locations": [
            "Canarias",
            "Murcia",
            "Las_Palmas_de_Gran_Canaria",
            "Santa_Cruz",
            "Boletín",
            "Lugo",
            "Palencia",
            "Pontevedra",
            "Ourense",
            "Aragón",
            "Baleares",
            "Galicia",
            "Asturias",
            "Navarra"
        ],
        "organizations": [
            "Sociedad_de_Tasación",
            "Comunidad",
            "CCAA",
            "Boletín_de_Vivienda_Nueva",
            "La_Orotava",
            "El_Puerto_de_la_Cruz",
            "Telde",
            "San_Cristóbal_de_la_Laguna",
            "Extremadura",
            "Sociedad_de_Tasación"
        ],
        "others": [],
        "dates": [],
        "numbers": [
            "3",
            "100",
            "2",
            "-3,2",
            "100",
            "3,9",
            "100",
            "2,6",
            "100",
            "1.669",
            "/m2",
            "1.582",
            "/m2",
            "-9,4/100",
            "-4,9/100",
            "-4,4/100",
            "-3,4/100",
            "-3,8/100",
            "36-40",
            "2010",
            "2,4",
            "100",
            "46",
            "3",
            "-5,8",
            "100",
            "-5,2",
            "100",
            "-4,6",
            "100",
            "-0,7",
            "100",
            "-1,4",
            "-1,5",
            "100",
            "7",
            "5",
            "100",
            "2009",
            "17",
            "3",
            "100",
            "5",
            "100",
            "23",
            "0",
            "100",
            "3",
            "100",
            "3",
            "3",
            "100",
            "2011",
            "2011",
            "2011",
            "2008"
        ]
    }
}
