{
    "province": "LAS PALMAS",
    "date": "2010-03-15T00:00:00",
    "url": "https://www.20minutos.es/noticia/652285/0/",
    "title": {
        "raw_text": "Canarias registra 1.904 delitos y faltas menos en 2009, cayendo la tasa de criminalidad casi un 2%",
        "lemmatized_text": "canario registrar 1.904 delito y falta menos en 2009 caer el tasa de criminalidad casi uno 2/100",
        "lemmatized_text_reduced": "canario registrar delito falta caer tasa criminalidad",
        "persons": [],
        "locations": [],
        "organizations": [],
        "others": [],
        "dates": [],
        "numbers": [
            "1.904",
            "2009",
            "2/100"
        ]
    },
    "lead": {
        "raw_text": "Los delitos de seguridad vial, pornografía infantil y malos tratos aumentan en el archipiélago",
        "lemmatized_text": "el delito de seguridad vial pornografía infantil y malo trato aumentar en el archipiélago",
        "lemmatized_text_reduced": "delito seguridad vial pornografía infantil malo trato aumentar archipiélago",
        "persons": [],
        "locations": [],
        "organizations": [],
        "others": [],
        "dates": [],
        "numbers": []
    },
    "body": {
        "raw_text": "La delegada del Gobierno en Canarias, Carolina Darias, anunció hoy la evolución de la tasa de criminalidad del archipiélago en 2009, indicando que se ha pasado de registrar 98.032 delitos y faltas en 2008 a los 96.128 del pasado año, lo que ha supuesto un descenso de 1.904 casos menos, cayendo dicha tasa casi un 2 por ciento en este periodo. Darias aseguró, en rueda de prensa, que estos son los \"mejores resultados\" desde el 2000, ya que la tasa de criminalidad, que son los delitos y faltas cometidos por cada 1.000 habitantes, se situó en 45.7 en Canarias en 2009. De todos modos, puntualizó que la tasa anual de criminalidad tendría una \"mayor aminoración\" si se excluyeran de estos datos estadísticos los delitos de seguridad vial, ya que así la tasa se situaría en 43.8 en 2009. Asimismo, apuntó que el pasado año cayó \"todo\" el conjunto de las infracciones penales \"más importantes\", tales como los delitos contra la vida, contra la integridad y contra la libertad de las personas. En este sentido, indicó que en 2009 y con respecto de 2008 han caído un 37,5 por ciento la corrupción de menores; un 24 por ciento la sustracción de vehículos; un 15 por ciento los hurtos; un 8,9 por ciento los delitos contra el patrimonio; un 5,5 por ciento los robos con fuerza en las cosas; y un 5,2 por ciento los asesinatos y homicidios dolosos, reducción que calificó como \"notable aminoración\". Respecto a los delitos contra la vida y la integridad de las personas \"por tasa se mantiene y porcentualmente aminora un 5,2 por ciento\". Darias también se refirió al descenso de robos con fuerza en establecimientos, que cayó un 17 por ciento; mientras que los robos con violencia en la vía pública descendieron un 10,3 por ciento y los robos con violencia en establecimientos también aminorizaron en un 9,5 por ciento. Otro de los datos aportados por la delegada del Gobierno en Canarias es que la falta por lesiones cayó un 1,6 por ciento. Incrementan tres delitos Los delitos de seguridad vial sí incrementaron en 2009 al igual que ocurrió con los de violencia en el ámbito familiar y pornografía infantil. En lo que se refiere a los delitos contra la seguridad vial, el general jefe de la 16º Zona de la Guardia Civil, Miguel Martínez, puntualizó que \"no es que aumenten propiamente dicho los delitos relacionados con la seguridad vial, es que aumentan el número de controles\". Agregó, Martínez que en los controles de alcoholemia el porcentaje de personas que dan positivo \"va cada vez en menor\", se ha pasado de un 7 por ciento de personas que daban positivo a un uno por ciento pero \"hay mayor número de controles\" de velocidad o de seguros, entre otros, de ahí que incremente este tipo de delitos en términos absolutos. Respecto a los malos tratos en el ámbito familiar incrementaron en un 3,8 por ciento, Darias lo justificó señalando que \"es debido a la mayor cantidad de mujeres que denuncia este tipo de situaciones que padecen\". Añadió que de estos, los malos tratos de ámbito familiar crecieron un 3,8 por ciento, mientras que los físicos y psíquicos aumentaron en un 2,8 por ciento. La delegada del Gobierno en Canarias también indicó que los delitos contra la pornografía infantil crecieron en un 20 por ciento como \"consecuencia de la mayor actividad policial\".24.103 Casos esclarecidos Por otro lado, Darias hizo hincapié en el esclarecimiento de los casos que alcanzó los 24.103 resueltos en 2009 en las islas, alcanzando una tasa del 52.4 a diferencia de la del 50 de 2008. \"Esto es producto del mayor trabajo, de la mayor actividad y de la mayor eficacia de las Fuerzas y Cuerpos de Seguridad del Estado\", subrayó. En cuanto a la tasa de detenidos el descenso fue de un punto, puntualizando Darias que hay que \"tener en cuenta que son menos los delitos que se han cometido en Canarias en el periodo de 2009\". La delegada también dio otros datos como el de agentes de Policía y Guardia Civil disponibles en el archipiélago durante el pasado año, donde se ha producido un incremento \"sustancial\". Aquí, dijo, que actualmente hay un total de 7.259 efectivos, de los que 3.511 son guardias civiles y 3.748 policías nacionales. De esta forma, entre 2003 y 2009 el número de agentes de la Benemérita ha aumentado en un 35,9 por ciento, mientras que el de Policía Nacional ha incrementado en un 45,6 por ciento. Agregó que la media de efectivos entre 2003 y 2009 ha aumentado en un 40,7 por ciento, mientras que la media nacional la subida fue de algo más del 24 por ciento. Darias destacó que la tasa de criminalidad de España, de 45.8, con respecto a otros países de sus alrededores ocupa una \"magnífica posición\" en relación con el resto. Añadió que en lo que se refiere a los presupuestos el Ejecutivo central incrementó la dotación económica de los Cuerpos y Fuerzas de Seguridad del Estado en un 55 por ciento entre 2004 y 2009. En cuanto a la percepción que tienen los ciudadanos sobre la seguridad, los últimos datos de enero de 2010 apuntan, en el conjunto nacional, que un 8,1 por ciento lo considera como el \"principal problema\" en España. Finalmente, cuestionada Darias por la inmigración que llega de forma ilegal a Canarias, recordó que ha habido un descenso del 75 por ciento en cuanto a la llegada de pateras y cayucos a las islas el pasado año y en cuanto a los patrones detenidos no especificó datos pero indicó que se prevé que al llegar menos embarcaciones, habrá \"menos\" arrestados.",
        "lemmatized_text": "el delegado de el gobierno en canarias carolina_darias anunciar hoy el evolución de el tasa de criminalidad de el archipiélago en 2009 indicar que se haber pasar de registrar 98.032 delito y falta en 2008 a el 96.128 de el pasar año el que haber suponer uno descenso de 1.904 caso menos caer decir tasa casi uno 2 por 100 en este periodo darias asegurar en rueda de prensa que este ser el mejor resultado desde el 2000 ya_que el tasa de criminalidad que ser el delito y falta cometer por cada 1 habitante se situar en 45.7 en canarias en 2009 de_todos_modos puntualizar que el tasa anual de criminalidad tener uno mayor aminoración si se excluir de este dato estadístico el delito de seguridad vial ya_que así el tasa se situar en 43.8 en 2009 asimismo apuntar que el pasar año caer todo el conjunto de el infracción penal más importante tal como el delito contra el vida contra el integridad y contra el libertad de el persona en este sentido indicar que en 2009 y con_respecto_de 2008 haber caer uno 37,5 por 100 el corrupción de menor uno 24 por 100 el sustracción de vehículo uno 15 por 100 el hurto uno 8,9 por 100 el delito contra el patrimonio uno 5,5 por 100 el robo con fuerza en el cosa y uno 5,2 por 100 el asesinato y homicidio doloso reducción que calificar como notable aminoración respecto_a el delito contra el vida y el integridad de el persona por tasa se mantener y porcentualmente aminorar uno 5,2 por 100 darias también se referir a el descenso de robo con fuerza en establecimiento que caer uno 17 por 100 mientras_que el robo con violencia en el vía público descender uno 10,3 por 100 y el robo con violencia en establecimiento también aminorizaron en uno 9,5 por 100 otro de el dato aportar por el delegado de el gobierno en canarias ser que el falta por lesión caer uno 1,6 por 100 incrementar 3 delito los delito de seguridad vial sí incrementar en 2009 al_igual_que ocurrir con el de violencia en el ámbito familiar y pornografía infantil en el que se referir a el delito contra el seguridad vial el general jefe de el 16º zona_de_la_guardia_civil miguel_martínez puntualizar que no ser que aumentar propiamente decir el delito relacionar con el seguridad vial ser que aumentar el número de control agregar martínez que en el control de alcoholemia el porcentaje de persona que dar positivo ir cada vez en menor se haber pasar de uno 7 por 100 de persona que dar positivo a uno uno por 100 pero haber mayor número de control de velocidad o de seguro entre otro de ahí que incrementar este tipo de delito en término absoluto respecto_a el malo trato en el ámbito familiar incrementar en uno 3,8 por 100 darias lo justificar señalar que ser debido_a el mayor cantidad de mujer que denunciar este tipo de situación que padecer añadir que de este el malo trato de ámbito familiar crecer uno 3,8 por 100 mientras_que el físico y psíquico aumentar en uno 2,8 por 100 el delegado de el gobierno en canarias también indicar que el delito contra el pornografía infantil crecer en uno 20 por 100 como consecuencia de el mayor actividad policial .24.103 casos esclarecer por_otro_lado darias hacer hincapié en el esclarecimiento de el caso que alcanzar el 24.103 resolver en 2009 en el isla alcanzar uno tasa de el 52.4 a_diferencia_de el de el 50 de 2008 este ser producto de el mayor trabajo de el mayor actividad y de el mayor eficacia de el fuerzas y cuerpos_de_seguridad_del_estado subrayar en_cuanto_a el tasa de detener el descenso ser de uno punto puntualizar darias que haber que tener_en_cuenta que ser menos el delito que se haber cometer en canarias en el periodo de 2009 el delegado también dar otro dato como el de agente de policía y guardia_civil disponible en el archipiélago durante el pasar año donde se haber producir uno incremento sustancial aquí decir que actualmente haber uno total de 7.259 efectivo de el que 3.511 ser guardia civil y 3.748 policía nacional de este forma entre 2003 y 2009 el número de agente de el benemérita haber aumentar en uno 35,9 por 100 mientras_que el de policía_nacional haber incrementar en uno 45,6 por 100 agregar que el media de efectivo entre 2003 y 2009 haber aumentar en uno 40,7 por 100 mientras_que el media nacional el subida ser de algo más de el 24 por 100 darias destacar que el tasa de criminalidad de españa de 45.8 con_respecto_a otro país de su alrededor ocupar uno magnífico posición en relación con el resto añadir que en el que se referir a el presupuesto el ejecutivo central incrementar el dotación económico de el cuerpos y fuerzas_de_seguridad_del_estado en uno 55 por 100 entre 2004 y 2009 en_cuanto_a el percepción que tener el ciudadano sobre el seguridad el último dato de [??:??/1/2010:??.??:??] apuntar en el conjunto nacional que uno 8,1 por 100 lo considerar como el principal problema en españa finalmente cuestionar darias por el inmigración que llegar de forma ilegal a canarias recordar que haber haber uno descenso de el 75 por 100 en_cuanto_a el llegada de patera y cayucos a el isla el pasar año y en_cuanto_a el patrón detener no especificar dato pero indicar que se prever que a el llegar menos embarcación haber menos arrestar",
        "lemmatized_text_reduced": "delegado gobierno canarias carolina_darias anunciar evolución tasa criminalidad archipiélago indicar haber pasar registrar delito falta pasar año haber suponer descenso caso caer decir tasa periodo darias asegurar rueda prensa ser mejor resultado tasa criminalidad ser delito falta cometer habitante situar canarias puntualizar tasa anual criminalidad tener mayor aminoración excluir dato estadístico delito seguridad vial tasa situar apuntar pasar año caer conjunto infracción penal importante delito vida integridad libertad persona sentido indicar haber caer corrupción menor sustracción vehículo hurto delito patrimonio robo fuerza cosa asesinato homicidio doloso reducción calificar notable aminoración delito vida integridad persona tasa mantener porcentualmente aminorar darias referir descenso robo fuerza establecimiento caer robo violencia vía público descender robo violencia establecimiento aminorizaron dato aportar delegado gobierno canarias ser falta lesión caer incrementar delito los delito seguridad vial incrementar ocurrir violencia ámbito familiar pornografía infantil referir delito seguridad vial general jefe zona_de_la_guardia_civil miguel_martínez puntualizar ser aumentar propiamente decir delito relacionar seguridad vial ser aumentar número control agregar martínez control alcoholemia porcentaje persona dar positivo ir vez menor haber pasar persona dar positivo haber mayor número control velocidad seguro incrementar tipo delito término absoluto malo trato ámbito familiar incrementar darias justificar señalar ser mayor cantidad mujer denunciar tipo situación padecer añadir malo trato ámbito familiar crecer físico psíquico aumentar delegado gobierno canarias indicar delito pornografía infantil crecer consecuencia mayor actividad policial casos esclarecer por_otro_lado darias hacer hincapié esclarecimiento caso alcanzar resolver isla alcanzar tasa ser producto mayor trabajo mayor actividad mayor eficacia fuerzas cuerpos_de_seguridad_del_estado subrayar tasa detener descenso ser punto puntualizar darias haber tener_en_cuenta ser delito haber cometer canarias periodo delegado dar dato agente policía guardia_civil disponible archipiélago pasar año haber producir incremento sustancial decir actualmente haber total efectivo ser guardia civil policía nacional forma número agente benemérita haber aumentar policía_nacional haber incrementar agregar media efectivo haber aumentar media nacional subida ser darias destacar tasa criminalidad españa país alrededor ocupar magnífico posición relación resto añadir referir presupuesto ejecutivo central incrementar dotación económico cuerpos fuerzas_de_seguridad_del_estado percepción tener ciudadano seguridad último dato apuntar conjunto nacional considerar principal problema españa finalmente cuestionar darias inmigración llegar forma ilegal canarias recordar haber haber descenso llegada patera cayucos isla pasar año patrón detener especificar dato indicar prever llegar embarcación haber arrestar",
        "persons": [
            "Carolina_Darias",
            "Darias",
            "Darias",
            "Miguel_Martínez",
            "Martínez",
            "Darias",
            "Por_otro_lado",
            "Darias",
            "Darias",
            "Darias",
            "Darias"
        ],
        "locations": [
            "Canarias",
            "Canarias",
            "Canarias",
            "Canarias",
            "Casos",
            "Canarias",
            "España",
            "España",
            "Canarias"
        ],
        "organizations": [
            "Gobierno",
            "Gobierno",
            "Zona_de_la_Guardia_Civil",
            "Gobierno",
            "Fuerzas",
            "Cuerpos_de_Seguridad_del_Estado",
            "Policía",
            "Guardia_Civil",
            "Benemérita",
            "Policía_Nacional",
            "Ejecutivo",
            "Cuerpos",
            "Fuerzas_de_Seguridad_del_Estado"
        ],
        "others": [
            "Los"
        ],
        "dates": [
            "[??:??/1/2010:??.??:??]"
        ],
        "numbers": [
            "2009",
            "98.032",
            "2008",
            "96.128",
            "1.904",
            "2",
            "100",
            "2000",
            "1",
            "45.7",
            "2009",
            "43.8",
            "2009",
            "2009",
            "2008",
            "37,5",
            "100",
            "24",
            "100",
            "15",
            "100",
            "8,9",
            "100",
            "5,5",
            "100",
            "5,2",
            "100",
            "5,2",
            "100",
            "17",
            "100",
            "10,3",
            "100",
            "9,5",
            "100",
            "1,6",
            "100",
            "3",
            "2009",
            "16º",
            "7",
            "100",
            "100",
            "3,8",
            "100",
            "3,8",
            "100",
            "2,8",
            "100",
            "20",
            "100",
            ".24.103",
            "24.103",
            "2009",
            "52.4",
            "50",
            "2008",
            "2009",
            "7.259",
            "3.511",
            "3.748",
            "2003",
            "2009",
            "35,9",
            "100",
            "45,6",
            "100",
            "2003",
            "2009",
            "40,7",
            "100",
            "24",
            "100",
            "45.8",
            "55",
            "100",
            "2004",
            "2009",
            "8,1",
            "100",
            "75",
            "100"
        ]
    }
}
