{
    "province": "LAS PALMAS",
    "date": "2008-04-23T00:00:00",
    "url": "https://www.20minutos.es/noticia/372428/0/almodovar/rodaje/lanzarote/",
    "title": {
        "raw_text": "Seleccionan figurantes para la película de Almodóvar que se rodará en Lanzarote",
        "lemmatized_text": "seleccionar figurante para el película de almodóvar que se rodar en lanzarote",
        "lemmatized_text_reduced": "seleccionar figurante película almodóvar rodar lanzarote",
        "persons": [
            "Almodóvar"
        ],
        "locations": [
            "Lanzarote"
        ],
        "organizations": [],
        "others": [],
        "dates": [],
        "numbers": []
    },
    "lead": {
        "raw_text": "Comenzará a rodarse en mayo en la isla durante dos semanas. En ella intervendrán Penélope Cruz, Lluís Homar y Blanca Portillo. CONSULTA AQUÍ MÁS NOTICIAS DE LAS PALMAS DE GRAN CANARIA",
        "lemmatized_text": "comenzar a rodar se en [??:??/5/??:??.??:??] en el isla durante 2 semana en él intervenir penélope_cruz lluís_homar y blanca_portillo consulta_aquí_más_noticias_de_las_palmas_de_gran_canaria",
        "lemmatized_text_reduced": "comenzar rodar isla semana intervenir penélope_cruz lluís_homar blanca_portillo consulta_aquí_más_noticias_de_las_palmas_de_gran_canaria",
        "persons": [
            "Penélope_Cruz",
            "Lluís_Homar",
            "Blanca_Portillo"
        ],
        "locations": [],
        "organizations": [
            "CONSULTA_AQUÍ_MÁS_NOTICIAS_DE_LAS_PALMAS_DE_GRAN_CANARIA"
        ],
        "others": [],
        "dates": [
            "[??:??/5/??:??.??:??]"
        ],
        "numbers": [
            "2"
        ]
    },
    "body": {
        "raw_text": "La productora El Deseo seleccionará el viernes y el sábado en Lanzarote a mujeres y hombres de \"todas las edades y perfiles\" para que participen como figurantes en la nueva película de Pedro Almodóvar , que comenzará a rodarse en mayo en la isla durante dos semanas. Así lo anunció hoy la productora que también seleccionará esos días para la próxima película del director manchego, que se llamará Los abrazos rotos, vehículos de todas las marcas y modelos, con fecha de matriculación anterior a 1994 \". El casting para este nuevo trabajo de Almodóvar, una producción en la que intervendrá Penélope Cruz, Lluís Homar y Blanca Portillo, tendrá lugar en un hotel del municipio lanzaroteño de Teguise en horario de mañana y tarde. CONSULTA AQUÍ MÁS NOTICIAS DE LAS PALMAS DE GRAN CANARIA",
        "lemmatized_text": "el productor el_deseo seleccionar el [V:??/??/??:??.??:??] y el [S:??/??/??:??.??:??] en lanzarote a mujer y hombre de todo el edad y perfil para que participar como figurante en el nuevo película de pedro_almodóvar que comenzar a rodar se en [??:??/5/??:??.??:??] en el isla durante 2 semana así lo anunciar hoy el productor que también seleccionar ese día para el próximo película de el director manchego que se llamar los abrazo romper vehículo de todo el marca y modelo con fecha de matriculación anterior a 1994 el casting para este nuevo trabajo de almodóvar uno producción en el que intervenir penélope_cruz lluís_homar y blanca_portillo tener_lugar en uno hotel de el municipio lanzaroteño de teguise en horario de mañana y tarde consulta_aquí_más_noticias_de_las_palmas_de_gran_canaria",
        "lemmatized_text_reduced": "productor el_deseo seleccionar lanzarote mujer hombre edad perfil participar figurante nuevo película pedro_almodóvar comenzar rodar isla semana anunciar productor seleccionar día próximo película director manchego llamar los abrazo romper vehículo marca modelo fecha matriculación anterior casting nuevo trabajo almodóvar producción intervenir penélope_cruz lluís_homar blanca_portillo tener_lugar hotel municipio lanzaroteño teguise horario mañana tarde consulta_aquí_más_noticias_de_las_palmas_de_gran_canaria",
        "persons": [
            "Pedro_Almodóvar",
            "Penélope_Cruz",
            "Lluís_Homar",
            "Blanca_Portillo"
        ],
        "locations": [
            "Lanzarote",
            "Almodóvar",
            "Teguise"
        ],
        "organizations": [
            "El_Deseo",
            "CONSULTA_AQUÍ_MÁS_NOTICIAS_DE_LAS_PALMAS_DE_GRAN_CANARIA"
        ],
        "others": [
            "Los"
        ],
        "dates": [
            "[V:??/??/??:??.??:??]",
            "[S:??/??/??:??.??:??]",
            "[??:??/5/??:??.??:??]"
        ],
        "numbers": [
            "2",
            "1994"
        ]
    }
}
