{
    "province": "LAS PALMAS",
    "date": "2010-02-21T00:00:00",
    "url": "https://www.20minutos.es/noticia/634490/0/",
    "title": {
        "raw_text": "Un talud de tierra provoca el cierre de una carretera de acceso a Tejeda (Gran Canaria)",
        "lemmatized_text": "uno talud de tierra provocar el cierre de uno carretera de acceso a tejeda gran_canaria",
        "lemmatized_text_reduced": "talud tierra provocar cierre carretera acceso tejeda gran_canaria",
        "persons": [],
        "locations": [
            "Tejeda"
        ],
        "organizations": [
            "Gran_Canaria"
        ],
        "others": [],
        "dates": [],
        "numbers": []
    },
    "lead": {
        "raw_text": "Un talud de tierra ha provocado hoy el cierre de la carretera GC-15, conocida como la variante de Tejeda, que conecta el Parador de Tejeda con el pueblo grancanario, según informaron a Europa Press fuentes del Cabildo, que indicaron que la única vía de acceso al municipio es por la carretera de Artenara.",
        "lemmatized_text": "uno talud de tierra haber provocar hoy el cierre de el carretera GC-15 conocer como el variante de tejeda que conectar el parador_de_tejeda con el pueblo grancanario según informar a europa_press fuente de el cabildo que indicar que el único vía de acceso a el municipio ser por el carretera de artenara",
        "lemmatized_text_reduced": "talud tierra haber provocar cierre carretera conocer variante tejeda conectar parador_de_tejeda pueblo grancanario informar europa_press fuente cabildo indicar único vía acceso municipio ser carretera artenara",
        "persons": [
            "Tejeda",
            "Europa_Press"
        ],
        "locations": [
            "Parador_de_Tejeda",
            "Artenara"
        ],
        "organizations": [
            "Cabildo"
        ],
        "others": [],
        "dates": [],
        "numbers": [
            "GC-15"
        ]
    },
    "body": {
        "raw_text": "Operarios del servicio de mantenimiento de Carreteras de la corporación insular trabajan desde las 07.30 horas en la zona afectada por el desprendimiento de tierra debido a las fuertes lluvias de los últimos días y que afecta a los dos carriles a dos kilómetros del Parador de Tejeda. Las mismas fuentes insisten en que los trabajadores están haciendo todo lo posible para que \"lo antes posible\" se pueda reanudar el tránsito de vehículos en la citada vía. Asimismo, para garantizar la accesibilidad en la vía que conecta Tejeda con Artenara, el Cabildo ha aumentado hoy los retenes de limpieza. El Cabildo grancanario informa también de que en la GC-60, a la altura de La Degollada de Fataga, se ha registrado corrimiento de tierras. Sin embargo, la carretera no está cortada, pero sólo hay un carril en funcionamiento, por lo que hay que \"circular con extremo cuidado\", advierte. Máxima precaución en las carreteras Desde la Consejería de Desarrollo Económico, Obras Públicas e Infraestructuras y Transportes del Cabildo de Gran Canaria se ruega a los ciudadanos que vayan a desplazarse por la red de carreteras insular que extremen la precaución. La corporación recuerda en un comunicado que las siguientes vías han sufrido una reducción de la calzada: GC-65 (carretera de los Cuchillos) en el punto kilométrico (pk) 0+500; la GC-504 (carretera de Ayagaures) entre el pk 1+000 y el 7+000; la GC-500 (carretera general al Sur) en el pk 25+900 y entre el 41+500 y el 45+500; la GC-505 (carretera a Soria desde Cercados de Espino) en el pk 16+900 y la GC-60 (de Tejeda a Maspalomas) en el pk 31+500. Asimismo, la institución insular informa a los ciudadanos de que se ha incrementado el peligro por desprendimientos en las carreteras GC-505 (desde Cercados de Espino a Soria) entre los ppkk 14+000 y 19+000; la GC-500 (carretera general al Sur) entre el 41+500 y el 45+600; la GC-60 (Tejeda-Maspalomas) desde el pk 25+500 al 39+000; y la GC-65 (carretera de Los Cuchillos) entre los ppkk 3+500 y 6+000.",
        "lemmatized_text": "operario de el servicio de mantenimiento de carreteras de el corporación insular trabajar desde el TM_h:7.3 en el zona afectar por el desprendimiento de tierra debido_a el fuerte lluvia de el último día y que afectar a el 2 carril a 2 kilómetro de el parador_de_tejeda el mismo fuente insistir en que el trabajador estar hacendar todo el posible para que el antes posible se poder reanudar el tránsito de vehículo en el citar vía asimismo para garantizar el accesibilidad en el vía que conectar tejeda con artenara el cabildo haber aumentar hoy el retén de limpieza el cabildo grancanario informar también de que en el GC-60 a el altura de la_degollada_de_fataga se haber registrar corrimiento de tierra sin embargo el carretera no estar cortar pero sólo haber uno carril en funcionamiento por el que haber que circular con extremo cuidar advertir máximo precaución en el carretera desde_la_consejería_de_desarrollo_económico obras_públicas y infraestructuras y transportes_del_cabildo_de_gran_canaria se rogar a el ciudadano que ir a desplazar se por el red de carretera insular que extremar el precaución el corporación recordar en uno comunicado que el siguiente vía haber sufrir uno reducción de el calzada GC-65 carretera de el cuchillos en el punto kilométrico pk 0+500 el GC-504 carretera de ayagaures entre el pk 1+000 y el 7+000 el GC-500 carretera general a el sur en el pk 25+900 y entre el 41+500 y el 45+500 el GC-505 carretera a soria desde cercados_de_espino en el pk 16+900 y el GC-60 de tejeda a maspalomas en el pk 31+500 asimismo el institución insular informar a el ciudadano de que se haber incrementar el peligro por desprendimiento en el carretera GC-505 desde cercados_de_espino a soria entre el ppkk 14+000 y 19+000 el GC-500 carretera general a el sur entre el 41+500 y el 45+600 el GC-60 tejeda-maspalomas desde el pk 25+500 a el 39+000 y el GC-65 carretera de los_cuchillos entre el ppkk 3+500 y 6+000",
        "lemmatized_text_reduced": "operario servicio mantenimiento carreteras corporación insular trabajar zona afectar desprendimiento tierra fuerte lluvia último día afectar carril kilómetro parador_de_tejeda mismo fuente insistir trabajador estar hacendar posible posible poder reanudar tránsito vehículo citar vía garantizar accesibilidad vía conectar tejeda artenara cabildo haber aumentar retén limpieza cabildo grancanario informar altura la_degollada_de_fataga haber registrar corrimiento tierra embargo carretera estar cortar haber carril funcionamiento haber circular extremo cuidar advertir máximo precaución carretera desde_la_consejería_de_desarrollo_económico obras_públicas infraestructuras transportes_del_cabildo_de_gran_canaria rogar ciudadano ir desplazar red carretera insular extremar precaución corporación recordar comunicado siguiente vía haber sufrir reducción calzada carretera cuchillos punto kilométrico pk carretera ayagaures pk carretera general sur pk carretera soria cercados_de_espino pk tejeda maspalomas pk institución insular informar ciudadano haber incrementar peligro desprendimiento carretera cercados_de_espino soria ppkk carretera general sur tejeda-maspalomas pk carretera los_cuchillos ppkk",
        "persons": [
            "Carreteras",
            "Tejeda",
            "La_Degollada_de_Fataga"
        ],
        "locations": [
            "Parador_de_Tejeda",
            "Cuchillos",
            "Ayagaures",
            "Soria",
            "Cercados_de_Espino",
            "Tejeda",
            "Maspalomas",
            "Cercados_de_Espino",
            "Soria",
            "Los_Cuchillos"
        ],
        "organizations": [
            "Artenara",
            "Cabildo",
            "Cabildo",
            "Obras_Públicas",
            "Transportes_del_Cabildo_de_Gran_Canaria",
            "Sur",
            "Sur",
            "Tejeda-Maspalomas"
        ],
        "others": [
            "Desde_la_Consejería_de_Desarrollo_Económico",
            "Infraestructuras"
        ],
        "dates": [],
        "numbers": [
            "TM_h:7.3",
            "2",
            "2",
            "GC-60",
            "GC-65",
            "0+500",
            "GC-504",
            "1+000",
            "7+000",
            "GC-500",
            "25+900",
            "41+500",
            "45+500",
            "GC-505",
            "16+900",
            "GC-60",
            "31+500",
            "GC-505",
            "14+000",
            "19+000",
            "GC-500",
            "41+500",
            "45+600",
            "GC-60",
            "25+500",
            "39+000",
            "GC-65",
            "3+500",
            "6+000"
        ]
    }
}
