{
    "province": "LAS PALMAS",
    "date": "2010-03-23T00:00:00",
    "url": "https://www.20minutos.es/noticia/658586/0/",
    "title": {
        "raw_text": "Seguridad Social en Canarias alcanza 80.139 afiliados extranjeros en febrero, lo que supone una caída del 6,48%",
        "lemmatized_text": "seguridad_social en canarias alcanzar 80.139 afiliado extranjero en [??:??/2/??:??.??:??] el que suponer uno caída de el 6,48/100",
        "lemmatized_text_reduced": "seguridad_social canarias alcanzar afiliado extranjero suponer caída",
        "persons": [],
        "locations": [
            "Canarias"
        ],
        "organizations": [],
        "others": [
            "Seguridad_Social"
        ],
        "dates": [
            "[??:??/2/??:??.??:??]"
        ],
        "numbers": [
            "80.139",
            "6,48/100"
        ]
    },
    "lead": {
        "raw_text": "La Seguridad Social en Canarias alcanzó los 80.139 afiliados extranjeros el pasado mes de febrero, lo que ha supuesto una caída interanual del 6,48 por ciento (5.551 personas menos), según datos difundidos hoy por el Ministerio de Trabajo e Inmigración.",
        "lemmatized_text": "el seguridad_social en canarias alcanzar el 80.139 afiliado extranjero el [??:??/2/??:??.??:??] el que haber suponer uno caída interanual de el 6,48 por 100 5.551 persona menos según dato difundir hoy por el ministerio_de_trabajo y inmigración",
        "lemmatized_text_reduced": "seguridad_social canarias alcanzar afiliado extranjero haber suponer caída interanual persona dato difundir ministerio_de_trabajo inmigración",
        "persons": [],
        "locations": [
            "Canarias"
        ],
        "organizations": [
            "Ministerio_de_Trabajo",
            "Inmigración"
        ],
        "others": [
            "Seguridad_Social"
        ],
        "dates": [
            "[??:??/2/??:??.??:??]"
        ],
        "numbers": [
            "80.139",
            "6,48",
            "100",
            "5.551"
        ]
    },
    "body": {
        "raw_text": "Por provincias, la de Las Palmas tuvo 43.134 cotizantes extranjeros, lo que supuso una caída interanual del 5,99 por ciento; mientras que en la de Santa Cruz de Tenerife el número de afiliados en febrero alcanzó los 37.005, produciéndose en esta un decrecimiento mayor, ya que fue del 7,05 por ciento. Por regímenes, el que mayor afiliados extranjeros tuvo en Canarias fue el General con 56.882, seguido de los Autónomos (14.947), así como de los Empleados del Hogar (4.757) y del sector Agrario (3.190) y tras ellos los Trabajadores del Mar que fueron 363 los cotizantes. En cuanto al género de los 80.139 afiliados extranjeros en los que se situó Canarias, 42.447 eran hombres y, el resto, 37.692 lo han cotizado mujeres. Además, en el archipiélago durante el mes de febrero ha habido más afiliados no pertenecientes a la Unión Europea, en concreto 45.680; mientras que 34.459 de los cotizantes a la Seguridad Social en las islas sí pertenecen a algún país de la comunidad europea.11.112 Afiliados extranjeros más en españa En lo que respecta al conjunto nacional, la afiliación media de trabajadores extranjeros se situó en febrero en 1,81 millón de ocupados, tras ganar en el mes un total de 11.112 cotizantes. Este leve ascenso del 0,6 por ciento en el segundo mes del año se produce tras seis meses consecutivos en los que la afiliación de extranjeros registró descensos, desde agosto de 2009. Del conjunto de extranjeros que estaban afiliados a la Seguridad Social al finalizar febrero, 1.179.025 cotizaban al Régimen General, 261.122 al Régimen Agrario, 194.963 al Régimen de Autónomos, 177.545 al del Hogar, 4.610 al del Mar y 720 al del Carbón. Dentro de los países no comunitarios, 221.682 eran de nacionalidad marroquí y 177.339, ecuatoriana. Colombia, con 112.091 trabajadores, se sitúa como tercer país de procedencia de afiliados, por delante de China, que cuenta con 74.424 cotizantes. El resto de afiliados no comunitarios se repartieron entre Bolivia(71.478), Perú (69.710), Argentina (45.361), Ucrania (33.493), República Dominicana (30.421) y Brasil (23.575), entre otros. Por su parte, de los que proceden de la UE-27, rumanos, italianos y portugueses son los más numerosos, con 280.316, 59.934 y 57.167 cotizantes, respectivamente. Les siguieron búlgaros y británicos, con 53.303 y 51.152, y algo más lejos, los alemanes, con 38.897 afiliados. La mayor parte de los extranjeros que estaban afiliados a la Seguridad Social al finalizar enero se encuadraban en el Régimen General, con 1.179.025 cotizantes, seguidos del Régimen Agrario (261.122), el Régimen Especial de Autónomos (194.963), el del Hogar (177.545), el del Mar (4.610) y el del Carbón (720). Dentro del Régimen General, un total de 235.634 extranjeros, el 19,99 por ciento, trabajaba en la hostelería, mientras que el 16,84 por ciento lo hacía en el comercio (198.550 afiliados) y el 14,85 por ciento en la construcción (175.110 cotizantes). Cataluña y madrid concentran el 43% De los inmigrantes Por comunidades autónomas, Cataluña y Madrid concentraron cuatro de cada diez extranjeros afiliados a la Seguridad Social en enero, al sumar entre ambas el 43,42 por ciento del total de inmigrantes ocupados. En concreto, Cataluña contaba con 398.148 extranjeros cotizantes, mientras que en Madrid la cifra era de 391.296. Tras estas dos regiones se situaron Andalucía, con 218.909 afiliados extranjeros; Comunidad Valenciana, con 199.764 ocupados; Murcia, con 87.400; Castilla-La Mancha, con 80.545; Canarias, con 80.139; Aragón, con 62.800; Castilla y León, con 59.509; Baleares, con 58.438, y País Vasco, con 50.662. Las comunidades con menor presencia de inmigrantes en alta a la Seguridad Social al finalizar enero fueron Galicia, con 38.537 extranjeros; Navarra, con 25.869; La Rioja, con 16.406; Extremadura, con 15.689; Asturias, con 15.370; Cantabria, con 11.888, y las ciudades autónomas de Melilla, con 4.001, y Ceuta, con 2.617.",
        "lemmatized_text": "por provincia el de las_palmas tener 43.134 cotizante extranjero el que suponer uno caída interanual de el 5,99 por 100 mientras_que en el de santa_cruz_de_tenerife el número de afiliado en [??:??/2/??:??.??:??] alcanzar el 37.005 producir se en este uno decrecimiento mayor ya_que ser de el 7,05 por 100 por régimen el que mayor afiliado extranjero tener en canarias ser el general con 56.882 seguir de el autónomos 14.947 así_como de el empleados_del_hogar 4.757 y de el sector agrario 3.19 y tras ellos el trabajadores_del_mar que ser 363 el cotizante en cuanto a el género de el 80.139 afiliado extranjero en el que se situar canarias 42.447 ser hombre y el resto 37.692 lo haber cotizar mujer además en el archipiélago durante el [??:??/2/??:??.??:??] haber haber más afiliado no perteneciente a el unión_europea en concreto 45.68 mientras_que 34.459 de el cotizante a el seguridad_social en el isla sí pertenecer a alguno país de el comunidad europea.11.112 afiliados extranjero más en españa en el que respectar a el conjunto nacional el afiliación medio de trabajador extranjero se situar en [??:??/2/??:??.??:??] en 1,81 millón de ocupar tras ganar en el [??:??/1/??:??.??:??] total de 11.112 cotizante este leve ascenso de el 0,6 por 100 en el 2 mes de el año se producir tras 6 mes consecutivo en el que el afiliación de extranjero registrar descenso desde [??:??/8/2009:??.??:??] de el conjunto de extranjero que estar afiliar a el seguridad_social a el finalizar [??:??/2/??:??.??:??] 1.179.025 cotizar a el régimen_general 261.122 a el régimen_agrario 194.963 a el régimen_de_autónomos 177.545 a el de el hogar 4.61 a el de el mar y 720 a el de el carbón dentro_de el país no comunitario 221.682 ser de nacionalidad marroquí y 177.339 ecuatoriano colombia con 112.091 trabajador se situar como 3 país de procedencia de afiliado por delante_de china que contar con 74.424 cotizante el resto de afiliado no comunitario se repartir entre bolivia 71.478 perú 69.71 argentina 45.361 ucrania 33.493 república_dominicana 30.421 y brasil 23.575 entre otro por su parte de el que proceder de el UE-27 rumano italiano y portugués ser el más numeroso con 280.316 59.934 y 57.167 cotizante respectivamente le seguir búlgaro y británico con 53.303 y 51.152 y algo más lejos el alemán con 38.897 afiliado el mayor parte de el extranjero que estar afiliar a el seguridad_social a el finalizar [??:??/1/??:??.??:??] se encuadrar en el régimen_general con 1.179.025 cotizante seguir de el régimen_agrario 261.122 el régimen_especial_de_autónomos 194.963 el de el hogar 177.545 el de el mar 4.61 y el de el carbón 720 dentro de el régimen_general uno total de 235.634 extranjero el 19,99 por 100 trabajar en el hostelería mientras_que el 16,84 por 100 lo hacer en el comercio 198.55 afiliado y el 14,85 por 100 en el construcción 175.11 cotizante cataluña y madrid concentrar el 43/100 de el inmigrante por comunidad autónomo cataluña y madrid concentrar 4/10 extranjero afiliar a el seguridad_social en [??:??/1/??:??.??:??] a el sumar entre ambos el 43,42 por 100 de el total de inmigrante ocupar en concreto cataluña contar con 398.148 extranjero cotizante mientras_que en madrid el cifra ser de 391.296 tras este 2 región se situar andalucía con 218.909 afiliado extranjero comunidad_valenciana con 199.764 ocupar murcia con 87.4 castilla-la_mancha con 80.545 canarias con 80.139 aragón con 62.8 castilla y león con 59.509 baleares con 58.438 y país_vasco con 50.662 el comunidad con menor presencia de inmigrante en alto a el seguridad_social a el finalizar [??:??/1/??:??.??:??] ser galicia con 38.537 extranjero navarra con 25.869 la_rioja con 16.406 extremadura con 15.689 asturias con 15.37 cantabria con 11.888 y el ciudad autónomo de melilla con 4.001 y ceuta con 2.617",
        "lemmatized_text_reduced": "provincia las_palmas tener cotizante extranjero suponer caída interanual santa_cruz_de_tenerife número afiliado alcanzar producir decrecimiento mayor ser régimen mayor afiliado extranjero tener canarias ser general seguir autónomos empleados_del_hogar sector agrario trabajadores_del_mar ser cotizante género afiliado extranjero situar canarias ser hombre resto haber cotizar mujer archipiélago haber haber afiliado perteneciente unión_europea concreto cotizante seguridad_social isla pertenecer país comunidad afiliados extranjero españa en respectar conjunto nacional afiliación medio trabajador extranjero situar millón ocupar ganar total cotizante leve ascenso 2 mes año producir mes consecutivo afiliación extranjero registrar descenso conjunto extranjero estar afiliar seguridad_social finalizar cotizar régimen_general régimen_agrario régimen_de_autónomos hogar mar carbón país comunitario ser nacionalidad marroquí ecuatoriano colombia trabajador situar 3 país procedencia afiliado china contar cotizante resto afiliado comunitario repartir bolivia perú argentina ucrania república_dominicana brasil parte proceder rumano italiano portugués ser numeroso cotizante respectivamente seguir búlgaro británico alemán afiliado mayor parte extranjero estar afiliar seguridad_social finalizar encuadrar régimen_general cotizante seguir régimen_agrario régimen_especial_de_autónomos hogar mar carbón régimen_general total extranjero trabajar hostelería hacer comercio afiliado construcción cotizante cataluña madrid concentrar de inmigrante por comunidad autónomo cataluña madrid concentrar extranjero afiliar seguridad_social sumar total inmigrante ocupar concreto cataluña contar extranjero cotizante madrid cifra ser región situar andalucía afiliado extranjero comunidad_valenciana ocupar murcia castilla-la_mancha canarias aragón castilla león baleares país_vasco comunidad menor presencia inmigrante alto seguridad_social finalizar ser galicia extranjero navarra la_rioja extremadura asturias cantabria ciudad autónomo melilla ceuta",
        "persons": [
            "Agrario",
            "De",
            "León"
        ],
        "locations": [
            "Las_Palmas",
            "Santa_Cruz_de_Tenerife",
            "Canarias",
            "Canarias",
            "Mar",
            "Carbón",
            "Colombia",
            "Bolivia",
            "Perú",
            "República_Dominicana",
            "Mar",
            "Carbón",
            "Cataluña",
            "Cataluña",
            "Cataluña",
            "Madrid",
            "Andalucía",
            "Comunidad_Valenciana",
            "Murcia",
            "Castilla-La_Mancha",
            "Canarias",
            "Aragón",
            "Castilla",
            "Baleares",
            "País_Vasco",
            "Galicia",
            "Navarra",
            "La_Rioja",
            "Extremadura",
            "Asturias",
            "Cantabria",
            "Melilla",
            "Ceuta"
        ],
        "organizations": [
            "General",
            "Autónomos",
            "Empleados_del_Hogar",
            "Trabajadores_del_Mar",
            "Unión_Europea",
            "Afiliados",
            "Régimen_General",
            "Régimen_Agrario",
            "Régimen_de_Autónomos",
            "Hogar",
            "China",
            "Argentina",
            "Ucrania",
            "Brasil",
            "Régimen_General",
            "Régimen_Agrario",
            "Régimen_Especial_de_Autónomos",
            "Hogar",
            "Régimen_General",
            "Por",
            "Madrid"
        ],
        "others": [
            "Seguridad_Social",
            "En",
            "Seguridad_Social",
            "Seguridad_Social",
            "Seguridad_Social",
            "Seguridad_Social"
        ],
        "dates": [
            "[??:??/2/??:??.??:??]",
            "[??:??/2/??:??.??:??]",
            "[??:??/2/??:??.??:??]",
            "[??:??/1/??:??.??:??]",
            "[??:??/8/2009:??.??:??]",
            "[??:??/2/??:??.??:??]",
            "[??:??/1/??:??.??:??]",
            "[??:??/1/??:??.??:??]",
            "[??:??/1/??:??.??:??]"
        ],
        "numbers": [
            "43.134",
            "5,99",
            "100",
            "37.005",
            "7,05",
            "100",
            "56.882",
            "14.947",
            "4.757",
            "3.19",
            "363",
            "80.139",
            "42.447",
            "37.692",
            "45.68",
            "34.459",
            "europea.11.112",
            "1,81",
            "11.112",
            "0,6",
            "100",
            "6",
            "1.179.025",
            "261.122",
            "194.963",
            "177.545",
            "4.61",
            "720",
            "221.682",
            "177.339",
            "112.091",
            "74.424",
            "71.478",
            "69.71",
            "45.361",
            "33.493",
            "30.421",
            "23.575",
            "UE-27",
            "280.316",
            "59.934",
            "57.167",
            "53.303",
            "51.152",
            "38.897",
            "1.179.025",
            "261.122",
            "194.963",
            "177.545",
            "4.61",
            "720",
            "235.634",
            "19,99",
            "100",
            "16,84",
            "100",
            "198.55",
            "14,85",
            "100",
            "175.11",
            "43/100",
            "4/10",
            "43,42",
            "100",
            "398.148",
            "391.296",
            "2",
            "218.909",
            "199.764",
            "87.4",
            "80.545",
            "80.139",
            "62.8",
            "59.509",
            "58.438",
            "50.662",
            "38.537",
            "25.869",
            "16.406",
            "15.689",
            "15.37",
            "11.888",
            "4.001",
            "2.617"
        ]
    }
}
