{
    "province": "LAS PALMAS",
    "date": "2011-01-24T00:00:00",
    "url": "https://www.20minutos.es/noticia/938026/0/",
    "title": {
        "raw_text": "Lanzarote pretende promocionarse por el Canal de La Mancha con embarcaciones de TUI",
        "lemmatized_text": "lanzarote pretender promocionar se por el canal_de_la_mancha con embarcación de tui",
        "lemmatized_text_reduced": "lanzarote pretender promocionar canal_de_la_mancha embarcación tui",
        "persons": [],
        "locations": [
            "Lanzarote"
        ],
        "organizations": [
            "Canal_de_La_Mancha",
            "TUI"
        ],
        "others": [],
        "dates": [],
        "numbers": []
    },
    "lead": {
        "raw_text": "El Patronato de Turismo de Lanzarote y la Sociedad de Promoción Exterior de la isla (SPEL) están negociando con la división náutica de TUI para promocionar la isla en 40 embarcaciones turísticas del touroperador que navegarán por el Canal de La Mancha en el invierno.",
        "lemmatized_text": "el patronato_de_turismo_de_lanzarote y el sociedad_de_promoción_exterior de el isla spel estar negociar con el división náutico de tui para promocionar el isla en 40 embarcación turístico de el touroperador que navegar por el canal_de_la_mancha en el invierno",
        "lemmatized_text_reduced": "patronato_de_turismo_de_lanzarote sociedad_de_promoción_exterior isla spel estar negociar división náutico tui promocionar isla embarcación turístico touroperador navegar canal_de_la_mancha invierno",
        "persons": [],
        "locations": [],
        "organizations": [
            "Patronato_de_Turismo_de_Lanzarote",
            "Sociedad_de_Promoción_Exterior",
            "SPEL",
            "TUI",
            "Canal_de_La_Mancha"
        ],
        "others": [],
        "dates": [],
        "numbers": [
            "40"
        ]
    },
    "body": {
        "raw_text": "El Patronato de Turismo de Lanzarote y la Sociedad de Promoción Exterior de la isla (SPEL) están negociando con la división náutica de TUI para promocionar la isla en 40 embarcaciones turísticas del touroperador que navegarán por el Canal de La Mancha en el invierno. El objetivo de Lanzarote en la Feria Internacional de Turismo (Fitur) de Madrid, que acaba de concluir, ha sido el de posicionar a esta isla canaria como uno de los \"mejores destinos turísticos de Europa\". Por ello, según informó el Cabildo insular en un comunicado, además de conseguir y negociar nuevas conexiones aéreas con la isla y acercar posturas sobre futuros acuerdos promocionales con los diferentes touroperadores y mayoristas, adelantan las negociaciones llevadas a cabo con la división náutica de TUI \"por su novedad e innovación en el campo promocional que se ha desarrollado hasta el momento\". Así, y según lo negociado con TUI, el touroperador estaría en disposición de posicionar en aguas de Lanzarote el próximo verano unas 20 embarcaciones turísticas que posibilitaría la llegada a la isla de visitantes de \"alto poder adquisitivo que repercutirá en los negocios locales\". El logotipo turístico de la marca Lanzarote junto a la del Gobierno de Canarias \"decoraría de forma visible y llamativa estas embarcaciones que en los meses de invierno se desplazarían hasta el Canal de La Mancha, donde se sumarían a otros tantos barcos que también portarían la marca de la isla de los volcanes\". \"Se trata de una acción promocional impagable, pues posicionar el nombre de nuestra isla en una de las rutas de cruceros más importantes del mundo no es algo que se consiga con facilidad\", subrayó la consejera de Turismo del Cabildo de Lanzarote, Carmen González. Ryanair incrementará sus operaciones Por otra parte, González y el gerente de la Sociedad de Promoción Exterior, Héctor Fernández, acudirán a la Feria turística de Dublín para reunirse con Ryanair con el objetivo de ultimar los aspectos promocionales que permitiría la \"consolidación definitiva\" de la compañía en la isla. En este sentido, y en el marco de Fitur 2011 tanto el Cabildo como la compañía aérea de low cost han avanzado en el posicionamiento de dos aviones de Ryanair en Lanzarote a partir de abril y en la promoción conjunta que se quiere llevar a cabo. Además, el \"inminente\" establecimiento de esta base operativa permitirá que \"los lanzaroteños estén mucho mejor conectados con diversas ciudades europeas y de España\", apuntó González. Añadió que la puesta en marcha de once nuevas rutas, se unen a las 18 ya existentes, con lo que Ryanair operará en Lanzarote a partir de abril con unas 70 operaciones semanales. Las nuevas conexiones unirán Lanzarote con los aeropuertos de Valencia, Sevilla, Santiago, Santander, Valladolid y Zaragoza, y con los aeródromos internacionales de Venecia, Eindhoven en Holanda, Baden-Baden en Alemania, Leeds en Inglaterra y Knock en Irlanda.",
        "lemmatized_text": "el patronato_de_turismo_de_lanzarote y el sociedad_de_promoción_exterior de el isla spel estar negociar con el división náutico de tui para promocionar el isla en 40 embarcación turístico de el touroperador que navegar por el canal_de_la_mancha en el invierno el objetivo de lanzarote en el feria_internacional_de_turismo fitur de madrid que acabar de concluir haber ser el de posicionar a este isla canario como uno de el mejor destino turístico de europa por ello según informar el cabildo insular en uno comunicado además_de conseguir y negociar nuevo conexión aéreo con el isla y acercar postura sobre futuro acuerdo promocional con el diferente touroperadores y mayorista adelantar el negociación llevar_a_cabo con el división náutico de tui por su novedad y innovación en el campo promocional que se haber desarrollar hasta el momento así y según el negociado con tui el touroperador estar en disposición de posicionar en agua de lanzarote el próximo verano uno 20 embarcación turístico que posibilitar el llegada a el isla de visitante de alto poder adquisitivo que repercutir en el negocio local el logotipo turístico de el marca lanzarote junto_a el de el gobierno_de_canarias decorar de forma visible y llamativo este embarcación que en el mes de invierno se desplazar hasta el canal_de_la_mancha donde se sumar a otro tanto barco que también portar el marca de el isla de el volcán se tratar de uno acción promocional impagable pues posicionar el nombre de nuestro isla en uno de el ruta de crucero más importante de el mundo no ser algo que se conseguir con facilidad subrayar el consejero de turismo_del_cabildo_de_lanzarote carmen_gonzález ryanair incrementar su operación por otro parte gonzález y el gerente de el sociedad_de_promoción_exterior héctor_fernández acudir a el feria turístico de dublín para reunir se con ryanair con el objetivo de ultimar el aspecto promocional que permitir el consolidación definitivo de el compañía en el isla en este sentido y en el marco de fitur 2011 tanto el cabildo como el compañía aéreo de low cost haber avanzar en el posicionamiento de 2 avión de ryanair en lanzarote a_partir_de [??:??/4/??:??.??:??] y en el promoción conjunto que se querer llevar_a_cabo además el inminente establecimiento de este base operativo permitir que el lanzaroteños estar mucho mejor conectar con diverso ciudad europeo y de españa apuntar gonzález añadir que el puesta en marcha de 11 nuevo ruta se unir a el 18 ya existente con el que ryanair operar en lanzarote a_partir_de [??:??/4/??:??.??:??] con uno 70 operación semanal el nuevo conexión unir lanzarote con el aeropuerto de valencia sevilla santiago santander valladolid y zaragoza y con el aeródromo internacional de venecia eindhoven en holanda baden-baden en alemania leeds en inglaterra y knock en irlanda",
        "lemmatized_text_reduced": "patronato_de_turismo_de_lanzarote sociedad_de_promoción_exterior isla spel estar negociar división náutico tui promocionar isla embarcación turístico touroperador navegar canal_de_la_mancha invierno objetivo lanzarote feria_internacional_de_turismo fitur madrid acabar concluir haber ser posicionar isla canario mejor destino turístico europa informar cabildo insular comunicado conseguir negociar nuevo conexión aéreo isla acercar postura futuro acuerdo promocional diferente touroperadores mayorista adelantar negociación llevar_a_cabo división náutico tui novedad innovación campo promocional haber desarrollar momento negociado tui touroperador estar disposición posicionar agua lanzarote próximo verano embarcación turístico posibilitar llegada isla visitante alto poder adquisitivo repercutir negocio local logotipo turístico marca lanzarote gobierno_de_canarias decorar forma visible llamativo embarcación mes invierno desplazar canal_de_la_mancha sumar barco portar marca isla volcán tratar acción promocional impagable posicionar nombre isla ruta crucero importante mundo ser conseguir facilidad subrayar consejero turismo_del_cabildo_de_lanzarote carmen_gonzález ryanair incrementar operación por parte gonzález gerente sociedad_de_promoción_exterior héctor_fernández acudir feria turístico dublín reunir ryanair objetivo ultimar aspecto promocional permitir consolidación definitivo compañía isla sentido marco fitur cabildo compañía aéreo low cost haber avanzar posicionamiento avión ryanair lanzarote promoción conjunto querer llevar_a_cabo inminente establecimiento base operativo permitir lanzaroteños estar conectar ciudad europeo españa apuntar gonzález añadir puesta marcha nuevo ruta unir existente ryanair operar lanzarote operación semanal nuevo conexión unir lanzarote aeropuerto valencia sevilla santiago santander valladolid zaragoza aeródromo internacional venecia eindhoven holanda baden-baden alemania leeds inglaterra knock irlanda",
        "persons": [
            "Carmen_González",
            "González",
            "Héctor_Fernández",
            "González"
        ],
        "locations": [
            "Lanzarote",
            "Madrid",
            "Europa",
            "Lanzarote",
            "Lanzarote",
            "Canal_de_La_Mancha",
            "Dublín",
            "Lanzarote",
            "España",
            "Lanzarote",
            "Lanzarote",
            "Valencia",
            "Sevilla",
            "Santiago",
            "Santander",
            "Valladolid",
            "Zaragoza",
            "Venecia",
            "Eindhoven",
            "Holanda",
            "Alemania",
            "Inglaterra",
            "Irlanda"
        ],
        "organizations": [
            "Patronato_de_Turismo_de_Lanzarote",
            "Sociedad_de_Promoción_Exterior",
            "SPEL",
            "TUI",
            "Canal_de_La_Mancha",
            "Fitur",
            "Cabildo",
            "TUI",
            "TUI",
            "Gobierno_de_Canarias",
            "Ryanair",
            "Por",
            "Sociedad_de_Promoción_Exterior",
            "Ryanair",
            "Fitur",
            "Cabildo",
            "Ryanair",
            "Ryanair",
            "Baden-Baden",
            "Leeds",
            "Knock"
        ],
        "others": [
            "Feria_Internacional_de_Turismo",
            "Turismo_del_Cabildo_de_Lanzarote",
            "Feria"
        ],
        "dates": [
            "[??:??/4/??:??.??:??]",
            "[??:??/4/??:??.??:??]"
        ],
        "numbers": [
            "40",
            "20",
            "2011",
            "2",
            "11",
            "18",
            "70"
        ]
    }
}
