{
    "province": "LAS PALMAS",
    "date": "2010-06-17T00:00:00",
    "url": "https://www.20minutos.es/noticia/739379/0/",
    "title": {
        "raw_text": "El precio del alquiler en Canarias sube un 0,8% en mayo, según fotocasa.es",
        "lemmatized_text": "el precio de el alquiler en canarias subir uno 0,8/100 en [??:??/5/??:??.??:??] según fotocasa ser",
        "lemmatized_text_reduced": "precio alquiler canarias subir fotocasa ser",
        "persons": [],
        "locations": [
            "Canarias"
        ],
        "organizations": [],
        "others": [],
        "dates": [
            "[??:??/5/??:??.??:??]"
        ],
        "numbers": [
            "0,8/100"
        ]
    },
    "lead": {
        "raw_text": "El precio medio de la vivienda en alquiler en las islas se sitúa en mayo en 6,88 euros por metro cuadrado al mes",
        "lemmatized_text": "el precio medio de el vivienda en alquiler en el isla se situar en [??:??/5/??:??.??:??] en $_ECU:6,88 por metro cuadrado a el mes",
        "lemmatized_text_reduced": "precio medio vivienda alquiler isla situar metro cuadrado mes",
        "persons": [],
        "locations": [],
        "organizations": [],
        "others": [],
        "dates": [
            "[??:??/5/??:??.??:??]"
        ],
        "numbers": [
            "$_ECU:6,88"
        ]
    },
    "body": {
        "raw_text": "La vivienda ha subido en Canarias un 0,8 por ciento respecto al mes anterior, lo que sitúa el valor medio de las rentas de alquiler en mayo en 6,88 euros por metro cuadrado al mes (?/m2 al mes), según el Informe de la Vivienda en Alquiler en España elaborado por fotocasa.es. Si se analizan los últimos doce meses (la variación interanual de mayo de 2009 a mayo de 2010), el precio de la vivienda en alquiler registra un descenso del -3,8 por ciento en el archipiélago, mientras que a nivel nacional se registró una caída del 6,1 por ciento en la variación anual, mientras que el precio medio del alquiler se situó en 8,36 euros por metro cuadrado. Con esta bajada en las islas, se completan 17 meses consecutivos (desde enero de 2009) con descensos en las rentas de la vivienda. Las palmas y tenerife al alza Igualmente, el estudio precisa que si se tiene en cuenta la variación mensual registrada en mayo, tanto en la provincia de Las Palmas como en Tenerife el precio de la vivienda en alquiler sube en el mes de mayo. En concreto un 1,2 por ciento en Las Palmas, lo que sitúa el precio medio en 6,96 ?/m2 al mes, y un 0,1 por ciento en Tenerife, lo que coloca el precio medio en 6,75 ?/m2 al mes. Según los datos del Informe de fotocasa.es, tres de los nueve municipios analizados en Canarias (el 33%) han visto caer el precio de la vivienda en mayo, mientras que los 6 restantes (el 67%) ha registrado crecimientos de precios. El que ha registrado el mayor incremento de precios en mayo es Arucas (Las Palmas) con un 2,3 por ciento. Le han seguido Santa Lucía de Tirajana (Las Palmas) con un 0,7 por ciento y San Cristóbal de la Laguna (Tenerife) con un 0,6 por ciento. En el caso opuesto, el municipio donde más ha bajado el precio de los alquileres en mayo es Telde (Las Palmas) con un -1,4 por ciento, seguido de Arona (Tenerife) con un -1,1 por ciento y Adeje (Tenerife) con un -1,0 por ciento. El municipio canario con el precio medio de la vivienda más cara en mayo de 2010 es Adeje con 7,75 ?/m2 al mes. Por otro lado, el municipio más barato es Santa Lucía de Tirajana con 5,97 ?/m2 al mes.",
        "lemmatized_text": "el vivienda haber subir en canarias uno 0,8 por 100 respecto a el mes anterior el que situar el valor medio de el renta de alquiler en [??:??/5/??:??.??:??] en $_ECU:6,88 por metro cuadrado a el mes /m2 a el mes según el informe_de_la_vivienda en alquiler en españa elaborar por fotocasa ser si se analizar el último 12 mes el variación interanual de [??:??/5/2009:??.??:??] a [??:??/5/2010:??.??:??] el precio de el vivienda en alquiler registrar uno descenso de el -3,8 por 100 en el archipiélago mientras_que a nivel nacional se registrar uno caída de el 6,1 por 100 en el variación anual mientras_que el precio medio de el alquiler se situar en $_ECU:8,36 por metro cuadrado con este bajada en el isla se completar 17 mes consecutivo desde [??:??/1/2009:??.??:??] con descenso en el renta de el vivienda el palma y tenerife a el alza igualmente el estudio precisar que si se tener_en_cuenta el variación mensual registrar en [??:??/5/??:??.??:??] tanto en el provincia de las_palmas como en tenerife el precio de el vivienda en alquiler subir en el [??:??/5/??:??.??:??] en concreto uno 1,2 por 100 en las_palmas el que situar el precio medio en 6,96 /m2 a el mes y uno 0,1 por 100 en tenerife el que colocar el precio medio en 6,75 /m2 a el mes según el dato de el informe de fotocasa ser 3 de el 9 municipio analizar en canarias el 33/100 haber ver caer el precio de el vivienda en [??:??/5/??:??.??:??] mientras_que el 6 restante el 67/100 haber registrar crecimiento de precio el que haber registrar el mayor incremento de precio en [??:??/5/??:??.??:??] ser arucas el palmas con uno 2,3 por 100 le haber seguir santa_lucía_de_tirajana el palmas con uno 0,7 por 100 y san_cristóbal_de_la_laguna tenerife con uno 0,6 por 100 en el caso oponer el municipio donde más haber bajar el precio de el alquiler en [??:??/5/??:??.??:??] ser telde el palmas con uno -1,4 por 100 seguir de arona tenerife con uno -1,1 por 100 y adeje tenerife con uno -1,0 por 100 el municipio canario con el precio medio de el vivienda más caro en [??:??/5/2010:??.??:??] ser adeje con 7,75 /m2 a el mes por_otro_lado el municipio más barato ser santa_lucía_de_tirajana con 5,97 /m2 a el mes",
        "lemmatized_text_reduced": "vivienda haber subir canarias respecto mes anterior situar valor medio renta alquiler metro cuadrado mes mes informe_de_la_vivienda alquiler españa elaborar fotocasa ser analizar último mes variación interanual precio vivienda alquiler registrar descenso archipiélago nivel nacional registrar caída variación anual precio medio alquiler situar metro cuadrado bajada isla completar mes consecutivo descenso renta vivienda palma tenerife alza igualmente estudio precisar tener_en_cuenta variación mensual registrar provincia las_palmas tenerife precio vivienda alquiler subir concreto las_palmas situar precio medio mes tenerife colocar precio medio mes dato informe fotocasa ser municipio analizar canarias haber ver caer precio vivienda restante haber registrar crecimiento precio haber registrar mayor incremento precio ser arucas palmas haber seguir santa_lucía_de_tirajana palmas san_cristóbal_de_la_laguna tenerife caso oponer municipio haber bajar precio alquiler ser telde palmas seguir arona tenerife adeje tenerife municipio canario precio medio vivienda caro ser adeje mes municipio barato ser santa_lucía_de_tirajana mes",
        "persons": [
            "Igualmente",
            "Arucas"
        ],
        "locations": [
            "Canarias",
            "Alquiler",
            "España",
            "Tenerife",
            "Canarias",
            "Palmas",
            "Santa_Lucía_de_Tirajana",
            "Palmas",
            "Palmas",
            "Arona",
            "Tenerife",
            "Santa_Lucía_de_Tirajana"
        ],
        "organizations": [
            "Las_Palmas",
            "Las_Palmas",
            "Tenerife",
            "San_Cristóbal_de_la_Laguna",
            "Tenerife",
            "Telde",
            "Adeje",
            "Tenerife",
            "Adeje"
        ],
        "others": [
            "Informe_de_la_Vivienda",
            "Informe"
        ],
        "dates": [
            "[??:??/5/??:??.??:??]",
            "[??:??/5/2009:??.??:??]",
            "[??:??/5/2010:??.??:??]",
            "[??:??/1/2009:??.??:??]",
            "[??:??/5/??:??.??:??]",
            "[??:??/5/??:??.??:??]",
            "[??:??/5/??:??.??:??]",
            "[??:??/5/??:??.??:??]",
            "[??:??/5/??:??.??:??]",
            "[??:??/5/2010:??.??:??]"
        ],
        "numbers": [
            "0,8",
            "100",
            "$_ECU:6,88",
            "/m2",
            "12",
            "-3,8",
            "100",
            "6,1",
            "100",
            "$_ECU:8,36",
            "17",
            "1,2",
            "100",
            "6,96",
            "/m2",
            "0,1",
            "100",
            "6,75",
            "/m2",
            "3",
            "9",
            "33/100",
            "6",
            "67/100",
            "2,3",
            "100",
            "0,7",
            "100",
            "0,6",
            "100",
            "-1,4",
            "100",
            "-1,1",
            "100",
            "-1,0",
            "100",
            "7,75",
            "/m2",
            "5,97",
            "/m2"
        ]
    }
}
