{
    "province": "LAS PALMAS",
    "date": "2010-06-17T00:00:00",
    "url": "https://www.20minutos.es/noticia/740220/0/",
    "title": {
        "raw_text": "Unas 3.000 personas piden asilo en España en 2009, un 33,6% menos que el año anterior",
        "lemmatized_text": "uno 3 persona pedir asilo en españa en 2009 uno 33,6/100 menos que el año anterior",
        "lemmatized_text_reduced": "persona pedir asilo españa año anterior",
        "persons": [],
        "locations": [
            "España"
        ],
        "organizations": [],
        "others": [],
        "dates": [],
        "numbers": [
            "3",
            "2009",
            "33,6/100"
        ]
    },
    "lead": {
        "raw_text": "Un total de 3.000 personas solicitaron asilo en España en 2009, lo que ha supuesto un descenso del 33,6 por ciento con respecto a 2008, convirtiéndose además en la cifra \"más baja\" de su historia en España.",
        "lemmatized_text": "uno total de 3 persona solicitar asilo en españa en 2009 el que haber suponer uno descenso de el 33,6 por 100 con_respecto_a 2008 convertir se además en el cifra más bajo de su historia en españa",
        "lemmatized_text_reduced": "total persona solicitar asilo españa haber suponer descenso convertir cifra bajo historia españa",
        "persons": [],
        "locations": [
            "España",
            "España"
        ],
        "organizations": [],
        "others": [],
        "dates": [],
        "numbers": [
            "3",
            "2009",
            "33,6",
            "100",
            "2008"
        ]
    },
    "body": {
        "raw_text": "Estos datos se recogen en el informe 2010 que la Comisión Española de Ayuda al Refugiado (CEAR) ha presentado y que aseguró \"llega en un momento de grave preocupación por el estado del asilo en España\". En la rueda de prensa en la que se dieron a conocer estas cifras también estuvo la activista saharaui por los Derechos Humanos El Mami Amar Salem. Respecto a los países de origen de las personas que solicitaron asilo en España procedían a Nigeria (459), Costa de Marfil (304), Colombia (247), Argelia (181), Guinea (130), República Dominicana del Congo (113) y Camerún (112). De todos modos, CEAR señaló que el descenso del número de solicitudes \"no se corresponde con las cifras de asilo en el mundo\", ya que según ACNUR, en los países industrializados han pedido asilo unas 377.000 personas durante 2009, la \"misma cantidad\" que en 2008. Añadió que España \"violó la ley al extraditar durante 2009 a dos solicitantes de asilo cuyas solicitudes estaban en proceso\". Además, los 27 países de la Unión Europea (UE) registraron 260.730 peticiones el pasado año, un 10 por ciento más que las 238.080 de 2008. Asimismo, aseguraron que el \"bajo número de solicitantes de asilo en España tampoco\" se corresponde con el de los países del entorno, ya que Francia recibió 47.625 solicitudes, un 35 por ciento más que en 2008; Grecia tramitó 15.925 peticiones de asilo e Italia 17.470. Madrid la que más solicitudes tuvo En concreto en el conjunto nacional de las 2.916 personas que solicitaron asilo en España el año pasado, 1.313 lo hicieron en la provincia de Madrid, y le siguió la ciudad autonómica de Ceuta (339 peticiones), Barcelona (187), Valencia (179), Málaga (114), Las Palmas (109) y Vizcaya (104). Respecto al caso de Canarias, en total lo solicitaron 143 personas, de las que 109 lo hicieron en la provincia de Las Palmas y 34 en la de Santa Cruz de Tenerife. Los polizones Por otro lado, CEAR también se refirió a los polizones en relación a las dificultades para acceder al derecho de asilo, ya que esta organización tuvo que intervenir en cinco casos en 2009. \"Continúa siendo preocupante el oscurantismo de los puertos y las dificultades para atender a polizones, tanto en Barcelona como en Valencia. La Comisión Catalana de Ayuda al Refugiado realizó gestiones para que dos polizones kurdos pudieran solicitar asilo en el puerto de Barcelona aunque se les negó la posibilidad de bajar del barco y finalmente lo pudieron solicitar en Italia\", criticó. También abogó la organización porque en los Centros de Internamiento de Extranjeros (CIE) se trabaje para garantizar el acceso al derecho de asilo, ya que en 2009 \"una de cada cuatro personas internas en los CIE tendría uno o más motivos para pedir asilo, una cifra veinte veces superior a la del número de personas que lo hacen\". Al respecto, apuntan a que \"sólo\" 83 personas pidieron asilo ante embajadas españolas el año pasado. Las barreras para no llegar a españa En relación a por qué los refugiados no llegan a España, el CEAR apuntó a las acciones de Frontex y a los convenios bilaterales como las barreras para no acceder, ya que ello ha hecho de los países de origen y tránsito de migrantes \"enormes cárceles donde éstos quedan atrapados, impiden que lleguen a territorio europeo inmigrantes y también solicitantes de asilo\". Las consecuencias de este control de fronteras, subrayan, son \"especialmente evidentes\" en el Sur de Europa, en territorio de operaciones de Frontex, donde han descendido en un 33 por ciento las peticiones de asilo (en Italia un -42%, en España -33,5%, Grecia -20% y Turquía -40%). Según ACNUR, los refugiados \"no tienen oportunidad de pedir asilo en la UE porque las patrulleras los devuelven a la costa sin preguntarles si son refugiados\". Por ello, CEAR solicitó que, \"independientemente de dónde y quién controle las fronteras, las prácticas de control fronterizo tengan en cuenta la identificación de personas que necesitan protección y que se garantice\" la protección en los países de tránsito. Los datos del informe de CEAR recogen que en España \"sólo\" 179 personas han obtenido estatuto de refugiado durante 2009, periodo en el que pedían asilo 3.005 personas. Además de esos 179 reconocimientos de estatuto, 162 personas recibían protección complementaria, y 8 protección por razones humanitarias. De esta forma, el ministro del Interior, Alfredo Pérez Rubalcaba, firmó la denegación de la protección internacional a 2.288 personas, por lo que según estos datos España \"se mantiene a la cola de Europa en la protección de las personas refugiadas\", ya que a modo de ejemplo Bélgica reconoció 2.425 estatutos y 480 protecciones subsidiarias el pasado año. Reglamento de asilo Por otro lado, en cuanto al reglamento de asilo, Cear propone cuestiones como el derecho de toda persona a la asistencia jurídica y a intérprete en todos los procedimientos, así como el acceso a las dependencias fronterizas y centros de internamiento. En este sentido, puntualizó que la Ley establece el derecho de los solicitantes de protección internacional a entrevistarse con un abogado en las dependencias fronterizas y los CIE. Para el CEAR el reglamento también debería mantener el plazo de las solicitudes en fronteras, de 72 horas para la resolución en las solicitudes iniciales en puesto fronterizo, ya que este punto ya ha sido aplicado. Además, se pidió la necesidad de que se presenten las peticiones en lo que respecta a las obligaciones de la persona, así como a las garantías del mismo y la formalización. También se pide que se incluyan las solicitudes de protección internacional en embajadas y consulados, ya que la nueva regulación \"no debería convertirse en una actuación discrecional de los funcionarios diplomáticos en la decisión del traslado a España\", pudiendo \"mantener la posibilidad del traslado urgente a España a propuesta del ACNUR, en aquellos casos en los que los refugiados se encuentren en situación de alto riesgo o desprotección en un tercer país\", entre otras cuestiones. Además, exigió la necesidad de que se analicen los expedientes de protección internacional, indicando que la entrevista inicial \"no puede en ningún caso suplir a la audiencia personal\". Información sobre el país de origen, tramitación de las solicitudes de asilo con criterios de género, recursos de revisión, respeto de los derechos sociales, acogida de los solicitantes de protección internacional o autorización de trabajo a los seis meses de formalizada la solicitud, son también cuestiones que se plantean para mantener e incluir en el documento. También solicitan que se regulen las condiciones mínimas de las dependencias en las que se encuentran las personas que piden asilo y garantizar que cumplen al menos con la normativa de centros que prestan atención residencial en las comunidades autónomas en las que se ubican. Además, reclaman que en lo que a efectos de las concesiones de protección se refiere se deberá establecer un plazo máximo de 10 días para la documentación de los beneficiarios de protección internacional, así como la especificación de los organismos competentes para su tramitación. Finalmente, exigen la regulación de los efectos de las resoluciones denegatorias por razones humanitarios, el mantenimiento de la unidad familiar, la realización de pruebas médicas en la extensión familiar cuando \"existan dudas razonables del parentesco sanguíneo\"; así como garantizar la defensa jurídica y la asistencia letrada de los menores no acompañados y de otras personas vulnerables, el reasentamiento, formar a los funcionarios, la cooperación de las administraciones públicas y desarrollar la protección a los apátridas.",
        "lemmatized_text": "este dato se recoger en el informe 2010 que el comisión_española_de_ayuda a el refugiado cear haber presentar y que asegurar llegar en uno momento de grave preocupación por el estado de el asilo en españa en el rueda de prensa en el que se dar_a_conocer este cifra también estar el activista saharaui por el derechos_humanos_el_mami_amar_salem respecto_a el país de origen de el persona que solicitar asilo en españa proceder a nigeria 459 costa_de_marfil 304 colombia 247 argelia 181 guinea 130 república_dominicana_del_congo 113 y camerún 112 de_todos_modos cear señalar que el descenso de el número de solicitud no se corresponder con el cifra de asilo en el mundo ya_que según acnur en el país industrializar haber pedir asilo uno 377 persona durante 2009 el mismo cantidad que en 2008 añadir que españa violar el ley a el extraditar durante 2009 a 2 solicitante de asilo cuyo solicitud estar en proceso además el 27 país de el unión_europea ue registrar 260.73 petición el pasar año uno 10 por 100 más que el 238.08 de 2008 asimismo asegurar que el bajo número de solicitante de asilo en españa tampoco se corresponder con el de el país de el entorno ya_que francia recibir 47.625 solicitud uno 35 por 100 más que en 2008 grecia tramitar 15.925 petición de asilo y italia 17.47 madrid el que más solicitud tener en concreto en el conjunto nacional de el 2.916 persona que solicitar asilo en españa el año pasar 1.313 lo hacer en el provincia de madrid y le seguir el ciudad autonómico de ceuta 339 petición barcelona 187 valencia 179 málaga 114 las_palmas 109 y vizcaya 104 respecto a el caso de canarias en total lo solicitar 143 persona de el que 109 lo hacer en el provincia de las_palmas y 34 en el de santa_cruz_de_tenerife el polizón por_otro_lado cear también se referir a el polizón en relación a el dificultad para acceder a el derecho de asilo ya_que este organización tener que intervenir en 5 caso en 2009 continuar ser preocupante el oscurantismo de el puerto y el dificultad para atender a polizón tanto en barcelona como en valencia el comisión_catalana_de_ayuda a el refugiado realizar gestión para que 2 polizón kurdo poder solicitar asilo en el puerto de barcelona aunque se le negar el posibilidad de bajar de el barco y finalmente lo poder solicitar en italia criticar también abogar el organización porque en el centros_de_internamiento_de_extranjeros cie se trabajar para garantizar el acceso a el derecho de asilo ya_que en 2009 uno de cada 4 persona interno en el cie tener uno o más motivo para pedir asilo uno cifra 20 vez superior a el de el número de persona que lo hacer a el respecto apuntar a que sólo 83 persona pedir asilo ante embajada español el año pasar el barrera para no llegar a españa en relación a por qué el refugiado no llegar a españa el cear apuntar a el acción de frontex y a el convenio bilateral como el barrera para no acceder ya_que ello haber hacer de el país de origen y tránsito de migrante enorme cárcel donde este quedar atrapar impedir que llegar a territorio europeo inmigrante y también solicitante de asilo el consecuencia de este control de frontera subrayar ser especialmente evidente en el sur_de_europa en territorio de operación de frontex donde haber descender en uno 33 por 100 el petición de asilo en italia uno -42/100 en españa -33,5/100 grecia -20/100 y turquía -40/100 según acnur el refugiado no tener oportunidad de pedir asilo en el ue porque el patrullera lo devolver a el costa sin preguntar le si ser refugiado por ello cear solicitar que independientemente de dónde y quién controlar el frontera el práctica de control fronterizo tener_en_cuenta el identificación de persona que necesitar protección y que se garantizar el protección en el país de tránsito el dato de el informe de cear recoger que en españa sólo 179 persona haber obtener estatuto de refugiado durante 2009 periodo en el que pedir asilo 3.005 persona además_de ese 179 reconocimiento de estatuto 162 persona recibir protección complementario y 8 protección por razón humanitario de este forma el ministro de el interior alfredo_pérez_rubalcaba firmar el denegación de el protección internacional a 2.288 persona por el que según este dato españa se mantener a_la_cola de europa en el protección de el persona refugiar ya_que a_modo_de ejemplo bélgica reconocer 2.425 estatuto y 480 protección subsidiario el pasar año reglamento de asilo por_otro_lado en cuanto a el reglamento de asilo cear proponer cuestión como el derecho de todo persona a el asistencia jurídico y a intérprete en todo el procedimiento así_como el acceso a el dependencia fronterizo y centro de internamiento en este sentido puntualizar que el ley establecer el derecho de el solicitante de protección internacional a entrevistar se con uno abogado en el dependencia fronterizo y el cie para el cear el reglamento también deber mantener el plazo de el solicitud en frontera de TM_h:72 para el resolución en el solicitud inicial en puesto fronterizo ya_que este punto ya haber ser aplicar además se pedir el necesidad de que se presentar el petición en el que respectar a el obligación de el persona así_como a el garantía de el mismo y el formalización también se pedir que se incluir el solicitud de protección internacional en embajada y consulado ya_que el nuevo regulación no deber convertir se en uno actuación discrecional de el funcionario diplomático en el decisión de el traslado a españa poder mantener el posibilidad de el traslado urgente a españa a propuesta de el acnur en aquel caso en el que el refugiado se encontrar en situación de alto riesgo o desprotección en uno 3 país entre otro cuestión además exigir el necesidad de que se analizar el expediente de protección internacional indicar que el entrevista inicial no poder en ninguno caso suplir a el audiencia personal información sobre el país de origen tramitación de el solicitud de asilo con criterio de género recurso de revisión respeto de el derecho social acogida de el solicitante de protección internacional o autorización de trabajo a el 6 mes de formalizar el solicitud ser también cuestión que se plantear para mantener y incluir en el documento también solicitar que se regular el condición mínimo de el dependencia en el que se encontrar el persona que pedir asilo y garantizar que cumplir a el menos con el normativa de centro que prestar atención residencial en el comunidad autónomo en el que se ubicar además reclamar que en el que a_efectos_de el concesión de protección se referir se deber establecer uno plazo máximo de TM_d:10 para el documentación de el beneficiario de protección internacional así_como el especificación de el organismo competente para su tramitación finalmente exigir el regulación de el efecto de el resolución denegatorio por razón humanitario el mantenimiento de el unidad familiar el realización de prueba médico en el extensión familiar cuando existir duda razonable de el parentesco sanguíneo así_como garantizar el defensa jurídico y el asistencia letrado de el menor no acompañar y de otro persona vulnerable el reasentamiento formar a el funcionario el cooperación de el administración público y desarrollar el protección a el apátrida",
        "lemmatized_text_reduced": "dato recoger informe comisión_española_de_ayuda refugiado cear haber presentar asegurar llegar momento grave preocupación estado asilo españa rueda prensa dar_a_conocer cifra estar activista saharaui derechos_humanos_el_mami_amar_salem país origen persona solicitar asilo españa proceder nigeria costa_de_marfil colombia argelia guinea república_dominicana_del_congo camerún cear señalar descenso número solicitud corresponder cifra asilo mundo acnur país industrializar haber pedir asilo persona mismo cantidad añadir españa violar ley extraditar solicitante asilo solicitud estar proceso país unión_europea ue registrar petición pasar año asegurar número solicitante asilo españa corresponder país entorno francia recibir solicitud grecia tramitar petición asilo italia madrid solicitud tener en concreto conjunto nacional persona solicitar asilo españa año pasar hacer provincia madrid seguir ciudad autonómico ceuta petición barcelona valencia málaga las_palmas vizcaya respecto caso canarias total solicitar persona hacer provincia las_palmas santa_cruz_de_tenerife polizón por_otro_lado cear referir polizón relación dificultad acceder derecho asilo organización tener intervenir caso continuar ser preocupante oscurantismo puerto dificultad atender polizón barcelona valencia comisión_catalana_de_ayuda refugiado realizar gestión polizón kurdo poder solicitar asilo puerto barcelona negar posibilidad bajar barco finalmente poder solicitar italia criticar abogar organización centros_de_internamiento_de_extranjeros cie trabajar garantizar acceso derecho asilo persona interno cie tener motivo pedir asilo cifra vez superior número persona hacer respecto apuntar persona pedir asilo embajada español año pasar barrera llegar españa en relación refugiado llegar españa cear apuntar acción frontex convenio bilateral barrera acceder haber hacer país origen tránsito migrante enorme cárcel quedar atrapar impedir llegar territorio europeo inmigrante solicitante asilo consecuencia control frontera subrayar ser especialmente evidente sur_de_europa territorio operación frontex haber descender petición asilo italia españa grecia turquía acnur refugiado tener oportunidad pedir asilo ue patrullera devolver costa preguntar ser refugiado cear solicitar independientemente controlar frontera práctica control fronterizo tener_en_cuenta identificación persona necesitar protección garantizar protección país tránsito dato informe cear recoger españa persona haber obtener estatuto refugiado periodo pedir asilo persona reconocimiento estatuto persona recibir protección complementario protección razón humanitario forma ministro interior alfredo_pérez_rubalcaba firmar denegación protección internacional persona dato españa mantener europa protección persona refugiar ejemplo bélgica reconocer estatuto protección subsidiario pasar año reglamento asilo por_otro_lado reglamento asilo cear proponer cuestión derecho persona asistencia jurídico intérprete procedimiento acceso dependencia fronterizo centro internamiento sentido puntualizar ley establecer derecho solicitante protección internacional entrevistar abogado dependencia fronterizo cie cear reglamento deber mantener plazo solicitud frontera resolución solicitud inicial puesto fronterizo punto haber ser aplicar pedir necesidad presentar petición respectar obligación persona garantía mismo formalización pedir incluir solicitud protección internacional embajada consulado nuevo regulación deber convertir actuación discrecional funcionario diplomático decisión traslado españa poder mantener posibilidad traslado urgente españa propuesta acnur caso refugiado encontrar situación alto riesgo desprotección 3 país cuestión exigir necesidad analizar expediente protección internacional indicar entrevista inicial poder caso suplir audiencia personal información país origen tramitación solicitud asilo criterio género recurso revisión respeto derecho social acogida solicitante protección internacional autorización trabajo mes formalizar solicitud ser cuestión plantear mantener incluir documento solicitar regular condición mínimo dependencia encontrar persona pedir asilo garantizar cumplir normativa centro prestar atención residencial comunidad autónomo ubicar reclamar concesión protección referir deber establecer plazo máximo documentación beneficiario protección internacional especificación organismo competente tramitación finalmente exigir regulación efecto resolución denegatorio razón humanitario mantenimiento unidad familiar realización prueba médico extensión familiar existir duda razonable parentesco sanguíneo garantizar defensa jurídico asistencia letrado menor acompañar persona vulnerable reasentamiento formar funcionario cooperación administración público desarrollar protección apátrida",
        "persons": [
            "Costa_de_Marfil",
            "Guinea",
            "República_Dominicana_del_Congo",
            "Camerún",
            "España",
            "En",
            "Por_otro_lado",
            "En",
            "Alfredo_Pérez_Rubalcaba",
            "España",
            "Cear",
            "España",
            "España"
        ],
        "locations": [
            "España",
            "España",
            "Nigeria",
            "Colombia",
            "Argelia",
            "España",
            "Grecia",
            "Madrid",
            "España",
            "Madrid",
            "Ceuta",
            "Valencia",
            "Málaga",
            "Vizcaya",
            "Canarias",
            "Las_Palmas",
            "Santa_Cruz_de_Tenerife",
            "Barcelona",
            "Valencia",
            "Barcelona",
            "Italia",
            "España",
            "Frontex",
            "Italia",
            "España",
            "España",
            "Por_otro_lado"
        ],
        "organizations": [
            "Comisión_Española_de_Ayuda",
            "Refugiado",
            "CEAR",
            "Derechos_Humanos_El_Mami_Amar_Salem",
            "CEAR",
            "ACNUR",
            "Unión_Europea",
            "UE",
            "Francia",
            "Italia",
            "Barcelona",
            "Las_Palmas",
            "CEAR",
            "Comisión_Catalana_de_Ayuda",
            "Refugiado",
            "Centros_de_Internamiento_de_Extranjeros",
            "CIE",
            "CIE",
            "CEAR",
            "Frontex",
            "Sur_de_Europa",
            "Grecia",
            "Turquía",
            "ACNUR",
            "UE",
            "CEAR",
            "CEAR",
            "Europa",
            "Bélgica",
            "CIE",
            "CEAR",
            "ACNUR"
        ],
        "others": [
            "Interior",
            "Ley",
            "Información"
        ],
        "dates": [],
        "numbers": [
            "2010",
            "459",
            "304",
            "247",
            "181",
            "130",
            "113",
            "112",
            "377",
            "2009",
            "2008",
            "2009",
            "2",
            "27",
            "260.73",
            "10",
            "100",
            "238.08",
            "2008",
            "47.625",
            "35",
            "100",
            "2008",
            "15.925",
            "17.47",
            "2.916",
            "1.313",
            "339",
            "187",
            "179",
            "114",
            "109",
            "104",
            "143",
            "109",
            "34",
            "5",
            "2009",
            "2",
            "2009",
            "4",
            "20",
            "83",
            "33",
            "100",
            "-42/100",
            "-33,5/100",
            "-20/100",
            "-40/100",
            "179",
            "2009",
            "3.005",
            "179",
            "162",
            "8",
            "2.288",
            "2.425",
            "480",
            "TM_h:72",
            "6",
            "TM_d:10"
        ]
    }
}
