{
    "province": "LAS PALMAS",
    "date": "2010-01-28T00:00:00",
    "url": "https://www.20minutos.es/noticia/616578/0/",
    "title": {
        "raw_text": "Canarias fue el destino preferido para alojarse en apartamentos en 2009, con más de 29 millones de pernoctaciones",
        "lemmatized_text": "canario ser el destino preferir para alojar se en apartamento en 2009 con más de 29000000 de pernoctación",
        "lemmatized_text_reduced": "canario ser destino preferir alojar apartamento pernoctación",
        "persons": [],
        "locations": [],
        "organizations": [],
        "others": [],
        "dates": [],
        "numbers": [
            "2009",
            "29000000"
        ]
    },
    "lead": {
        "raw_text": "La Comunidad Autónoma de Canarias fue el destino preferido por los turistas que apostaron por un apartamento para alojarse durante 2009, ya que registró más de 29,1 millones de pernoctaciones el pasado año, un 16,9 por ciento menos que en 2008, según los datos difundidos hoy por el Instituto Nacional de Estadística (INE).",
        "lemmatized_text": "el comunidad_autónoma_de_canarias ser el destino preferir por el turista que apostar por uno apartamento para alojar se durante 2009 ya_que registrar más de 29,1 millón de pernoctación el pasar año uno 16,9 por 100 menos que en 2008 según el dato difundir hoy por el instituto_nacional_de_estadística ine",
        "lemmatized_text_reduced": "comunidad_autónoma_de_canarias ser destino preferir turista apostar apartamento alojar registrar millón pernoctación pasar año dato difundir instituto_nacional_de_estadística ine",
        "persons": [],
        "locations": [],
        "organizations": [
            "Comunidad_Autónoma_de_Canarias",
            "Instituto_Nacional_de_Estadística"
        ],
        "others": [],
        "dates": [],
        "numbers": [
            "2009",
            "29,1",
            "16,9",
            "100",
            "2008"
        ]
    },
    "body": {
        "raw_text": "En concreto, Canarias recibió en 2009 más de 3,3 millones de viajeros, de los que 719.000 eran residentes en España y 2,6 millones procedían del extranjero. Por tanto, el archipiélago contabilizó más de 29 millones de pernoctaciones en alojamientos turísticos extrahoteleros (apartamentos, campings y alojamientos de turismo rural), registrando una estancia media de 8,61 días. El archipiélago canario ocupó el segundo lugar a nivel nacional en el grado de ocupación, con 57,6 por ciento seguido por Baleares con el 58,7 por ciento de los apartamentos ofertados. Por zonas turísticas, la isla de Gran Canaria fue el destino preferido en esta modalidad de alojamiento, con más de 10,9 millones de pernoctaciones. La isla de Tenerife alcanzó en media la mayor ocupación, el 62,0 por ciento de los apartamentos ofertados. Los puntos turísticos con mayor número de pernoctaciones fueron San Bartolomé de Tirajana (Gran Canaria), Arona (Tenerife) y Tías (Lanzarote). A nivel nacional, las pernoctaciones realizadas en alojamientos turísticos extrahoteleros alcanzaron los 97,5 millones en 2009, lo que supone un descenso del 9,1 por ciento respecto a 2008, confirmando así el mal año que ha tenido el turismo a causa de la crisis. Se trata de la tercera caída anual consecutiva que experimenta el turismo extrahotelero, que en 2007 vio reducir el número de pernoctaciones un 1,2 por ciento y en 2008, un 2,3 por ciento, si bien el organismo estadístico precisó que los datos de 2009 no son directamente comparables con los anteriores debido a la actualización en el directorio de alojamientos de turismo rural de Canarias. El fuerte descenso de las pernoctaciones en alojamientos extrahoteleros experimentada el año pasado fue resultado de la intensa disminución registrada por las pernoctaciones de los extranjeros, que se redujeron un 13,3 por ciento en 2009, mientras que las realizadas por los residentes cayeron más levemente, un 1,9 por ciento. Sumando los datos de los hoteles, publicados recientemente por el INE, las pernoctaciones en alojamientos españoles de turismo colectivo totalizaron 349,4 millones el año pasado, un 7,4 por ciento menos que en 2008, consecuencia de las caídas en un 10,5 por ciento de las pernoctaciones de los extranjeros y en un 2,9 por ciento de las efectuadas por los españoles. Teniendo en cuenta todos los alojamientos turísticos colectivos (hoteles, apartamentos, campings y casas rurales), la estancia media de 2009 se situó en 3,7 pernoctaciones por viajero, un 1,4 por ciento menos que en 2008. Del total de pernoctaciones realizadas en todos estos establecimientos, el 72,1 por ciento se efectuaron en hoteles y el 27,9 por ciento en apartamentos, campings y casas rurales. Bajan un 14% Las pernoctaciones en apartamentos Del conjunto de pernoctaciones realizadas el año pasado en alojamientos extrahoteleros, seis de cada diez correspondieron a apartamentos turísticos. No obstante, las pernoctaciones en esta clase de alojamiento disminuyeron un 13,8 por ciento en 2009, hasta situarse en 58,9 millones. Este descenso se produjo tanto entre los residentes, cuya tasa anual cayó un 6,7 por ciento, como entre los no residentes, donde las pernoctaciones bajaron un 15,9 por ciento. La oferta en apartamentos turísticos subió un 0,2 por ciento el año pasado, alcanzando una media de 442.550 plazas. Durante 2009 se ocuparon el 36,2 por ciento del total de plazas ofertadas, un 13,3 por ciento menos que en 2008. El grado de ocupación por plazas en fin de semana se situó en el 37,8 por ciento, con un descenso anual del 12 por ciento. Del total de apartamentos turísticos ofertados se ocuparon el 51,1 por ciento, lo que supone una bajada del 11,8 por ciento. Las pernoctaciones de no residentes en apartamentos supusieron el 75 por ciento del total. Reino Unido continuó siendo el primer mercado emisor en apartamentos turísticos, con 15,4 millones de pernoctaciones en 2009, un 21,5 por ciento menos que en 2008, seguido del mercado alemán, con 8,5 millones de pernoctaciones, un 15 por ciento menos. Por su lado, los acampamentos turísticos alcanzaron en 2009 la cifra de 30,6 millones de pernoctaciones, lo que supone un descenso del 1,3 por ciento con respecto a 2008, mientras que los alojamientos de turismo rural sumaron 7,9 millones de pernoctaciones, con un repunte del 0,3 por ciento sobre el año anterior. LOS PRECIOS EN APARTAMENTOS TURÍSTICOS Bajan un 1,7% De acuerdo con los datos del INE, el índice de precios en apartamentos turísticos registró una disminución media del 1,7 por ciento el año pasado. La tarifa 'touroperador y agencia de viajes', que tuvo el mayor peso en la estructura de ponderaciones todo los meses del año, descendió un 1,4 por ciento. Por modalidades, los apartamentos de entre dos y cuatro plazas redujeron sus precios un 2,1 por ciento de media respecto a 2008. Por su parte, el índice de precios en acampamentos turísticos experimentó un crecimiento interanual del 3,1 por ciento en 2009. La tarifa normal, con una ponderación superior al 43 por ciento todos los meses del año, presentó una subida media del 3,5 por ciento. Por categorías, la tarifa de segunda registró un aumento anual promedio del 2,7 por ciento. Finalmente, el índice de precios de alojamientos de turismo rural registró un incremento anual del 0,3 por ciento. Por modalidad de alquiler, la de uso completo registró un repunte de sus precios del 0,6 por ciento. Asimismo, la 'tarifa fin de semana' se abarató el año pasado una media del 0,5 por ciento.",
        "lemmatized_text": "en concreto canarias recibir en 2009 más de 3,3 millón de viajero de el que 719 ser residente en españa y 2,6 millón proceder de el extranjero por tanto el archipiélago contabilizar más de 29000000 de pernoctación en alojamiento turístico extrahoteleros apartamento camping y alojamiento de turismo rural registrar uno estancia medio de TM_d:8,61 el archipiélago canario ocupar el 2 lugar a nivel nacional en el grado de ocupación con 57,6 por 100 seguir por baleares con el 58,7 por 100 de el apartamento ofertar por zona turístico el isla de gran_canaria ser el destino preferir en este modalidad de alojamiento con más de 10,9 millón de pernoctación el isla de tenerife alcanzar en medio el mayor ocupación el 62,0 por 100 de el apartamento ofertar el punto turístico con mayor número de pernoctación ser san_bartolomé_de_tirajana gran_canaria arona tenerife y tías lanzarote a nivel nacional el pernoctación realizar en alojamiento turístico extrahoteleros alcanzar el 97,5 millón en 2009 el que suponer uno descenso de el 9,1 por 100 respecto_a 2008 confirmar así el mal año que haber tener el turismo a_causa_de el crisis se tratar de el 3 caída anual consecutivo que experimentar el turismo extrahotelero que en 2007 ver reducir el número de pernoctación uno 1,2 por 100 y en 2008 uno 2,3 por 100 si bien el organismo estadístico precisar que el dato de 2009 no ser directamente comparable con el anterior debido_a el actualización en el directorio de alojamiento de turismo rural de canarias el fuerte descenso de el pernoctación en alojamiento extrahoteleros experimentar el año pasar ser resultar de el intenso disminución registrar por el pernoctación de el extranjero que se reducir uno 13,3 por 100 en 2009 mientras_que el realizar por el residente caer más levemente uno 1,9 por 100 sumar el dato de el hotel publicar recientemente por el ine el pernoctación en alojamiento español de turismo colectivo totalizar 349,4 millón el año pasar uno 7,4 por 100 menos que en 2008 consecuencia de el caída en uno 10,5 por 100 de el pernoctación de el extranjero y en uno 2,9 por 100 de el efectuar por el español tener_en_cuenta todo el alojamiento turístico colectivo hotel apartamento camping y casa rural el estancia medio de 2009 se situar en 3,7 pernoctación por viajero uno 1,4 por 100 menos que en 2008 de el total de pernoctación realizar en todo este establecimiento el 72,1 por 100 se efectuar en hotel y el 27,9 por 100 en apartamento camping y casa rural bajar uno 14/100 las pernoctación en apartamento del conjunto de pernoctación realizar el año pasar en alojamiento extrahoteleros 6/10 corresponder a apartamento turístico no_obstante el pernoctación en este clase de alojamiento disminuir uno 13,8 por 100 en 2009 hasta situar se en 58,9 millón este descenso se producir tanto entre el residente cuyo tasa anual caer uno 6,7 por 100 como entre el no residente donde el pernoctación bajar uno 15,9 por 100 el oferta en apartamento turístico subir uno 0,2 por 100 el año pasar alcanzar uno medio de 442.55 plaza durante 2009 se ocupar el 36,2 por 100 de el total de plaza ofertar uno 13,3 por 100 menos que en 2008 el grado de ocupación por plaza en fin de semana se situar en el 37,8 por 100 con uno descenso anual de el 12 por 100 de el total de apartamento turístico ofertar se ocupar el 51,1 por 100 el que suponer uno bajada de el 11,8 por 100 el pernoctación de no residente en apartamento suponer el 75 por 100 de el total reino_unido continuar ser el 1 mercado emisor en apartamento turístico con 15,4 millón de pernoctación en 2009 uno 21,5 por 100 menos que en 2008 seguir de el mercado alemán con 8,5 millón de pernoctación uno 15 por 100 menos por su lado el acampamento turístico alcanzar en 2009 el cifra de 30,6 millón de pernoctación el que suponer uno descenso de el 1,3 por 100 con_respecto_a 2008 mientras_que el alojamiento de turismo rural sumar 7,9 millón de pernoctación con uno repunte de el 0,3 por 100 sobre el año anterior los_precios_en_apartamentos_turísticos_bajan uno 1,7/100 de_acuerdo_con el dato de el ine el índice de precio en apartamento turístico registrar uno disminución medio de el 1,7 por 100 el año pasar el tarifa touroperador y agencia de viaje que tener el mayor peso en el estructura de ponderación todo el mes de el año descender uno 1,4 por 100 por modalidad el apartamento de entre 2 y 4 plaza reducir su precio uno 2,1 por 100 de medio respecto_a 2008 por su parte el índice de precio en acampamento turístico experimentar uno crecimiento interanual de el 3,1 por 100 en 2009 el tarifa normal con uno ponderación superior a el 43 por 100 todo el mes de el año presentar uno subida medio de el 3,5 por 100 por categoría el tarifa de 2 registrar uno aumento anual promedio de el 2,7 por 100 finalmente el índice de precio de alojamiento de turismo rural registrar uno incremento anual de el 0,3 por 100 por modalidad de alquiler el de uso completo registrar uno repunte de su precio de el 0,6 por 100 asimismo el tarifa fin de semana se abaratar el año pasar uno medio de el 0,5 por 100",
        "lemmatized_text_reduced": "concreto canarias recibir millón viajero ser residente españa millón proceder extranjero archipiélago contabilizar pernoctación alojamiento turístico extrahoteleros apartamento camping alojamiento turismo rural registrar estancia medio archipiélago canario ocupar 2 lugar nivel nacional grado ocupación seguir baleares apartamento ofertar zona turístico isla gran_canaria ser destino preferir modalidad alojamiento millón pernoctación isla tenerife alcanzar medio mayor ocupación apartamento ofertar punto turístico mayor número pernoctación ser san_bartolomé_de_tirajana gran_canaria arona tenerife tías lanzarote nivel nacional pernoctación realizar alojamiento turístico extrahoteleros alcanzar millón suponer descenso confirmar mal año haber tener turismo crisis tratar 3 caída anual consecutivo experimentar turismo extrahotelero ver reducir número pernoctación organismo estadístico precisar dato ser directamente comparable anterior actualización directorio alojamiento turismo rural canarias fuerte descenso pernoctación alojamiento extrahoteleros experimentar año pasar ser resultar intenso disminución registrar pernoctación extranjero reducir realizar residente caer levemente sumar dato hotel publicar recientemente ine pernoctación alojamiento español turismo colectivo totalizar millón año pasar consecuencia caída pernoctación extranjero efectuar español tener_en_cuenta alojamiento turístico colectivo hotel apartamento camping casa rural estancia medio situar pernoctación viajero total pernoctación realizar establecimiento efectuar hotel apartamento camping casa rural bajar las pernoctación apartamento del conjunto pernoctación realizar año pasar alojamiento extrahoteleros corresponder apartamento turístico pernoctación clase alojamiento disminuir situar millón descenso producir residente tasa anual caer residente pernoctación bajar oferta apartamento turístico subir año pasar alcanzar medio plaza ocupar total plaza ofertar grado ocupación plaza fin semana situar descenso anual total apartamento turístico ofertar ocupar suponer bajada pernoctación residente apartamento suponer total reino_unido continuar ser 1 mercado emisor apartamento turístico millón pernoctación seguir mercado alemán millón pernoctación lado acampamento turístico alcanzar cifra millón pernoctación suponer descenso alojamiento turismo rural sumar millón pernoctación repunte año anterior los_precios_en_apartamentos_turísticos_bajan de_acuerdo_con dato ine índice precio apartamento turístico registrar disminución medio año pasar tarifa touroperador agencia viaje tener mayor peso estructura ponderación mes año descender modalidad apartamento plaza reducir precio medio parte índice precio acampamento turístico experimentar crecimiento interanual tarifa normal ponderación superior mes año presentar subida medio categoría tarifa 2 registrar aumento anual promedio finalmente índice precio alojamiento turismo rural registrar incremento anual modalidad alquiler uso completo registrar repunte precio tarifa fin semana abaratar año pasar medio",
        "persons": [
            "Arona",
            "Tías",
            "De_acuerdo_con"
        ],
        "locations": [
            "Canarias",
            "España",
            "Baleares",
            "Gran_Canaria",
            "Tenerife",
            "Canarias",
            "Reino_Unido"
        ],
        "organizations": [
            "San_Bartolomé_de_Tirajana",
            "Gran_Canaria",
            "Tenerife",
            "Lanzarote",
            "INE",
            "INE"
        ],
        "others": [
            "Las",
            "Del",
            "LOS_PRECIOS_EN_APARTAMENTOS_TURÍSTICOS_Bajan"
        ],
        "dates": [],
        "numbers": [
            "2009",
            "3,3",
            "719",
            "2,6",
            "29000000",
            "TM_d:8,61",
            "57,6",
            "100",
            "58,7",
            "100",
            "10,9",
            "62,0",
            "100",
            "97,5",
            "2009",
            "9,1",
            "100",
            "2008",
            "2007",
            "1,2",
            "100",
            "2008",
            "2,3",
            "100",
            "2009",
            "13,3",
            "100",
            "2009",
            "1,9",
            "100",
            "349,4",
            "7,4",
            "100",
            "2008",
            "10,5",
            "100",
            "2,9",
            "100",
            "2009",
            "3,7",
            "1,4",
            "100",
            "2008",
            "72,1",
            "100",
            "27,9",
            "100",
            "14/100",
            "6/10",
            "13,8",
            "100",
            "2009",
            "58,9",
            "6,7",
            "100",
            "15,9",
            "100",
            "0,2",
            "100",
            "442.55",
            "2009",
            "36,2",
            "100",
            "13,3",
            "100",
            "2008",
            "37,8",
            "100",
            "12",
            "100",
            "51,1",
            "100",
            "11,8",
            "100",
            "75",
            "100",
            "15,4",
            "2009",
            "21,5",
            "100",
            "2008",
            "8,5",
            "15",
            "100",
            "2009",
            "30,6",
            "1,3",
            "100",
            "2008",
            "7,9",
            "0,3",
            "100",
            "1,7/100",
            "1,7",
            "100",
            "1,4",
            "100",
            "2",
            "4",
            "2,1",
            "100",
            "2008",
            "3,1",
            "100",
            "2009",
            "43",
            "100",
            "3,5",
            "100",
            "2,7",
            "100",
            "0,3",
            "100",
            "0,6",
            "100",
            "0,5",
            "100"
        ]
    }
}
