{
    "province": "LAS PALMAS",
    "date": "2009-12-21T00:00:00",
    "url": "https://www.20minutos.es/noticia/592658/0/",
    "title": {
        "raw_text": "La llegada de turistas extranjeros a Canarias cae un 13% hasta noviembre, con 7,4 millones",
        "lemmatized_text": "el llegada de turista extranjero a canarias caer uno 13/100 hasta [??:??/11/??:??.??:??] con 7,4 millón",
        "lemmatized_text_reduced": "llegada turista extranjero canarias caer millón",
        "persons": [],
        "locations": [
            "Canarias"
        ],
        "organizations": [],
        "others": [],
        "dates": [
            "[??:??/11/??:??.??:??]"
        ],
        "numbers": [
            "13/100",
            "7,4"
        ]
    },
    "lead": {
        "raw_text": "Canarias fue la región que más visitantes recibió en noviembre, con 800.000 millones llegadas (-6,8%)",
        "lemmatized_text": "canario ser el región que más visitante recibir en [??:??/11/??:??.??:??] con 800000000 llegar -6,8/100",
        "lemmatized_text_reduced": "canario ser región visitante recibir llegar",
        "persons": [],
        "locations": [],
        "organizations": [],
        "others": [],
        "dates": [
            "[??:??/11/??:??.??:??]"
        ],
        "numbers": [
            "800000000",
            "-6,8/100"
        ]
    },
    "body": {
        "raw_text": "España recibió 49,5 millones de turistas extranjeros hasta noviembre, lo que representa una caída del 8,9 por ciento en relación al mismo periodo de 2008, según los datos de la Encuesta de Movimientos Turísticos en Frontera (Frontur) hechos públicos hoy por el Ministerio de Industria, Turismo y Comercio, que precisan que Canarias registró 7,4 millones de visitantes, lo que supone un recorte del 13 por ciento respecto a la misma etapa del pasado año. El Ministerio señaló que \"se consolida la tendencia de desaceleración en el ritmo de caída de la llegada de turistas que se viene observando desde el segundo trimestre\". El descenso en el número de visitantes en octubre fue del 9,3% mientras que en septiembre, agosto y julio se situó en torno al 10%. El primer mercado emisor de visitantes de enero a noviembre siguió siendo Reino Unido, que con 12,7 millones de turistas registró una caída del 15,6% con respecto al mismo periodo del ejercicio anterior. En segundo lugar se situó el mercado alemán, con la llegada de 8,5 millones de turistas, un 11,3% menos. En tercer lugar se sitúa Francia, con 7,5 millones de turistas, un 2,9% menos que en los once primeros meses del año pasado, seguido de los Países Nórdicos y de Italia, con 3,1 millones (-6,6%) y 2,9 millones (-6,7%) de turistas, respectivamente. Por comunidades, Cataluña fue de enero a noviembre el primer destino nacional al alcanzar los 12,1 millones de turistas, pese a experimentar un descenso del 10,7%. Le siguieron Baleares, con 8,9 millones de turistas, un 9,5% menos; así como Canarias y Andalucía, que con 7,4 millones de visitantes y 6,9 millones, respectivamente, registraron ambas recortes del 13% y del 9,2%, en cada caso. La Comunidad Valenciana contabilizó 4,8 millones de turistas, un 10,9% menos, mientras que la comunidad de Madrid alcanzó los 4,5 millones, tras registrar un ascenso del 5,9%, representando la única comunidad que creció en número de visitantes en el periodo acumulado.UN 3,1% Menos en noviembre . En el mes de noviembre, España recibió 2,8 millones de turistas, lo que supone un descenso del 3,1% con respecto al mismo mes del año anterior, pero una moderación de medio punto porcentual respecto a la caída registrada en octubre, del 3,6%. La comunidad que más visitantes recibió en noviembre fue Canarias, con 800.000 millones llegadas (-6,8%), seguida de Cataluña, con más de 650.000 visitantes (-12,9%); Andalucía, con más de 375.000 turistas (+6,9%) y Madrid, con unos 370.500 turistas (+15,4%). Finalmente, la Comunidad Valenciana, con 248.019 visitantes (-0,6%) y Baleares, con 148.019 turistas (-17,6%), presentaron los menores registros. Por mercados, Reino Unido continuó su senda descendente con un desplome del 13,3%, hasta 629.194 de visitantes, mientras que la llegada de alemanes se desplomó un 15,5%, con 445.109 visitantes. Los turistas procedentes de Francia, un total de 389.326 visitantes, y los de Bélgica, un total de 91.063, se elevaron un 4,3% y un 9,2%, respectivamente. Industria señala que el descenso en la llegada de turistas de Reino Unido, origen del 20% de los turistas internacionales que visitan España, continúa experimentando una \"tendencia de caída general\".EL 69,4% De viajeros , Sin paquete turístico . La principal vía de acceso de los turistas internacionales recibidos en los once primeros meses del año fue la aérea, elegida por 38,1 millones de visitantes —el 77,1% del total—, con un descenso del 9,5%. Por carretera llegaron 9,8 millones de turistas, lo que supone un descenso del 7,1% en relación al mismo periodo del año anterior. Paralelamente, un 69,4% (34,3 millones) de los turistas que llegaron a España no habían contratado un paquete turístico, un 8,9% menos. Los turistas que sí lo contrataron, por su parte, fueron 14,8 millones, una cifra un 8,6% inferior a la del mismo periodo del ejercicio anterior. El tipo de alojamiento mayoritariamente elegido por los turistas internacionales recibidos en hasta noviembre fue el hotelero, al que acudió el 61,2% de los visitantes (30,2 millones, un 12,8% menos). Por su parte, el alojamiento extrahotelero —vivienda propia o de familiares, vivienda alquilada, camping, etc.— registró un retroceso del 1,7% respecto al mismo periodo del ejercicio anterior, situándose en los 18,8 millones de turistas. En noviembre, los turistas sin paquete turístico ascendieron un 4%, mientras que los que lo utilizaron se redujo en un 16,4% con respecto al mismo mes de 2008. El alojamiento hotelero aún siendo el preferido cayó un 7%, mientras que el no hotelero se incrementó un 5,5%, especialmente por la vivienda propia y de familiares o amigos (+12,2%). Las llegadas por vía aérea descendieron un 3,7% y los viajes por carretera se elevaron un 0,4% el mes pasado.",
        "lemmatized_text": "españa recibir 49,5 millón de turista extranjero hasta [??:??/11/??:??.??:??] el que representar uno caída de el 8,9 por 100 en relación a el mismo periodo de 2008 según el dato de el encuesta_de_movimientos_turísticos en frontera frontur hecho público hoy por el ministerio_de_industria turismo y comercio que precisar que canarias registrar 7,4 millón de visitante el que suponer uno recorte de el 13 por 100 respecto_a el mismo etapa de el pasar año el ministerio señalar que se consolidar el tendencia de desaceleración en el ritmo de caída de el llegada de turista que se venir observar desde el 2 trimestre el descenso en el número de visitante en [??:??/10/??:??.??:??] ser de el 9,3/100 mientras_que en [??:??/9/??:??.??:??] [??:??/8/??:??.??:??] y [??:??/7/??:??.??:??] se situar en torno a el 10/100 el 1 mercado emisor de visitante de [??:??/1/??:??.??:??] a [??:??/11/??:??.??:??] seguir ser reino_unido que con 12,7 millón de turista registrar uno caída de el 15,6/100 con respecto a el mismo periodo de el ejercicio anterior en 2 lugar se situar el mercado alemán con el llegada de 8,5 millón de turista uno 11,3/100 menos en 3 lugar se situar francia con 7,5 millón de turista uno 2,9/100 menos que en el 11 1 mes de el año pasar seguir de el países_nórdicos y de italia con 3,1 millón -6,6/100 y 2,9 millón -6,7/100 de turista respectivamente por comunidad cataluña ser de [??:??/1/??:??.??:??] a [??:??/11/??:??.??:??] el 1 destino nacional a el alcanzar el 12,1 millón de turista pese_a experimentar uno descenso de el 10,7/100 le seguir baleares con 8,9 millón de turista uno 9,5/100 menos así_como canarias y andalucía que con 7,4 millón de visitante y 6,9 millón respectivamente registrar ambos recorte de el 13/100 y de el 9,2/100 en cada caso el comunidad_valenciana contabilizar 4,8 millón de turista uno 10,9/100 menos mientras_que el comunidad de madrid alcanzar el 4,5 millón tras registrar uno ascenso de el 5,9/100 representar el único comunidad que crecer en número de visitante en el periodo acumular uno 3,1/100 menos en [??:??/11/??:??.??:??] en el [??:??/11/??:??.??:??] españa recibir 2,8 millón de turista el que suponer uno descenso de el 3,1/100 con respecto a el mismo mes de el año anterior pero uno moderación de medio punto porcentual respecto_a el caída registrar en [??:??/10/??:??.??:??] de el 3,6/100 el comunidad que más visitante recibir en [??:??/11/??:??.??:??] ser canarias con 800000000 llegar -6,8/100 seguir de cataluña con más de 650 visitante -12,9/100 andalucía con más de 375 turista +6,9/100 y madrid con uno 370.5 turista +15,4/100 finalmente el comunidad_valenciana con 248.019 visitante -0,6/100 y baleares con 148.019 turista -17,6/100 presentar el menor registro por mercado reino_unido continuar su senda descendente con uno desplome de el 13,3/100 hasta 629.194 de visitante mientras_que el llegada de alemán se desplomar uno 15,5/100 con 445.109 visitante el turista procedente de francia uno total de 389.326 visitante y el de bélgica uno total de 91.063 se elevar uno 4,3/100 y uno 9,2/100 respectivamente industria señalar que el descenso en el llegada de turista de reino_unido origen de el 20/100 de el turista internacional que visitar españa continuar experimentar uno tendencia de caída general el 69,4/100 de viajero sin paquete turístico el principal vía de acceso de el turista internacional recibir en el 11 1 mes de el año ser el aéreo elegir por 38,1 millón de visitante el 77,1/100 de el total con uno descenso de el 9,5/100 por carretera llegar 9,8 millón de turista el que suponer uno descenso de el 7,1/100 en relación a el mismo periodo de el año anterior paralelamente uno 69,4/100 34,3 millón de el turista que llegar a españa no haber contratar uno paquete turístico uno 8,9/100 menos el turista que sí lo contratar por su parte ser 14,8 millón uno cifra uno 8,6/100 inferior a el de el mismo periodo de el ejercicio anterior el tipo de alojamiento mayoritariamente elegir por el turista internacional recibir en hasta [??:??/11/??:??.??:??] ser el hotelero a el que acudir el 61,2/100 de el visitante 30,2 millón uno 12,8/100 menos por su parte el alojamiento extrahotelero vivienda propio o de familiar vivienda alquilar camping registrar uno retroceso de el 1,7/100 respecto a el mismo periodo de el ejercicio anterior situar se en el 18,8 millón de turista en [??:??/11/??:??.??:??] el turista sin paquete turístico ascender uno 4/100 mientras_que el que lo utilizar se reducir en uno 16,4/100 con respecto a el mismo mes de 2008 el alojamiento hotelero aun ser el preferir caer uno 7/100 mientras_que el no hotelero se incrementar uno 5,5/100 especialmente por el vivienda propio y de familiar o amigo +12,2/100 el llegada por vía aéreo descender uno 3,7/100 y el viaje por carretera se elevar uno 0,4/100 el mes pasar",
        "lemmatized_text_reduced": "españa recibir millón turista extranjero representar caída relación mismo periodo dato encuesta_de_movimientos_turísticos frontera frontur hecho público ministerio_de_industria turismo comercio precisar canarias registrar millón visitante suponer recorte mismo etapa pasar año ministerio señalar consolidar tendencia desaceleración ritmo caída llegada turista venir observar 2 trimestre descenso número visitante ser situar torno 1 mercado emisor visitante seguir ser reino_unido millón turista registrar caída respecto mismo periodo ejercicio anterior 2 lugar situar mercado alemán llegada millón turista 3 lugar situar francia millón turista 1 mes año pasar seguir países_nórdicos italia millón millón turista respectivamente comunidad cataluña ser 1 destino nacional alcanzar millón turista experimentar descenso seguir baleares millón turista canarias andalucía millón visitante millón respectivamente registrar recorte caso comunidad_valenciana contabilizar millón turista comunidad madrid alcanzar millón registrar ascenso representar único comunidad crecer número visitante periodo acumular menos españa recibir millón turista suponer descenso respecto mismo mes año anterior moderación medio punto porcentual caída registrar comunidad visitante recibir ser canarias llegar seguir cataluña visitante andalucía turista madrid turista finalmente comunidad_valenciana visitante baleares turista presentar menor registro mercado reino_unido continuar senda descendente desplome visitante llegada alemán desplomar visitante turista procedente francia total visitante bélgica total elevar respectivamente industria señalar descenso llegada turista reino_unido origen turista internacional visitar españa continuar experimentar tendencia caída general de viajero sin paquete turístico principal vía acceso turista internacional recibir 1 mes año ser aéreo elegir millón visitante total descenso carretera llegar millón turista suponer descenso relación mismo periodo año anterior paralelamente millón turista llegar españa haber contratar paquete turístico turista contratar parte ser millón cifra inferior mismo periodo ejercicio anterior tipo alojamiento mayoritariamente elegir turista internacional recibir ser hotelero acudir visitante millón parte alojamiento extrahotelero vivienda propio familiar vivienda alquilar camping registrar retroceso respecto mismo periodo ejercicio anterior situar millón turista turista paquete turístico ascender utilizar reducir respecto mismo mes alojamiento hotelero ser preferir caer hotelero incrementar especialmente vivienda propio familiar amigo llegada vía aéreo descender viaje carretera elevar mes pasar",
        "persons": [
            "España",
            "Menos",
            "España",
            "España"
        ],
        "locations": [
            "Frontera",
            "Frontur",
            "Canarias",
            "Reino_Unido",
            "Italia",
            "Cataluña",
            "Baleares",
            "Canarias",
            "Madrid",
            "Canarias",
            "Cataluña",
            "Andalucía",
            "Madrid",
            "Comunidad_Valenciana",
            "Baleares",
            "Francia",
            "Bélgica",
            "Reino_Unido",
            "España"
        ],
        "organizations": [
            "Ministerio_de_Industria",
            "Turismo",
            "Comercio",
            "Ministerio",
            "Francia",
            "Países_Nórdicos",
            "Andalucía",
            "Comunidad_Valenciana",
            "Reino_Unido",
            "Industria",
            "Sin"
        ],
        "others": [
            "Encuesta_de_Movimientos_Turísticos",
            "De"
        ],
        "dates": [
            "[??:??/11/??:??.??:??]",
            "[??:??/10/??:??.??:??]",
            "[??:??/9/??:??.??:??]",
            "[??:??/8/??:??.??:??]",
            "[??:??/7/??:??.??:??]",
            "[??:??/1/??:??.??:??]",
            "[??:??/11/??:??.??:??]",
            "[??:??/1/??:??.??:??]",
            "[??:??/11/??:??.??:??]",
            "[??:??/11/??:??.??:??]",
            "[??:??/11/??:??.??:??]",
            "[??:??/10/??:??.??:??]",
            "[??:??/11/??:??.??:??]",
            "[??:??/11/??:??.??:??]",
            "[??:??/11/??:??.??:??]"
        ],
        "numbers": [
            "49,5",
            "8,9",
            "100",
            "2008",
            "7,4",
            "13",
            "100",
            "9,3/100",
            "10/100",
            "12,7",
            "15,6/100",
            "8,5",
            "11,3/100",
            "7,5",
            "2,9/100",
            "11",
            "3,1",
            "-6,6/100",
            "2,9",
            "-6,7/100",
            "12,1",
            "10,7/100",
            "8,9",
            "9,5/100",
            "7,4",
            "6,9",
            "13/100",
            "9,2/100",
            "4,8",
            "10,9/100",
            "4,5",
            "5,9/100",
            "3,1/100",
            "2,8",
            "3,1/100",
            "3,6/100",
            "800000000",
            "-6,8/100",
            "650",
            "-12,9/100",
            "375",
            "+6,9/100",
            "370.5",
            "+15,4/100",
            "248.019",
            "-0,6/100",
            "148.019",
            "-17,6/100",
            "13,3/100",
            "629.194",
            "15,5/100",
            "445.109",
            "389.326",
            "91.063",
            "4,3/100",
            "9,2/100",
            "20/100",
            "69,4/100",
            "11",
            "38,1",
            "77,1/100",
            "9,5/100",
            "9,8",
            "7,1/100",
            "69,4/100",
            "34,3",
            "8,9/100",
            "14,8",
            "8,6/100",
            "61,2/100",
            "30,2",
            "12,8/100",
            "1,7/100",
            "18,8",
            "4/100",
            "16,4/100",
            "2008",
            "7/100",
            "5,5/100",
            "+12,2/100",
            "3,7/100",
            "0,4/100"
        ]
    }
}
