{
    "province": "LAS PALMAS",
    "date": "2010-02-04T00:00:00",
    "url": "https://www.20minutos.es/noticia/622371/0/",
    "title": {
        "raw_text": "El consejero de Turismo de Gran Canaria afirma que hay datos para ser optimista de cara a salir de la crisis",
        "lemmatized_text": "el consejero de turismo_de_gran_canaria afirmar que haber dato para ser optimista de_cara_a salir de el crisis",
        "lemmatized_text_reduced": "consejero turismo_de_gran_canaria afirmar haber dato ser optimista salir crisis",
        "persons": [],
        "locations": [],
        "organizations": [],
        "others": [
            "Turismo_de_Gran_Canaria"
        ],
        "dates": [],
        "numbers": []
    },
    "lead": {
        "raw_text": "El consejero de Turismo del Cabildo de Gran Canaria, Roberto Moreno, ha afirmado hoy que hay datos para ser optimistas en el sector de cara a salir de la crisis este año. \"Hay datos más para el optimismo que para el pesimismo. Yo creo que vamos a ir saliendo, no vamos a ir saliendo de la noche a la mañana\", aseguró en relación con la situación económica actual que atraviesa el turismo.",
        "lemmatized_text": "el consejero de turismo_del_cabildo_de_gran_canaria roberto_moreno haber afirmar hoy que haber dato para ser optimista en el sector de_cara_a salir de el crisis este año haber dato más para el optimismo que para el pesimismo yo creer que ir a ir salir no ir a ir salir de_la_noche_a_la_mañana asegurar en relación con el situación económico actual que atravesar el turismo",
        "lemmatized_text_reduced": "consejero turismo_del_cabildo_de_gran_canaria roberto_moreno haber afirmar haber dato ser optimista sector salir crisis año haber dato optimismo pesimismo creer ir ir salir ir ir salir asegurar relación situación económico actual atravesar turismo",
        "persons": [
            "Roberto_Moreno"
        ],
        "locations": [],
        "organizations": [],
        "others": [
            "Turismo_del_Cabildo_de_Gran_Canaria"
        ],
        "dates": [],
        "numbers": []
    },
    "body": {
        "raw_text": "Moreno que apuntó que el \"grueso\" de la planta alojativa de Gran Canaria son los hoteles de \"gama alta\", incidió en que la isla en diciembre del pasado año mejoró la ocupación hotelera con respecto al mismo mes de 2008. \"En diciembre de 2009, en plena crisis, la ocupación hotelera mejoramos en casi 5 puntos con respecto a diciembre de 2008 y lideramos el país sin ninguna duda. El siguiente fue Tenerife que se mantuvo, no creció; y el siguiente Lanzarote y Fuerteventura. El resto de España viene a mucha distancia\", apuntilló en declaraciones a Europa Press. Asimismo, indicó que la media de Canarias \"se aleja de Gran Canaria\", ya que la isla le saca \"seis puntos\" de ventaja a la media del archipiélago en su conjunto en diciembre de 2009. De todos modos, puntualizó que \"nadie puede esperar\" que en un año donde se han \"tenido descensos muy fuerte, de pronto\" comiencen los \"números en positivo\". Sin embargo, indicó que los meses de noviembre y diciembre del pasado año la bajada de turistas se ha sido \"frenada\". Ante ello, apuntó que posiblemente las cifras de enero de 2010, continúen esa bajada. \"Pero no podemos pasar de un menos 18 por ciento de turistas en septiembre a un, de repente, más 15 por ciento en cuestión de tres meses. En diciembre el descenso fue muy pequeño, en enero será pequeño también, en febrero y marzo nos iremos acercando a niveles normales, posiblemente para verano podamos ver algún incremento\", auguró. También se refirió al incremento de número de plazas aéreas que desde la península y el resto de mercado hacia Canarias prevén programar las aerolíneas de cara al verano y lo que contribuirá en el turismo del archipiélago.",
        "lemmatized_text": "moreno que apuntar que el grueso de el planta alojativa de gran_canaria ser el hotel de gama alto incidir en que el isla en [??:??/12/??:??.??:??] de el pasar año mejorar el ocupación hotelero con respecto a el mismo mes de 2008 en [??:??/12/2009:??.??:??] en pleno crisis el ocupación hotelero mejorar en casi 5 punto con_respecto_a [??:??/12/2008:??.??:??] y liderar el país sin_ninguna_duda el siguiente ser tenerife que se mantener no crecer y el siguiente lanzarote y fuerteventura el resto de españa venir a mucho distancia apuntillar en declaración a europa_press asimismo indicar que el media de canarias se alejar de gran_canaria ya_que el isla le sacar 6 punto de ventaja a el media de el archipiélago en su conjunto en [??:??/12/2009:??.??:??] de_todos_modos puntualizar que nadie poder esperar que en uno año donde se haber tener descenso muy fuerte de pronto comenzar el número en positivo sin embargo indicar que el mes de [??:??/11/??:??.??:??] y [??:??/12/??:??.??:??] de el pasar año el bajada de turista se haber ser frenar ante ello apuntar que posiblemente el cifra de [??:??/1/2010:??.??:??] continuar ese bajada pero no poder pasar de uno menos 18 por 100 de turista en [??:??/9/??:??.??:??] a uno de_repente más 15 por 100 en_cuestión_de 3 mes en [??:??/12/??:??.??:??] el descenso ser muy pequeño en [??:??/1/??:??.??:??] ser pequeño también en [??:??/2/??:??.??:??] y [??:??/3/??:??.??:??] nos ir acercar a nivel normal posiblemente para verano poder ver alguno incremento augurar también se referir a el incremento de número de plaza aéreo que desde el península y el resto de mercado hacia canarias prever programar el aerolínea de cara a el verano y el que contribuir en el turismo de el archipiélago",
        "lemmatized_text_reduced": "moreno apuntar grueso planta alojativa gran_canaria ser hotel gama alto incidir isla pasar año mejorar ocupación hotelero respecto mismo mes pleno crisis ocupación hotelero mejorar punto liderar país siguiente ser tenerife mantener crecer siguiente lanzarote fuerteventura resto españa venir distancia apuntillar declaración europa_press indicar media canarias alejar gran_canaria isla sacar punto ventaja media archipiélago conjunto puntualizar poder esperar año haber tener descenso fuerte comenzar número positivo embargo indicar mes pasar año bajada turista haber ser frenar apuntar posiblemente cifra continuar bajada poder pasar turista mes descenso ser pequeño ser pequeño ir acercar nivel normal posiblemente verano poder ver incremento augurar referir incremento número plaza aéreo península resto mercado canarias prever programar aerolínea cara verano contribuir turismo archipiélago",
        "persons": [
            "España"
        ],
        "locations": [
            "Lanzarote",
            "Canarias",
            "Canarias"
        ],
        "organizations": [
            "Tenerife",
            "Fuerteventura",
            "Europa_Press"
        ],
        "others": [
            "Gran_Canaria",
            "Gran_Canaria"
        ],
        "dates": [
            "[??:??/12/??:??.??:??]",
            "[??:??/12/2009:??.??:??]",
            "[??:??/12/2008:??.??:??]",
            "[??:??/12/2009:??.??:??]",
            "[??:??/11/??:??.??:??]",
            "[??:??/12/??:??.??:??]",
            "[??:??/1/2010:??.??:??]",
            "[??:??/9/??:??.??:??]",
            "[??:??/12/??:??.??:??]",
            "[??:??/1/??:??.??:??]",
            "[??:??/2/??:??.??:??]",
            "[??:??/3/??:??.??:??]"
        ],
        "numbers": [
            "2008",
            "5",
            "6",
            "18",
            "100",
            "15",
            "100",
            "3"
        ]
    }
}
