{
    "province": "LAS PALMAS",
    "date": "2011-01-29T00:00:00",
    "url": "https://www.20minutos.es/noticia/943515/0/",
    "title": {
        "raw_text": "Abierta la inscripción para participar en jurado popular de Festival Internacional de Cine de Las Palmas de Gran Canaria",
        "lemmatized_text": "abrir el inscripción para participar en jurado popular de festival_internacional_de_cine_de_las_palmas_de_gran_canaria",
        "lemmatized_text_reduced": "abrir inscripción participar jurado popular festival_internacional_de_cine_de_las_palmas_de_gran_canaria",
        "persons": [],
        "locations": [],
        "organizations": [],
        "others": [
            "Festival_Internacional_de_Cine_de_Las_Palmas_de_Gran_Canaria"
        ],
        "dates": [],
        "numbers": []
    },
    "lead": {
        "raw_text": "El Festival Internacional de Cine de Las Palmas de Gran Canaria ya ha abierto la inscripción para quienes quieran participar en el jurado popular que otorga el Premio del Público.",
        "lemmatized_text": "el festival_internacional_de_cine_de_las_palmas_de_gran_canaria ya haber abrir el inscripción para quien querer participar en el jurado popular que otorgar el premio_del_público",
        "lemmatized_text_reduced": "festival_internacional_de_cine_de_las_palmas_de_gran_canaria haber abrir inscripción querer participar jurado popular otorgar premio_del_público",
        "persons": [],
        "locations": [],
        "organizations": [
            "Festival_Internacional_de_Cine_de_Las_Palmas_de_Gran_Canaria"
        ],
        "others": [
            "Premio_del_Público"
        ],
        "dates": [],
        "numbers": []
    },
    "body": {
        "raw_text": "El Festival Internacional de Cine de Las Palmas de Gran Canaria ya ha abierto la inscripción para quienes quieran participar en el jurado popular que otorga el Premio del Público. La inscripción podrá realizarse en la sede del certamen (calle León y Castillo, 322, 4º planta) del 27 de enero al 10 de febrero, de lunes a viernes de 9.00 a 14.00 horas, ya que el XII Festival Internacional de Cine de la capital grancanaria se celebrará entre el 1 y 9 de abril, según informó el Ayuntamiento de Las Palmas de Gran Canaria en nota de prensa. El jurado popular deberá estar compuesto por un máximo de 30 personas, que tendrán que otorgar el Premio del Público entre las películas que formen parte de la sección oficial. Este es uno de los galardones \"más valorados\" por los espectadores. Así, quienes quieran formar parte de dicho jurado tendrán que ser mayor de 18 años y una vez seleccionados deberán comprometerse a asistir al pase de todas y cada una de las películas de la sección oficial, para lo que estarán coordinadas por un miembro de la organización del certamen. También tendrán que participar en una reunión informativa previa al inicio del festival y a la reunión de deliberación, en la que todos y cada uno de ellos fallará el Premio del Público. Los miembros seleccionados serán avisados por la organización y, en el caso de que alguno no pudiera asumir el compromiso de asistencia, se avisará al primero de la lista de reserva.",
        "lemmatized_text": "el festival_internacional_de_cine_de_las_palmas_de_gran_canaria ya haber abrir el inscripción para quien querer participar en el jurado popular que otorgar el premio_del_público el inscripción poder realizar se en el sede de el certamen calle león y castillo 322 4º planta de el [??:27/1/??:??.??:??] a el [??:10/2/??:??.??:??] de [L:??/??/??:??.??:??] a [V:??/??/??:??.??:??] de 9 a TM_h:14 ya_que el xii_festival_internacional_de_cine de el capital grancanaria se celebrar entre el 1 y [??:9/4/??:??.??:??] según informar el ayuntamiento_de_las_palmas_de_gran_canaria en nota de prensa el jurado popular deber estar componer por uno máximo de 30 persona que tener que otorgar el premio_del_público entre el película que formar_parte de el sección oficial este ser uno de el galardón más valorar por el espectador así quien querer formar_parte de decir jurado tener que ser mayor de 18 año y uno vez seleccionar deber comprometer se a asistir a el pase de todo y cada uno de el película de el sección oficial para el que estar coordinar por uno miembro de el organización de el certamen también tener que participar en uno reunión informativo previo a el inicio de el festival y a el reunión de deliberación en el que todo y cada uno de ellos fallar el premio_del_público el miembro seleccionar ser avisar por el organización y en el caso de que alguno no poder asumir el compromiso de asistencia se avisar a el primero de el lista de_reserva",
        "lemmatized_text_reduced": "festival_internacional_de_cine_de_las_palmas_de_gran_canaria haber abrir inscripción querer participar jurado popular otorgar premio_del_público inscripción poder realizar sede certamen calle león castillo planta xii_festival_internacional_de_cine capital grancanaria celebrar informar ayuntamiento_de_las_palmas_de_gran_canaria nota prensa jurado popular deber estar componer máximo persona tener otorgar premio_del_público película formar_parte sección oficial ser galardón valorar espectador querer formar_parte decir jurado tener ser mayor año vez seleccionar deber comprometer asistir pase película sección oficial estar coordinar miembro organización certamen tener participar reunión informativo previo inicio festival reunión deliberación fallar premio_del_público miembro seleccionar ser avisar organización caso poder asumir compromiso asistencia avisar lista",
        "persons": [
            "León",
            "Castillo"
        ],
        "locations": [],
        "organizations": [
            "Festival_Internacional_de_Cine_de_Las_Palmas_de_Gran_Canaria",
            "Ayuntamiento_de_Las_Palmas_de_Gran_Canaria"
        ],
        "others": [
            "Premio_del_Público",
            "XII_Festival_Internacional_de_Cine",
            "Premio_del_Público",
            "Premio_del_Público"
        ],
        "dates": [
            "[??:27/1/??:??.??:??]",
            "[??:10/2/??:??.??:??]",
            "[L:??/??/??:??.??:??]",
            "[V:??/??/??:??.??:??]",
            "[??:9/4/??:??.??:??]"
        ],
        "numbers": [
            "322",
            "4º",
            "9",
            "TM_h:14",
            "1",
            "30",
            "18"
        ]
    }
}
