{
    "province": "LAS PALMAS",
    "date": "2010-03-05T00:00:00",
    "url": "https://www.20minutos.es/noticia/644951/0/",
    "title": {
        "raw_text": "Un 96,5% de mujeres no se incorporan al mercado laboral en Las Palmas de Gran Canaria por motivos familiares",
        "lemmatized_text": "uno 96,5/100 de mujer no se incorporar a el mercado laboral en las_palmas_de_gran_canaria por motivo familiar",
        "lemmatized_text_reduced": "mujer incorporar mercado laboral las_palmas_de_gran_canaria motivo familiar",
        "persons": [],
        "locations": [
            "Las_Palmas_de_Gran_Canaria"
        ],
        "organizations": [],
        "others": [],
        "dates": [],
        "numbers": [
            "96,5/100"
        ]
    },
    "lead": {
        "raw_text": "Juzgado de Violencia de Género dictó 799 órdenes de protección en la capital en 2009",
        "lemmatized_text": "juzgado_de_violencia_de_género dictar 799 orden de protección en el capital en 2009",
        "lemmatized_text_reduced": "juzgado_de_violencia_de_género dictar orden protección capital",
        "persons": [],
        "locations": [],
        "organizations": [
            "Juzgado_de_Violencia_de_Género"
        ],
        "others": [],
        "dates": [],
        "numbers": [
            "799",
            "2009"
        ]
    },
    "body": {
        "raw_text": "El 96,5 por ciento de las personas que manifiestan no incorporarse al mercado laboral en Las Palmas de Gran Canaria por motivos familiares son mujeres. Ellas, las trabajadoras, son las que solicitan el 95,3 por ciento de las excedencias para cuidar a los hijos, según informó hoy en rueda de prensa la concejala de Juventud e Igualdad, Isabel Mena, en la presentación del Programa de Acceso al Empleo. \"Es un hecho que las mujeres no hemos tenido cabida en el sector en auge en Canarias durante las últimas décadas, la construcción\", explica la responsable del área, para quien \"eso explica que, por ejemplo, las mujeres reciban más del 86 por ciento de las ayudas básicas, sobre todo en la franja de edad de ser madre\". Otro dato que llama a la reflexión es el nivel formativo. El municipio de Las Palmas de Gran Canaria tiene 10.345 estudiantes universitarios. De los que cursan una diplomatura, 3.877 son mujeres y 2.702 son hombres. De los que estudian una licenciatura, 2.897 son mujeres y 2.205 son hombres. \"clara desventaja\" Mena informó de que en la capital hay censadas 193.144 mujeres. Sin embargo, su capacidad de desarrollo laboral está en \"clara desventaja\" frente a los hombres, ya que los oficios con crecimiento en las últimas décadas en Canarias han sido ocupados mayoritariamente por trabajadores y no por trabajadoras. Esta discriminación formativa por razón de sexo es una de las barreras que combate el Programa de Acceso al Empleo de la Concejalía de Igualdad. Los ejemplos estadísticos de las profesiones masculinizadas y feminizadas abundan. Ellas tienen presencia destacada en sectores como el de los telefonistas (86'96 por ciento), taquilleros (84,68 por ciento), auxiliares de enfermería (86,15 por ciento), asistentes domiciliarios (92,73 por ciento), empleados para el cuidado de niños (100 por ciento), dependientes (82,8 por ciento) y empleados de hogar (87,24 por ciento). En el otro extremo de la balanza están las profesiones masculinizadas. Las mujeres ocupan de forma residual puestos como técnicos en electrónica y mecánica (1,69 por ciento), oficiales maquinistas (0 por ciento), encargados de obra (2,63 por ciento), albañiles, encofradores y escayolistas (1,16 por ciento), fontaneros, electricistas, pintores y soldadores (1,02 por ciento) y conductores de guaguas y camiones (3,83 por ciento), indica el Consistorio en un comunicado. A la vista de estos datos (extraídos del II Plan de Igualdad municipal), el área de Igualdad del Ayuntamiento de Las Palmas de Gran Canaria inició en 2009 un Programa de Acceso al Empleo para intentar corregir la discriminación de las mujeres debido a que su formación laboral no se amplía a otras profesiones. La Concejalía de Juventud e Igualdad del Ayuntamiento de Las Palmas de Gran Canaria tiene dos grandes áreas de trabajo: el Programa de Acceso al Empleo y la Atención Integral a Víctimas de Violencia de Género. En el último año, estos dos servicios de Igualdad han asesorado a más de 2.500 personas (la gran mayoría mujeres, aunque también es destacable el trabajado de concienciación realizado con alumnos de Secundaria). Un total de 799 órdenes de protección El Juzgado de Violencia de Género dictó el pasado año un total de 799 órdenes de protección a mujeres víctimas con residencia en Las Palmas de Gran Canaria, de las que 496 utilizaron los servicios de las distintas asesorías de Igualdad (Jurídica, Social, Psicológica y Laboral). De las 197 mujeres atendidas en la Asesoría Laboral, 82 eran víctimas de violencia de género y 108 mujeres de difícil inserción en el mercado de trabajo, Al final del proceso, 85 mujeres accedieron a cursos de formación gracias a convenios entre el Ayuntamiento y Hecansa, Radio Ecca y Cemain, así como de la línea de colaboración con el Imef. Y 56 mujeres accedieron a planes de empleo: 31 a los PIEC del Imef y 24 a los PIEC del Cabildo. Por otra parte, 464 mujeres fueron atendidas por el Servicio de Información, Orientación y Valoración (SIOV) de la Concejalía de Igualdad por diversos motivos. Además, 469 mujeres fueron atendidas en la Asesoría Jurídica. Día de la mujer Los actos organizados por el Ayuntamiento con motivo del Día de la Mujer (lunes 8 de marzo) se centran en una campaña de sensibilización que llevará un 'cuenta cuentos' didáctico sobre la situación de la mujer. Este montaje se llevará a distintos puntos de nuestra ciudad. Asimismo, ese día se pondrá en marcha la campaña 'Gestos por la igualdad' que consistirá en fotografiar a todos los ciudadanos y ciudadanas que lo deseen para la creación y publicación de un mural en apoyo a la igualdad de género. Se realizará una encuesta que permitirá a la Concejalía de Igualdad elaborar un perfil de la concienciación ciudadana sobre la igualdad.",
        "lemmatized_text": "el 96,5 por 100 de el persona que manifestar no incorporar se a el mercado laboral en las_palmas_de_gran_canaria por motivo familiar ser mujer ellos el trabajador ser el que solicitar el 95,3 por 100 de el excedencia para cuidar a el hijo según informar hoy en rueda de prensa el concejal de juventud y igualdad isabel_mena en el presentación de el programa_de_acceso a el empleo ser uno hecho que el mujer no haber tener cabida en el sector en auge en canarias durante el último década el construcción explicar el responsable de el área para quien ese explicar que por_ejemplo el mujer recibir más de el 86 por 100 de el ayuda básico sobre todo en el franja de edad de ser madre otro dato que llamar a el reflexión ser el nivel formativo el municipio de las_palmas_de_gran_canaria tener 10.345 estudiante universitario de el que cursar uno diplomatura 3.877 ser mujer y 2.702 ser hombre de el que estudiar uno licenciatura 2.897 ser mujer y 2.205 ser hombre claro desventaja mena informar de que en el capital haber censar 193.144 mujer sin embargo su capacidad de desarrollo laboral estar en claro desventaja frente_a el hombre ya_que el oficio con crecimiento en el último década en canarias haber ser ocupar mayoritariamente por trabajador y no por trabajador este discriminación formativo por_razón_de sexo ser uno de el barrera que combatir el programa_de_acceso a el empleo_de_la_concejalía_de_igualdad el ejemplo estadístico de el profesión masculinizadas y feminizadas abundar ellos tener presencia destacar en sector como el de el telefonista 86 96 por 100 taquillero 84,68 por 100 auxiliar de enfermería 86,15 por 100 asistente domiciliario 92,73 por 100 empleado para el cuidado de niño 100 por 100 dependiente 82,8 por 100 y empleado de hogar 87,24 por 100 en el otro extremo de el balanza estar el profesión masculinizadas el mujer ocupar de forma residual puesto como técnico en electrónico y mecánico 1,69 por 100 oficial maquinista 0 por 100 encargar de obra 2,63 por 100 albañil encofradores y escayolista 1,16 por 100 fontanero electricista pintor y soldador 1,02 por 100 y conductor de guagua y camión 3,83 por 100 indicar el consistorio en uno comunicado a el vista de este dato extraer de el ii_plan_de_igualdad municipal el área de igualdad_del_ayuntamiento_de_las_palmas_de_gran_canaria iniciar en 2009 uno programa_de_acceso a el empleo para intentar corregir el discriminación de el mujer debido_a que su formación laboral no se ampliar a otro profesión el concejalía_de_juventud y igualdad_del_ayuntamiento_de_las_palmas_de_gran_canaria tener 2 grande área de trabajo el programa_de_acceso a el empleo y el atención_integral a víctimas_de_violencia_de_género en el último año este 2 servicio de igualdad haber asesorar a más de 2.5 persona el gran mayoría mujer aunque también ser destacable el trabajar de concienciación realizar con alumno de secundaria uno total de 799 orden de protección el_juzgado_de_violencia_de_género dictar el pasar año uno total de 799 orden de protección a mujer víctima con residencia en las_palmas_de_gran_canaria de el que 496 utilizar el servicio de el distinto asesoría de igualdad jurídica social psicológica y laboral de el 197 mujer atender en el asesoría_laboral 82 ser víctima de violencia de género y 108 mujer de difícil inserción en el mercado de trabajo al final de el proceso 85 mujer acceder a curso de formación gracias_a convenio entre el ayuntamiento y hecansa radio_ecca y cemain así_como de el línea de colaboración con el imef y 56 mujer acceder a plan de empleo 31 a el piec_del_imef y 24 a el piec_del_cabildo por otro parte 464 mujer ser atender por el servicio_de_información orientación y valoración siov de el concejalía_de_igualdad por diverso motivo además 469 mujer ser atender en el asesoría_jurídica día de el mujer los acto organizar por el ayuntamiento con motivo de el día_de_la_mujer [L:8/3/??:??.??:??] se centrar en uno campaña de sensibilización que llevar uno contar cuento didáctico sobre el situación de el mujer este montaje se llevar a distinto punto de nuestro ciudad asimismo ese día se poner en marcha el campaña gesto por el igualdad que consistir en fotografiar a todo el ciudadano y ciudadano que lo desear para el creación y publicación de uno mural en apoyo a el igualdad de género se realizar uno encuesta que permitir a el concejalía_de_igualdad elaborar uno perfil de el concienciación ciudadano sobre el igualdad",
        "lemmatized_text_reduced": "persona manifestar incorporar mercado laboral las_palmas_de_gran_canaria motivo familiar ser mujer trabajador ser solicitar excedencia cuidar hijo informar rueda prensa concejal juventud igualdad isabel_mena presentación programa_de_acceso empleo ser hecho mujer haber tener cabida sector auge canarias último década construcción explicar responsable área explicar mujer recibir ayuda básico franja edad ser madre dato llamar reflexión ser nivel formativo municipio las_palmas_de_gran_canaria tener estudiante universitario cursar diplomatura ser mujer ser hombre estudiar licenciatura ser mujer ser hombre claro desventaja mena informar capital haber censar mujer embargo capacidad desarrollo laboral estar claro desventaja hombre oficio crecimiento último década canarias haber ser ocupar mayoritariamente trabajador trabajador discriminación formativo sexo ser barrera combatir programa_de_acceso empleo_de_la_concejalía_de_igualdad ejemplo estadístico profesión masculinizadas feminizadas abundar tener presencia destacar sector telefonista taquillero auxiliar enfermería asistente domiciliario empleado cuidado niño dependiente empleado hogar extremo balanza estar profesión masculinizadas mujer ocupar forma residual puesto técnico electrónico mecánico oficial maquinista encargar obra albañil encofradores escayolista fontanero electricista pintor soldador conductor guagua camión indicar consistorio comunicado vista dato extraer ii_plan_de_igualdad municipal área igualdad_del_ayuntamiento_de_las_palmas_de_gran_canaria iniciar programa_de_acceso empleo intentar corregir discriminación mujer formación laboral ampliar profesión concejalía_de_juventud igualdad_del_ayuntamiento_de_las_palmas_de_gran_canaria tener grande área trabajo programa_de_acceso empleo atención_integral víctimas_de_violencia_de_género último año servicio igualdad haber asesorar persona gran mayoría mujer ser destacable trabajar concienciación realizar alumno secundaria total orden protección el_juzgado_de_violencia_de_género dictar pasar año total orden protección mujer víctima residencia las_palmas_de_gran_canaria utilizar servicio distinto asesoría igualdad jurídica social psicológica laboral mujer atender asesoría_laboral ser víctima violencia género mujer difícil inserción mercado trabajo al final proceso mujer acceder curso formación convenio ayuntamiento hecansa radio_ecca cemain línea colaboración imef mujer acceder plan empleo piec_del_imef piec_del_cabildo parte mujer ser atender servicio_de_información orientación valoración siov concejalía_de_igualdad motivo mujer ser atender asesoría_jurídica día mujer los acto organizar ayuntamiento motivo día_de_la_mujer centrar campaña sensibilización llevar contar cuento didáctico situación mujer montaje llevar punto ciudad día poner marcha campaña gesto igualdad consistir fotografiar ciudadano ciudadano desear creación publicación mural apoyo igualdad género realizar encuesta permitir concejalía_de_igualdad elaborar perfil concienciación ciudadano igualdad",
        "persons": [
            "Isabel_Mena",
            "Mena",
            "Víctimas_de_Violencia_de_Género",
            "Igualdad",
            "Al",
            "PIEC_del_Cabildo",
            "Orientación",
            "Valoración",
            "Día"
        ],
        "locations": [
            "Las_Palmas_de_Gran_Canaria",
            "Canarias",
            "Las_Palmas_de_Gran_Canaria",
            "Canarias",
            "Igualdad_del_Ayuntamiento_de_Las_Palmas_de_Gran_Canaria",
            "Las_Palmas_de_Gran_Canaria",
            "Jurídica",
            "Psicológica",
            "Cemain",
            "Asesoría_Jurídica"
        ],
        "organizations": [
            "Empleo",
            "Empleo_de_la_Concejalía_de_Igualdad",
            "Consistorio",
            "Empleo",
            "Concejalía_de_Juventud",
            "Igualdad_del_Ayuntamiento_de_Las_Palmas_de_Gran_Canaria",
            "Empleo",
            "Atención_Integral",
            "El_Juzgado_de_Violencia_de_Género",
            "Social",
            "Laboral",
            "Ayuntamiento",
            "Hecansa",
            "Radio_Ecca",
            "Imef",
            "Servicio_de_Información",
            "SIOV",
            "Ayuntamiento",
            "Concejalía_de_Igualdad"
        ],
        "others": [
            "Juventud",
            "Igualdad",
            "Programa_de_Acceso",
            "Programa_de_Acceso",
            "II_Plan_de_Igualdad",
            "Programa_de_Acceso",
            "Programa_de_Acceso",
            "Igualdad",
            "Secundaria",
            "Asesoría_Laboral",
            "PIEC_del_Imef",
            "Concejalía_de_Igualdad",
            "Los",
            "Día_de_la_Mujer"
        ],
        "dates": [
            "[L:8/3/??:??.??:??]"
        ],
        "numbers": [
            "96,5",
            "100",
            "95,3",
            "100",
            "86",
            "100",
            "10.345",
            "3.877",
            "2.702",
            "2.897",
            "2.205",
            "193.144",
            "86",
            "96",
            "100",
            "84,68",
            "100",
            "86,15",
            "100",
            "92,73",
            "100",
            "100",
            "100",
            "82,8",
            "100",
            "87,24",
            "100",
            "1,69",
            "100",
            "0",
            "100",
            "2,63",
            "100",
            "1,16",
            "100",
            "1,02",
            "100",
            "3,83",
            "100",
            "2009",
            "2",
            "2",
            "2.5",
            "799",
            "799",
            "496",
            "197",
            "82",
            "108",
            "85",
            "56",
            "31",
            "24",
            "464",
            "469"
        ]
    }
}
