{
    "province": "LAS PALMAS",
    "date": "2010-02-19T00:00:00",
    "url": "https://www.20minutos.es/noticia/633520/0/",
    "title": {
        "raw_text": "Abiertos los accesos a Arteara y La Culata al sur de Gran Canaria pero sigue cerrada la vía a Ayacata",
        "lemmatized_text": "abrir el acceso a arteara y la_culata a el sur de gran_canaria pero seguir cerrar el vía a ayacata",
        "lemmatized_text_reduced": "abrir acceso arteara la_culata sur gran_canaria seguir cerrar vía ayacata",
        "persons": [
            "Ayacata"
        ],
        "locations": [
            "Arteara",
            "Gran_Canaria"
        ],
        "organizations": [
            "La_Culata"
        ],
        "others": [],
        "dates": [],
        "numbers": []
    },
    "lead": {
        "raw_text": "Aumenta el peligro por desprendimientos en la vía desde Cercados de Espino a Soria, en la carretera general al sur, de Tejeda a Maspalomas y en la carretera de Los Cuchillos",
        "lemmatized_text": "aumentar el peligro por desprendimiento en el vía desde cercados_de_espino a soria en el carretera general a el sur de tejeda a maspalomas y en el carretera de los_cuchillos",
        "lemmatized_text_reduced": "aumentar peligro desprendimiento vía cercados_de_espino soria carretera general sur tejeda maspalomas carretera los_cuchillos",
        "persons": [],
        "locations": [
            "Cercados_de_Espino",
            "Soria",
            "Tejeda",
            "Maspalomas",
            "Los_Cuchillos"
        ],
        "organizations": [],
        "others": [],
        "dates": [],
        "numbers": []
    },
    "body": {
        "raw_text": "La alcaldesa de San Bartolomé de Tirajana, María del Pino Torres, acompañada por varios concejales de la Corporación, visitaron algunas de las zonas más afectadas por el último temporal de lluvia y viento, que ha ocasionado graves destrozos en algunas carreteras de las medianías y cumbres del municipio. Durante la jornada de hoy, operarios de la Concejalía de Vías y Obras procedían a abrir los accesos a Arteara, La Culata y el Puente de la Barca, según informó el Consistorio en un comunicado. Sin embargo, siguen cerradas las entradas a los barrios de La Montaña, Casas Blancas, y en la carretera GC-60 el barro y las rocas siguen obligando a los conductores a dar la vuelta a la altura del cruce entre Chira y Ayacata, ya que la circulación es imposible allí. Riadas de agua y barro La institución local señala que la tarde de ayer fue especialmente difícil para los vecinos de los barrios de la zona alta del municipio, debido a las fuertes lluvias que se registraron y que produjeron auténticas riadas de agua y barro. El agua arrastró por el barranquillo de la Huerta gran cantidad de tierra de las obras del nuevo parque de Tunte. Al llegar al merendero del Algarrobero, a la entrada del Casco de la Villa, esta cantidad de residuos obstruyeron el ojo de buey, con lo que la riada saltó por encima del puente y la carretera. La rápida actuación de los operarios de Vías y Obras, levantando un montículo de arena cruzando la vía, hizo que se desviara el caudal hacia el barranquillo, evitando que el agua y el barro llegaran a las viviendas y a la Iglesia. El cabildo ruega máxima precaución en las carreteras Por su parte, desde la Consejería de Desarrollo Económico, Obras Públicas e Infraestructuras y Transportes del Cabildo de Gran Canaria se ruega a los ciudadanos que vayan a desplazarse este fin de semana por la red de carreteras insular que extremen la precaución especialmente en las vías de la zona Sur. Las siguientes vías han sufrido una reducción de la calzada: GC-65 (carretera de los Cuchillos) en el punto kilométrico (pk) 0+500; la GC-504 (carretera de Ayagaures) entre el pk 1+000 y el 7+000; la GC-500 (carretera general al Sur) en el pk 25+900 y entre el 41+500 y el 45+500; la GC-505 (carretera a Soria desde Cercados de Espino) en el pk 16+900 y la GC-60 (de Tejeda a Maspalomas) en el pk 31+500. Asimismo, la institución insular informa a los ciudadanos de que se ha incrementado el peligro por desprendimientos en las carreteras GC-505 (desde Cercados de Espino a Soria) entre los ppkk 14+000 y 19+000; la GC-500 ( carretera general al Sur) entre el 41+500 y el 45+600; la GC-60 (Tejeda-Maspalomas) desde el pk 25+500 al 39+000; y la GC-65 (carretera de Los Cuchillos) entre los ppkk 3+500 y 6+000.",
        "lemmatized_text": "el alcaldesa de san_bartolomé_de_tirajana maría_del_pino_torres acompañar por varios concejal de el corporación visitar alguno de el zona más afectar por el último temporal de lluvia y viento que haber ocasionar grave destrozo en alguno carretera de el medianía y cumbre de el municipio durante el jornada de hoy operario de el concejalía_de_vías y obras proceder a abrir el acceso a arteara la_culata y el puente_de_la_barca según informar el consistorio en uno comunicado sin embargo seguir cerrar el entrada a el barrio de la_montaña casas_blancas y en el carretera GC-60 el barro y el roca seguir obligar a el conductor a dar el vuelta a el altura de el cruce entre chira y ayacata ya_que el circulación ser imposible allí riada de agua y barro la institución local señalar que el tarde de ayer ser especialmente difícil para el vecino de el barrio de el zona alto de el municipio debido_a el fuerte lluvia que se registrar y que producir auténtico riada de agua y barro el agua arrastrar por el barranco de el huerta gran cantidad de tierra de el obra de el nuevo parque de tunte a el llegar a el merendero de el algarrobero a el entrada de el casco_de_la_villa este cantidad de residuo obstruir el ojo de buey con el que el riada saltar por encima de el puente y el carretera el rápido actuación de el operario de vías y obras levantar uno montículo de arena cruzar el vía hacer que se desviar el caudal hacia el barranco evitar que el agua y el barro llegar a el vivienda y a el iglesia el cabildo rogar máximo precaución en el carretera por su parte desde el consejería_de_desarrollo_económico obras_públicas y infraestructuras y transportes_del_cabildo_de_gran_canaria se rogar a el ciudadano que ir a desplazar se este fin de semana por el red de carretera insular que extremar el precaución especialmente en el vía de el zona sur el siguiente vía haber sufrir uno reducción de el calzada GC-65 carretera de el cuchillos en el punto kilométrico pk 0+500 el GC-504 carretera de ayagaures entre el pk 1+000 y el 7+000 el GC-500 carretera general a el sur en el pk 25+900 y entre el 41+500 y el 45+500 el GC-505 carretera a soria desde cercados_de_espino en el pk 16+900 y el GC-60 de tejeda a maspalomas en el pk 31+500 asimismo el institución insular informar a el ciudadano de que se haber incrementar el peligro por desprendimiento en el carretera GC-505 desde cercados_de_espino a soria entre el ppkk 14+000 y 19+000 el GC-500 carretera general a el sur entre el 41+500 y el 45+600 el GC-60 tejeda-maspalomas desde el pk 25+500 a el 39+000 y el GC-65 carretera de los_cuchillos entre el ppkk 3+500 y 6+000",
        "lemmatized_text_reduced": "alcaldesa san_bartolomé_de_tirajana maría_del_pino_torres acompañar concejal corporación visitar zona afectar último temporal lluvia viento haber ocasionar grave destrozo carretera medianía cumbre municipio jornada operario concejalía_de_vías obras proceder abrir acceso arteara la_culata puente_de_la_barca informar consistorio comunicado embargo seguir cerrar entrada barrio la_montaña casas_blancas carretera barro roca seguir obligar conductor dar vuelta altura cruce chira ayacata circulación ser imposible riada agua barro la institución local señalar tarde ser especialmente difícil vecino barrio zona alto municipio fuerte lluvia registrar producir auténtico riada agua barro agua arrastrar barranco huerta gran cantidad tierra obra nuevo parque tunte llegar merendero algarrobero entrada casco_de_la_villa cantidad residuo obstruir ojo buey riada saltar puente carretera rápido actuación operario vías obras levantar montículo arena cruzar vía hacer desviar caudal barranco evitar agua barro llegar vivienda iglesia cabildo rogar máximo precaución carretera por parte consejería_de_desarrollo_económico obras_públicas infraestructuras transportes_del_cabildo_de_gran_canaria rogar ciudadano ir desplazar fin semana red carretera insular extremar precaución especialmente vía zona sur siguiente vía haber sufrir reducción calzada carretera cuchillos punto kilométrico pk carretera ayagaures pk carretera general sur pk carretera soria cercados_de_espino pk tejeda maspalomas pk institución insular informar ciudadano haber incrementar peligro desprendimiento carretera cercados_de_espino soria ppkk carretera general sur tejeda-maspalomas pk carretera los_cuchillos ppkk",
        "persons": [
            "María_del_Pino_Torres",
            "Casas_Blancas",
            "Ayacata",
            "La"
        ],
        "locations": [
            "San_Bartolomé_de_Tirajana",
            "La_Culata",
            "La_Montaña",
            "Tunte",
            "Casco_de_la_Villa",
            "Vías",
            "Por",
            "Cuchillos",
            "Ayagaures",
            "Soria",
            "Cercados_de_Espino",
            "Tejeda",
            "Maspalomas",
            "Cercados_de_Espino",
            "Soria",
            "Los_Cuchillos"
        ],
        "organizations": [
            "Corporación",
            "Concejalía_de_Vías",
            "Arteara",
            "Puente_de_la_Barca",
            "Consistorio",
            "Chira",
            "Huerta",
            "Algarrobero",
            "Iglesia",
            "Consejería_de_Desarrollo_Económico",
            "Obras_Públicas",
            "Transportes_del_Cabildo_de_Gran_Canaria",
            "Sur",
            "Sur",
            "Sur",
            "Tejeda-Maspalomas"
        ],
        "others": [
            "Obras",
            "Obras",
            "Infraestructuras"
        ],
        "dates": [],
        "numbers": [
            "GC-60",
            "GC-65",
            "0+500",
            "GC-504",
            "1+000",
            "7+000",
            "GC-500",
            "25+900",
            "41+500",
            "45+500",
            "GC-505",
            "16+900",
            "GC-60",
            "31+500",
            "GC-505",
            "14+000",
            "19+000",
            "GC-500",
            "41+500",
            "45+600",
            "GC-60",
            "25+500",
            "39+000",
            "GC-65",
            "3+500",
            "6+000"
        ]
    }
}
