{
    "province": "LAS PALMAS",
    "date": "2010-05-10T00:00:00",
    "url": "https://www.20minutos.es/noticia/702421/0/",
    "title": {
        "raw_text": "Lanzarote registra en abril menor ocupación turística por las cenizas volcánicas",
        "lemmatized_text": "lanzarote registrar en [??:??/4/??:??.??:??] menor ocupación turístico por el ceniza volcánico",
        "lemmatized_text_reduced": "lanzarote registrar menor ocupación turístico ceniza volcánico",
        "persons": [],
        "locations": [
            "Lanzarote"
        ],
        "organizations": [],
        "others": [],
        "dates": [
            "[??:??/4/??:??.??:??]"
        ],
        "numbers": []
    },
    "lead": {
        "raw_text": "La Asociación de Empresarios de Hoteles y Apartamentos de Lanzarote (Asolan) informó hoy de que el cierre de los aeropuertos del Reino Unido e Irlanda por las cenizas volcánicas ha provocado que abril sea el mes con menor ocupación turística en la isla durante el cuatrimestre del 2010.",
        "lemmatized_text": "el asociación_de_empresarios_de_hoteles y apartamentos_de_lanzarote asolar informar hoy de que el cierre de el aeropuerto de el reino_unido y irlanda por el ceniza volcánico haber provocar que [??:??/4/??:??.??:??] ser el mes con menor ocupación turístico en el isla durante el cuatrimestre de el 2010",
        "lemmatized_text_reduced": "asociación_de_empresarios_de_hoteles apartamentos_de_lanzarote asolar informar cierre aeropuerto reino_unido irlanda ceniza volcánico haber provocar ser mes menor ocupación turístico isla cuatrimestre",
        "persons": [],
        "locations": [
            "Reino_Unido",
            "Irlanda"
        ],
        "organizations": [
            "Asociación_de_Empresarios_de_Hoteles",
            "Apartamentos_de_Lanzarote"
        ],
        "others": [],
        "dates": [
            "[??:??/4/??:??.??:??]"
        ],
        "numbers": [
            "2010"
        ]
    },
    "body": {
        "raw_text": "La patronal recuerda en un comunicado que ambos aeródromos, de los principales países emisores de turismo, registraron a finales del pasado mes de abril una situación de bloqueo y cierre por la presencia de cenizas volcánicas en ese espacio aéreo que provocaron las cancelaciones de vuelos hacia Lanzarote, entre otros lugares. \"Esta circunstancia ha originando que el mes de abril, por ahora, arroje los índices más bajos del año 2010 tras unos meses donde la afluencia de turistas hacia la isla de los volcanes aportaba datos de recuperación y optimismo\", añade. Ocupación media del 62,52% Los establecimientos alojativos en la isla de Lanzarote han registrado una ocupación media del 62,52 por ciento durante el pasado mes de abril. El estudio que mensualmente elabora Asolan, la patronal turística de Lanzarote, presidida por Susana Pérez, refleja que por segmentos los aparhoteles registraron en abril el mejor porcentaje, con una media del 73,41. Seguidos de los hoteles de 4 estrellas, con un 63,46. Por su parte, los aparhoteles lograron un 59,72 y los hoteles de 5 estrellas una media del 55,88 por el valor añadido de la Semana Santa. Y los bungalows, el menor porcentaje, con un 51,80. En abril del pasado año 2009 la media fue del 61,25 por ciento. En enero de este 2010 el ratio ascendió al 65,11; en febrero, 70,35: en Marzo, 75,36, convirtiéndose en el mejor mes del presente cuatrimestre.",
        "lemmatized_text": "el patronal recordar en uno comunicado que ambos aeródromo de el principal país emisor de turismo registrar a final de el [??:??/4/??:??.??:??] uno situación de bloqueo y cierre por el presencia de ceniza volcánico en ese espacio aéreo que provocar el cancelación de vuelo hacia lanzarote entre otro lugar este circunstancia haber originar que el [??:??/4/??:??.??:??] por ahora arrojar el índice más bajo de el [??:??/??/2010:??.??:??] tras uno mes donde el afluencia de turista hacia el isla de el volcán aportar dato de recuperación y optimismo añadir ocupación medio de el 62,52/100 los establecimiento alojativos en el isla de lanzarote haber registrar uno ocupación medio de el 62,52 por 100 durante el [??:??/4/??:??.??:??] el estudio que mensualmente elaborar asolan el patronal turístico de lanzarote presidir por susana_pérez reflejar que por segmento el aparhoteles registrar en [??:??/4/??:??.??:??] el mejor porcentaje con uno medio de el 73,41 seguir de el hotel de 4 estrella con uno 63,46 por su parte el aparhoteles lograr uno 59,72 y el hotel de 5 estrella uno medio de el 55,88 por el valor añadir de el semana_santa y el bungalow el menor porcentaje con uno 51,80 en [??:??/4/2009:??.??:??] el medio ser de el 61,25 por 100 en [??:??/1/??:??.??:??] de este 2010 el ratio ascender a el 65,11 en [??:??/2/??:??.??:??] 70,35 en [??:??/3/??:??.??:??] 75,36 convertir se en el mejor mes de el presente cuatrimestre",
        "lemmatized_text_reduced": "patronal recordar comunicado aeródromo principal país emisor turismo registrar final situación bloqueo cierre presencia ceniza volcánico espacio aéreo provocar cancelación vuelo lanzarote lugar circunstancia haber originar arrojar índice bajo mes afluencia turista isla volcán aportar dato recuperación optimismo añadir ocupación medio los establecimiento alojativos isla lanzarote haber registrar ocupación medio estudio mensualmente elaborar asolan patronal turístico lanzarote presidir susana_pérez reflejar segmento aparhoteles registrar mejor porcentaje medio seguir hotel estrella parte aparhoteles lograr hotel estrella medio valor añadir semana_santa bungalow menor porcentaje medio ser ratio ascender convertir mejor mes presente cuatrimestre",
        "persons": [
            "Asolan",
            "Susana_Pérez"
        ],
        "locations": [
            "Lanzarote",
            "Lanzarote",
            "Lanzarote"
        ],
        "organizations": [
            "Semana_Santa"
        ],
        "others": [
            "Los"
        ],
        "dates": [
            "[??:??/4/??:??.??:??]",
            "[??:??/4/??:??.??:??]",
            "[??:??/??/2010:??.??:??]",
            "[??:??/4/??:??.??:??]",
            "[??:??/4/??:??.??:??]",
            "[??:??/4/2009:??.??:??]",
            "[??:??/1/??:??.??:??]",
            "[??:??/2/??:??.??:??]",
            "[??:??/3/??:??.??:??]"
        ],
        "numbers": [
            "62,52/100",
            "62,52",
            "100",
            "73,41",
            "4",
            "63,46",
            "59,72",
            "5",
            "55,88",
            "51,80",
            "61,25",
            "100",
            "2010",
            "65,11",
            "70,35",
            "75,36"
        ]
    }
}
