{
    "province": "LAS PALMAS",
    "date": "2011-01-13T00:00:00",
    "url": "https://www.20minutos.es/noticia/927329/0/",
    "title": {
        "raw_text": "El derbi entre C.D. Tenerife y U.D. Las Palmas se declarará de interés general para emitirlo en directo",
        "lemmatized_text": "el derbi entre c.d._tenerife y u.d._las_palmas se declarar de interés general para emitir lo en directo",
        "lemmatized_text_reduced": "derbi c.d._tenerife u.d._las_palmas declarar interés general emitir directo",
        "persons": [
            "C.D._Tenerife"
        ],
        "locations": [],
        "organizations": [
            "U.D._Las_Palmas"
        ],
        "others": [],
        "dates": [],
        "numbers": []
    },
    "lead": {
        "raw_text": "La consejera de Educación, Cultura, Deporte y Universidades del Gobierno de Canarias, Milagros Luis Brito, firmará una orden para declarar de interés general el derbi que enfrentará al C.D Tenerife y a la U.D. Las Palmas.",
        "lemmatized_text": "el consejero de educación cultura deporte y universidades_del_gobierno_de_canarias milagros_luis_brito firmar uno orden para declarar de interés general el derbi que enfrentar a el c._d_tenerife y a el u.d._las_palmas",
        "lemmatized_text_reduced": "consejero educación cultura deporte universidades_del_gobierno_de_canarias milagros_luis_brito firmar orden declarar interés general derbi enfrentar c._d_tenerife u.d._las_palmas",
        "persons": [
            "Milagros_Luis_Brito"
        ],
        "locations": [],
        "organizations": [
            "Universidades_del_Gobierno_de_Canarias",
            "C._D_Tenerife",
            "U.D._Las_Palmas"
        ],
        "others": [
            "Educación",
            "Cultura",
            "Deporte"
        ],
        "dates": [],
        "numbers": []
    },
    "body": {
        "raw_text": "La consejera de Educación, Cultura, Deporte y Universidades del Gobierno de Canarias, Milagros Luis Brito, firmará una orden para declarar de interés general el derbi que enfrentará al C.D Tenerife y a la U.D. Las Palmas. El portavoz del Ejecutivo canario, Martín Marrero, así lo ha anunciado en la rueda de prensa posterior al Consejo de Gobierno. Marrero explicó que se ha tomado esta decisión con el objetivo de que se pueda emitir \"en directo y en abierto\" en toda Canarias. Asimismo, recordó que este mismo hecho se produjo en la temporada 2008-2009. Además, recordó que esta orden \"tiene pleno respaldo jurídico y legal\" a través del Decreto 219 de 11 de Noviembre de 2008, por el que se atribuye a la Consejería del área la competencia para determinar los acontecimientos deportivos que se consideran de interés general. El pabellón de gran canaria a la espera del cabildo Por otro lado, cuestionado por la concreción del convenio para llevar a cabo el pabellón del Mundial de Baloncesto de 2014 en Gran Canaria, Marrero aseguró que \"se ha completado desde hace días el expediente para suscribir el convenio que de luz verde al pabellón\". En este sentido, afirmó que \"están a la espera de que el Cabildo —de Gran Canaria— convoque la firma\" del acuerdo. De todos modos, ha subrayado que Luis Brito se ha dirigido \"reiteradamente al Cabildo para apremiarle a la firma del convenio y la respuesta que ha obtenido es que ha de celebrarse una sesión plenaria de la corporación insular para dar viabilidad\" al acuerdo.",
        "lemmatized_text": "el consejero de educación cultura deporte y universidades_del_gobierno_de_canarias milagros_luis_brito firmar uno orden para declarar de interés general el derbi que enfrentar a el c._d_tenerife y a el u.d._las_palmas el portavoz de el ejecutivo canario martín_marrero así lo haber anunciar en el rueda de prensa posterior a el consejo_de_gobierno marrero explicar que se haber tomar este decisión con el objetivo de que se poder emitir en directo y en abrir en todo canarias asimismo recordar que este mismo hecho se producir en el temporada 2008-2009 además recordar que este orden tener pleno respaldo jurídico y legal a través de el decreto 219 de [??:11/11/2008:??.??:??] por el que se atribuir a el consejería de el área el competencia para determinar el acontecimiento deportivo que se considerar de interés general el pabellón de gran canario a el espera de el cabildo por_otro_lado cuestionar por el concreción de el convenio para llevar_a_cabo el pabellón de el mundial_de_baloncesto de 2014 en gran_canaria marrero asegurar que se haber completar desde hacer día el expediente para suscribir el convenio que de luz verde a el pabellón en este sentido afirmar que estar a_la_espera_de que el cabildo de gran_canaria convocar el firma de el acuerdo de_todos_modos haber subrayar que luis_brito se haber dirigir reiteradamente a el cabildo para apremiar le a el firma de el convenio y el respuesta que haber obtener ser que haber de celebrar se uno sesión plenario de el corporación insular para dar viabilidad a el acuerdo",
        "lemmatized_text_reduced": "consejero educación cultura deporte universidades_del_gobierno_de_canarias milagros_luis_brito firmar orden declarar interés general derbi enfrentar c._d_tenerife u.d._las_palmas portavoz ejecutivo canario martín_marrero haber anunciar rueda prensa posterior consejo_de_gobierno marrero explicar haber tomar decisión objetivo poder emitir directo abrir canarias recordar mismo hecho producir temporada recordar orden tener pleno respaldo jurídico legal través decreto atribuir consejería área competencia determinar acontecimiento deportivo considerar interés general pabellón gran canario espera cabildo por_otro_lado cuestionar concreción convenio llevar_a_cabo pabellón mundial_de_baloncesto gran_canaria marrero asegurar haber completar hacer día expediente suscribir convenio luz verde pabellón sentido afirmar estar cabildo gran_canaria convocar firma acuerdo haber subrayar luis_brito haber dirigir reiteradamente cabildo apremiar firma convenio respuesta haber obtener ser haber celebrar sesión plenario corporación insular dar viabilidad acuerdo",
        "persons": [
            "Milagros_Luis_Brito",
            "Martín_Marrero",
            "Marrero",
            "Marrero",
            "Luis_Brito"
        ],
        "locations": [
            "Canarias",
            "Gran_Canaria"
        ],
        "organizations": [
            "Universidades_del_Gobierno_de_Canarias",
            "C._D_Tenerife",
            "U.D._Las_Palmas",
            "Ejecutivo",
            "Consejo_de_Gobierno",
            "Consejería",
            "Cabildo",
            "Cabildo"
        ],
        "others": [
            "Educación",
            "Cultura",
            "Deporte",
            "Decreto",
            "Por_otro_lado",
            "Mundial_de_Baloncesto",
            "Gran_Canaria"
        ],
        "dates": [
            "[??:11/11/2008:??.??:??]"
        ],
        "numbers": [
            "2008-2009",
            "219",
            "2014"
        ]
    }
}
