{
    "province": "LAS PALMAS",
    "date": "2009-12-22T00:00:00",
    "url": "https://www.20minutos.es/noticia/594064/0/",
    "title": {
        "raw_text": "La demanda de energía eléctrica cae un 2,1% en Canarias durante el año 2009",
        "lemmatized_text": "el demanda de energía eléctrico caer uno 2,1/100 en canarias durante el [??:??/??/2009:??.??:??]",
        "lemmatized_text_reduced": "demanda energía eléctrico caer canarias",
        "persons": [],
        "locations": [
            "Canarias"
        ],
        "organizations": [],
        "others": [],
        "dates": [
            "[??:??/??/2009:??.??:??]"
        ],
        "numbers": [
            "2,1/100"
        ]
    },
    "lead": {
        "raw_text": "La demanda de energía eléctrica en Canarias ha descendido en un 2,1 por ciento a lo largo del presente año, según informó hoy el gestor del sistema eléctrico en un avance del Informe del Sistema Eléctrico Español del 2009.",
        "lemmatized_text": "el demanda de energía eléctrico en canarias haber descender en uno 2,1 por 100 a el largo de el presente año según informar hoy el gestor de el sistema eléctrico en uno avance de el informe_del_sistema_eléctrico_español de el 2009",
        "lemmatized_text_reduced": "demanda energía eléctrico canarias haber descender largo presente año informar gestor sistema eléctrico avance informe_del_sistema_eléctrico_español",
        "persons": [],
        "locations": [
            "Canarias"
        ],
        "organizations": [],
        "others": [
            "Informe_del_Sistema_Eléctrico_Español"
        ],
        "dates": [],
        "numbers": [
            "2,1",
            "100",
            "2009"
        ]
    },
    "body": {
        "raw_text": "Así, a nivel nacional esta demanda eléctrica se situó a finales de 2009 en 251.305 gigavatios hora (GWh), un 4,6 por ciento menos que en el año anterior, lo que representa la primera tasa negativa anual en la serie de registros que viene realizando Red Eléctrica de España (REE) sobre la evolución de la demanda desde 1985. Este descenso del consumo habría sido del 4,3 por ciento una vez corregidos los efectos de la laboralidad y la temperatura. Este descenso de la demanda es el resultado de la acumulación de tasas negativas registradas en todos los meses del año. En concreto, un periodo de fuerte caída finalizó en abril con el mayor descenso (un 11,8%), a partir del cual se inició una segunda etapa donde los descensos fueron más moderados, hasta situarse en diciembre en una tasa negativa del 2,3 por ciento. Los valores máximos de demanda de potencia media horaria y de energía diaria se alcanzaron el 13 de enero, con 44.440 megavatios (MW), y el 3 de diciembre, con 886 GWh, respectivamente. Estos valores superan en un 3,4 por ciento y en 4,6 por ciento a los correspondientes del 2008 y son inferiores en alrededor a un 1 por ciento a los equivalentes históricos registrados en el 2007. Además, la energía eólica superó en varias ocasiones los anteriores máximos históricos de potencia instantánea, de energía horaria y de energía diaria. Así, el 8 de noviembre se registraron nuevos máximos históricos de producción eólica: 11.620 MW de potencia instantánea, 11.429 MWh de producción eólica horaria y 251.543 MWh de producción eólica diaria, el 44,9 por ciento de la demanda eléctrica de ese día. Asimismo, en noviembre se produjo un máximo mensual de energía eólica que cubrió el 22,7 por ciento de la demanda de ese mes, superando por primera vez la aportación de la nuclear (un 19,5%). La potencia instalada en el sistema peninsular aumentó en 2.682 MW durante el año, alcanzando un total de 93.215 MW, lo que representa un incremento del 3 por ciento respecto a 2008. La mayor parte de esta nueva potencia procede de los nuevos parques eólicos, que aportan a la potencia instalada 2.576 MW, alcanzado un total de 18.119 MW a final de año, y de los ciclos combinados con 568 MW. La producción de la eólica supera al carbón En lo que respecta a la cobertura de la demanda, por primera vez en la historia de la energía eólica su producción ha superado a la del carbón, con una aportación del 13 por ciento frente al 12 por ciento. Asimismo, la aportación de las energías renovables a la cobertura de demanda ha alcanzado el 26 por ciento, frente al 24 por ciento en 2008, siendo un 3 por ciento de ella procedente de la energía solar. Este descenso del consumo eléctrico y el incremento de las energías renovables, así como una menor producción de los grupos de carbón, han contribuido a reducir las emisiones de CO2 del sector eléctrico un 15,5 por ciento con respecto al año pasado, al estimarse que se han alcanzado los 74,5 millones de toneladas este año. En los sistemas extrapeninsulares la demanda de energía alcanzó los 15.569 GWh, un 1,9 por ciento inferior a la del año anterior. En Baleares se experimentó un descenso del 1,9 por ciento, mientras que Ceuta y Melilla registraron crecimientos del 1,8 por ciento y 1,5 por ciento, respectivamente. Además, por sexto año consecutivo el saldo de los intercambios internacionales resultó exportador con 8.398 GWh, un 23,9 por ciento inferior al del 2008. Este descenso se debió tanto a la reducción de las exportaciones, en un 11 por ciento, como al incremento del volumen de importaciones, en un 13,2 por ciento.",
        "lemmatized_text": "así a nivel nacional este demanda eléctrico se situar a final de 2009 en 251.305 gigavatios hora gwh uno 4,6 por 100 menos que en el año anterior el que representar el 1 tasa negativo anual en el serie de registro que venir realizar red_eléctrica_de_españa ree sobre el evolución de el demanda desde 1985 este descenso de el consumo haber ser de el 4,3 por 101 vez corregir el efecto de el laboralidad y el temperatura este descenso de el demanda ser el resultado de el acumulación de tasa negativo registrar en todo el mes de el año en concreto uno periodo de fuerte caída finalizar en [??:??/4/??:??.??:??] con el mayor descenso uno 11,8/100 a partir de el cual se iniciar uno 2 etapa donde el descenso ser más moderar hasta situar se en [??:??/12/??:??.??:??] en uno tasa negativo de el 2,3 por 100 el valor máximo de demanda de potencia medio horario y de energía diario se alcanzar el [??:13/1/??:??.??:??] con 44.44 megavatio mw y el [??:3/12/??:??.??:??] con 886 gwh respectivamente este valor superar en uno 3,4 por 100 y en 4,6 por 100 a el correspondiente de el 2008 y ser inferior en alrededor a uno 1 por 100 a el equivalente histórico registrar en el 2007 además el energía eólico superar en varios ocasión el anterior máximo histórico de potencia instantáneo de energía horario y de energía diario así el [??:8/11/??:??.??:??] se registrar nuevo máximo histórico de producción eólico 11.62 mw de potencia instantáneo 11.429 mwh de producción eólico horario y 251.543 mwh de producción eólico diario el 44,9 por 100 de el demanda eléctrico de ese día asimismo en [??:??/11/??:??.??:??] se producir uno máximo mensual de energía eólico que cubrir el 22,7 por 100 de el demanda de ese mes superar por 1 vez el aportación de el nuclear uno 19,5/100 el potencia instalar en el sistema peninsular aumentar en 2.682 mw durante el año alcanzar uno total de 93.215 mw el que representar uno incremento de el 3 por 100 respecto_a 2008 el mayor parte de este nuevo potencia proceder de el nuevo parque eólico que aportar a el potencia instalar 2.576 mw alcanzar uno total de 18.119 mw a final de año y de el ciclo combinar con 568 mw el producción de el eólico superar a el carbón en el que respectar a el cobertura de el demanda por 1 vez en el historia de el energía eólico su producción haber superar a el de el carbón con uno aportación de el 13 por 100 frente a el 12 por 100 asimismo el aportación de el energía renovable a el cobertura de demanda haber alcanzar el 26 por 100 frente a el 24 por 100 en 2008 ser uno 3 por 100 de él procedente de el energía solar este descenso de el consumo eléctrico y el incremento de el energía renovable así_como uno menor producción de el grupo de carbón haber contribuir a reducir el emisión de CO2 de el sector eléctrico uno 15,5 por 100 con respecto a el año pasar a el estimar se que se haber alcanzar el 74,5 millón de tonelada este año en el sistema extrapeninsulares el demanda de energía alcanzar el 15.569 gwh uno 1,9 por 100 inferior a el de el año anterior en baleares se experimentar uno descenso de el 1,9 por 100 mientras_que ceuta y melilla registrar crecimiento de el 1,8 por 100 y 1,5 por 100 respectivamente además por 6 año consecutivo el saldo de el intercambio internacional resultar exportador con 8.398 gwh uno 23,9 por 100 inferior a el de el 2008 este descenso se deber tanto a el reducción de el exportación en uno 11 por 100 como a el incremento de el volumen de importación en uno 13,2 por 100",
        "lemmatized_text_reduced": "nivel nacional demanda eléctrico situar final gigavatios hora gwh año anterior representar 1 tasa negativo anual serie registro venir realizar red_eléctrica_de_españa ree evolución demanda descenso consumo haber ser vez corregir efecto laboralidad temperatura descenso demanda ser resultado acumulación tasa negativo registrar mes año concreto periodo fuerte caída finalizar mayor descenso partir iniciar 2 etapa descenso ser moderar situar tasa negativo valor máximo demanda potencia medio horario energía diario alcanzar megavatio mw gwh respectivamente valor superar correspondiente ser inferior equivalente histórico registrar energía eólico superar ocasión anterior máximo histórico potencia instantáneo energía horario energía diario registrar nuevo máximo histórico producción eólico mw potencia instantáneo mwh producción eólico horario mwh producción eólico diario demanda eléctrico día producir máximo mensual energía eólico cubrir demanda mes superar 1 vez aportación nuclear potencia instalar sistema peninsular aumentar mw año alcanzar total mw representar incremento mayor parte nuevo potencia proceder nuevo parque eólico aportar potencia instalar mw alcanzar total mw final año ciclo combinar mw producción eólico superar carbón en respectar cobertura demanda 1 vez historia energía eólico producción haber superar carbón aportación frente aportación energía renovable cobertura demanda haber alcanzar ser procedente energía solar descenso consumo eléctrico incremento energía renovable menor producción grupo carbón haber contribuir reducir emisión sector eléctrico respecto año pasar estimar haber alcanzar millón tonelada año sistema extrapeninsulares demanda energía alcanzar gwh inferior año anterior baleares experimentar descenso ceuta melilla registrar crecimiento respectivamente 6 año consecutivo saldo intercambio internacional resultar exportador gwh inferior descenso deber reducción exportación incremento volumen importación",
        "persons": [
            "GWh",
            "En"
        ],
        "locations": [
            "Baleares",
            "Melilla"
        ],
        "organizations": [
            "Red_Eléctrica_de_España",
            "REE",
            "MW",
            "MW",
            "MW",
            "MW",
            "Ceuta"
        ],
        "others": [
            "GWh",
            "MW",
            "MWh",
            "MWh",
            "MW",
            "MW",
            "GWh",
            "GWh"
        ],
        "dates": [
            "[??:??/4/??:??.??:??]",
            "[??:??/12/??:??.??:??]",
            "[??:13/1/??:??.??:??]",
            "[??:3/12/??:??.??:??]",
            "[??:8/11/??:??.??:??]",
            "[??:??/11/??:??.??:??]"
        ],
        "numbers": [
            "2009",
            "251.305",
            "4,6",
            "100",
            "1985",
            "4,3",
            "101",
            "11,8/100",
            "2,3",
            "100",
            "44.44",
            "886",
            "3,4",
            "100",
            "4,6",
            "100",
            "2008",
            "1",
            "100",
            "2007",
            "11.62",
            "11.429",
            "251.543",
            "44,9",
            "100",
            "22,7",
            "100",
            "19,5/100",
            "2.682",
            "93.215",
            "3",
            "100",
            "2008",
            "2.576",
            "18.119",
            "568",
            "13",
            "100",
            "12",
            "100",
            "26",
            "100",
            "24",
            "100",
            "2008",
            "3",
            "100",
            "CO2",
            "15,5",
            "100",
            "74,5",
            "15.569",
            "1,9",
            "100",
            "1,9",
            "100",
            "1,8",
            "100",
            "1,5",
            "100",
            "8.398",
            "23,9",
            "100",
            "2008",
            "11",
            "100",
            "13,2",
            "100"
        ]
    }
}
