{
    "province": "LAS PALMAS",
    "date": "2009-12-16T00:00:00",
    "url": "https://www.20minutos.es/noticia/589206/0/",
    "title": {
        "raw_text": "Cabildo grancanario prevé un \"buen comportamiento\" en diciembre y confía en turismo peninsular para 2010",
        "lemmatized_text": "cabildo grancanario prever uno bueno comportamiento en [??:??/12/??:??.??:??] y confiar en turismo peninsular para 2010",
        "lemmatized_text_reduced": "cabildo grancanario prever bueno comportamiento confiar turismo peninsular",
        "persons": [
            "Cabildo"
        ],
        "locations": [],
        "organizations": [],
        "others": [],
        "dates": [
            "[??:??/12/??:??.??:??]"
        ],
        "numbers": [
            "2010"
        ]
    },
    "lead": {
        "raw_text": "El Cabildo de Gran Canaria ha asegurado hoy que prevé un \"buen comportamiento\" para el turismo durante el presente mes de diciembre y a su vez confió en el mantenimiento de la llegada de los visitantes peninsulares para los primeros meses de 2010.",
        "lemmatized_text": "el cabildo_de_gran_canaria haber asegurar hoy que prever uno bueno comportamiento para el turismo durante el [??:??/12/??:??.??:??] y a su vez confiar en el mantenimiento de el llegada de el visitante peninsular para el 1 mes de 2010",
        "lemmatized_text_reduced": "cabildo_de_gran_canaria haber asegurar prever bueno comportamiento turismo vez confiar mantenimiento llegada visitante peninsular 1 mes",
        "persons": [],
        "locations": [],
        "organizations": [
            "Cabildo_de_Gran_Canaria"
        ],
        "others": [],
        "dates": [
            "[??:??/12/??:??.??:??]"
        ],
        "numbers": [
            "2010"
        ]
    },
    "body": {
        "raw_text": "Así lo manifestó hoy el consejero de Turismo, Comercio Exterior e Innovación Tecnológica de la Corporación insular, Roberto Moreno, en declaraciones a los medios de comunicación concedidas en el marco del desayuno de trabajo del secretario de Estado de Telecomunicaciones con los empresarios de la isla. Para Moreno, el Cabildo \"prevé un buen comportamiento del mes de diciembre\" ya que \"no va a ser igual que el resto del año\" 2009 que finalizará con una caída del 12 o 13 por ciento. No obstante, destacó el \"muy buen comportamiento del mercado peninsular en los meses de octubre y noviembre\" y esperó \"que se mantenga en diciembre y en los primeros meses del año 2010\". En este sentido, el consejero de Turismo recordó que \"las plazas de avión para venir de la Península a Canarias han aumentado en este invierno un 25 por ciento con respecto del invierno pasado\". \"Así que partimos de una buena base\", dijo. \"La buena noticia es que el mercado británico se está empezando a recuperar, ya en noviembre hemos tenido por primera vez en muchos meses un porcentaje positivo no negativo, es decir, ha habido un crecimiento de turistas británicos en la isla de Gran Canaria\", añadió Moreno. Preguntado sobre la posibilidad de que las compañías de bajo coste abandonen los aeropuertos canarios por la subida de tasas aeroportuarias, el también presidente del Patronato de Turismo indicó que \"la posición del Cabildo de Gran Canaria es pedirle al Gobierno de España que mantenga en lo posible esa reducción de tasas\". \"Por lo pronto, hay compañías de bajo coste que sí permiten seguir comprando billetes de avión desde diversos puntos de Europa a Gran Canaria más allá de finales de marzo, por tanto creo que vamos en la buena dirección\", concluyó.",
        "lemmatized_text": "así lo manifestar hoy el consejero de turismo comercio_exterior y innovación_tecnológica_de_la_corporación insular roberto_moreno en declaración a el medio de comunicación conceder en el marco de el desayuno de trabajo de el secretario de estado_de_telecomunicaciones con el empresario de el isla para moreno el cabildo prever uno bueno comportamiento de el [??:??/12/??:??.??:??] ya_que no ir a ser igual que el resto de el año 2009 que finalizar con uno caída de el 12 o 13 por 100 no_obstante destacar el muy bueno comportamiento de el mercado peninsular en el mes de [??:??/10/??:??.??:??] y [??:??/11/??:??.??:??] y esperar que se mantener en [??:??/12/??:??.??:??] y en el 1 mes de el [??:??/??/2010:??.??:??] en este sentido el consejero de turismo recordar que el plaza de avión para venir de el península a canarias haber aumentar en este invierno uno 25 por 100 con respecto de el invierno pasar así que partir de uno bueno base decir el bueno noticia ser que el mercado británico se estar empezar a recuperar ya en [??:??/11/??:??.??:??] haber tener por 1 vez en mucho mes uno porcentaje positivo no negativo ser decir haber haber uno crecimiento de turista británico en el isla de gran_canaria añadir moreno preguntar sobre el posibilidad de que el compañía de bajo coste abandonar el aeropuerto canario por el subida de tasa aeroportuario el también presidente de el patronato_de_turismo indicar que el posición de el cabildo_de_gran_canaria ser pedir le a el gobierno_de_españa que mantener en el posible ese reducción de tasa por_lo_pronto haber compañía de bajo coste que sí permitir seguir comprar billete de avión desde diverso punto de europa a gran_canaria más_allá_de final de [??:??/3/??:??.??:??] por tanto creer que ir en el bueno dirección concluir",
        "lemmatized_text_reduced": "manifestar consejero turismo comercio_exterior innovación_tecnológica_de_la_corporación insular roberto_moreno declaración medio comunicación conceder marco desayuno trabajo secretario estado_de_telecomunicaciones empresario isla moreno cabildo prever bueno comportamiento ir ser igual resto año finalizar caída destacar bueno comportamiento mercado peninsular mes esperar mantener 1 mes sentido consejero turismo recordar plaza avión venir península canarias haber aumentar invierno respecto invierno pasar partir bueno base decir bueno noticia ser mercado británico estar empezar recuperar haber tener 1 vez mes porcentaje positivo negativo ser decir haber haber crecimiento turista británico isla gran_canaria añadir moreno preguntar posibilidad compañía coste abandonar aeropuerto canario subida tasa aeroportuario presidente patronato_de_turismo indicar posición cabildo_de_gran_canaria ser pedir gobierno_de_españa mantener posible reducción tasa haber compañía coste permitir seguir comprar billete avión punto europa gran_canaria final creer ir bueno dirección concluir",
        "persons": [
            "Roberto_Moreno",
            "Moreno",
            "Moreno"
        ],
        "locations": [
            "Península",
            "Canarias"
        ],
        "organizations": [
            "Innovación_Tecnológica_de_la_Corporación",
            "Estado_de_Telecomunicaciones",
            "Cabildo",
            "Patronato_de_Turismo",
            "Gobierno_de_España",
            "Europa",
            "Gran_Canaria"
        ],
        "others": [
            "Turismo",
            "Comercio_Exterior",
            "Turismo",
            "Gran_Canaria",
            "Cabildo_de_Gran_Canaria"
        ],
        "dates": [
            "[??:??/12/??:??.??:??]",
            "[??:??/10/??:??.??:??]",
            "[??:??/11/??:??.??:??]",
            "[??:??/12/??:??.??:??]",
            "[??:??/??/2010:??.??:??]",
            "[??:??/11/??:??.??:??]",
            "[??:??/3/??:??.??:??]"
        ],
        "numbers": [
            "2009",
            "12",
            "13",
            "100",
            "25",
            "100"
        ]
    }
}
