{
    "province": "LAS PALMAS",
    "date": "2011-02-03T00:00:00",
    "url": "https://www.20minutos.es/noticia/948872/0/",
    "title": {
        "raw_text": "La zona de ocio del Carnaval de Las Palmas de Gran Canaria contará con 52 chiringuitos",
        "lemmatized_text": "el zona de ocio de el carnaval_de_las_palmas_de_gran_canaria contar con 52 chiringuito",
        "lemmatized_text_reduced": "zona ocio carnaval_de_las_palmas_de_gran_canaria contar chiringuito",
        "persons": [],
        "locations": [],
        "organizations": [],
        "others": [
            "Carnaval_de_Las_Palmas_de_Gran_Canaria"
        ],
        "dates": [],
        "numbers": [
            "52"
        ]
    },
    "lead": {
        "raw_text": "La zona de ocio del Carnaval de Las Palmas de Gran Canaria, situada en la trasera de los edificios Elder y Miller, contará 52 chiringuitos, de los que 11 son chiringuays, y al igual que el año pasado, 16 son chiringays, 21 de estudiantes y 4 de patrocinadores.",
        "lemmatized_text": "el zona de ocio de el carnaval_de_las_palmas_de_gran_canaria situar en el trasero de el edificio elder y miller contar 52 chiringuito de el que 11 ser chiringuays y al_igual_que el año pasar 16 ser chiringays 21 de estudiante y 4 de patrocinador",
        "lemmatized_text_reduced": "zona ocio carnaval_de_las_palmas_de_gran_canaria situar trasero edificio elder miller contar chiringuito ser chiringuays año pasar ser chiringays estudiante patrocinador",
        "persons": [
            "Miller"
        ],
        "locations": [],
        "organizations": [],
        "others": [
            "Carnaval_de_Las_Palmas_de_Gran_Canaria",
            "Elder"
        ],
        "dates": [],
        "numbers": [
            "52",
            "11",
            "16",
            "21",
            "4"
        ]
    },
    "body": {
        "raw_text": "La zona de ocio del Carnaval de Las Palmas de Gran Canaria, situada en la trasera de los edificios Elder y Miller, contará 52 chiringuitos, de los que 11 son chiringuays, y al igual que el año pasado, 16 son chiringays, 21 de estudiantes y 4 de patrocinadores. En un comunicado, el Ayuntamiento capitalino explicó que en la parte trasera de la zona de ocio se podrá encontrar, además, un ventorrillo que representa un molino, 10 hamburgueserías y 10 puestos de comida. Además, dos atracciones y dos casetas de feria se ubicarán en la trasera del Edificio Elder. En el parque de Santa Catalina, delante del escenario, se ubicarán los puestos de golosinas y un mesón, mientras que los ventorrillos podrán permanecer abiertos hasta las 3 de la madrugada de domingo a jueves, aunque sin música los domingos, lunes (a excepción del lunes de carnaval) y martes. Los miércoles, en cambio, se admitirá hasta las 00.30 horas, y los jueves podrán disfrutar de ella hasta las 01.30 horas. Ya de cara al fin de semana el panorama cambiará los viernes, sábados y el lunes de carnaval, cuando la actividad se mantendrá hasta las 5 de la madrugada, aunque la música tendrá cabida hasta media hora antes del cierre de establecimientos. Por su parte, las atracciones funcionarán de lunes a sábado de 12.00 a 24.00 horas, y los domingos y festivos de 10.00 a 24.00 horas. En aras de hacer compatible el derecho al ocio y la diversión con el derecho al descanso, no sólo se establecen limitaciones horarias, sino que este año, el Escenario Boulevard, situado junto a la zona de ocio, mirará por primera vez hacia el mar, de forma que se evitará la propagación del ruido hacia los edificios colindantes. Este escenario acogerá conciertos de orquestas locales y la animación musical de Djs durante el periodo festivo.",
        "lemmatized_text": "el zona de ocio de el carnaval_de_las_palmas_de_gran_canaria situar en el trasero de el edificio elder y miller contar 52 chiringuito de el que 11 ser chiringuays y al_igual_que el año pasar 16 ser chiringays 21 de estudiante y 4 de patrocinador en uno comunicado el ayuntamiento capitalino explicar que en el parte trasero de el zona de ocio se poder encontrar además uno ventorrillo que representar uno molino 10 hamburguesería y 10 puesto de comida además 2 atracción y 2 caseta de feria se ubicar en el trasero de el edificio_elder en el parque de santa_catalina delante de el escenario se ubicar el puesto de golosina y uno mesón mientras_que el ventorrillo poder permanecer abrir hasta el [G:??/??/??:3.00:am] a [J:??/??/??:??.??:??] aunque sin música el domingo [L:??/??/??:??.??:??] a excepción de el [L:??/??/??:??.??:??] de carnaval y [M:??/??/??:??.??:??] el [X:??/??/??:??.??:??] en cambio se admitir hasta el TM_h:0.3 y el [J:??/??/??:??.??:??] poder disfrutar de él hasta el TM_h:1.3 ya de cara a el fin de semana el panorama cambiar el [V:??/??/??:??.??:??] sábado y el [L:??/??/??:??.??:??] de carnaval cuando el actividad se mantener hasta el [??:??/??/??:5.00:am] aunque el música tener cabida hasta medio hora antes de el cierre de establecimiento por su parte el atracción funcionar de [L:??/??/??:??.??:??] a [S:??/??/??:??.??:??] de 12 a TM_h:24 y el domingo y festivo de 10 a TM_h:24 en_aras_de hacer compatible el derecho a el ocio y el diversión con el derecho a el descanso no_sólo se establecer limitación horario sino_que este año el escenario_boulevard situar junto_a el zona de ocio mirar por 1 vez hacia el mar de forma que se evitar el propagación de el ruido hacia el edificio colindante este escenario acoger concierto de orquesta local y el animación musical de djs durante el periodo festivo",
        "lemmatized_text_reduced": "zona ocio carnaval_de_las_palmas_de_gran_canaria situar trasero edificio elder miller contar chiringuito ser chiringuays año pasar ser chiringays estudiante patrocinador comunicado ayuntamiento capitalino explicar parte trasero zona ocio poder encontrar ventorrillo representar molino hamburguesería puesto comida atracción caseta feria ubicar trasero edificio_elder parque santa_catalina escenario ubicar puesto golosina mesón ventorrillo poder permanecer abrir música domingo excepción carnaval cambio admitir poder disfrutar cara fin semana panorama cambiar sábado carnaval actividad mantener música tener cabida medio hora cierre establecimiento parte atracción funcionar domingo festivo hacer compatible derecho ocio diversión derecho descanso establecer limitación horario año escenario_boulevard situar zona ocio mirar 1 vez mar forma evitar propagación ruido edificio colindante escenario acoger concierto orquesta local animación musical djs periodo festivo",
        "persons": [
            "Miller",
            "Djs"
        ],
        "locations": [
            "Edificio_Elder",
            "Santa_Catalina",
            "Escenario_Boulevard"
        ],
        "organizations": [
            "Ayuntamiento"
        ],
        "others": [
            "Carnaval_de_Las_Palmas_de_Gran_Canaria",
            "Elder"
        ],
        "dates": [
            "[G:??/??/??:3.00:am]",
            "[J:??/??/??:??.??:??]",
            "[L:??/??/??:??.??:??]",
            "[L:??/??/??:??.??:??]",
            "[M:??/??/??:??.??:??]",
            "[X:??/??/??:??.??:??]",
            "[J:??/??/??:??.??:??]",
            "[V:??/??/??:??.??:??]",
            "[L:??/??/??:??.??:??]",
            "[??:??/??/??:5.00:am]",
            "[L:??/??/??:??.??:??]",
            "[S:??/??/??:??.??:??]"
        ],
        "numbers": [
            "52",
            "11",
            "16",
            "21",
            "4",
            "10",
            "10",
            "2",
            "2",
            "TM_h:0.3",
            "TM_h:1.3",
            "12",
            "TM_h:24",
            "10",
            "TM_h:24"
        ]
    }
}
