{
    "province": "LAS PALMAS",
    "date": "2010-02-25T00:00:00",
    "url": "https://www.20minutos.es/noticia/637637/0/",
    "title": {
        "raw_text": "La filial de mantenimiento de Binter cierra con Air Europa y negocia con Ryanair asistencia a sus aviones en Canarias",
        "lemmatized_text": "el filial de mantenimiento de binter cerrar con air_europa y negociar con ryanair asistencia a su avión en canarias",
        "lemmatized_text_reduced": "filial mantenimiento binter cerrar air_europa negociar ryanair asistencia avión canarias",
        "persons": [],
        "locations": [
            "Canarias"
        ],
        "organizations": [
            "Binter",
            "Air_Europa",
            "Ryanair"
        ],
        "others": [],
        "dates": [],
        "numbers": []
    },
    "lead": {
        "raw_text": "BinterTechnic \"baraja la posibilidad\" de desembarcar en Caribe, Centroamérica y Sudamérica, que considera \"mercados potenciales\"",
        "lemmatized_text": "bintertechnic barajar el posibilidad de desembarcar en caribe centroamérica y sudamérica que considerar mercado potencial",
        "lemmatized_text_reduced": "bintertechnic barajar posibilidad desembarcar caribe centroamérica sudamérica considerar mercado potencial",
        "persons": [
            "BinterTechnic"
        ],
        "locations": [
            "Caribe",
            "Centroamérica",
            "Sudamérica"
        ],
        "organizations": [],
        "others": [],
        "dates": [],
        "numbers": []
    },
    "body": {
        "raw_text": "La filial de mantenimiento de aviones de Binter, BinterTechnic, ha alcanzado un acuerdo con Air Europa para la asistencia técnica de sus aviones B737 en Canarias, mientras que mantiene negociaciones con la aerolínea de bajo coste Ryanair al mismo efecto, según informó la compañía canaria en un comunicado. La reciente consecución de la certificación para asistir técnicamente a los Boeing B737 ha permitido cerrar este acuerdo acuerdo no sólo con Air Europa sino también con la aerolínea Calima, al tiempo que \"se está negociando con compañías charter y 'low cost' como Luxair, Tui o Ryanair\". Además, la empresa canaria espera su \"pronta\" autorización para prestar asistencia a los modelos Airbus 319, 320 y 321, lo que ampliaría su oferta de servicios. La filial de Binter trabaja también en la ampliación de su actividad en el mercado europeo y africano, a la vez que \"baraja la posibilidad\" de ofrecer sus servicios en otros \"mercados potenciales como el Caribe, Centroamérica y Sudamérica\". Evolución en 3 AÑOS El director comercial de BinterTechnic, Enrique Linares, aseguró que con tres años de vida se ha \"pasado de ser la unidad de mantenimiento de una aerolínea de transporte regional\" a convertirse \"en una empresa de prestigio internacional, en plena expansión comercial\". BinterTechnic cuenta con la autorización oficial del fabricante de aeronaves ATR, lo cual ha posicionado a la empresa de las Islas como \"el segundo taller más importante de Europa para las revisiones de sus modelos de aviones\".",
        "lemmatized_text": "el filial de mantenimiento de avión de binter bintertechnic haber alcanzar uno acuerdo con air_europa para el asistencia técnico de su avión B737 en canarias mientras_que mantener negociación con el aerolínea de bajo coste ryanair a el mismo efecto según informar el compañía canario en uno comunicado el reciente consecución de el certificación para asistir técnicamente a el boeing B737 haber permitir cerrar este acuerdo acuerdo no_sólo con air_europa sino también con el aerolínea calima al_tiempo_que se estar negociar con compañía charter y low cost como luxair tui o ryanair además el empresa canario esperar su pronto autorización para prestar asistencia a el modelo airbus 319 320 y 321 el que ampliar su oferta de servicio el filial de binter trabajar también en el ampliación de su actividad en el mercado europeo y africano a_la_vez_que barajar el posibilidad de ofrecer su servicio en otro mercado potencial como el caribe centroamérica y sudamérica evolución en 3 años_el director comercial de bintertechnic enrique_linares asegurar que con 3 año de vida se haber pasar de ser el unidad de mantenimiento de uno aerolínea de transporte regional a convertir se en uno empresa de prestigio internacional en pleno expansión comercial bintertechnic contar con el autorización oficial de el fabricante de aeronave atr el cual haber posicionar a el empresa de el islas como el 2 taller más importante de europa para el revisión de su modelo de avión",
        "lemmatized_text_reduced": "filial mantenimiento avión binter bintertechnic haber alcanzar acuerdo air_europa asistencia técnico avión canarias mantener negociación aerolínea coste ryanair mismo efecto informar compañía canario comunicado reciente consecución certificación asistir técnicamente boeing haber permitir cerrar acuerdo acuerdo air_europa aerolínea calima estar negociar compañía charter low cost luxair tui ryanair empresa canario esperar pronto autorización prestar asistencia modelo airbus ampliar oferta servicio filial binter trabajar ampliación actividad mercado europeo africano barajar posibilidad ofrecer servicio mercado potencial caribe centroamérica sudamérica evolución años_el director comercial bintertechnic enrique_linares asegurar año vida haber pasar ser unidad mantenimiento aerolínea transporte regional convertir empresa prestigio internacional pleno expansión comercial bintertechnic contar autorización oficial fabricante aeronave atr haber posicionar empresa islas 2 taller importante europa revisión modelo avión",
        "persons": [
            "BinterTechnic",
            "Luxair",
            "Tui",
            "Binter",
            "Enrique_Linares",
            "BinterTechnic"
        ],
        "locations": [
            "Binter",
            "Canarias",
            "Calima",
            "Centroamérica",
            "Sudamérica",
            "Europa"
        ],
        "organizations": [
            "Air_Europa",
            "Boeing",
            "Air_Europa",
            "Ryanair",
            "Airbus",
            "Caribe",
            "BinterTechnic",
            "ATR",
            "Islas"
        ],
        "others": [
            "Ryanair",
            "Evolución",
            "AÑOS_El"
        ],
        "dates": [],
        "numbers": [
            "B737",
            "B737",
            "319",
            "320",
            "321",
            "3",
            "3"
        ]
    }
}
