{
    "province": "LAS PALMAS",
    "date": "2011-02-02T00:00:00",
    "url": "https://www.20minutos.es/noticia/947395/0/",
    "title": {
        "raw_text": "El Gobierno deja más de 358 millones en Canarias gracias al primer Plan E",
        "lemmatized_text": "el gobierno dejar más de 358000000 en canarias gracia a el 1 plan_e",
        "lemmatized_text_reduced": "gobierno dejar canarias gracia 1 plan_e",
        "persons": [],
        "locations": [
            "Canarias"
        ],
        "organizations": [
            "Gobierno"
        ],
        "others": [
            "Plan_E"
        ],
        "dates": [],
        "numbers": [
            "358000000"
        ]
    },
    "lead": {
        "raw_text": "El secretario de Estado de Cooperación Territorial, Gaspar Zarrías, ha presentado este miércoles un informe del Ministerio de Política Territorial sobre los fondos que del FEIL 2009 se han destinado en los 8.116 municipios españoles, y que en la Comunidad Autónoma de Canarias ha dejado 358,5 millones de euros.",
        "lemmatized_text": "el secretario de estado_de_cooperación_territorial gaspar_zarrías haber presentar este [X:??/??/??:??.??:??] uno informe de el ministerio_de_política_territorial sobre el fondo que de el feil 2009 se haber destinar en el 8.116 municipio español y que en el comunidad_autónoma_de_canarias haber dejar 358,5 millón de euro",
        "lemmatized_text_reduced": "secretario estado_de_cooperación_territorial gaspar_zarrías haber presentar informe ministerio_de_política_territorial fondo feil haber destinar municipio español comunidad_autónoma_de_canarias haber dejar millón euro",
        "persons": [
            "Gaspar_Zarrías"
        ],
        "locations": [],
        "organizations": [
            "Estado_de_Cooperación_Territorial",
            "Ministerio_de_Política_Territorial",
            "FEIL",
            "Comunidad_Autónoma_de_Canarias"
        ],
        "others": [],
        "dates": [
            "[X:??/??/??:??.??:??]"
        ],
        "numbers": [
            "2009",
            "8.116",
            "358,5"
        ]
    },
    "body": {
        "raw_text": "El secretario de Estado de Cooperación Territorial, Gaspar Zarrías, ha presentado este miércoles un informe del Ministerio de Política Territorial sobre los fondos que del FEIL 2009 se han destinado en los 8.116 municipios españoles, y que en la Comunidad Autónoma de Canarias ha dejado 358,5 millones de euros. Zarrías recordó, en rueda de prensa, que en 2009, el Gobierno destinó al FEIL 8.000 millones de euros para inversión, de los que 358,5 millones fueron para Canarias, lo que permitió la ejecución de 1.009 proyectos. Al respecto, subrayó que con dichos proyectos se preveía \"crear o mantener\" unos 12.786 puestos de trabajos, sin embargo, esta cifra se incrementó en un 84 por ciento, alcanzando finalmente los 23.581 contratos en las islas. Por provincias, Zarrías apuntó que en Las Palmas se invirtió 184,4 millones de euros, que han posibilitado la realización de 492 proyectos y la creación de 12.760 puestos de trabajo. En cuanto a la de Santa Cruz de Tenerife, se destinó 174,1 millones de euros para invertir en 517 proyectos y realizando 10.821 contratos. Por tipología de obra, la que más se han realizado en el archipiélago durante 2009 y se prevé que en 2010 sea \"parecido\" este porcentaje, el 30,8 por ciento fueron de rehabilitación y mejora de espacios públicos; 24,4 por ciento para equipamientos e infraestructuras de servicios básicos; 19,4 por ciento para equipamientos educativos, culturales y deportivos; 12,59 por ciento para equipamiento de edificios sociosanitarios; y el 12,69 por ciento restante para otros. El secretario de Estado señaló que en un \"tiempo récord\" se ha podido invertir el \"100 por 100\" de la cantidad prevista para Canarias. Ante ello, ha asegurado que en las islas el objetivo ha estado \"plenamente\" conseguido, ya que los proyectos, dijo, han permitido \"dinamizar la economía local\". En 2010, el Gobierno continúo ejecutando el FEIL, que dejaría en el archipiélago 224,4 millones de euros para la inversión en diferentes trabajos, con los que se \"ha dado luz verde\" a 961 proyectos, de los que un 80 por ciento pertenecen a inversión \"pura y dura\" de obras, mientras que el 20 por ciento restante para gasto social aunque todavía hay acciones que se están desarrollando. Aquí indicó que en generación de empleo, en la primera fase del FEIL en 2010, se han realizado un 13.733 contratos. Asimismo, recordó que el criterio de distribución de la cantidad económica para cada ayuntamiento ha sido \"en función del número de habitantes\". Objetivo cumplido Zarrías ha incidido en que se \"ha cumplido el objetivo\" del FEIL, insistiendo en que de \"no haber sido por este tipo de obras en los peores momentos de la crisis el desempleo hubiera sido significativamente mayor\". Añadió que un porcentaje \"muy importante\" de las empresas que han participado en el FEIL de \"no ser por estos fondos hubieran tenido problemas importantes para sobrevivir en su actividad económica\". En este sentido, Zarrías subrayó que ha permitido que \"no se hayan cerrado más empresas de las que se han cerrado\". Al respecto, apuntó que \"cerca de un 50 por ciento\" de las empresas que han trabajado con estos fondos, \"ha mantenido su actividad económica como consecuencia de las obras del Fondo de Inversión Local o Plan E\", ya que indicó que al ser obras de inversión, pública, civil, son trabajos que \"tienen un tiempo de ejecución que en el caso de edificios van sumando diferentes trabajadores de diversa especialidades durante toda\" el periodo, desde constructores hasta carpinteros, entre otros. \"Evidentemente cuando termina la obra la empresa deja esa actividad pero es la obra la que le ha permitido mantener la actividad durante el peor periodo de la crisis\", insistió. En cuanto a la duración de los contratos laborales que se han producido con los proyectos del FEIL en los diferentes municipios españoles, indicó que el mayor se ha fijado en una año y tres meses, aunque apuntó que todo ha dependido de la \"tipología\" de la obra. Finalmente, Zarrías señaló que en tres años, ya que en 2011 los Presupuestos Generales del Estado también contemplan fondos FEIL para los municipios, el Gobierno destinará unos 14.500 millones de euros a los ayuntamientos.",
        "lemmatized_text": "el secretario de estado_de_cooperación_territorial gaspar_zarrías haber presentar este [X:??/??/??:??.??:??] uno informe de el ministerio_de_política_territorial sobre el fondo que de el feil 2009 se haber destinar en el 8.116 municipio español y que en el comunidad_autónoma_de_canarias haber dejar 358,5 millón de euro zarrías recordar en rueda de prensa que en 2009 el gobierno destinar a el feil $_ECU:8000000 para inversión de el que 358,5 millón ser para canarias el que permitir el ejecución de 1.009 proyecto a el respecto subrayar que con decir proyecto se prever crear o mantener uno 12.786 puesto de trabajo sin embargo este cifra se incrementar en uno 84 por 100 alcanzar finalmente el 23.581 contrato en el isla por provincia zarrías apuntar que en las_palmas se invertir 184,4 millón de euro que haber posibilitar el realización de 492 proyecto y el creación de 12.76 puesto de trabajo en_cuanto_a el de santa_cruz_de_tenerife se destinar 174,1 millón de euro para invertir en 517 proyecto y realizar 10.821 contrato por tipología de obra el que más se haber realizar en el archipiélago durante 2009 y se prever que en 2010 ser parecer este porcentaje el 30,8 por 100 ser de rehabilitación y mejora de espacio público 24,4 por 100 para equipamiento y infraestructura de servicio básico 19,4 por 100 para equipamiento educativo cultural y deportivo 12,59 por 100 para equipamiento de edificio sociosanitario y el 12,69 por 100 restante para otro el secretario de estado señalar que en uno tiempo récord se haber poder invertir el 100/100 de el cantidad prever para canarias ante ello haber asegurar que en el isla el objetivo haber estar plenamente conseguir ya_que el proyecto decir haber permitir dinamizar el economía local en 2010 el gobierno continuar ejecutar el feil que dejar en el archipiélago 224,4 millón de euro para el inversión en diferente trabajo con el que se haber dar luz verde a 961 proyecto de el que uno 80 por 100 pertenecer a inversión puro y duro de obra mientras_que el 20 por 100 restante para gasto social aunque todavía haber acción que se estar desarrollar aquí indicar que en generación de empleo en el 1 fase de el feil en 2010 se haber realizar uno 13.733 contrato asimismo recordar que el criterio de distribución de el cantidad económico para cada ayuntamiento haber ser en función de el número de habitante objetivo cumplir zarrías haber incidir en que se haber cumplir el objetivo de el feil insistir en que de no haber ser por este tipo de obra en el peor momento de el crisis el desempleo haber ser significativamente mayor añadir que uno porcentaje muy importante de el empresa que haber participar en el feil de no ser por este fondo haber tener problema importante para sobrevivir en su actividad económico en este sentido zarrías subrayar que haber permitir que no se haber cerrar más empresa de el que se haber cerrar a el respecto apuntar que cerca de uno 50 por 100 de el empresa que haber trabajar con este fondo haber mantener su actividad económico como consecuencia de el obra de el fondo_de_inversión_local o plan_e ya_que indicar que a el ser obra de inversión público civil ser trabajo que tener uno tiempo de ejecución que en el caso de edificio ir sumar diferente trabajador de diverso especialidad durante todo el periodo desde constructor hasta carpintero entre otro evidentemente cuando terminar el obra el empresa dejar ese actividad pero ser el obra el que le haber permitir mantener el actividad durante el peor periodo de el crisis insistir en_cuanto_a el duración de el contrato laboral que se haber producir con el proyecto de el feil en el diferente municipio español indicar que el mayor se haber fijar en uno año y 3 mes aunque apuntar que todo haber depender de el tipología de el obra finalmente zarrías señalar que en 3 año ya_que en 2011 el presupuestos_generales_del_estado también contemplar fondo feil para el municipio el gobierno destinar uno $_ECU:14500000 a el ayuntamiento",
        "lemmatized_text_reduced": "secretario estado_de_cooperación_territorial gaspar_zarrías haber presentar informe ministerio_de_política_territorial fondo feil haber destinar municipio español comunidad_autónoma_de_canarias haber dejar millón euro zarrías recordar rueda prensa gobierno destinar feil inversión millón ser canarias permitir ejecución proyecto respecto subrayar decir proyecto prever crear mantener puesto trabajo embargo cifra incrementar alcanzar finalmente contrato isla provincia zarrías apuntar las_palmas invertir millón euro haber posibilitar realización proyecto creación puesto trabajo santa_cruz_de_tenerife destinar millón euro invertir proyecto realizar contrato tipología obra haber realizar archipiélago prever ser parecer porcentaje ser rehabilitación mejora espacio público equipamiento infraestructura servicio básico equipamiento educativo cultural deportivo equipamiento edificio sociosanitario restante secretario estado señalar tiempo récord haber poder invertir cantidad prever canarias haber asegurar isla objetivo haber estar plenamente conseguir proyecto decir haber permitir dinamizar economía local gobierno continuar ejecutar feil dejar archipiélago millón euro inversión trabajo haber dar luz verde proyecto pertenecer inversión puro duro obra restante gasto social haber acción estar desarrollar indicar generación empleo 1 fase feil haber realizar contrato recordar criterio distribución cantidad económico ayuntamiento haber ser función número habitante objetivo cumplir zarrías haber incidir haber cumplir objetivo feil insistir haber ser tipo obra peor momento crisis desempleo haber ser significativamente mayor añadir porcentaje importante empresa haber participar feil ser fondo haber tener problema importante sobrevivir actividad económico sentido zarrías subrayar haber permitir haber cerrar empresa haber cerrar respecto apuntar empresa haber trabajar fondo haber mantener actividad económico consecuencia obra fondo_de_inversión_local plan_e indicar ser obra inversión público civil ser trabajo tener tiempo ejecución caso edificio ir sumar trabajador especialidad periodo constructor carpintero evidentemente terminar obra empresa dejar actividad ser obra haber permitir mantener actividad peor periodo crisis insistir duración contrato laboral haber producir proyecto feil diferente municipio español indicar mayor haber fijar año mes apuntar haber depender tipología obra finalmente zarrías señalar año presupuestos_generales_del_estado contemplar fondo feil municipio gobierno destinar ayuntamiento",
        "persons": [
            "Gaspar_Zarrías",
            "Zarrías",
            "Zarrías",
            "Zarrías",
            "Zarrías",
            "Zarrías"
        ],
        "locations": [
            "Canarias",
            "Canarias"
        ],
        "organizations": [
            "Estado_de_Cooperación_Territorial",
            "Ministerio_de_Política_Territorial",
            "FEIL",
            "Comunidad_Autónoma_de_Canarias",
            "Gobierno",
            "FEIL",
            "Las_Palmas",
            "Santa_Cruz_de_Tenerife",
            "Estado",
            "Gobierno",
            "FEIL",
            "FEIL",
            "FEIL",
            "FEIL",
            "FEIL",
            "Presupuestos_Generales_del_Estado",
            "FEIL",
            "Gobierno"
        ],
        "others": [
            "Fondo_de_Inversión_Local",
            "Plan_E"
        ],
        "dates": [
            "[X:??/??/??:??.??:??]"
        ],
        "numbers": [
            "2009",
            "8.116",
            "358,5",
            "2009",
            "$_ECU:8000000",
            "358,5",
            "1.009",
            "12.786",
            "84",
            "100",
            "23.581",
            "184,4",
            "492",
            "12.76",
            "174,1",
            "517",
            "10.821",
            "2009",
            "2010",
            "30,8",
            "100",
            "24,4",
            "100",
            "19,4",
            "100",
            "12,59",
            "100",
            "12,69",
            "100",
            "100/100",
            "2010",
            "224,4",
            "961",
            "80",
            "100",
            "20",
            "100",
            "2010",
            "13.733",
            "50",
            "100",
            "3",
            "3",
            "2011",
            "$_ECU:14500000"
        ]
    }
}
