{
    "province": "LAS PALMAS",
    "date": "2011-02-02T00:00:00",
    "url": "https://www.20minutos.es/noticia/948011/0/",
    "title": {
        "raw_text": "Más de 790 jóvenes canarios participan en el programa 'Turismo juvenil' del Gobierno regional en 2010",
        "lemmatized_text": "más de 790 joven canario participar en el programa turismo juvenil de el gobierno regional en 2010",
        "lemmatized_text_reduced": "joven canario participar programa turismo juvenil gobierno regional",
        "persons": [],
        "locations": [],
        "organizations": [
            "Gobierno"
        ],
        "others": [],
        "dates": [],
        "numbers": [
            "790",
            "2010"
        ]
    },
    "lead": {
        "raw_text": "Más de 790 jóvenes canarios han participado en el programa 'Turismo Juvenil' del Gobierno autonómico durante 2010. Esta acción está dirigida a personas de entre 14 y 30 años de edad, a las que se pretende ofrecer una oferta cultural diversa.",
        "lemmatized_text": "más de 790 joven canario haber participar en el programa turismo_juvenil de el gobierno autonómico durante 2010 este acción estar dirigir a persona de entre 14 y 30 año de edad a el que se pretender ofrecer uno oferta cultural diverso",
        "lemmatized_text_reduced": "joven canario haber participar programa turismo_juvenil gobierno autonómico acción estar dirigir persona año edad pretender ofrecer oferta cultural diverso",
        "persons": [
            "Turismo_Juvenil"
        ],
        "locations": [],
        "organizations": [
            "Gobierno"
        ],
        "others": [],
        "dates": [],
        "numbers": [
            "790",
            "2010",
            "14",
            "30"
        ]
    },
    "body": {
        "raw_text": "Más de 790 jóvenes canarios han participado en el programa 'Turismo Juvenil' del Gobierno autonómico durante 2010. Esta acción está dirigida a personas de entre 14 y 30 años de edad, a las que se pretende ofrecer una oferta cultural diversa. Este programa, según informó el Gobierno canario en nota de prensa, incluye la realización de cursos de idiomas en diversos países extranjeros, la gestión del billete Interrail, así como la gestión de reservas de albergues en más de 300 ciudades del mundo. Al respecto, la directora general de Juventud del Gobierno de Canarias, Laura Díaz, destacó durante la presentación del Programa 2011 la importancia del mismo, ya que \"además de fomentar el ocio y la cultura en el tiempo libre, promueve la interacción de los jóvenes canarios, tanto con los habitantes de las distintas islas como con los de otros lugares fuera del archipiélago\". Díaz señaló que el programa se creó, entre otras cuestiones, por la situación geográfica de Canarias, ya que de esta forma se permite \"promover y facilitar diferentes actividades a la juventud de la Comunidad Autónoma de Canarias, especialmente en lo que respecta a sus desplazamientos\". En 2010, participaron 799 jóvenes, 206 en cursos de idiomas, 26 en Interrail, 354 jóvenes solicitaron los Seguros de Viaje, 52 se alojaron en albergues y 161 viajaron con alguno de los Paquetes lúdico-culturales. Respecto a los cursos de idiomas en el extranjero, las lenguas que pueden estudiarse son inglés en el Reino Unido, Irlanda, Canadá, Estados Unidos, Malta y Australia; francés en Francia y Canadá; alemán en Alemania y Austria; italiano; portugués; ruso y chino. Por su parte, el Interrail promueve la movilidad del joven pudiendo elegir entre muchas opciones, tales como Francia, Alemania, Gran Bretaña, Suecia, Noruega, Austria, Hungría, Polonia, Turquía, Bosnia, o Macedonia. La acción de Central de Reservas de Albergues permite gestionar en más de 300 ciudades de todo el mundo, en la que los jóvenes tienen la oportunidad de alojarse de una forma económica. En cuanto a los seguros de viaje individuales otorgan una amplia protección a los jóvenes en el extranjero, cubriendo gastos de asistencia médica y medicinal, en los casos de enfermedad o accidente y pérdida de equipaje, incluido dentro del país de origen. En 2010 se tramitaron 354 de pólizas; España sigue siendo el destino más demandado (207), seguido de Europa (123) y Resto del Mundo (24). Respecto a los Paquetes Lúdico-culturales, dirigidos a jóvenes de Canarias con edades de hasta los 30 años, para que puedan viajar y conocer otras islas y países, se realizaron diez paquetes (uno más que en 2009 y 4 más que en 2008) el pasado año de distinto contenido, en los que participaron un total de 161 jóvenes. En cuanto a las previsiones para 2011, se ofertarán ocho actividades lúdico-culturales más un viaje orientado a centros de enseñanza ('Viaje de Fin de Curso Londres- París' de 7 días, 6 noches), con lo que el número de acciones de esta naturaleza \"apenas experimenta disminución respecto al año anterior\". En 2011 habrá novedades, entre ellas el viaje de grupo lúdico-cultural que es un paquete Londres-París con distintas excursiones a los lugares más emblemáticos de Londres y París. Tendrá un precio \"competitivo\" ofrecido directamente por una agencia de Londres . Asimismo, este año se pone en marcha el Servicio Trabaja en el extranjero (Hotels, Au-Pair y Jobs Premium), opción que permite a los jóvenes estudiar un idioma extranjero in situ y trabajar para poder costearse los gastos de estudio y estancia en el país elegido.",
        "lemmatized_text": "más de 790 joven canario haber participar en el programa turismo_juvenil de el gobierno autonómico durante 2010 este acción estar dirigir a persona de entre 14 y 30 año de edad a el que se pretender ofrecer uno oferta cultural diverso este programa según informar el gobierno canario en nota de prensa incluir el realización de curso de idioma en diverso país extranjero el gestión de el billete interrail así_como el gestión de reserva de albergue en más de 300 ciudad de el mundo a el respecto el director general de juventud_del_gobierno_de_canarias laura_díaz destacar durante el presentación de el programa 2011 el importancia de el mismo ya_que además_de fomentar el ocio y el cultura en el tiempo libre promover el interacción de el joven canario tanto con el habitante de el distinto isla como con el de otro lugar fuera de el archipiélago díaz señalar que el programa se crear entre otro cuestión por el situación geográfico de canarias ya_que de este forma se permitir promover y facilitar diferente actividad a el juventud de el comunidad_autónoma_de_canarias especialmente en el que respectar a su desplazamiento en 2010 participar 799 joven 206 en curso de idioma 26 en interrail 354 joven solicitar el seguros_de_viaje 52 se alojar en albergue y 161 viajar con alguno de el paquetes lúdico-culturales respecto_a el curso de idioma en el extranjero el lengua que poder estudiar se ser inglés en el reino_unido irlanda canadá estados_unidos malta y australia francés en francia y canadá alemán en alemania y austria italiano portugués ruso y chino por su parte el interrail promover el movilidad de el joven poder elegir entre mucho opción tal como francia alemania gran_bretaña suecia noruega austria hungría polonia turquía bosnia o macedonia el acción de central_de_reservas_de_albergues permitir gestionar en más de 300 ciudad de todo el mundo en el que el joven tener el oportunidad de alojar se de uno forma económico en_cuanto_a el seguro de viaje individual otorgar uno amplio protección a el joven en el extranjero cubrir gasto de asistencia médico y medicinal en el caso de enfermedad o accidente y pérdida de equipaje incluir dentro de el país de origen en 2010 se tramitar 354 de póliza españa seguir ser el destino más demandar 207 seguir de europa 123 y resto_del_mundo 24 respecto_a el paquetes_lúdico-culturales dirigir a joven de canarias con edad de hasta el 30 año para que poder viajar y conocer otro isla y país se realizar 10 paquete uno más que en 2009 y 4 más que en 2008 el pasar año de distinto contenido en el que participar uno total de 161 joven en_cuanto_a el previsión para 2011 se ofertar 8 actividad lúdico-culturales más uno viaje orientar a centro de enseñanza viaje_de_fin_de_curso_londres parir de TM_d:7 6 noche con el que el número de acción de este naturaleza apenas experimentar disminución respecto a el año anterior en 2011 haber novedad entre ellos el viaje de grupo lúdico-cultural que ser uno paquete londres-parís con distinto excursión a el lugar más emblemático de londres y parís tener uno precio competitivo ofrecer directamente por uno agencia de londres asimismo este año se poner en marcha el servicio_trabaja en el extranjero hotels au-pair y jobs_premium opción que permitir a el joven estudiar uno idioma extranjero in_situ y trabajar para poder costear se el gasto de estudio y estancia en el país elegir",
        "lemmatized_text_reduced": "joven canario haber participar programa turismo_juvenil gobierno autonómico acción estar dirigir persona año edad pretender ofrecer oferta cultural diverso programa informar gobierno canario nota prensa incluir realización curso idioma país extranjero gestión billete interrail gestión reserva albergue ciudad mundo respecto director general juventud_del_gobierno_de_canarias laura_díaz destacar presentación programa importancia fomentar ocio cultura tiempo libre promover interacción joven canario habitante distinto isla lugar archipiélago díaz señalar programa crear cuestión situación geográfico canarias forma permitir promover facilitar actividad juventud comunidad_autónoma_de_canarias especialmente respectar desplazamiento participar joven curso idioma interrail joven solicitar seguros_de_viaje alojar albergue viajar paquetes lúdico-culturales curso idioma extranjero lengua poder estudiar ser inglés reino_unido irlanda canadá estados_unidos malta australia francés francia canadá alemán alemania austria italiano portugués ruso chino parte interrail promover movilidad joven poder elegir opción francia alemania gran_bretaña suecia noruega austria hungría polonia turquía bosnia macedonia acción central_de_reservas_de_albergues permitir gestionar ciudad mundo joven tener oportunidad alojar forma económico seguro viaje individual otorgar amplio protección joven extranjero cubrir gasto asistencia médico medicinal caso enfermedad accidente pérdida equipaje incluir país origen tramitar póliza españa seguir ser destino demandar seguir europa resto_del_mundo paquetes_lúdico-culturales dirigir joven canarias edad año poder viajar conocer isla país realizar paquete pasar año distinto contenido participar total joven previsión ofertar actividad lúdico-culturales viaje orientar centro enseñanza viaje_de_fin_de_curso_londres parir noche número acción naturaleza experimentar disminución respecto año anterior haber novedad viaje grupo lúdico-cultural ser paquete londres-parís excursión lugar emblemático londres parís tener precio competitivo ofrecer directamente agencia londres año poner marcha servicio_trabaja extranjero hotels au-pair jobs_premium opción permitir joven estudiar idioma extranjero trabajar poder costear gasto estudio estancia país elegir",
        "persons": [
            "Turismo_Juvenil",
            "Laura_Díaz",
            "Díaz",
            "España",
            "Resto_del_Mundo",
            "Hotels",
            "Jobs_Premium"
        ],
        "locations": [
            "Canarias",
            "Reino_Unido",
            "Australia",
            "Francia",
            "Alemania",
            "Bosnia",
            "Macedonia",
            "Europa",
            "Canarias",
            "Viaje_de_Fin_de_Curso_Londres",
            "Londres",
            "París",
            "Londres"
        ],
        "organizations": [
            "Gobierno",
            "Gobierno",
            "Juventud_del_Gobierno_de_Canarias",
            "Comunidad_Autónoma_de_Canarias",
            "Paquetes",
            "Irlanda",
            "Canadá",
            "Estados_Unidos",
            "Malta",
            "Canadá",
            "Austria",
            "Francia",
            "Alemania",
            "Gran_Bretaña",
            "Suecia",
            "Noruega",
            "Austria",
            "Hungría",
            "Polonia",
            "Turquía",
            "Central_de_Reservas_de_Albergues",
            "Londres-París",
            "Servicio_Trabaja",
            "Au-Pair"
        ],
        "others": [
            "Interrail",
            "Programa",
            "Interrail",
            "Seguros_de_Viaje",
            "Interrail",
            "Paquetes_Lúdico-culturales"
        ],
        "dates": [],
        "numbers": [
            "790",
            "2010",
            "14",
            "30",
            "300",
            "2011",
            "2010",
            "799",
            "206",
            "26",
            "354",
            "52",
            "161",
            "300",
            "2010",
            "354",
            "207",
            "123",
            "24",
            "30",
            "10",
            "2009",
            "4",
            "2008",
            "161",
            "2011",
            "8",
            "TM_d:7",
            "6",
            "2011"
        ]
    }
}
