{
    "province": "LAS PALMAS",
    "date": "2011-02-02T00:00:00",
    "url": "https://www.20minutos.es/noticia/947243/0/",
    "title": {
        "raw_text": "Zarrías admite que las cifras de enero son un \"mal dato\" pero afirma que en 2011 habrá creación de empleo neto",
        "lemmatized_text": "zarrías admitir que el cifra de [??:??/1/??:??.??:??] ser uno mal dato pero afirmar que en 2011 haber creación de empleo neto",
        "lemmatized_text_reduced": "zarrías admitir cifra ser mal dato afirmar haber creación empleo neto",
        "persons": [
            "Zarrías"
        ],
        "locations": [],
        "organizations": [],
        "others": [],
        "dates": [
            "[??:??/1/??:??.??:??]"
        ],
        "numbers": [
            "2011"
        ]
    },
    "lead": {
        "raw_text": "El secretario de Estado de Cooperación Territorial, Gaspar Zarrías, ha admitido este miércoles que las cifras del paro en enero, donde sitúa en más de 4,2 millones el desempleo en España, son un \"mal dato\" aunque ha afirmado en que habrá creación de empleo neto en 2011.",
        "lemmatized_text": "el secretario de estado_de_cooperación_territorial gaspar_zarrías haber admitir este [X:??/??/??:??.??:??] que el cifra de el paro en [??:??/1/??:??.??:??] donde situar en más de 4,2 millón el desempleo en españa ser uno mal dato aunque haber afirmar en que haber creación de empleo neto en 2011",
        "lemmatized_text_reduced": "secretario estado_de_cooperación_territorial gaspar_zarrías haber admitir cifra paro situar millón desempleo españa ser mal dato haber afirmar haber creación empleo neto",
        "persons": [
            "Gaspar_Zarrías"
        ],
        "locations": [
            "España"
        ],
        "organizations": [
            "Estado_de_Cooperación_Territorial"
        ],
        "others": [],
        "dates": [
            "[X:??/??/??:??.??:??]",
            "[??:??/1/??:??.??:??]"
        ],
        "numbers": [
            "4,2",
            "2011"
        ]
    },
    "body": {
        "raw_text": "El secretario de Estado de Cooperación Territorial, Gaspar Zarrías, ha admitido este miércoles que las cifras del paro en enero, donde sitúa en más de 4,2 millones el desempleo en España, son un \"mal dato\" aunque ha afirmado en que habrá creación de empleo neto en 2011. \"Es un mal dato y es un mal dato como suelen ser todos los meses de enero pero estamos convencidos de que la recuperación económica comienza a ser un hecho y que en el año 2011 habrá creación de empleo neto. Esa es la previsión que tiene el Gobierno\", apuntilló en una rueda de prensa que ofreció en Las Palmas de Gran Canaria donde presentó los datos del Feil en el archipiélago. Zarrías subrayó que el Gobierno confía en la recuperación económica y la creación del empleo este año \"por varias razones\", apuntando así al \"crecimiento económico\" y a \"lo que significa la actividad de la economía en estos últimos meses\". \"bocanada de confianza\" Asimismo, ha indicado que los acuerdos que está suscribiendo el Gobierno de José Luis Rodríguez Zapatero con diferentes sectores de la sociedad, va a suponer una \"bocanada de confianza que va a enchufar al conjunto del país\". \"Bocanada de confianza para poder poner en marcha una serie de actuaciones que traten de ir corrigiendo lo que es nuestro principal problema y no solamente hay confianza desde el punto de vista interno sino también de credibilidad de nuestro país desde el punto de vista de lo que piensan fuera de nuestro país\", apostilló. En este sentido, destacó el pacto social que el Gobierno central ha firmado este miércoles con sindicatos y empresarios, calificándolo como el \"más importante desde los pactos de La Moncloa\" porque permitirá poner en marcha una serie de actuaciones. Añadió que ello unido a la reordenación del sistema financiero español, principalmente en cajas de ahorro, permitirá que \"empiece a fluir el crédito y eso es algo que viene no solamente bien a las administraciones públicas, sino también a las familias y a las empresas\". Finalmente, incidió en que \"no es un dato bueno\" pero reiteró que el Ejecutivo central está convencido de que \"el clima que se crea a través del pacto social que hoy se firma, la reforma laboral y la incentivación que va a suponer la entrada de dinero en la economía de país\" junto con el crecimiento, \"permiten ser moderadamente optimista respecto a lo que es el empleo en los próximos meses\".",
        "lemmatized_text": "el secretario de estado_de_cooperación_territorial gaspar_zarrías haber admitir este [X:??/??/??:??.??:??] que el cifra de el paro en [??:??/1/??:??.??:??] donde situar en más de 4,2 millón el desempleo en españa ser uno mal dato aunque haber afirmar en que haber creación de empleo neto en 2011 ser uno mal dato y ser uno mal dato como soler ser todo el mes de [??:??/1/??:??.??:??] pero estar convencer de que el recuperación económico comenzar a ser uno hecho y que en el [??:??/??/2011:??.??:??] haber creación de empleo neto ese ser el previsión que tener el gobierno apuntillar en uno rueda de prensa que ofrecer en las_palmas_de_gran_canaria donde presentar el dato de el feil en el archipiélago zarrías subrayar que el gobierno confiar en el recuperación económico y el creación de el empleo este año por varios razón apuntar así a el crecimiento económico y a el que significar el actividad de el economía en este último mes bocanada de confianza asimismo haber indicar que el acuerdo que estar suscribir el gobierno_de_josé_luis_rodríguez_zapatero con diferente sector de el sociedad ir a suponer uno bocanada de confianza que ir a enchufar a el conjunto de el país bocanada de confianza para poder poner en marcha uno serie de actuación que tratar de ir corregir el que ser nuestro principal problema y no solamente haber confianza desde el punto de vista interno sino también de credibilidad de nuestro país desde el punto de vista de el que pensar fuera_de nuestro país apostillar en este sentido destacar el pacto social que el gobierno central haber firmar este [X:??/??/??:??.??:??] con sindicato y empresario calificar lo como el más importante desde el pacto de la_moncloa porque permitir poner en marcha uno serie de actuación añadir que ello unir a el reordenación de el sistema financiero español principalmente en caja de ahorro permitir que empezar a fluir el crédito y ese ser algo que venir no solamente bien a el administración público sino también a el familia y a el empresa finalmente incidir en que no ser uno dato bueno pero reiterar que el ejecutivo central estar convencer de que el clima que se creer a través de el pacto social que hoy se firma el reforma laboral y el incentivación que ir a suponer el entrada de dinero en el economía de país junto_con el crecimiento permitir ser moderadamente optimista respecto_a el que ser el empleo en el próximo mes",
        "lemmatized_text_reduced": "secretario estado_de_cooperación_territorial gaspar_zarrías haber admitir cifra paro situar millón desempleo españa ser mal dato haber afirmar haber creación empleo neto ser mal dato ser mal dato soler ser mes estar convencer recuperación económico comenzar ser hecho haber creación empleo neto ser previsión tener gobierno apuntillar rueda prensa ofrecer las_palmas_de_gran_canaria presentar dato feil archipiélago zarrías subrayar gobierno confiar recuperación económico creación empleo año razón apuntar crecimiento económico significar actividad economía último mes bocanada confianza haber indicar acuerdo estar suscribir gobierno_de_josé_luis_rodríguez_zapatero sector sociedad ir suponer bocanada confianza ir enchufar conjunto país bocanada confianza poder poner marcha serie actuación tratar ir corregir ser principal problema solamente haber confianza punto vista interno credibilidad país punto vista pensar país apostillar sentido destacar pacto social gobierno central haber firmar sindicato empresario calificar importante pacto la_moncloa permitir poner marcha serie actuación añadir unir reordenación sistema financiero español principalmente caja ahorro permitir empezar fluir crédito ser venir solamente administración público familia empresa finalmente incidir ser dato bueno reiterar ejecutivo central estar convencer clima creer través pacto social firma reforma laboral incentivación ir suponer entrada dinero economía país crecimiento permitir ser moderadamente optimista ser empleo próximo mes",
        "persons": [
            "Gaspar_Zarrías",
            "Zarrías"
        ],
        "locations": [
            "España",
            "Las_Palmas_de_Gran_Canaria",
            "Feil",
            "La_Moncloa"
        ],
        "organizations": [
            "Estado_de_Cooperación_Territorial",
            "Gobierno",
            "Gobierno",
            "Gobierno_de_José_Luis_Rodríguez_Zapatero",
            "Gobierno",
            "Ejecutivo"
        ],
        "others": [],
        "dates": [
            "[X:??/??/??:??.??:??]",
            "[??:??/1/??:??.??:??]",
            "[??:??/1/??:??.??:??]",
            "[??:??/??/2011:??.??:??]",
            "[X:??/??/??:??.??:??]"
        ],
        "numbers": [
            "4,2",
            "2011"
        ]
    }
}
