{
    "province": "LAS PALMAS",
    "date": "2011-02-02T00:00:00",
    "url": "https://www.20minutos.es/noticia/947001/0/",
    "title": {
        "raw_text": "El paro aumenta en 3.691 personas durante enero en Canarias, hasta los 258.311 desempleados",
        "lemmatized_text": "el paro aumentar en 3.691 persona durante [??:??/1/??:??.??:??] en canarias hasta el 258.311 desempleado",
        "lemmatized_text_reduced": "paro aumentar persona canarias desempleado",
        "persons": [],
        "locations": [
            "Canarias"
        ],
        "organizations": [],
        "others": [],
        "dates": [
            "[??:??/1/??:??.??:??]"
        ],
        "numbers": [
            "3.691",
            "258.311"
        ]
    },
    "lead": {
        "raw_text": "El número de parados registrados en las oficinas de los servicios públicos de empleo (antiguo Inem) se ha situado al finalizar enero en la Comunidad Autónoma de Canarias en 258.311 personas, tras subir en 3.691 desempleados, con un aumento porcentual del 1,45 por ciento respecto al mes de diciembre, según ha informado este miércoles el Ministerio de Trabajo e Inmigración.",
        "lemmatized_text": "el número de parado registrar en el oficina de el servicio público de empleo antiguo inem se haber situar a el finalizar [??:??/1/??:??.??:??] en el comunidad_autónoma_de_canarias en 258.311 persona tras subir en 3.691 desempleado con uno aumento porcentual de el 1,45 por 100 respecto a el [??:??/12/??:??.??:??] según haber informar este [X:??/??/??:??.??:??] el ministerio_de_trabajo y inmigración",
        "lemmatized_text_reduced": "número parado registrar oficina servicio público empleo antiguo inem haber situar finalizar comunidad_autónoma_de_canarias persona subir desempleado aumento porcentual respecto haber informar ministerio_de_trabajo inmigración",
        "persons": [],
        "locations": [
            "Comunidad_Autónoma_de_Canarias"
        ],
        "organizations": [
            "Inem",
            "Ministerio_de_Trabajo",
            "Inmigración"
        ],
        "others": [],
        "dates": [
            "[??:??/1/??:??.??:??]",
            "[??:??/12/??:??.??:??]",
            "[X:??/??/??:??.??:??]"
        ],
        "numbers": [
            "258.311",
            "3.691",
            "1,45",
            "100"
        ]
    },
    "body": {
        "raw_text": "El número de parados registrados en las oficinas de los servicios públicos de empleo (antiguo Inem) se ha situado al finalizar enero en la Comunidad Autónoma de Canarias en 258.311 personas, tras subir en 3.691 desempleados, con un aumento porcentual del 1,45 por ciento respecto al mes de diciembre, según ha informado este miércoles el Ministerio de Trabajo e Inmigración. En cuanto al dato interanual, durante el pasado mes se registraron 4.381 parados más en las islas que los que había en el mes de enero de 2010, lo que supone un incremento del 1,73 por ciento. Por provincias, Santa Cruz de Tenerife subió en enero en 2.233 desempleados, un 1,91 por ciento más que en diciembre; mientras que en Las Palmas se incrementó en 1.458 individuos, representando una subida del 1,06 por ciento y un total de 139.338 parados, por 118.973 que hay que la provincia occidental canaria. Aquí, en términos interanuales el paro aumentó más en Santa Cruz de Tenerife que en Las Palmas. En la primera provincia hubo 3.449 desempleados más respecto al mismo mes del año pasado (+2,99%) y en la segunda subió en 932 personas (+0,67%). Por sexos, de los 258.311 parados canarios, 129.480 son hombres y 128.831 mujeres, una semejanza que se repite en Las Palmas (68.184 hombres y 71.154 mujeres paradas) y en Santa Cruz de Tenerife (61.296 varones por 57.677 féminas). Además, por edades, un total de 20.508 canarios en situación de desempleo tiene menos de 25 años. Respecto a los sectores, de los 3.691 parados nuevos durante enero, 3.148 correspondieron al sector servicios, con un total de 171.742 parados en este área; 445 fueron de la construcción (51.644 desempleados); 163 a la industria (12.604 personas); y 24 personas sin empleo anterior, un grupo que se sitúa en 17.429 individuos. Por el contrario, el paro en la agricultura bajó en 89 personas, por lo que el número de parados del sector se ubica en 4.892. En lo que supone al área de los contratos, en Canarias hubo 41.833 nuevas contrataciones, representando un 10,69 por ciento menos que el mes de diciembre con 5.008 contratos. Un total de 4,2 Millones de parados en españa A nivel nacional, el número de parados registrados en las oficinas de los servicios públicos de empleo (antiguo Inem) se situó al finalizar enero en más de 4,2 millones de personas, tras subir en 130.930 desempleados, con un aumento porcentual del 3,2% respecto al mes de diciembre. En concreto, el volumen total de parados alcanzó en enero la cifra de 4.231.003 desempleados, su nivel más alto en toda la serie histórica comparable, que arranca en 1996, y el más elevado, por tanto, de los tres años de crisis que arrastra ya España. Pese a ello, la subida del desempleo en enero ha sido ligeramente superior a la experimentada en el mismo mes de 2010, en el que las listas de las oficinas públicas de empleo sumaron 124.890 desempleados. En enero de 2009 se registraron 198.838 desempleados más, y en igual mes de 2008 la cifra fue muy similar a la de 2011, con 132.378 nuevos desempleados. La secretaria de Estado de Empleo, Mari Luz Rodríguez, ha reconocido en un comunicado que la cifra del paro es \"negativa\" y ha recordado que enero suele ser un mes malo para el empleo. No obstante, Rodríguez ha destacado que, gracias al acuerdo social alcanzado con sindicatos y empresarios, se va a poder atender mejor a las personas en desempleo, ayudándolas a estar mejor preparadas y dándoles protección económica. Sube más el paro entre las mujeres El paro subió en enero en ambos sexos, aunque más entre las mujeres, con 78.879 nuevas paradas (+3,8%), frente a un incremento del desempleo masculino de 52.051 hombres (+2,5%), situándose el total de mujeres en paro en 2.125.764 y el de varones, en 2.105.239. Por sectores, el paro subió en enero en todos ellos, pero sobre todo en los servicios, que acaparó más del 80% de los nuevos parados. Así, este sector registró en el primer mes del año 105.080 desempleados más (+4,4%). Le siguieron el colectivo sin empleo anterior, que sumó 10.019 parados (+2,8%); la industria, con 8.266 desempleados más (+1,7%); la construcción, que registró 5.275 parados más (+0,7%), y la agricultura, con 2.290 desempleados más (+1,8%). La subida del paro se nota también entre la población extranjera, que en enero experimentó un incremento del 2,2% en su cifra de parados, con 13.438 desempleados más. En total, los inmigrantes en paro sumaban al finalizar el mes pasado 619.276 desempleados, con un repunte de 34.823 parados (+5,9%) respecto a enero de 2010. Por edades, la subida del desempleo en enero se concentró en los mayores de 25 años, con 116.838 nuevos parados (+3,2%), mientras que entre los menores de 25 años el desempleo subió en 14.092 personas, un 3,2% más. Sólo baja en baleares En enero, el paro aumentó en todas las comunidades autónomas, menos en Baleares, donde bajó en 562 personas. Las subidas estuvieron encabezadas por Cataluña, con 26.950 desempleados más, Andalucía (26.622 parados más) y Comunidad Valenciana (12.485 parados más). Por provincias, el desempleo sólo descendió en Baleares y subió en las 51 provincias restantes, especialmente en Barcelona (+19.399 parados) y Madrid (+10.540). En cuanto a la contratación, en enero se registraron en el Inem un total de 1.116.019 contratos, un 6,2% más que en igual mes de 2010. De ellos, el 9,2%, es decir, 102.733 contratos, fueron de carácter indefinido, con un crecimiento del 8,6% en tasa interanual. En enero se hicieron 1.002.982 contratos temporales y 10.304 contratos formativos. El 29,45% de los contratos temporales fueron eventuales por circunstancias de la producción y el 29,41% eran de obra o servicio.",
        "lemmatized_text": "el número de parado registrar en el oficina de el servicio público de empleo antiguo inem se haber situar a el finalizar [??:??/1/??:??.??:??] en el comunidad_autónoma_de_canarias en 258.311 persona tras subir en 3.691 desempleado con uno aumento porcentual de el 1,45 por 100 respecto a el [??:??/12/??:??.??:??] según haber informar este [X:??/??/??:??.??:??] el ministerio_de_trabajo y inmigración en cuanto a el dato interanual durante el pasar mes se registrar 4.381 parado más en el isla que el que haber en el [??:??/1/2010:??.??:??] el que suponer uno incremento de el 1,73 por 100 por provincia santa_cruz_de_tenerife subir en [??:??/1/??:??.??:??] en 2.233 desempleado uno 1,91 por 100 más que en [??:??/12/??:??.??:??] mientras_que en las_palmas se incrementar en 1.458 individuo representar uno subida de el 1,06 por 100 y uno total de 139.338 parado por 118.973 que haber que el provincia occidental canario aquí en término interanual el paro aumentar más en santa_cruz_de_tenerife que en las_palmas en el 1 provincia haber 3.449 desempleado más respecto a el mismo mes de el año pasar +2,99/100 y en el 2 subir en 932 persona +0,67/100 por sexo de el 258.311 parado canario 129.48 ser hombre y 128.831 mujer uno semejanza que se repetir en las_palmas 68.184 hombre y 71.154 mujer parar y en santa_cruz_de_tenerife 61.296 varón por 57.677 fémina además por edad uno total de 20.508 canario en situación de desempleo tener menos de 25 año respecto_a el sector de el 3.691 parado nuevo durante [??:??/1/??:??.??:??] 3.148 corresponder a el sector servicio con uno total de 171.742 parado en este área 445 ser de el construcción 51.644 desempleado 163 a el industria 12.604 persona y 24 persona sin empleo anterior uno grupo que se situar en 17.429 individuo por_el_contrario el paro en el agricultura bajar en 89 persona por el que el número de parado de el sector se ubicar en 4.892 en el que suponer a el área de el contrato en canarias haber 41.833 nuevo contratación representar uno 10,69 por 100 menos que el [??:??/12/??:??.??:??] con 5.008 contrato uno total de 4,2 millones de parado en españa a nivel nacional el número de parado registrar en el oficina de el servicio público de empleo antiguo inem se situar a el finalizar [??:??/1/??:??.??:??] en más de 4,2 millón de persona tras subir en 130.93 desempleado con uno aumento porcentual de el 3,2/100 respecto a el [??:??/12/??:??.??:??] en concreto el volumen total de parado alcanzar en [??:??/1/??:??.??:??] el cifra de 4.231.003 desempleado su nivel más alto en todo el serie histórico comparable que arrancar en 1996 y el más elevar por tanto de el 3 año de crisis que arrastrar ya españa pese_a ello el subida de el desempleo en [??:??/1/??:??.??:??] haber ser ligeramente superior a el experimentar en el mismo mes de 2010 en el que el lista de el oficina público de empleo sumar 124.89 desempleado en [??:??/1/2009:??.??:??] se registrar 198.838 desempleado más y en igual mes de 2008 el cifra ser muy similar a el de 2011 con 132.378 nuevo desempleado el secretario de estado_de_empleo mari_luz_rodríguez haber reconocer en uno comunicado que el cifra de el paro ser negativo y haber recordar que [??:??/1/??:??.??:??] soler ser uno mes malo para el empleo no_obstante rodríguez haber destacar que gracia a el acuerdo social alcanzar con sindicato y empresario se ir a poder atender mejor a el persona en desempleo ayudar lo a estar mejor preparar y dar le protección económico subir más el paro entre el mujer el paro subir en [??:??/1/??:??.??:??] en ambos sexo aunque más entre el mujer con 78.879 nuevo parada +3,8/100 frente_a uno incremento de el desempleo masculino de 52.051 hombre +2,5/100 situar se el total de mujer en paro en 2.125.764 y el de varón en 2.105.239 por sector el paro subir en [??:??/1/??:??.??:??] en todo ellos pero sobre todo en el servicio que acaparar más de el 80/100 de el nuevo parado así este sector registrar en el 1 mes de el [??:??/??/105:??.??:??] desempleado más +4,4/100 le seguir el colectivo sin empleo anterior que sumar 10.019 parado +2,8/100 el industria con 8.266 desempleado más +1,7/100 el construcción que registrar 5.275 parado más +0,7/100 y el agricultura con 2.29 desempleado más +1,8/100 el subida de el paro se notar también entre el población extranjero que en [??:??/1/??:??.??:??] experimentar uno incremento de el 2,2/100 en su cifra de parado con 13.438 desempleado más en total el inmigrante en paro sumar a el finalizar el mes pasar 619.276 desempleado con uno repunte de 34.823 parado +5,9/100 respecto_a [??:??/1/2010:??.??:??] por edad el subida de el desempleo en [??:??/1/??:??.??:??] se concentrar en el mayor de 25 año con 116.838 nuevo parado +3,2/100 mientras_que entre el menor de 25 año el desempleo subir en 14.092 persona uno 3,2/100 más sólo bajo en balear en [??:??/1/??:??.??:??] el paro aumentar en todo el comunidad autónomo menos en baleares donde bajar en 562 persona el subida estar encabezar por cataluña con 26.95 desempleado más andalucía 26.622 parado más y comunidad_valenciana 12.485 parado más por provincia el desempleo sólo descender en baleares y subir en el 51 provincia restante especialmente en barcelona +19.399 parado y madrid +10.540 en_cuanto_a el contratación en [??:??/1/??:??.??:??] se registrar en el inem uno total de 1.116.019 contrato uno 6,2/100 más que en igual mes de 2010 de ellos el 9,2/100 ser decir 102.733 contrato ser de carácter indefinido con uno crecimiento de el 8,6/100 en tasa interanual en [??:??/1/??:??.??:??] se hacer 1.002.982 contrato temporal y 10.304 contrato formativo el 29,45/100 de el contrato temporal ser eventual por circunstancia de el producción y el 29,41/100 ser de obra o servicio",
        "lemmatized_text_reduced": "número parado registrar oficina servicio público empleo antiguo inem haber situar finalizar comunidad_autónoma_de_canarias persona subir desempleado aumento porcentual respecto haber informar ministerio_de_trabajo inmigración dato interanual pasar mes registrar parado isla haber suponer incremento provincia santa_cruz_de_tenerife subir desempleado las_palmas incrementar individuo representar subida total parado haber provincia occidental canario término interanual paro aumentar santa_cruz_de_tenerife las_palmas 1 provincia haber desempleado respecto mismo mes año pasar 2 subir persona sexo parado canario ser hombre mujer semejanza repetir las_palmas hombre mujer parar santa_cruz_de_tenerife varón fémina edad total canario situación desempleo tener año sector parado nuevo corresponder sector servicio total parado área ser construcción desempleado industria persona persona empleo anterior grupo situar individuo paro agricultura bajar persona número parado sector ubicar suponer área contrato canarias haber nuevo contratación representar contrato total millones parado españa a nivel nacional número parado registrar oficina servicio público empleo antiguo inem situar finalizar millón persona subir desempleado aumento porcentual respecto concreto volumen total parado alcanzar cifra desempleado nivel alto serie histórico comparable arrancar elevar año crisis arrastrar españa subida desempleo haber ser ligeramente superior experimentar mismo mes lista oficina público empleo sumar desempleado registrar desempleado igual mes cifra ser similar nuevo desempleado secretario estado_de_empleo mari_luz_rodríguez haber reconocer comunicado cifra paro ser negativo haber recordar soler ser mes malo empleo rodríguez haber destacar gracia acuerdo social alcanzar sindicato empresario ir poder atender persona desempleo ayudar estar preparar dar protección económico subir paro mujer el paro subir sexo mujer nuevo parada incremento desempleo masculino hombre situar total mujer paro varón sector paro subir servicio acaparar nuevo parado sector registrar 1 mes desempleado seguir colectivo empleo anterior sumar parado industria desempleado construcción registrar parado agricultura desempleado subida paro notar población extranjero experimentar incremento cifra parado desempleado total inmigrante paro sumar finalizar mes pasar desempleado repunte parado edad subida desempleo concentrar mayor año nuevo parado menor año desempleo subir persona bajo balear en paro aumentar comunidad autónomo baleares bajar persona subida estar encabezar cataluña desempleado andalucía parado comunidad_valenciana parado provincia desempleo descender baleares subir provincia restante especialmente barcelona parado madrid contratación registrar inem total contrato igual mes ser decir contrato ser carácter indefinido crecimiento tasa interanual hacer contrato temporal contrato formativo contrato temporal ser eventual circunstancia producción ser obra servicio",
        "persons": [
            "Mari_Luz_Rodríguez",
            "Rodríguez"
        ],
        "locations": [
            "Comunidad_Autónoma_de_Canarias",
            "Santa_Cruz_de_Tenerife",
            "Las_Palmas",
            "Santa_Cruz_de_Tenerife",
            "Canarias",
            "España",
            "Baleares",
            "Cataluña",
            "Andalucía",
            "Comunidad_Valenciana",
            "Baleares",
            "Barcelona",
            "Madrid"
        ],
        "organizations": [
            "Inem",
            "Ministerio_de_Trabajo",
            "Inmigración",
            "Santa_Cruz_de_Tenerife",
            "Las_Palmas",
            "Las_Palmas",
            "Inem",
            "Inem"
        ],
        "others": [
            "Millones",
            "A",
            "Estado_de_Empleo",
            "El",
            "En"
        ],
        "dates": [
            "[??:??/1/??:??.??:??]",
            "[??:??/12/??:??.??:??]",
            "[X:??/??/??:??.??:??]",
            "[??:??/1/2010:??.??:??]",
            "[??:??/1/??:??.??:??]",
            "[??:??/12/??:??.??:??]",
            "[??:??/1/??:??.??:??]",
            "[??:??/12/??:??.??:??]",
            "[??:??/1/??:??.??:??]",
            "[??:??/12/??:??.??:??]",
            "[??:??/1/??:??.??:??]",
            "[??:??/1/??:??.??:??]",
            "[??:??/1/2009:??.??:??]",
            "[??:??/1/??:??.??:??]",
            "[??:??/1/??:??.??:??]",
            "[??:??/1/??:??.??:??]",
            "[??:??/??/105:??.??:??]",
            "[??:??/1/??:??.??:??]",
            "[??:??/1/2010:??.??:??]",
            "[??:??/1/??:??.??:??]",
            "[??:??/1/??:??.??:??]",
            "[??:??/1/??:??.??:??]",
            "[??:??/1/??:??.??:??]"
        ],
        "numbers": [
            "258.311",
            "3.691",
            "1,45",
            "100",
            "4.381",
            "1,73",
            "100",
            "2.233",
            "1,91",
            "100",
            "1.458",
            "1,06",
            "100",
            "139.338",
            "118.973",
            "3.449",
            "+2,99/100",
            "932",
            "+0,67/100",
            "258.311",
            "129.48",
            "128.831",
            "68.184",
            "71.154",
            "61.296",
            "57.677",
            "20.508",
            "25",
            "3.691",
            "3.148",
            "171.742",
            "445",
            "51.644",
            "163",
            "12.604",
            "24",
            "17.429",
            "89",
            "4.892",
            "41.833",
            "10,69",
            "100",
            "5.008",
            "4,2",
            "4,2",
            "130.93",
            "3,2/100",
            "4.231.003",
            "1996",
            "3",
            "2010",
            "124.89",
            "198.838",
            "2008",
            "2011",
            "132.378",
            "78.879",
            "+3,8/100",
            "52.051",
            "+2,5/100",
            "2.125.764",
            "2.105.239",
            "80/100",
            "+4,4/100",
            "10.019",
            "+2,8/100",
            "8.266",
            "+1,7/100",
            "5.275",
            "+0,7/100",
            "2.29",
            "+1,8/100",
            "2,2/100",
            "13.438",
            "619.276",
            "34.823",
            "+5,9/100",
            "25",
            "116.838",
            "+3,2/100",
            "25",
            "14.092",
            "3,2/100",
            "562",
            "26.95",
            "26.622",
            "12.485",
            "51",
            "+19.399",
            "+10.540",
            "1.116.019",
            "6,2/100",
            "2010",
            "9,2/100",
            "102.733",
            "8,6/100",
            "1.002.982",
            "10.304",
            "29,45/100",
            "29,41/100"
        ]
    }
}
