{
    "province": "LAS PALMAS",
    "date": "2011-02-02T00:00:00",
    "url": "https://www.20minutos.es/noticia/946984/0/",
    "title": {
        "raw_text": "El paro aumenta en 3.691 personas durante enero en Canarias, hasta los 258.311 desempleados",
        "lemmatized_text": "el paro aumentar en 3.691 persona durante [??:??/1/??:??.??:??] en canarias hasta el 258.311 desempleado",
        "lemmatized_text_reduced": "paro aumentar persona canarias desempleado",
        "persons": [],
        "locations": [
            "Canarias"
        ],
        "organizations": [],
        "others": [],
        "dates": [
            "[??:??/1/??:??.??:??]"
        ],
        "numbers": [
            "3.691",
            "258.311"
        ]
    },
    "lead": {
        "raw_text": "El número de parados registrados en las oficinas de los servicios públicos de empleo (antiguo Inem) se ha situado al finalizar enero en la Comunidad Autónoma de Canarias en 258.311 personas, tras subir en 3.691 desempleados, con un aumento porcentual del 1,45 por ciento respecto al mes de diciembre, según ha informado este miércoles el Ministerio de Trabajo e Inmigración.",
        "lemmatized_text": "el número de parado registrar en el oficina de el servicio público de empleo antiguo inem se haber situar a el finalizar [??:??/1/??:??.??:??] en el comunidad_autónoma_de_canarias en 258.311 persona tras subir en 3.691 desempleado con uno aumento porcentual de el 1,45 por 100 respecto a el [??:??/12/??:??.??:??] según haber informar este [X:??/??/??:??.??:??] el ministerio_de_trabajo y inmigración",
        "lemmatized_text_reduced": "número parado registrar oficina servicio público empleo antiguo inem haber situar finalizar comunidad_autónoma_de_canarias persona subir desempleado aumento porcentual respecto haber informar ministerio_de_trabajo inmigración",
        "persons": [],
        "locations": [
            "Comunidad_Autónoma_de_Canarias"
        ],
        "organizations": [
            "Inem",
            "Ministerio_de_Trabajo",
            "Inmigración"
        ],
        "others": [],
        "dates": [
            "[??:??/1/??:??.??:??]",
            "[??:??/12/??:??.??:??]",
            "[X:??/??/??:??.??:??]"
        ],
        "numbers": [
            "258.311",
            "3.691",
            "1,45",
            "100"
        ]
    },
    "body": {
        "raw_text": "El número de parados registrados en las oficinas de los servicios públicos de empleo (antiguo Inem) se ha situado al finalizar enero en la Comunidad Autónoma de Canarias en 258.311 personas, tras subir en 3.691 desempleados, con un aumento porcentual del 1,45 por ciento respecto al mes de diciembre, según ha informado este miércoles el Ministerio de Trabajo e Inmigración. En cuanto al dato interanual, durante el pasado mes se registraron 4.381 parados más en las islas que los que había en el mes de enero de 2010, lo que supone un incremento del 1,73 por ciento. A nivel nacional, por su parte, el paro ha subido en enero en 130.930 personas, hasta alcanzar los más de 4,2 millones de parados, con un aumento porcentual del 3,2 por ciento respecto a diciembre. En concreto, el volumen total de parados ha alcanzado en enero en España la cifra de 4.231.003 desempleados, su nivel más alto en toda la serie histórica comparable, que arranca en 1996, y el más elevado, por tanto, de los tres años de crisis que arrastra ya España. (Habrá ampliación)",
        "lemmatized_text": "el número de parado registrar en el oficina de el servicio público de empleo antiguo inem se haber situar a el finalizar [??:??/1/??:??.??:??] en el comunidad_autónoma_de_canarias en 258.311 persona tras subir en 3.691 desempleado con uno aumento porcentual de el 1,45 por 100 respecto a el [??:??/12/??:??.??:??] según haber informar este [X:??/??/??:??.??:??] el ministerio_de_trabajo y inmigración en cuanto a el dato interanual durante el pasar mes se registrar 4.381 parado más en el isla que el que haber en el [??:??/1/2010:??.??:??] el que suponer uno incremento de el 1,73 por 100 a nivel nacional por su parte el paro haber subir en [??:??/1/??:??.??:??] en 130.93 persona hasta alcanzar el más de 4,2 millón de parado con uno aumento porcentual de el 3,2 por 100 respecto_a [??:??/12/??:??.??:??] en concreto el volumen total de parado haber alcanzar en [??:??/1/??:??.??:??] en españa el cifra de 4.231.003 desempleado su nivel más alto en todo el serie histórico comparable que arrancar en 1996 y el más elevar por tanto de el 3 año de crisis que arrastrar ya españa haber ampliación",
        "lemmatized_text_reduced": "número parado registrar oficina servicio público empleo antiguo inem haber situar finalizar comunidad_autónoma_de_canarias persona subir desempleado aumento porcentual respecto haber informar ministerio_de_trabajo inmigración dato interanual pasar mes registrar parado isla haber suponer incremento nivel nacional parte paro haber subir persona alcanzar millón parado aumento porcentual concreto volumen total parado haber alcanzar españa cifra desempleado nivel alto serie histórico comparable arrancar elevar año crisis arrastrar españa haber ampliación",
        "persons": [
            "España"
        ],
        "locations": [
            "Comunidad_Autónoma_de_Canarias",
            "España"
        ],
        "organizations": [
            "Inem",
            "Ministerio_de_Trabajo",
            "Inmigración"
        ],
        "others": [],
        "dates": [
            "[??:??/1/??:??.??:??]",
            "[??:??/12/??:??.??:??]",
            "[X:??/??/??:??.??:??]",
            "[??:??/1/2010:??.??:??]",
            "[??:??/1/??:??.??:??]",
            "[??:??/12/??:??.??:??]",
            "[??:??/1/??:??.??:??]"
        ],
        "numbers": [
            "258.311",
            "3.691",
            "1,45",
            "100",
            "4.381",
            "1,73",
            "100",
            "130.93",
            "4,2",
            "3,2",
            "100",
            "4.231.003",
            "1996",
            "3"
        ]
    }
}
