{
    "province": "LAS PALMAS",
    "date": "2011-02-02T00:00:00",
    "url": "https://www.20minutos.es/noticia/947027/0/",
    "title": {
        "raw_text": "La Seguridad Social perdió 7.953 personas en Canarias durante enero, hasta los 682.118 afiliados",
        "lemmatized_text": "el seguridad_social perder 7.953 persona en canarias durante [??:??/1/??:??.??:??] hasta el 682.118 afiliado",
        "lemmatized_text_reduced": "seguridad_social perder persona canarias afiliado",
        "persons": [],
        "locations": [
            "Canarias"
        ],
        "organizations": [],
        "others": [
            "Seguridad_Social"
        ],
        "dates": [
            "[??:??/1/??:??.??:??]"
        ],
        "numbers": [
            "7.953",
            "682.118"
        ]
    },
    "lead": {
        "raw_text": "La Seguridad Social cerró enero con un descenso de 7.953 personas en la Comunidad Autónoma de Canarias, lo que supone un descenso del número total de afiliados del 1,15 por ciento respecto al pasado mes de diciembre, situándose en 682.118, informó el Ministerio de Trabajo e Inmigración.",
        "lemmatized_text": "el seguridad_social cerrar [??:??/1/??:??.??:??] con uno descenso de 7.953 persona en el comunidad_autónoma_de_canarias el que suponer uno descenso de el número total de afiliado de el 1,15 por 100 respecto a el [??:??/12/??:??.??:??] situar se en 682.118 informar el ministerio_de_trabajo y inmigración",
        "lemmatized_text_reduced": "seguridad_social cerrar descenso persona comunidad_autónoma_de_canarias suponer descenso número total afiliado respecto situar informar ministerio_de_trabajo inmigración",
        "persons": [],
        "locations": [
            "Comunidad_Autónoma_de_Canarias"
        ],
        "organizations": [
            "Ministerio_de_Trabajo",
            "Inmigración"
        ],
        "others": [
            "Seguridad_Social"
        ],
        "dates": [
            "[??:??/1/??:??.??:??]",
            "[??:??/12/??:??.??:??]"
        ],
        "numbers": [
            "7.953",
            "1,15",
            "100",
            "682.118"
        ]
    },
    "body": {
        "raw_text": "La Seguridad Social cerró enero con un descenso de 7.953 personas en la Comunidad Autónoma de Canarias, lo que supone un descenso del número total de afiliados del 1,15 por ciento respecto al pasado mes de diciembre, situándose en 682.118, informó el Ministerio de Trabajo e Inmigración. En términos interanuales, el descenso fue de 6.671 personas, un 0,97 por ciento menos que el mismo mes de 2010. Por sectores, de los 682.118 afiliados, 160.486 corresponden al régimen General, 104.854 a los Autónomos, 15.681 al sector Agrario, 5.170 trabajadores del mar y 7.243 empleadas del hogar. Además, por provincias, Las Palmas perdió 4.148 afiliados (-1,14%) en enero, con un total del 259.253 personas, mientras que Santa Cruz de Tenerife bajó en 3.805 individuos (-1,15%), hasta los 322.865. A nivel nacional, el descenso medio fue de 223.143 afiliados (-1,27%), con lo que el total de ocupados, en términos promedios, se situó en 17.361.839 cotizantes. El retroceso de enero es inferior a los descensos que se registraron en los mismos meses de 2010 y 2009, cuando la afiliación cayó en 257.828 y 349.569 ocupados, respectivamente. El Régimen General, el más numeroso del sistema, fue el que registró la mayor caída mensual, al perder 218.750 ocupados, un 1,65% respecto a diciembre, seguido del Régimen de Autónomos (RETA), con 12.431 afiliados menos (-0,4%). También perdieron afiliados en enero los regímenes especiales del Hogar (-899 cotizantes), del Mar (-837) y del Carbón (-189), y sólo el Régimen Agrario ganó cotizantes, con 9.963 ocupados más. Al finalizar enero, el Régimen General contaba con 13.054.517 cotizantes de media, 131.301 menos que hace un año (-1%), mientras que al RETA estaban afiliados 3.091.817 trabajadores, 54.345 menos en comparación con enero de 2010 (-1,7%). Con estos datos, la afiliación al Régimen General acumula seis meses consecutivos de caídas, mientras que la de autónomos lleva ya siete meses bajando. En términos interanuales, la afiliación a la Seguridad Social se redujo en enero en 184.173 personas, lo que supone un 1,05% menos, frente a la tasa negativa del 3,5% de un año atrás. Trabajo ha destacado que esta caída interanual de la afiliación es muy inferior a la registrada entre enero de 2009 y 2010, que fue de 635.732 cotizantes. El secretario de Estado de la Seguridad Social, Octavio Granado, ha recordado en un comunicado que enero es un mal mes para el empleo, ya que incluso en etapas de crecimiento económico, la afiliación cae por los contratos que se interrumpen con el paréntesis navideño y que luego se reanudad a mediados de mes. Granado también ha afirmado que el descenso de enero ha sido menos intenso que en los dos años anteriores. \"Seguimos acercándonos al mes en el que ya encontraremos que hemos pasado de los números rojos a los números negros\", ha resaltado. Dentro del Régimen General, la evolución de la afiliación en enero fue negativa. El mayor descenso de ocupados lo registró la construcción, que perdió 38.220 afiliados (-3,6%), seguido del comercio, con 35.852 cotizantes menos (-1,6%); de las actividades administrativas (-28.691 cotizantes menos) y de la hostelería (-23.290 ocupados). Baja en ambos sexos y entre los extranjeros En enero, la afiliación al sistema bajó en ambos sexos, pero algo más entre los hombres. En concreto, la afiliación masculina se redujo en 117.458 personas (-1,2%), frente a un descenso de la ocupación femenina de 105.685 mujeres (-1,3%). En total, al finalizar enero estaban afiliadas a la Seguridad Social una media de 7.840.563 mujeres, mientras que los hombres sumaban 9.521.276 afiliados. Por su parte, la afiliación media de trabajadores extranjeros bajó en enero en 37.412 personas (-2%), sexta caída mensual consecutiva, hasta un total de 1.777.567 ocupados. De ellos, 1.132.465 cotizaban al Régimen General, 264.748 al Agrario, 197.693 al de Autónomos, 178.173 al del Hogar, 3.923 al del Mar y 565 al del Carbón. La afiliación descendió en enero en todas las comunidades autónomas, encabezadas por Cataluña (-45.382 ocupados), Madrid (-30.166 cotizantes), y Comunidad Valenciana (-26.398).",
        "lemmatized_text": "el seguridad_social cerrar [??:??/1/??:??.??:??] con uno descenso de 7.953 persona en el comunidad_autónoma_de_canarias el que suponer uno descenso de el número total de afiliado de el 1,15 por 100 respecto a el [??:??/12/??:??.??:??] situar se en 682.118 informar el ministerio_de_trabajo y inmigración en término interanual el descenso ser de 6.671 persona uno 0,97 por 100 menos que el mismo mes de 2010 por sector de el 682.118 afiliado 160.486 corresponder a el régimen general 104.854 a el autónomos 15.681 a el sector agrario 5.17 trabajador de el mar y 7.243 empleado de el hogar además por provincia las_palmas perder 4.148 afiliado -1,14/100 en [??:??/1/??:??.??:??] con uno total de el 259.253 persona mientras_que santa_cruz_de_tenerife bajar en 3.805 individuo -1,15/100 hasta el 322.865 a nivel nacional el descenso medio ser de 223.143 afiliado -1,27/100 con el que el total de ocupar en término promedio se situar en 17.361.839 cotizante el retroceso de [??:??/1/??:??.??:??] ser inferior a el descenso que se registrar en el mismo mes de 2010 y 2009 cuando el afiliación caer en 257.828 y 349.569 ocupar respectivamente el régimen_general el más numeroso de el sistema ser el que registrar el mayor caída mensual a el perder 218.75 ocupar uno 1,65/100 respecto_a [??:??/12/??:??.??:??] seguir de el régimen_de_autónomos reta con 12.431 afiliado menos -0,4/100 también perder afiliar en [??:??/1/??:??.??:??] el régimen especial de el hogar -899 cotizante de el mar -837 y de el carbón -189 y sólo el régimen_agrario ganar cotizante con 9.963 ocupar más a el finalizar [??:??/1/??:??.??:??] el régimen_general contar con 13.054.517 cotizante de media 131.301 menos que hacer uno año -1/100 mientras_que a el reta estar afiliar 3.091.817 trabajador 54.345 menos en comparación con [??:??/1/2010:??.??:??] -1,7/100 con este dato el afiliación a el régimen_general acumular 6 mes consecutivo de caída mientras_que el de autónomo llevar ya 7 mes bajar en término interanual el afiliación a el seguridad_social se reducir en [??:??/1/??:??.??:??] en 184.173 persona el que suponer uno 1,05/100 menos frente_a el tasa negativo de el 3,5/100 de uno año atrás trabajo haber destacar que este caída interanual de el afiliación ser muy inferior a el registrar entre [??:??/1/2009:??.??:??] y 2010 que ser de 635.732 cotizante el secretario de estado_de_la_seguridad_social octavio_granado haber recordar en uno comunicado que [??:??/1/??:??.??:??] ser uno mal mes para el empleo ya_que incluso en etapa de crecimiento económico el afiliación caer por el contrato que se interrumpir con el paréntesis navideño y que luego se reanudar a_mediados_de mes granar también haber afirmar que el descenso de [??:??/1/??:??.??:??] haber ser menos intenso que en el 2 año anterior seguir acercar nos a el mes en el que ya encontrar que haber pasar de el número rojo a el número negro haber resaltar dentro de el régimen_general el evolución de el afiliación en [??:??/1/??:??.??:??] ser negativo el mayor descenso de ocupar lo registrar el construcción que perder 38.22 afiliado -3,6/100 seguir de el comercio con 35.852 cotizante menos -1,6/100 de el actividad administrativo -28.691 cotizante menos y de el hostelería -23.290 ocupar baja en ambos sexo y entre el extranjero en [??:??/1/??:??.??:??] el afiliación a el sistema bajar en ambos sexo pero algo más entre el hombre en concreto el afiliación masculino se reducir en 117.458 persona -1,2/100 frente_a uno descenso de el ocupación femenino de 105.685 mujer -1,3/100 en total a el finalizar [??:??/1/??:??.??:??] estar afiliar a el seguridad_social uno media de 7.840.563 mujer mientras_que el hombre sumar 9.521.276 afiliado por su parte el afiliación medio de trabajador extranjero bajar en [??:??/1/??:??.??:??] en 37.412 persona -2/100 6 caída mensual consecutivo hasta uno total de 1.777.567 ocupar de ellos 1.132.465 cotizar a el régimen_general 264.748 a el agrario 197.693 a el de autónomos 178.173 a el de el hogar 3.923 a el de el mar y 565 a el de el carbón el afiliación descender en [??:??/1/??:??.??:??] en todo el comunidad autónomo encabezar por cataluña -45.382 ocupar madrid -30.166 cotizante y comunidad_valenciana -26.398",
        "lemmatized_text_reduced": "seguridad_social cerrar descenso persona comunidad_autónoma_de_canarias suponer descenso número total afiliado respecto situar informar ministerio_de_trabajo inmigración término interanual descenso ser persona mismo mes sector afiliado corresponder régimen general autónomos sector agrario trabajador mar empleado hogar provincia las_palmas perder afiliado total persona santa_cruz_de_tenerife bajar individuo nivel nacional descenso medio ser afiliado total ocupar término promedio situar cotizante retroceso ser inferior descenso registrar mismo mes afiliación caer ocupar respectivamente régimen_general numeroso sistema ser registrar mayor caída mensual perder ocupar seguir régimen_de_autónomos reta afiliado perder afiliar régimen especial hogar cotizante mar carbón régimen_agrario ganar cotizante ocupar finalizar régimen_general contar cotizante media hacer año reta estar afiliar trabajador comparación dato afiliación régimen_general acumular mes consecutivo caída autónomo llevar mes bajar término interanual afiliación seguridad_social reducir persona suponer tasa negativo año trabajo haber destacar caída interanual afiliación ser inferior registrar ser cotizante secretario estado_de_la_seguridad_social octavio_granado haber recordar comunicado ser mal mes empleo etapa crecimiento económico afiliación caer contrato interrumpir paréntesis navideño reanudar mes granar haber afirmar descenso haber ser intenso año anterior seguir acercar mes encontrar haber pasar número rojo número negro haber resaltar régimen_general evolución afiliación ser negativo mayor descenso ocupar registrar construcción perder afiliado seguir comercio cotizante actividad administrativo cotizante hostelería ocupar baja sexo extranjero en afiliación sistema bajar sexo hombre concreto afiliación masculino reducir persona descenso ocupación femenino mujer total finalizar estar afiliar seguridad_social media mujer hombre sumar afiliado parte afiliación medio trabajador extranjero bajar persona 6 caída mensual consecutivo total ocupar cotizar régimen_general agrario autónomos hogar mar carbón afiliación descender comunidad autónomo encabezar cataluña ocupar madrid cotizante comunidad_valenciana",
        "persons": [
            "Agrario",
            "Octavio_Granado",
            "En"
        ],
        "locations": [
            "Comunidad_Autónoma_de_Canarias",
            "Mar",
            "Autónomos",
            "Mar",
            "Carbón",
            "Cataluña",
            "Madrid"
        ],
        "organizations": [
            "Ministerio_de_Trabajo",
            "Inmigración",
            "General",
            "Autónomos",
            "Las_Palmas",
            "Santa_Cruz_de_Tenerife",
            "Régimen_General",
            "Régimen_de_Autónomos",
            "RETA",
            "Hogar",
            "Carbón",
            "Régimen_Agrario",
            "Régimen_General",
            "RETA",
            "Régimen_General",
            "Trabajo",
            "Estado_de_la_Seguridad_Social",
            "Régimen_General",
            "Régimen_General",
            "Agrario",
            "Hogar",
            "Comunidad_Valenciana"
        ],
        "others": [
            "Seguridad_Social",
            "Seguridad_Social",
            "Seguridad_Social"
        ],
        "dates": [
            "[??:??/1/??:??.??:??]",
            "[??:??/12/??:??.??:??]",
            "[??:??/1/??:??.??:??]",
            "[??:??/1/??:??.??:??]",
            "[??:??/12/??:??.??:??]",
            "[??:??/1/??:??.??:??]",
            "[??:??/1/??:??.??:??]",
            "[??:??/1/2010:??.??:??]",
            "[??:??/1/??:??.??:??]",
            "[??:??/1/2009:??.??:??]",
            "[??:??/1/??:??.??:??]",
            "[??:??/1/??:??.??:??]",
            "[??:??/1/??:??.??:??]",
            "[??:??/1/??:??.??:??]",
            "[??:??/1/??:??.??:??]",
            "[??:??/1/??:??.??:??]",
            "[??:??/1/??:??.??:??]"
        ],
        "numbers": [
            "7.953",
            "1,15",
            "100",
            "682.118",
            "6.671",
            "0,97",
            "100",
            "2010",
            "682.118",
            "160.486",
            "104.854",
            "15.681",
            "5.17",
            "7.243",
            "4.148",
            "-1,14/100",
            "259.253",
            "3.805",
            "-1,15/100",
            "322.865",
            "223.143",
            "-1,27/100",
            "17.361.839",
            "2010",
            "2009",
            "257.828",
            "349.569",
            "218.75",
            "1,65/100",
            "12.431",
            "-0,4/100",
            "-899",
            "-837",
            "-189",
            "9.963",
            "13.054.517",
            "131.301",
            "-1/100",
            "3.091.817",
            "54.345",
            "-1,7/100",
            "6",
            "7",
            "184.173",
            "1,05/100",
            "3,5/100",
            "2010",
            "635.732",
            "2",
            "38.22",
            "-3,6/100",
            "35.852",
            "-1,6/100",
            "-28.691",
            "-23.290",
            "117.458",
            "-1,2/100",
            "105.685",
            "-1,3/100",
            "7.840.563",
            "9.521.276",
            "37.412",
            "-2/100",
            "1.777.567",
            "1.132.465",
            "264.748",
            "197.693",
            "178.173",
            "3.923",
            "565",
            "-45.382",
            "-30.166",
            "-26.398"
        ]
    }
}
