{
    "province": "LAS PALMAS",
    "date": "2010-02-15T00:00:00",
    "url": "https://www.20minutos.es/noticia/629687/0/",
    "title": {
        "raw_text": "PSC-PSOE acusa a Rivero y Soria de \"boicotear\" la Ley de Dependencia en Canarias y \"hacer caja\"",
        "lemmatized_text": "psc-psoe acusar a rivero y soria de boicotear el ley_de_dependencia en canarias y hacer caja",
        "lemmatized_text_reduced": "psc-psoe acusar rivero soria boicotear ley_de_dependencia canarias hacer caja",
        "persons": [
            "Rivero"
        ],
        "locations": [
            "Soria",
            "Canarias"
        ],
        "organizations": [
            "PSC-PSOE"
        ],
        "others": [
            "Ley_de_Dependencia"
        ],
        "dates": [],
        "numbers": []
    },
    "lead": {
        "raw_text": "Pide el cese de la consejera de Bienestar Social por castigar a 19.293 dependientes Canarias es la última de las CCAA en número de dictámenes emitidos y en las prestaciones concedidas, y la penúltima en solicitudes presentadas",
        "lemmatized_text": "pedir el cese de el consejero de bienestar_social por castigar a 19.293 dependiente canarias ser el último de el ccaa en número de dictamen emitir y en el prestación conceder y el penúltimo en solicitud presentar",
        "lemmatized_text_reduced": "pedir cese consejero bienestar_social castigar dependiente canarias ser último ccaa número dictamen emitir prestación conceder penúltimo solicitud presentar",
        "persons": [],
        "locations": [
            "Canarias"
        ],
        "organizations": [
            "CCAA"
        ],
        "others": [
            "Bienestar_Social"
        ],
        "dates": [],
        "numbers": [
            "19.293"
        ]
    },
    "body": {
        "raw_text": "Pide el cese de la consejera de Bienestar Social por castigar a 19.293 dependientesCanarias es la última de las CCAA en número de dictámenes emitidos y en las prestaciones concedidas, y la penúltima en solicitudes presentadas La diputada del Partido Socialista Canario (PSC-PSOE), Francisca Luengo, acusó hoy al presidente del Gobierno regional, Paulino Rivero, y al vicepresidente y consejero de Economía y Hacienda, José Manuel Soria, de \"boicotear\" la Ley de Dependencia, \"impedir su aplicación\" en las islas y \"hacer caja\" con los fondos procedentes del Estado, ya que el dinero que la comunidad autónoma recibe \"no se destina a crear servicios nuevos, sino a financiar plazas y centros de mayores anteriores a 2007\". \"Hay claramente un trapicheo entre Rivero y la consejera de Bienestar Social, Inés Rojas, con el dinero que da el Gobierno de España al autonómico y esto está castigando y haciendo sufrir a 19.293 canarios dependientes y a sus familias, que todavía esperan una resolución de sus expedientes\", afirmó Luengo en rueda de prensa en la capital grancanaria, donde aseguró que estas \"personas valoradas pero están en el limbo de la dependencia y no reciben una prestación\". En su opinión, \"los canarios no pueden ser menos que ningún catalán, vasco ni andaluz\". \"Por el mero hecho de nacer en Canarias no puede ser maltratado ni discriminado y hay que buscar forzar la aplicación de la ley en el archipiélago\", apostilló. Así, denunció que desde que entró en vigor la Ley el 1 de enero de 2007 y hasta marzo de 2008 en Canarias no se aplicó y \"no se hizo absolutamente nada en las islas porque había unas elecciones generales y apostaron para que las ganara el presidente del PP, Mariano Rajoy, pero ganó el secretario general de los socialistas, José Luis Rodríguez Zapatero y CC y PP han estado en la misma sintonía hasta después de las elecciones europeas\". De ahí que, a su juicio, \"desde el principio tanto Paulino como Soria han boicoteado la ley y han impedido su aplicación en canarias\". Añadió que dicho \"boicot no sólo frena la creación de 15.000 empleos directos, sino que está haciendo sufrir aún más si cabe a los 19.293 dependientes valorados que esperan por la ayuda que les corresponde y a los 7.000 más que simplemente han presentado su solicitud y que están en los cajones de la Consejería\".A La cabeza en el retraso en la tramitación Luengo tacha de \"última desvergüenza\" la excusa de Inés Rojas de que el sistema está saturado porque hay muchas peticiones. \"Hay otras comunidades con muchas más peticiones que Canarias y en absoluto tardan hasta 30 meses en resolverlo. Esta vergüenza sólo la aporta Canarias, que tiene el récord en el boicot que sólo hacen las comunidades del PP a la Ley de Dependencia: la nuestra va a la cabeza en el retraso en la aplicación de la Ley\". A este respecto, pidió que, \"ante la falta de sensibilidad social de la consejera\", el presidente canario debe destituirla si ella \"no tiene la ética y la dignidad suficiente para abandonar su puesto\". En relación a las numerosas solicitudes que alega Rojas, Luengo dijo \"deshacer esa mentira\" porque, a 1 de febrero de 2010 comparativamente con otras comunidades autónomas con la misma población que Canarias, como Castilla La Mancha y País Vasco, el número de solicitudes es de 67.301 y de 77.094, lo que representa unos porcentajes del 3,23 por ciento y 3,55 por ciento, respectivamente, más del doble que Canarias, que registró 25.500 solicitudes, un 1,21 por ciento de la población, cifra superior a la media nacional de 2,49 por ciento. De este modo, para Luengo, las otras dos comunidades citadas son \"un ejemplo de buenas prácticas en la aplicación de la ley en sus territorios\". Además, reiteró que Canarias es la última comunidad en la emisión de dictámenes ya que, a 1 de febrero de 2010, en las islas se emitieron 19.293 dictámenes, que representan el 0,92 por ciento de la población, mientras que la media española está cifrada en el 2,24 por ciento. Por su parte, Castilla La Mancha y el País Vasco están el 2,75 por ciento y en el 3,19 por ciento, con un número de dictámenes de 57.280 y 69.296 respectivamente. Igualmente, criticó que en Canarias sólo reciben atención 6.809 personas, que representan el 0,32 por ciento en relación a la población, mientras que la media nacional es de un 1,08 por ciento. De ahí que las islas \"también son la última región en cuanto al número de personas atendidas\", aseveró. Siguiendo con la comparativa de Castilla La Mancha y el País Vasco, observó una atención de cuatro y cinco veces más que en canarias, con un número de atendidos de 26.514, en Castilla La Mancha y de 33.727 en el País Vasco. Por tanto, reiteró que Canarias es la última de todas las CCAA en el número de dictámenes emitidos y en las prestaciones concedidas, y la penúltima en solicitudes presentadas. Más de 1.500 Personas han fallecido \"en el camino\" En este sentido, recuerda que más de 1.500 personas \"han fallecido en el camino\", dado que la dependencia la sufren principalmente las mujeres, casi todas mayores de 80 años. \"El resultado es que Canarias encabeza el lamentable ranking del retraso en la tramitación de los expedientes, alineándose con las comunidades de Murcia, Valencia y Madrid, gobernadas por PP, en las que se usa la burocracia como escudo para no cumplir la ley\", subraya. Luengo recuerda que \"en junio Canarias deberá tener puesto al día todos los expedientes atrasados, y no tardar en el futuro más de seis meses en la tramitación, tal y como lo acordó el Gobierno canario con el Ministerio el pasado 25 de enero al fijar un tope de seis meses en la tramitación de las prestaciones\". Indica que \"ésta es la última oportunidad que tiene Rivero de arreglar el desaguisado administrativo que han montado él y Rojas con el boicot a la Dependencia\". \"Por mucho que manipulen lo cierto es que los datos son incontestables y no mienten\", insistió Luengo, para quien \"el problema es que por mucho que digan, ningún canario que sufre este desprecio por parte de CC y PP les va a creer; pueden cargar las culpas contra otros todo lo que quieran y manipular las cifras un día sí y otro también, que la realidad es que existen las transferencias bancarias desde el Gobierno central al de Canarias pero no el servicio. Que expliquen qué han hecho con el dinero, no que nos vuelvan a leer las cifras manipuladas y distintas cada vez que hablan\". \"dónde está el dinero de la dependencia\" Manifestó que \"la dependencia exige una aportación específica que el Gobierno canario no aporta, y la que recibe del Estado no la destina a crear servicios nuevos, sino a financiar plazas y centros de mayores anteriores a 2007, que ya vienen siendo financiados por el sistema de financiación de las comunidades autónomas, aprobado en 2009, al igual que todos los servicios sociales\". Por este motivo, insiste, el PSC-PSOE exige al Ejecutivo regional que diga \"dónde está el dinero que recibe de la dependencia\". Además, Luengo exige al Ejecutivo de Canarias que \"reconozca\" las competencias de cabildos y ayuntamientos, no les considere \"recaderos\" y les transfiera a totalidad de los fondos que recibe del Gobierno de España y \"los 132 millones de euros que Rivero dice que aporta a la Dependencia, para que tramiten los expedientes mucho más rápido y no llegar a los 30 meses que actualmente está tardando este mal Gobierno\". \"En Canarias ni existe ni nunca existió un sistema canario de la dependencia. El sistema conocido en Canarias era el de la 'cuña\"'; la grandeza de la Ley de la Dependencia es que se tiene derecho a ser atendido se tengan o no recursos. A partir de 2007, la atención a las personas dependientes ha dejado de ser una limosna para ser un derecho, de ahí que tanto les moleste tanto esta Ley a Soria y a Rivero\", sentenció Luengo.",
        "lemmatized_text": "pedir el cese de el consejero de bienestar_social por castigar a 19.293 dependientescanarias ser el último de el ccaa en número de dictamen emitir y en el prestación conceder y el penúltimo en solicitud presentar la diputado de el partido_socialista_canario psc-psoe francisca_luengo acusar hoy a el presidente de el gobierno regional paulino_rivero y a el vicepresidente y consejero de economía y hacienda josé_manuel_soria de boicotear el ley_de_dependencia impedir su aplicación en el isla y hacer caja con el fondo procedente de el estado ya_que el dinero que el comunidad autónomo recibir no se destinar a crear servicio nuevo sino a financiar plaza y centro de mayor anterior a 2007 haber claramente uno trapicheo entre rivero y el consejero de bienestar_social inés_rojas con el dinero que dar el gobierno_de_españa a el autonómico y este estar castigar y hacer sufrir a 19.293 canario dependiente y a su familia que todavía esperar uno resolución de su expediente afirmar luengo en rueda de prensa en el capital grancanaria donde asegurar que este persona valorar pero estar en el limbo de el dependencia y no recibir uno prestación en su opinión el canario no poder ser menos que ninguno catalán vasco ni andaluz por el mero hacer de nacer en canarias no poder ser maltratar ni discriminar y haber que buscar forzar el aplicación de el ley en el archipiélago apostillar así denunciar que desde que entrar en vigor el ley el [??:1/1/2007:??.??:??] y hasta [??:??/3/2008:??.??:??] en canarias no se aplicar y no se hacer absolutamente nada en el isla porque haber uno elección general y apostar para que lo ganar el presidente de el pp mariano_rajoy pero ganar el secretario general de el socialista josé_luis_rodríguez_zapatero y cc y pp haber estar en el mismo sintonía hasta después_de el elección europeo de ahí que a su juicio desde el principio tanto paulino como soria haber boicotear el ley y haber impedir su aplicación en canario añadir que decir boicot no_sólo frenar el creación de 15 empleo directo sino_que estar hacendar sufrir aun más si caber a el 19.293 dependiente valorar que esperar por el ayuda que le corresponder y a el 7 más que simplemente haber presentar su solicitud y que estar en el cajón de el consejería a la cabeza en el retraso en el tramitación luengo tachar de último desvergüenza el excusa de inés_rojas de que el sistema estar saturar porque haber mucho petición haber otro comunidad con mucho más petición que canarias y en absoluto tardar hasta 30 mes en resolver lo este vergüenza sólo lo aportar canarias que tener el récord en el boicot que sólo hacer el comunidad de el pp a el ley_de_dependencia el nuestro ir a el cabeza en el retraso en el aplicación de el ley a este respecto pedir que ante el falta de sensibilidad social de el consejero el presidente canario deber destituir lo si él no tener el ética y el dignidad suficiente para abandonar su puesto en relación a el numeroso solicitud que alegar rojas luengo decir deshacer ese mentira porque a [??:1/2/2010:??.??:??] comparativamente con otro comunidad autónomo con el mismo población que canarias como castilla_la_mancha y país_vasco el número de solicitud ser de 67.301 y de 77.094 el que representar uno porcentaje de el 3,23 por 100 y 3,55 por 100 respectivamente más de el doble que canarias que registrar 25.5 solicitud uno 1,21 por 100 de el población cifra superior a el media nacional de 2,49 por 100 de este modo para luengo el otro 2 comunidad citar ser uno ejemplo de bueno práctica en el aplicación de el ley en su territorio además reiterar que canarias ser el último comunidad en el emisión de dictamen ya_que a [??:1/2/2010:??.??:??] en el isla se emitir 19.293 dictamen que representar el 0,92 por 100 de el población mientras_que el media español estar cifrar en el 2,24 por 100 por su parte castilla_la_mancha y el país_vasco estar el 2,75 por 100 y en el 3,19 por 100 con uno número de dictamen de 57.28 y 69.296 respectivamente igualmente criticar que en canarias sólo recibir atención 6.809 persona que representar el 0,32 por 100 en relación a el población mientras_que el media nacional ser de uno 1,08 por 100 de ahí que el isla también ser el último región en cuanto a el número de persona atender aseverar seguir con el comparativa de castilla_la_mancha y el país_vasco observar uno atención de 4 y 5 vez más que en canario con uno número de atender de 26.514 en castilla_la_mancha y de 33.727 en el país_vasco por tanto reiterar que canarias ser el último de todo el ccaa en el número de dictamen emitir y en el prestación conceder y el penúltimo en solicitud presentar más de 1.5 personas haber fallecer en el camino en este sentido recordar que más de 1.5 persona haber fallecer en el camino dado_que el dependencia lo sufrir principalmente el mujer casi todo mayor de 80 año el resultado ser que canarias encabezar el lamentable ranking de el retraso en el tramitación de el expediente alinear se con el comunidad de murcia valencia y madrid gobernar por pp en el que se usar el burocracia como escudo para no cumplir el ley subrayar luengo recordar que en [??:??/6/??:??.??:??] canarias deber tener puesto a el día todo el expediente atrasar y no tardar en el futuro más de 6 mes en el tramitación tal_y_como lo acordar el gobierno canario con el ministerio el [??:25/1/??:??.??:??] a el fijar uno tope de 6 mes en el tramitación de el prestación indicar que este ser el último oportunidad que tener rivero de arreglar el desaguisado administrativo que haber montar él y rojas con el boicot a el dependencia por_mucho_que manipular el cierto ser que el dato ser incontestable y no mentir insistir luengo para quien el problema ser que por_mucho_que decir ninguno canario que sufrir este desprecio por parte de cc y pp le ir a creer poder cargar el culpa contra otro todo el que querer y manipular el cifra uno día sí y otro también que el realidad ser que existir el transferencia bancario desde el gobierno central a el de canarias pero no el servicio que explicar qué haber hacer con el dinero no que nos volver a leer el cifra manipular y distinto cada vez que hablar dónde estar el dinero de el dependencia manifestar que el dependencia exigir uno aportación específico que el gobierno canario no aportar y el que recibir de el estado no lo destinar a crear servicio nuevo sino a financiar plaza y centro de mayor anterior a 2007 que ya venir ser financiar por el sistema de financiación de el comunidad autónomo aprobar en 2009 al_igual_que todo el servicio social por este motivo insistir el psc-psoe exigir a el ejecutivo regional que decir dónde estar el dinero que recibir de el dependencia además luengo exigir a el ejecutivo_de_canarias que reconocer el competencia de cabildo y ayuntamiento no le considerar recadero y le transferir a totalidad de el fondo que recibir de el gobierno_de_españa y el $_ECU:132000000 que rivero decir que aportar a el dependencia para que tramitar el expediente mucho más rápido y no llegar a el 30 mes que actualmente estar tardar este mal gobierno en canarias ni existir ni nunca existir uno sistema canario de el dependencia el sistema conocer en canarias ser el de el cuña el grandeza de el ley_de_la_dependencia ser que se tener derecho a ser atender se tener o no recurso a_partir_de 2007 el atención a el persona dependiente haber dejar de ser uno limosna para ser uno derecho de ahí que tanto le molestar tanto este ley a soria y a rivero sentenciar luengo",
        "lemmatized_text_reduced": "pedir cese consejero bienestar_social castigar dependientescanarias ser último ccaa número dictamen emitir prestación conceder penúltimo solicitud presentar la diputado partido_socialista_canario psc-psoe francisca_luengo acusar presidente gobierno regional paulino_rivero vicepresidente consejero economía hacienda josé_manuel_soria boicotear ley_de_dependencia impedir aplicación isla hacer caja fondo procedente estado dinero comunidad autónomo recibir destinar crear servicio nuevo financiar plaza centro mayor anterior haber claramente trapicheo rivero consejero bienestar_social inés_rojas dinero dar gobierno_de_españa autonómico estar castigar hacer sufrir canario dependiente familia esperar resolución expediente afirmar luengo rueda prensa capital grancanaria asegurar persona valorar estar limbo dependencia recibir prestación opinión canario poder ser catalán vasco andaluz mero hacer nacer canarias poder ser maltratar discriminar haber buscar forzar aplicación ley archipiélago apostillar denunciar entrar vigor ley canarias aplicar hacer absolutamente isla haber elección general apostar ganar presidente pp mariano_rajoy ganar secretario general socialista josé_luis_rodríguez_zapatero cc pp haber estar mismo sintonía elección europeo juicio principio paulino soria haber boicotear ley haber impedir aplicación canario añadir decir boicot frenar creación empleo directo estar hacendar sufrir caber dependiente valorar esperar ayuda corresponder simplemente haber presentar solicitud estar cajón consejería la cabeza retraso tramitación luengo tachar último desvergüenza excusa inés_rojas sistema estar saturar haber petición haber comunidad petición canarias absoluto tardar mes resolver vergüenza aportar canarias tener récord boicot hacer comunidad pp ley_de_dependencia nuestro ir cabeza retraso aplicación ley respecto pedir falta sensibilidad social consejero presidente canario deber destituir tener ética dignidad suficiente abandonar puesto relación numeroso solicitud alegar rojas luengo decir deshacer mentira comparativamente comunidad autónomo mismo población canarias castilla_la_mancha país_vasco número solicitud ser representar porcentaje respectivamente doble canarias registrar solicitud población cifra superior media nacional modo luengo comunidad citar ser ejemplo bueno práctica aplicación ley territorio reiterar canarias ser último comunidad emisión dictamen isla emitir dictamen representar población media español estar cifrar parte castilla_la_mancha país_vasco estar número dictamen respectivamente igualmente criticar canarias recibir atención persona representar relación población media nacional ser isla ser último región número persona atender aseverar seguir comparativa castilla_la_mancha país_vasco observar atención vez canario número atender castilla_la_mancha país_vasco reiterar canarias ser último ccaa número dictamen emitir prestación conceder penúltimo solicitud presentar personas haber fallecer camino sentido recordar persona haber fallecer camino dependencia sufrir principalmente mujer mayor año resultado ser canarias encabezar lamentable ranking retraso tramitación expediente alinear comunidad murcia valencia madrid gobernar pp usar burocracia escudo cumplir ley subrayar luengo recordar canarias deber tener puesto día expediente atrasar tardar futuro mes tramitación acordar gobierno canario ministerio fijar tope mes tramitación prestación indicar ser último oportunidad tener rivero arreglar desaguisado administrativo haber montar rojas boicot dependencia manipular cierto ser dato ser incontestable mentir insistir luengo problema ser decir canario sufrir desprecio parte cc pp ir creer poder cargar culpa querer manipular cifra día realidad ser existir transferencia bancario gobierno central canarias servicio explicar haber hacer dinero volver leer cifra manipular vez hablar estar dinero dependencia manifestar dependencia exigir aportación específico gobierno canario aportar recibir estado destinar crear servicio nuevo financiar plaza centro mayor anterior venir ser financiar sistema financiación comunidad autónomo aprobar servicio social motivo insistir psc-psoe exigir ejecutivo regional decir estar dinero recibir dependencia luengo exigir ejecutivo_de_canarias reconocer competencia cabildo ayuntamiento considerar recadero transferir totalidad fondo recibir gobierno_de_españa rivero decir aportar dependencia tramitar expediente rápido llegar mes actualmente estar tardar mal gobierno canarias existir existir sistema canario dependencia sistema conocer canarias ser cuña grandeza ley_de_la_dependencia ser tener derecho ser atender tener recurso atención persona dependiente haber dejar ser limosna ser derecho molestar ley soria rivero sentenciar luengo",
        "persons": [
            "La",
            "Francisca_Luengo",
            "Paulino_Rivero",
            "José_Manuel_Soria",
            "Rivero",
            "Inés_Rojas",
            "Luengo",
            "Mariano_Rajoy",
            "José_Luis_Rodríguez_Zapatero",
            "La",
            "Inés_Rojas",
            "Rojas",
            "Luengo",
            "Luengo",
            "Castilla_La_Mancha",
            "Personas",
            "Luengo",
            "Rivero",
            "Rojas",
            "Luengo",
            "Luengo",
            "Ejecutivo_de_Canarias",
            "Rivero",
            "Rivero",
            "Luengo"
        ],
        "locations": [
            "Canarias",
            "Canarias",
            "Paulino",
            "Soria",
            "Canarias",
            "Canarias",
            "Canarias",
            "Castilla_La_Mancha",
            "País_Vasco",
            "Canarias",
            "Canarias",
            "Canarias",
            "Castilla_La_Mancha",
            "País_Vasco",
            "Castilla_La_Mancha",
            "País_Vasco",
            "Canarias",
            "Canarias",
            "Murcia",
            "Valencia",
            "Madrid",
            "Canarias",
            "Canarias",
            "Canarias",
            "Canarias",
            "Soria"
        ],
        "organizations": [
            "CCAA",
            "Partido_Socialista_Canario",
            "PSC-PSOE",
            "Gobierno",
            "Economía",
            "Estado",
            "Gobierno_de_España",
            "PP",
            "CC",
            "PP",
            "Consejería",
            "PP",
            "País_Vasco",
            "CCAA",
            "PP",
            "Gobierno",
            "Ministerio",
            "Dependencia",
            "CC",
            "PP",
            "Gobierno",
            "Gobierno",
            "Estado",
            "PSC-PSOE",
            "Ejecutivo",
            "Gobierno_de_España",
            "Dependencia",
            "Gobierno"
        ],
        "others": [
            "Bienestar_Social",
            "Hacienda",
            "Ley_de_Dependencia",
            "Bienestar_Social",
            "Ley",
            "Luengo",
            "Ley_de_Dependencia",
            "Ley",
            "Ley_de_la_Dependencia",
            "Ley"
        ],
        "dates": [
            "[??:1/1/2007:??.??:??]",
            "[??:??/3/2008:??.??:??]",
            "[??:1/2/2010:??.??:??]",
            "[??:1/2/2010:??.??:??]",
            "[??:??/6/??:??.??:??]",
            "[??:25/1/??:??.??:??]"
        ],
        "numbers": [
            "19.293",
            "2007",
            "19.293",
            "15",
            "19.293",
            "7",
            "30",
            "67.301",
            "77.094",
            "3,23",
            "100",
            "3,55",
            "100",
            "25.5",
            "1,21",
            "100",
            "2,49",
            "100",
            "2",
            "19.293",
            "0,92",
            "100",
            "2,24",
            "100",
            "2,75",
            "100",
            "3,19",
            "100",
            "57.28",
            "69.296",
            "6.809",
            "0,32",
            "100",
            "1,08",
            "100",
            "4",
            "5",
            "26.514",
            "33.727",
            "1.5",
            "1.5",
            "80",
            "6",
            "6",
            "2007",
            "2009",
            "$_ECU:132000000",
            "30",
            "2007"
        ]
    }
}
