{
    "province": "LAS PALMAS",
    "date": "2010-02-15T00:00:00",
    "url": "https://www.20minutos.es/noticia/629643/0/",
    "title": {
        "raw_text": "Alcohol, tabaco y cannabis son las drogas más consumidas por jóvenes canarios, aunque están por debajo de media nacional",
        "lemmatized_text": "alcohol tabaco y cannabis ser el droga más consumir por joven canario aunque estar por debajo_de media nacional",
        "lemmatized_text_reduced": "alcohol tabaco cannabis ser droga consumir joven canario estar media nacional",
        "persons": [
            "Alcohol"
        ],
        "locations": [],
        "organizations": [],
        "others": [],
        "dates": [],
        "numbers": []
    },
    "lead": {
        "raw_text": "El botellón de fin de semana aumenta; el 19,5% admite beber durante estos días",
        "lemmatized_text": "el botella de fin de semana aumentar el 19,5/100 admitir beber durante este día",
        "lemmatized_text_reduced": "botella fin semana aumentar admitir beber día",
        "persons": [],
        "locations": [],
        "organizations": [],
        "others": [],
        "dates": [],
        "numbers": [
            "19,5/100"
        ]
    },
    "body": {
        "raw_text": "El Alcohol, el tabaco y el cannabis son las tres drogas que más consumen los jóvenes canarios de entre 14 y 18 años, aunque la media en las islas de estas sustancias está por debajo de la media nacional, según se desprende de la Encuesta sobre Drogas a la Población Escolar de la Comunidad Autónoma de 2008, presentada hoy por la consejera de Sanidad del Gobierno regional, Mercedes Roldós, y el director general de Atención a las Drogodependencias, Fernando Gómez-Pomo, durante una rueda de prensa. \"El consumo de sustancias adictivas en Canarias disminuye respecto a la Encuesta Nacional sobre drogas. Esta encuesta es una herramienta que sirve para conocer las tendencias de consumo en los estudiantes de enseñanza secundaria en las islas, por lo que, de lo que se trata, es de orientar, con los resultados obtenidos en la encuesta, para reducir los consumos y atajar los problemas asociados al consumo de drogas\", dijo Roldós. La encuesta, que se hizo a 2.196 alumnos de Educación Secundaria Obligatoria (ESO), bachillerato y ciclos formativos de Grado Medio, permite establecer un análisis comparativo con los resultados de la encuesta escolar de ámbito estatal. \"Aquí —añadió—, el consumo de drogas en Canarias, disminuye en comparación a la media del Estado\". En este sentido, el alcohol sigue siendo la droga más consumida entre los jóvenes de entre 14 y 18 años, seguido del tabaco y el cannabis. Así, el 76 por ciento de los encuestados admitió haber consumido alcohol alguna vez en su vida; el 66,4 por ciento dijo haberlo hecho en los últimos 12 meses; y el 45,5 por ciento afirmó haber bebido en los últimos 30 días. Pese a estos datos, el consumo de alcohol en Canarias es menor que en el resto de España, ya que el 81,2 por ciento de los jóvenes españoles han bebido alcohol alguna vez en su vida; el 72,9 por ciento lo hizo en el último año; y el 58,5 por ciento en el último mes. Aumenta el botellón de fin de semana Por su parte, la Comunidad Autónoma ha experimentado un ligero ascenso en el número de jóvenes que se emborracha durante el fin de semana, puesto que dicho dato aumentó del 16,8 por ciento de 2006 hasta el 19,5 por ciento de 2008. Aunque ha subido la cantidad de jóvenes que bebe durante los viernes y sábados en las islas, la cifra está casi 10 puntos porcentuales por debajo de la media nacional, que se situó en el 29,1 por ciento. Al respecto, el director general de Atención a las Drogodependencias del Gobierno de Canarias, Fernando Gómez-Pamo, explicó que el consumo de fin de semana \"es fundamentalmente un consumo de combinados, lo que se conoce por cubata, en las calles o plazas\". \"Lo consiguen, que es un dato que nos tiene que preocupar, directamente. Estamos hablando de jóvenes de entre 14 y 18 años\", alertó. \"Si bien —continuó— globalmente ha disminuido el número de jóvenes que beben alcohol, sí que ha aumentado el número de jóvenes que se emborrachan en los consumos abusivos de fin de semana, que han aumentado ligeramente, siempre por debajo de la media nacional. Han bajado los jóvenes que consumen alcohol, pero los que lo hacen, lo hacen se forma más compulsiva los fines de semana\". En cuanto a la edad de inicio, en el caso del alcohol se ha situado en 14 años, cinco décimas por encima de la encuesta de 2006 y tres décimas superior a la media nacional, que se situó en 13,7 años. Sobre el tabaco, se ha colocado como la segunda sustancia más extendida entre los jóvenes de 14 a 18 años. El 28,8 por ciento de los encuestados declaró haber consumido alguna vez; el 21,5 por ciento haberlo hecho en el último año; y el 15,8 por ciento en durante el último mes. Disminuye el número de cigarrillos que fuman Por su parte, el número medio de cigarrillos que fuman al día ha disminuido de 5,3 que dijeron consumir en 2006 a los 3,8 de 2008. En la encuesta nacional, son 5 los cigarrillos al día por término medio. Aquí, la cantidad de encuestados que no fumó ningún cigarrillo durante el último mes pasó del 3,3 por ciento en 2006 al 25,8 por ciento de 2008. Sobre la edad de inicio al tabaquismo, se ha situado en 13,4 años, por debajo de la cifra nacional aunque en términos similares, 13,5 años. Respecto a las drogas ilegales, el cannabis, la cocaína, el speed, las anfetaminas, las sustancias volátiles y los tranquilizantes son sustancias que han aumentado en comparación con la encuesta de 2006, mientras que la cocaína, los alucinógenos y el éxtasis han bajado ligeramente. Aquí, tanto Roldós como Gómez-Pamo hicieron especial hincapié en que son las chicas las que consumen generalmente los tranquilizantes sin receta médica, ya que existen cifras superiores al nivel nacional. Las chicas de entre 14 y 18 años consiguen estas sustancias, entre otras formas, cogiéndolas de las que utilizan sus madres o abuelas. Finalmente, el 18,9 por ciento de los encuestados afirmaron haber consumido cannabis durante el último año, un porcentaje que es inferior a los datos del conjunto del Estado, que se situó en el 30,5 por ciento.",
        "lemmatized_text": "el alcohol el tabaco y el cannabis ser el 3 droga que más consumir el joven canario de entre 14 y 18 año aunque el media en el isla de este sustancia estar por debajo_de el media nacional según se desprender de el encuesta sobre drogas a el población_escolar_de_la_comunidad_autónoma de 2008 presentar hoy por el consejero de sanidad_del_gobierno regional mercedes_roldós y el director general de atención a el drogodependencias fernando_gómez-pomo durante uno rueda de prensa el consumo de sustancia adictivo en canarias disminuir respecto_a el encuesta_nacional sobre droga este encuesta ser uno herramienta que servir para conocer el tendencia de consumo en el estudiante de enseñanza secundario en el isla por el que de el que se tratar ser de orientar con el resultado obtener en el encuesta para reducir el consumo y atajar el problema asociar a el consumo de droga decir roldós el encuesta que se hacer a 2.196 alumno de educación_secundaria_obligatoria eso bachillerato y ciclo formativo de grado_medio permitir establecer uno análisis comparativo con el resultado de el encuesta escolar de ámbito estatal aquí añadir el consumo de droga en canarias disminuir en comparación a el media de el estado en este sentido el alcohol seguir ser el droga más consumir entre el joven de entre 14 y 18 año seguir de el tabaco y el cannabis así el 76 por 100 de el encuestar admitir haber consumir alcohol alguno vez en su vida el 66,4 por 100 decir haber lo hacer en el último 12 mes y el 45,5 por 100 afirmar haber beber en el último TM_d:30 pese_a este dato el consumo de alcohol en canarias ser menor que en el resto de españa ya_que el 81,2 por 100 de el joven español haber beber alcohol alguno vez en su vida el 72,9 por 100 lo hacer en el último año y el 58,5 por 100 en el último mes aumentar el botella de fin de semana por su parte el comunidad_autónoma haber experimentar uno ligero ascenso en el número de joven que se emborrachar durante el fin de semana poner que decir dato aumentar de el 16,8 por 100 de 2006 hasta el 19,5 por 100 de 2008 aunque haber subir el cantidad de joven que beber durante el [V:??/??/??:??.??:??] y sábado en el isla el cifra estar casi 10 punto porcentual por debajo_de el media nacional que se situar en el 29,1 por 100 a el respecto el director general de atención a el drogodependencias_del_gobierno_de_canarias fernando_gómez-pamo explicar que el consumo de fin de semana ser fundamentalmente uno consumo de combinado el que se conocer por cubata en el calle o plaza lo conseguir que ser uno dato que nos tener que preocupar directamente estar hablar de joven de entre 14 y 18 año alertar si bien continuar globalmente haber disminuir el número de joven que beber alcohol sí que haber aumentar el número de joven que se emborrachar en el consumo abusivo de fin de semana que haber aumentar ligeramente siempre por debajo_de el media nacional haber bajar el joven que consumir alcohol pero el que lo hacer lo hacer se formar más compulsivo el fin de semana en_cuanto_a el edad de inicio en el caso de el alcohol se haber situar en 14 año 5 décima por encima_de el encuesta de 2006 y 3 décima superior a el media nacional que se situar en 13,7 año sobre el tabaco se haber colocar como el 2 sustancia más extender entre el joven de 14 a 18 año el 28,8 por 100 de el encuestar declarar haber consumir alguno vez el 21,5 por 100 haber lo hacer en el último año y el 15,8 por 100 en durante el último mes disminuir el número de cigarrillo que fumar por su parte el número medio de cigarrillo que fumar a el día haber disminuir de 5,3 que decir consumir en 2006 a el 3,8 de 2008 en el encuesta nacional ser 5 el cigarrillo a el día por término medio aquí el cantidad de encuestar que no fumar ninguno cigarrillo durante el último mes pasar de el 3,3 por 100 en 2006 a el 25,8 por 100 de 2008 sobre el edad de inicio a el tabaquismo se haber situar en 13,4 año por debajo_de el cifra nacional aunque en término similar 13,5 año respecto_a el droga ilegal el cannabis el cocaína el speed el anfetamina el sustancia volátil y el tranquilizante ser sustancia que haber aumentar en comparación con el encuesta de 2006 mientras_que el cocaína el alucinógeno y el éxtasis haber bajar ligeramente aquí tanto roldós como gómez-pamo hacer especial hincapié en que ser el chico el que consumir generalmente el tranquilizante sin receta médico ya_que existir cifra superior a el nivel nacional el chico de entre 14 y 18 año conseguir este sustancia entre otro forma coger lo de el que utilizar su madre o abuelo finalmente el 18,9 por 100 de el encuestar afirmar haber consumir cannabis durante el último año uno porcentaje que ser inferior a el dato de el conjunto de el estado que se situar en el 30,5 por 100",
        "lemmatized_text_reduced": "alcohol tabaco cannabis ser droga consumir joven canario año media isla sustancia estar media nacional desprender encuesta drogas población_escolar_de_la_comunidad_autónoma presentar consejero sanidad_del_gobierno regional mercedes_roldós director general atención drogodependencias fernando_gómez-pomo rueda prensa consumo sustancia adictivo canarias disminuir encuesta_nacional droga encuesta ser herramienta servir conocer tendencia consumo estudiante enseñanza secundario isla tratar ser orientar resultado obtener encuesta reducir consumo atajar problema asociar consumo droga decir roldós encuesta hacer alumno educación_secundaria_obligatoria eso bachillerato ciclo formativo grado_medio permitir establecer análisis comparativo resultado encuesta escolar ámbito estatal añadir consumo droga canarias disminuir comparación media estado sentido alcohol seguir ser droga consumir joven año seguir tabaco cannabis encuestar admitir haber consumir alcohol vez vida decir haber hacer último mes afirmar haber beber último dato consumo alcohol canarias ser menor resto españa joven español haber beber alcohol vez vida hacer último año último mes aumentar botella fin semana por parte comunidad_autónoma haber experimentar ligero ascenso número joven emborrachar fin semana poner decir dato aumentar haber subir cantidad joven beber sábado isla cifra estar punto porcentual media nacional situar respecto director general atención drogodependencias_del_gobierno_de_canarias fernando_gómez-pamo explicar consumo fin semana ser fundamentalmente consumo combinado conocer cubata calle plaza conseguir ser dato tener preocupar directamente estar hablar joven año alertar continuar globalmente haber disminuir número joven beber alcohol haber aumentar número joven emborrachar consumo abusivo fin semana haber aumentar ligeramente media nacional haber bajar joven consumir alcohol hacer hacer formar compulsivo fin semana edad inicio caso alcohol haber situar año décima encuesta décima superior media nacional situar año tabaco haber colocar 2 sustancia extender joven año encuestar declarar haber consumir vez haber hacer último año último mes disminuir número cigarrillo fumar por parte número medio cigarrillo fumar día haber disminuir decir consumir encuesta nacional ser cigarrillo día término medio cantidad encuestar fumar cigarrillo último mes pasar edad inicio tabaquismo haber situar año cifra nacional término similar año droga ilegal cannabis cocaína speed anfetamina sustancia volátil tranquilizante ser sustancia haber aumentar comparación encuesta cocaína alucinógeno éxtasis haber bajar ligeramente roldós gómez-pamo hacer especial hincapié ser chico consumir generalmente tranquilizante receta médico existir cifra superior nivel nacional chico año conseguir sustancia forma coger utilizar madre abuelo finalmente encuestar afirmar haber consumir cannabis último año porcentaje ser inferior dato conjunto estado situar",
        "persons": [
            "Mercedes_Roldós",
            "Fernando_Gómez-Pomo",
            "Roldós",
            "Fernando_Gómez-Pamo",
            "Roldós"
        ],
        "locations": [
            "Drogas",
            "Canarias",
            "Canarias",
            "Canarias",
            "España"
        ],
        "organizations": [
            "Alcohol",
            "Encuesta",
            "Población_Escolar_de_la_Comunidad_Autónoma",
            "Sanidad_del_Gobierno",
            "Atención",
            "Drogodependencias",
            "Encuesta_Nacional",
            "Estado",
            "Por",
            "Comunidad_Autónoma",
            "Atención",
            "Drogodependencias_del_Gobierno_de_Canarias",
            "Por",
            "Gómez-Pamo",
            "Estado"
        ],
        "others": [
            "Educación_Secundaria_Obligatoria",
            "ESO",
            "Grado_Medio"
        ],
        "dates": [
            "[V:??/??/??:??.??:??]"
        ],
        "numbers": [
            "3",
            "14",
            "18",
            "2008",
            "2.196",
            "14",
            "18",
            "76",
            "100",
            "66,4",
            "100",
            "12",
            "45,5",
            "100",
            "TM_d:30",
            "81,2",
            "100",
            "72,9",
            "100",
            "58,5",
            "100",
            "16,8",
            "100",
            "2006",
            "19,5",
            "100",
            "2008",
            "10",
            "29,1",
            "100",
            "14",
            "18",
            "14",
            "5",
            "2006",
            "3",
            "13,7",
            "14",
            "18",
            "28,8",
            "100",
            "21,5",
            "100",
            "15,8",
            "100",
            "5,3",
            "2006",
            "3,8",
            "2008",
            "5",
            "3,3",
            "100",
            "2006",
            "25,8",
            "100",
            "2008",
            "13,4",
            "13,5",
            "2006",
            "14",
            "18",
            "18,9",
            "100",
            "30,5",
            "100"
        ]
    }
}
