{
    "province": "LAS PALMAS",
    "date": "2010-04-16T00:00:00",
    "url": "https://www.20minutos.es/noticia/680193/0/",
    "title": {
        "raw_text": "Spanair ofrece este verano más de un millón de asientos a Canarias repartidos en 25 rutas",
        "lemmatized_text": "spanair ofrecer este verano más de 1000000 de asiento a canarias repartir en 25 ruta",
        "lemmatized_text_reduced": "spanair ofrecer verano asiento canarias repartir ruta",
        "persons": [],
        "locations": [
            "Canarias"
        ],
        "organizations": [
            "Spanair"
        ],
        "others": [],
        "dates": [],
        "numbers": [
            "1000000",
            "25"
        ]
    },
    "lead": {
        "raw_text": "Amplía su mapa de rutas con vuelos a Dubrovnik y Malta desde Barcelona",
        "lemmatized_text": "ampliar su mapa de ruta con vuelo a dubrovnik y malta desde barcelona",
        "lemmatized_text_reduced": "ampliar mapa ruta vuelo dubrovnik malta barcelona",
        "persons": [],
        "locations": [
            "Dubrovnik",
            "Barcelona"
        ],
        "organizations": [
            "Malta"
        ],
        "others": [],
        "dates": [],
        "numbers": []
    },
    "body": {
        "raw_text": "La compañía Spanair ofrece este verano más de un millón de asientos a Canarias repartidos en 25 rutas a distintos puntos de la geografía española. Además, Spanair conecta directamente Barcelona con Lanzarote, Fuerteventura, Tenerife (Norte y Sur) y Gran Canaria operando casi 900 vuelos mensuales entre la Península y Canarias, informa la empresa en un comunicado. Respecto al archipiélago balear Spanair ofrece este verano más de 1,4 millones de asientos, con más de 1.300 vuelos al mes que conectan Madrid y Barcelona con Menorca, Ibiza y Mallorca además de la conexión que cada domingo une Palma y Argel. Dos nuevos destinos desde barcelona Asimismo, Spanair ha ampliado su mapa de rutas para este verano con dos nuevos destinos a Dubrovnik y Malta desde Barcelona. La compañía asegura que \"por primera vez una aerolínea española vuela a las dos principales ciudades de Croacia (Zagreb y Dubrovnik) permitiendo la entrada en el país por una de ellas y la salida por otra\". De esta forma se da respuesta a una demanda del mercado turístico interesado en conocer Croacia por vía terrestre y que obligaba, hasta ahora, a regresar a la ciudad donde se aterrizaba. Los vuelos entre Barcelona y Dubrovnik se operarán los lunes, miércoles y viernes igual como la conexión con Zagreb que se hará en esos mismos días de la semana. La isla mediterránea de Malta es otro de los nuevos destinos operados por Spanair esta temporada desde Barcelona cada viernes y domingo. La ampliación de las nuevas rutas desde Barcelona responde al objetivo estratégico de Spanair de dotar al aeropuerto de El Prat de los suficientes vuelos de corto y medio radio como para poderlo convertir en un hub de vuelos intercontinentales gracias a Spanair y Star Alliance. Tras la inauguración ayer del primer vuelo a Belgrado, Spanair conecta Barcelona con 16 conexiones internacionales directas a Edimburgo, Birmingham, Venecia, Zagreb, Dubrovnik, Malta, Estambul, Tel Aviv, Nador, Argel, Banjul, Copenhague, Estocolmo, Marsella y Munich. Madrid y edimburgo , Más cerca Spanair también ha ampliado sus rutas desde Madrid con la nueva conexión los lunes, miércoles y viernes a la ciudad escocesa de Edimburgo. Con esta nueva ruta, Spanair ya enlaza directamente Madrid con Belgrado, Birmingham, Copenhaguen, Edimburgo y Frankfurt. La apuesta por Málaga. Esta temporada Spanair ha apostado por la nueva Terminal del aeropuerto de Málaga y ha ampliado los vuelos internacionales desde la ciudad andaluza. Tánger y Marrakech contarán con dos vuelos semanales y Venecia estará conectada cada miércoles y sábado. Desde Málaga Spanair también ofrece dos conexiones directas semanales, los sábados y domingos a Copenhaguen además de operar a partir de julio un vuelo semanal directo a Fuerteventura. Gracias a los 4 vuelos diarios entre Barcelona y Málaga y a los 2 entre Madrid y Málaga, Spanair garantiza a sus pasajeros la posibilidad de conectar con un gran número de vuelos internacionales.",
        "lemmatized_text": "el compañía spanair ofrecer este verano más de 1000000 de asiento a canarias repartir en 25 ruta a distinto punto de el geografía español además spanair conectar directamente barcelona con lanzarote fuerteventura tenerife norte y sur y gran_canaria operar casi 900 vuelo mensual entre el península y canarias informar el empresa en uno comunicado respecto a el archipiélago balear spanair ofrecer este verano más de 1,4 millón de asiento con más de 1.3 vuelo a el mes que conectar madrid y barcelona con menorca ibiza y mallorca además_de el conexión que cada [G:??/??/??:??.??:??] unir palma y argel 2 nuevo destino desde barcelona asimismo spanair haber ampliar su mapa de ruta para este verano con 2 nuevo destino a dubrovnik y malta desde barcelona el compañía asegurar que por 1 vez uno aerolínea español volar a el 2 principal ciudad de croacia zagreb y dubrovnik permitir el entrada en el país por uno de ellos y el salida por otro de este forma se dar respuesta a uno demanda de el mercado turístico interesar en conocer croacia por vía terrestre y que obligar hasta ahora a regresar a el ciudad donde se aterrizar el vuelo entre barcelona y dubrovnik se operar el [L:??/??/??:??.??:??] [X:??/??/??:??.??:??] y [V:??/??/??:??.??:??] igual como el conexión con zagreb que se hacer en ese mismo día de el semana el isla mediterráneo de malta ser otro de el nuevo destino operar por spanair este temporada desde barcelona cada [V:??/??/??:??.??:??] y [G:??/??/??:??.??:??] el ampliación de el nuevo ruta desde barcelona responder a el objetivo estratégico de spanair de dotar a el aeropuerto de el_prat de el suficiente vuelo de corto y medio radio como para poder lo convertir en uno hub de vuelo intercontinental gracias_a spanair y star_alliance tras el inauguración ayer de el 1 vuelo a belgrado spanair conectar barcelona con 16 conexión internacional directo a edimburgo birmingham venecia zagreb dubrovnik malta estambul tel_aviv nador argel banjul copenhague estocolmo marsella y munich madrid y edimburgo más cerca spanair también haber ampliar su ruta desde madrid con el nuevo conexión el [L:??/??/??:??.??:??] [X:??/??/??:??.??:??] y [V:??/??/??:??.??:??] a el ciudad escocés de edimburgo con este nuevo ruta spanair ya enlazar directamente madrid con belgrado birmingham copenhaguen edimburgo y frankfurt el apuesta por málaga este temporada spanair haber apostar por el nuevo terminal de el aeropuerto de málaga y haber ampliar el vuelo internacional desde el ciudad andaluz tánger y marrakech contar con 2 vuelo semanal y venecia estar conectar cada [X:??/??/??:??.??:??] y [S:??/??/??:??.??:??] desde málaga_spanair también ofrecer 2 conexión directo semanal el sábado y domingo a copenhaguen además_de operar a_partir_de [??:??/7/??:??.??:??] uno vuelo semanal directo a fuerteventura gracias_a el 4 vuelo diario entre barcelona y málaga y a el 2 entre madrid y málaga spanair garantizar a su pasajero el posibilidad de conectar con uno gran número de vuelo internacional",
        "lemmatized_text_reduced": "compañía spanair ofrecer verano asiento canarias repartir ruta punto geografía español spanair conectar directamente barcelona lanzarote fuerteventura tenerife norte sur gran_canaria operar vuelo mensual península canarias informar empresa comunicado respecto archipiélago balear spanair ofrecer verano millón asiento vuelo mes conectar madrid barcelona menorca ibiza mallorca conexión unir palma argel nuevo destino barcelona asimismo spanair haber ampliar mapa ruta verano nuevo destino dubrovnik malta barcelona compañía asegurar 1 vez aerolínea español volar principal ciudad croacia zagreb dubrovnik permitir entrada país salida forma dar respuesta demanda mercado turístico interesar conocer croacia vía terrestre obligar regresar ciudad aterrizar vuelo barcelona dubrovnik operar conexión zagreb hacer mismo día semana isla mediterráneo malta ser nuevo destino operar spanair temporada barcelona ampliación nuevo ruta barcelona responder objetivo estratégico spanair dotar aeropuerto el_prat suficiente vuelo corto medio radio poder convertir hub vuelo intercontinental spanair star_alliance inauguración 1 vuelo belgrado spanair conectar barcelona conexión internacional directo edimburgo birmingham venecia zagreb dubrovnik malta estambul tel_aviv nador argel banjul copenhague estocolmo marsella munich madrid edimburgo más spanair haber ampliar ruta madrid nuevo conexión ciudad escocés edimburgo nuevo ruta spanair enlazar directamente madrid belgrado birmingham copenhaguen edimburgo frankfurt apuesta málaga temporada spanair haber apostar nuevo terminal aeropuerto málaga haber ampliar vuelo internacional ciudad andaluz tánger marrakech contar vuelo semanal venecia estar conectar málaga_spanair ofrecer conexión directo semanal sábado domingo copenhaguen operar vuelo semanal directo fuerteventura vuelo diario barcelona málaga madrid málaga spanair garantizar pasajero posibilidad conectar gran número vuelo internacional",
        "persons": [
            "Palma",
            "Star_Alliance",
            "Edimburgo",
            "Más",
            "Tánger",
            "Marrakech",
            "Málaga_Spanair"
        ],
        "locations": [
            "Canarias",
            "Lanzarote",
            "Tenerife",
            "Norte",
            "Gran_Canaria",
            "Madrid",
            "Menorca",
            "Ibiza",
            "Mallorca",
            "Argel",
            "Dubrovnik",
            "Barcelona",
            "Croacia",
            "Zagreb",
            "Croacia",
            "Barcelona",
            "Dubrovnik",
            "Zagreb",
            "Malta",
            "Barcelona",
            "Barcelona",
            "El_Prat",
            "Belgrado",
            "Barcelona",
            "Venecia",
            "Zagreb",
            "Nador",
            "Copenhague",
            "Estocolmo",
            "Marsella",
            "Munich",
            "Madrid",
            "Madrid",
            "Edimburgo",
            "Madrid",
            "Edimburgo",
            "Frankfurt",
            "Málaga",
            "Málaga",
            "Málaga",
            "Madrid",
            "Málaga"
        ],
        "organizations": [
            "Spanair",
            "Spanair",
            "Barcelona",
            "Fuerteventura",
            "Sur",
            "Península",
            "Canarias",
            "Spanair",
            "Barcelona",
            "Spanair",
            "Malta",
            "Dubrovnik",
            "Spanair",
            "Spanair",
            "Spanair",
            "Spanair",
            "Birmingham",
            "Dubrovnik",
            "Malta",
            "Estambul",
            "Tel_Aviv",
            "Argel",
            "Banjul",
            "Spanair",
            "Spanair",
            "Belgrado",
            "Birmingham",
            "Copenhaguen",
            "Spanair",
            "Terminal",
            "Venecia",
            "Copenhaguen",
            "Fuerteventura",
            "Barcelona",
            "Spanair"
        ],
        "others": [
            "Asimismo"
        ],
        "dates": [
            "[G:??/??/??:??.??:??]",
            "[L:??/??/??:??.??:??]",
            "[X:??/??/??:??.??:??]",
            "[V:??/??/??:??.??:??]",
            "[V:??/??/??:??.??:??]",
            "[G:??/??/??:??.??:??]",
            "[L:??/??/??:??.??:??]",
            "[X:??/??/??:??.??:??]",
            "[V:??/??/??:??.??:??]",
            "[X:??/??/??:??.??:??]",
            "[S:??/??/??:??.??:??]",
            "[??:??/7/??:??.??:??]"
        ],
        "numbers": [
            "1000000",
            "25",
            "900",
            "1,4",
            "1.3",
            "2",
            "2",
            "2",
            "16",
            "2",
            "2",
            "4",
            "2"
        ]
    }
}
