{
    "province": "LAS PALMAS",
    "date": "2011-01-14T00:00:00",
    "url": "https://www.20minutos.es/noticia/928473/0/",
    "title": {
        "raw_text": "El presidente del Cabildo de Gran Canaria: \"El responsable de ese incendio tiene nombre y apellidos\"",
        "lemmatized_text": "el presidente de el cabildo_de_gran_canaria el responsable de ese incendio tener nombre y apellido",
        "lemmatized_text_reduced": "presidente cabildo_de_gran_canaria responsable incendio tener nombre apellido",
        "persons": [],
        "locations": [],
        "organizations": [
            "Cabildo_de_Gran_Canaria"
        ],
        "others": [],
        "dates": [],
        "numbers": []
    },
    "lead": {
        "raw_text": "El presidente del Cabildo de Gran Canaria, José Miguel Pérez (PSOE), ha incidido este viernes en que el responsable del incendio que sufrió la isla en 2007 \"tiene nombre y apellidos\".",
        "lemmatized_text": "el presidente de el cabildo_de_gran_canaria josé_miguel_pérez psoe haber incidir este [V:??/??/??:??.??:??] en que el responsable de el incendio que sufrir el isla en 2007 tener nombre y apellido",
        "lemmatized_text_reduced": "presidente cabildo_de_gran_canaria josé_miguel_pérez psoe haber incidir responsable incendio sufrir isla tener nombre apellido",
        "persons": [
            "José_Miguel_Pérez"
        ],
        "locations": [],
        "organizations": [
            "Cabildo_de_Gran_Canaria",
            "PSOE"
        ],
        "others": [],
        "dates": [
            "[V:??/??/??:??.??:??]"
        ],
        "numbers": [
            "2007"
        ]
    },
    "body": {
        "raw_text": "El presidente del Cabildo de Gran Canaria, José Miguel Pérez (PSOE), ha incidido este viernes en que el responsable del incendio que sufrió la isla en 2007 \"tiene nombre y apellidos\". \"El responsable de ese incendio tiene nombre y apellidos, y entre otras cosas, lo ha reconocido así. El responsable principal, real, está ahí. Esta persona trabajaba contratada por una empresa del Gobierno de Canarias. Esto no significa que ni esa empresa ni el Gobierno de Canarias lo consideremos nosotros responsables o culpable pero esa era la realidad en una encomienda que hizo mi antecesor\", apuntilló en rueda de prensa. De esta forma, se mostró al ser cuestionado por su opinión sobre la alegación de los servicios jurídicos del Gobierno de Canarias respecto a que sea la institución insular la que asuma las indemnizaciones del incendio de 2007. Pérez incidió en que el Cabildo de Gran Canaria \"no se considera responsable\" de dicho incendio porque \"hay dos cosas distintas\". En este sentido, dijo que por un lado está lo que \"es el derecho que tienen las personas afectadas, que se vieron terriblemente afectadas a reclamar, y otra cosa es imputar la responsabilidad al bolsillo de los ciudadanos\". Ante ello, hizo hincapié en que, por dicho motivo, la institución insular defenderá con \"uñas y dientes que no, que no tiene el resto de ciudadanos la culpa de que haya un individuo que fuera de su horario laboral haya ido a pegarle fuego a la isla de Gran Canaria\". Finalmente, señaló que tras reunirse este viernes con el consejero canario de Medio Ambiente, Domingo Berriel, no le ha dicho que el Cabildo de Gran Canaria \"tiene esa responsabilidad\".",
        "lemmatized_text": "el presidente de el cabildo_de_gran_canaria josé_miguel_pérez psoe haber incidir este [V:??/??/??:??.??:??] en que el responsable de el incendio que sufrir el isla en 2007 tener nombre y apellido el responsable de ese incendio tener nombre y apellido y entre otro cosa lo haber reconocer así el responsable principal real estar ahí este persona trabajar contratar por uno empresa de el gobierno_de_canarias este no significar que ni ese empresa ni el gobierno_de_canarias lo considerar nosotros responsable o culpable pero ese ser el realidad en uno encomienda que hacer mi antecesor apuntillar en rueda de prensa de este forma se mostrar a el ser cuestionar por su opinión sobre el alegación de el servicio jurídico de el gobierno_de_canarias respecto_a que ser el institución insular el que asumir el indemnización de el incendio de 2007 pérez incidir en que el cabildo_de_gran_canaria no se considerar responsable de decir incendio porque haber 2 cosa distinto en este sentido decir que por uno lado estar el que ser el derecho que tener el persona afectar que se ver terriblemente afectar a reclamar y otro cosa ser imputar el responsabilidad a el bolsillo de el ciudadano ante ello hacer hincapié en que por decir motivo el institución insular defender con uña y diente que no que no tener el resto de ciudadano el culpa de que haber uno individuo que fuera_de su horario laboral haber ir a pegar le fuego a el isla de gran_canaria finalmente señalar que tras reunir se este [V:??/??/??:??.??:??] con el consejero canario de medio_ambiente [G:??/??/??:??.??:??] berriel no le haber decir que el cabildo_de_gran_canaria tener ese responsabilidad",
        "lemmatized_text_reduced": "presidente cabildo_de_gran_canaria josé_miguel_pérez psoe haber incidir responsable incendio sufrir isla tener nombre apellido responsable incendio tener nombre apellido cosa haber reconocer responsable principal real estar persona trabajar contratar empresa gobierno_de_canarias significar empresa gobierno_de_canarias considerar responsable culpable ser realidad encomienda hacer antecesor apuntillar rueda prensa forma mostrar ser cuestionar opinión alegación servicio jurídico gobierno_de_canarias ser institución insular asumir indemnización incendio pérez incidir cabildo_de_gran_canaria considerar responsable decir incendio haber cosa distinto sentido decir lado estar ser derecho tener persona afectar ver terriblemente afectar reclamar cosa ser imputar responsabilidad bolsillo ciudadano hacer hincapié decir motivo institución insular defender uña diente tener resto ciudadano culpa haber individuo horario laboral haber ir pegar fuego isla gran_canaria finalmente señalar reunir consejero canario medio_ambiente berriel haber decir cabildo_de_gran_canaria tener responsabilidad",
        "persons": [
            "José_Miguel_Pérez",
            "Pérez",
            "Berriel"
        ],
        "locations": [
            "Gran_Canaria"
        ],
        "organizations": [
            "Cabildo_de_Gran_Canaria",
            "PSOE",
            "Gobierno_de_Canarias",
            "Gobierno_de_Canarias",
            "Gobierno_de_Canarias",
            "Cabildo_de_Gran_Canaria",
            "Medio_Ambiente",
            "Cabildo_de_Gran_Canaria"
        ],
        "others": [],
        "dates": [
            "[V:??/??/??:??.??:??]",
            "[V:??/??/??:??.??:??]",
            "[G:??/??/??:??.??:??]"
        ],
        "numbers": [
            "2007",
            "2007",
            "2"
        ]
    }
}
