{
    "province": "LAS PALMAS",
    "date": "2010-01-05T00:00:00",
    "url": "https://www.20minutos.es/noticia/600681/0/",
    "title": {
        "raw_text": "Los décimos con terminaciones en 69, 13 y 22 los que más solicitan para 'El Niño' en la provincia de Las Palmas",
        "lemmatized_text": "el décimo con terminación en 69 13 y 22 el que más solicitar para el niño en el provincia de las_palmas",
        "lemmatized_text_reduced": "décimo terminación solicitar niño provincia las_palmas",
        "persons": [
            "Niño"
        ],
        "locations": [
            "Las_Palmas"
        ],
        "organizations": [],
        "others": [],
        "dates": [],
        "numbers": [
            "69",
            "13",
            "22"
        ]
    },
    "lead": {
        "raw_text": "El responsable en la provincia de Las Palmas de la Delegación Comercial de Loterías y Apuestas del Estado, Juan Manuel Moraga, señaló hoy que los décimos con terminaciones en 69, 13 y 22 son los que más se solicitan para el sorteo extraordinario de 'El Niño' en dicha provincia.",
        "lemmatized_text": "el responsable en el provincia de las_palmas_de_la_delegación_comercial_de_loterías y apuestas_del_estado juan_manuel_moraga señalar hoy que el décimo con terminación en 69 13 y 22 ser el que más se solicitar para el sorteo extraordinario de el niño en decir provincia",
        "lemmatized_text_reduced": "responsable provincia las_palmas_de_la_delegación_comercial_de_loterías apuestas_del_estado juan_manuel_moraga señalar décimo terminación ser solicitar sorteo extraordinario niño decir provincia",
        "persons": [
            "Juan_Manuel_Moraga",
            "Niño"
        ],
        "locations": [],
        "organizations": [
            "Las_Palmas_de_la_Delegación_Comercial_de_Loterías",
            "Apuestas_del_Estado"
        ],
        "others": [],
        "dates": [],
        "numbers": [
            "69",
            "13",
            "22"
        ]
    },
    "body": {
        "raw_text": "De todos modos, Moraga indicó que se \"suelen pedir las mismas\" terminaciones que para la lotería de Navidad aunque afirmó, en declaraciones a Europa Press, que se solicitan \"casi más\" los décimos que terminan en números impares que en pares. Respecto a las perspectivas de venta de lotería para 'El Niño' indicó que este año son un \"poco mejor\" que en 2009, por lo que \"no se espera la bajada que hubo el año pasado\". Añadió que esto podría deberse a que ha habido \"mucho reintegro y mucha pedrea\" en el sorteo de Navidad \"y entonces normalmente se reinvierte mucho\". En cuanto a la consignación que en la provincia de Las Palmas tiene el sorteo de 'El Niño' este año se ha fijado en \"17,5 millones de euros\". En canarias , 35,8 Millones en décimos En el conjunto de la Comunidad Autónoma de Canarias, el archipiélago se sitúa como la undécima región española donde más lotería de 'El Niño' se vende, con un total de 35,8 millones de euros, según la información facilitada hoy por Loterías y Apuestas del Estado (LAE) en nota de prensa. La media nacional de venta de lotería de 'El Niño' es de 23,21 euros por habitante y de un gasto total de más de un millón de euros (1.048.936 euros), cuando están pendientes de consignar en el conjunto del país 151.064.000 euros (755.320 billetes) para alcanzar el total de emisión previsto en 1.200 millones de euros con 6 millones de billetes. Por comunidades autónomas, el lugar donde más lotería de 'El Niño' se ha vendido es la Comunidad Valenciana con 154,44 millones. En segundo lugar está Madrid, con un total de 149,9 millones de euros, le siguen Cataluña, con 140,7 millones y Andalucía, con 139.97 millones. Asimismo, por encima de Asturias (34,5 millones) se sitúan Castilla y León (84,06 millones); País Vasco (63,2 millones); Galicia (57,57 millones); Castilla-La Mancha (46,69 millones); Murcia (40,12 millones); y Canarias (35,8 millones). Por detrás del Principado están Aragón (32,58 millones); Extremadura (18,17 millones); Baleares (15,13 millones); Cantabria (13,51 millones); Navarra (11,85 millones); La Rioja (9,36 millones); Ceuta (641,800 euros) y Melilla (508.400 euros).",
        "lemmatized_text": "de_todos_modos moraga indicar que se soler pedir el mismo terminación que para el lotería de navidad aunque afirmar en declaración a europa_press que se solicitar casi más el décimo que terminar en número impar que en par respecto_a el perspectiva de venta de lotería para el niño indicar que este año ser uno poco mejor que en 2009 por el que no se esperar el bajada que haber el año pasar añadir que este poder deber se a que haber haber mucho reintegro y mucho pedrea en el sorteo de navidad y entonces normalmente se reinvertir mucho en_cuanto_a el consignación que en el provincia de las_palmas tener el sorteo de el niño este año se haber fijar en 17,5 millón de euro en canario 35,8 millones en décimo en el conjunto de el comunidad_autónoma_de_canarias el archipiélago se situar como el 11 región español donde más lotería de el niño se vender con uno total de 35,8 millón de euro según el información facilitar hoy por loterías y apuestas_del_estado lae en nota de prensa el media nacional de venta de lotería de el niño ser de $_ECU:23,21 por habitante y de uno gasto total de más de $_ECU:1000000 $_ECU:1.048.936 cuando estar pendiente de consignar en el conjunto de el país $_ECU:151.064.000 755.32 billete para alcanzar el total de emisión prever en $_ECU:1200000 con 6000000 de billete por comunidad autónomo el lugar donde más lotería de el niño se haber vender ser el comunidad_valenciana con 154,44 millón en 2 lugar estar madrid con uno total de 149,9 millón de euro le seguir cataluña con 140,7 millón y andalucía con 139970000 asimismo por encima_de asturias 34,5 millón se situar castilla y león 84,06 millón país_vasco 63,2 millón galicia 57,57 millón castilla-la_mancha 46,69 millón murcia 40,12 millón y canarias 35,8 millón por detrás de el principado estar aragón 32,58 millón extremadura 18,17 millón baleares 15,13 millón cantabria 13,51 millón navarra 11,85 millón la_rioja 9,36 millón ceuta $_ECU:641800 y melilla $_ECU:508.4",
        "lemmatized_text_reduced": "moraga indicar soler pedir mismo terminación lotería navidad afirmar declaración europa_press solicitar décimo terminar número impar par perspectiva venta lotería niño indicar año ser mejor esperar bajada haber año pasar añadir poder deber haber haber reintegro pedrea sorteo navidad normalmente reinvertir consignación provincia las_palmas tener sorteo niño año haber fijar millón euro canario millones décimo en conjunto comunidad_autónoma_de_canarias archipiélago situar 11 región español lotería niño vender total millón euro información facilitar loterías apuestas_del_estado lae nota prensa media nacional venta lotería niño ser habitante gasto total estar pendiente consignar conjunto país billete alcanzar total emisión prever billete comunidad autónomo lugar lotería niño haber vender ser comunidad_valenciana millón 2 lugar estar madrid total millón euro seguir cataluña millón andalucía asturias millón situar castilla león millón país_vasco millón galicia millón castilla-la_mancha millón murcia millón canarias millón principado estar aragón millón extremadura millón baleares millón cantabria millón navarra millón la_rioja millón ceuta melilla",
        "persons": [
            "Moraga",
            "Europa_Press",
            "Niño",
            "Niño",
            "Niño",
            "Loterías",
            "Niño",
            "Niño",
            "León"
        ],
        "locations": [
            "Las_Palmas",
            "Madrid",
            "Cataluña",
            "Andalucía",
            "Asturias",
            "Castilla",
            "País_Vasco",
            "Galicia",
            "Castilla-La_Mancha",
            "Murcia",
            "Canarias",
            "Aragón",
            "Extremadura",
            "Baleares",
            "Cantabria",
            "Navarra",
            "La_Rioja",
            "Ceuta",
            "Melilla"
        ],
        "organizations": [
            "En",
            "Comunidad_Autónoma_de_Canarias",
            "Apuestas_del_Estado",
            "LAE",
            "Comunidad_Valenciana",
            "Principado"
        ],
        "others": [
            "Navidad",
            "Navidad",
            "Millones"
        ],
        "dates": [],
        "numbers": [
            "2009",
            "17,5",
            "35,8",
            "35,8",
            "$_ECU:23,21",
            "$_ECU:1000000",
            "$_ECU:1.048.936",
            "$_ECU:151.064.000",
            "755.32",
            "$_ECU:1200000",
            "6000000",
            "154,44",
            "149,9",
            "140,7",
            "139970000",
            "34,5",
            "84,06",
            "63,2",
            "57,57",
            "46,69",
            "40,12",
            "35,8",
            "32,58",
            "18,17",
            "15,13",
            "13,51",
            "11,85",
            "9,36",
            "$_ECU:641800",
            "$_ECU:508.4"
        ]
    }
}
