{
    "province": "LAS PALMAS",
    "date": "2011-01-25T00:00:00",
    "url": "https://www.20minutos.es/noticia/939572/0/",
    "title": {
        "raw_text": "La Aemet mantiene la alerta por viento y oleaje en Tenerife, Gran Canaria, Lanzarote y Fuerteventura",
        "lemmatized_text": "el aemet mantener el alerta por viento y oleaje en tenerife gran_canaria lanzarote y fuerteventura",
        "lemmatized_text_reduced": "aemet mantener alerta viento oleaje tenerife gran_canaria lanzarote fuerteventura",
        "persons": [],
        "locations": [
            "Lanzarote"
        ],
        "organizations": [
            "Aemet",
            "Tenerife",
            "Gran_Canaria",
            "Fuerteventura"
        ],
        "others": [],
        "dates": [],
        "numbers": []
    },
    "lead": {
        "raw_text": "La borrasca en Canarias tiende a remitir, si bien la Agencia Estatal de Meteorología (Aemet) mantiene para este miércoles la alerta amarilla por riesgo de oleaje y rachas máximas de viento que podrán alcanzar los 85 kilómetros por hora en el norte de Tenerife y Gran Canaria, así como en las islas de Lanzarote y Fuerteventura.",
        "lemmatized_text": "el borrasca en canarias tender a remitir si bien el agencia_estatal_de_meteorología aemet mantener para este [X:??/??/??:??.??:??] el alerta amarillo por riesgo de oleaje y racha máximo de viento que poder alcanzar el SP_km/h:85 en el norte de tenerife y gran_canaria así_como en el isla de lanzarote y fuerteventura",
        "lemmatized_text_reduced": "borrasca canarias tender remitir agencia_estatal_de_meteorología aemet mantener alerta amarillo riesgo oleaje racha máximo viento poder alcanzar norte tenerife gran_canaria isla lanzarote fuerteventura",
        "persons": [],
        "locations": [
            "Canarias",
            "Gran_Canaria",
            "Lanzarote"
        ],
        "organizations": [
            "Agencia_Estatal_de_Meteorología",
            "Aemet",
            "Tenerife",
            "Fuerteventura"
        ],
        "others": [],
        "dates": [
            "[X:??/??/??:??.??:??]"
        ],
        "numbers": [
            "SP_km/h:85"
        ]
    },
    "body": {
        "raw_text": "La borrasca en Canarias tiende a remitir, si bien la Agencia Estatal de Meteorología (Aemet) mantiene para este miércoles la alerta amarilla por riesgo de oleaje y rachas máximas de viento que podrán alcanzar los 85 kilómetros por hora en el norte de Tenerife y Gran Canaria, así como en las islas de Lanzarote y Fuerteventura. En concreto, estas dos últimas ínsulas se verán afectadas especialmente por el temporal, ya que sufrirán rachas máximas de viento de hasta 80 kilómetros por hora hasta las 15.00 horas del miércoles; mientras que registrarán fenómenos costeros adversos hasta la medianoche del jueves, según datos de la Aemet recogidos por Europa Press. En Gran Canaria se prevén ráfagas de hasta 70 kilómetros por hora y fuerte oleaje en la costa norte, situación que persistirá hasta las siete de la mañana aproximadamente de este miércoles. En Tenerife, el viento azotará a la costa norte, con rachas de hasta 80 kilómetros por hora, y especialmente en La Orotava y Vilaflor, donde se vivirán hasta 85 kilómetros por hora. Además de oleaje en la costa norte de la isla. Olas de hasta 3 Metros de altura Así pues, las aguas costeras de la provincia de Santa Cruz de Tenerife serán del noroeste con fuerza cuatro a cinco con intervalos de fuerza seis. Con visibilidad buena a regular por lluvias y predomimio de la fuerte marejada. Habrá mar de fondo del norte a noroeste de dos metros ocasionalmente hasta los tres metros. En cuanto a la provincia de Las Palmas, la Aemet avisa de aguas costeras del oeste rolando pronto a noroeste fuerza cinco a seis con intervalos de fuerza siete al norte y oeste de Lanzarote y Fuerteventura, principalmente durante la primera mitad del día, así como visibilidad buena a regular por lluvias. Habrá fuerte marejada con áreas de mar gruesa en costas de Lanzarote y Fuerteventura y al principio en costas norte de Gran Canaria, y áreas de marejadilla en costas sur de esta isla durante la tarde. Se prevé mar de fondo del norte a noroeste de dos metros ocasionalmente hasta los tres metros. Un total de 26 Provincias en alerta Un total de 26 provincias estarán este miércoles en alerta por temperaturas mínimas que podrán alcanzar los 10 grados bajo cero en Aragón y Cataluña, según la Aemet. Así, las provincias de Guadalajara, Teruel, Zaragoza, Huesca, Lleida y Girona estarán en alerta naranja —riesgo importante— por bajas temperaturas, mientras que Lugo, Orense, Zamora, León, Palencia, Burgos, Ávila, Soria, Segovia, Asturias, Navarra, La Rioja, Madrid, Guadalajara, Cuenca, Valencia, Castellón, el resto de Aragón y Cataluña, Mallorca e Ibiza, estarán en alerta amarilla —riesgo— con temperaturas de entre ocho y cuatro grados negativos. De esta forma, las heladas serán de moderadas a fuertes en el centro y norte peninsular así como en Baleares permaneciendo con pocos cambios, excepto por un ligero descenso de los valores mínimos en las Islas Baleares. Por otra parte, los chubascos serán localmente fuertes o persistentes en el área del estrecho y zonas próximas donde podrían ir acompañados de tormentas. En el sur de Andalucía, Ceuta y Melilla los cielos permanecerán muy nubosos con precipitaciones moderadas. El extremo norte se mantendrá nuboso, con alguna lluvia débil al final de la jornada en el norte de Galicia y en el resto de la Península habrá cielos despejados, algo nubosos en Canarias con lluvias débiles que tenderán a remitir. El viento soplará del noroeste fuerte en las Islas Canarias y de moderado a fuerte de componente este en el litoral de Andalucía y Melilla. La cota de nieve se situará entre los 1.300 y los 1.500 metros en el sur peninsular.",
        "lemmatized_text": "el borrasca en canarias tender a remitir si bien el agencia_estatal_de_meteorología aemet mantener para este [X:??/??/??:??.??:??] el alerta amarillo por riesgo de oleaje y racha máximo de viento que poder alcanzar el SP_km/h:85 en el norte de tenerife y gran_canaria así_como en el isla de lanzarote y fuerteventura en concreto este 2 último ínsula se ver afectar especialmente por el temporal ya_que sufrir racha máximo de viento de hasta SP_km/h:80 hasta el [X:??/??/??:3.00:pm] mientras_que registrar fenómeno costero adverso hasta el [J:??/??/??:00.00:am] según dato de el aemet recoger por europa_press en gran_canaria se prever ráfaga de hasta SP_km/h:70 y fuerte oleaje en el costa norte situación que persistir hasta el [??:??/??/??:7.00:am] aproximadamente de este [X:??/??/??:??.??:??] en tenerife el viento azotar a el costa norte con racha de hasta SP_km/h:80 y especialmente en la_orotava y vilaflor donde se vivir hasta SP_km/h:85 además_de oleaje en el costa norte de el isla olas de hasta 3 metros de altura así_pues el agua costero de el provincia de santa_cruz_de_tenerife ser de el noroeste con fuerza 4 a 5 con intervalo de fuerza 6 con visibilidad bueno a regular por lluvia y predomimio de el fuerte marejada haber mar de fondo de el norte a noroeste de 2 metro ocasionalmente hasta el LN_m:3 en_cuanto_a el provincia de las_palmas el aemet avisar de agua costero de el oeste rolar pronto a noroeste fuerza 5 a 6 con intervalo de fuerza 7 a el norte y oeste de lanzarote y fuerteventura principalmente durante el 1 mitad de el día así_como visibilidad bueno a regular por lluvia haber fuerte marejada con área de mar grueso en costa de lanzarote y fuerteventura y a el principio en costa norte de gran_canaria y área de marejadilla en costa sur de este isla durante el tarde se prever mar de fondo de el norte a noroeste de 2 metro ocasionalmente hasta el LN_m:3 uno total de 26 provincias en alertar uno total de 26 provincia estar este [X:??/??/??:??.??:??] en alerta por temperatura mínimo que poder alcanzar el 10 grado bajo 0 en aragón y cataluña según el aemet así el provincia de guadalajara teruel zaragoza huesca lleida y girona estar en alerta naranja riesgo importante por bajo temperatura mientras_que lugo orense zamora león palencia burgos ávila soria segovia asturias navarra la_rioja madrid guadalajara cuenca valencia castellón el resto de aragón y cataluña mallorca y ibiza estar en alerta amarillo riesgo con temperatura de entre 8 y 4 grado negativo de este forma el helada ser de moderado a fuerte en el centro y norte peninsular así_como en baleares permanecer con poco cambio excepto por uno ligero descenso de el valor mínimo en el islas_baleares por otro parte el chubasco ser localmente fuerte o persistente en el área de el estrecho y zona próximo donde poder ir acompañar de tormenta en el sur de andalucía ceuta y melilla el cielo permanecer muy nuboso con precipitación moderar el extremo norte se mantener nuboso con alguno lluvia débil a el final de el jornada en el norte de galicia y en el resto de el península haber cielo despejar algo nuboso en canarias con lluvia débil que tender a remitir el viento soplar de el noroeste fuerte en el islas_canarias y de moderar a fuerte de componente este en el litoral de andalucía y melilla el cota de nieve se situar entre el 1.3 y el LN_m:1.5 en el sur peninsular",
        "lemmatized_text_reduced": "borrasca canarias tender remitir agencia_estatal_de_meteorología aemet mantener alerta amarillo riesgo oleaje racha máximo viento poder alcanzar norte tenerife gran_canaria isla lanzarote fuerteventura concreto último ínsula ver afectar especialmente temporal sufrir racha máximo viento registrar fenómeno costero adverso dato aemet recoger europa_press gran_canaria prever ráfaga fuerte oleaje costa norte situación persistir aproximadamente tenerife viento azotar costa norte racha especialmente la_orotava vilaflor vivir oleaje costa norte isla olas metros altura así_pues agua costero provincia santa_cruz_de_tenerife ser noroeste fuerza intervalo fuerza visibilidad bueno regular lluvia predomimio fuerte marejada haber mar fondo norte noroeste metro ocasionalmente provincia las_palmas aemet avisar agua costero oeste rolar noroeste fuerza intervalo fuerza norte oeste lanzarote fuerteventura principalmente 1 mitad día visibilidad bueno regular lluvia haber fuerte marejada área mar grueso costa lanzarote fuerteventura principio costa norte gran_canaria área marejadilla costa sur isla tarde prever mar fondo norte noroeste metro ocasionalmente total provincias alertar total provincia estar alerta temperatura mínimo poder alcanzar grado aragón cataluña aemet provincia guadalajara teruel zaragoza huesca lleida girona estar alerta naranja riesgo importante bajo temperatura lugo orense zamora león palencia burgos ávila soria segovia asturias navarra la_rioja madrid guadalajara cuenca valencia castellón resto aragón cataluña mallorca ibiza estar alerta amarillo riesgo temperatura grado negativo forma helada ser moderado fuerte centro norte peninsular baleares permanecer cambio ligero descenso valor mínimo islas_baleares parte chubasco ser localmente fuerte persistente área estrecho zona próximo poder ir acompañar tormenta sur andalucía ceuta melilla cielo permanecer nuboso precipitación moderar extremo norte mantener nuboso lluvia débil final jornada norte galicia resto península haber cielo despejar nuboso canarias lluvia débil tender remitir viento soplar noroeste fuerte islas_canarias moderar fuerte componente litoral andalucía melilla cota nieve situar sur peninsular",
        "persons": [
            "Olas",
            "Zamora",
            "León",
            "Burgos"
        ],
        "locations": [
            "Canarias",
            "Gran_Canaria",
            "Lanzarote",
            "Gran_Canaria",
            "La_Orotava",
            "Vilaflor",
            "Santa_Cruz_de_Tenerife",
            "Las_Palmas",
            "Lanzarote",
            "Lanzarote",
            "Gran_Canaria",
            "Aragón",
            "Cataluña",
            "Guadalajara",
            "Teruel",
            "Zaragoza",
            "Lleida",
            "Girona",
            "Lugo",
            "Orense",
            "Palencia",
            "Soria",
            "Segovia",
            "Asturias",
            "Navarra",
            "La_Rioja",
            "Madrid",
            "Guadalajara",
            "Valencia",
            "Castellón",
            "Aragón",
            "Cataluña",
            "Ibiza",
            "Baleares",
            "Islas_Baleares",
            "Andalucía",
            "Ceuta",
            "Melilla",
            "Galicia",
            "Península",
            "Canarias",
            "Islas_Canarias",
            "Andalucía",
            "Melilla"
        ],
        "organizations": [
            "Agencia_Estatal_de_Meteorología",
            "Aemet",
            "Tenerife",
            "Fuerteventura",
            "Aemet",
            "Europa_Press",
            "Tenerife",
            "Aemet",
            "Fuerteventura",
            "Fuerteventura",
            "Aemet",
            "Huesca",
            "Ávila",
            "Cuenca",
            "Mallorca"
        ],
        "others": [
            "Metros",
            "Así_pues",
            "Provincias"
        ],
        "dates": [
            "[X:??/??/??:??.??:??]",
            "[X:??/??/??:3.00:pm]",
            "[J:??/??/??:00.00:am]",
            "[??:??/??/??:7.00:am]",
            "[X:??/??/??:??.??:??]",
            "[X:??/??/??:??.??:??]"
        ],
        "numbers": [
            "SP_km/h:85",
            "2",
            "SP_km/h:80",
            "SP_km/h:70",
            "SP_km/h:80",
            "SP_km/h:85",
            "3",
            "4",
            "5",
            "6",
            "2",
            "LN_m:3",
            "5",
            "6",
            "7",
            "2",
            "LN_m:3",
            "26",
            "26",
            "10",
            "0",
            "8",
            "4",
            "1.3",
            "LN_m:1.5"
        ]
    }
}
