{
    "province": "LAS PALMAS",
    "date": "2010-04-06T00:00:00",
    "url": "https://www.20minutos.es/noticia/669465/0/",
    "title": {
        "raw_text": "La Seguridad Social pierde 288 afiliados en Canarias durante el mes de marzo y se sitúa en 686.285 personas",
        "lemmatized_text": "el seguridad_social perder 288 afiliado en canarias durante el [??:??/3/??:??.??:??] y se situar en 686.285 persona",
        "lemmatized_text_reduced": "seguridad_social perder afiliado canarias situar persona",
        "persons": [],
        "locations": [
            "Canarias"
        ],
        "organizations": [],
        "others": [
            "Seguridad_Social"
        ],
        "dates": [
            "[??:??/3/??:??.??:??]"
        ],
        "numbers": [
            "288",
            "686.285"
        ]
    },
    "lead": {
        "raw_text": "La Seguridad Social ha perdido 288 afiliados en la Comunidad Autónoma de Canarias en el mes de marzo, un 0,04 por ciento respecto a febrero, con lo que el número total de cotizantes es de 686.285, según los datos hechos públicos hoy por el Ministerio de Trabajo e Inmigración.",
        "lemmatized_text": "el seguridad_social haber perder 288 afiliado en el comunidad_autónoma_de_canarias en el [??:??/3/??:??.??:??] uno 0,04 por 100 respecto_a [??:??/2/??:??.??:??] con el que el número total de cotizante ser de 686.285 según el dato hecho público hoy por el ministerio_de_trabajo y inmigración",
        "lemmatized_text_reduced": "seguridad_social haber perder afiliado comunidad_autónoma_de_canarias número total cotizante ser dato hecho público ministerio_de_trabajo inmigración",
        "persons": [],
        "locations": [
            "Comunidad_Autónoma_de_Canarias"
        ],
        "organizations": [
            "Ministerio_de_Trabajo",
            "Inmigración"
        ],
        "others": [
            "Seguridad_Social"
        ],
        "dates": [
            "[??:??/3/??:??.??:??]",
            "[??:??/2/??:??.??:??]"
        ],
        "numbers": [
            "288",
            "0,04",
            "100",
            "686.285"
        ]
    },
    "body": {
        "raw_text": "Si se comparan estos datos con los registrados hace un año, se puede ver que el sistema ha perdido en el archipiélago 28.548 cotizantes, lo que supone una disminución del 3,99 por ciento respecto al mismo mes de 2009. Por provincias, el número de afiliados aumentó este mes en 450 personas en Las Palmas, lo que significa un aumento del 0,12 por ciento, aunque respecto al mismo dato del año pasado, hubo 13.552 cotizantes menos (-3,61%). Santa Cruz de Tenerife, por su parte, perdió en marzo 738 individuos, un descenso del 0,23 por ciento, mientras que a nivel interanual, la provincia occidental bajó en 14.996 cotizantes (-4,41%). Del número total de afiliados canarios, 552.259 cotizaban en el régimen general, 105.558 fueron autónomos, 15.581 pertenecían al sector agrario, 7.495 fueron empleados del hogar y 5.391 en el Marítimo.22.457 Afiliados más en toda españa A nivel nacional, la Seguridad Social ganó 22.457 afiliados (+0,13%) en el mes de marzo, con lo que el total de ocupados se situó al finalizar el mes pasado en 17.594.808 cotizantes. Este aumento es el segundo que encadena la afiliación a la Seguridad Social tras los 26.000 nuevos cotizantes que ganó en febrero. En el último año, la Seguridad Social ha perdido 463.313 afiliados, un 2,57 por ciento menos. Por su parte, trabajo destacó que esta tasa contrasta con la caída interanual del 6,5 por ciento que se experimentó hace un año, \"lo que revela una importante moderación en la pérdida de afiliados\" con respecto a marzo de 2009. El secretario de Estado de la Seguridad Social, Octavio Granado, subrayó que el dato de marzo demuestra que el sistema \"está dejando atrás con mucha velocidad los meses peores de la crisis económica\" y añadió que el balance del mes podría haber sido mejor de no haberse visto resentidas las actividades agrarias por las inclemencias climatológicas. De hecho, el Régimen Especial Agrario perdió en marzo 15.288 afiliados, un 1,8 por ciento, mientras que el resto de regímenes, a excepción del Carbón, que registró 17 bajas, ganaron cotizantes en el tercer mes del año.",
        "lemmatized_text": "si se comparar este dato con el registrar hacer uno año se poder ver que el sistema haber perder en el archipiélago 28.548 cotizante el que suponer uno disminución de el 3,99 por 100 respecto a el mismo mes de 2009 por provincia el número de afiliado aumentar este mes en 450 persona en las_palmas el que significar uno aumento de el 0,12 por 100 aunque respecto a el mismo dato de el año pasar haber 13.552 cotizante menos -3,61/100 santa_cruz_de_tenerife por su parte perder en [??:??/3/??:??.??:??] 738 individuo uno descenso de el 0,23 por 100 mientras_que a nivel interanual el provincia occidental bajar en 14.996 cotizante -4,41/100 de el número total de afiliado canario 552.259 cotizar en el régimen general 105.558 ser autónomo 15.581 pertenecer a el sector agrario 7.495 ser empleado de el hogar y 5.391 en el Marítimo.22.457 afiliados más en todo españa a nivel nacional el seguridad_social ganar 22.457 afiliado +0,13/100 en el [??:??/3/??:??.??:??] con el que el total de ocupar se situar a el finalizar el mes pasar en 17.594.808 cotizante este aumento ser el 2 que encadenar el afiliación a el seguridad_social tras el 26 nuevo cotizante que ganar en [??:??/2/??:??.??:??] en el último año el seguridad_social haber perder 463.313 afiliado uno 2,57 por 100 menos por su parte trabajo destacar que este tasa contrastar con el caída interanual de el 6,5 por 100 que se experimentar hacer uno año el que revelar uno importante moderación en el pérdida de afiliado con_respecto_a [??:??/3/2009:??.??:??] el secretario de estado_de_la_seguridad_social octavio_granado subrayar que el dato de [??:??/3/??:??.??:??] demostrar que el sistema estar dejar atrás con mucho velocidad el mes peor de el crisis económico y añadir que el balance de el mes poder haber ser mejor de no haber se ver resentir el actividad agrario por el inclemencia climatológico de hecho el régimen_especial_agrario perder en [??:??/3/??:??.??:??] 15.288 afiliado uno 1,8 por 100 mientras_que el resto de régimen a excepción de el carbón que registrar 17 baja ganar cotizante en el 3 mes de el año",
        "lemmatized_text_reduced": "comparar dato registrar hacer año poder ver sistema haber perder archipiélago cotizante suponer disminución respecto mismo mes provincia número afiliado aumentar mes persona las_palmas significar aumento respecto mismo dato año pasar haber cotizante santa_cruz_de_tenerife parte perder individuo descenso nivel interanual provincia occidental bajar cotizante número total afiliado canario cotizar régimen general ser autónomo pertenecer sector agrario ser empleado hogar afiliados españa a nivel nacional seguridad_social ganar afiliado total ocupar situar finalizar mes pasar cotizante aumento ser 2 encadenar afiliación seguridad_social nuevo cotizante ganar último año seguridad_social haber perder afiliado parte trabajo destacar tasa contrastar caída interanual experimentar hacer año revelar importante moderación pérdida afiliado secretario estado_de_la_seguridad_social octavio_granado subrayar dato demostrar sistema estar dejar velocidad mes peor crisis económico añadir balance mes poder haber ser mejor haber ver resentir actividad agrario inclemencia climatológico hecho régimen_especial_agrario perder afiliado resto régimen excepción carbón registrar baja ganar cotizante 3 mes año",
        "persons": [
            "Octavio_Granado"
        ],
        "locations": [
            "Las_Palmas",
            "Afiliados"
        ],
        "organizations": [
            "Santa_Cruz_de_Tenerife",
            "Estado_de_la_Seguridad_Social",
            "Régimen_Especial_Agrario"
        ],
        "others": [
            "A",
            "Seguridad_Social",
            "Seguridad_Social",
            "Seguridad_Social",
            "Carbón"
        ],
        "dates": [
            "[??:??/3/??:??.??:??]",
            "[??:??/3/??:??.??:??]",
            "[??:??/2/??:??.??:??]",
            "[??:??/3/2009:??.??:??]",
            "[??:??/3/??:??.??:??]",
            "[??:??/3/??:??.??:??]"
        ],
        "numbers": [
            "28.548",
            "3,99",
            "100",
            "2009",
            "450",
            "0,12",
            "100",
            "13.552",
            "-3,61/100",
            "738",
            "0,23",
            "100",
            "14.996",
            "-4,41/100",
            "552.259",
            "105.558",
            "15.581",
            "7.495",
            "5.391",
            "Marítimo.22.457",
            "22.457",
            "+0,13/100",
            "17.594.808",
            "26",
            "463.313",
            "2,57",
            "100",
            "6,5",
            "100",
            "15.288",
            "1,8",
            "100",
            "17"
        ]
    }
}
