{
    "province": "LAS PALMAS",
    "date": "2011-01-27T00:00:00",
    "url": "https://www.20minutos.es/noticia/941817/0/",
    "title": {
        "raw_text": "Fallece un varón apuñalado en Arrecife (Lanzarote)",
        "lemmatized_text": "fallecer uno varón apuñalar en arrecife lanzarote",
        "lemmatized_text_reduced": "fallecer varón apuñalar arrecife lanzarote",
        "persons": [],
        "locations": [
            "Arrecife",
            "Lanzarote"
        ],
        "organizations": [],
        "others": [],
        "dates": [],
        "numbers": []
    },
    "lead": {
        "raw_text": "Un hombre de 37 años de edad ha fallecido este miércoles tras ser apuñalado en la calle Cid Campeador, en el barrio de San Francisco Javier, en Arrecife (Lanzarote), según informaron hoy a Europa Press fuentes del Centro Coordinador de Emergencias y Seguridad (Cecoes) 112.",
        "lemmatized_text": "uno hombre de 37 año de edad haber fallecer este [X:??/??/??:??.??:??] tras ser apuñalar en el calle cid_campeador en el barrio de san_francisco_javier en arrecife lanzarote según informar hoy a europa_press fuente de el centro_coordinador_de_emergencias y seguridad cecoes 112",
        "lemmatized_text_reduced": "hombre año edad haber fallecer ser apuñalar calle cid_campeador barrio san_francisco_javier arrecife lanzarote informar europa_press fuente centro_coordinador_de_emergencias seguridad cecoes",
        "persons": [],
        "locations": [
            "Cid_Campeador",
            "San_Francisco_Javier",
            "Arrecife",
            "Lanzarote"
        ],
        "organizations": [
            "Europa_Press",
            "Centro_Coordinador_de_Emergencias",
            "Cecoes"
        ],
        "others": [
            "Seguridad"
        ],
        "dates": [
            "[X:??/??/??:??.??:??]"
        ],
        "numbers": [
            "37",
            "112"
        ]
    },
    "body": {
        "raw_text": "Un hombre de 37 años de edad ha fallecido este miércoles tras ser apuñalado en la calle Cid Campeador, en el barrio de San Francisco Javier, en Arrecife (Lanzarote), según informaron hoy a Europa Press fuentes del Centro Coordinador de Emergencias y Seguridad (Cecoes) 112. La agresión se produjo el pasado lunes, a las 23.27 horas, cuando una llamada alertó al Cecoes de que un varón había sufrido una agresión por arma blanca en plena calle. De este modo, el 112 activó de inmediato el dispositivo de emergencias necesario. Hasta el lugar se desplazó personal del Servicio de Urgencias Canario (SUC), que atendió al hombre con traumatismo en miembro superior con herida abierta, por lo que fue trasladado en estado en principio menos grave en una ambulancia de soporte vital básico del SUC hasta el Hospital Doctor José Molina Orosa, donde su situación empeoró y falleció ayer. En dicha actuación intervino el Cuerpo Nacional de Policía, que se ha hecho cargo de la instrucción de las correspondientes diligencias para esclarecer los hechos.",
        "lemmatized_text": "uno hombre de 37 año de edad haber fallecer este [X:??/??/??:??.??:??] tras ser apuñalar en el calle cid_campeador en el barrio de san_francisco_javier en arrecife lanzarote según informar hoy a europa_press fuente de el centro_coordinador_de_emergencias y seguridad cecoes 112 el agresión se producir el [L:??/??/??:??.??:??] a el TM_h:23.27 cuando uno llamada alertar a el cecoes de que uno varón haber sufrir uno agresión por arma blanco en pleno calle de este modo el 112 activar de inmediato el dispositivo de emergencia necesario hasta el lugar se desplazar personal de el servicio_de_urgencias_canario suc que atender a el hombre con traumatismo en miembro superior con herida abrir por el que ser trasladar en estado en principio menos grave en uno ambulancia de soporte vital básico de el suc hasta el hospital_doctor_josé_molina_orosa donde su situación empeorar y fallecer ayer en decir actuación intervenir el cuerpo_nacional_de_policía que se haber hacer_cargo de el instrucción de el correspondiente diligencia para esclarecer el hecho",
        "lemmatized_text_reduced": "hombre año edad haber fallecer ser apuñalar calle cid_campeador barrio san_francisco_javier arrecife lanzarote informar europa_press fuente centro_coordinador_de_emergencias seguridad cecoes agresión producir llamada alertar cecoes varón haber sufrir agresión arma blanco pleno calle modo activar inmediato dispositivo emergencia necesario lugar desplazar personal servicio_de_urgencias_canario suc atender hombre traumatismo miembro superior herida abrir ser trasladar estado principio grave ambulancia soporte vital básico suc hospital_doctor_josé_molina_orosa situación empeorar fallecer decir actuación intervenir cuerpo_nacional_de_policía haber hacer_cargo instrucción correspondiente diligencia esclarecer hecho",
        "persons": [],
        "locations": [
            "Cid_Campeador",
            "San_Francisco_Javier",
            "Arrecife",
            "Lanzarote"
        ],
        "organizations": [
            "Europa_Press",
            "Centro_Coordinador_de_Emergencias",
            "Cecoes",
            "Cecoes",
            "Servicio_de_Urgencias_Canario",
            "SUC",
            "SUC",
            "Hospital_Doctor_José_Molina_Orosa",
            "Cuerpo_Nacional_de_Policía"
        ],
        "others": [
            "Seguridad"
        ],
        "dates": [
            "[X:??/??/??:??.??:??]",
            "[L:??/??/??:??.??:??]"
        ],
        "numbers": [
            "37",
            "112",
            "TM_h:23.27",
            "112"
        ]
    }
}
