{
    "province": "LAS PALMAS",
    "date": "2008-01-31T00:00:00",
    "url": "https://www.20minutos.es/noticia/341715/0/chillida/obra/postuma/",
    "title": {
        "raw_text": "La obra póstuma de Chillida, en la montaña de Tindaya, comenzará en 2009",
        "lemmatized_text": "el obra póstumo de chillida en el montaña de tindaya comenzar en 2009",
        "lemmatized_text_reduced": "obra póstumo chillida montaña tindaya comenzar",
        "persons": [
            "Chillida"
        ],
        "locations": [
            "Tindaya"
        ],
        "organizations": [],
        "others": [],
        "dates": [],
        "numbers": [
            "2009"
        ]
    },
    "lead": {
        "raw_text": "Se trata del \"Monumento a la Tolerancia\". Consiste en el vaciado de la montaña.",
        "lemmatized_text": "se tratar de el monumento a el tolerancia consistir en el vaciado de el montaña",
        "lemmatized_text_reduced": "tratar monumento tolerancia consistir vaciado montaña",
        "persons": [],
        "locations": [],
        "organizations": [
            "Tolerancia"
        ],
        "others": [],
        "dates": [],
        "numbers": []
    },
    "body": {
        "raw_text": "La obra póstuma del escultor Eduardo Chillida, \"Monumento a la Tolerancia\", enclavada en la montaña de Tindaya , en la isla de Fuerteventura, comenzará a realizarse en febrero de 2009 , según reveló hoy el consejero de Medio Ambiente y Ordenación Territorial, Domingo Berriel. El consejero del Gobierno canario, en una comparecencia parlamentaria, indicó que la obra, que consiste en el vaciado del corazón de la montaña , comenzará cuando concluya el periodo de licitación. El periodo de licitación, así como la aprobación definitiva de las normas de conservación de la montaña , está previsto para octubre del presente año. Berriel señaló en su comparecencia que en breve se formalizará la Fundación que se encargará de la licitación y control de la ejecución y gestión del \"Monumento a la Tolerancia\", y para su constitución se han mantenido conversaciones con la familia del escultor donostiarra, el Cabildo de Fuerteventura y el Ayuntamiento de La Oliva . El consejero canario afirmó que el proyecto de Chillida contará con una declaración de impacto ambiental que garantizará una construcción ambiental viable que conserve intacto el paisaje natural del espacio. Berriel indicó que la obra del escultor \"constituye una referencia necesaria y muy valiosa para canalizar el futuro turístico de Canarias \", pues estimó que su proyecto se sitúa en la vanguardia de la ingeniería actual.",
        "lemmatized_text": "el obra póstumo de el escultor eduardo_chillida monumento a el tolerancia enclavar en el montaña de tindaya en el isla de fuerteventura comenzar a realizar se en [??:??/2/2009:??.??:??] según revelar hoy el consejero de medio_ambiente y ordenación_territorial [G:??/??/??:??.??:??] berriel el consejero de el gobierno canario en uno comparecencia parlamentario indicar que el obra que consistir en el vaciado de el corazón de el montaña comenzar cuando concluir el periodo de licitación el periodo de licitación así_como el aprobación definitivo de el norma de conservación de el montaña estar prever para [??:??/10/??:??.??:??] de el presente año berriel señalar en su comparecencia que en breve se formalizar el fundación que se encargar de el licitación y control de el ejecución y gestión de el monumento a el tolerancia y para su constitución se haber mantener conversación con el familia de el escultor donostiarra el cabildo_de_fuerteventura y el ayuntamiento_de_la_oliva el consejero canario afirmar que el proyecto de chillida contar con uno declaración de impacto ambiental que garantizar uno construcción ambiental viable que conservar intacto el paisaje natural de el espacio berriel indicar que el obra de el escultor constituir uno referencia necesario y muy valioso para canalizar el futuro turístico de canarias pues estimar que su proyecto se situar en el vanguardia de el ingeniería actual",
        "lemmatized_text_reduced": "obra póstumo escultor eduardo_chillida monumento tolerancia enclavar montaña tindaya isla fuerteventura comenzar realizar revelar consejero medio_ambiente ordenación_territorial berriel consejero gobierno canario comparecencia parlamentario indicar obra consistir vaciado corazón montaña comenzar concluir periodo licitación periodo licitación aprobación definitivo norma conservación montaña estar prever presente año berriel señalar comparecencia breve formalizar fundación encargar licitación control ejecución gestión monumento tolerancia constitución haber mantener conversación familia escultor donostiarra cabildo_de_fuerteventura ayuntamiento_de_la_oliva consejero canario afirmar proyecto chillida contar declaración impacto ambiental garantizar construcción ambiental viable conservar intacto paisaje natural espacio berriel indicar obra escultor constituir referencia necesario valioso canalizar futuro turístico canarias estimar proyecto situar vanguardia ingeniería actual",
        "persons": [
            "Eduardo_Chillida",
            "Berriel",
            "Berriel",
            "Chillida",
            "Berriel"
        ],
        "locations": [
            "Tindaya",
            "Canarias"
        ],
        "organizations": [
            "Tolerancia",
            "Fuerteventura",
            "Medio_Ambiente",
            "Ordenación_Territorial",
            "Gobierno",
            "Fundación",
            "Tolerancia",
            "Cabildo_de_Fuerteventura",
            "Ayuntamiento_de_La_Oliva"
        ],
        "others": [],
        "dates": [
            "[??:??/2/2009:??.??:??]",
            "[G:??/??/??:??.??:??]",
            "[??:??/10/??:??.??:??]"
        ],
        "numbers": []
    }
}
