{
    "province": "LAS PALMAS",
    "date": "2010-04-22T00:00:00",
    "url": "https://www.20minutos.es/noticia/685032/0/",
    "title": {
        "raw_text": "La Seguridad Social alcanza los 80.746 afiliados extranjeros en marzo",
        "lemmatized_text": "el seguridad_social alcanzar el 80.746 afiliado extranjero en [??:??/3/??:??.??:??]",
        "lemmatized_text_reduced": "seguridad_social alcanzar afiliado extranjero",
        "persons": [],
        "locations": [],
        "organizations": [],
        "others": [
            "Seguridad_Social"
        ],
        "dates": [
            "[??:??/3/??:??.??:??]"
        ],
        "numbers": [
            "80.746"
        ]
    },
    "lead": {
        "raw_text": "El número medio de afiliados extranjeros a la Seguridad Social en Canarias alcanzó en marzo los 80.746, lo que supone un decrecimiento interanual del -4,42%, al perder 3.737 cotizantes extranjeros, mientras que en toda España la media de afiliados extranjeros se situó en 1.828.230, según datos difundidos hoy por el Ministerio de Trabajo e Inmigración.",
        "lemmatized_text": "el número medio de afiliado extranjero a el seguridad_social en canarias alcanzar en [??:??/3/??:??.??:??] el 80.746 el que suponer uno decrecimiento interanual de el -4,42/100 a el perder 3.737 cotizante extranjero mientras_que en todo españa el media de afiliado extranjero se situar en 1.828.230 según dato difundir hoy por el ministerio_de_trabajo y inmigración",
        "lemmatized_text_reduced": "número medio afiliado extranjero seguridad_social canarias alcanzar suponer decrecimiento interanual perder cotizante extranjero españa media afiliado extranjero situar dato difundir ministerio_de_trabajo inmigración",
        "persons": [],
        "locations": [
            "Canarias",
            "España"
        ],
        "organizations": [
            "Ministerio_de_Trabajo",
            "Inmigración"
        ],
        "others": [
            "Seguridad_Social"
        ],
        "dates": [
            "[??:??/3/??:??.??:??]"
        ],
        "numbers": [
            "80.746",
            "-4,42/100",
            "3.737",
            "1.828.230"
        ]
    },
    "body": {
        "raw_text": "Por provincias, la de Las Palmas tuvo 43.645 cotizantes extranjeros, lo que supuso una caída interanual del 3,6 por ciento; mientras que en la de Santa Cruz de Tenerife el número de afiliados en marzo alcanzó los 37.101, produciéndose en esta un decrecimiento mayor, ya que fue del 5,37 por ciento. Por regímenes, el que mayor afiliados extranjeros tuvo en Canarias fue el General con 57.413, seguido de los Autónomos (14.937), así como de los Empleados del Hogar (4.811) y del sector Agrario (3.187) y tras ellos los Trabajadores del Mar que fueron 398 los cotizantes. Datos nacionales La afiliación media de trabajadores extranjeros a nivel nacional se situó al finalizar marzo en 1.828.230 ocupados, tras ganar en el mes un total de 10.245 cotizantes (+0,56%), según datos difundidos hoy por el Ministerio de Trabajo e Inmigración. Este ascenso en el número de afiliados extranjeros es el segundo aumento mensual consecutivo tras el de febrero, mes en el que el sistema ganó 11.112 cotizantes extranjeros. Del total de inmigrantes afiliados al finalizar marzo, 1.162.346 pertenecían a países extracomunitarios, frente a 665.884 cotizantes provenientes de países de la Unión Europea. Dentro de los países no comunitarios, 223.259 eran de nacionalidad marroquí y 175.964, ecuatoriana. Colombia, con 112.751 trabajadores, se sitúa como tercer país de procedencia de afiliados, por delante de China, que cuenta con 76.588 cotizantes. El resto de afiliados no comunitarios se repartieron entre Bolivia(73.124), Perú (69.611), Argentina (45.750), Ucrania (33.838), República Dominicana (30.779) y Brasil (24.045), entre otros. Por su parte, de los que proceden de la UE-27, rumanos, italianos y portugueses son los más numerosos, con 281.884, 60.662 y 56.368 cotizantes, respectivamente. Les siguieron búlgaros y británicos, con 53.128 y 51.744, y algo más lejos, los alemanes, con 39.580 afiliados. La mayor parte de los extranjeros que estaban afiliados a la Seguridad Social al finalizar marzo se encuadraban en el Régimen General, con 1.190.815 cotizantes, seguidos del Régimen Agrario (255.740), el Régimen Especial de Autónomos (196.038), el del Hogar (179.916), el del Mar (4.994) y el del Carbón (728). Dentro del Régimen General, un total de 243.883 extranjeros, el 20,48%, trabajaba en la hostelería, mientras que el 16,67% lo hacía en el comercio (198.500 afiliados) y el 14,76% en la construcción (64.167 cotizantes). Cataluña y madrid concentran el 43% De los inmigrantes . Por comunidades autónomas, Cataluña y Madrid concentraron cuatro de cada diez extranjeros afiliados a la Seguridad Social en marzo, al sumar entre ambas el 43,43% del total de inmigrantes ocupados. En concreto, Cataluña contaba con 400.861 extranjeros cotizantes, mientras que en Madrid la cifra era de 393.136. Tras estas dos regiones se situaron Andalucía, con 223.377 afiliados extranjeros; Comunidad Valenciana, con 198.871 ocupados; Murcia, con 87.293; Canarias, con 80.746; Castilla-La Mancha, con 79.363; Aragón, con 61.988; Baleares, con 61.280; Castilla y León, con 59.829, y País Vasco, con 51.027. Las comunidades con menor presencia de inmigrantes en alta a la Seguridad Social al finalizar marzo fueron Galicia, con 38.804 extranjeros; Navarra, con 25.749; La Rioja, con 16.143; Extremadura, con 15.545; Asturias, con 15.500; Cantabria, con 12.039, y las ciudades autónomas de Melilla, con 4.034, y Ceuta, con 2.644.",
        "lemmatized_text": "por provincia el de las_palmas tener 43.645 cotizante extranjero el que suponer uno caída interanual de el 3,6 por 100 mientras_que en el de santa_cruz_de_tenerife el número de afiliado en [??:??/3/??:??.??:??] alcanzar el 37.101 producir se en este uno decrecimiento mayor ya_que ser de el 5,37 por 100 por régimen el que mayor afiliado extranjero tener en canarias ser el general con 57.413 seguir de el autónomos 14.937 así_como de el empleados_del_hogar 4.811 y de el sector agrario 3.187 y tras ellos el trabajadores_del_mar que ser 398 el cotizante dato nacional la afiliación medio de trabajador extranjero a nivel nacional se situar a el finalizar [??:??/3/??:??.??:??] en 1.828.230 ocupar tras ganar en el [??:??/1/??:??.??:??] total de 10.245 cotizante +0,56/100 según dato difundir hoy por el ministerio_de_trabajo y inmigración este ascenso en el número de afiliado extranjero ser el 2 aumento mensual consecutivo tras el de [??:??/2/??:??.??:??] mes en el que el sistema ganar 11.112 cotizante extranjero de el total de inmigrante afiliar a el finalizar [??:??/3/??:??.??:??] 1.162.346 pertenecer a país extracomunitario frente_a 665.884 cotizante proveniente de país de el unión_europea dentro_de el país no comunitario 223.259 ser de nacionalidad marroquí y 175.964 ecuatoriano colombia con 112.751 trabajador se situar como 3 país de procedencia de afiliado por delante_de china que contar con 76.588 cotizante el resto de afiliado no comunitario se repartir entre bolivia 73.124 perú 69.611 argentina 45.75 ucrania 33.838 república_dominicana 30.779 y brasil 24.045 entre otro por su parte de el que proceder de el UE-27 rumano italiano y portugués ser el más numeroso con 281.884 60.662 y 56.368 cotizante respectivamente le seguir búlgaro y británico con 53.128 y 51.744 y algo más lejos el alemán con 39.58 afiliado el mayor parte de el extranjero que estar afiliar a el seguridad_social a el finalizar [??:??/3/??:??.??:??] se encuadrar en el régimen_general con 1.190.815 cotizante seguir de el régimen_agrario 255.74 el régimen_especial_de_autónomos 196.038 el de el hogar 179.916 el de el mar 4.994 y el de el carbón 728 dentro de el régimen_general uno total de 243.883 extranjero el 20,48/100 trabajar en el hostelería mientras_que el 16,67/100 lo hacer en el comercio 198.5 afiliado y el 14,76/100 en el construcción 64.167 cotizante cataluña y madrid concentrar el 43/100 de el inmigrante por comunidad autónomo cataluña y madrid concentrar 4/10 extranjero afiliar a el seguridad_social en [??:??/3/??:??.??:??] a el sumar entre ambos el 43,43/100 de el total de inmigrante ocupar en concreto cataluña contar con 400.861 extranjero cotizante mientras_que en madrid el cifra ser de 393.136 tras este 2 región se situar andalucía con 223.377 afiliado extranjero comunidad_valenciana con 198.871 ocupar murcia con 87.293 canarias con 80.746 castilla-la_mancha con 79.363 aragón con 61.988 baleares con 61.28 castilla y león con 59.829 y país_vasco con 51.027 el comunidad con menor presencia de inmigrante en alto a el seguridad_social a el finalizar [??:??/3/??:??.??:??] ser galicia con 38.804 extranjero navarra con 25.749 la_rioja con 16.143 extremadura con 15.545 asturias con 15.5 cantabria con 12.039 y el ciudad autónomo de melilla con 4.034 y ceuta con 2.644",
        "lemmatized_text_reduced": "provincia las_palmas tener cotizante extranjero suponer caída interanual santa_cruz_de_tenerife número afiliado alcanzar producir decrecimiento mayor ser régimen mayor afiliado extranjero tener canarias ser general seguir autónomos empleados_del_hogar sector agrario trabajadores_del_mar ser cotizante dato nacional la afiliación medio trabajador extranjero nivel nacional situar finalizar ocupar ganar total cotizante dato difundir ministerio_de_trabajo inmigración ascenso número afiliado extranjero ser 2 aumento mensual consecutivo mes sistema ganar cotizante extranjero total inmigrante afiliar finalizar pertenecer país extracomunitario cotizante proveniente país unión_europea país comunitario ser nacionalidad marroquí ecuatoriano colombia trabajador situar 3 país procedencia afiliado china contar cotizante resto afiliado comunitario repartir bolivia perú argentina ucrania república_dominicana brasil parte proceder rumano italiano portugués ser numeroso cotizante respectivamente seguir búlgaro británico alemán afiliado mayor parte extranjero estar afiliar seguridad_social finalizar encuadrar régimen_general cotizante seguir régimen_agrario régimen_especial_de_autónomos hogar mar carbón régimen_general total extranjero trabajar hostelería hacer comercio afiliado construcción cotizante cataluña madrid concentrar de inmigrante comunidad autónomo cataluña madrid concentrar extranjero afiliar seguridad_social sumar total inmigrante ocupar concreto cataluña contar extranjero cotizante madrid cifra ser región situar andalucía afiliado extranjero comunidad_valenciana ocupar murcia canarias castilla-la_mancha aragón baleares castilla león país_vasco comunidad menor presencia inmigrante alto seguridad_social finalizar ser galicia extranjero navarra la_rioja extremadura asturias cantabria ciudad autónomo melilla ceuta",
        "persons": [
            "Agrario",
            "León"
        ],
        "locations": [
            "Las_Palmas",
            "Santa_Cruz_de_Tenerife",
            "Canarias",
            "Colombia",
            "Bolivia",
            "Perú",
            "República_Dominicana",
            "Mar",
            "Carbón",
            "Cataluña",
            "De",
            "Cataluña",
            "Cataluña",
            "Madrid",
            "Andalucía",
            "Comunidad_Valenciana",
            "Murcia",
            "Canarias",
            "Castilla-La_Mancha",
            "Aragón",
            "Baleares",
            "Castilla",
            "País_Vasco",
            "Galicia",
            "Navarra",
            "La_Rioja",
            "Extremadura",
            "Asturias",
            "Cantabria",
            "Melilla",
            "Ceuta"
        ],
        "organizations": [
            "General",
            "Autónomos",
            "Empleados_del_Hogar",
            "Trabajadores_del_Mar",
            "Ministerio_de_Trabajo",
            "Inmigración",
            "Unión_Europea",
            "China",
            "Argentina",
            "Ucrania",
            "Brasil",
            "Régimen_General",
            "Régimen_Agrario",
            "Régimen_Especial_de_Autónomos",
            "Hogar",
            "Régimen_General",
            "Madrid"
        ],
        "others": [
            "La",
            "Seguridad_Social",
            "Seguridad_Social",
            "Seguridad_Social"
        ],
        "dates": [
            "[??:??/3/??:??.??:??]",
            "[??:??/3/??:??.??:??]",
            "[??:??/1/??:??.??:??]",
            "[??:??/2/??:??.??:??]",
            "[??:??/3/??:??.??:??]",
            "[??:??/3/??:??.??:??]",
            "[??:??/3/??:??.??:??]",
            "[??:??/3/??:??.??:??]"
        ],
        "numbers": [
            "43.645",
            "3,6",
            "100",
            "37.101",
            "5,37",
            "100",
            "57.413",
            "14.937",
            "4.811",
            "3.187",
            "398",
            "1.828.230",
            "10.245",
            "+0,56/100",
            "11.112",
            "1.162.346",
            "665.884",
            "223.259",
            "175.964",
            "112.751",
            "76.588",
            "73.124",
            "69.611",
            "45.75",
            "33.838",
            "30.779",
            "24.045",
            "UE-27",
            "281.884",
            "60.662",
            "56.368",
            "53.128",
            "51.744",
            "39.58",
            "1.190.815",
            "255.74",
            "196.038",
            "179.916",
            "4.994",
            "728",
            "243.883",
            "20,48/100",
            "16,67/100",
            "198.5",
            "14,76/100",
            "64.167",
            "43/100",
            "4/10",
            "43,43/100",
            "400.861",
            "393.136",
            "2",
            "223.377",
            "198.871",
            "87.293",
            "80.746",
            "79.363",
            "61.988",
            "61.28",
            "59.829",
            "51.027",
            "38.804",
            "25.749",
            "16.143",
            "15.545",
            "15.5",
            "12.039",
            "4.034",
            "2.644"
        ]
    }
}
