{
    "province": "LAS PALMAS",
    "date": "2010-02-26T00:00:00",
    "url": "https://www.20minutos.es/noticia/638801/0/",
    "title": {
        "raw_text": "El Instituto Valenciano de Infertilidad se asienta en Canarias para acercar sus técnicas a la población del archipiélago",
        "lemmatized_text": "el instituto_valenciano_de_infertilidad se asentar en canarias para acercar su técnica a el población de el archipiélago",
        "lemmatized_text_reduced": "instituto_valenciano_de_infertilidad asentar canarias acercar técnica población archipiélago",
        "persons": [],
        "locations": [
            "Canarias"
        ],
        "organizations": [
            "Instituto_Valenciano_de_Infertilidad"
        ],
        "others": [],
        "dates": [],
        "numbers": []
    },
    "lead": {
        "raw_text": "El Instituto Valenciano de Infertilidad (IVI) ha abierto hoy, en Las Palmas de Gran Canaria, una nueva clínica de reproducción asistida, la primera en las islas, y con la que IVI pretende acercar sus técnicas a la población del archipiélago.",
        "lemmatized_text": "el instituto_valenciano_de_infertilidad ivi haber abrir hoy en las_palmas_de_gran_canaria uno nuevo clínica de reproducción asistir el 1 en el isla y con el que ivi pretender acercar su técnica a el población de el archipiélago",
        "lemmatized_text_reduced": "instituto_valenciano_de_infertilidad ivi haber abrir las_palmas_de_gran_canaria nuevo clínica reproducción asistir 1 isla ivi pretender acercar técnica población archipiélago",
        "persons": [],
        "locations": [
            "Las_Palmas_de_Gran_Canaria"
        ],
        "organizations": [
            "Instituto_Valenciano_de_Infertilidad",
            "IVI",
            "IVI"
        ],
        "others": [],
        "dates": [],
        "numbers": []
    },
    "body": {
        "raw_text": "El director de IVI en Las Palmas de Gran Canaria, Javier Domingo, aseguró que el Instituto \"llega al archipiélago canario con la intención de acercar\" sus técnicas a la población canaria, ya que ésta en los últimos años \"se ha desplazado a la península para buscar una solución a su infertilidad\" en las clínicas de IVI en Madrid y Valencia. Domingo, en nota de prensa, afirmó que en los últimos 5 años \"más de 400 parejas canarias acudieron a IVI\", mientras que \"9 de cada 10 logró su objetivo de ser padres\". En cuanto al nuevo centro en la capital grancanaria, son 1.200 metros cuadrados distribuidos en 7 unidades médicas, 6 consultas, 5 habitaciones, 2 quirófanos y 4 laboratorios dotados con la \"más avanzada\" tecnología para fecundación in vitro, inseminación artificial, donación de ovocitos y diagnóstico genético preimplantacional. Respecto al personal que trabajará en IVI, en Las Palmas de Gran Canaria, estará compuesto por una plantilla de 14 profesionales entre ginecólogos, embriólogos y resto del personal con una filosofía basada en la atención personalizada y soluciones \"concretas para cada caso\". De esta forma, IVI ya dispone de un total de 18 los centros repartidos en Alicante, Almería, Barcelona, Bilbao, Castellón, Madrid, Murcia, Sevilla, Valencia, Vigo, Las Palmas de Gran Canaria, Lisboa, Estambul, México D.F., Buenos Aires, Santiago de Chile y Panamá. El Instituto Valenciano de Infertilidad nace 1990 como la primera institución médica en España especializada \"íntegramente\" en reproducción humana y desde entonces \"ha ayudado a nacer a más de 50.000 niños gracias a la aplicación de los más novedosos\" métodos de reproducción asistida.",
        "lemmatized_text": "el director de ivi en las_palmas_de_gran_canaria javier [G:??/??/??:??.??:??] asegurar que el instituto llegar a el archipiélago canario con el intención de acercar su técnica a el población canario ya_que este en el último año se haber desplazar a el península para buscar uno solución a su infertilidad en el clínica de ivi en madrid y valencia [G:??/??/??:??.??:??] en nota de prensa afirmar que en el último 5 año más de 400 pareja canario acudir a ivi mientras_que 9/10 lograr su objetivo de ser padre en cuanto a el nuevo centro en el capital grancanaria ser AR_m2:1.2 distribuir en 7 unidad médico 6 consulta 5 habitación 2 quirófano y 4 laboratorio dotar con el más avanzar tecnología para fecundación in_vitro inseminación artificial donación de ovocito y diagnóstico genético preimplantacional respecto a el personal que trabajar en ivi en las_palmas_de_gran_canaria estar componer por uno plantilla de 14 profesional entre ginecólogo embriólogo y resto de el personal con uno filosofía basar en el atención personalizar y solución concreto para cada caso de este forma ivi ya disponer de uno total de 18 el centro repartir en alicante almería barcelona bilbao castellón madrid murcia sevilla valencia vigo las_palmas_de_gran_canaria lisboa estambul méxico_d.f. buenos_aires santiago_de_chile y panamá el instituto_valenciano_de_infertilidad nacer 1990 como el 1 institución médico en españa especializar íntegramente en reproducción humano y desde entonces haber ayudar a nacer a más de 50 niño gracias_a el aplicación de el más novedoso método de reproducción asistir",
        "lemmatized_text_reduced": "director ivi las_palmas_de_gran_canaria javier asegurar instituto llegar archipiélago canario intención acercar técnica población canario último año haber desplazar península buscar solución infertilidad clínica ivi madrid valencia nota prensa afirmar último año pareja canario acudir ivi lograr objetivo ser padre nuevo centro capital grancanaria ser distribuir unidad médico consulta habitación quirófano laboratorio dotar avanzar tecnología fecundación in_vitro inseminación artificial donación ovocito diagnóstico genético preimplantacional respecto personal trabajar ivi las_palmas_de_gran_canaria estar componer plantilla profesional ginecólogo embriólogo resto personal filosofía basar atención personalizar solución concreto caso forma ivi disponer total centro repartir alicante almería barcelona bilbao castellón madrid murcia sevilla valencia vigo las_palmas_de_gran_canaria lisboa estambul méxico_d.f. buenos_aires santiago_de_chile panamá instituto_valenciano_de_infertilidad nacer 1 institución médico españa especializar íntegramente reproducción humano haber ayudar nacer niño aplicación novedoso método reproducción asistir",
        "persons": [
            "Javier"
        ],
        "locations": [
            "Las_Palmas_de_Gran_Canaria",
            "Madrid",
            "Valencia",
            "IVI",
            "Las_Palmas_de_Gran_Canaria",
            "Alicante",
            "Almería",
            "Bilbao",
            "Castellón",
            "Madrid",
            "Murcia",
            "Sevilla",
            "Valencia",
            "Vigo",
            "Lisboa",
            "Buenos_Aires",
            "Santiago_de_Chile",
            "Panamá",
            "España"
        ],
        "organizations": [
            "IVI",
            "Instituto",
            "IVI",
            "IVI",
            "IVI",
            "Barcelona",
            "Las_Palmas_de_Gran_Canaria",
            "Estambul",
            "México_D.F.",
            "Instituto_Valenciano_de_Infertilidad"
        ],
        "others": [],
        "dates": [
            "[G:??/??/??:??.??:??]",
            "[G:??/??/??:??.??:??]"
        ],
        "numbers": [
            "5",
            "400",
            "9/10",
            "AR_m2:1.2",
            "7",
            "6",
            "5",
            "2",
            "4",
            "14",
            "18",
            "1990",
            "50"
        ]
    }
}
