{
    "province": "LAS PALMAS",
    "date": "2007-12-03T00:00:00",
    "url": "https://www.20minutos.es/noticia/316087/0/viviendas/canarias/vacias/",
    "title": {
        "raw_text": "Una de cada siete viviendas en las islas Canarias permanece desocupada",
        "lemmatized_text": "uno de cada 7 vivienda en el isla canarias permanecer desocupar",
        "lemmatized_text_reduced": "vivienda isla canarias permanecer desocupar",
        "persons": [],
        "locations": [
            "Canarias"
        ],
        "organizations": [],
        "others": [],
        "dates": [],
        "numbers": [
            "7"
        ]
    },
    "lead": {
        "raw_text": "La de las islas es la séptima autonomía española con más casas desocupadas. El Archipiélago tiene 851.463 viviendas. CONSULTA AQUÍ MÁS NOTICIAS DE LAS PALMAS DE GRAN CANARIA .",
        "lemmatized_text": "el de el isla ser el 7 autonomía español con más casa desocupar el archipiélago tener 851.463 vivienda consulta_aquí_más_noticias_de_las_palmas_de_gran_canaria",
        "lemmatized_text_reduced": "isla ser 7 autonomía español casa desocupar archipiélago tener vivienda consulta_aquí_más_noticias_de_las_palmas_de_gran_canaria",
        "persons": [],
        "locations": [],
        "organizations": [
            "Archipiélago",
            "CONSULTA_AQUÍ_MÁS_NOTICIAS_DE_LAS_PALMAS_DE_GRAN_CANARIA"
        ],
        "others": [],
        "dates": [],
        "numbers": [
            "851.463"
        ]
    },
    "body": {
        "raw_text": "Una de cada siete viviendas en Canarias está vacía, lo que coloca a las Islas en la séptima posición a nivel nacional con más viviendas desocupadas, según afirma un artículo de la última edición de la revista 'Índice' del Instituto Nacional de Estadística (INE) dedicada en exclusiva al turismo y al suelo residencial. El Archipiélago tiene 851.463 viviendas, lo que coloca a las Islas en la novena posición a nivel estatal, puesto que también repiten en el número de viviendas principales con una cifra de 552.351, pero descienden hasta la octava posición en lo que se refiere a su número de 120.331 viviendas secundarias. Sin embargo, Canarias asciende hasta la séptima posición en lo que se refiere a viviendas vacías con la citada cifra de 138.892 que es sólo superada por Andalucía (548.699), Castilla-La Mancha (452.921), Cataluña (444.823), Madrid (306.556), Galicia (229.360) y Castilla y León (209.006). CONSULTA AQUÍ MÁS NOTICIAS DE LAS PALMAS DE GRAN CANARIA .",
        "lemmatized_text": "uno de cada 7 vivienda en canarias estar vacío el que colocar a el islas en el 7 posición a nivel nacional con más vivienda desocupar según afirmar uno artículo de el último edición de el revista índice de el instituto_nacional_de_estadística ine dedicar en exclusiva a el turismo y a el suelo residencial el archipiélago tener 851.463 vivienda el que colocar a el islas en el 9 posición a nivel estatal puesto que también repetir en el número de vivienda principal con uno cifra de 552.351 pero descender hasta el 8 posición en el que se referir a su número de 120.331 vivienda secundario sin embargo canarias ascender hasta el 7 posición en el que se referir a vivienda vacío con el citar cifra de 138.892 que ser sólo superar por andalucía 548.699 castilla-la_mancha 452.921 cataluña 444.823 madrid 306.556 galicia 229.36 y castilla y león 209.006 consulta_aquí_más_noticias_de_las_palmas_de_gran_canaria",
        "lemmatized_text_reduced": "vivienda canarias estar vacío colocar islas 7 posición nivel nacional vivienda desocupar afirmar artículo último edición revista índice instituto_nacional_de_estadística ine dedicar exclusiva turismo suelo residencial archipiélago tener vivienda colocar islas 9 posición nivel estatal puesto repetir número vivienda principal cifra descender 8 posición referir número vivienda secundario embargo canarias ascender 7 posición referir vivienda vacío citar cifra ser superar andalucía castilla-la_mancha cataluña madrid galicia castilla león consulta_aquí_más_noticias_de_las_palmas_de_gran_canaria",
        "persons": [
            "León"
        ],
        "locations": [
            "Canarias",
            "Canarias",
            "Andalucía",
            "Castilla-La_Mancha",
            "Cataluña",
            "Madrid",
            "Galicia",
            "Castilla"
        ],
        "organizations": [
            "Islas",
            "Índice",
            "Instituto_Nacional_de_Estadística",
            "Archipiélago",
            "Islas",
            "CONSULTA_AQUÍ_MÁS_NOTICIAS_DE_LAS_PALMAS_DE_GRAN_CANARIA"
        ],
        "others": [],
        "dates": [],
        "numbers": [
            "7",
            "851.463",
            "552.351",
            "120.331",
            "138.892",
            "548.699",
            "452.921",
            "444.823",
            "306.556",
            "229.36",
            "209.006"
        ]
    }
}
